Workbook

Sheet Cover
B2: =Cover!$C$7&" ("&Cover!$C$8&": "&Cover!$C$9&")" -> Grab Holdings Limited (NASDAQ: GRAB)
B4: Last Updated: | C4: =TODAY() -> 46034
B5: COMPANY INFORMATION
B7: Company Name: | C7: Grab Holdings Limited
B8: Exchange: | C8: NASDAQ
B9: Ticker: | C9: GRAB
B10: Applied Currency: | C10: USD Mn
B11: Scenario: | C11: Base Case
B13: Valuation
B15: DCF - Perpetual Growth Method | C15: =DCF!D51 -> 5.4653114 | D15: 0.4
B16: DCF - Exit Multiple Method | C16: =DCF!N51 -> 10.769891 | D16: 0.4
B17: Relative Valuation - EV/CY 2026 EBITDA | C17: ='Trading Comps'!F204 -> 3.5697554 | D17: 0.2
B18: Target Price | C18: =SUMPRODUCT(C15:C17,D15:D17) -> 7.2080319 | D18: =SUM(D15:D17) -> 1
B19: Current Price: | C19: 5.27
B20: Upside/(Downside): | C20: =(C18-C19)/C19 -> 0.36774798
B22: BUSINESS DESCRIPTION
B23: Grab is a Singapore-based technology company that began as a ride-hailing service and has evolved into a leading super app in Southeast Asia, now offering a broad suite of services including transportation, food and package delivery, and digital payments. The firm's success and research focus span technology innovation, market strategy, competitive positioning, AI applications, and economic impact studies across its regional markets
B29: STYLE GUIDE
B31: Number Format | F31: General Format | G31: Colour Format
B32: _(0.0%_);(0.0%);- | C32: 0.105 | F32: Hardcoded Numbers | G32: #0000FF
B33: _(* #,##0.0_);_(* (#,##0.0);_(* "-"??_);_(@_) | C33: -100000 | F33: Assumptions | G33: #FFFFCC
B34: #,##0.0"x";(#,##0.0)"x" | C34: 10.0x | F34: From Another Sheet | G34: #00B050
B35: "$"#,##0.00 | C35: $10.55 | F35: Dollar Values | G35: #000000
B36: #,##0.0;(#,##0.0) | C36: -20334.118 | F36: Formula | G36: #000000
C127: Adjustments:

Sheet Valuations>>

Sheet 3FS
B1: =Cover!$C$7&" ("&Cover!$C$8&": "&Cover!$C$9&")" -> Grab Holdings Limited (NASDAQ: GRAB)
B3: 12M Target Price: | C3: =Cover!$C$18 -> 7.2080319
B4: Scenario: | C4: Base Case
D5: Historical (31 Dec) | I5: Forecasted (31 Dec)
B6: ="In "&Cover!$C$10&", unless stated otherwise" -> In USD Mn, unless stated otherwise | C6: Units | D6: 20 | E6: =D6+1 -> 21 | F6: =E6+1 -> 22 | G6: =F6+1 -> 23 | H6: =G6+1 -> 24 | I6: =H6+1 -> 25 | J6: =I6+1 -> 26 | K6: =J6+1 -> 27 | L6: =K6+1 -> 28 | M6: =L6+1 -> 29 | O6: Notes:
B8: Deliveries | C8: USD Mns | D8: 5 | E8: 148 | F8: 724 | G8: 1310 | H8: 1493 | I8: ='Revenue Build'!K11 -> 1777.4296 | J8: ='Revenue Build'!L11 -> 2109.9432 | K8: ='Revenue Build'!M11 -> 2528.1524 | L8: ='Revenue Build'!N11 -> 3029.4183 | M8: ='Revenue Build'!O11 -> 3627.8214
B9: Mobility | C9: USD Mns | D9: 438 | E9: 456 | F9: 643 | G9: 871 | H9: 1047 | I9: ='Revenue Build'!K12 -> 1346.1042 | J9: ='Revenue Build'!L12 -> 1729.3739 | K9: ='Revenue Build'!M12 -> 2236.1567 | L9: ='Revenue Build'!N12 -> 2888.0171 | M9: ='Revenue Build'!O12 -> 3724.1225
B10: Financial Services | C10: USD Mns | D10: -10 | E10: 27 | F10: 64 | G10: 177 | H10: 253 | I10: ='Revenue Build'!K13 -> 317.85641 | J10: ='Revenue Build'!L13 -> 394.52885 | K10: ='Revenue Build'!M13 -> 484.23552 | L10: ='Revenue Build'!N13 -> 589.61205 | M10: ='Revenue Build'!O13 -> 719.12533
B11: Enterprise, Others and New Initiatives | C11: USD Mns | D11: 36 | E11: 44 | F11: 2 | G11: 1 | H11: 4 | I11: ='Revenue Build'!K14 -> 5.7676768 | J11: ='Revenue Build'!L14 -> 8.3165238 | K11: ='Revenue Build'!M14 -> 11.991755 | L11: ='Revenue Build'!N14 -> 17.291142 | M11: ='Revenue Build'!O14 -> 24.93243
B12: Total Revenues | C12: USD Mns | D12: =SUM(D8:D11) -> 469 | E12: =SUM(E8:E11) -> 675 | F12: =SUM(F8:F11) -> 1433 | G12: =SUM(G8:G11) -> 2359 | H12: =SUM(H8:H11) -> 2797 | I12: =SUM(I8:I11) -> 3447.158 | J12: =SUM(J8:J11) -> 4242.1624 | K12: =SUM(K8:K11) -> 5260.5364 | ... M12: =SUM(M8:M11) -> 8096.0017
B14: Cost of Revenues | C14: USD Mns | D14: -963 | E14: -1070 | F14: -1356 | G14: -1499 | H14: -1623 | I14: =Projections!L17 -> -1914.0847 | J14: =Projections!M17 -> -2249.4684 | K14: =Projections!N17 -> -2657.9627 | L14: =Projections!O17 -> -3133.4086 | M14: =Projections!P17 -> -3685.8227
B15: Gross Profit | C15: USD Mns | D15: =SUM(D14,D12) -> -494 | E15: =SUM(E14,E12) -> -395 | F15: =SUM(F14,F12) -> 77 | G15: =SUM(G14,G12) -> 860 | H15: =SUM(H14,H12) -> 1174 | I15: =SUM(I14,I12) -> 1533.0733 | J15: =SUM(J14,J12) -> 1992.694 | K15: =SUM(K14,K12) -> 2602.5737 | ... M15: =SUM(M14,M12) -> 4410.179
B16: Gross Profit Margin | C16: % | D16: =D15/D12 -> -1.0533049 | E16: =E15/E12 -> -0.58518519 | F16: =F15/F12 -> 0.053733426 | G16: =G15/G12 -> 0.36456125 | H16: =H15/H12 -> 0.41973543 | I16: =I15/I12 -> 0.44473543 | J16: =J15/J12 -> 0.46973543 | K16: =K15/K12 -> 0.49473543 | ... M16: =M15/M12 -> 0.54473543
A18: x | B18: Operating Items
B19: Sales and Marketing Expenses | C19: USD Mns | D19: -151 | E19: -241 | F19: -278 | G19: -293 | H19: -324 | I19: =Projections!L28 -> -382.07747 | J19: =Projections!M28 -> -448.98368 | K19: =Projections!N28 -> -530.46407 | L19: =Projections!O28 -> -625.28216 | M19: =Projections!P28 -> -735.42782
B20: General and Administrative Expenses | C20: USD Mns | D20: -326 | E20: -544 | F20: -646 | G20: -550 | H20: -512 | I20: =Projections!L34 -> -613.77775 | J20: =Projections!M34 -> -734.12009 | K20: =Projections!N34 -> -884.05035 | L20: =Projections!O34 -> -1063.8147 | M20: =Projections!P34 -> -1279.5995
B21: Research and Development Expenses | C21: USD Mns | D21: -257 | E21: -356 | F21: -465 | G21: -421 | H21: -410 | I21: =Projections!L40 -> -505.30381 | J21: =Projections!M40 -> -600.62923 | K21: =Projections!N40 -> -718.51367 | L21: =Projections!O40 -> -858.50918 | M21: =Projections!P40 -> -1024.8375
B22: Other Income | C22: USD Mns | D22: 33 | E22: 12 | F22: 17 | G22: 17 | H22: 17 | I22: =Projections!L46 -> 40.894407 | J22: =Projections!M46 -> 50.325723 | K22: =Projections!N46 -> 62.406922 | L22: =Projections!O46 -> 77.39969 | M22: =Projections!P46 -> 96.044681
B23: Other Expenses | C23: USD Mns | D23: -40 | E23: -11 | F23: -12 | G23: -4 | H23: -4 | I23: =Projections!L52 -> -28.86664 | J23: =Projections!M52 -> -35.52404 | K23: =Projections!N52 -> -44.051945 | L23: =Projections!O52 -> -54.635075 | M23: =Projections!P52 -> -67.796246
B24: Net Impairment Losses on Financial Assets | C24: USD Mns | D24: -63 | E24: -19 | F24: -58 | G24: -72 | H24: -95 | I24: =Projections!L58 -> -117.08259 | J24: =Projections!M58 -> -144.08489 | K24: =Projections!N58 -> -178.67392 | L24: =Projections!O58 -> -221.59891 | M24: =Projections!P58 -> -274.98039
B25: Restructuring Costs | C25: USD Mns | D25: 0 | E25: -1 | F25: -8 | G25: -56 | H25: -14 | I25: =Projections!L64 -> -17.254276 | J25: =Projections!M64 -> -21.233562 | K25: =Projections!N64 -> -26.330894 | L25: =Projections!O64 -> -32.656682 | M25: =Projections!P64 -> -40.523426
B26: Net Change in Fair Value of Financial Assets and Liabilities | C26: USD Mns | D26: 0 | E26: 37 | F26: -294 | G26: -39 | H26: 0 | I26: =Projections!L70 -> 0 | J26: =Projections!M70 -> 0 | K26: =Projections!N70 -> 0 | L26: =Projections!O70 -> 0 | M26: =Projections!P70 -> 0
B27: Share Listing and Associated Expenses | C27: USD Mns | D27: 0 | E27: -353 | F27: 0 | G27: 0 | H27: 0 | I27: =Projections!L76 -> 0 | J27: =Projections!M76 -> 0 | K27: =Projections!N76 -> 0 | L27: =Projections!O76 -> 0 | M27: =Projections!P76 -> 0
B28: Total Operating Items: | C28: USD Mns | D28: =SUM(D19:D27) -> -804 | E28: =SUM(E19:E27) -> -1476 | F28: =SUM(F19:F27) -> -1744 | G28: =SUM(G19:G27) -> -1418 | H28: =SUM(H19:H27) -> -1342 | I28: =SUM(I19:I27) -> -1623.4681 | J28: =SUM(J19:J27) -> -1934.2498 | K28: =SUM(K19:K27) -> -2319.6779 | ... M28: =SUM(M19:M27) -> -3327.1202
B29: Operating Income | C29: USD Mns | D29: =SUM(D28,D15) -> -1298 | E29: =SUM(E28,E15) -> -1871 | F29: =SUM(F28,F15) -> -1667 | G29: =SUM(G28,G15) -> -558 | H29: =SUM(H28,H15) -> -168 | I29: =SUM(I28,I15) -> -90.394851 | J29: =SUM(J28,J15) -> 58.444237 | K29: =SUM(K28,K15) -> 282.89582 | ... M29: =SUM(M28,M15) -> 1083.0588
A31: x | B31: Non-Operating Items
B32: Non-operating Income/expense | C32: USD Mns | D32: -42 | E32: 0 | F32: 0 | G32: 0 | H32: 0 | I32: =Projections!L86 -> 0 | J32: =Projections!M86 -> 0 | K32: =Projections!N86 -> 0 | L32: =Projections!O86 -> 0 | M32: =Projections!P86 -> 0
B33: Finance Costs | C33: USD Mns | D33: -1448 | E33: -1701 | F33: -166 | G33: -99 | H33: -106 | I33: ='Debt & Equity'!M80 -> -23.845 | J33: ='Debt & Equity'!N80 -> -21.115 | K33: ='Debt & Equity'!O80 -> -21.115 | L33: ='Debt & Equity'!P80 -> -21.115 | M33: ='Debt & Equity'!Q80 -> -20.935
B34: Finance Income | C34: USD Mns | D34: 53 | E34: 28 | F34: 107 | G34: 198 | H34: 187 | I34: =Projections!L89 -> 257.39421 | J34: =Projections!M89 -> 316.75602 | K34: =Projections!N89 -> 392.79651 | L34: =Projections!O89 -> 487.16275 | M34: =Projections!P89 -> 604.51652
B35: Earnings Before Tax | C35: USD Mns | D35: =SUM(D32:D34,D29) -> -2735 | E35: =SUM(E32:E34,E29) -> -3544 | F35: =SUM(F32:F34,F29) -> -1726 | G35: =SUM(G32:G34,G29) -> -459 | H35: =SUM(H32:H34,H29) -> -87 | I35: =SUM(I32:I34,I29) -> 143.15436 | J35: =SUM(J32:J34,J29) -> 354.08526 | K35: =SUM(K32:K34,K29) -> 654.57733 | ... M35: =SUM(M32:M34,M29) -> 1666.6403
B36: Provision for Income Tax | C36: USD Mns | D36: -2 | E36: -3 | F36: -6 | G36: -19 | H36: -63 | I36: =Projections!L96 -> 0.49763971 | J36: =Projections!M96 -> 1.2308873 | K36: =Projections!N96 -> 2.2754716 | L36: =Projections!O96 -> 3.7469777 | M36: =Projections!P96 -> 5.793651
B37: Share of Loss of Equity Accounted Investee (net of Tax) | C37: USD Mns | D37: -8 | E37: -8 | F37: -8 | G37: -7 | H37: -8 | I37: =Projections!L99 -> -19.244427 | J37: =Projections!M99 -> -23.682693 | K37: =Projections!N99 -> -29.367963 | L37: =Projections!O99 -> -36.423383 | M37: =Projections!P99 -> -45.197497
B38: Minority Interest (After Tax) | C38: USD Mns | D38: 137 | E38: 106 | F38: 57 | G38: 51 | H38: 53 | I38: 0 | J38: 0 | K38: 0 | L38: 0 | M38: 0
B39: Net Income | C39: USD Mns | D39: =SUM(D35:D38) -> -2608 | E39: =SUM(E35:E38) -> -3449 | F39: =SUM(F35:F38) -> -1683 | G39: =SUM(G35:G38) -> -434 | H39: =SUM(H35:H38) -> -105 | I39: =SUM(I35:I38) -> 124.40757 | J39: =SUM(J35:J38) -> 331.63345 | K39: =SUM(K35:K38) -> 627.48484 | ... M39: =SUM(M35:M38) -> 1627.2364
B40: Net Income Margin | D40: =D39/D12 -> -5.5607676 | E40: =E39/E12 -> -5.1096296 | F40: =F39/F12 -> -1.1744592 | G40: =G39/G12 -> -0.18397626 | H40: =H39/H12 -> -0.037540222 | I40: =I39/I12 -> 0.036089896 | J40: =J39/J12 -> 0.078175567 | K40: =K39/K12 -> 0.11928153 | ... M40: =M39/M12 -> 0.2009926
B42: EBIT | C42: USD Mns | D42: =D35-D33 -> -1287 | E42: =E35-E33 -> -1843 | F42: =F35-F33 -> -1560 | G42: =G35-G33 -> -360 | H42: =H35-H33 -> 19 | I42: =I35-I33 -> 166.99936 | J42: =J35-J33 -> 375.20026 | K42: =K35-K33 -> 675.69233 | ... M42: =M35-M33 -> 1687.5753
B43: EBIT Margin | C43: % | D43: =D42/D12 -> -2.7441365 | E43: =E42/E12 -> -2.7303704 | F43: =F42/F12 -> -1.0886253 | G43: =G42/G12 -> -0.15260704 | H43: =H42/H12 -> 0.0067929925 | I43: =I42/I12 -> 0.048445519 | J43: =J42/J12 -> 0.088445519 | K43: =K42/K12 -> 0.12844552 | ... M43: =M42/M12 -> 0.20844552
B45: EBITDA | C45: USD Mns | D45: =D42+D112+D113 -> -900 | E45: =E42+E112+E113 -> -1498 | F45: =F42+F112+F113 -> -1410 | G45: =G42+G112+G113 -> -215 | H45: =H42+H112+H113 -> 166 | I45: =I42+I112+I113 -> 440.93236 | J45: =J42+J112+J113 -> 699.525 | K45: =K42+K112+K113 -> 1062.5059 | ... M45: =M42+M112+M113 -> 2067.7115
B46: EBITDA Margin | C46: % | D46: =D45/D12 -> -1.9189765 | E46: =E45/E12 -> -2.2192593 | F46: =F45/F12 -> -0.98394976 | G46: =G45/G12 -> -0.091140314 | H46: =H45/H12 -> 0.059349303 | I46: =I45/I12 -> 0.12791185 | J46: =J45/J12 -> 0.16489821 | K46: =K45/K12 -> 0.20197671 | ... M46: =M45/M12 -> 0.25539909
B49: Balance Sheet | D49: 20 | E49: =D49+1 -> 21 | F49: =E49+1 -> 22 | G49: =F49+1 -> 23 | H49: =G49+1 -> 24 | I49: =H49+1 -> 25 | J49: =I49+1 -> 26 | K49: =J49+1 -> 27 | L49: =K49+1 -> 28 | M49: =L49+1 -> 29
A51: x | B51: Assets
B52: Current Assets:
B53: Cash and Cash Equivalents | C53: USD Mns | D53: 2173 | E53: 4991 | F53: 1952 | G53: 3138 | H53: 2964 | I53: =I154 -> 3387.2668 | J53: =J154 -> 3227.6697 | K53: =K154 -> 3232.7186 | L53: =L154 -> 1940.4896 | M53: =M154 -> 2397.5071
B54: Other Investments | C54: USD Mns | D54: 1298 | E54: 3240 | F54: 3134 | G54: 1905 | H54: 2665 | I54: =Projections!L142 -> 2757.7264 | J54: =Projections!M142 -> 3181.6218 | K54: =Projections!N142 -> 3682.3755 | L54: =Projections!O142 -> 4240.8201 | M54: =Projections!P142 -> 4857.601
B55: Deposits Prepayments and Other Assets | C55: USD Mns | D55: 0 | E55: 0 | F55: 182 | G55: 208 | H55: 241 | I55: =Projections!L121 -> 297.02005 | J55: =Projections!M121 -> 365.52061 | K55: =Projections!N121 -> 453.26753 | L55: =Projections!O121 -> 562.16145 | M55: =Projections!P121 -> 697.58184
B56: Trade and Other Receivables | C56: USD Mns | D56: 172 | E56: 255 | F56: 187 | G56: 196 | H56: 206 | I56: =Projections!L110 -> 254.57993 | J56: =Projections!M110 -> 313.29269 | K56: =Projections!N110 -> 388.50177 | L56: =Projections!O110 -> 480.51975 | M56: =Projections!P110 -> 597.9069
B57: Loan receivables in the Financial Services segment | C57: USD Mns | D57: 0 | E57: 0 | F57: 185 | G57: 272 | H57: 431 | I57: =Projections!L145 -> 397.46798 | J57: =Projections!M145 -> 489.13446 | K57: =Projections!N145 -> 606.55613 | L57: =Projections!O145 -> 752.27642 | M57: =Projections!P145 -> 933.49405
B58: Inventories | C58: USD Mns | D58: 3 | E58: 4 | F58: 48 | G58: 49 | H58: 59 | I58: =Projections!L114 -> 112.68228 | J58: =Projections!M114 -> 138.66975 | K58: =Projections!N114 -> 171.95883 | L58: =Projections!O114 -> 212.68787 | M58: =Projections!P114 -> 264.64582
B59: Prepayments and Other Assets | C59: USD Mns | D59: 109 | E59: 185 | F59: 0 | G59: 0 | H59: 0 | I59: =Projections!L118 -> 0 | J59: =Projections!M118 -> 0 | K59: =Projections!N118 -> 0 | L59: =Projections!O118 -> 0 | M59: =Projections!P118 -> 0
B60: Total Current Assets | C60: USD Mns | D60: =SUM(D53:D59) -> 3755 | E60: =SUM(E53:E59) -> 8675 | F60: =SUM(F53:F59) -> 5688 | G60: =SUM(G53:G59) -> 5768 | H60: =SUM(H53:H59) -> 6566 | I60: =SUM(I53:I59) -> 7206.7434 | J60: =SUM(J53:J59) -> 7715.9091 | K60: =SUM(K53:K59) -> 8535.3784 | ... M60: =SUM(M53:M59) -> 9748.7367
B62: Non-Current Assets:
B63: Property, Plant and Equipment | C63: USD Mns | D63: 384 | E63: 441 | F63: 492 | G63: 512 | H63: 567 | I63: =PPE!L12 -> 553.56588 | J63: =PPE!M12 -> 547.11344 | K63: =PPE!N12 -> 550.96528 | L63: =PPE!O12 -> 586.09443 | M63: =PPE!P12 -> 703.86684
B64: Associates and Joint Ventures | C64: USD Mns | D64: 9 | E64: 14 | F64: 107 | G64: 102 | H64: 131 | I64: =Projections!L150 -> 149.05049 | J64: =Projections!M150 -> 183.42542 | K64: =Projections!N150 -> 227.45855 | L64: =Projections!O150 -> 282.10366 | M64: =Projections!P150 -> 350.06027
B65: Other Investments | C65: USD Mns | D65: 377 | E65: 1241 | F65: 1742 | G65: 1188 | H65: 765 | I65: =Projections!L153 -> 942.82297 | J65: =Projections!M153 -> 1160.2625 | K65: =Projections!N153 -> 1438.7953 | L65: =Projections!O153 -> 1784.4544 | M65: =Projections!P153 -> 2214.3158
B66: Deferred Tax Assets | C66: USD Mns | D66: 0 | E66: 5 | F66: 20 | G66: 56 | H66: 67 | I66: =Projections!L156 -> 48.111067 | J66: =Projections!M156 -> 59.206733 | K66: =Projections!N156 -> 73.419908 | L66: =Projections!O156 -> 91.058458 | M66: =Projections!P156 -> 112.99374
B67: Other Receivables | C67: USD Mns | D67: 0 | E67: 0 | F67: 0 | G67: 0 | H67: 0 | I67: =H67 -> 0 | J67: =I67 -> 0 | K67: =J67 -> 0 | L67: =K67 -> 0 | M67: =L67 -> 0
B68: Loan receivables in the Financial Services segment | C68: USD Mns | D68: 0 | E68: 0 | F68: 0 | G68: 54 | H68: 105 | I68: =Projections!L159 -> 0 | J68: =Projections!M159 -> 0 | K68: =Projections!N159 -> 0 | L68: =Projections!O159 -> 0 | M68: =Projections!P159 -> 0
B69: Intangible Assets and Goodwill | C69: USD Mns | D69: 913 | E69: 675 | F69: 904 | G69: 916 | H69: 975 | I69: ='Goodwill & Intangibles'!L12 -> 961.25697 | J69: ='Goodwill & Intangibles'!M12 -> 947.04886 | K69: ='Goodwill & Intangibles'!N12 -> 932.94535 | L69: ='Goodwill & Intangibles'!O12 -> 998.50321 | M69: ='Goodwill & Intangibles'!P12 -> 1080.1258
B70: Deposits Prepayments and Other Assets | C70: USD Mns | D70: 4 | E70: 127 | F70: 217 | G70: 196 | H70: 119 | I70: =Projections!L162 -> 286.41075 | J70: =Projections!M162 -> 352.46453 | K70: =Projections!N162 -> 437.07721 | L70: =Projections!O162 -> 542.08154 | M70: =Projections!P162 -> 672.66483
B71: Total Non-Current Assets | C71: USD Mns | D71: =SUM(D63:D70) -> 1687 | E71: =SUM(E63:E70) -> 2503 | F71: =SUM(F63:F70) -> 3482 | G71: =SUM(G63:G70) -> 3024 | H71: =SUM(H63:H70) -> 2729 | I71: =SUM(I63:I70) -> 2941.2181 | J71: =SUM(J63:J70) -> 3249.5215 | K71: =SUM(K63:K70) -> 3660.6616 | ... M71: =SUM(M63:M70) -> 5134.0273
B73: Total Assets | C73: USD Mns | D73: =SUM(D71,D60) -> 5442 | E73: =SUM(E71,E60) -> 11178 | F73: =SUM(F71,F60) -> 9170 | G73: =SUM(G71,G60) -> 8792 | H73: =SUM(H71,H60) -> 9295 | I73: =SUM(I71,I60) -> 10147.962 | J73: =SUM(J71,J60) -> 10965.431 | K73: =SUM(K71,K60) -> 12196.04 | ... M73: =SUM(M71,M60) -> 14882.764
A75: x | B75: Liabilities
B76: Current Liabilities:
B77: Trade and Other Payables | C77: USD Mns | D77: 661 | E77: 844 | F77: 930 | G77: 925 | H77: 1169 | I77: =Projections!L126 -> 1444.6793 | J77: =Projections!M126 -> 1777.86 | K77: =Projections!N126 -> 2204.6533 | L77: =Projections!O126 -> 2726.8329 | M77: =Projections!P126 -> 3392.9765
B78: Loans and Borrowings | C78: USD Mns | D78: 140 | E78: 144 | F78: 117 | G78: 125 | H78: 123 | I78: ='Debt & Equity'!M11 -> 1584 | J78: ='Debt & Equity'!N11 -> 1584 | K78: ='Debt & Equity'!O11 -> 1584 | L78: ='Debt & Equity'!P11 -> 75 | M78: ='Debt & Equity'!Q11 -> 0
B79: Current Tax Liabilities | C79: USD Mns | D79: 0 | E79: 3 | F79: 9 | G79: 15 | H79: 34 | I79: =Projections!L167 -> 21.64998 | J79: =Projections!M167 -> 26.64303 | K79: =Projections!N167 -> 33.038959 | L79: =Projections!O167 -> 40.976306 | M79: =Projections!P167 -> 50.847184
B80: Provisions | C80: USD Mns | D80: 35 | E80: 35 | F80: 38 | G80: 39 | H80: 41 | I80: =Projections!L130 -> 91.411027 | J80: =Projections!M130 -> 112.49279 | K80: =Projections!N130 -> 139.49783 | L80: =Projections!O130 -> 173.01107 | M80: =Projections!P130 -> 214.68811
B81: Deposits from Customers in the Banking Business | C81: USD Mns | D81: 0 | E81: 0 | F81: 3 | G81: 374 | H81: 1225 | I81: =Projections!L133 -> 7.2166601 | J81: =Projections!M133 -> 8.88101 | K81: =Projections!N133 -> 11.012986 | L81: =Projections!O133 -> 13.658769 | M81: =Projections!P133 -> 16.949061
B82: Total Current Liabilities | C82: USD Mns | D82: =SUM(D77:D81) -> 836 | E82: =SUM(E77:E81) -> 1026 | F82: =SUM(F77:F81) -> 1097 | G82: =SUM(G77:G81) -> 1478 | H82: =SUM(H77:H81) -> 2592 | I82: =SUM(I77:I81) -> 3148.957 | J82: =SUM(J77:J81) -> 3509.8768 | K82: =SUM(K77:K81) -> 3972.203 | ... M82: =SUM(M77:M81) -> 3675.4609
B84: Non-Current Liabilities:
B85: Convertible Redeemable Preference Shares | C85: USD Mns | D85: 10767 | E85: 0 | F85: 0 | G85: 0 | H85: 0 | I85: =H85 -> 0 | J85: =I85 -> 0 | K85: =J85 -> 0 | L85: =K85 -> 0 | M85: =L85 -> 0
B86: Loans and Borrowings | C86: USD Mns | D86: 111 | E86: 2031 | F86: 1248 | G86: 668 | H86: 241 | I86: ='Debt & Equity'!M12 -> 241 | J86: ='Debt & Equity'!N12 -> 241 | K86: ='Debt & Equity'!O12 -> 241 | L86: ='Debt & Equity'!P12 -> 241 | M86: ='Debt & Equity'!Q12 -> 158
B87: Deferred Tax Liabilities | C87: USD Mns | D87: 1 | E87: 3 | F87: 18 | G87: 20 | H87: 25 | I87: =Projections!L172 -> 29.225587 | J87: =Projections!M172 -> 35.965769 | K87: =Projections!N172 -> 44.599715 | L87: =Projections!O172 -> 55.314443 | M87: =Projections!P172 -> 68.639268
B88: Minority Interest | C88: USD Mns | D88: 105 | E88: 286 | F88: 54 | G88: 19 | H88: -48 | I88: =H88 -> -48 | J88: =I88 -> -48 | K88: =J88 -> -48 | L88: =K88 -> -48 | M88: =L88 -> -48
B89: Other Liabilities | C89: USD Mns | D89: 0 | E89: 81 | F89: 132 | G89: 140 | H89: 66 | I89: =Projections!L175 -> 204.57911 | J89: =Projections!M175 -> 251.76038 | K89: =Projections!N175 -> 312.19801 | L89: =Projections!O175 -> 387.2011 | M89: =Projections!P175 -> 480.47488
B90: Provisions | C90: USD Mns | D90: 3 | E90: 18 | F90: 18 | G90: 18 | H90: 20 | I90: =Projections!G178 -> 3 | J90: =Projections!H178 -> 18 | K90: =Projections!I178 -> 18 | L90: =Projections!J178 -> 18 | M90: =Projections!K178 -> 20
B91: Trade and Other Payables | C91: USD Mns | D91: 18 | E91: 0 | F91: 0 | G91: 0 | H91: 0 | I91: =H91 -> 0 | J91: =I91 -> 0 | K91: =J91 -> 0 | L91: =K91 -> 0 | M91: =L91 -> 0
B92: Other Payables | C92: USD Mns | D92: 0 | E92: 0 | F92: 0 | G92: 0 | H92: 0 | I92: =H92 -> 0 | J92: =I92 -> 0 | K92: =J92 -> 0 | L92: =K92 -> 0 | M92: =L92 -> 0
B93: Total Non-Current Liabilities | C93: USD Mns | D93: =SUM(D85:D92) -> 11005 | E93: =SUM(E85:E92) -> 2419 | F93: =SUM(F85:F92) -> 1470 | G93: =SUM(G85:G92) -> 865 | H93: =SUM(H85:H92) -> 304 | I93: =SUM(I85:I92) -> 429.80469 | J93: =SUM(J85:J92) -> 498.72615 | K93: =SUM(K85:K92) -> 567.79772 | ... M93: =SUM(M85:M92) -> 679.11414
B95: Total Liabilities | C95: USD Mns | D95: =SUM(D93,D82) -> 11841 | E95: =SUM(E93,E82) -> 3445 | F95: =SUM(F93,F82) -> 2567 | G95: =SUM(G93,G82) -> 2343 | H95: =SUM(H93,H82) -> 2896 | I95: =SUM(I93,I82) -> 3578.7617 | J95: =SUM(J93,J82) -> 4008.603 | K95: =SUM(K93,K82) -> 4540.0008 | ... M95: =SUM(M93,M82) -> 4354.575
A97: x | B97: Shareholders' Equity
B98: Common Stock - Par Value | C98: USD Mns | D98: 140 | E98: 21529 | F98: 22278 | G98: 22669 | H98: 23549 | I98: ='Debt & Equity'!M96 -> 23549 | J98: ='Debt & Equity'!N96 -> 23549 | K98: ='Debt & Equity'!O96 -> 23549 | L98: ='Debt & Equity'!P96 -> 23549 | M98: ='Debt & Equity'!Q96 -> 23549
B99: Accumulated Losses | C99: USD Mns | D99: -10490 | E99: -14402 | F99: -16277 | G99: -16764 | H99: -17347 | I99: ='Debt & Equity'!M89 -> -17222.592 | J99: ='Debt & Equity'!N89 -> -16890.959 | K99: ='Debt & Equity'!O89 -> -16263.474 | L99: ='Debt & Equity'!P89 -> -15218.27 | M99: ='Debt & Equity'!Q89 -> -13591.034
B100: Reserves | C100: USD Mns | D100: 3951 | E100: 606 | F100: 602 | G100: 544 | H100: 197 | I100: ='Debt & Equity'!M100 -> 242.79232 | J100: ='Debt & Equity'!N100 -> 298.78656 | K100: ='Debt & Equity'!O100 -> 370.51329 | L100: ='Debt & Equity'!P100 -> 459.52617 | M100: ='Debt & Equity'!Q100 -> 570.2225
B101: Total Shareholders' Equity | C101: USD Mns | D101: =SUM(D98:D100) -> -6399 | E101: =SUM(E98:E100) -> 7733 | F101: =SUM(F98:F100) -> 6603 | G101: =SUM(G98:G100) -> 6449 | H101: =SUM(H98:H100) -> 6399 | I101: =SUM(I98:I100) -> 6569.1999 | J101: =SUM(J98:J100) -> 6956.8276 | K101: =SUM(K98:K100) -> 7656.0392 | ... M101: =SUM(M98:M100) -> 10528.189
B103: Total Liabilities & Shareholders' Equity | C103: USD Mns | D103: =SUM(D101,D95) -> 5442 | E103: =SUM(E101,E95) -> 11178 | F103: =SUM(F101,F95) -> 9170 | G103: =SUM(G101,G95) -> 8792 | H103: =SUM(H101,H95) -> 9295 | I103: =SUM(I101,I95) -> 10147.962 | J103: =SUM(J101,J95) -> 10965.431 | K103: =SUM(K101,K95) -> 12196.04 | ... M103: =SUM(M101,M95) -> 14882.764
B104: Balance Check | D104: =IF(ROUND(ABS(D103-D73),5)=0,"OK",D103-D73) -> OK | E104: =IF(ROUND(ABS(E103-E73),5)=0,"OK",E103-E73) -> OK | F104: =IF(ROUND(ABS(F103-F73),5)=0,"OK",F103-F73) -> OK | G104: =IF(ROUND(ABS(G103-G73),5)=0,"OK",G103-G73) -> OK | H104: =IF(ROUND(ABS(H103-H73),5)=0,"OK",H103-H73) -> OK | I104: =IF(ROUND(ABS(I103-I73),5)=0,"OK",I103-I73) -> OK | J104: =IF(ROUND(ABS(J103-J73),5)=0,"OK",J103-J73) -> OK | K104: =IF(ROUND(ABS(K103-K73),5)=0,"OK",K103-K73) -> OK | ... M104: =IF(ROUND(ABS(M103-M73),5)=0,"OK",M103-M73) -> OK
B107: Statement of Cash Flows | D107: 20 | E107: =D107+1 -> 21 | F107: =E107+1 -> 22 | G107: =F107+1 -> 23 | H107: =G107+1 -> 24 | I107: =H107+1 -> 25 | J107: =I107+1 -> 26 | K107: =J107+1 -> 27 | L107: =K107+1 -> 28 | M107: =L107+1 -> 29
A109: x | B109: Cash Flow From Operating Activities
B110: Net Income | C110: USD Mns | D110: =D39 -> -2608 | E110: =E39 -> -3449 | F110: =F39 -> -1683 | G110: =G39 -> -434 | H110: =H39 -> -105 | I110: =I39 -> 124.40757 | J110: =J39 -> 331.63345 | K110: =K39 -> 627.48484 | ... M110: =M39 -> 1627.2364
B111: Adjustments:
B112: Depreciation of Property, Plant and Equipment | C112: USD Mns | D112: 126 | E112: 109 | F112: 129 | G112: 128 | H112: 122 | I112: =-PPE!L88 -> 187.96923 | J112: =-PPE!M88 -> 221.2399 | K112: =-PPE!N88 -> 262.49753 | L112: =-PPE!O88 -> 295.20853 | M112: =-PPE!P88 -> 292.14109
B113: Amortization of Intangible Assets | C113: USD Mns | D113: 261 | E113: 236 | F113: 21 | G113: 17 | H113: 25 | I113: =-'Goodwill & Intangibles'!L55 -> 85.963768 | J113: =-'Goodwill & Intangibles'!M55 -> 103.08484 | K113: =-'Goodwill & Intangibles'!N55 -> 124.31599 | L113: =-'Goodwill & Intangibles'!O55 -> 71.132299 | M113: =-'Goodwill & Intangibles'!P55 -> 87.995128
B114: Changes in Operating Working Capital:
B115: (Increase)/Decrease in Trade and Other Receivables | C115: USD Mns | I115: =H56-I56 -> -48.579928 | J115: =I56-J56 -> -58.712767 | K115: =J56-K56 -> -75.209079 | L115: =K56-L56 -> -92.017976 | M115: =L56-M56 -> -117.38715
B116: (Increase)/Decrease in Inventories | C116: USD Mns | I116: =H58-I58 -> -53.682281 | J116: =I58-J58 -> -25.987471 | K116: =J58-K58 -> -33.289076 | L116: =K58-L58 -> -40.729038 | M116: =L58-M58 -> -51.957952
B117: (Increase)/Decrease in Prepayments and Other Assets | C117: USD Mns | I117: =H59-I59 -> 0 | J117: =I59-J59 -> 0 | K117: =J59-K59 -> 0 | L117: =K59-L59 -> 0 | M117: =L59-M59 -> 0
B118: (Increase)/Decrease in Deposits, Prepayments and Other Assets | C118: USD Mns | I118: =H55-I55 -> -56.020045 | J118: =I55-J55 -> -68.500564 | K118: =J55-K55 -> -87.746918 | L118: =K55-L55 -> -108.89393 | M118: =L55-M55 -> -135.42038
B119: (Increase)/Decrease in Trade and Other Payables | C119: USD Mns | I119: =I77-H77 -> 275.6793 | J119: =J77-I77 -> 333.1807 | K119: =K77-J77 -> 426.79327 | L119: =L77-K77 -> 522.17968 | M119: =M77-L77 -> 666.14358
B120: (Increase)/Decrease in Provisions (Current) | C120: USD Mns | I120: =I80-H80 -> 50.411027 | J120: =J80-I80 -> 21.081765 | K120: =K80-J80 -> 27.005032 | L120: =L80-K80 -> 33.513246 | M120: =M80-L80 -> 41.67704
...

Sheet WACC
C1: =Cover!$C$7&" ("&Cover!$C$8&": "&Cover!$C$9&")" -> Grab Holdings Limited (NASDAQ: GRAB)
C3: 12M Target Price: | D3: =Cover!$C$18 -> 7.2080319
C4: Scenario: | D4: Base Case
C6: ="In "&Cover!$C$10&", unless stated otherwise" -> In USD Mn, unless stated otherwise | Q6: Notes:
C7: Fiscal year end date
A10: 1 | C10: WACC Summary
C12: Assumptions
D13: Country/Region | E13: Yield
C14: Risk Free Rate(1) | D14: USA | E14: 0.04079 | Q14: Trading Currency in USD, so use the US 10Y Note
C15: Tax Rate | E15: =O143 -> 0.2149891
C17: WACC Calculation
I19: D/E | L19: After-Tax | O19: Weightage
C20: Capital Structure | I20: Ratio | J20: %Debt | K20: %Equity | L20: COD | M20: COE | N20: WACC | O20: (%)
C21: Target Capital Structure - Current D/E | I21: =M96 -> 0.020856865 | J21: =I21/(1+I21) -> 0.020430744 | K21: =1-J21 -> 0.97956926 | L21: =$E$42 -> 0.11684102 | M21: =$E$51 -> 0.10429586 | N21: =SUMPRODUCT(J21:K21,L21:M21) -> 0.10455216 | O21: 0.5
C22: Target Capital Structure - Median Comps D/E | I22: =M97 -> 0.23563553 | J22: =I22/(1+I22) -> 0.19069986 | K22: =1-J22 -> 0.80930014 | L22: =$E$42 -> 0.11684102 | M22: =$E$51 -> 0.10429586 | N22: =SUMPRODUCT(J22:K22,L22:M22) -> 0.10668822 | O22: 0.5
C23: WACC | O23: =SUMPRODUCT(O21:O22,N21:N22) -> 0.10562019
A25: 2 | C25: Cost of Debt
C27: Synthetic Rating Method
F29: Historical (31 Dec) | K29: Forecasted (31 Dec)
C30: ICR Calculation | F30: 20 | G30: =F30+1 -> 21 | H30: =G30+1 -> 22 | I30: =H30+1 -> 23 | J30: =I30+1 -> 24 | K30: =J30+1 -> 25 | L30: =K30+1 -> 26 | M30: =L30+1 -> 27 | N30: =M30+1 -> 28 | O30: =N30+1 -> 29
C31: EBIT | F31: ='3FS'!D42 -> -1287 | G31: ='3FS'!E42 -> -1843 | H31: ='3FS'!F42 -> -1560 | I31: ='3FS'!G42 -> -360 | J31: ='3FS'!H42 -> 19 | K31: ='3FS'!I42 -> 166.99936 | L31: ='3FS'!J42 -> 375.20026 | M31: ='3FS'!K42 -> 675.69233 | ... O31: ='3FS'!M42 -> 1687.5753
C32: Interest Expense | F32: ='3FS'!D33 -> -1448 | G32: ='3FS'!E33 -> -1701 | H32: ='3FS'!F33 -> -166 | I32: ='3FS'!G33 -> -99 | J32: ='3FS'!H33 -> -106 | K32: ='3FS'!I33 -> -23.845 | L32: ='3FS'!J33 -> -21.115 | M32: ='3FS'!K33 -> -21.115 | ... O32: ='3FS'!M33 -> -20.935
C33: Interest Coverage Ratio | F33: =IFERROR(F31/ABS(F32),NA()) -> -0.88881215 | G33: =IFERROR(G31/ABS(G32),NA()) -> -1.0834803 | H33: =IFERROR(H31/ABS(H32),NA()) -> -9.3975904 | I33: =IFERROR(I31/ABS(I32),NA()) -> -3.6363636 | J33: =IFERROR(J31/ABS(J32),NA()) -> 0.17924528 | K33: =IFERROR(K31/ABS(K32),NA()) -> 7.0035378 | L33: =IFERROR(L31/ABS(L32),NA()) -> 17.769371 | M33: =IFERROR(M31/ABS(M32),NA()) -> 32.000584 | ... O33: =IFERROR(O31/ABS(O32),NA()) -> 80.610235
C35: Risk-Free Rate - US 10Y Government Bond Yield | E35: =E14 -> 0.04079 | H35: Rating | I35: Default Risk Spread | J35: Weight
C36: Average ICR | E36: =AVERAGE(F33:J33) -> -2.9654002 | F36: Synthetic Credit Rating | H36: =E37 -> D2/D | I36: =Damodaran!O11 -> 0.19 | J36: 0.5
C37: Synthetic Credit Rating | E37: =Damodaran!N11 -> D2/D | F37: Actual Credit Rating | H37: =E38 -> BB-/Ba3 | I37: =Damodaran!O17 -> 0.0261 | J37: 0.5
C38: Actual Credit Rating | E38: BB-/Ba3 | F38: Final Risk Spread | J38: =SUMPRODUCT(J36:J37,I36:I37) -> 0.10805
C39: Default risk spread - Damodaran's Estimates | E39: =J38 -> 0.10805
C40: Pre-Tax Cost of Debt | E40: =E35+E39 -> 0.14884
C41: Tax Rate | E41: =E15 -> 0.2149891
C42: After-Tax Cost of Debt | E42: =E40*(1-E41) -> 0.11684102
A44: 3 | C44: Cost of Equity
C46: Capital Asset Pricing Model (CAPM)
C47: Risk Free Rate | E47: =E14 -> 0.04079 | G47: Beta | H47: Weight
C48: Weighted Average Beta | E48: =G50 -> 0.6819609 | F48: Levered Beta | G48: =O98 -> 0.6819609 | H48: 1
C49: Equity Risk Premium | E49: =O113 -> 0.062787344 | F49: Regression Beta | G49: 1.0332297 | H49: 0
C50: Country Risk Premium | E50: =O128 -> 0.020687344 | F50: Weighted Beta | G50: =SUMPRODUCT(G48:G49,H48:H49) -> 0.6819609 | H50: =SUM(H48:H49) -> 1
C51: Cost of Equity | E51: =E47+E48*E49+E50 -> 0.10429586
A53: 4 | C53: Levered Beta
C55: Identified Peer Group
C57: Deliveries | F57: Levered | G57: BV | H57: Cost of | I57: Debt | J57: Interest | K57: MV | L57: Market | M57: D/E | N57: Tax | O57: Unlevered
C58: Name | D58: Country | E58: Ticker | F58: Beta | G58: Debt | H58: Debt | I58: Maturity | J58: Expense | K58: Debt | L58: Capitalisation | M58: Ratio | N58: Rate | O58: Beta
C59: ='Financial Data'!A25 -> Delivery Hero SE (XTRA:DHER) | D59: Germany | E59: XTRA:DHER | F59: =_xlfn.XLOOKUP($C59,'Financial Data'!$A$15:$A$32,'Financial Data'!$Q$15:$Q$32) -> 1.69 | G59: =_xlfn.XLOOKUP($C59,'Financial Data'!$A$15:$A$32,'Financial Data'!$T$15:$T$32) -> 6610.8 | L59: =_xlfn.XLOOKUP($C59,'Financial Data'!$A$15:$A$32,'Financial Data'!$D$15:$D$32) -> 6613.6 | M59: =G59/L59 -> 0.99957663 | N59: =Damodaran!I65 -> 0.3 | O59: =F59/(1+M59*(1-N59)) -> 0.99429098
C60: ='Financial Data'!A31 -> Sea Limited (NYSE:SE) | D60: Singapore | E60: NYSE:SE | F60: =_xlfn.XLOOKUP($C60,'Financial Data'!$A$15:$A$32,'Financial Data'!$Q$15:$Q$32) -> 1.58 | G60: =_xlfn.XLOOKUP($C60,'Financial Data'!$A$15:$A$32,'Financial Data'!$T$15:$T$32) -> 4124.1 | L60: =_xlfn.XLOOKUP($C60,'Financial Data'!$A$15:$A$32,'Financial Data'!$D$15:$D$32) -> 81598.1 | M60: =G60/L60 -> 0.050541618 | N60: =_xlfn.XLOOKUP($C60,'Financial Data'!$A$15:$A$32,'Financial Data'!$V$15:$V$32) -> 0.2696 | O60: =F60/(1+M60*(1-N60)) -> 1.5237499
C61: ='Financial Data'!A29 -> PT GoTo Gojek Tokopedia Tbk (IDX:GOTO) | D61: Indonesia | E61: IDX:GOTO | F61: =_xlfn.XLOOKUP($C61,'Financial Data'!$A$15:$A$32,'Financial Data'!$Q$15:$Q$32) -> 0.46 | G61: =_xlfn.XLOOKUP($C61,'Financial Data'!$A$15:$A$32,'Financial Data'!$T$15:$T$32) -> 290.2 | L61: =_xlfn.XLOOKUP($C61,'Financial Data'!$A$15:$A$32,'Financial Data'!$D$15:$D$32) -> 4076.2 | M61: =G61/L61 -> 0.071193759 | N61: =O136 -> 0.22 | O61: =F61/(1+M61*(1-N61)) -> 0.43579956
C62: Average | F62: =AVERAGE(F59:F61) -> 1.2433333 | M62: =AVERAGE(M59:M61) -> 0.37377067 | O62: =AVERAGE(O59:O61) -> 0.98461347
C63: Median | F63: =MEDIAN(F59:F61) -> 1.58 | M63: =MEDIAN(M59:M61) -> 0.071193759 | O63: =MEDIAN(O59:O61) -> 0.99429098
C65: Mobility | F65: Levered | G65: BV | H65: Cost of | I65: Debt | J65: Interest | K65: MV | L65: Market | M65: D/E | N65: Tax | O65: Unlevered
C66: Name | D66: Country | E66: Ticker | F66: Beta | G66: Debt | H66: Debt | I66: Maturity | J66: Expense | K66: Debt | L66: Capitalisation | M66: Ratio | N66: Rate | O66: Beta
C67: ='Financial Data'!A29 -> PT GoTo Gojek Tokopedia Tbk (IDX:GOTO) | D67: Indonesia | E67: IDX:GOTO | F67: =_xlfn.XLOOKUP($C67,'Financial Data'!$A$15:$A$32,'Financial Data'!$Q$15:$Q$32) -> 0.46 | G67: =_xlfn.XLOOKUP($C67,'Financial Data'!$A$15:$A$32,'Financial Data'!$T$15:$T$32) -> 290.2 | L67: =_xlfn.XLOOKUP($C67,'Financial Data'!$A$15:$A$32,'Financial Data'!$D$15:$D$32) -> 4076.2 | M67: =G67/L67 -> 0.071193759 | N67: =O136 -> 0.22 | O67: =F67/(1+M67*(1-N67)) -> 0.43579956
C68: ='Financial Data'!A23 -> ComfortDelGro Corporation Limited (SGX:C52) | D68: Singapore | E68: SGX:C52 | F68: =_xlfn.XLOOKUP($C68,'Financial Data'!$A$15:$A$32,'Financial Data'!$Q$15:$Q$32) -> 0.19 | G68: =_xlfn.XLOOKUP($C68,'Financial Data'!$A$15:$A$32,'Financial Data'!$T$15:$T$32) -> 1047.2 | L68: =_xlfn.XLOOKUP($C68,'Financial Data'!$A$15:$A$32,'Financial Data'!$D$15:$D$32) -> 2404.4 | M68: =G68/L68 -> 0.43553485 | N68: =_xlfn.XLOOKUP($C68,'Financial Data'!$A$15:$A$32,'Financial Data'!$V$15:$V$32) -> 0.1982 | O68: =F68/(1+M68*(1-N68)) -> 0.14082296
C69: ='Financial Data'!A27 -> PT Blue Bird Tbk (IDX:BIRD) | D69: Indonesia | E69: IDX:BIRD | F69: =_xlfn.XLOOKUP($C69,'Financial Data'!$A$15:$A$32,'Financial Data'!$Q$15:$Q$32) -> 0.26 | G69: =_xlfn.XLOOKUP($C69,'Financial Data'!$A$15:$A$32,'Financial Data'!$T$15:$T$32) -> 82.1 | L69: =_xlfn.XLOOKUP($C69,'Financial Data'!$A$15:$A$32,'Financial Data'!$D$15:$D$32) -> 262 | M69: =G69/L69 -> 0.31335878 | N69: =_xlfn.XLOOKUP($C69,'Financial Data'!$A$15:$A$32,'Financial Data'!$V$15:$V$32) -> 0.2201 | O69: =F69/(1+M69*(1-N69)) -> 0.20893796
C70: ='Financial Data'!A24 -> BTS Group Holdings Public Company Limited (SET:BTS) | D70: Thailand | E70: SET:BTS | F70: =_xlfn.XLOOKUP($C70,'Financial Data'!$A$15:$A$32,'Financial Data'!$Q$15:$Q$32) -> 0.02 | G70: =_xlfn.XLOOKUP($C70,'Financial Data'!$A$15:$A$32,'Financial Data'!$T$15:$T$32) -> 5790.2 | L70: =_xlfn.XLOOKUP($C70,'Financial Data'!$A$15:$A$32,'Financial Data'!$D$15:$D$32) -> 1284.9 | M70: =G70/L70 -> 4.5063429 | N70: =_xlfn.XLOOKUP($C70,'Financial Data'!$A$15:$A$32,'Financial Data'!$V$15:$V$32) -> 0.504 | O70: =F70/(1+M70*(1-N70)) -> 0.0061821011
C71: Average | F71: =AVERAGE(F67:F70) -> 0.2325 | M71: =AVERAGE(M67:M70) -> 1.3316076 | O71: =AVERAGE(O67:O70) -> 0.19793564
C72: Median | F72: =MEDIAN(F67:F70) -> 0.225 | M72: =MEDIAN(M67:M70) -> 0.37444682 | O72: =MEDIAN(O67:O70) -> 0.17488046
C74: Financial Services | F74: Levered | G74: BV | H74: Cost of | I74: Debt | J74: Interest | K74: MV | L74: Market | M74: D/E | N74: Tax | O74: Unlevered
C75: Name | D75: Country | E75: Ticker | F75: Beta | G75: Debt | H75: Debt | I75: Maturity | J75: Expense | K75: Debt | L75: Capitalisation | M75: Ratio | N75: Rate | O75: Beta
C76: ='Financial Data'!A31 -> Sea Limited (NYSE:SE) | D76: Singapore | E76: NYSE:SE | F76: =_xlfn.XLOOKUP($C76,'Financial Data'!$A$15:$A$32,'Financial Data'!$Q$15:$Q$32) -> 1.58 | G76: =_xlfn.XLOOKUP($C76,'Financial Data'!$A$15:$A$32,'Financial Data'!$T$15:$T$32) -> 4124.1 | L76: =_xlfn.XLOOKUP($C76,'Financial Data'!$A$15:$A$32,'Financial Data'!$D$15:$D$32) -> 81598.1 | M76: =G76/L76 -> 0.050541618 | N76: =_xlfn.XLOOKUP($C76,'Financial Data'!$A$15:$A$32,'Financial Data'!$V$15:$V$32) -> 0.2696 | O76: =F76/(1+M76*(1-N76)) -> 1.5237499
C77: ='Financial Data'!A29 -> PT GoTo Gojek Tokopedia Tbk (IDX:GOTO) | D77: Indonesia | E77: IDX:GOTO | F77: =_xlfn.XLOOKUP($C77,'Financial Data'!$A$15:$A$32,'Financial Data'!$Q$15:$Q$32) -> 0.46 | G77: =_xlfn.XLOOKUP($C77,'Financial Data'!$A$15:$A$32,'Financial Data'!$T$15:$T$32) -> 290.2 | L77: =_xlfn.XLOOKUP($C77,'Financial Data'!$A$15:$A$32,'Financial Data'!$D$15:$D$32) -> 4076.2 | M77: =G77/L77 -> 0.071193759 | N77: =O136 -> 0.22 | O77: =F77/(1+M77*(1-N77)) -> 0.43579956
C78: ='Financial Data'!A30 -> PT Bank Jago Tbk (IDX:ARTO) | D78: Indonesia | E78: IDX:ARTO | F78: =_xlfn.XLOOKUP($C78,'Financial Data'!$A$15:$A$32,'Financial Data'!$Q$15:$Q$32) -> 1.46 | G78: =_xlfn.XLOOKUP($C78,'Financial Data'!$A$15:$A$32,'Financial Data'!$T$15:$T$32) -> 26.6 | L78: =_xlfn.XLOOKUP($C78,'Financial Data'!$A$15:$A$32,'Financial Data'!$D$15:$D$32) -> 1751.7 | M78: =G78/L78 -> 0.015185249 | N78: =_xlfn.XLOOKUP($C78,'Financial Data'!$A$15:$A$32,'Financial Data'!$V$15:$V$32) -> 0.2554 | O78: =F78/(1+M78*(1-N78)) -> 1.4436764
C79: ='Financial Data'!A17 -> DBS Group Holdings Ltd (SGX:D05) | D79: Singapore | E79: SGX:D05 | F79: =_xlfn.XLOOKUP($C79,'Financial Data'!$A$15:$A$32,'Financial Data'!$Q$15:$Q$32) -> 0.3 | G79: =_xlfn.XLOOKUP($C79,'Financial Data'!$A$15:$A$32,'Financial Data'!$T$15:$T$32) -> 124739.5 | L79: =_xlfn.XLOOKUP($C79,'Financial Data'!$A$15:$A$32,'Financial Data'!$D$15:$D$32) -> 119020.6 | M79: =G79/L79 -> 1.0480497 | N79: =_xlfn.XLOOKUP($C79,'Financial Data'!$A$15:$A$32,'Financial Data'!$V$15:$V$32) -> 0.1495 | O79: =F79/(1+M79*(1-N79)) -> 0.1586155
C80: ='Financial Data'!A16 -> United Overseas Bank Limited (SGX:U11) | D80: Singapore | E80: SGX:U11 | F80: =_xlfn.XLOOKUP($C80,'Financial Data'!$A$15:$A$32,'Financial Data'!$Q$15:$Q$32) -> 0.41 | G80: =_xlfn.XLOOKUP($C80,'Financial Data'!$A$15:$A$32,'Financial Data'!$T$15:$T$32) -> 41866.1 | L80: =_xlfn.XLOOKUP($C80,'Financial Data'!$A$15:$A$32,'Financial Data'!$D$15:$D$32) -> 43988.8 | M80: =G80/L80 -> 0.95174453 | N80: =_xlfn.XLOOKUP($C80,'Financial Data'!$A$15:$A$32,'Financial Data'!$V$15:$V$32) -> 0.1514 | O80: =F80/(1+M80*(1-N80)) -> 0.22681377
C81: ='Financial Data'!A15 -> PLDT Inc. (PSE:TEL) | D81: Philippines | E81: PSE:TEL | F81: =_xlfn.XLOOKUP($C81,'Financial Data'!$A$15:$A$32,'Financial Data'!$Q$15:$Q$32) -> 0.48 | G81: =_xlfn.XLOOKUP($C81,'Financial Data'!$A$15:$A$32,'Financial Data'!$T$15:$T$32) -> 5686.6 | L81: =_xlfn.XLOOKUP($C81,'Financial Data'!$A$15:$A$32,'Financial Data'!$D$15:$D$32) -> 4698.6 | M81: =G81/L81 -> 1.2102754 | N81: =_xlfn.XLOOKUP($C81,'Financial Data'!$A$15:$A$32,'Financial Data'!$V$15:$V$32) -> 0.2316 | O81: =F81/(1+M81*(1-N81)) -> 0.24870781
C82: ='Financial Data'!A20 -> Kasikornbank Public Company Limited (SET:KBANK) | D82: Thailand | E82: SET:KBANK | F82: =_xlfn.XLOOKUP($C82,'Financial Data'!$A$15:$A$32,'Financial Data'!$Q$15:$Q$32) -> 0.23 | G82: =_xlfn.XLOOKUP($C82,'Financial Data'!$A$15:$A$32,'Financial Data'!$T$15:$T$32) -> 8913.8 | L82: =_xlfn.XLOOKUP($C82,'Financial Data'!$A$15:$A$32,'Financial Data'!$D$15:$D$32) -> 14113.3 | M82: =G82/L82 -> 0.63158864 | N82: =_xlfn.XLOOKUP($C82,'Financial Data'!$A$15:$A$32,'Financial Data'!$V$15:$V$32) -> 0.199 | O82: =F82/(1+M82*(1-N82)) -> 0.15273233
C83: Average | F83: =AVERAGE(F76:F82) -> 0.70285714 | M83: =AVERAGE(M76:M82) -> 0.56836841 | O83: =AVERAGE(O76:O82) -> 0.59858504
C84: Median | F84: =MEDIAN(F76:F82) -> 0.46 | M84: =MEDIAN(M76:M82) -> 0.63158864 | O84: =MEDIAN(O76:O82) -> 0.24870781
C86: ='Financial Data'!A32 -> Grab Holdings Limited (NasdaqGS:GRAB) | D86: Singapore | E86: NasdaqGS:GRAB | F86: =_xlfn.XLOOKUP($C86,'Financial Data'!$A$15:$A$32,'Financial Data'!$Q$15:$Q$32) -> 0.89 | G86: =_xlfn.XLOOKUP($C86,'Financial Data'!$A$15:$A$32,'Financial Data'!$T$15:$T$32) -> 364 | H86: =E40 -> 0.14884 | I86: 2 | J86: ='3FS'!H33 -> -106 | K86: =PV(H86,I86,J86,-G86) -> 448.37255 | L86: =_xlfn.XLOOKUP($C86,'Financial Data'!$A$15:$A$32,'Financial Data'!$D$15:$D$32) -> 21497.6 | M86: =K86/L86 -> 0.020856865 | N86: =E15 -> 0.2149891 | O86: =F86/(1+M86*(1-N86)) -> 0.87566289
C88: Revenue Split
L89: Unlevered Beta: | M89: Revenue: | N89: Revenue Split: | O89: D/E Ratio
C90: Deliveries | L90: =O63 -> 0.99429098 | M90: ='3FS'!H8 -> 1493 | N90: =M90/SUM($M$90:$M$92) -> 0.53455066 | O90: =M63 -> 0.071193759
C91: Mobility | L91: =O72 -> 0.17488046 | M91: ='3FS'!H9 -> 1047 | N91: =M91/SUM($M$90:$M$92) -> 0.37486574 | O91: =M72 -> 0.37444682
C92: Financial Services | L92: =O84 -> 0.24870781 | M92: ='3FS'!H10 -> 253 | N92: =M92/SUM($M$90:$M$92) -> 0.090583602 | O92: =M84 -> 0.63158864
K94: Weightage | L94: Unlevered | M94: D/E | O94: Levered
C95: Capital Structure | K95: (%) | L95: Beta | M95: Ratio | N95: Tax Rate | O95: Beta
C96: Target Capital Structure - Current D/E | K96: 0.5 | L96: =SUMPRODUCT($L$90:$L$92,$N$90:$N$92) -> 0.61958444 | M96: =M86 -> 0.020856865 | N96: =N86 -> 0.2149891 | O96: =L96*(1+M96*(1-N96)) -> 0.62972882
C97: Target Capital Structure - Median Comps D/E | K97: 0.5 | L97: =SUMPRODUCT($L$90:$L$92,$N$90:$N$92) -> 0.61958444 | M97: =SUMPRODUCT(O90:O92,N90:N92) -> 0.23563553 | N97: =N86 -> 0.2149891 | O97: =L97*(1+M97*(1-N97)) -> 0.73419298
A98: x | C98: Levered Beta | O98: =SUMPRODUCT(O96:O97,K96:K97) -> 0.6819609
A100: 5 | C100: Equity Risk Premium
M102: Revenue | N102: Weightage | O102: ERP
C103: Country | M103: (USD Mn) | N103: (%) | O103: (%)
C104: Singapore | M104: ='Revenue Build'!J29 -> 578 | N104: =M104/SUM($M$104:$M$110) -> 0.20664998 | O104: =_xlfn.XLOOKUP($C104,Damodaran!$C$10:$C$166,Damodaran!$G$10:$G$166) -> 0.0421
C105: Malaysia | M105: ='Revenue Build'!J30 -> 816 | N105: =M105/SUM($M$104:$M$110) -> 0.29174115 | O105: =_xlfn.XLOOKUP($C105,Damodaran!$C$10:$C$166,Damodaran!$G$10:$G$166) -> 0.0598
C106: Indonesia | M106: ='Revenue Build'!J31 -> 643 | N106: =M106/SUM($M$104:$M$110) -> 0.22988917 | O106: =_xlfn.XLOOKUP($C106,Damodaran!$C$10:$C$166,Damodaran!$G$10:$G$166) -> 0.0703
C107: Philippines | M107: ='Revenue Build'!J32 -> 265 | N107: =M107/SUM($M$104:$M$110) -> 0.094744369 | O107: =_xlfn.XLOOKUP($C107,Damodaran!$C$10:$C$166,Damodaran!$G$10:$G$166) -> 0.0703
C108: Thailand | M108: ='Revenue Build'!J33 -> 252 | N108: =M108/SUM($M$104:$M$110) -> 0.090096532 | O108: =_xlfn.XLOOKUP($C108,Damodaran!$C$10:$C$166,Damodaran!$G$10:$G$166) -> 0.0657
C109: Vietnam | M109: ='Revenue Build'!J34 -> 228 | N109: =M109/SUM($M$104:$M$110) -> 0.08151591 | O109: =_xlfn.XLOOKUP($C109,Damodaran!$C$10:$C$166,Damodaran!$G$10:$G$166) -> 0.0866
C110: Rest of Southeast Asia | M110: ='Revenue Build'!J35 -> 15 | N110: =M110/SUM($M$104:$M$110) -> 0.0053628888 | O110: =AVERAGE(O111:O112) -> 0.1568
C111: Cambodia | O111: =_xlfn.XLOOKUP($C111,Damodaran!$C$10:$C$166,Damodaran!$G$10:$G$166) -> 0.1235
C112: Laos | O112: =_xlfn.XLOOKUP($C112,Damodaran!$C$10:$C$166,Damodaran!$G$10:$G$166) -> 0.1901
C113: Equity Risk Premium | O113: =SUMPRODUCT(O104:O110,N104:N110) -> 0.062787344
A115: 6 | C115: Country Risk Premium
M117: Revenue | N117: Weightage | O117: CRP
C118: Country | M118: (USD Mn) | N118: (%) | O118: (%)
C119: Singapore | M119: ='Revenue Build'!J29 -> 578 | N119: =M119/SUM($M$119:$M$125) -> 0.20664998 | O119: =_xlfn.XLOOKUP($C119,Damodaran!$C$10:$C$166,Damodaran!$H$10:$H$166) -> 0
C120: Malaysia | M120: ='Revenue Build'!J30 -> 816 | N120: =M120/SUM($M$119:$M$125) -> 0.29174115 | O120: =_xlfn.XLOOKUP($C120,Damodaran!$C$10:$C$166,Damodaran!$H$10:$H$166) -> 0.0177
C121: Indonesia | M121: ='Revenue Build'!J31 -> 643 | N121: =M121/SUM($M$119:$M$125) -> 0.22988917 | O121: =_xlfn.XLOOKUP($C121,Damodaran!$C$10:$C$166,Damodaran!$H$10:$H$166) -> 0.0282
C122: Philippines | M122: ='Revenue Build'!J32 -> 265 | N122: =M122/SUM($M$119:$M$125) -> 0.094744369 | O122: =_xlfn.XLOOKUP($C122,Damodaran!$C$10:$C$166,Damodaran!$H$10:$H$166) -> 0.0282
C123: Thailand | M123: ='Revenue Build'!J33 -> 252 | N123: =M123/SUM($M$119:$M$125) -> 0.090096532 | O123: =_xlfn.XLOOKUP($C123,Damodaran!$C$10:$C$166,Damodaran!$H$10:$H$166) -> 0.0236
C124: Vietnam | M124: ='Revenue Build'!J34 -> 228 | N124: =M124/SUM($M$119:$M$125) -> 0.08151591 | O124: =_xlfn.XLOOKUP($C124,Damodaran!$C$10:$C$166,Damodaran!$H$10:$H$166) -> 0.0445
C125: Rest of Southeast Asia | M125: ='Revenue Build'!J35 -> 15 | N125: =M125/SUM($M$119:$M$125) -> 0.0053628888 | O125: =AVERAGE(O126:O127) -> 0.1147
...

Sheet Trading Comps
B1: =Cover!$C$7&" ("&Cover!$C$8&": "&Cover!$C$9&")" -> Grab Holdings Limited (NASDAQ: GRAB)
B3: 12M Target Price | C3: =Cover!$C$18 -> 7.2080319
B4: Scenario | C4: =[1]Cover!D11 -> Base Case
E5: EV/EBITDA | H5: EV/Revenue | K5: P/E
E6: LTM | F6: 1 | G6: 2 | H6: LTM | I6: 1 | J6: 2 | K6: LTM | L6: 1 | M6: 2 | O6: Comments:
A8: x | B8: Mobility | O8: All values which returned "NM" were manually recomputed to zero
O9: Due to a lack of publicly traded comparables, Gojek was included as a competitor in certain markets which it may have exited from previously
B10: Singapore
B11: ='Raw Trading Comps'!A29 -> PT GoTo Gojek Tokopedia Tbk (IDX:GOTO) | E11: 0 | F11: =_xlfn.XLOOKUP($B11,'Raw Trading Comps'!$A$15:$A$32,'Raw Trading Comps'!H$15:H$32) -> 41.57 | G11: =_xlfn.XLOOKUP($B11,'Raw Trading Comps'!$A$15:$A$32,'Raw Trading Comps'!I$15:I$32) -> 21.65 | H11: =_xlfn.XLOOKUP($B11,'Raw Trading Comps'!$A$15:$A$32,'Raw Trading Comps'!J$15:J$32) -> 2.9 | I11: =_xlfn.XLOOKUP($B11,'Raw Trading Comps'!$A$15:$A$32,'Raw Trading Comps'!K$15:K$32) -> 2.8 | J11: =_xlfn.XLOOKUP($B11,'Raw Trading Comps'!$A$15:$A$32,'Raw Trading Comps'!L$15:L$32) -> 2.43 | K11: 0 | L11: 0 | M11: =_xlfn.XLOOKUP($B11,'Raw Trading Comps'!$A$15:$A$32,'Raw Trading Comps'!O$15:O$32) -> 86.32
B12: ='Raw Trading Comps'!A23 -> ComfortDelGro Corporation Limited (SGX:C52) | E12: =_xlfn.XLOOKUP($B12,'Raw Trading Comps'!$A$15:$A$32,'Raw Trading Comps'!G$15:G$32) -> 6 | F12: =_xlfn.XLOOKUP($B12,'Raw Trading Comps'!$A$15:$A$32,'Raw Trading Comps'!H$15:H$32) -> 5.51 | G12: =_xlfn.XLOOKUP($B12,'Raw Trading Comps'!$A$15:$A$32,'Raw Trading Comps'!I$15:I$32) -> 5.32 | H12: =_xlfn.XLOOKUP($B12,'Raw Trading Comps'!$A$15:$A$32,'Raw Trading Comps'!J$15:J$32) -> 0.9 | I12: =_xlfn.XLOOKUP($B12,'Raw Trading Comps'!$A$15:$A$32,'Raw Trading Comps'!K$15:K$32) -> 0.87 | J12: =_xlfn.XLOOKUP($B12,'Raw Trading Comps'!$A$15:$A$32,'Raw Trading Comps'!L$15:L$32) -> 0.85 | K12: =_xlfn.XLOOKUP($B12,'Raw Trading Comps'!$A$15:$A$32,'Raw Trading Comps'!M$15:M$32) -> 19.9 | L12: =_xlfn.XLOOKUP($B12,'Raw Trading Comps'!$A$15:$A$32,'Raw Trading Comps'!N$15:N$32) -> 13.65 | M12: =_xlfn.XLOOKUP($B12,'Raw Trading Comps'!$A$15:$A$32,'Raw Trading Comps'!O$15:O$32) -> 12.46
B13: Average | E13: =AVERAGE(E11:E12) -> 3 | F13: =AVERAGE(F11:F12) -> 23.54 | G13: =AVERAGE(G11:G12) -> 13.485 | H13: =AVERAGE(H11:H12) -> 1.9 | I13: =AVERAGE(I11:I12) -> 1.835 | J13: =AVERAGE(J11:J12) -> 1.64 | K13: =AVERAGE(K11:K12) -> 9.95 | L13: =AVERAGE(L11:L12) -> 6.825 | M13: =AVERAGE(M11:M12) -> 49.39
B14: Median | E14: =MEDIAN(E11:E12) -> 3 | F14: =MEDIAN(F11:F12) -> 23.54 | G14: =MEDIAN(G11:G12) -> 13.485 | H14: =MEDIAN(H11:H12) -> 1.9 | I14: =MEDIAN(I11:I12) -> 1.835 | J14: =MEDIAN(J11:J12) -> 1.64 | K14: =MEDIAN(K11:K12) -> 9.95 | L14: =MEDIAN(L11:L12) -> 6.825 | M14: =MEDIAN(M11:M12) -> 49.39
B15: 1st Quartile | E15: =_xlfn.PERCENTILE.INC(E11:E12,0.25) -> 1.5 | F15: =_xlfn.PERCENTILE.INC(F11:F12,0.25) -> 14.525 | G15: =_xlfn.PERCENTILE.INC(G11:G12,0.25) -> 9.4025 | H15: =_xlfn.PERCENTILE.INC(H11:H12,0.25) -> 1.4 | I15: =_xlfn.PERCENTILE.INC(I11:I12,0.25) -> 1.3525 | J15: =_xlfn.PERCENTILE.INC(J11:J12,0.25) -> 1.245 | K15: =_xlfn.PERCENTILE.INC(K11:K12,0.25) -> 4.975 | L15: =_xlfn.PERCENTILE.INC(L11:L12,0.25) -> 3.4125 | M15: =_xlfn.PERCENTILE.INC(M11:M12,0.25) -> 30.925
B16: 3rd Quartile | E16: =_xlfn.PERCENTILE.INC(E11:E12,0.75) -> 4.5 | F16: =_xlfn.PERCENTILE.INC(F11:F12,0.75) -> 32.555 | G16: =_xlfn.PERCENTILE.INC(G11:G12,0.75) -> 17.5675 | H16: =_xlfn.PERCENTILE.INC(H11:H12,0.75) -> 2.4 | I16: =_xlfn.PERCENTILE.INC(I11:I12,0.75) -> 2.3175 | J16: =_xlfn.PERCENTILE.INC(J11:J12,0.75) -> 2.035 | K16: =_xlfn.PERCENTILE.INC(K11:K12,0.75) -> 14.925 | L16: =_xlfn.PERCENTILE.INC(L11:L12,0.75) -> 10.2375 | M16: =_xlfn.PERCENTILE.INC(M11:M12,0.75) -> 67.855
B18: Malaysia
B19: ='Raw Trading Comps'!A29 -> PT GoTo Gojek Tokopedia Tbk (IDX:GOTO) | E19: 0 | F19: =_xlfn.XLOOKUP($B19,'Raw Trading Comps'!$A$15:$A$32,'Raw Trading Comps'!H$15:H$32) -> 41.57 | G19: =_xlfn.XLOOKUP($B19,'Raw Trading Comps'!$A$15:$A$32,'Raw Trading Comps'!I$15:I$32) -> 21.65 | H19: =_xlfn.XLOOKUP($B19,'Raw Trading Comps'!$A$15:$A$32,'Raw Trading Comps'!J$15:J$32) -> 2.9 | I19: =_xlfn.XLOOKUP($B19,'Raw Trading Comps'!$A$15:$A$32,'Raw Trading Comps'!K$15:K$32) -> 2.8 | J19: =_xlfn.XLOOKUP($B19,'Raw Trading Comps'!$A$15:$A$32,'Raw Trading Comps'!L$15:L$32) -> 2.43 | K19: 0 | L19: 0 | M19: =_xlfn.XLOOKUP($B19,'Raw Trading Comps'!$A$15:$A$32,'Raw Trading Comps'!O$15:O$32) -> 86.32
B20: Average | E20: =AVERAGE(E19:E19) -> 0 | F20: =AVERAGE(F19:F19) -> 41.57 | G20: =AVERAGE(G19:G19) -> 21.65 | H20: =AVERAGE(H19:H19) -> 2.9 | I20: =AVERAGE(I19:I19) -> 2.8 | J20: =AVERAGE(J19:J19) -> 2.43 | K20: =AVERAGE(K19:K19) -> 0 | L20: =AVERAGE(L19:L19) -> 0 | M20: =AVERAGE(M19:M19) -> 86.32
B21: Median | E21: =MEDIAN(E19:E19) -> 0 | F21: =MEDIAN(F19:F19) -> 41.57 | G21: =MEDIAN(G19:G19) -> 21.65 | H21: =MEDIAN(H19:H19) -> 2.9 | I21: =MEDIAN(I19:I19) -> 2.8 | J21: =MEDIAN(J19:J19) -> 2.43 | K21: =MEDIAN(K19:K19) -> 0 | L21: =MEDIAN(L19:L19) -> 0 | M21: =MEDIAN(M19:M19) -> 86.32
B22: 1st Quartile | E22: =_xlfn.PERCENTILE.INC(E19:E19,0.25) -> 0 | F22: =_xlfn.PERCENTILE.INC(F19:F19,0.25) -> 41.57 | G22: =_xlfn.PERCENTILE.INC(G19:G19,0.25) -> 21.65 | H22: =_xlfn.PERCENTILE.INC(H19:H19,0.25) -> 2.9 | I22: =_xlfn.PERCENTILE.INC(I19:I19,0.25) -> 2.8 | J22: =_xlfn.PERCENTILE.INC(J19:J19,0.25) -> 2.43 | K22: =_xlfn.PERCENTILE.INC(K19:K19,0.25) -> 0 | L22: =_xlfn.PERCENTILE.INC(L19:L19,0.25) -> 0 | M22: =_xlfn.PERCENTILE.INC(M19:M19,0.25) -> 86.32
B23: 3rd Quartile | E23: =_xlfn.PERCENTILE.INC(E19:E19,0.75) -> 0 | F23: =_xlfn.PERCENTILE.INC(F19:F19,0.75) -> 41.57 | G23: =_xlfn.PERCENTILE.INC(G19:G19,0.75) -> 21.65 | H23: =_xlfn.PERCENTILE.INC(H19:H19,0.75) -> 2.9 | I23: =_xlfn.PERCENTILE.INC(I19:I19,0.75) -> 2.8 | J23: =_xlfn.PERCENTILE.INC(J19:J19,0.75) -> 2.43 | K23: =_xlfn.PERCENTILE.INC(K19:K19,0.75) -> 0 | L23: =_xlfn.PERCENTILE.INC(L19:L19,0.75) -> 0 | M23: =_xlfn.PERCENTILE.INC(M19:M19,0.75) -> 86.32
B25: Indonesia
B26: ='Raw Trading Comps'!A29 -> PT GoTo Gojek Tokopedia Tbk (IDX:GOTO) | E26: 0 | F26: =_xlfn.XLOOKUP($B26,'Raw Trading Comps'!$A$15:$A$32,'Raw Trading Comps'!H$15:H$32) -> 41.57 | G26: =_xlfn.XLOOKUP($B26,'Raw Trading Comps'!$A$15:$A$32,'Raw Trading Comps'!I$15:I$32) -> 21.65 | H26: =_xlfn.XLOOKUP($B26,'Raw Trading Comps'!$A$15:$A$32,'Raw Trading Comps'!J$15:J$32) -> 2.9 | I26: =_xlfn.XLOOKUP($B26,'Raw Trading Comps'!$A$15:$A$32,'Raw Trading Comps'!K$15:K$32) -> 2.8 | J26: =_xlfn.XLOOKUP($B26,'Raw Trading Comps'!$A$15:$A$32,'Raw Trading Comps'!L$15:L$32) -> 2.43 | K26: 0 | L26: 0 | M26: =_xlfn.XLOOKUP($B26,'Raw Trading Comps'!$A$15:$A$32,'Raw Trading Comps'!O$15:O$32) -> 86.32
B27: ='Raw Trading Comps'!A27 -> PT Blue Bird Tbk (IDX:BIRD) | E27: =_xlfn.XLOOKUP($B27,'Raw Trading Comps'!$A$15:$A$32,'Raw Trading Comps'!G$15:G$32) -> 4 | F27: =_xlfn.XLOOKUP($B27,'Raw Trading Comps'!$A$15:$A$32,'Raw Trading Comps'!H$15:H$32) -> 3.91 | G27: =_xlfn.XLOOKUP($B27,'Raw Trading Comps'!$A$15:$A$32,'Raw Trading Comps'!I$15:I$32) -> 3.44 | H27: =_xlfn.XLOOKUP($B27,'Raw Trading Comps'!$A$15:$A$32,'Raw Trading Comps'!J$15:J$32) -> 1 | I27: =_xlfn.XLOOKUP($B27,'Raw Trading Comps'!$A$15:$A$32,'Raw Trading Comps'!K$15:K$32) -> 0.93 | J27: =_xlfn.XLOOKUP($B27,'Raw Trading Comps'!$A$15:$A$32,'Raw Trading Comps'!L$15:L$32) -> 0.85 | K27: =_xlfn.XLOOKUP($B27,'Raw Trading Comps'!$A$15:$A$32,'Raw Trading Comps'!M$15:M$32) -> 10.3 | L27: =_xlfn.XLOOKUP($B27,'Raw Trading Comps'!$A$15:$A$32,'Raw Trading Comps'!N$15:N$32) -> 6.75 | M27: =_xlfn.XLOOKUP($B27,'Raw Trading Comps'!$A$15:$A$32,'Raw Trading Comps'!O$15:O$32) -> 6.12
B28: Average | E28: =AVERAGE(E26:E27) -> 2 | F28: =AVERAGE(F26:F27) -> 22.74 | G28: =AVERAGE(G26:G27) -> 12.545 | H28: =AVERAGE(H26:H27) -> 1.95 | I28: =AVERAGE(I26:I27) -> 1.865 | J28: =AVERAGE(J26:J27) -> 1.64 | K28: =AVERAGE(K26:K27) -> 5.15 | L28: =AVERAGE(L26:L27) -> 3.375 | M28: =AVERAGE(M26:M27) -> 46.22
B29: Median | E29: =MEDIAN(E26:E27) -> 2 | F29: =MEDIAN(F26:F27) -> 22.74 | G29: =MEDIAN(G26:G27) -> 12.545 | H29: =MEDIAN(H26:H27) -> 1.95 | I29: =MEDIAN(I26:I27) -> 1.865 | J29: =MEDIAN(J26:J27) -> 1.64 | K29: =MEDIAN(K26:K27) -> 5.15 | L29: =MEDIAN(L26:L27) -> 3.375 | M29: =MEDIAN(M26:M27) -> 46.22
B30: 1st Quartile | E30: =_xlfn.PERCENTILE.INC(E26:E27,0.25) -> 1 | F30: =_xlfn.PERCENTILE.INC(F26:F27,0.25) -> 13.325 | G30: =_xlfn.PERCENTILE.INC(G26:G27,0.25) -> 7.9925 | H30: =_xlfn.PERCENTILE.INC(H26:H27,0.25) -> 1.475 | I30: =_xlfn.PERCENTILE.INC(I26:I27,0.25) -> 1.3975 | J30: =_xlfn.PERCENTILE.INC(J26:J27,0.25) -> 1.245 | K30: =_xlfn.PERCENTILE.INC(K26:K27,0.25) -> 2.575 | L30: =_xlfn.PERCENTILE.INC(L26:L27,0.25) -> 1.6875 | M30: =_xlfn.PERCENTILE.INC(M26:M27,0.25) -> 26.17
B31: 3rd Quartile | E31: =_xlfn.PERCENTILE.INC(E26:E27,0.75) -> 3 | F31: =_xlfn.PERCENTILE.INC(F26:F27,0.75) -> 32.155 | G31: =_xlfn.PERCENTILE.INC(G26:G27,0.75) -> 17.0975 | H31: =_xlfn.PERCENTILE.INC(H26:H27,0.75) -> 2.425 | I31: =_xlfn.PERCENTILE.INC(I26:I27,0.75) -> 2.3325 | J31: =_xlfn.PERCENTILE.INC(J26:J27,0.75) -> 2.035 | K31: =_xlfn.PERCENTILE.INC(K26:K27,0.75) -> 7.725 | L31: =_xlfn.PERCENTILE.INC(L26:L27,0.75) -> 5.0625 | M31: =_xlfn.PERCENTILE.INC(M26:M27,0.75) -> 66.27
B33: Philippines
B34: ='Raw Trading Comps'!A29 -> PT GoTo Gojek Tokopedia Tbk (IDX:GOTO) | E34: 0 | F34: =_xlfn.XLOOKUP($B34,'Raw Trading Comps'!$A$15:$A$32,'Raw Trading Comps'!H$15:H$32) -> 41.57 | G34: =_xlfn.XLOOKUP($B34,'Raw Trading Comps'!$A$15:$A$32,'Raw Trading Comps'!I$15:I$32) -> 21.65 | H34: =_xlfn.XLOOKUP($B34,'Raw Trading Comps'!$A$15:$A$32,'Raw Trading Comps'!J$15:J$32) -> 2.9 | I34: =_xlfn.XLOOKUP($B34,'Raw Trading Comps'!$A$15:$A$32,'Raw Trading Comps'!K$15:K$32) -> 2.8 | J34: =_xlfn.XLOOKUP($B34,'Raw Trading Comps'!$A$15:$A$32,'Raw Trading Comps'!L$15:L$32) -> 2.43 | K34: 0 | L34: 0 | M34: =_xlfn.XLOOKUP($B34,'Raw Trading Comps'!$A$15:$A$32,'Raw Trading Comps'!O$15:O$32) -> 86.32
B35: Average | E35: =AVERAGE(E34:E34) -> 0 | F35: =AVERAGE(F34:F34) -> 41.57 | G35: =AVERAGE(G34:G34) -> 21.65 | H35: =AVERAGE(H34:H34) -> 2.9 | I35: =AVERAGE(I34:I34) -> 2.8 | J35: =AVERAGE(J34:J34) -> 2.43 | K35: =AVERAGE(K34:K34) -> 0 | L35: =AVERAGE(L34:L34) -> 0 | M35: =AVERAGE(M34:M34) -> 86.32
B36: Median | E36: =MEDIAN(E34:E34) -> 0 | F36: =MEDIAN(F34:F34) -> 41.57 | G36: =MEDIAN(G34:G34) -> 21.65 | H36: =MEDIAN(H34:H34) -> 2.9 | I36: =MEDIAN(I34:I34) -> 2.8 | J36: =MEDIAN(J34:J34) -> 2.43 | K36: =MEDIAN(K34:K34) -> 0 | L36: =MEDIAN(L34:L34) -> 0 | M36: =MEDIAN(M34:M34) -> 86.32
B37: 1st Quartile | E37: =_xlfn.PERCENTILE.INC(E34:E34,0.25) -> 0 | F37: =_xlfn.PERCENTILE.INC(F34:F34,0.25) -> 41.57 | G37: =_xlfn.PERCENTILE.INC(G34:G34,0.25) -> 21.65 | H37: =_xlfn.PERCENTILE.INC(H34:H34,0.25) -> 2.9 | I37: =_xlfn.PERCENTILE.INC(I34:I34,0.25) -> 2.8 | J37: =_xlfn.PERCENTILE.INC(J34:J34,0.25) -> 2.43 | K37: =_xlfn.PERCENTILE.INC(K34:K34,0.25) -> 0 | L37: =_xlfn.PERCENTILE.INC(L34:L34,0.25) -> 0 | M37: =_xlfn.PERCENTILE.INC(M34:M34,0.25) -> 86.32
B38: 3rd Quartile | E38: =_xlfn.PERCENTILE.INC(E34:E34,0.75) -> 0 | F38: =_xlfn.PERCENTILE.INC(F34:F34,0.75) -> 41.57 | G38: =_xlfn.PERCENTILE.INC(G34:G34,0.75) -> 21.65 | H38: =_xlfn.PERCENTILE.INC(H34:H34,0.75) -> 2.9 | I38: =_xlfn.PERCENTILE.INC(I34:I34,0.75) -> 2.8 | J38: =_xlfn.PERCENTILE.INC(J34:J34,0.75) -> 2.43 | K38: =_xlfn.PERCENTILE.INC(K34:K34,0.75) -> 0 | L38: =_xlfn.PERCENTILE.INC(L34:L34,0.75) -> 0 | M38: =_xlfn.PERCENTILE.INC(M34:M34,0.75) -> 86.32
B40: Thailand
B41: ='Raw Trading Comps'!A29 -> PT GoTo Gojek Tokopedia Tbk (IDX:GOTO) | E41: 0 | F41: =_xlfn.XLOOKUP($B41,'Raw Trading Comps'!$A$15:$A$32,'Raw Trading Comps'!H$15:H$32) -> 41.57 | G41: =_xlfn.XLOOKUP($B41,'Raw Trading Comps'!$A$15:$A$32,'Raw Trading Comps'!I$15:I$32) -> 21.65 | H41: =_xlfn.XLOOKUP($B41,'Raw Trading Comps'!$A$15:$A$32,'Raw Trading Comps'!J$15:J$32) -> 2.9 | I41: =_xlfn.XLOOKUP($B41,'Raw Trading Comps'!$A$15:$A$32,'Raw Trading Comps'!K$15:K$32) -> 2.8 | J41: =_xlfn.XLOOKUP($B41,'Raw Trading Comps'!$A$15:$A$32,'Raw Trading Comps'!L$15:L$32) -> 2.43 | K41: 0 | L41: 0 | M41: =_xlfn.XLOOKUP($B41,'Raw Trading Comps'!$A$15:$A$32,'Raw Trading Comps'!O$15:O$32) -> 86.32
B42: ='Raw Trading Comps'!A24 -> BTS Group Holdings Public Company Limited (SET:BTS) | E42: =_xlfn.XLOOKUP($B42,'Raw Trading Comps'!$A$15:$A$32,'Raw Trading Comps'!G$15:G$32) -> 55 | F42: =_xlfn.XLOOKUP($B42,'Raw Trading Comps'!$A$15:$A$32,'Raw Trading Comps'!H$15:H$32) -> 29.55 | G42: =_xlfn.XLOOKUP($B42,'Raw Trading Comps'!$A$15:$A$32,'Raw Trading Comps'!I$15:I$32) -> 23.74 | H42: =_xlfn.XLOOKUP($B42,'Raw Trading Comps'!$A$15:$A$32,'Raw Trading Comps'!J$15:J$32) -> 10.8 | I42: =_xlfn.XLOOKUP($B42,'Raw Trading Comps'!$A$15:$A$32,'Raw Trading Comps'!K$15:K$32) -> 10.85 | J42: =_xlfn.XLOOKUP($B42,'Raw Trading Comps'!$A$15:$A$32,'Raw Trading Comps'!L$15:L$32) -> 10.09 | K42: =_xlfn.XLOOKUP($B42,'Raw Trading Comps'!$A$15:$A$32,'Raw Trading Comps'!M$15:M$32) -> 55.7 | L42: =_xlfn.XLOOKUP($B42,'Raw Trading Comps'!$A$15:$A$32,'Raw Trading Comps'!N$15:N$32) -> 69 | M42: =_xlfn.XLOOKUP($B42,'Raw Trading Comps'!$A$15:$A$32,'Raw Trading Comps'!O$15:O$32) -> 46.55
B43: Average | E43: =AVERAGE(E41:E42) -> 27.5 | F43: =AVERAGE(F41:F42) -> 35.56 | G43: =AVERAGE(G41:G42) -> 22.695 | H43: =AVERAGE(H41:H42) -> 6.85 | I43: =AVERAGE(I41:I42) -> 6.825 | J43: =AVERAGE(J41:J42) -> 6.26 | K43: =AVERAGE(K41:K42) -> 27.85 | L43: =AVERAGE(L41:L42) -> 34.5 | M43: =AVERAGE(M41:M42) -> 66.435
B44: Median | E44: =MEDIAN(E41:E42) -> 27.5 | F44: =MEDIAN(F41:F42) -> 35.56 | G44: =MEDIAN(G41:G42) -> 22.695 | H44: =MEDIAN(H41:H42) -> 6.85 | I44: =MEDIAN(I41:I42) -> 6.825 | J44: =MEDIAN(J41:J42) -> 6.26 | K44: =MEDIAN(K41:K42) -> 27.85 | L44: =MEDIAN(L41:L42) -> 34.5 | M44: =MEDIAN(M41:M42) -> 66.435
B45: 1st Quartile | E45: =_xlfn.PERCENTILE.INC(E41:E42,0.25) -> 13.75 | F45: =_xlfn.PERCENTILE.INC(F41:F42,0.25) -> 32.555 | G45: =_xlfn.PERCENTILE.INC(G41:G42,0.25) -> 22.1725 | H45: =_xlfn.PERCENTILE.INC(H41:H42,0.25) -> 4.875 | I45: =_xlfn.PERCENTILE.INC(I41:I42,0.25) -> 4.8125 | J45: =_xlfn.PERCENTILE.INC(J41:J42,0.25) -> 4.345 | K45: =_xlfn.PERCENTILE.INC(K41:K42,0.25) -> 13.925 | L45: =_xlfn.PERCENTILE.INC(L41:L42,0.25) -> 17.25 | M45: =_xlfn.PERCENTILE.INC(M41:M42,0.25) -> 56.4925
B46: 3rd Quartile | E46: =_xlfn.PERCENTILE.INC(E41:E42,0.75) -> 41.25 | F46: =_xlfn.PERCENTILE.INC(F41:F42,0.75) -> 38.565 | G46: =_xlfn.PERCENTILE.INC(G41:G42,0.75) -> 23.2175 | H46: =_xlfn.PERCENTILE.INC(H41:H42,0.75) -> 8.825 | I46: =_xlfn.PERCENTILE.INC(I41:I42,0.75) -> 8.8375 | J46: =_xlfn.PERCENTILE.INC(J41:J42,0.75) -> 8.175 | K46: =_xlfn.PERCENTILE.INC(K41:K42,0.75) -> 41.775 | L46: =_xlfn.PERCENTILE.INC(L41:L42,0.75) -> 51.75 | M46: =_xlfn.PERCENTILE.INC(M41:M42,0.75) -> 76.3775
B48: Vietnam
B49: ='Raw Trading Comps'!A29 -> PT GoTo Gojek Tokopedia Tbk (IDX:GOTO) | E49: 0 | F49: =_xlfn.XLOOKUP($B49,'Raw Trading Comps'!$A$15:$A$32,'Raw Trading Comps'!H$15:H$32) -> 41.57 | G49: =_xlfn.XLOOKUP($B49,'Raw Trading Comps'!$A$15:$A$32,'Raw Trading Comps'!I$15:I$32) -> 21.65 | H49: =_xlfn.XLOOKUP($B49,'Raw Trading Comps'!$A$15:$A$32,'Raw Trading Comps'!J$15:J$32) -> 2.9 | I49: =_xlfn.XLOOKUP($B49,'Raw Trading Comps'!$A$15:$A$32,'Raw Trading Comps'!K$15:K$32) -> 2.8 | J49: =_xlfn.XLOOKUP($B49,'Raw Trading Comps'!$A$15:$A$32,'Raw Trading Comps'!L$15:L$32) -> 2.43 | K49: 0 | L49: 0 | M49: =_xlfn.XLOOKUP($B49,'Raw Trading Comps'!$A$15:$A$32,'Raw Trading Comps'!O$15:O$32) -> 86.32
B50: Average | E50: =AVERAGE(E49:E49) -> 0 | F50: =AVERAGE(F49:F49) -> 41.57 | G50: =AVERAGE(G49:G49) -> 21.65 | H50: =AVERAGE(H49:H49) -> 2.9 | I50: =AVERAGE(I49:I49) -> 2.8 | J50: =AVERAGE(J49:J49) -> 2.43 | K50: =AVERAGE(K49:K49) -> 0 | L50: =AVERAGE(L49:L49) -> 0 | M50: =AVERAGE(M49:M49) -> 86.32
B51: Median | E51: =MEDIAN(E49:E49) -> 0 | F51: =MEDIAN(F49:F49) -> 41.57 | G51: =MEDIAN(G49:G49) -> 21.65 | H51: =MEDIAN(H49:H49) -> 2.9 | I51: =MEDIAN(I49:I49) -> 2.8 | J51: =MEDIAN(J49:J49) -> 2.43 | K51: =MEDIAN(K49:K49) -> 0 | L51: =MEDIAN(L49:L49) -> 0 | M51: =MEDIAN(M49:M49) -> 86.32
B52: 1st Quartile | E52: =_xlfn.PERCENTILE.INC(E49:E49,0.25) -> 0 | F52: =_xlfn.PERCENTILE.INC(F49:F49,0.25) -> 41.57 | G52: =_xlfn.PERCENTILE.INC(G49:G49,0.25) -> 21.65 | H52: =_xlfn.PERCENTILE.INC(H49:H49,0.25) -> 2.9 | I52: =_xlfn.PERCENTILE.INC(I49:I49,0.25) -> 2.8 | J52: =_xlfn.PERCENTILE.INC(J49:J49,0.25) -> 2.43 | K52: =_xlfn.PERCENTILE.INC(K49:K49,0.25) -> 0 | L52: =_xlfn.PERCENTILE.INC(L49:L49,0.25) -> 0 | M52: =_xlfn.PERCENTILE.INC(M49:M49,0.25) -> 86.32
B53: 3rd Quartile | E53: =_xlfn.PERCENTILE.INC(E49:E49,0.75) -> 0 | F53: =_xlfn.PERCENTILE.INC(F49:F49,0.75) -> 41.57 | G53: =_xlfn.PERCENTILE.INC(G49:G49,0.75) -> 21.65 | H53: =_xlfn.PERCENTILE.INC(H49:H49,0.75) -> 2.9 | I53: =_xlfn.PERCENTILE.INC(I49:I49,0.75) -> 2.8 | J53: =_xlfn.PERCENTILE.INC(J49:J49,0.75) -> 2.43 | K53: =_xlfn.PERCENTILE.INC(K49:K49,0.75) -> 0 | L53: =_xlfn.PERCENTILE.INC(L49:L49,0.75) -> 0 | M53: =_xlfn.PERCENTILE.INC(M49:M49,0.75) -> 86.32
B55: Mobility Segment Comparables | C55: Revenue: | D55: Weightage:
B56: Singapore | C56: 578 | D56: =C56/SUM($C$56:$C$62) -> 0.20664998 | E56: =E14 -> 3 | F56: =F14 -> 23.54 | G56: =G14 -> 13.485 | H56: =H14 -> 1.9 | I56: =I14 -> 1.835 | J56: =J14 -> 1.64 | K56: =K14 -> 9.95 | L56: =L14 -> 6.825 | M56: =M14 -> 49.39
B57: Malaysia | C57: 816 | D57: =C57/SUM($C$56:$C$62) -> 0.29174115 | E57: =E21 -> 0 | F57: =F21 -> 41.57 | G57: =G21 -> 21.65 | H57: =H21 -> 2.9 | I57: =I21 -> 2.8 | J57: =J21 -> 2.43 | K57: =K21 -> 0 | L57: =L21 -> 0 | M57: =M21 -> 86.32
B58: Indonesia | C58: 643 | D58: =C58/SUM($C$56:$C$62) -> 0.22988917 | E58: =E29 -> 2 | F58: =F29 -> 22.74 | G58: =G29 -> 12.545 | H58: =H29 -> 1.95 | I58: =I29 -> 1.865 | J58: =J29 -> 1.64 | K58: =K29 -> 5.15 | L58: =L29 -> 3.375 | M58: =M29 -> 46.22
B59: Philippines | C59: 265 | D59: =C59/SUM($C$56:$C$62) -> 0.094744369 | E59: =E36 -> 0 | F59: =F36 -> 41.57 | G59: =G36 -> 21.65 | H59: =H36 -> 2.9 | I59: =I36 -> 2.8 | J59: =J36 -> 2.43 | K59: =K36 -> 0 | L59: =L36 -> 0 | M59: =M36 -> 86.32
B60: Thailand | C60: 252 | D60: =C60/SUM($C$56:$C$62) -> 0.090096532 | E60: =E44 -> 27.5 | F60: =F44 -> 35.56 | G60: =G44 -> 22.695 | H60: =H44 -> 6.85 | I60: =I44 -> 6.825 | J60: =J44 -> 6.26 | K60: =K44 -> 27.85 | L60: =L44 -> 34.5 | M60: =M44 -> 66.435
B61: Vietnam | C61: 228 | D61: =C61/SUM($C$56:$C$62) -> 0.08151591 | E61: =E51 -> 0 | F61: =F51 -> 41.57 | G61: =G51 -> 21.65 | H61: =H51 -> 2.9 | I61: =I51 -> 2.8 | J61: =J51 -> 2.43 | K61: =K51 -> 0 | L61: =L51 -> 0 | M61: =M51 -> 86.32
B62: Rest of Southeast Asia | C62: 15 | D62: =C62/SUM($C$56:$C$62) -> 0.0053628888 | E62: =MEDIAN(E56:E61) -> 1 | F62: =MEDIAN(F56:F61) -> 38.565 | G62: =MEDIAN(G56:G61) -> 21.65 | H62: =MEDIAN(H56:H61) -> 2.9 | I62: =MEDIAN(I56:I61) -> 2.8 | J62: =MEDIAN(J56:J61) -> 2.43 | K62: =MEDIAN(K56:K61) -> 2.575 | L62: =MEDIAN(L56:L61) -> 1.6875 | M62: =MEDIAN(M56:M61) -> 76.3775 | O62: Rest of Southeast Asia Comps were derived by getting the median value of all other operating countries due to the lack of publicly available data of the Competitors within the region.
B63: Mobility Segment (Median) | C63: =SUM(C56:C62) -> 2797 | D63: =SUM(D56:D62) -> 1 | E63: =SUMPRODUCT(E56:E62,$D$56:$D$62) -> 3.5627458 | F63: =SUMPRODUCT(F56:F62,$D$56:$D$62) -> 32.957692 | G63: =SUMPRODUCT(G56:G62,$D$56:$D$62) -> 17.963713 | H63: =SUMPRODUCT(H56:H62,$D$56:$D$62) -> 2.8308366 | I63: =SUMPRODUCT(I56:I62,$D$56:$D$62) -> 2.7482749 | J63: =SUMPRODUCT(J56:J62,$D$56:$D$62) -> 2.4302038 | K63: =SUMPRODUCT(K56:K62,$D$56:$D$62) -> 5.7630944 | L63: =SUMPRODUCT(L56:L62,$D$56:$D$62) -> 5.3036423 | M63: =SUMPRODUCT(M56:M62,$D$56:$D$62) -> 67.624971
A65: x | B65: Deliveries
B67: Singapore
B68: ='Raw Trading Comps'!A29 -> PT GoTo Gojek Tokopedia Tbk (IDX:GOTO) | E68: 0 | F68: =_xlfn.XLOOKUP($B68,'Raw Trading Comps'!$A$15:$A$32,'Raw Trading Comps'!H$15:H$32) -> 41.57 | G68: =_xlfn.XLOOKUP($B68,'Raw Trading Comps'!$A$15:$A$32,'Raw Trading Comps'!I$15:I$32) -> 21.65 | H68: =_xlfn.XLOOKUP($B68,'Raw Trading Comps'!$A$15:$A$32,'Raw Trading Comps'!J$15:J$32) -> 2.9 | I68: =_xlfn.XLOOKUP($B68,'Raw Trading Comps'!$A$15:$A$32,'Raw Trading Comps'!K$15:K$32) -> 2.8 | J68: =_xlfn.XLOOKUP($B68,'Raw Trading Comps'!$A$15:$A$32,'Raw Trading Comps'!L$15:L$32) -> 2.43 | K68: 0 | L68: 0 | M68: =_xlfn.XLOOKUP($B68,'Raw Trading Comps'!$A$15:$A$32,'Raw Trading Comps'!O$15:O$32) -> 86.32
B69: ='Raw Trading Comps'!A25 -> Delivery Hero SE (XTRA:DHER) | E69: =_xlfn.XLOOKUP($B69,'Raw Trading Comps'!$A$15:$A$32,'Raw Trading Comps'!G$15:G$32) -> 14.9 | F69: =_xlfn.XLOOKUP($B69,'Raw Trading Comps'!$A$15:$A$32,'Raw Trading Comps'!H$15:H$32) -> 8.42 | G69: =_xlfn.XLOOKUP($B69,'Raw Trading Comps'!$A$15:$A$32,'Raw Trading Comps'!I$15:I$32) -> 6.84 | H69: =_xlfn.XLOOKUP($B69,'Raw Trading Comps'!$A$15:$A$32,'Raw Trading Comps'!J$15:J$32) -> 0.6 | I69: =_xlfn.XLOOKUP($B69,'Raw Trading Comps'!$A$15:$A$32,'Raw Trading Comps'!K$15:K$32) -> 0.54 | J69: =_xlfn.XLOOKUP($B69,'Raw Trading Comps'!$A$15:$A$32,'Raw Trading Comps'!L$15:L$32) -> 0.49 | K69: 0 | L69: =_xlfn.XLOOKUP($B69,'Raw Trading Comps'!$A$15:$A$32,'Raw Trading Comps'!N$15:N$32) -> 37.62 | M69: =_xlfn.XLOOKUP($B69,'Raw Trading Comps'!$A$15:$A$32,'Raw Trading Comps'!O$15:O$32) -> 19.64
B70: Average | E70: =AVERAGE(E68:E69) -> 7.45 | F70: =AVERAGE(F68:F69) -> 24.995 | G70: =AVERAGE(G68:G69) -> 14.245 | H70: =AVERAGE(H68:H69) -> 1.75 | I70: =AVERAGE(I68:I69) -> 1.67 | J70: =AVERAGE(J68:J69) -> 1.46 | K70: =AVERAGE(K68:K69) -> 0 | L70: =AVERAGE(L68:L69) -> 18.81 | M70: =AVERAGE(M68:M69) -> 52.98
B71: Median | E71: =MEDIAN(E68:E69) -> 7.45 | F71: =MEDIAN(F68:F69) -> 24.995 | G71: =MEDIAN(G68:G69) -> 14.245 | H71: =MEDIAN(H68:H69) -> 1.75 | I71: =MEDIAN(I68:I69) -> 1.67 | J71: =MEDIAN(J68:J69) -> 1.46 | K71: =MEDIAN(K68:K69) -> 0 | L71: =MEDIAN(L68:L69) -> 18.81 | M71: =MEDIAN(M68:M69) -> 52.98
B72: 1st Quartile | E72: =_xlfn.PERCENTILE.INC(E68:E69,0.25) -> 3.725 | F72: =_xlfn.PERCENTILE.INC(F68:F69,0.25) -> 16.7075 | G72: =_xlfn.PERCENTILE.INC(G68:G69,0.25) -> 10.5425 | H72: =_xlfn.PERCENTILE.INC(H68:H69,0.25) -> 1.175 | I72: =_xlfn.PERCENTILE.INC(I68:I69,0.25) -> 1.105 | J72: =_xlfn.PERCENTILE.INC(J68:J69,0.25) -> 0.975 | K72: =_xlfn.PERCENTILE.INC(K68:K69,0.25) -> 0 | L72: =_xlfn.PERCENTILE.INC(L68:L69,0.25) -> 9.405 | M72: =_xlfn.PERCENTILE.INC(M68:M69,0.25) -> 36.31
B73: 3rd Quartile | E73: =_xlfn.PERCENTILE.INC(E68:E69,0.75) -> 11.175 | F73: =_xlfn.PERCENTILE.INC(F68:F69,0.75) -> 33.2825 | G73: =_xlfn.PERCENTILE.INC(G68:G69,0.75) -> 17.9475 | H73: =_xlfn.PERCENTILE.INC(H68:H69,0.75) -> 2.325 | I73: =_xlfn.PERCENTILE.INC(I68:I69,0.75) -> 2.235 | J73: =_xlfn.PERCENTILE.INC(J68:J69,0.75) -> 1.945 | K73: =_xlfn.PERCENTILE.INC(K68:K69,0.75) -> 0 | L73: =_xlfn.PERCENTILE.INC(L68:L69,0.75) -> 28.215 | M73: =_xlfn.PERCENTILE.INC(M68:M69,0.75) -> 69.65
B75: Malaysia
B76: ='Raw Trading Comps'!A29 -> PT GoTo Gojek Tokopedia Tbk (IDX:GOTO) | E76: 0 | F76: =_xlfn.XLOOKUP($B76,'Raw Trading Comps'!$A$15:$A$32,'Raw Trading Comps'!H$15:H$32) -> 41.57 | G76: =_xlfn.XLOOKUP($B76,'Raw Trading Comps'!$A$15:$A$32,'Raw Trading Comps'!I$15:I$32) -> 21.65 | H76: =_xlfn.XLOOKUP($B76,'Raw Trading Comps'!$A$15:$A$32,'Raw Trading Comps'!J$15:J$32) -> 2.9 | I76: =_xlfn.XLOOKUP($B76,'Raw Trading Comps'!$A$15:$A$32,'Raw Trading Comps'!K$15:K$32) -> 2.8 | J76: =_xlfn.XLOOKUP($B76,'Raw Trading Comps'!$A$15:$A$32,'Raw Trading Comps'!L$15:L$32) -> 2.43 | K76: 0 | L76: 0 | M76: =_xlfn.XLOOKUP($B76,'Raw Trading Comps'!$A$15:$A$32,'Raw Trading Comps'!O$15:O$32) -> 86.32
B77: ='Raw Trading Comps'!A25 -> Delivery Hero SE (XTRA:DHER) | E77: =_xlfn.XLOOKUP($B77,'Raw Trading Comps'!$A$15:$A$32,'Raw Trading Comps'!G$15:G$32) -> 14.9 | F77: =_xlfn.XLOOKUP($B77,'Raw Trading Comps'!$A$15:$A$32,'Raw Trading Comps'!H$15:H$32) -> 8.42 | G77: =_xlfn.XLOOKUP($B77,'Raw Trading Comps'!$A$15:$A$32,'Raw Trading Comps'!I$15:I$32) -> 6.84 | H77: =_xlfn.XLOOKUP($B77,'Raw Trading Comps'!$A$15:$A$32,'Raw Trading Comps'!J$15:J$32) -> 0.6 | I77: =_xlfn.XLOOKUP($B77,'Raw Trading Comps'!$A$15:$A$32,'Raw Trading Comps'!K$15:K$32) -> 0.54 | J77: =_xlfn.XLOOKUP($B77,'Raw Trading Comps'!$A$15:$A$32,'Raw Trading Comps'!L$15:L$32) -> 0.49 | K77: 0 | L77: =_xlfn.XLOOKUP($B77,'Raw Trading Comps'!$A$15:$A$32,'Raw Trading Comps'!N$15:N$32) -> 37.62 | M77: =_xlfn.XLOOKUP($B77,'Raw Trading Comps'!$A$15:$A$32,'Raw Trading Comps'!O$15:O$32) -> 19.64
B78: Average | E78: =AVERAGE(E76:E77) -> 7.45 | F78: =AVERAGE(F76:F77) -> 24.995 | G78: =AVERAGE(G76:G77) -> 14.245 | H78: =AVERAGE(H76:H77) -> 1.75 | I78: =AVERAGE(I76:I77) -> 1.67 | J78: =AVERAGE(J76:J77) -> 1.46 | K78: =AVERAGE(K76:K77) -> 0 | L78: =AVERAGE(L76:L77) -> 18.81 | M78: =AVERAGE(M76:M77) -> 52.98
B79: Median | E79: =MEDIAN(E76:E77) -> 7.45 | F79: =MEDIAN(F76:F77) -> 24.995 | G79: =MEDIAN(G76:G77) -> 14.245 | H79: =MEDIAN(H76:H77) -> 1.75 | I79: =MEDIAN(I76:I77) -> 1.67 | J79: =MEDIAN(J76:J77) -> 1.46 | K79: =MEDIAN(K76:K77) -> 0 | L79: =MEDIAN(L76:L77) -> 18.81 | M79: =MEDIAN(M76:M77) -> 52.98
B80: 1st Quartile | E80: =_xlfn.PERCENTILE.INC(E76:E77,0.25) -> 3.725 | F80: =_xlfn.PERCENTILE.INC(F76:F77,0.25) -> 16.7075 | G80: =_xlfn.PERCENTILE.INC(G76:G77,0.25) -> 10.5425 | H80: =_xlfn.PERCENTILE.INC(H76:H77,0.25) -> 1.175 | I80: =_xlfn.PERCENTILE.INC(I76:I77,0.25) -> 1.105 | J80: =_xlfn.PERCENTILE.INC(J76:J77,0.25) -> 0.975 | K80: =_xlfn.PERCENTILE.INC(K76:K77,0.25) -> 0 | L80: =_xlfn.PERCENTILE.INC(L76:L77,0.25) -> 9.405 | M80: =_xlfn.PERCENTILE.INC(M76:M77,0.25) -> 36.31
B81: 3rd Quartile | E81: =_xlfn.PERCENTILE.INC(E76:E77,0.75) -> 11.175 | F81: =_xlfn.PERCENTILE.INC(F76:F77,0.75) -> 33.2825 | G81: =_xlfn.PERCENTILE.INC(G76:G77,0.75) -> 17.9475 | H81: =_xlfn.PERCENTILE.INC(H76:H77,0.75) -> 2.325 | I81: =_xlfn.PERCENTILE.INC(I76:I77,0.75) -> 2.235 | J81: =_xlfn.PERCENTILE.INC(J76:J77,0.75) -> 1.945 | K81: =_xlfn.PERCENTILE.INC(K76:K77,0.75) -> 0 | L81: =_xlfn.PERCENTILE.INC(L76:L77,0.75) -> 28.215 | M81: =_xlfn.PERCENTILE.INC(M76:M77,0.75) -> 69.65
B83: Indonesia
B84: ='Raw Trading Comps'!A29 -> PT GoTo Gojek Tokopedia Tbk (IDX:GOTO) | E84: 0 | F84: =_xlfn.XLOOKUP($B84,'Raw Trading Comps'!$A$15:$A$32,'Raw Trading Comps'!H$15:H$32) -> 41.57 | G84: =_xlfn.XLOOKUP($B84,'Raw Trading Comps'!$A$15:$A$32,'Raw Trading Comps'!I$15:I$32) -> 21.65 | H84: =_xlfn.XLOOKUP($B84,'Raw Trading Comps'!$A$15:$A$32,'Raw Trading Comps'!J$15:J$32) -> 2.9 | I84: =_xlfn.XLOOKUP($B84,'Raw Trading Comps'!$A$15:$A$32,'Raw Trading Comps'!K$15:K$32) -> 2.8 | J84: =_xlfn.XLOOKUP($B84,'Raw Trading Comps'!$A$15:$A$32,'Raw Trading Comps'!L$15:L$32) -> 2.43 | K84: 0 | L84: 0 | M84: =_xlfn.XLOOKUP($B84,'Raw Trading Comps'!$A$15:$A$32,'Raw Trading Comps'!O$15:O$32) -> 86.32
B85: ='Raw Trading Comps'!A31 -> Sea Limited (NYSE:SE) | E85: =_xlfn.XLOOKUP($B85,'Raw Trading Comps'!$A$15:$A$32,'Raw Trading Comps'!G$15:G$32) -> 35.3 | F85: =_xlfn.XLOOKUP($B85,'Raw Trading Comps'!$A$15:$A$32,'Raw Trading Comps'!H$15:H$32) -> 21.78 | G85: =_xlfn.XLOOKUP($B85,'Raw Trading Comps'!$A$15:$A$32,'Raw Trading Comps'!I$15:I$32) -> 17.08 | H85: =_xlfn.XLOOKUP($B85,'Raw Trading Comps'!$A$15:$A$32,'Raw Trading Comps'!J$15:J$32) -> 3.6 | I85: =_xlfn.XLOOKUP($B85,'Raw Trading Comps'!$A$15:$A$32,'Raw Trading Comps'!K$15:K$32) -> 3.41 | J85: =_xlfn.XLOOKUP($B85,'Raw Trading Comps'!$A$15:$A$32,'Raw Trading Comps'!L$15:L$32) -> 2.74 | K85: =_xlfn.XLOOKUP($B85,'Raw Trading Comps'!$A$15:$A$32,'Raw Trading Comps'!M$15:M$32) -> 70.3 | L85: =_xlfn.XLOOKUP($B85,'Raw Trading Comps'!$A$15:$A$32,'Raw Trading Comps'!N$15:N$32) -> 39.42 | M85: =_xlfn.XLOOKUP($B85,'Raw Trading Comps'!$A$15:$A$32,'Raw Trading Comps'!O$15:O$32) -> 26.82
B86: Average | E86: =AVERAGE(E84:E85) -> 17.65 | F86: =AVERAGE(F84:F85) -> 31.675 | G86: =AVERAGE(G84:G85) -> 19.365 | H86: =AVERAGE(H84:H85) -> 3.25 | I86: =AVERAGE(I84:I85) -> 3.105 | J86: =AVERAGE(J84:J85) -> 2.585 | K86: =AVERAGE(K84:K85) -> 35.15 | L86: =AVERAGE(L84:L85) -> 19.71 | M86: =AVERAGE(M84:M85) -> 56.57
B87: Median | E87: =MEDIAN(E84:E85) -> 17.65 | F87: =MEDIAN(F84:F85) -> 31.675 | G87: =MEDIAN(G84:G85) -> 19.365 | H87: =MEDIAN(H84:H85) -> 3.25 | I87: =MEDIAN(I84:I85) -> 3.105 | J87: =MEDIAN(J84:J85) -> 2.585 | K87: =MEDIAN(K84:K85) -> 35.15 | L87: =MEDIAN(L84:L85) -> 19.71 | M87: =MEDIAN(M84:M85) -> 56.57
B88: 1st Quartile | E88: =_xlfn.PERCENTILE.INC(E84:E85,0.25) -> 8.825 | F88: =_xlfn.PERCENTILE.INC(F84:F85,0.25) -> 26.7275 | G88: =_xlfn.PERCENTILE.INC(G84:G85,0.25) -> 18.2225 | H88: =_xlfn.PERCENTILE.INC(H84:H85,0.25) -> 3.075 | I88: =_xlfn.PERCENTILE.INC(I84:I85,0.25) -> 2.9525 | J88: =_xlfn.PERCENTILE.INC(J84:J85,0.25) -> 2.5075 | K88: =_xlfn.PERCENTILE.INC(K84:K85,0.25) -> 17.575 | L88: =_xlfn.PERCENTILE.INC(L84:L85,0.25) -> 9.855 | M88: =_xlfn.PERCENTILE.INC(M84:M85,0.25) -> 41.695
B89: 3rd Quartile | E89: =_xlfn.PERCENTILE.INC(E84:E85,0.75) -> 26.475 | F89: =_xlfn.PERCENTILE.INC(F84:F85,0.75) -> 36.6225 | G89: =_xlfn.PERCENTILE.INC(G84:G85,0.75) -> 20.5075 | H89: =_xlfn.PERCENTILE.INC(H84:H85,0.75) -> 3.425 | I89: =_xlfn.PERCENTILE.INC(I84:I85,0.75) -> 3.2575 | J89: =_xlfn.PERCENTILE.INC(J84:J85,0.75) -> 2.6625 | K89: =_xlfn.PERCENTILE.INC(K84:K85,0.75) -> 52.725 | L89: =_xlfn.PERCENTILE.INC(L84:L85,0.75) -> 29.565 | M89: =_xlfn.PERCENTILE.INC(M84:M85,0.75) -> 71.445
B91: Philippines
B92: ='Raw Trading Comps'!A25 -> Delivery Hero SE (XTRA:DHER) | E92: =_xlfn.XLOOKUP($B92,'Raw Trading Comps'!$A$15:$A$32,'Raw Trading Comps'!G$15:G$32) -> 14.9 | F92: =_xlfn.XLOOKUP($B92,'Raw Trading Comps'!$A$15:$A$32,'Raw Trading Comps'!H$15:H$32) -> 8.42 | G92: =_xlfn.XLOOKUP($B92,'Raw Trading Comps'!$A$15:$A$32,'Raw Trading Comps'!I$15:I$32) -> 6.84 | H92: =_xlfn.XLOOKUP($B92,'Raw Trading Comps'!$A$15:$A$32,'Raw Trading Comps'!J$15:J$32) -> 0.6 | I92: =_xlfn.XLOOKUP($B92,'Raw Trading Comps'!$A$15:$A$32,'Raw Trading Comps'!K$15:K$32) -> 0.54 | J92: =_xlfn.XLOOKUP($B92,'Raw Trading Comps'!$A$15:$A$32,'Raw Trading Comps'!L$15:L$32) -> 0.49 | K92: 0 | L92: =_xlfn.XLOOKUP($B92,'Raw Trading Comps'!$A$15:$A$32,'Raw Trading Comps'!N$15:N$32) -> 37.62 | M92: =_xlfn.XLOOKUP($B92,'Raw Trading Comps'!$A$15:$A$32,'Raw Trading Comps'!O$15:O$32) -> 19.64
B93: ='Raw Trading Comps'!A31 -> Sea Limited (NYSE:SE) | E93: =_xlfn.XLOOKUP($B93,'Raw Trading Comps'!$A$15:$A$32,'Raw Trading Comps'!G$15:G$32) -> 35.3 | F93: =_xlfn.XLOOKUP($B93,'Raw Trading Comps'!$A$15:$A$32,'Raw Trading Comps'!H$15:H$32) -> 21.78 | G93: =_xlfn.XLOOKUP($B93,'Raw Trading Comps'!$A$15:$A$32,'Raw Trading Comps'!I$15:I$32) -> 17.08 | H93: =_xlfn.XLOOKUP($B93,'Raw Trading Comps'!$A$15:$A$32,'Raw Trading Comps'!J$15:J$32) -> 3.6 | I93: =_xlfn.XLOOKUP($B93,'Raw Trading Comps'!$A$15:$A$32,'Raw Trading Comps'!K$15:K$32) -> 3.41 | J93: =_xlfn.XLOOKUP($B93,'Raw Trading Comps'!$A$15:$A$32,'Raw Trading Comps'!L$15:L$32) -> 2.74 | K93: =_xlfn.XLOOKUP($B93,'Raw Trading Comps'!$A$15:$A$32,'Raw Trading Comps'!M$15:M$32) -> 70.3 | L93: =_xlfn.XLOOKUP($B93,'Raw Trading Comps'!$A$15:$A$32,'Raw Trading Comps'!N$15:N$32) -> 39.42 | M93: =_xlfn.XLOOKUP($B93,'Raw Trading Comps'!$A$15:$A$32,'Raw Trading Comps'!O$15:O$32) -> 26.82
B94: Average | E94: =AVERAGE(E92:E93) -> 25.1 | F94: =AVERAGE(F92:F93) -> 15.1 | G94: =AVERAGE(G92:G93) -> 11.96 | H94: =AVERAGE(H92:H93) -> 2.1 | I94: =AVERAGE(I92:I93) -> 1.975 | J94: =AVERAGE(J92:J93) -> 1.615 | K94: =AVERAGE(K92:K93) -> 35.15 | L94: =AVERAGE(L92:L93) -> 38.52 | M94: =AVERAGE(M92:M93) -> 23.23
B95: Median | E95: =MEDIAN(E92:E93) -> 25.1 | F95: =MEDIAN(F92:F93) -> 15.1 | G95: =MEDIAN(G92:G93) -> 11.96 | H95: =MEDIAN(H92:H93) -> 2.1 | I95: =MEDIAN(I92:I93) -> 1.975 | J95: =MEDIAN(J92:J93) -> 1.615 | K95: =MEDIAN(K92:K93) -> 35.15 | L95: =MEDIAN(L92:L93) -> 38.52 | M95: =MEDIAN(M92:M93) -> 23.23
B96: 1st Quartile | E96: =_xlfn.PERCENTILE.INC(E92:E93,0.25) -> 20 | F96: =_xlfn.PERCENTILE.INC(F92:F93,0.25) -> 11.76 | G96: =_xlfn.PERCENTILE.INC(G92:G93,0.25) -> 9.4 | H96: =_xlfn.PERCENTILE.INC(H92:H93,0.25) -> 1.35 | I96: =_xlfn.PERCENTILE.INC(I92:I93,0.25) -> 1.2575 | J96: =_xlfn.PERCENTILE.INC(J92:J93,0.25) -> 1.0525 | K96: =_xlfn.PERCENTILE.INC(K92:K93,0.25) -> 17.575 | L96: =_xlfn.PERCENTILE.INC(L92:L93,0.25) -> 38.07 | M96: =_xlfn.PERCENTILE.INC(M92:M93,0.25) -> 21.435
B97: 3rd Quartile | E97: =_xlfn.PERCENTILE.INC(E92:E93,0.75) -> 30.2 | F97: =_xlfn.PERCENTILE.INC(F92:F93,0.75) -> 18.44 | G97: =_xlfn.PERCENTILE.INC(G92:G93,0.75) -> 14.52 | H97: =_xlfn.PERCENTILE.INC(H92:H93,0.75) -> 2.85 | I97: =_xlfn.PERCENTILE.INC(I92:I93,0.75) -> 2.6925 | J97: =_xlfn.PERCENTILE.INC(J92:J93,0.75) -> 2.1775 | K97: =_xlfn.PERCENTILE.INC(K92:K93,0.75) -> 52.725 | L97: =_xlfn.PERCENTILE.INC(L92:L93,0.75) -> 38.97 | M97: =_xlfn.PERCENTILE.INC(M92:M93,0.75) -> 25.025
B99: Thailand
B100: ='Raw Trading Comps'!A25 -> Delivery Hero SE (XTRA:DHER) | E100: =_xlfn.XLOOKUP($B100,'Raw Trading Comps'!$A$15:$A$32,'Raw Trading Comps'!G$15:G$32) -> 14.9 | F100: =_xlfn.XLOOKUP($B100,'Raw Trading Comps'!$A$15:$A$32,'Raw Trading Comps'!H$15:H$32) -> 8.42 | G100: =_xlfn.XLOOKUP($B100,'Raw Trading Comps'!$A$15:$A$32,'Raw Trading Comps'!I$15:I$32) -> 6.84 | H100: =_xlfn.XLOOKUP($B100,'Raw Trading Comps'!$A$15:$A$32,'Raw Trading Comps'!J$15:J$32) -> 0.6 | I100: =_xlfn.XLOOKUP($B100,'Raw Trading Comps'!$A$15:$A$32,'Raw Trading Comps'!K$15:K$32) -> 0.54 | J100: =_xlfn.XLOOKUP($B100,'Raw Trading Comps'!$A$15:$A$32,'Raw Trading Comps'!L$15:L$32) -> 0.49 | K100: 0 | L100: =_xlfn.XLOOKUP($B100,'Raw Trading Comps'!$A$15:$A$32,'Raw Trading Comps'!N$15:N$32) -> 37.62 | M100: =_xlfn.XLOOKUP($B100,'Raw Trading Comps'!$A$15:$A$32,'Raw Trading Comps'!O$15:O$32) -> 19.64
B101: ='Raw Trading Comps'!A31 -> Sea Limited (NYSE:SE) | E101: =_xlfn.XLOOKUP($B101,'Raw Trading Comps'!$A$15:$A$32,'Raw Trading Comps'!G$15:G$32) -> 35.3 | F101: =_xlfn.XLOOKUP($B101,'Raw Trading Comps'!$A$15:$A$32,'Raw Trading Comps'!H$15:H$32) -> 21.78 | G101: =_xlfn.XLOOKUP($B101,'Raw Trading Comps'!$A$15:$A$32,'Raw Trading Comps'!I$15:I$32) -> 17.08 | H101: =_xlfn.XLOOKUP($B101,'Raw Trading Comps'!$A$15:$A$32,'Raw Trading Comps'!J$15:J$32) -> 3.6 | I101: =_xlfn.XLOOKUP($B101,'Raw Trading Comps'!$A$15:$A$32,'Raw Trading Comps'!K$15:K$32) -> 3.41 | J101: =_xlfn.XLOOKUP($B101,'Raw Trading Comps'!$A$15:$A$32,'Raw Trading Comps'!L$15:L$32) -> 2.74 | K101: =_xlfn.XLOOKUP($B101,'Raw Trading Comps'!$A$15:$A$32,'Raw Trading Comps'!M$15:M$32) -> 70.3 | L101: =_xlfn.XLOOKUP($B101,'Raw Trading Comps'!$A$15:$A$32,'Raw Trading Comps'!N$15:N$32) -> 39.42 | M101: =_xlfn.XLOOKUP($B101,'Raw Trading Comps'!$A$15:$A$32,'Raw Trading Comps'!O$15:O$32) -> 26.82
B102: Average | E102: =AVERAGE(E100:E101) -> 25.1 | F102: =AVERAGE(F100:F101) -> 15.1 | G102: =AVERAGE(G100:G101) -> 11.96 | H102: =AVERAGE(H100:H101) -> 2.1 | I102: =AVERAGE(I100:I101) -> 1.975 | J102: =AVERAGE(J100:J101) -> 1.615 | K102: =AVERAGE(K100:K101) -> 35.15 | L102: =AVERAGE(L100:L101) -> 38.52 | M102: =AVERAGE(M100:M101) -> 23.23
B103: Median | E103: =MEDIAN(E100:E101) -> 25.1 | F103: =MEDIAN(F100:F101) -> 15.1 | G103: =MEDIAN(G100:G101) -> 11.96 | H103: =MEDIAN(H100:H101) -> 2.1 | I103: =MEDIAN(I100:I101) -> 1.975 | J103: =MEDIAN(J100:J101) -> 1.615 | K103: =MEDIAN(K100:K101) -> 35.15 | L103: =MEDIAN(L100:L101) -> 38.52 | M103: =MEDIAN(M100:M101) -> 23.23
B104: 1st Quartile | E104: =_xlfn.PERCENTILE.INC(E100:E101,0.25) -> 20 | F104: =_xlfn.PERCENTILE.INC(F100:F101,0.25) -> 11.76 | G104: =_xlfn.PERCENTILE.INC(G100:G101,0.25) -> 9.4 | H104: =_xlfn.PERCENTILE.INC(H100:H101,0.25) -> 1.35 | I104: =_xlfn.PERCENTILE.INC(I100:I101,0.25) -> 1.2575 | J104: =_xlfn.PERCENTILE.INC(J100:J101,0.25) -> 1.0525 | K104: =_xlfn.PERCENTILE.INC(K100:K101,0.25) -> 17.575 | L104: =_xlfn.PERCENTILE.INC(L100:L101,0.25) -> 38.07 | M104: =_xlfn.PERCENTILE.INC(M100:M101,0.25) -> 21.435
B105: 3rd Quartile | E105: =_xlfn.PERCENTILE.INC(E100:E101,0.75) -> 30.2 | F105: =_xlfn.PERCENTILE.INC(F100:F101,0.75) -> 18.44 | G105: =_xlfn.PERCENTILE.INC(G100:G101,0.75) -> 14.52 | H105: =_xlfn.PERCENTILE.INC(H100:H101,0.75) -> 2.85 | I105: =_xlfn.PERCENTILE.INC(I100:I101,0.75) -> 2.6925 | J105: =_xlfn.PERCENTILE.INC(J100:J101,0.75) -> 2.1775 | K105: =_xlfn.PERCENTILE.INC(K100:K101,0.75) -> 52.725 | L105: =_xlfn.PERCENTILE.INC(L100:L101,0.75) -> 38.97 | M105: =_xlfn.PERCENTILE.INC(M100:M101,0.75) -> 25.025
B107: Vietnam
B108: ='Raw Trading Comps'!A29 -> PT GoTo Gojek Tokopedia Tbk (IDX:GOTO) | E108: =AVERAGE(F108:G108) -> 31.61 | F108: =_xlfn.XLOOKUP($B108,'Raw Trading Comps'!$A$15:$A$32,'Raw Trading Comps'!H$15:H$32) -> 41.57 | G108: =_xlfn.XLOOKUP($B108,'Raw Trading Comps'!$A$15:$A$32,'Raw Trading Comps'!I$15:I$32) -> 21.65 | H108: =_xlfn.XLOOKUP($B108,'Raw Trading Comps'!$A$15:$A$32,'Raw Trading Comps'!J$15:J$32) -> 2.9 | I108: =_xlfn.XLOOKUP($B108,'Raw Trading Comps'!$A$15:$A$32,'Raw Trading Comps'!K$15:K$32) -> 2.8 | J108: =_xlfn.XLOOKUP($B108,'Raw Trading Comps'!$A$15:$A$32,'Raw Trading Comps'!L$15:L$32) -> 2.43 | K108: 0 | L108: 0 | M108: =_xlfn.XLOOKUP($B108,'Raw Trading Comps'!$A$15:$A$32,'Raw Trading Comps'!O$15:O$32) -> 86.32
B109: ='Raw Trading Comps'!A31 -> Sea Limited (NYSE:SE) | E109: =_xlfn.XLOOKUP($B109,'Raw Trading Comps'!$A$15:$A$32,'Raw Trading Comps'!G$15:G$32) -> 35.3 | F109: =_xlfn.XLOOKUP($B109,'Raw Trading Comps'!$A$15:$A$32,'Raw Trading Comps'!H$15:H$32) -> 21.78 | G109: =_xlfn.XLOOKUP($B109,'Raw Trading Comps'!$A$15:$A$32,'Raw Trading Comps'!I$15:I$32) -> 17.08 | H109: =_xlfn.XLOOKUP($B109,'Raw Trading Comps'!$A$15:$A$32,'Raw Trading Comps'!J$15:J$32) -> 3.6 | I109: =_xlfn.XLOOKUP($B109,'Raw Trading Comps'!$A$15:$A$32,'Raw Trading Comps'!K$15:K$32) -> 3.41 | J109: =_xlfn.XLOOKUP($B109,'Raw Trading Comps'!$A$15:$A$32,'Raw Trading Comps'!L$15:L$32) -> 2.74 | K109: =_xlfn.XLOOKUP($B109,'Raw Trading Comps'!$A$15:$A$32,'Raw Trading Comps'!M$15:M$32) -> 70.3 | L109: =_xlfn.XLOOKUP($B109,'Raw Trading Comps'!$A$15:$A$32,'Raw Trading Comps'!N$15:N$32) -> 39.42 | M109: =_xlfn.XLOOKUP($B109,'Raw Trading Comps'!$A$15:$A$32,'Raw Trading Comps'!O$15:O$32) -> 26.82
B110: Average | E110: =AVERAGE(E108:E109) -> 33.455 | F110: =AVERAGE(F108:F109) -> 31.675 | G110: =AVERAGE(G108:G109) -> 19.365 | H110: =AVERAGE(H108:H109) -> 3.25 | I110: =AVERAGE(I108:I109) -> 3.105 | J110: =AVERAGE(J108:J109) -> 2.585 | K110: =AVERAGE(K108:K109) -> 35.15 | L110: =AVERAGE(L108:L109) -> 19.71 | M110: =AVERAGE(M108:M109) -> 56.57
B111: Median | E111: =MEDIAN(E108:E109) -> 33.455 | F111: =MEDIAN(F108:F109) -> 31.675 | G111: =MEDIAN(G108:G109) -> 19.365 | H111: =MEDIAN(H108:H109) -> 3.25 | I111: =MEDIAN(I108:I109) -> 3.105 | J111: =MEDIAN(J108:J109) -> 2.585 | K111: =MEDIAN(K108:K109) -> 35.15 | L111: =MEDIAN(L108:L109) -> 19.71 | M111: =MEDIAN(M108:M109) -> 56.57
B112: 1st Quartile | E112: =_xlfn.PERCENTILE.INC(E108:E109,0.25) -> 32.5325 | F112: =_xlfn.PERCENTILE.INC(F108:F109,0.25) -> 26.7275 | G112: =_xlfn.PERCENTILE.INC(G108:G109,0.25) -> 18.2225 | H112: =_xlfn.PERCENTILE.INC(H108:H109,0.25) -> 3.075 | I112: =_xlfn.PERCENTILE.INC(I108:I109,0.25) -> 2.9525 | J112: =_xlfn.PERCENTILE.INC(J108:J109,0.25) -> 2.5075 | K112: =_xlfn.PERCENTILE.INC(K108:K109,0.25) -> 17.575 | L112: =_xlfn.PERCENTILE.INC(L108:L109,0.25) -> 9.855 | M112: =_xlfn.PERCENTILE.INC(M108:M109,0.25) -> 41.695
B113: 3rd Quartile | E113: =_xlfn.PERCENTILE.INC(E108:E109,0.75) -> 34.3775 | F113: =_xlfn.PERCENTILE.INC(F108:F109,0.75) -> 36.6225 | G113: =_xlfn.PERCENTILE.INC(G108:G109,0.75) -> 20.5075 | H113: =_xlfn.PERCENTILE.INC(H108:H109,0.75) -> 3.425 | I113: =_xlfn.PERCENTILE.INC(I108:I109,0.75) -> 3.2575 | J113: =_xlfn.PERCENTILE.INC(J108:J109,0.75) -> 2.6625 | K113: =_xlfn.PERCENTILE.INC(K108:K109,0.75) -> 52.725 | L113: =_xlfn.PERCENTILE.INC(L108:L109,0.75) -> 29.565 | M113: =_xlfn.PERCENTILE.INC(M108:M109,0.75) -> 71.445
B115: Delivery Segment Comparables | C115: Revenue: | D115: Weightage:
B116: Singapore | C116: 578 | D116: =C116/$C$123 -> 0.20664998 | E116: =E71 -> 7.45 | F116: =F74 -> 0 | G116: =G74 -> 0 | H116: =H74 -> 0 | I116: =I74 -> 0 | J116: =J74 -> 0 | K116: =K74 -> 0 | L116: =L74 -> 0 | M116: =M74 -> 0
...

Sheet DCF
C1: =Cover!$C$7&" ("&Cover!$C$8&": "&Cover!$C$9&")" -> Grab Holdings Limited (NASDAQ: GRAB)
C3: 12M Target Price: | D3: =Cover!$C$18 -> 7.2080319
C4: Upside: | D4: =D81 -> 0.36622391
C5: Scenario: | D5: Base Case
E6: Historical (31 Dec) | J6: Forecasted (31 Dec)
C7: ="In "&Cover!$C$10&", unless stated otherwise" -> In USD Mn, unless stated otherwise | E7: 20 | F7: =E7+1 -> 21 | G7: =F7+1 -> 22 | H7: =G7+1 -> 23 | I7: =H7+1 -> 24 | J7: =I7+1 -> 25 | K7: =J7+1 -> 26 | L7: =K7+1 -> 27 | M7: =L7+1 -> 28 | N7: =M7+1 -> 29 | P7: Notes:
C8: Fiscal year end date | E8: 44196 | F8: =EOMONTH(E8,12) -> 44561 | G8: =EOMONTH(F8,12) -> 44926 | H8: =EOMONTH(G8,12) -> 45291 | I8: =EOMONTH(H8,12) -> 45657 | J8: =EOMONTH(I8,12) -> 46022 | K8: =EOMONTH(J8,12) -> 46387 | L8: =EOMONTH(K8,12) -> 46752 | M8: =EOMONTH(L8,12) -> 47118 | N8: =EOMONTH(M8,12) -> 47483
A10: 1 | C10: DCF Model | E10: 20 | F10: =E10+1 -> 21 | G10: =F10+1 -> 22 | H10: =G10+1 -> 23 | I10: =H10+1 -> 24 | J10: =I10+1 -> 25 | K10: =J10+1 -> 26 | L10: =K10+1 -> 27 | M10: =L10+1 -> 28 | N10: =M10+1 -> 29
C12: General Assumptions
C13: WACC: | D13: =WACC!O23 -> 0.10562019
C14: Tax Rate: | D14: =WACC!E15 -> 0.2149891
C15: Valuation Date: | D15: 46028
C17: Revenue | E17: ='3FS'!D12 -> 469 | F17: ='3FS'!E12 -> 675 | G17: ='3FS'!F12 -> 1433 | H17: ='3FS'!G12 -> 2359 | I17: ='3FS'!H12 -> 2797 | J17: ='3FS'!I12 -> 3447.158 | K17: ='3FS'!J12 -> 4242.1624 | L17: ='3FS'!K12 -> 5260.5364 | ... N17: ='3FS'!M12 -> 8096.0017
C18: %yoy | F18: =F17/E17-1 -> 0.43923241 | G18: =G17/F17-1 -> 1.122963 | H18: =H17/G17-1 -> 0.64619679 | I18: =I17/H17-1 -> 0.18567189 | J18: =J17/I17-1 -> 0.23244832 | K18: =K17/J17-1 -> 0.23062606 | L18: =L17/K17-1 -> 0.24006011 | M18: =M17/L17-1 -> 0.24024207 | N18: =N17/M17-1 -> 0.24089233
C20: EBITDA | E20: ='3FS'!D45 -> -900 | F20: ='3FS'!E45 -> -1498 | G20: ='3FS'!F45 -> -1410 | H20: ='3FS'!G45 -> -215 | I20: ='3FS'!H45 -> 166 | J20: ='3FS'!I45 -> 440.93236 | K20: ='3FS'!J45 -> 699.525 | L20: ='3FS'!K45 -> 1062.5059 | ... N20: ='3FS'!M45 -> 2067.7115
C21: %revenue | E21: =E20/E17 -> -1.9189765 | F21: =F20/F17 -> -2.2192593 | G21: =G20/G17 -> -0.98394976 | H21: =H20/H17 -> -0.091140314 | I21: =I20/I17 -> 0.059349303 | J21: =J20/J17 -> 0.12791185 | K21: =K20/K17 -> 0.16489821 | L21: =L20/L17 -> 0.20197671 | ... N21: =N20/N17 -> 0.25539909
C23: EBIT | E23: ='3FS'!D42 -> -1287 | F23: ='3FS'!E42 -> -1843 | G23: ='3FS'!F42 -> -1560 | H23: ='3FS'!G42 -> -360 | I23: ='3FS'!H42 -> 19 | J23: ='3FS'!I42 -> 166.99936 | K23: ='3FS'!J42 -> 375.20026 | L23: ='3FS'!K42 -> 675.69233 | ... N23: ='3FS'!M42 -> 1687.5753
C24: %revenue | E24: =E23/E17 -> -2.7441365 | F24: =F23/F17 -> -2.7303704 | G24: =G23/G17 -> -1.0886253 | H24: =H23/H17 -> -0.15260704 | I24: =I23/I17 -> 0.0067929925 | J24: =J23/J17 -> 0.048445519 | K24: =K23/K17 -> 0.088445519 | L24: =L23/L17 -> 0.12844552 | ... N24: =N23/N17 -> 0.20844552
C26: Tax rate | J26: =D14 -> 0.2149891 | K26: =J26 -> 0.2149891 | L26: =K26 -> 0.2149891 | M26: =L26 -> 0.2149891 | N26: =M26 -> 0.2149891
C27: NOPAT | J27: =J23*(1-J26) -> 131.09632 | K27: =K23*(1-K26) -> 294.53629 | L27: =L23*(1-L26) -> 530.42585 | M27: =M23*(1-M26) -> 862.72353 | N27: =N23*(1-N26) -> 1324.765
C28: (+) D&A | J28: =SUM('3FS'!I112:I113) -> 273.933 | K28: =SUM('3FS'!J112:J113) -> 324.32474 | L28: =SUM('3FS'!K112:K113) -> 386.81352 | M28: =SUM('3FS'!L112:L113) -> 366.34083 | N28: =SUM('3FS'!M112:M113) -> 380.13622
C29: (-) Capital Expenditures | J29: =SUM('3FS'!I134:I135) -> -246.75585 | K29: =SUM('3FS'!J134:J135) -> -303.66419 | L29: =SUM('3FS'!K134:K135) -> -376.56184 | M29: =SUM('3FS'!L134:L135) -> -467.02784 | N29: =SUM('3FS'!M134:M135) -> -579.53126
C30: (-) Increases in Net Working Capital | J30: =SUM('3FS'!I115:I119) -> 117.39704 | K30: =SUM('3FS'!J115:J119) -> 179.9799 | L30: =SUM('3FS'!K115:K119) -> 230.5482 | M30: =SUM('3FS'!L115:L119) -> 280.53874 | N30: =SUM('3FS'!M115:M119) -> 361.37809
C31: UFCF | J31: =SUM(J27:J30) -> 275.67051 | K31: =SUM(K27:K30) -> 495.17674 | L31: =SUM(L27:L30) -> 771.22572 | M31: =SUM(M27:M30) -> 1042.5753 | N31: =SUM(N27:N30) -> 1486.748
C32: Discount Factor | J32: =YEARFRAC(D15,J8)/2 -> 0.0083333333 | K32: =J32+1 -> 1.0083333 | L32: =K32+1 -> 2.0083333 | M32: =L32+1 -> 3.0083333 | N32: =M32+1 -> 4.0083333
C33: PV of UFCF | J33: =J31/(1+J32)^$D$13 -> 275.42898 | K33: =K31/(1+K32)^$D$13 -> 460.01783 | L33: =L31/(1+L32)^$D$13 -> 686.53175 | M33: =M31/(1+M32)^$D$13 -> 900.37257 | N33: =N31/(1+N32)^$D$13 -> 1254.11
A35: 2 | C35: DCF Value Summary
C37: Gordon Growth Method | I37: EV/EBITDA Exit Multiple Method
C38: Terminal Growth Rate | D38: 0.04 | I38: Terminal Multiple - EV/EBITDA | N38: ='Trading Comps'!F194 -> 26.884175 | P38: 4.0% Terminal Growth Rate selected is meaningfully under the weighted average 20 year average GDP growth rate of Grabs countries of operations
C39: FY2029 UFCF x (1+g) | D39: =N31*(1+D38) -> 1546.218 | I39: FY2029 EBITDA | N39: =N20 -> 2067.7115
C40: Terminal Value in FY29E | D40: =D39/(D13-D38) -> 23563.143 | I40: Terminal Value in FY29E | N40: =N38*N39 -> 55588.717
C41: PV of Terminal Value | D41: =D40/(1+D13)^N32 -> 15756.001 | I41: PV of Terminal Value | N41: =N40/(1+D13)^N32 -> 37170.587
C42: PV of Stage 1 Cash Flows | D42: =SUM(J33:N33) -> 3576.4612 | I42: PV of Stage 1 Cash Flows | N42: =SUM(J33:N33) -> 3576.4612
A43: x | C43: Implied Enterprise Value | D43: =SUM(D41:D42) -> 19332.462 | I43: Implied Enterprise Value | N43: =SUM(N41:N42) -> 40747.049
C44: (+) Cash and Cash Equivalents | D44: ='3FS'!H53 -> 2964 | I44: (+) Cash and Cash Equivalents | N44: =D44 -> 2964
C45: (+) Other Financial Assets | D45: 0 | I45: (+) Short-Term Investments | N45: =D45 -> 0
C46: (+) Investments in associates and joint ventures | D46: ='3FS'!H64 -> 131 | I46: (+) Investments in associates and joint ventures | N46: =D46 -> 131
C47: (-) MV of Total Debt | D47: =-'3FS'!H78-'3FS'!H86 -> -364 | I47: (-) MV of Total Debt | N47: =D47 -> -364
C48: (-) Non-Controlling Interest | D48: 0 | I48: (-) Non-Controlling Interest | N48: =D48 -> 0
C49: Implied Equity Value | D49: =SUM(D43:D48) -> 22063.462 | I49: Implied Equity Value | N49: =SUM(N43:N48) -> 43478.049
C50: Fully Diluted Shares Outstanding | D50: ='Debt & Equity'!L103 -> 4037 | I50: Fully Diluted Shares Outstanding | N50: =D50 -> 4037
A51: x | C51: Implied Share Price | D51: =D49/D50 -> 5.4653114 | I51: Implied Share Price | N51: =N49/N50 -> 10.769891
C52: Current Share price | D52: =Cover!$C$19 -> 5.27 | I52: Current Share price | N52: =Cover!$C$19 -> 5.27
C53: Implied upside | D53: =D51/D52-1 -> 0.037060979 | I53: Implied upside | N53: =N51/N52-1 -> 1.0436225
A55: 3 | C55: Sensitivity Analysis
D57: Terminal Growth Rate
D58: =D51 -> 5.4653114 | E58: =F58-0.5% -> 0.03 | F58: =G58-0.5% -> 0.035 | G58: 0.04 | H58: =G58+0.5% -> 0.045 | I58: =H58+0.5% -> 0.05
D59: =D60-1% -> 0.085620191 | E59: 6.4907943 | F59: 7.0016066 | G59: 7.6243895 | H59: 8.400491 | I59: 9.3944749
C60: WACC | D60: =D61-1% -> 0.095620191 | E60: 5.5820016 | F60: 5.9337105 | G60: 6.3486533 | H60: 6.8455679 | I60: 7.4514068
D61: 0.10562019 | E61: 4.9166276 | F61: 5.1715457 | G61: 5.4653114 | H61: 5.807537 | I61: 6.2112917
D62: =D61+1% -> 0.11562019 | E62: 4.4091601 | F62: 4.601108 | G62: 4.8184392 | H62: 5.066545 | I62: 5.3524601
D63: =D62+1% -> 0.12562019 | E63: 4.0098726 | F63: 4.1587299 | G63: 4.3249729 | H63: 4.5118365 | I63: 4.723411
D65: Terminal Multiple
D66: =N51 -> 10.769891 | E66: =F66-1 -> 24.9 | F66: =G66-1 -> 25.9 | G66: 26.9 | H66: =G66+1 -> 27.9 | I66: =H66+1 -> 28.9
D67: =D68-1% -> 0.085620191 | E67: 10.759592 | F67: 11.128079 | G67: 11.496566 | H67: 11.865054 | I67: 12.233541
C68: WACC | D68: =D69-1% -> 0.095620191 | E68: 10.417491 | F68: 10.772681 | G68: 11.127871 | H68: 11.483061 | I68: 11.83825
D69: 0.10562019 | E69: 10.090337 | F69: 10.432824 | G69: 10.775311 | H69: 11.117797 | I69: 11.460284
D70: =D69+1% -> 0.11562019 | E70: 9.7773416 | F70: 10.107688 | G70: 10.438035 | H70: 10.768381 | I70: 11.098728
D71: =D70+1% -> 0.12562019 | E71: 9.4777654 | F71: 9.7965046 | G71: 10.115244 | H71: 10.433983 | I71: 10.752722
A74: 4 | C74: Final Valuation Summary
C76: DCF - Gordon Growth Method | D76: =D84 -> 5.4653114 | E76: 0.4
C77: DCF - Exit Multiple Method | D77: =D85 -> 10.769891 | E77: 0.4
C78: Relative Valuation - EV/ CY26 EBITDA | D78: ='Trading Comps'!F204 -> 3.5697554 | E78: 0.2
C79: Final Share Price | D79: 7.2 | E79: =SUM(E76:E78) -> 1
C80: Current Share price | D80: =Cover!$C$19 -> 5.27
C81: Implied upside | D81: =D79/D80-1 -> 0.36622391
C83: DCF Share Price
C84: DCF - Gordon Growth Method | D84: =D51 -> 5.4653114 | E84: 0.5
C85: DCF - Exit Multiple Method | D85: =N51 -> 10.769891 | E85: 0.5
C86: Final DCF Share Price | D86: =SUMPRODUCT(D84:D85,E84:E85) -> 8.117601 | E86: =SUM(E84:E85) -> 1
C87: Current Share price | D87: =Cover!$C$19 -> 5.27
C88: Implied upside | D88: =D86/D87-1 -> 0.54034175
C90: Relative Valuation
C91: EV/ CY26 EBITDA | D91: ='Trading Comps'!F204 -> 3.5697554 | E91: 1
C92: Final DCF Share Price | D92: =SUMPRODUCT(D91:D91,E91:E91) -> 3.5697554 | E92: =SUM(E91:E91) -> 1
C93: Current Share price | D93: =Cover!$C$19 -> 5.27
C94: Implied upside | D94: =D92/D93-1 -> -0.32262706
C96: Football Field
D97: Bear | E97: Diff | F97: Bull | G97: Reference
C98: 52W H&L | D98: 3.36 | E98: =F98-D98 -> 3.26 | F98: 6.62
C99: Blended Valuation | D99: 5.0504384 | E99: =F99-D99 -> 7.2692648 | F99: 12.319703 | G99: =$D$79 -> 7.2
C100: Relative Valuation - EV/CY 2026 EBITDA | D100: 2.0823059 | E100: =F100-D100 -> 3.1083825 | F100: 5.1906884 | G100: =$D$92 -> 3.5697554
C101: DCF - Gordon Growth Method | D101: 3.3378046 | E101: =F101-D101 -> 5.0487152 | F101: 8.3865198 | G101: =$D$84 -> 5.4653114
C102: DCF - Exit Multiple Method | D102: 6.7630722 | E102: =F102-D102 -> 9.4898145 | F102: 16.252887 | G102: =$D$85 -> 10.769891

Sheet Reverse DCF
C1: =Cover!$C$7&" ("&Cover!$C$8&": "&Cover!$C$9&")" -> Grab Holdings Limited (NASDAQ: GRAB)
C3: 12M Target Price: | D3: =Cover!$C$18 -> 7.2080319
C4: Upside: | D4: =Cover!$C$20 -> 0.36774798
C5: Scenario: | D5: Base Case
E6: Historical (31 Dec) | J6: Forecasted (31 Dec)
C7: ="In "&Cover!$C$10&", unless stated otherwise" -> In USD Mn, unless stated otherwise | E7: 20 | F7: =E7+1 -> 21 | G7: =F7+1 -> 22 | H7: =G7+1 -> 23 | I7: =H7+1 -> 24 | J7: =I7+1 -> 25 | K7: =J7+1 -> 26 | L7: =K7+1 -> 27 | M7: =L7+1 -> 28 | N7: =M7+1 -> 29 | P7: Notes:
E8: 44196 | F8: =EOMONTH(E8,12) -> 44561 | G8: =EOMONTH(F8,12) -> 44926 | H8: =EOMONTH(G8,12) -> 45291 | I8: =EOMONTH(H8,12) -> 45657 | J8: =EOMONTH(I8,12) -> 46022 | K8: =EOMONTH(J8,12) -> 46387 | L8: =EOMONTH(K8,12) -> 46752 | M8: =EOMONTH(L8,12) -> 47118 | N8: =EOMONTH(M8,12) -> 47483 | P8: Utilising the same operating assumptions as my initial discounted cash flow model (WACC, Tax Rate and Terminal growth rate, 5 year Revenue CAGR the street expects for Grab is 26.2%
A10: 1 | C10: Reverse DCF Model | P10: Can argue that my revenue build was conservative to reflect a margin of safety before arriving at my target price where Grab still trades at a meaningful discount
C12: General Assumptions
C13: WACC: | D13: =WACC!O23 -> 0.10562019
C14: Tax Rate: | D14: =WACC!E15 -> 0.2149891
C15: Valuation Date: | D15: 46016
C16: 5 Year Revenue CAGR: | D16: 0.16
C17: Terminal Growth Rate: | D17: 0.04
C19: Revenue | E19: ='3FS'!D12 -> 469 | F19: ='3FS'!E12 -> 675 | G19: ='3FS'!F12 -> 1433 | H19: ='3FS'!G12 -> 2359 | I19: ='3FS'!H12 -> 2797 | J19: =I19*(1+J20) -> 3244.52 | K19: =J19*(1+K20) -> 3763.6432 | L19: =K19*(1+L20) -> 4365.8261 | M19: =L19*(1+M20) -> 5064.3583 | N19: =M19*(1+N20) -> 5874.6556
C20: %yoy | F20: =(F19-E19)/E19 -> 0.43923241 | G20: =(G19-F19)/F19 -> 1.122963 | H20: =(H19-G19)/G19 -> 0.64619679 | I20: =(I19-H19)/H19 -> 0.18567189 | J20: =$D$16 -> 0.16 | K20: =$D$16 -> 0.16 | L20: =$D$16 -> 0.16 | M20: =$D$16 -> 0.16 | N20: =$D$16 -> 0.16
C22: EBIT | E22: ='3FS'!D42 -> -1287 | F22: ='3FS'!E42 -> -1843 | G22: ='3FS'!F42 -> -1560 | H22: ='3FS'!G42 -> -360 | I22: ='3FS'!H42 -> 19 | J22: =J19*J23 -> 55.081879 | K22: =K19*K23 -> 270.28731 | L22: =L19*L23 -> 466.77422 | M22: =M19*M23 -> 642.74527 | N22: =N19*N23 -> 863.07762
C23: % EBIT Margin | E23: =E22/'3FS'!D12 -> -2.7441365 | F23: =F22/'3FS'!E12 -> -2.7303704 | G23: =G22/'3FS'!F12 -> -1.0886253 | H23: =H22/'3FS'!G12 -> -0.15260704 | I23: =I22/'3FS'!H12 -> 0.0067929925 | J23: 0.016976896 | K23: 0.071815339 | L23: 0.10691544 | M23: =L23+2% -> 0.12691544 | N23: =M23+2% -> 0.14691544
C25: Tax Rate | J25: =$D$14 -> 0.2149891 | K25: =$D$14 -> 0.2149891 | L25: =$D$14 -> 0.2149891 | M25: =$D$14 -> 0.2149891 | N25: =$D$14 -> 0.2149891
C26: NOPAT | J26: =J22-(J22*J25) -> 43.239876 | K26: =K22-(K22*K25) -> 212.17849 | L26: =L22-(L22*L25) -> 366.42286 | M26: =M22-(M22*M25) -> 504.56204 | N26: =N22-(N22*N25) -> 677.52534
C27: % NOPAT Margin
C28: (+) D&A | J28: =SUM('3FS'!I112:I113) -> 273.933 | K28: =SUM('3FS'!J112:J113) -> 324.32474 | L28: =SUM('3FS'!K112:K113) -> 386.81352 | M28: =SUM('3FS'!L112:L113) -> 366.34083 | N28: =SUM('3FS'!M112:M113) -> 380.13622
C29: (-) Capital Expenditures | J29: ='3FS'!I134+'3FS'!I135 -> -246.75585 | K29: ='3FS'!J134+'3FS'!J135 -> -303.66419 | L29: ='3FS'!K134+'3FS'!K135 -> -376.56184 | M29: ='3FS'!L134+'3FS'!L135 -> -467.02784 | N29: ='3FS'!M134+'3FS'!M135 -> -579.53126
C30: (-) Increases in Net Working Capital | J30: =SUM('3FS'!I115:I119) -> 117.39704 | K30: =SUM('3FS'!J115:J119) -> 179.9799 | L30: =SUM('3FS'!K115:K119) -> 230.5482 | M30: =SUM('3FS'!L115:L119) -> 280.53874 | N30: =SUM('3FS'!M115:M119) -> 361.37809
C31: UFCF | J31: =SUM(J28:J30,J26) -> 187.81406 | K31: =SUM(K28:K30,K26) -> 412.81894 | L31: =SUM(L28:L30,L26) -> 607.22273 | M31: =SUM(M28:M30,M26) -> 684.41377 | N31: =SUM(N28:N30,N26) -> 839.50839
C32: Discount Factor | J32: =YEARFRAC(D15,J8)/2 -> 0.0083333333 | K32: =J32+1 -> 1.0083333 | L32: =K32+1 -> 2.0083333 | M32: =L32+1 -> 3.0083333 | N32: =M32+1 -> 4.0083333
C33: PV of UFCF | J33: =J31/(1+J32)^$D$13 -> 187.64951 | K33: =K31/(1+K32)^$D$13 -> 383.50765 | L33: =L31/(1+L32)^$D$13 -> 540.53913 | M33: =M31/(1+M32)^$D$13 -> 591.06274 | N33: =N31/(1+N32)^$D$13 -> 708.14681
A35: 2 | C35: DCF Value Summary
C37: Gordon Growth Method | I37: EV/EBITDA Exit Multiple Method
C38: Terminal Growth Rate | D38: =D17 -> 0.04 | I38: Terminal Multiple - EV/EBITDA | N38: ='Trading Comps'!F194 -> 26.884175
C39: FY2029 UFCF x (1+g) | D39: =N31*(1+D38) -> 873.08872 | I39: FY2029 EBITDA | N39: =N22+N28 -> 1243.2138
C40: Terminal Value in FY29E | D40: =D39/(D13-D38) -> 13305.184 | I40: Terminal Value in FY29E | N40: =N38*N39 -> 33422.778
C41: PV of Terminal Value | D41: =D40/(1+D13)^N32 -> 8896.7965 | I41: PV of Terminal Value | N41: =N40/(1+D13)^N32 -> 22348.857
C42: PV of Stage 1 Cash Flows | D42: =SUM(J33:N33) -> 2410.9059 | I42: PV of Stage 1 Cash Flows | N42: =SUM(J33:N33) -> 2410.9059
C43: Implied Enterprise Value | D43: =SUM(D41:D42) -> 11307.702 | I43: Implied Enterprise Value | N43: =SUM(N41:N42) -> 24759.763
C44: (+) Cash and Cash Equivalents | D44: =DCF!D44 -> 2964 | I44: (+) Cash and Cash Equivalents | N44: 2964
C45: (+) Other Financial Assets | D45: =DCF!D45 -> 0 | I45: (+) Short-Term Investments | N45: 0
C46: (+) Investments in associates and joint ventures | D46: =DCF!D46 -> 131 | I46: (+) Investments in associates and joint ventures | N46: 131
C47: (-) MV of Total Debt | D47: =DCF!D47 -> -364 | I47: (-) MV of Total Debt | N47: -364
C48: (-) Non-Controlling Interest | D48: =DCF!D48 -> 0 | I48: (-) Non-Controlling Interest | N48: 0
C49: Implied Equity Value | D49: =SUM(D43:D48) -> 14038.702 | I49: Implied Equity Value | N49: =SUM(N43:N48) -> 27490.763
C50: Fully Diluted Shares Outstanding | D50: =DCF!D50 -> 4037 | I50: Fully Diluted Shares Outstanding | N50: =D50 -> 4037
C51: Implied Share Price | D51: =D49/D50 -> 3.4775086 | I51: Implied Share Price | N51: =N49/N50 -> 6.809701
C52: Current Share Price | D52: =Cover!C19 -> 5.27 | I52: Current Share price | N52: =Cover!$C$19 -> 5.27
C54: DCF Share Price
C55: DCF - Gordon Growth Method | D55: =D51 -> 3.4775086 | E55: 0.5
C56: DCF - Exit Multiple Method | D56: =N51 -> 6.809701 | E56: 0.5
C57: Final DCF Share Price | D57: =SUMPRODUCT(D55:D56,E55:E56) -> 5.1436048 | E57: =SUM(E55:E56) -> 1
C58: Current Share price | D58: =Cover!$C$19 -> 5.27

Sheet Terminal Growth Rate
B1: =Cover!$C$7&" ("&Cover!$C$8&": "&Cover!$C$9&")" -> Grab Holdings Limited (NASDAQ: GRAB)
B3: 12M Target Price | C3: =Cover!$C$18 -> 7.2080319
B4: Scenario | C4: =[1]Cover!D11 -> Base Case
A8: x | B8: Series Name | C8: Series Code | D8: Country Name | E8: Country Code | F8: 2005 [YR2005] | G8: 2006 [YR2006] | H8: 2007 [YR2007] | I8: 2008 [YR2008] | J8: 2009 [YR2009] | K8: 2010 [YR2010] | L8: 2011 [YR2011] | M8: 2012 [YR2012] | N8: 2013 [YR2013] | O8: 2014 [YR2014] | P8: 2015 [YR2015] | Q8: 2016 [YR2016] | R8: 2017 [YR2017] | S8: 2018 [YR2018] | T8: 2019 [YR2019] | U8: 2020 [YR2020] | V8: 2021 [YR2021] | W8: 2022 [YR2022] | X8: 2023 [YR2023] | Y8: 2024 [YR2024]
B9: GDP growth (annual %) | C9: NY.GDP.MKTP.KD.ZG | D9: Afghanistan | E9: AFG | F9: ='GDP Growth Rates'!E2/100 -> 0.11229715 | G9: ='GDP Growth Rates'!F2/100 -> 0.053574032 | H9: ='GDP Growth Rates'!G2/100 -> 0.1382632 | I9: ='GDP Growth Rates'!H2/100 -> 0.039249838 | J9: ='GDP Growth Rates'!I2/100 -> 0.21390528 | K9: ='GDP Growth Rates'!J2/100 -> 0.14362441 | L9: ='GDP Growth Rates'!K2/100 -> 0.0042635478 | M9: ='GDP Growth Rates'!L2/100 -> 0.12752287 | ... Y9: ='GDP Growth Rates'!X2/100 -> #VALUE!
B10: GDP growth (annual %) | C10: NY.GDP.MKTP.KD.ZG | D10: Albania | E10: ALB | F10: ='GDP Growth Rates'!E3/100 -> 0.051308219 | G10: ='GDP Growth Rates'!F3/100 -> 0.060189812 | H10: ='GDP Growth Rates'!G3/100 -> 0.065000926 | I10: ='GDP Growth Rates'!H3/100 -> 0.069070623 | J10: ='GDP Growth Rates'!I3/100 -> 0.026907515 | K10: ='GDP Growth Rates'!J3/100 -> 0.029731544 | L10: ='GDP Growth Rates'!K3/100 -> 0.024635168 | M10: ='GDP Growth Rates'!L3/100 -> 0.0098412988 | ... Y10: ='GDP Growth Rates'!X3/100 -> 0.039617191
B11: GDP growth (annual %) | C11: NY.GDP.MKTP.KD.ZG | D11: Algeria | E11: DZA | F11: ='GDP Growth Rates'!E4/100 -> 0.054 | G11: ='GDP Growth Rates'!F4/100 -> 0.029 | H11: ='GDP Growth Rates'!G4/100 -> 0.031 | I11: ='GDP Growth Rates'!H4/100 -> 0.025 | J11: ='GDP Growth Rates'!I4/100 -> 0.012 | K11: ='GDP Growth Rates'!J4/100 -> 0.048 | L11: ='GDP Growth Rates'!K4/100 -> 0.03 | M11: ='GDP Growth Rates'!L4/100 -> 0.024 | ... Y11: ='GDP Growth Rates'!X4/100 -> 0.033
B12: GDP growth (annual %) | C12: NY.GDP.MKTP.KD.ZG | D12: American Samoa | E12: ASM | F12: ='GDP Growth Rates'!E5/100 -> -0.0040816327 | G12: ='GDP Growth Rates'!F5/100 -> -0.040983607 | H12: ='GDP Growth Rates'!G5/100 -> 0.018518519 | I12: ='GDP Growth Rates'!H5/100 -> -0.026573427 | J12: ='GDP Growth Rates'!I5/100 -> -0.041666667 | K12: ='GDP Growth Rates'!J5/100 -> 0.0029985007 | L12: ='GDP Growth Rates'!K5/100 -> 0 | M12: ='GDP Growth Rates'!L5/100 -> -0.043348281 | ... Y12: ='GDP Growth Rates'!X5/100 -> #VALUE!
B13: GDP growth (annual %) | C13: NY.GDP.MKTP.KD.ZG | D13: Andorra | E13: AND | F13: ='GDP Growth Rates'!E6/100 -> 0.05397796 | G13: ='GDP Growth Rates'!F6/100 -> 0.048086887 | H13: ='GDP Growth Rates'!G6/100 -> 0.015531881 | I13: ='GDP Growth Rates'!H6/100 -> -0.055591864 | J13: ='GDP Growth Rates'!I6/100 -> -0.053028465 | K13: ='GDP Growth Rates'!J6/100 -> -0.01974958 | L13: ='GDP Growth Rates'!K6/100 -> -8.0697534e-05 | M13: ='GDP Growth Rates'!L6/100 -> -0.049744437 | ... Y13: ='GDP Growth Rates'!X6/100 -> 0.033718203
B14: GDP growth (annual %) | C14: NY.GDP.MKTP.KD.ZG | D14: Angola | E14: AGO | F14: ='GDP Growth Rates'!E7/100 -> 0.1503 | G14: ='GDP Growth Rates'!F7/100 -> 0.1155 | H14: ='GDP Growth Rates'!G7/100 -> 0.1401 | I14: ='GDP Growth Rates'!H7/100 -> 0.1117 | J14: ='GDP Growth Rates'!I7/100 -> 0.0086 | K14: ='GDP Growth Rates'!J7/100 -> 0.043983759 | L14: ='GDP Growth Rates'!K7/100 -> 0.034720531 | M14: ='GDP Growth Rates'!L7/100 -> 0.085421071 | ... Y14: ='GDP Growth Rates'!X7/100 -> 0.044239045
B15: GDP growth (annual %) | C15: NY.GDP.MKTP.KD.ZG | D15: Antigua and Barbuda | E15: ATG | F15: ='GDP Growth Rates'!E8/100 -> 0.064736894 | G15: ='GDP Growth Rates'!F8/100 -> 0.12708147 | H15: ='GDP Growth Rates'!G8/100 -> 0.093151827 | I15: ='GDP Growth Rates'!H8/100 -> -0.00014006598 | J15: ='GDP Growth Rates'!I8/100 -> -0.11962879 | K15: ='GDP Growth Rates'!J8/100 -> -0.078405068 | L15: ='GDP Growth Rates'!K8/100 -> -0.019587426 | M15: ='GDP Growth Rates'!L8/100 -> 0.033731427 | ... Y15: ='GDP Growth Rates'!X8/100 -> 0.043275215
B16: GDP growth (annual %) | C16: NY.GDP.MKTP.KD.ZG | D16: Argentina | E16: ARG | F16: ='GDP Growth Rates'!E9/100 -> 0.088516599 | G16: ='GDP Growth Rates'!F9/100 -> 0.080471515 | H16: ='GDP Growth Rates'!G9/100 -> 0.090076509 | I16: ='GDP Growth Rates'!H9/100 -> 0.040572331 | J16: ='GDP Growth Rates'!I9/100 -> -0.059185251 | K16: ='GDP Growth Rates'!J9/100 -> 0.10125398 | L16: ='GDP Growth Rates'!K9/100 -> 0.060039517 | M16: ='GDP Growth Rates'!L9/100 -> -0.010264205 | ... Y16: ='GDP Growth Rates'!X9/100 -> -0.017191051
B17: GDP growth (annual %) | C17: NY.GDP.MKTP.KD.ZG | D17: Armenia | E17: ARM | F17: ='GDP Growth Rates'!E10/100 -> 0.139 | G17: ='GDP Growth Rates'!F10/100 -> 0.132 | H17: ='GDP Growth Rates'!G10/100 -> 0.137 | I17: ='GDP Growth Rates'!H10/100 -> 0.069 | J17: ='GDP Growth Rates'!I10/100 -> -0.141 | K17: ='GDP Growth Rates'!J10/100 -> 0.022 | L17: ='GDP Growth Rates'!K10/100 -> 0.047 | M17: ='GDP Growth Rates'!L10/100 -> 0.072 | ... Y17: ='GDP Growth Rates'!X10/100 -> 0.059
B18: GDP growth (annual %) | C18: NY.GDP.MKTP.KD.ZG | D18: Aruba | E18: ABW | F18: ='GDP Growth Rates'!E11/100 -> -0.0038313767 | G18: ='GDP Growth Rates'!F11/100 -> 0.011274115 | H18: ='GDP Growth Rates'!G11/100 -> 0.030895444 | I18: ='GDP Growth Rates'!H11/100 -> 0.018357552 | J18: ='GDP Growth Rates'!I11/100 -> -0.11677741 | K18: ='GDP Growth Rates'!J11/100 -> -0.027334568 | L18: ='GDP Growth Rates'!K11/100 -> 0.033692372 | M18: ='GDP Growth Rates'!L11/100 -> -0.010407999 | ... Y18: ='GDP Growth Rates'!X11/100 -> #VALUE!
B19: GDP growth (annual %) | C19: NY.GDP.MKTP.KD.ZG | D19: Australia | E19: AUS | F19: ='GDP Growth Rates'!E12/100 -> 0.031541675 | G19: ='GDP Growth Rates'!F12/100 -> 0.027553461 | H19: ='GDP Growth Rates'!G12/100 -> 0.037733217 | I19: ='GDP Growth Rates'!H12/100 -> 0.03586267 | J19: ='GDP Growth Rates'!I12/100 -> 0.018925558 | K19: ='GDP Growth Rates'!J12/100 -> 0.022199803 | L19: ='GDP Growth Rates'!K12/100 -> 0.024070802 | M19: ='GDP Growth Rates'!L12/100 -> 0.039167094 | ... Y19: ='GDP Growth Rates'!X12/100 -> 0.014311125
B20: GDP growth (annual %) | C20: NY.GDP.MKTP.KD.ZG | D20: Austria | E20: AUT | F20: ='GDP Growth Rates'!E13/100 -> 0.023203651 | G20: ='GDP Growth Rates'!F13/100 -> 0.03269336 | H20: ='GDP Growth Rates'!G13/100 -> 0.037752247 | I20: ='GDP Growth Rates'!H13/100 -> 0.014533056 | J20: ='GDP Growth Rates'!I13/100 -> -0.035862647 | K20: ='GDP Growth Rates'!J13/100 -> 0.018089824 | L20: ='GDP Growth Rates'!K13/100 -> 0.02927468 | M20: ='GDP Growth Rates'!L13/100 -> 0.0062824624 | ... Y20: ='GDP Growth Rates'!X13/100 -> -0.011735405
... B274: GDP growth (annual %) | C274: NY.GDP.MKTP.KD.ZG | D274: World | E274: WLD | F274: ='GDP Growth Rates'!E267/100 -> 0.040386153 | G274: ='GDP Growth Rates'!F267/100 -> 0.044712212 | H274: ='GDP Growth Rates'!G267/100 -> 0.043855832 | I274: ='GDP Growth Rates'!H267/100 -> 0.020739527 | J274: ='GDP Growth Rates'!I267/100 -> -0.013195982 | K274: ='GDP Growth Rates'!J267/100 -> 0.045271471 | L274: ='GDP Growth Rates'!K267/100 -> 0.03347311 | M274: ='GDP Growth Rates'!L267/100 -> 0.027072811 | ... Y274: ='GDP Growth Rates'!X267/100 -> 0.02863263
A276: x | C276: 2005 | D276: =C276+1 -> 2006 | E276: =D276+1 -> 2007 | F276: =E276+1 -> 2008 | G276: =F276+1 -> 2009 | H276: =G276+1 -> 2010 | I276: =H276+1 -> 2011 | J276: =I276+1 -> 2012 | K276: =J276+1 -> 2013 | ... V276: =U276+1 -> 2024
B277: Singapore | C277: =_xlfn.XLOOKUP($B277,$D$9:$D$274,F$9:F$274) -> 0.073663224 | D277: =_xlfn.XLOOKUP($B277,$D$9:$D$274,G$9:G$274) -> 0.090067661 | E277: =_xlfn.XLOOKUP($B277,$D$9:$D$274,H$9:H$274) -> 0.090215195 | F277: =_xlfn.XLOOKUP($B277,$D$9:$D$274,I$9:I$274) -> 0.018634835 | G277: =_xlfn.XLOOKUP($B277,$D$9:$D$274,J$9:J$274) -> 0.0012795338 | H277: =_xlfn.XLOOKUP($B277,$D$9:$D$274,K$9:K$274) -> 0.1451975 | I277: =_xlfn.XLOOKUP($B277,$D$9:$D$274,L$9:L$274) -> 0.062149342 | J277: =_xlfn.XLOOKUP($B277,$D$9:$D$274,M$9:M$274) -> 0.044354976 | ... V277: =_xlfn.XLOOKUP($B277,$D$9:$D$274,Y$9:Y$274) -> 0.043880236
B278: Malaysia | C278: =_xlfn.XLOOKUP($B278,$D$9:$D$274,F$9:F$274) -> 0.053321392 | D278: =_xlfn.XLOOKUP($B278,$D$9:$D$274,G$9:G$274) -> 0.055848471 | E278: =_xlfn.XLOOKUP($B278,$D$9:$D$274,H$9:H$274) -> 0.062987859 | F278: =_xlfn.XLOOKUP($B278,$D$9:$D$274,I$9:I$274) -> 0.048317699 | G278: =_xlfn.XLOOKUP($B278,$D$9:$D$274,J$9:J$274) -> -0.015135287 | H278: =_xlfn.XLOOKUP($B278,$D$9:$D$274,K$9:K$274) -> 0.074248474 | I278: =_xlfn.XLOOKUP($B278,$D$9:$D$274,L$9:L$274) -> 0.052939128 | J278: =_xlfn.XLOOKUP($B278,$D$9:$D$274,M$9:M$274) -> 0.054734542 | ... V278: =_xlfn.XLOOKUP($B278,$D$9:$D$274,Y$9:Y$274) -> 0.051141555
B279: Indonesia | C279: =_xlfn.XLOOKUP($B279,$D$9:$D$274,F$9:F$274) -> 0.056925713 | D279: =_xlfn.XLOOKUP($B279,$D$9:$D$274,G$9:G$274) -> 0.055009518 | E279: =_xlfn.XLOOKUP($B279,$D$9:$D$274,H$9:H$274) -> 0.063450222 | F279: =_xlfn.XLOOKUP($B279,$D$9:$D$274,I$9:I$274) -> 0.060137036 | G279: =_xlfn.XLOOKUP($B279,$D$9:$D$274,J$9:J$274) -> 0.046288712 | H279: =_xlfn.XLOOKUP($B279,$D$9:$D$274,K$9:K$274) -> 0.062238542 | I279: =_xlfn.XLOOKUP($B279,$D$9:$D$274,L$9:L$274) -> 0.061697842 | J279: =_xlfn.XLOOKUP($B279,$D$9:$D$274,M$9:M$274) -> 0.060300507 | ... V279: =_xlfn.XLOOKUP($B279,$D$9:$D$274,Y$9:Y$274) -> 0.050303447
B280: Philippines | C280: =_xlfn.XLOOKUP($B280,$D$9:$D$274,F$9:F$274) -> 0.049425051 | D280: =_xlfn.XLOOKUP($B280,$D$9:$D$274,G$9:G$274) -> 0.053164168 | E280: =_xlfn.XLOOKUP($B280,$D$9:$D$274,H$9:H$274) -> 0.065192916 | F280: =_xlfn.XLOOKUP($B280,$D$9:$D$274,I$9:I$274) -> 0.043444873 | G280: =_xlfn.XLOOKUP($B280,$D$9:$D$274,J$9:J$274) -> 0.014483231 | H280: =_xlfn.XLOOKUP($B280,$D$9:$D$274,K$9:K$274) -> 0.073345 | I280: =_xlfn.XLOOKUP($B280,$D$9:$D$274,L$9:L$274) -> 0.038582328 | J280: =_xlfn.XLOOKUP($B280,$D$9:$D$274,M$9:M$274) -> 0.068969517 | ... V280: =_xlfn.XLOOKUP($B280,$D$9:$D$274,Y$9:Y$274) -> 0.056920161
B281: Thailand | C281: =_xlfn.XLOOKUP($B281,$D$9:$D$274,F$9:F$274) -> 0.041876384 | D281: =_xlfn.XLOOKUP($B281,$D$9:$D$274,G$9:G$274) -> 0.049678109 | E281: =_xlfn.XLOOKUP($B281,$D$9:$D$274,H$9:H$274) -> 0.054351517 | F281: =_xlfn.XLOOKUP($B281,$D$9:$D$274,I$9:I$274) -> 0.017256988 | G281: =_xlfn.XLOOKUP($B281,$D$9:$D$274,J$9:J$274) -> -0.0069061823 | H281: =_xlfn.XLOOKUP($B281,$D$9:$D$274,K$9:K$274) -> 0.075133905 | I281: =_xlfn.XLOOKUP($B281,$D$9:$D$274,L$9:L$274) -> 0.0084013208 | J281: =_xlfn.XLOOKUP($B281,$D$9:$D$274,M$9:M$274) -> 0.072427962 | ... V281: =_xlfn.XLOOKUP($B281,$D$9:$D$274,Y$9:Y$274) -> 0.025259618
B282: Vietnam | C282: 0.0629 | D282: 0.0629 | E282: 0.0629 | F282: 0.0629 | G282: 0.0629 | H282: 0.0629 | I282: 0.0629 | J282: 0.0629 | K282: 0.0629 | L282: 0.0629 | M282: 0.0629 | N282: 0.0629 | O282: 0.0629 | P282: 0.0629 | Q282: 0.0629 | R282: 0.0629 | S282: 0.0629 | T282: 0.0629 | U282: 0.0629 | V282: 0.0629
B283: Rest of Southeast Asia | C283: =AVERAGE(C284:C285) -> 0.13436142 | D283: =AVERAGE(D284:D285) -> 0.12009731 | E283: =AVERAGE(E284:E285) -> 0.11194947 | F283: =AVERAGE(F284:F285) -> 0.088658357 | G283: =AVERAGE(G284:G285) -> 0.073123938 | H283: =AVERAGE(H284:H285) -> 0.073556789 | I283: =AVERAGE(I284:I285) -> 0.064390703 | J283: =AVERAGE(J284:J285) -> 0.074914635 | ... V283: =AVERAGE(V284:V285) -> 0.025218841
B284: Cambodia | C284: =_xlfn.XLOOKUP($B284,$D$9:$D$274,F$9:F$274) -> 0.13303334 | D284: =_xlfn.XLOOKUP($B284,$D$9:$D$274,G$9:G$274) -> 0.1094336 | E284: =_xlfn.XLOOKUP($B284,$D$9:$D$274,H$9:H$274) -> 0.10398458 | F284: =_xlfn.XLOOKUP($B284,$D$9:$D$274,I$9:I$274) -> 0.074763661 | G284: =_xlfn.XLOOKUP($B284,$D$9:$D$274,J$9:J$274) -> 0.040747785 | H284: =_xlfn.XLOOKUP($B284,$D$9:$D$274,K$9:K$274) -> 0.050769184 | I284: =_xlfn.XLOOKUP($B284,$D$9:$D$274,L$9:L$274) -> 0.072866581 | J284: =_xlfn.XLOOKUP($B284,$D$9:$D$274,M$9:M$274) -> 0.076502566 | ... V284: =_xlfn.XLOOKUP($B284,$D$9:$D$274,Y$9:Y$274) -> 0.060158146
B285: Myanmar | C285: =_xlfn.XLOOKUP($B285,$D$9:$D$274,F$9:F$274) -> 0.1356895 | D285: =_xlfn.XLOOKUP($B285,$D$9:$D$274,G$9:G$274) -> 0.13076101 | E285: =_xlfn.XLOOKUP($B285,$D$9:$D$274,H$9:H$274) -> 0.11991435 | F285: =_xlfn.XLOOKUP($B285,$D$9:$D$274,I$9:I$274) -> 0.10255305 | G285: =_xlfn.XLOOKUP($B285,$D$9:$D$274,J$9:J$274) -> 0.10550009 | H285: =_xlfn.XLOOKUP($B285,$D$9:$D$274,K$9:K$274) -> 0.096344395 | I285: =_xlfn.XLOOKUP($B285,$D$9:$D$274,L$9:L$274) -> 0.055914824 | J285: =_xlfn.XLOOKUP($B285,$D$9:$D$274,M$9:M$274) -> 0.073326704 | ... V285: =_xlfn.XLOOKUP($B285,$D$9:$D$274,Y$9:Y$274) -> -0.0097204641
A287: x | B287: Revenue Split | L287: Revenue (USD Mns) | M287: Split | N287: Average GDP Growth
B288: Singapore | L288: ='Revenue Build'!J29 -> 578 | M288: =L288/SUM($L$288:$L$294) -> 0.20664998 | N288: =AVERAGE($C277:$V277) -> 0.046765109
B289: Malaysia | L289: ='Revenue Build'!J30 -> 816 | M289: =L289/SUM($L$288:$L$294) -> 0.29174115 | N289: =AVERAGE($C278:$V278) -> 0.044713475
B290: Indonesia | L290: ='Revenue Build'!J31 -> 643 | M290: =L290/SUM($L$288:$L$294) -> 0.22988917 | N290: =AVERAGE($C279:$V279) -> 0.049682718
B291: Philippines | L291: ='Revenue Build'!J32 -> 265 | M291: =L291/SUM($L$288:$L$294) -> 0.094744369 | N291: =AVERAGE($C280:$V280) -> 0.05081819
B292: Thailand | L292: ='Revenue Build'!J33 -> 252 | M292: =L292/SUM($L$288:$L$294) -> 0.090096532 | N292: =AVERAGE($C281:$V281) -> 0.027302249
B293: Vietnam | L293: ='Revenue Build'!J34 -> 228 | M293: =L293/SUM($L$288:$L$294) -> 0.08151591 | N293: =AVERAGE($C282:$V282) -> 0.0629
B294: Rest of Southeast Asia | L294: ='Revenue Build'!J35 -> 15 | M294: =L294/SUM($L$288:$L$294) -> 0.0053628888 | N294: =AVERAGE($C283:$V283) -> 0.062762684
B295: Weighted Average GDP Growth Rate | N295: =SUMPRODUCT(M288:M294,N288:N294) -> 0.046868804

Sheet Drivers>>

Sheet Debt & Equity
C1: =Cover!$C$7&" ("&Cover!$C$8&": "&Cover!$C$9&")" -> Grab Holdings Limited (NASDAQ: GRAB)
C3: 12M Target Price: | E3: =Cover!$C$18 -> 7.2080319
C4: Scenario: | E4: =Cover!$C$11 -> Base Case
H5: Historical (31 Jan) | M5: Forecast (31 Jan)
C6: ="In "&Cover!$C$10&", unless stated otherwise" -> In USD Mn, unless stated otherwise | H6: 20 | I6: =H6+1 -> 21 | J6: =I6+1 -> 22 | K6: =J6+1 -> 23 | L6: =K6+1 -> 24 | M6: =L6+1 -> 25 | N6: =M6+1 -> 26 | O6: =N6+1 -> 27 | P6: =O6+1 -> 28 | ... R6: =Q6+1 -> 30 | T6: Comments:
C7: Fiscal year end date | H7: 44196 | I7: =EOMONTH(H7,12) -> 44561 | J7: =EOMONTH(I7,12) -> 44926 | K7: =EOMONTH(J7,12) -> 45291 | L7: =EOMONTH(K7,12) -> 45657 | M7: =EOMONTH(L7,12) -> 46022 | N7: =EOMONTH(M7,12) -> 46387 | O7: =EOMONTH(N7,12) -> 46752 | P7: =EOMONTH(O7,12) -> 47118 | Q7: =EOMONTH(P7,12) -> 47483
A9: 1 | C9: Debt Schedule | H9: 20 | I9: =H9+1 -> 21 | J9: =I9+1 -> 22 | K9: =J9+1 -> 23 | L9: =K9+1 -> 24 | M9: 25 | N9: =M9+1 -> 26 | O9: =N9+1 -> 27 | P9: =O9+1 -> 28 | Q9: =P9+1 -> 29
C11: Financial Debt, Current | H11: ='3FS'!D78 -> 140 | I11: ='3FS'!E78 -> 144 | J11: ='3FS'!F78 -> 117 | K11: ='3FS'!G78 -> 125 | L11: ='3FS'!H78 -> 123 | M11: =MAX(L11+M36+M62,0) -> 1584 | N11: =MAX(M11+N36+N62,0) -> 1584 | O11: =MAX(N11+O36+O62,0) -> 1584 | P11: =MAX(O11+P36+P62,0) -> 75 | Q11: =MAX(P11+Q36+Q62,0) -> 0
C12: Financial Debt, Non-Current | H12: ='3FS'!D86 -> 111 | I12: ='3FS'!E86 -> 2031 | J12: ='3FS'!F86 -> 1248 | K12: ='3FS'!G86 -> 668 | L12: ='3FS'!H86 -> 241 | M12: =M41-M11 -> 241 | N12: =N41-N11 -> 241 | O12: =O41-O11 -> 241 | P12: =P41-P11 -> 241 | Q12: =Q41-Q11 -> 158
C13: Total Debt | H13: =SUM(H11:H12) -> 251 | I13: =SUM(I11:I12) -> 2175 | J13: =SUM(J11:J12) -> 1365 | K13: =SUM(K11:K12) -> 793 | L13: =SUM(L11:L12) -> 364 | M13: =SUM(M11:M12) -> 1825 | N13: =SUM(N11:N12) -> 1825 | O13: =SUM(O11:O12) -> 1825 | ... Q13: =SUM(Q11:Q12) -> 158
C16: Revolver Schedule | H16: 21 | I16: =H16+1 -> 22 | J16: =I16+1 -> 23 | K16: =J16+1 -> 24 | L16: =K16+1 -> 25 | M16: 26 | N16: =M16+1 -> 27 | O16: =N16+1 -> 28 | P16: =O16+1 -> 29 | Q16: =P16+1 -> 30
C18: CIRCULARITY | F18: OFF
C20: Revenue | H20: ='3FS'!D12 -> 469 | I20: ='3FS'!E12 -> 675 | J20: ='3FS'!F12 -> 1433 | K20: ='3FS'!G12 -> 2359 | L20: ='3FS'!H12 -> 2797 | M20: ='3FS'!I12 -> 3447.158 | N20: ='3FS'!J12 -> 4242.1624 | O20: ='3FS'!K12 -> 5260.5364 | ... Q20: ='3FS'!M12 -> 8096.0017
C22: Beginning Cash and Equivalents | M22: ='3FS'!H53 -> 2964 | N22: ='3FS'!I53 -> 3387.2668 | O22: ='3FS'!J53 -> 3227.6697 | P22: ='3FS'!K53 -> 3232.7186 | Q22: ='3FS'!L53 -> 1940.4896
C23: (+) Cash Flow from Operations + Investing | M23: ='3FS'!I131+'3FS'!I142 -> -1037.7332 | N23: ='3FS'!J131+'3FS'!J142 -> -159.5971 | O23: ='3FS'!K131+'3FS'!K142 -> 5.04889 | P23: ='3FS'!L131+'3FS'!L142 -> 216.77099 | Q23: ='3FS'!M131+'3FS'!M142 -> 615.01748
C24: (-) Debt Principal Repayments | M24: =M40 -> -39 | N24: =N40 -> 0 | O24: =O40 -> 0 | P24: =P40 -> -1509 | Q24: =Q40 -> -158
C25: (-) Mandatory Lease Repayments | M25: 0 | N25: 0 | O25: 0 | P25: 0 | Q25: 0
C26: (-) Dividends | M26: 0 | N26: 0 | O26: 0 | P26: 0 | Q26: 0
C27: (-) Minimum Cash Balance | F27: 0.05 | M27: =-M20*$F$27 -> -172.3579 | N27: =-N20*$F$27 -> -212.10812 | O27: =-O20*$F$27 -> -263.02682 | P27: =-P20*$F$27 -> -326.21693 | Q27: =-Q20*$F$27 -> -404.80008
C28: (Required Fundraise) | M28: =IF($F$18="OFF",MIN(SUM(M22:M27),0),0) -> 0 | N28: =IF($F$18="OFF",MIN(SUM(N22:N27),0),0) -> 0 | O28: =IF($F$18="OFF",MIN(SUM(O22:O27),0),0) -> 0 | P28: =IF($F$18="OFF",MIN(SUM(P22:P27),0),0) -> 0 | Q28: =IF($F$18="OFF",MIN(SUM(Q22:Q27),0),0) -> 0
C30: %Debt Financing: | F30: 1
C32: Required Fundraise: | M32: =ABS(M28) -> 0 | N32: =ABS(N28) -> 0 | O32: =ABS(O28) -> 0 | P32: =ABS(P28) -> 0 | Q32: =ABS(Q28) -> 0
C33: Debt Financing | M33: =$F$30*M32 -> 0 | N33: =$F$30*N32 -> 0 | O33: =$F$30*O32 -> 0 | P33: =$F$30*P32 -> 0 | Q33: =$F$30*Q32 -> 0
C34: Equity Financing | M34: =(1-$F$30)*M32 -> 0 | N34: =(1-$F$30)*N32 -> 0 | O34: =(1-$F$30)*O32 -> 0 | P34: =(1-$F$30)*P32 -> 0 | Q34: =(1-$F$30)*Q32 -> 0
C36: Convertible Notes Proceeds | M36: 1500 | N36: 0 | O36: 0 | P36: 0 | Q36: 0
C38: Total Debt Beginning Balance | M38: =L13 -> 364 | N38: =M13 -> 1825 | O38: =N13 -> 1825 | P38: =O13 -> 1825 | Q38: =P13 -> 316
C39: (+) Borrowings | M39: =M33+M36 -> 1500 | N39: =N33+N36 -> 0 | O39: =O33+O36 -> 0 | P39: =P33+P36 -> 0 | Q39: =Q33+Q36 -> 0
C40: (-) Repayments | M40: =M62 -> -39 | N40: =N62 -> 0 | O40: =O62 -> 0 | P40: =P62 -> -1509 | Q40: =Q62 -> -158
C41: Ending Balance | M41: =SUM(M38:M40) -> 1825 | N41: =SUM(N38:N40) -> 1825 | O41: =SUM(O38:O40) -> 1825 | P41: =SUM(P38:P40) -> 316 | Q41: =SUM(Q38:Q40) -> 158
C44: Repayment Schedule
C46: Principal Repayments
C48: Loans from banks | E48: Principal | F48: Effective Rate | G48: Maturity
C49: THB Loan | E49: 39 | F49: 0.07 | G49: 25 | M49: =IF(M$6=$G49,-$E49,0) -> -39 | N49: =IF(N$6=$G49,-$E49,0) -> 0 | O49: =IF(O$6=$G49,-$E49,0) -> 0 | P49: =IF(P$6=$G49,-$E49,0) -> 0 | Q49: =IF(Q$6=$G49,-$E49,0) -> 0 | R49: =IF(R$6=$G49,-$E49,0) -> 0
C50: MYR loan | E50: =9 -> 9 | F50: 0.02 | G50: 28 | M50: =IF(M$6=$G50,-$E50,0) -> 0 | N50: =IF(N$6=$G50,-$E50,0) -> 0 | O50: =IF(O$6=$G50,-$E50,0) -> 0 | P50: =IF(P$6=$G50,-$E50,0) -> -9 | Q50: =IF(Q$6=$G50,-$E50,0) -> 0 | R50: =IF(R$6=$G50,-$E50,0) -> 0
C51: SGD Loan | E51: 158 | F51: 0.0495 | G51: 29 | M51: =IF(M$6=$G51,-$E51,0) -> 0 | N51: =IF(N$6=$G51,-$E51,0) -> 0 | O51: =IF(O$6=$G51,-$E51,0) -> 0 | P51: =IF(P$6=$G51,-$E51,0) -> 0 | Q51: =IF(Q$6=$G51,-$E51,0) -> -158 | R51: =IF(R$6=$G51,-$E51,0) -> 0
C52: 2030 Convertible Notes | E52: 1500 | F52: 0 | G52: 28 | M52: =IF(M$6=$G52,-$E52,0) -> 0 | N52: =IF(N$6=$G52,-$E52,0) -> 0 | O52: =IF(O$6=$G52,-$E52,0) -> 0 | P52: =IF(P$6=$G52,-$E52,0) -> -1500 | Q52: =IF(Q$6=$G52,-$E52,0) -> 0 | R52: =IF(R$6=$G52,-$E52,0) -> 0
C53: 2037 Notes | E53: 158 | F53: 0.083 | G53: 37 | M53: =IF(M$6=$G53,-$E53,0) -> 0 | N53: =IF(N$6=$G53,-$E53,0) -> 0 | O53: =IF(O$6=$G53,-$E53,0) -> 0 | P53: =IF(P$6=$G53,-$E53,0) -> 0 | Q53: =IF(Q$6=$G53,-$E53,0) -> 0 | R53: =IF(R$6=$G53,-$E53,0) -> 0
C55: Credit Revolver | E55: Principal | F55: Interest Rate | G55: Maturity
C56: {=TRANSPOSE($M$6:$Q$6)} -> 25 | E56: {=TRANSPOSE($M$39:$Q$39)} -> 1500 | F56: 0 | G56: =C56+5 -> 30 | M56: =IF(M$6=$G56,-$E56,0) -> 0 | N56: =IF(N$44=$G56,-$E56,0) -> 0 | O56: =IF(O$44=$G56,-$E56,0) -> 0 | P56: =IF(P$44=$G56,-$E56,0) -> 0 | Q56: =IF(Q$44=$G56,-$E56,0) -> 0 | R56: =IF(R$44=$G56,-$E56,0) -> 0
C57: 26 | E57: 0 | F57: 0 | G57: =C57+5 -> 31 | M57: =IF(M$44=$G57,-$E57,0) -> 0 | N57: =IF(N$44=$G57,-$E57,0) -> 0 | O57: =IF(O$44=$G57,-$E57,0) -> 0 | P57: =IF(P$44=$G57,-$E57,0) -> 0 | Q57: =IF(Q$44=$G57,-$E57,0) -> 0 | R57: =IF(R$44=$G57,-$E57,0) -> 0
C58: 27 | E58: 0 | F58: 0 | G58: =C58+5 -> 32 | M58: =IF(M$44=$G58,-$E58,0) -> 0 | N58: =IF(N$44=$G58,-$E58,0) -> 0 | O58: =IF(O$44=$G58,-$E58,0) -> 0 | P58: =IF(P$44=$G58,-$E58,0) -> 0 | Q58: =IF(Q$44=$G58,-$E58,0) -> 0 | R58: =IF(R$44=$G58,-$E58,0) -> 0
C59: 28 | E59: 0 | F59: 0 | G59: =C59+5 -> 33 | M59: =IF(M$44=$G59,-$E59,0) -> 0 | N59: =IF(N$44=$G59,-$E59,0) -> 0 | O59: =IF(O$44=$G59,-$E59,0) -> 0 | P59: =IF(P$44=$G59,-$E59,0) -> 0 | Q59: =IF(Q$44=$G59,-$E59,0) -> 0 | R59: =IF(R$44=$G59,-$E59,0) -> 0
C60: 29 | E60: 0 | F60: 0 | G60: =C60+5 -> 34 | M60: =IF(M$44=$G60,-$E60,0) -> 0 | N60: =IF(N$44=$G60,-$E60,0) -> 0 | O60: =IF(O$44=$G60,-$E60,0) -> 0 | P60: =IF(P$44=$G60,-$E60,0) -> 0 | Q60: =IF(Q$44=$G60,-$E60,0) -> 0 | R60: =IF(R$44=$G60,-$E60,0) -> 0
C62: Total Principal Repayments | M62: =SUM(M49:M60) -> -39 | N62: =SUM(N49:N60) -> 0 | O62: =SUM(O49:O60) -> 0 | P62: =SUM(P49:P60) -> -1509 | Q62: =SUM(Q49:Q60) -> -158 | R62: =SUM(R56:R60,R49:R49) -> 0
C64: Interest Schedule
C66: Loans from banks | E66: Principal | F66: Effective Rate | G66: Maturity
C67: THB Loan | E67: 39 | F67: 0.07 | G67: 25 | M67: =IF(M$6<=$G67,-$E67*$F67,0) -> -2.73 | N67: =IF(N$6<=$G67,-$E67*$F67,0) -> 0 | O67: =IF(O$6<=$G67,-$E67*$F67,0) -> 0 | P67: =IF(P$6<=$G67,-$E67*$F67,0) -> 0 | Q67: =IF(Q$6<=$G67,-$E67*$F67,0) -> 0 | R67: =IF(R$6=$G67,-$E67,0) -> 0
C68: MYR loan | E68: =9 -> 9 | F68: 0.02 | G68: 28 | M68: =IF(M$6<=$G68,-$E68*$F68,0) -> -0.18 | N68: =IF(N$6<=$G68,-$E68*$F68,0) -> -0.18 | O68: =IF(O$6<=$G68,-$E68*$F68,0) -> -0.18 | P68: =IF(P$6<=$G68,-$E68*$F68,0) -> -0.18 | Q68: =IF(Q$6<=$G68,-$E68*$F68,0) -> 0 | R68: =IF(R$6=$G68,-$E68,0) -> 0
C69: SGD Loan | E69: 158 | F69: 0.0495 | G69: 29 | M69: =IF(M$6<=$G69,-$E69*$F69,0) -> -7.821 | N69: =IF(N$6<=$G69,-$E69*$F69,0) -> -7.821 | O69: =IF(O$6<=$G69,-$E69*$F69,0) -> -7.821 | P69: =IF(P$6<=$G69,-$E69*$F69,0) -> -7.821 | Q69: =IF(Q$6<=$G69,-$E69*$F69,0) -> -7.821 | R69: =IF(R$6=$G69,-$E69,0) -> 0
C70: 2030 Convertible Notes | E70: 1500 | F70: 0 | G70: 28 | M70: =IF(M$6<=$G70,-$E70*$F70,0) -> 0 | N70: =IF(N$6<=$G70,-$E70*$F70,0) -> 0 | O70: =IF(O$6<=$G70,-$E70*$F70,0) -> 0 | P70: =IF(P$6<=$G70,-$E70*$F70,0) -> 0 | Q70: =IF(Q$6<=$G70,-$E70*$F70,0) -> 0 | R70: =IF(R$6=$G70,-$E70,0) -> 0
C71: 2037 Notes | E71: 158 | F71: 0.083 | G71: 37 | M71: =IF(M$6<=$G71,-$E71*$F71,0) -> -13.114 | N71: =IF(N$6<=$G71,-$E71*$F71,0) -> -13.114 | O71: =IF(O$6<=$G71,-$E71*$F71,0) -> -13.114 | P71: =IF(P$6<=$G71,-$E71*$F71,0) -> -13.114 | Q71: =IF(Q$6<=$G71,-$E71*$F71,0) -> -13.114 | R71: =IF(R$6=$G71,-$E71,0) -> 0
C73: Credit Revolver | E73: Principal | F73: Interest Rate | G73: Maturity
C74: {=TRANSPOSE($M$6:$Q$6)} -> 25 | E74: {=TRANSPOSE($M$39:$Q$39)} -> 1500 | F74: 0 | G74: =C74+5 -> 30 | M74: =IF(M$6<=$G74,-$E74*$F74,0) -> 0 | N74: =IF(N$6<=$G74,-$E74*$F74,0) -> 0 | O74: =IF(O$6<=$G74,-$E74*$F74,0) -> 0 | P74: =IF(P$6<=$G74,-$E74*$F74,0) -> 0 | Q74: =IF(Q$6<=$G74,-$E74*$F74,0) -> 0 | R74: =IF(R$44=$G74,-$E74,0) -> 0
C75: 26 | E75: 0 | F75: 0 | G75: =C75+5 -> 31 | M75: =IF(M$6<=$G75,-$E75*$F75,0) -> 0 | N75: =IF(N$6<=$G75,-$E75*$F75,0) -> 0 | O75: =IF(O$6<=$G75,-$E75*$F75,0) -> 0 | P75: =IF(P$6<=$G75,-$E75*$F75,0) -> 0 | Q75: =IF(Q$6<=$G75,-$E75*$F75,0) -> 0 | R75: =IF(R$44=$G75,-$E75,0) -> 0
C76: 27 | E76: 0 | F76: 0 | G76: =C76+5 -> 32 | M76: =IF(M$6<=$G76,-$E76*$F76,0) -> 0 | N76: =IF(N$6<=$G76,-$E76*$F76,0) -> 0 | O76: =IF(O$6<=$G76,-$E76*$F76,0) -> 0 | P76: =IF(P$6<=$G76,-$E76*$F76,0) -> 0 | Q76: =IF(Q$6<=$G76,-$E76*$F76,0) -> 0 | R76: =IF(R$44=$G76,-$E76,0) -> 0
C77: 28 | E77: 0 | F77: 0 | G77: =C77+5 -> 33 | M77: =IF(M$6<=$G77,-$E77*$F77,0) -> 0 | N77: =IF(N$6<=$G77,-$E77*$F77,0) -> 0 | O77: =IF(O$6<=$G77,-$E77*$F77,0) -> 0 | P77: =IF(P$6<=$G77,-$E77*$F77,0) -> 0 | Q77: =IF(Q$6<=$G77,-$E77*$F77,0) -> 0 | R77: =IF(R$44=$G77,-$E77,0) -> 0
C78: 29 | E78: 0 | F78: 0 | G78: =C78+5 -> 34 | M78: =IF(M$6<=$G78,-$E78*$F78,0) -> 0 | N78: =IF(N$6<=$G78,-$E78*$F78,0) -> 0 | O78: =IF(O$6<=$G78,-$E78*$F78,0) -> 0 | P78: =IF(P$6<=$G78,-$E78*$F78,0) -> 0 | Q78: =IF(Q$6<=$G78,-$E78*$F78,0) -> 0 | R78: =IF(R$44=$G78,-$E78,0) -> 0
C80: Total Interest Expense | M80: =SUM(M74:M78,M67:M71) -> -23.845 | N80: =SUM(N74:N78,N67:N71) -> -21.115 | O80: =SUM(O74:O78,O67:O71) -> -21.115 | P80: =SUM(P74:P78,P67:P71) -> -21.115 | Q80: =SUM(Q74:Q78,Q67:Q71) -> -20.935 | R80: =SUM(R74:R78,R67:R71) -> 0
A82: 2 | C82: Equity Schedule
C84: Equity attributable to the Parent
C85: Equity attributable to the Parent, BOP | M85: =L89 -> -17347 | N85: =M89 -> -17222.592 | O85: =N89 -> -16890.959 | P85: =O89 -> -16263.474 | Q85: =P89 -> -15218.27
C86: (+) Net Income | H86: ='3FS'!D110 -> -2608 | I86: ='3FS'!E110 -> -3449 | J86: ='3FS'!F110 -> -1683 | K86: ='3FS'!G110 -> -434 | L86: ='3FS'!H110 -> -105 | M86: ='3FS'!I110 -> 124.40757 | N86: ='3FS'!J110 -> 331.63345 | O86: ='3FS'!K110 -> 627.48484 | ... Q86: ='3FS'!M110 -> 1627.2364
C87: (+) Equity Financing | M87: =M34 -> 0 | N87: =N34 -> 0 | O87: =O34 -> 0 | P87: =P34 -> 0 | Q87: =Q34 -> 0
C88: (-) Dividends | M88: 0 | N88: 0 | O88: 0 | P88: 0 | Q88: 0
C89: Equity attributable to the Parent, EOP | H89: ='3FS'!D99 -> -10490 | I89: ='3FS'!E99 -> -14402 | J89: ='3FS'!F99 -> -16277 | K89: ='3FS'!G99 -> -16764 | L89: ='3FS'!H99 -> -17347 | M89: =SUM(M85:M88) -> -17222.592 | N89: =SUM(N85:N88) -> -16890.959 | O89: =SUM(O85:O88) -> -16263.474 | P89: =SUM(P85:P88) -> -15218.27 | Q89: =SUM(Q85:Q88) -> -13591.034
C91: Stock Based Compensation
C93: APIC Opening | I93: =H96 -> 140 | J93: =I96 -> 21529 | K93: =J96 -> 22278 | L93: =K96 -> 22669 | M93: =L96 -> 23549 | N93: =M96 -> 23549 | O93: =N96 -> 23549 | P93: =O96 -> 23549 | Q93: =P96 -> 23549
C94: SBC Expense | H94: 54 | I94: 357 | J94: 412 | K94: 304 | L94: 279 | M94: 0 | N94: 0 | O94: 0 | P94: 0 | Q94: 0
C95: Cash Equity Issuance | H95: 0 | I95: 0 | J95: 0 | K95: 0 | L95: 0 | M95: 0 | N95: 0 | O95: 0 | P95: 0 | Q95: 0
C96: APIC Closing | H96: ='3FS'!D98 -> 140 | I96: ='3FS'!E98 -> 21529 | J96: ='3FS'!F98 -> 22278 | K96: ='3FS'!G98 -> 22669 | L96: ='3FS'!H98 -> 23549 | M96: =SUM(M93:M95) -> 23549 | N96: =SUM(N93:N95) -> 23549 | O96: =SUM(O93:O95) -> 23549 | P96: =SUM(P93:P95) -> 23549 | Q96: =SUM(Q93:Q95) -> 23549
C98: Equity Schedule
C100: Reserves | G100: USD Mns | H100: ='3FS'!D100 -> 3951 | I100: ='3FS'!E100 -> 606 | J100: ='3FS'!F100 -> 602 | K100: ='3FS'!G100 -> 544 | L100: ='3FS'!H100 -> 197 | M100: =M101*M20 -> 242.79232 | N100: =N101*N20 -> 298.78656 | O100: =O101*O20 -> 370.51329 | P100: =P101*P20 -> 459.52617 | Q100: =Q101*Q20 -> 570.2225
C101: % Revenue | H101: =H100/H20 -> 8.424307 | I101: =I100/I20 -> 0.89777778 | J101: =J100/J20 -> 0.4200977 | K101: =K100/K20 -> 0.23060619 | L101: =L100/L20 -> 0.070432606 | M101: =L101 -> 0.070432606 | N101: =M101 -> 0.070432606 | O101: =N101 -> 0.070432606 | P101: =O101 -> 0.070432606 | Q101: =P101 -> 0.070432606
C103: Shares Outstanding | G103: USD Mns | H103: 3740 | I103: 3840 | J103: 3930 | K103: 4070 | L103: 4037 | M103: =L103 -> 4037 | N103: =M103 -> 4037 | O103: =N103 -> 4037 | P103: =O103 -> 4037 | Q103: =P103 -> 4037
M104: 0 | N104: 0 | O104: 0 | P104: 0 | Q104: 0
C106: EPS | G106: USD | H106: =H86/H103 -> -0.6973262 | I106: =I86/I103 -> -0.89817708 | J106: =J86/J103 -> -0.42824427 | K106: =K86/K103 -> -0.10663391 | L106: =L86/L103 -> -0.026009413 | M106: =M86/M103 -> 0.030816837 | N106: =N86/N103 -> 0.08214849 | O106: =O86/O103 -> 0.15543345 | ... Q106: =Q86/Q103 -> 0.40308061
C108: FCF | H108: -872 | I108: -1039 | J108: -872 | K108: -6 | L108: 739

Sheet Goodwill & Intangibles
C1: =Cover!$C$7&" ("&Cover!$C$8&": "&Cover!$C$9&")" -> Grab Holdings Limited (NASDAQ: GRAB)
C3: 12M Target Price: | F3: =Cover!$C$18 -> 7.2080319
C4: Scenario: | F4: =Cover!$C$11 -> Base Case
G5: Historical (31 Jan) | L5: Forecast (31 Jan)
C6: ="In "&Cover!$C$10&", unless stated otherwise" -> In USD Mn, unless stated otherwise | G6: 20 | H6: =G6+1 -> 21 | I6: =H6+1 -> 22 | J6: =I6+1 -> 23 | K6: =J6+1 -> 24 | L6: =K6+1 -> 25 | M6: =L6+1 -> 26 | N6: =M6+1 -> 27 | O6: =N6+1 -> 28 | P6: =O6+1 -> 29 | R6: Comments:
A10: 1 | C10: PPE
C12: Intangible Assets and Goodwill | G12: ='3FS'!D69 -> 913 | H12: ='3FS'!E69 -> 675 | I12: ='3FS'!F69 -> 904 | J12: ='3FS'!G69 -> 916 | K12: ='3FS'!H69 -> 975 | L12: =L35+L56 -> 961.25697 | M12: =M35+M56 -> 947.04886 | N12: =N35+N56 -> 932.94535 | O12: =O35+O56 -> 998.50321 | P12: =P35+P56 -> 1080.1258
C13: %yoy | H13: =H12/G12-1 -> -0.26067908 | I13: =I12/H12-1 -> 0.33925926 | J13: =J12/I12-1 -> 0.013274336 | K13: =K12/J12-1 -> 0.06441048 | L13: =L12/K12-1 -> -0.014095414 | M13: =M12/L12-1 -> -0.014780763 | N13: =N12/M12-1 -> -0.014892061 | O13: =O12/N12-1 -> 0.070269772 | P13: =P12/O12-1 -> 0.081744994
A15: x | C15: Assumptions
C17: Useful Life : | D17: Min | E17: Max | F17: Average
C18: Trademark | F18: 13
C19: Non-compete agreement | F19: 4
C20: Other intangible assets | F20: 3
C22: Revenue | G22: ='3FS'!D12 -> 469 | H22: ='3FS'!E12 -> 675 | I22: ='3FS'!F12 -> 1433 | J22: ='3FS'!G12 -> 2359 | K22: ='3FS'!H12 -> 2797 | L22: ='3FS'!I12 -> 3447.158 | M22: ='3FS'!J12 -> 4242.1624 | N22: ='3FS'!K12 -> 5260.5364 | ... P22: ='3FS'!M12 -> 8096.0017
C23: %yoy | H23: =H22/G22-1 -> 0.43923241 | I23: =I22/H22-1 -> 1.122963 | J23: =J22/I22-1 -> 0.64619679 | K23: =K22/J22-1 -> 0.18567189 | L23: =L22/K22-1 -> 0.23244832 | M23: =M22/L22-1 -> 0.23062606 | N23: =N22/M22-1 -> 0.24006011 | O23: =O22/N22-1 -> 0.24024207 | P23: =P22/O22-1 -> 0.24089233
C25: Additions to Intangible Assets and Goodwill | H25: =H42 -> 6 | I25: =I42 -> 252 | J25: =J42 -> 28 | K25: =K42 -> 84 | L25: =L22*L26 -> 72.22074 | M25: =M22*M26 -> 88.876725 | N25: =N22*N26 -> 110.21248 | O25: =O22*O26 -> 136.69016 | P25: =P22*P26 -> 169.61777
C26: % Revenue | H26: =H25/H22 -> 0.0088888889 | I26: =I25/I22 -> 0.17585485 | J26: =J25/J22 -> 0.011869436 | K26: =K25/K22 -> 0.030032177 | L26: =MEDIAN(H26:K26) -> 0.020950807 | M26: =L26 -> 0.020950807 | N26: =M26 -> 0.020950807 | O26: =N26 -> 0.020950807 | P26: =O26 -> 0.020950807
A28: x | C28: Capex Schedule and Allocation
C30: Cost Allocation:
C31: Trademark | G31: 84 | H31: 89 | I31: 69 | J31: 69 | K31: 70 | L31: =K31+L38 -> 83.827979 | M31: =L31+M38 -> 100.84505 | N31: =M31+N38 -> 121.94724 | O31: =N31+O38 -> 148.11907 | P31: =O31+P38 -> 180.59549
C32: Non-compete agreement | G32: 1644 | H32: 1644 | I32: 1644 | J32: 1644 | K32: 1644 | L32: =K32+L39 -> 1644 | M32: =L32+M39 -> 1644 | N32: =M32+N39 -> 1644 | O32: =N32+O39 -> 1644 | P32: =O32+P39 -> 1644
C33: Other intangible assets | G33: 17 | H33: 18 | I33: 127 | J33: 155 | K33: 200 | L33: =K33+L40 -> 238.54639 | M33: =L33+M40 -> 285.98258 | N33: =M33+N40 -> 344.8063 | O33: =N33+O40 -> 417.76196 | P33: =O33+P40 -> 508.29208
C34: Goodwill | G34: 712 | H34: 712 | I34: 875 | J34: 875 | K34: 913 | L34: =K34+L41 -> 932.84637 | M34: =L34+M41 -> 957.26984 | N34: =M34+N41 -> 987.5564 | O34: =N34+O41 -> 1025.1191 | P34: =O34+P41 -> 1071.7303
C35: Intangible Assets, gross | G35: =SUM(G31:G34) -> 2457 | H35: =SUM(H31:H34) -> 2463 | I35: =SUM(I31:I34) -> 2715 | J35: =SUM(J31:J34) -> 2743 | K35: =SUM(K31:K34) -> 2827 | L35: =SUM(L31:L34) -> 2899.2207 | M35: =SUM(M31:M34) -> 2988.0975 | N35: =SUM(N31:N34) -> 3098.3099 | ... P35: =SUM(P31:P34) -> 3404.6179
C37: Net Additions
C38: Trademark | H38: =H31-G31 -> 5 | I38: =I31-H31 -> -20 | J38: =J31-I31 -> 0 | K38: =K31-J31 -> 1 | L38: =L45*L$25 -> 13.827979 | M38: =M45*M$25 -> 17.017071 | N38: =N45*N$25 -> 21.102191 | O38: =O45*O$25 -> 26.171826 | P38: =P45*P$25 -> 32.476418
C39: Non-compete agreement | H39: =H32-G32 -> 0 | I39: =I32-H32 -> 0 | J39: =J32-I32 -> 0 | K39: =K32-J32 -> 0 | L39: =L46*L$25 -> 0 | M39: =M46*M$25 -> 0 | N39: =N46*N$25 -> 0 | O39: =O46*O$25 -> 0 | P39: =P46*P$25 -> 0
C40: Other intangible assets | H40: =H33-G33 -> 1 | I40: =I33-H33 -> 109 | J40: =J33-I33 -> 28 | K40: =K33-J33 -> 45 | L40: =L47*L$25 -> 38.546387 | M40: =M47*M$25 -> 47.436189 | N40: =N47*N$25 -> 58.823725 | O40: =O47*O$25 -> 72.955659 | P40: =P47*P$25 -> 90.530117
C41: Goodwill | H41: =H34-G34 -> 0 | I41: =I34-H34 -> 163 | J41: =J34-I34 -> 0 | K41: =K34-J34 -> 38 | L41: =L48*L$25 -> 19.846374 | M41: =M48*M$25 -> 24.423465 | N41: =N48*N$25 -> 30.286565 | O41: =O48*O$25 -> 37.562672 | P41: =P48*P$25 -> 46.611231
C42: Total Net Additions | H42: =SUM(H38:H41) -> 6 | I42: =SUM(I38:I41) -> 252 | J42: =SUM(J38:J41) -> 28 | K42: =SUM(K38:K41) -> 84 | L42: =SUM(L38:L41) -> 72.22074 | M42: =SUM(M38:M41) -> 88.876725 | N42: =SUM(N38:N41) -> 110.21248 | O42: =SUM(O38:O41) -> 136.69016 | P42: =SUM(P38:P41) -> 169.61777
C44: % OF ADDITIONS:
C45: Trademark | H45: =H38/H$42 -> 0.83333333 | I45: =I38/I$42 -> -0.079365079 | J45: =J38/J$42 -> 0 | K45: =K38/K$42 -> 0.011904762 | L45: =AVERAGE(G45:K45) -> 0.19146825 | M45: =L45 -> 0.19146825 | N45: =M45 -> 0.19146825 | O45: =N45 -> 0.19146825 | P45: =O45 -> 0.19146825
C46: Non-compete agreement | H46: =H39/H$42 -> 0 | I46: =I39/I$42 -> 0 | J46: =J39/J$42 -> 0 | K46: =K39/K$42 -> 0 | L46: =AVERAGE(G46:K46) -> 0 | M46: =L46 -> 0 | N46: =M46 -> 0 | O46: =N46 -> 0 | P46: =O46 -> 0
C47: Other intangible assets | H47: =H40/H$42 -> 0.16666667 | I47: =I40/I$42 -> 0.43253968 | J47: =J40/J$42 -> 1 | K47: =K40/K$42 -> 0.53571429 | L47: =AVERAGE(G47:K47) -> 0.53373016 | M47: =L47 -> 0.53373016 | N47: =M47 -> 0.53373016 | O47: =N47 -> 0.53373016 | P47: =O47 -> 0.53373016
C48: Goodwill | H48: =H41/H$42 -> 0 | I48: =I41/I$42 -> 0.6468254 | J48: =J41/J$42 -> 0 | K48: =K41/K$42 -> 0.45238095 | L48: =AVERAGE(G48:K48) -> 0.27480159 | M48: =L48 -> 0.27480159 | N48: =M48 -> 0.27480159 | O48: =N48 -> 0.27480159 | P48: =O48 -> 0.27480159
C49: Total(%) | H49: =SUM(H45:H48) -> 1 | I49: =SUM(I45:I48) -> 1 | J49: =SUM(J45:J48) -> 1 | K49: =SUM(K45:K48) -> 1 | L49: =SUM(L45:L48) -> 1 | M49: =SUM(M45:M48) -> 1 | N49: =SUM(N45:N48) -> 1 | O49: =SUM(O45:O48) -> 1 | P49: =SUM(P45:P48) -> 1
A51: x | C51: Depreciation Schedules
C53: Total Amortisation
C54: Beginning Accumulated Amortisation | L54: =K56 -> -1852 | M54: =L56 -> -1937.9638 | N54: =M56 -> -2041.0486 | O54: =N56 -> -2165.3646 | P54: =O56 -> -2236.4969
C55: (+) Amortisation | L55: =SUM(L64,L82) -> -85.963768 | M55: =SUM(M64,M82) -> -103.08484 | N55: =SUM(N64,N82) -> -124.31599 | O55: =SUM(O64,O82) -> -71.132299 | P55: =SUM(P64,P82) -> -87.995128
C56: Ending Accumulated Amortisation | K56: -1852 | L56: =SUM(L54:L55) -> -1937.9638 | M56: =SUM(M54:M55) -> -2041.0486 | N56: =SUM(N54:N55) -> -2165.3646 | O56: =SUM(O54:O55) -> -2236.4969 | P56: =SUM(P54:P55) -> -2324.492
A58: x | C58: =C18 -> Trademark
C60: Useful Life | F60: =F18 -> 13
C62: Beginning Balance | L62: =K31 -> 70 | M62: =L65 -> 77.379673 | N62: =M65 -> 86.639433 | O62: =N65 -> 98.361067 | P62: =O65 -> 113.13912
C63: (+) Additions | L63: =L38 -> 13.827979 | M63: =M38 -> 17.017071 | N63: =N38 -> 21.102191 | O63: =O38 -> 26.171826 | P63: =P38 -> 32.476418
C64: (-) Depreciation | L64: =L74 -> -6.4483061 | M64: =M74 -> -7.7573116 | N64: =N74 -> -9.3805571 | O64: =O74 -> -11.393774 | P64: =P74 -> -13.89196
C65: Ending Balance, net | L65: =SUM(L62:L64) -> 77.379673 | M65: =SUM(M62:M64) -> 86.639433 | N65: =SUM(N62:N64) -> 98.361067 | O65: =SUM(O62:O64) -> 113.13912 | P65: =SUM(P62:P64) -> 131.72358
C67: Beginning Year | E67: Amount | F67: Final Year
C68: =$L$6 -> 25 | E68: =L62 -> 70 | F68: =C68+$F$60-1 -> 37 | L68: =IF(AND(L$6<=$F68,L$6>=$C68),IFERROR(-$E68/$F$60,0),0) -> -5.3846154 | M68: =IF(AND(M$6<=$F68,M$6>=$C68),IFERROR(-$E68/$F$60,0),0) -> -5.3846154 | N68: =IF(AND(N$6<=$F68,N$6>=$C68),IFERROR(-$E68/$F$60,0),0) -> -5.3846154 | O68: =IF(AND(O$6<=$F68,O$6>=$C68),IFERROR(-$E68/$F$60,0),0) -> -5.3846154 | P68: =IF(AND(P$6<=$F68,P$6>=$C68),IFERROR(-$E68/$F$60,0),0) -> -5.3846154
C69: {=TRANSPOSE($L$6:$P$6)} -> 25 | E69: {=TRANSPOSE(L63:P63)} -> 13.827979 | F69: =C69+$F$60-1 -> 37 | L69: =IF(AND(L$6<=$F69,L$6>=$C69),IFERROR(-$E69/$F$60,0),0) -> -1.0636907 | M69: =IF(AND(M$6<=$F69,M$6>=$C69),IFERROR(-$E69/$F$60,0),0) -> -1.0636907 | N69: =IF(AND(N$6<=$F69,N$6>=$C69),IFERROR(-$E69/$F$60,0),0) -> -1.0636907 | O69: =IF(AND(O$6<=$F69,O$6>=$C69),IFERROR(-$E69/$F$60,0),0) -> -1.0636907 | P69: =IF(AND(P$6<=$F69,P$6>=$C69),IFERROR(-$E69/$F$60,0),0) -> -1.0636907
C70: 26 | E70: 17.017071 | F70: =C70+$F$60-1 -> 38 | L70: =IF(AND(L$6<=$F70,L$6>=$C70),IFERROR(-$E70/$F$60,0),0) -> 0 | M70: =IF(AND(M$6<=$F70,M$6>=$C70),IFERROR(-$E70/$F$60,0),0) -> -1.3090055 | N70: =IF(AND(N$6<=$F70,N$6>=$C70),IFERROR(-$E70/$F$60,0),0) -> -1.3090055 | O70: =IF(AND(O$6<=$F70,O$6>=$C70),IFERROR(-$E70/$F$60,0),0) -> -1.3090055 | P70: =IF(AND(P$6<=$F70,P$6>=$C70),IFERROR(-$E70/$F$60,0),0) -> -1.3090055
C71: 27 | E71: 21.102191 | F71: =C71+$F$60-1 -> 39 | L71: =IF(AND(L$6<=$F71,L$6>=$C71),IFERROR(-$E71/$F$60,0),0) -> 0 | M71: =IF(AND(M$6<=$F71,M$6>=$C71),IFERROR(-$E71/$F$60,0),0) -> 0 | N71: =IF(AND(N$6<=$F71,N$6>=$C71),IFERROR(-$E71/$F$60,0),0) -> -1.6232455 | O71: =IF(AND(O$6<=$F71,O$6>=$C71),IFERROR(-$E71/$F$60,0),0) -> -1.6232455 | P71: =IF(AND(P$6<=$F71,P$6>=$C71),IFERROR(-$E71/$F$60,0),0) -> -1.6232455
C72: 28 | E72: 26.171826 | F72: =C72+$F$60-1 -> 40 | L72: =IF(AND(L$6<=$F72,L$6>=$C72),IFERROR(-$E72/$F$60,0),0) -> 0 | M72: =IF(AND(M$6<=$F72,M$6>=$C72),IFERROR(-$E72/$F$60,0),0) -> 0 | N72: =IF(AND(N$6<=$F72,N$6>=$C72),IFERROR(-$E72/$F$60,0),0) -> 0 | O72: =IF(AND(O$6<=$F72,O$6>=$C72),IFERROR(-$E72/$F$60,0),0) -> -2.0132173 | P72: =IF(AND(P$6<=$F72,P$6>=$C72),IFERROR(-$E72/$F$60,0),0) -> -2.0132173
C73: 29 | E73: 32.476418 | F73: =C73+$F$60-1 -> 41 | L73: =IF(AND(L$6<=$F73,L$6>=$C73),IFERROR(-$E73/$F$60,0),0) -> 0 | M73: =IF(AND(M$6<=$F73,M$6>=$C73),IFERROR(-$E73/$F$60,0),0) -> 0 | N73: =IF(AND(N$6<=$F73,N$6>=$C73),IFERROR(-$E73/$F$60,0),0) -> 0 | O73: =IF(AND(O$6<=$F73,O$6>=$C73),IFERROR(-$E73/$F$60,0),0) -> 0 | P73: =IF(AND(P$6<=$F73,P$6>=$C73),IFERROR(-$E73/$F$60,0),0) -> -2.498186
C74: Total Depreciation | L74: =SUM(L68:L73) -> -6.4483061 | M74: =SUM(M68:M73) -> -7.7573116 | N74: =SUM(N68:N73) -> -9.3805571 | O74: =SUM(O68:O73) -> -11.393774 | P74: =SUM(P68:P73) -> -13.89196
A76: x | C76: =C20 -> Other intangible assets
C78: Useful Life | F78: =F20 -> 3
C80: Beginning Balance | L80: =K33 -> 200 | M80: =L83 -> 159.03092 | N80: =M83 -> 111.13959 | O80: =N83 -> 55.02788 | P80: =O83 -> 68.245014
C81: (+) Additions | L81: =L40 -> 38.546387 | M81: =M40 -> 47.436189 | N81: =N40 -> 58.823725 | O81: =O40 -> 72.955659 | P81: =P40 -> 90.530117
C82: (-) Depreciation | L82: =L92 -> -79.515462 | M82: =M92 -> -95.327525 | N82: =N92 -> -114.93543 | O82: =O92 -> -59.738524 | P82: =P92 -> -74.103167
C83: Ending Balance, net | L83: =SUM(L80:L82) -> 159.03092 | M83: =SUM(M80:M82) -> 111.13959 | N83: =SUM(N80:N82) -> 55.02788 | O83: =SUM(O80:O82) -> 68.245014 | P83: =SUM(P80:P82) -> 84.671965
C85: Beginning Year | E85: Amount | F85: Final Year
C86: =$L$6 -> 25 | E86: =L80 -> 200 | F86: =C86+$F$78-1 -> 27 | L86: =IF(AND(L$6<=$F86,L$6>=$C86),IFERROR(-$E86/$F$78,0),0) -> -66.666667 | M86: =IF(AND(M$6<=$F86,M$6>=$C86),IFERROR(-$E86/$F$78,0),0) -> -66.666667 | N86: =IF(AND(N$6<=$F86,N$6>=$C86),IFERROR(-$E86/$F$78,0),0) -> -66.666667 | O86: =IF(AND(O$6<=$F86,O$6>=$C86),IFERROR(-$E86/$F$78,0),0) -> 0 | P86: =IF(AND(P$6<=$F86,P$6>=$C86),IFERROR(-$E86/$F$78,0),0) -> 0
C87: {=TRANSPOSE($L$6:$P$6)} -> 25 | E87: {=TRANSPOSE(L81:P81)} -> 38.546387 | F87: =C87+$F$78-1 -> 27 | L87: =IF(AND(L$6<=$F87,L$6>=$C87),IFERROR(-$E87/$F$78,0),0) -> -12.848796 | M87: =IF(AND(M$6<=$F87,M$6>=$C87),IFERROR(-$E87/$F$78,0),0) -> -12.848796 | N87: =IF(AND(N$6<=$F87,N$6>=$C87),IFERROR(-$E87/$F$78,0),0) -> -12.848796 | O87: =IF(AND(O$6<=$F87,O$6>=$C87),IFERROR(-$E87/$F$78,0),0) -> 0 | P87: =IF(AND(P$6<=$F87,P$6>=$C87),IFERROR(-$E87/$F$78,0),0) -> 0
C88: 26 | E88: 47.436189 | F88: =C88+$F$78-1 -> 28 | L88: =IF(AND(L$6<=$F88,L$6>=$C88),IFERROR(-$E88/$F$78,0),0) -> 0 | M88: =IF(AND(M$6<=$F88,M$6>=$C88),IFERROR(-$E88/$F$78,0),0) -> -15.812063 | N88: =IF(AND(N$6<=$F88,N$6>=$C88),IFERROR(-$E88/$F$78,0),0) -> -15.812063 | O88: =IF(AND(O$6<=$F88,O$6>=$C88),IFERROR(-$E88/$F$78,0),0) -> -15.812063 | P88: =IF(AND(P$6<=$F88,P$6>=$C88),IFERROR(-$E88/$F$78,0),0) -> 0
C89: 27 | E89: 58.823725 | F89: =C89+$F$78-1 -> 29 | L89: =IF(AND(L$6<=$F89,L$6>=$C89),IFERROR(-$E89/$F$78,0),0) -> 0 | M89: =IF(AND(M$6<=$F89,M$6>=$C89),IFERROR(-$E89/$F$78,0),0) -> 0 | N89: =IF(AND(N$6<=$F89,N$6>=$C89),IFERROR(-$E89/$F$78,0),0) -> -19.607908 | O89: =IF(AND(O$6<=$F89,O$6>=$C89),IFERROR(-$E89/$F$78,0),0) -> -19.607908 | P89: =IF(AND(P$6<=$F89,P$6>=$C89),IFERROR(-$E89/$F$78,0),0) -> -19.607908
C90: 28 | E90: 72.955659 | F90: =C90+$F$78-1 -> 30 | L90: =IF(AND(L$6<=$F90,L$6>=$C90),IFERROR(-$E90/$F$78,0),0) -> 0 | M90: =IF(AND(M$6<=$F90,M$6>=$C90),IFERROR(-$E90/$F$78,0),0) -> 0 | N90: =IF(AND(N$6<=$F90,N$6>=$C90),IFERROR(-$E90/$F$78,0),0) -> 0 | O90: =IF(AND(O$6<=$F90,O$6>=$C90),IFERROR(-$E90/$F$78,0),0) -> -24.318553 | P90: =IF(AND(P$6<=$F90,P$6>=$C90),IFERROR(-$E90/$F$78,0),0) -> -24.318553
C91: 29 | E91: 90.530117 | F91: =C91+$F$78-1 -> 31 | L91: =IF(AND(L$6<=$F91,L$6>=$C91),IFERROR(-$E91/$F$78,0),0) -> 0 | M91: =IF(AND(M$6<=$F91,M$6>=$C91),IFERROR(-$E91/$F$78,0),0) -> 0 | N91: =IF(AND(N$6<=$F91,N$6>=$C91),IFERROR(-$E91/$F$78,0),0) -> 0 | O91: =IF(AND(O$6<=$F91,O$6>=$C91),IFERROR(-$E91/$F$78,0),0) -> 0 | P91: =IF(AND(P$6<=$F91,P$6>=$C91),IFERROR(-$E91/$F$78,0),0) -> -30.176706
C92: Total Depreciation | L92: =SUM(L86:L91) -> -79.515462 | M92: =SUM(M86:M91) -> -95.327525 | N92: =SUM(N86:N91) -> -114.93543 | O92: =SUM(O86:O91) -> -59.738524 | P92: =SUM(P86:P91) -> -74.103167

Sheet Projections
C1: =Cover!$C$7&" ("&Cover!$C$8&": "&Cover!$C$9&")" -> Grab Holdings Limited (NASDAQ: GRAB)
C3: 12M Target Price: | F3: =Cover!$C$18 -> 7.2080319
C4: Scenario: | F4: =Cover!$C$11 -> Base Case
G5: Historical (31 Dec) | L5: Forecasted (31 Dec)
C6: ="In "&Cover!$C$10&", unless stated otherwise" -> In USD Mn, unless stated otherwise | F6: Units | G6: 20 | H6: =G6+1 -> 21 | I6: =H6+1 -> 22 | J6: =I6+1 -> 23 | K6: =J6+1 -> 24 | L6: =K6+1 -> 25 | M6: =L6+1 -> 26 | N6: =M6+1 -> 27 | O6: =N6+1 -> 28 | P6: =O6+1 -> 29 | Q6: Notes:
G7: 44196 | H7: =EOMONTH(G7,12) -> 44561 | I7: =EOMONTH(H7,12) -> 44926 | J7: =EOMONTH(I7,12) -> 45291 | K7: =EOMONTH(J7,12) -> 45657 | L7: =EOMONTH(K7,12) -> 46022 | M7: =EOMONTH(L7,12) -> 46387 | N7: =EOMONTH(M7,12) -> 46752 | O7: =EOMONTH(N7,12) -> 47118 | P7: =EOMONTH(O7,12) -> 47483
G8: 366 | H8: 365 | I8: 365 | J8: 365 | K8: 366 | L8: 365 | M8: 365 | N8: 365 | O8: 366 | P8: 365
A10: 1 | C10: Revenue Build
C12: Total Revenue | F12: USD Mns | G12: ='3FS'!D12 -> 469 | H12: ='3FS'!E12 -> 675 | I12: ='3FS'!F12 -> 1433 | J12: ='3FS'!G12 -> 2359 | K12: ='3FS'!H12 -> 2797 | L12: ='3FS'!I12 -> 3447.158 | M12: ='3FS'!J12 -> 4242.1624 | N12: ='3FS'!K12 -> 5260.5364 | ... P12: ='3FS'!M12 -> 8096.0017
C13: %yoy | H13: =(H12-G12)/G12 -> 0.43923241 | I13: =(I12-H12)/H12 -> 1.122963 | J13: =(J12-I12)/I12 -> 0.64619679 | K13: =(K12-J12)/J12 -> 0.18567189 | L13: =(L12-K12)/K12 -> 0.23244832 | M13: =(M12-L12)/L12 -> 0.23062606 | N13: =(N12-M12)/M12 -> 0.24006011 | O13: =(O12-N12)/N12 -> 0.24024207 | P13: =(P12-O12)/O12 -> 0.24089233
A15: 2 | C15: COGS
C17: Cost of Revenues | F17: USD Mns | G17: ='3FS'!D14 -> -963 | H17: ='3FS'!E14 -> -1070 | I17: ='3FS'!F14 -> -1356 | J17: ='3FS'!G14 -> -1499 | K17: ='3FS'!H14 -> -1623 | L17: =L18*L$12 -> -1914.0847 | M17: =M18*M$12 -> -2249.4684 | N17: =N18*N$12 -> -2657.9627 | O17: =O18*O$12 -> -3133.4086 | P17: =P18*P$12 -> -3685.8227
C18: % Revenue | G18: =G17/G$12 -> -2.0533049 | H18: =H17/H$12 -> -1.5851852 | I18: =I17/I$12 -> -0.94626657 | J18: =J17/J$12 -> -0.63543875 | K18: =K17/K$12 -> -0.58026457 | L18: =_xlfn.XLOOKUP($F$4,$C19:$C21,L19:L21) -> -0.55526457 | M18: =_xlfn.XLOOKUP($F$4,$C19:$C21,M19:M21) -> -0.53026457 | N18: =_xlfn.XLOOKUP($F$4,$C19:$C21,N19:N21) -> -0.50526457 | O18: =_xlfn.XLOOKUP($F$4,$C19:$C21,O19:O21) -> -0.48026457 | P18: =_xlfn.XLOOKUP($F$4,$C19:$C21,P19:P21) -> -0.45526457
C19: Bull Case | E19: 0.01 | L19: =L20+$E19 -> -0.54526457 | M19: =M20+$E19 -> -0.52026457 | N19: =N20+$E19 -> -0.49526457 | O19: =O20+$E19 -> -0.47026457 | P19: =P20+$E19 -> -0.44526457
C20: Base Case | E20: -0.025 | L20: =K18-E20 -> -0.55526457 | M20: =L20-$E20 -> -0.53026457 | N20: =M20-$E20 -> -0.50526457 | O20: =N20-$E20 -> -0.48026457 | P20: =O20-$E20 -> -0.45526457
C21: Bear Case | E21: -0.01 | L21: =L20+$E21 -> -0.56526457 | M21: =M20+$E21 -> -0.54026457 | N21: =N20+$E21 -> -0.51526457 | O21: =O20+$E21 -> -0.49026457 | P21: =P20+$E21 -> -0.46526457
A23: 3 | C23: Operating Items
C25: Total Operating Expenses | F25: USD Mns | G25: ='3FS'!D28 -> -804 | H25: ='3FS'!E28 -> -1476 | I25: ='3FS'!F28 -> -1744 | J25: ='3FS'!G28 -> -1418 | K25: ='3FS'!H28 -> -1342 | L25: =SUM(L28,L34,L40,L46,L52,L58,L64,L70,L76) -> -1623.4681 | M25: =SUM(M28,M34,M40,M46,M52,M58,M64,M70,M76) -> -1934.2498 | N25: =SUM(N28,N34,N40,N46,N52,N58,N64,N70,N76) -> -2319.6779 | O25: =SUM(O28,O34,O40,O46,O52,O58,O64,O70,O76) -> -2779.0971 | P25: =SUM(P28,P34,P40,P46,P52,P58,P64,P70,P76) -> -3327.1202
C26: % Revenue | G26: =G25/G12 -> -1.7142857 | H26: =H25/H12 -> -2.1866667 | I26: =I25/I12 -> -1.2170272 | J26: =J25/J12 -> -0.60110216 | K26: =K25/K12 -> -0.47979979 | L26: =L25/L12 -> -0.47095844 | M26: =M25/M12 -> -0.45595844 | N26: =N25/N12 -> -0.44095844 | ... P26: =P25/P12 -> -0.41095844
C28: Sales and Marketing Expenses | F28: USD Mns | G28: ='3FS'!D19 -> -151 | H28: ='3FS'!E19 -> -241 | I28: ='3FS'!F19 -> -278 | J28: ='3FS'!G19 -> -293 | K28: ='3FS'!H19 -> -324 | L28: =L29*L$12 -> -382.07747 | M28: =M29*M$12 -> -448.98368 | N28: =N29*N$12 -> -530.46407 | O28: =O29*O$12 -> -625.28216 | P28: =P29*P$12 -> -735.42782
C29: % Revenue | G29: =G28/G$12 -> -0.32196162 | H29: =H28/H$12 -> -0.35703704 | I29: =I28/I$12 -> -0.1939986 | J29: =J28/J$12 -> -0.12420517 | K29: =K28/K$12 -> -0.1158384 | L29: =_xlfn.XLOOKUP($F$4,$C30:$C32,L30:L32) -> -0.1108384 | M29: =_xlfn.XLOOKUP($F$4,$C30:$C32,M30:M32) -> -0.1058384 | N29: =_xlfn.XLOOKUP($F$4,$C30:$C32,N30:N32) -> -0.1008384 | O29: =_xlfn.XLOOKUP($F$4,$C30:$C32,O30:O32) -> -0.095838398 | P29: =_xlfn.XLOOKUP($F$4,$C30:$C32,P30:P32) -> -0.090838398
C30: Bull Case | E30: 0.01 | L30: =L31+$E30 -> -0.1008384 | M30: =M31+$E30 -> -0.095838398 | N30: =N31+$E30 -> -0.090838398 | O30: =O31+$E30 -> -0.085838398 | P30: =P31+$E30 -> -0.080838398
C31: Base Case | E31: -0.005 | L31: =K29-E31 -> -0.1108384 | M31: =L31-$E31 -> -0.1058384 | N31: =M31-$E31 -> -0.1008384 | O31: =N31-$E31 -> -0.095838398 | P31: =O31-$E31 -> -0.090838398
C32: Bear Case | E32: -0.01 | L32: =L31+$E32 -> -0.1208384 | M32: =M31+$E32 -> -0.1158384 | N32: =N31+$E32 -> -0.1108384 | O32: =O31+$E32 -> -0.1058384 | P32: =P31+$E32 -> -0.1008384
C34: General and Administrative Expenses | F34: USD Mns | G34: ='3FS'!D20 -> -326 | H34: ='3FS'!E20 -> -544 | I34: ='3FS'!F20 -> -646 | J34: ='3FS'!G20 -> -550 | K34: ='3FS'!H20 -> -512 | L34: =(L35*L$12) -> -613.77775 | M34: =(M35*M$12) -> -734.12009 | N34: =(N35*N$12) -> -884.05035 | O34: =(O35*O$12) -> -1063.8147 | P34: =(P35*P$12) -> -1279.5995
C35: % Revenue | G35: =G34/G$12 -> -0.69509595 | H35: =H34/H$12 -> -0.80592593 | I35: =I34/I$12 -> -0.45080251 | J35: =J34/J$12 -> -0.23314964 | K35: =K34/K$12 -> -0.18305327 | L35: =_xlfn.XLOOKUP($F$4,$C36:$C38,L36:L38) -> -0.17805327 | M35: =_xlfn.XLOOKUP($F$4,$C36:$C38,M36:M38) -> -0.17305327 | N35: =_xlfn.XLOOKUP($F$4,$C36:$C38,N36:N38) -> -0.16805327 | O35: =_xlfn.XLOOKUP($F$4,$C36:$C38,O36:O38) -> -0.16305327 | P35: =_xlfn.XLOOKUP($F$4,$C36:$C38,P36:P38) -> -0.15805327
C36: Bull Case | E36: 0.005 | L36: =L37+$E36 -> -0.17305327 | M36: =M37+$E36 -> -0.16805327 | N36: =N37+$E36 -> -0.16305327 | O36: =O37+$E36 -> -0.15805327 | P36: =P37+$E36 -> -0.15305327
C37: Base Case | E37: -0.005 | L37: =K35-E37 -> -0.17805327 | M37: =L37-$E37 -> -0.17305327 | N37: =M37-$E37 -> -0.16805327 | O37: =N37-$E37 -> -0.16305327 | P37: =O37-$E37 -> -0.15805327
C38: Bear Case | E38: -0.005 | L38: =L37+$E38 -> -0.18305327 | M38: =M37+$E38 -> -0.17805327 | N38: =N37+$E38 -> -0.17305327 | O38: =O37+$E38 -> -0.16805327 | P38: =P37+$E38 -> -0.16305327
C40: Research and Development Expenses | F40: USD Mns | G40: ='3FS'!D21 -> -257 | H40: ='3FS'!E21 -> -356 | I40: ='3FS'!F21 -> -465 | J40: ='3FS'!G21 -> -421 | K40: ='3FS'!H21 -> -410 | L40: =L41*L$12 -> -505.30381 | M40: =M41*M$12 -> -600.62923 | N40: =N41*N$12 -> -718.51367 | O40: =O41*O$12 -> -858.50918 | P40: =P41*P$12 -> -1024.8375
C41: % Revenue | G41: =G40/G$12 -> -0.54797441 | H41: =H40/H$12 -> -0.52740741 | I41: =I40/I$12 -> -0.32449407 | J41: =J40/J$12 -> -0.17846545 | K41: =K40/K$12 -> -0.14658563 | L41: =_xlfn.XLOOKUP($F$4,$C42:$C44,L42:L44) -> -0.14658563 | M41: =_xlfn.XLOOKUP($F$4,$C42:$C44,M42:M44) -> -0.14158563 | N41: =_xlfn.XLOOKUP($F$4,$C42:$C44,N42:N44) -> -0.13658563 | O41: =_xlfn.XLOOKUP($F$4,$C42:$C44,O42:O44) -> -0.13158563 | P41: =_xlfn.XLOOKUP($F$4,$C42:$C44,P42:P44) -> -0.12658563
C42: Bull Case | E42: 0.01 | L42: =L43+$E42 -> -0.13658563 | M42: =M43+$E42 -> -0.13158563 | N42: =N43+$E42 -> -0.12658563 | O42: =O43+$E42 -> -0.12158563 | P42: =P43+$E42 -> -0.11658563
C43: Base Case | E43: -0.005 | L43: =K41 -> -0.14658563 | M43: =L43-$E43 -> -0.14158563 | N43: =M43-$E43 -> -0.13658563 | O43: =N43-$E43 -> -0.13158563 | P43: =O43-$E43 -> -0.12658563
C44: Bear Case | E44: -0.01 | L44: =L43+$E44 -> -0.15658563 | M44: =M43+$E44 -> -0.15158563 | N44: =N43+$E44 -> -0.14658563 | O44: =O43+$E44 -> -0.14158563 | P44: =P43+$E44 -> -0.13658563
C46: Other Income | F46: USD Mns | G46: ='3FS'!D22 -> 33 | H46: ='3FS'!E22 -> 12 | I46: ='3FS'!F22 -> 17 | J46: ='3FS'!G22 -> 17 | K46: ='3FS'!H22 -> 17 | L46: =L47*L$12 -> 40.894407 | M46: =M47*M$12 -> 50.325723 | N46: =N47*N$12 -> 62.406922 | O46: =O47*O$12 -> 77.39969 | P46: =P47*P$12 -> 96.044681
C47: % Revenue | G47: =G46/G$12 -> 0.070362473 | H47: =H46/H$12 -> 0.017777778 | I47: =I46/I$12 -> 0.011863224 | J47: =J46/J$12 -> 0.0072064434 | K47: =K46/K$12 -> 0.0060779407 | L47: =_xlfn.XLOOKUP($F$4,$C48:$C50,L48:L50) -> 0.011863224 | M47: =_xlfn.XLOOKUP($F$4,$C48:$C50,M48:M50) -> 0.011863224 | N47: =_xlfn.XLOOKUP($F$4,$C48:$C50,N48:N50) -> 0.011863224 | O47: =_xlfn.XLOOKUP($F$4,$C48:$C50,O48:O50) -> 0.011863224 | P47: =_xlfn.XLOOKUP($F$4,$C48:$C50,P48:P50) -> 0.011863224
C48: Bull Case | E48: 0.005 | L48: =L49+$E48 -> 0.016863224 | M48: =M49+$E48 -> 0.016863224 | N48: =N49+$E48 -> 0.016863224 | O48: =O49+$E48 -> 0.016863224 | P48: =P49+$E48 -> 0.016863224
C49: Base Case | E49: 0 | L49: =MEDIAN($G47:$K47)-$E49 -> 0.011863224 | M49: =L49-$E49 -> 0.011863224 | N49: =M49-$E49 -> 0.011863224 | O49: =N49-$E49 -> 0.011863224 | P49: =O49-$E49 -> 0.011863224
C50: Bear Case | E50: -0.005 | L50: =L49+$E50 -> 0.006863224 | M50: =M49+$E50 -> 0.006863224 | N50: =N49+$E50 -> 0.006863224 | O50: =O49+$E50 -> 0.006863224 | P50: =P49+$E50 -> 0.006863224
C52: Other Expenses | F52: USD Mns | G52: ='3FS'!D23 -> -40 | H52: ='3FS'!E23 -> -11 | I52: ='3FS'!F23 -> -12 | J52: ='3FS'!G23 -> -4 | K52: ='3FS'!H23 -> -4 | L52: =L53*L$12 -> -28.86664 | M52: =M53*M$12 -> -35.52404 | N52: =N53*N$12 -> -44.051945 | O52: =O53*O$12 -> -54.635075 | P52: =P53*P$12 -> -67.796246
C53: % Revenue | G53: =G52/G$12 -> -0.085287846 | H53: =H52/H$12 -> -0.016296296 | I53: =I52/I$12 -> -0.0083740405 | J53: =J52/J$12 -> -0.0016956337 | K53: =K52/K$12 -> -0.0014301037 | L53: =_xlfn.XLOOKUP($F$4,$C54:$C56,L54:L56) -> -0.0083740405 | M53: =_xlfn.XLOOKUP($F$4,$C54:$C56,M54:M56) -> -0.0083740405 | N53: =_xlfn.XLOOKUP($F$4,$C54:$C56,N54:N56) -> -0.0083740405 | O53: =_xlfn.XLOOKUP($F$4,$C54:$C56,O54:O56) -> -0.0083740405 | P53: =_xlfn.XLOOKUP($F$4,$C54:$C56,P54:P56) -> -0.0083740405
C54: Bull Case | E54: 0.005 | L54: =L55+$E54 -> -0.0033740405 | M54: =M55+$E54 -> -0.0033740405 | N54: =N55+$E54 -> -0.0033740405 | O54: =O55+$E54 -> -0.0033740405 | P54: =P55+$E54 -> -0.0033740405
C55: Base Case | E55: 0 | L55: =MEDIAN($G53:$K53)-$E55 -> -0.0083740405 | M55: =L55-$E55 -> -0.0083740405 | N55: =M55-$E55 -> -0.0083740405 | O55: =N55-$E55 -> -0.0083740405 | P55: =O55-$E55 -> -0.0083740405
C56: Bear Case | E56: -0.005 | L56: =L55+$E56 -> -0.01337404 | M56: =M55+$E56 -> -0.01337404 | N56: =N55+$E56 -> -0.01337404 | O56: =O55+$E56 -> -0.01337404 | P56: =P55+$E56 -> -0.01337404
C58: Net Impairment Losses on Financial Assets | F58: USD Mns | G58: ='3FS'!D24 -> -63 | H58: ='3FS'!E24 -> -19 | I58: ='3FS'!F24 -> -58 | J58: ='3FS'!G24 -> -72 | K58: ='3FS'!H24 -> -95 | L58: =L59*L$12 -> -117.08259 | M58: =M59*M$12 -> -144.08489 | N58: =N59*N$12 -> -178.67392 | O58: =O59*O$12 -> -221.59891 | P58: =P59*P$12 -> -274.98039
C59: % Revenue | G59: =G58/G$12 -> -0.13432836 | H59: =H58/H$12 -> -0.028148148 | I59: =I58/I$12 -> -0.040474529 | J59: =J58/J$12 -> -0.030521407 | K59: =K58/K$12 -> -0.033964962 | L59: =_xlfn.XLOOKUP($F$4,$C60:$C62,L60:L62) -> -0.033964962 | M59: =_xlfn.XLOOKUP($F$4,$C60:$C62,M60:M62) -> -0.033964962 | N59: =_xlfn.XLOOKUP($F$4,$C60:$C62,N60:N62) -> -0.033964962 | O59: =_xlfn.XLOOKUP($F$4,$C60:$C62,O60:O62) -> -0.033964962 | P59: =_xlfn.XLOOKUP($F$4,$C60:$C62,P60:P62) -> -0.033964962
C60: Bull Case | E60: 0.01 | L60: =L61+$E60 -> -0.023964962 | M60: =M61+$E60 -> -0.023964962 | N60: =N61+$E60 -> -0.023964962 | O60: =O61+$E60 -> -0.023964962 | P60: =P61+$E60 -> -0.023964962
C61: Base Case | E61: 0 | L61: =MEDIAN($G59:$K59)-$E61 -> -0.033964962 | M61: =L61-$E61 -> -0.033964962 | N61: =M61-$E61 -> -0.033964962 | O61: =N61-$E61 -> -0.033964962 | P61: =O61-$E61 -> -0.033964962
C62: Bear Case | E62: -0.01 | L62: =L61+$E62 -> -0.043964962 | M62: =M61+$E62 -> -0.043964962 | N62: =N61+$E62 -> -0.043964962 | O62: =O61+$E62 -> -0.043964962 | P62: =P61+$E62 -> -0.043964962
C64: Restructuring Costs | F64: USD Mns | G64: ='3FS'!D25 -> 0 | H64: ='3FS'!E25 -> -1 | I64: ='3FS'!F25 -> -8 | J64: ='3FS'!G25 -> -56 | K64: ='3FS'!H25 -> -14 | L64: =L65*L$12 -> -17.254276 | M64: =M65*M$12 -> -21.233562 | N64: =N65*N$12 -> -26.330894 | O64: =O65*O$12 -> -32.656682 | P64: =P65*P$12 -> -40.523426
C65: % Revenue | G65: =G64/G$12 -> 0 | H65: =H64/H$12 -> -0.0014814815 | I65: =I64/I$12 -> -0.0055826936 | J65: =J64/J$12 -> -0.023738872 | K65: =K64/K$12 -> -0.0050053629 | L65: =_xlfn.XLOOKUP($F$4,$C66:$C68,L66:L68) -> -0.0050053629 | M65: =_xlfn.XLOOKUP($F$4,$C66:$C68,M66:M68) -> -0.0050053629 | N65: =_xlfn.XLOOKUP($F$4,$C66:$C68,N66:N68) -> -0.0050053629 | O65: =_xlfn.XLOOKUP($F$4,$C66:$C68,O66:O68) -> -0.0050053629 | P65: =_xlfn.XLOOKUP($F$4,$C66:$C68,P66:P68) -> -0.0050053629
C66: Bull Case | E66: 0 | L66: =L67+$E66 -> -0.0050053629 | M66: =M67+$E66 -> -0.0050053629 | N66: =N67+$E66 -> -0.0050053629 | O66: =O67+$E66 -> -0.0050053629 | P66: =P67+$E66 -> -0.0050053629
C67: Base Case | E67: 0 | L67: =MEDIAN($G65:$K65)-$E67 -> -0.0050053629 | M67: =L67-$E67 -> -0.0050053629 | N67: =M67-$E67 -> -0.0050053629 | O67: =N67-$E67 -> -0.0050053629 | P67: =O67-$E67 -> -0.0050053629
C68: Bear Case | E68: 0 | L68: =L67+$E68 -> -0.0050053629 | M68: =M67+$E68 -> -0.0050053629 | N68: =N67+$E68 -> -0.0050053629 | O68: =O67+$E68 -> -0.0050053629 | P68: =P67+$E68 -> -0.0050053629
C70: Net Change in Fair Value of Financial Assets and Liabilities | F70: USD Mns | G70: ='3FS'!D26 -> 0 | H70: ='3FS'!E26 -> 37 | I70: ='3FS'!F26 -> -294 | J70: ='3FS'!G26 -> -39 | K70: ='3FS'!H26 -> 0 | L70: =L71*L$12 -> 0 | M70: =M71*M$12 -> 0 | N70: =N71*N$12 -> 0 | O70: =O71*O$12 -> 0 | P70: =P71*P$12 -> 0
C71: % Revenue | G71: =G70/G$12 -> 0 | H71: =H70/H$12 -> 0.054814815 | I71: =I70/I$12 -> -0.20516399 | J71: =J70/J$12 -> -0.016532429 | K71: =K70/K$12 -> 0 | L71: =_xlfn.XLOOKUP($F$4,$C72:$C74,L72:L74) -> 0 | M71: =_xlfn.XLOOKUP($F$4,$C72:$C74,M72:M74) -> 0 | N71: =_xlfn.XLOOKUP($F$4,$C72:$C74,N72:N74) -> 0 | O71: =_xlfn.XLOOKUP($F$4,$C72:$C74,O72:O74) -> 0 | P71: =_xlfn.XLOOKUP($F$4,$C72:$C74,P72:P74) -> 0
C72: Bull Case | E72: 0 | L72: =L73+$E72 -> 0 | M72: =M73+$E72 -> 0 | N72: =N73+$E72 -> 0 | O72: =O73+$E72 -> 0 | P72: =P73+$E72 -> 0
C73: Base Case | E73: 0 | L73: =MEDIAN($G71:$K71)-$E73 -> 0 | M73: =L73-$E73 -> 0 | N73: =M73-$E73 -> 0 | O73: =N73-$E73 -> 0 | P73: =O73-$E73 -> 0
C74: Bear Case | E74: 0 | L74: =L73+$E74 -> 0 | M74: =M73+$E74 -> 0 | N74: =N73+$E74 -> 0 | O74: =O73+$E74 -> 0 | P74: =P73+$E74 -> 0
C76: Share Listing and Associated Expenses | F76: USD Mns | G76: ='3FS'!D27 -> 0 | H76: ='3FS'!E27 -> -353 | I76: ='3FS'!F27 -> 0 | J76: ='3FS'!G27 -> 0 | K76: ='3FS'!H27 -> 0 | L76: =L77*L$12 -> 0 | M76: =M77*M$12 -> 0 | N76: =N77*N$12 -> 0 | O76: =O77*O$12 -> 0 | P76: =P77*P$12 -> 0
C77: % Revenue | G77: =G76/G$12 -> 0 | H77: =H76/H$12 -> -0.52296296 | I77: =I76/I$12 -> 0 | J77: =J76/J$12 -> 0 | K77: =K76/K$12 -> 0 | L77: =_xlfn.XLOOKUP($F$4,$C78:$C80,L78:L80) -> 0 | M77: =_xlfn.XLOOKUP($F$4,$C78:$C80,M78:M80) -> 0 | N77: =_xlfn.XLOOKUP($F$4,$C78:$C80,N78:N80) -> 0 | O77: =_xlfn.XLOOKUP($F$4,$C78:$C80,O78:O80) -> 0 | P77: =_xlfn.XLOOKUP($F$4,$C78:$C80,P78:P80) -> 0
C78: Bull Case | E78: 0 | L78: =L79+$E78 -> 0 | M78: =M79+$E78 -> 0 | N78: =N79+$E78 -> 0 | O78: =O79+$E78 -> 0 | P78: =P79+$E78 -> 0
C79: Base Case | E79: 0 | L79: =MEDIAN($G77:$K77)-$E79 -> 0 | M79: =L79-$E79 -> 0 | N79: =M79-$E79 -> 0 | O79: =N79-$E79 -> 0 | P79: =O79-$E79 -> 0
C80: Bear Case | E80: 0 | L80: =L79+$E80 -> 0 | M80: =M79+$E80 -> 0 | N80: =N79+$E80 -> 0 | O80: =O79+$E80 -> 0 | P80: =P79+$E80 -> 0
A82: 4 | C82: Non-Operating Items
C84: Before Tax Items
C86: Non-operating Income/expense | F86: USD Mns | G86: ='3FS'!D32 -> -42 | H86: ='3FS'!E32 -> 0 | I86: ='3FS'!F32 -> 0 | J86: ='3FS'!G32 -> 0 | K86: ='3FS'!H32 -> 0 | L86: =L87*L$12 -> 0 | M86: =M87*M$12 -> 0 | N86: =N87*N$12 -> 0 | O86: =O87*O$12 -> 0 | P86: =P87*P$12 -> 0
C87: % Revenue | G87: =G86/G$12 -> -0.089552239 | H87: =H86/H$12 -> 0 | I87: =I86/I$12 -> 0 | J87: =J86/J$12 -> 0 | K87: =K86/K$12 -> 0 | L87: =MEDIAN(G87:K87) -> 0 | M87: =L87 -> 0 | N87: =M87 -> 0 | O87: =N87 -> 0 | P87: =O87 -> 0
C89: Finance Income | F89: USD Mns | G89: ='3FS'!D34 -> 53 | H89: ='3FS'!E34 -> 28 | I89: ='3FS'!F34 -> 107 | J89: ='3FS'!G34 -> 198 | K89: ='3FS'!H34 -> 187 | L89: =L90*L$12 -> 257.39421 | M89: =M90*M$12 -> 316.75602 | N89: =N90*N$12 -> 392.79651 | O89: =O90*O$12 -> 487.16275 | P89: =P90*P$12 -> 604.51652
C90: % Revenue | G90: =G89/G$12 -> 0.1130064 | H90: =H89/H$12 -> 0.041481481 | I90: =I89/I$12 -> 0.074668528 | J90: =J89/J$12 -> 0.08393387 | K90: =K89/K$12 -> 0.066857347 | L90: =MEDIAN(G90:K90) -> 0.074668528 | M90: =L90 -> 0.074668528 | N90: =M90 -> 0.074668528 | O90: =N90 -> 0.074668528 | P90: =O90 -> 0.074668528
C92: After Tax Items
C94: Earnings Before Taxes | F94: USD Mns | G94: ='3FS'!D35 -> -2735 | H94: ='3FS'!E35 -> -3544 | I94: ='3FS'!F35 -> -1726 | J94: ='3FS'!G35 -> -459 | K94: ='3FS'!H35 -> -87 | L94: ='3FS'!I35 -> 143.15436 | M94: ='3FS'!J35 -> 354.08526 | N94: ='3FS'!K35 -> 654.57733 | ... P94: ='3FS'!M35 -> 1666.6403
C96: Provision for Income Tax | F96: USD Mns | G96: ='3FS'!D36 -> -2 | H96: ='3FS'!E36 -> -3 | I96: ='3FS'!F36 -> -6 | J96: ='3FS'!G36 -> -19 | K96: ='3FS'!H36 -> -63 | L96: =L97*L94 -> 0.49763971 | M96: =M97*M94 -> 1.2308873 | N96: =N97*N94 -> 2.2754716 | O96: =O97*O94 -> 3.7469777 | P96: =P97*P94 -> 5.793651
C97: % Effective Tax Rate | G97: =G96/G94 -> 0.00073126143 | H97: =H96/H94 -> 0.00084650113 | I97: =I96/I94 -> 0.0034762457 | J97: =J96/J94 -> 0.041394336 | K97: =K96/K94 -> 0.72413793 | L97: =MEDIAN(G97:K97) -> 0.0034762457 | M97: =L97 -> 0.0034762457 | N97: =M97 -> 0.0034762457 | O97: =N97 -> 0.0034762457 | P97: =O97 -> 0.0034762457
C99: Share of Loss of Equity Accounted Investee (net of Tax) | F99: USD Mns | G99: ='3FS'!D37 -> -8 | H99: ='3FS'!E37 -> -8 | I99: ='3FS'!F37 -> -8 | J99: ='3FS'!G37 -> -7 | K99: ='3FS'!H37 -> -8 | L99: =L100*L$12 -> -19.244427 | M99: =M100*M$12 -> -23.682693 | N99: =N100*N$12 -> -29.367963 | O99: =O100*O$12 -> -36.423383 | P99: =P100*P$12 -> -45.197497
C100: % Revenue | G100: =G99/G$12 -> -0.017057569 | H100: =H99/H$12 -> -0.011851852 | I100: =I99/I$12 -> -0.0055826936 | J100: =J99/J$12 -> -0.0029673591 | K100: =K99/K$12 -> -0.0028602074 | L100: =MEDIAN(G100:K100) -> -0.0055826936 | M100: =L100 -> -0.0055826936 | N100: =M100 -> -0.0055826936 | O100: =N100 -> -0.0055826936 | P100: =O100 -> -0.0055826936
C102: Minority Interest (After Tax) | F102: USD Mns | G102: ='3FS'!D38 -> 137 | H102: ='3FS'!E38 -> 106 | I102: ='3FS'!F38 -> 57 | J102: ='3FS'!G38 -> 51 | K102: ='3FS'!H38 -> 53 | L102: =L103*L$12 -> 137.11654 | M102: =M103*M$12 -> 168.73919 | N102: =N103*N$12 -> 209.24674 | O102: =O103*O$12 -> 259.51661 | P102: =P103*P$12 -> 322.03217
C103: % Revenue | G103: =G102/G$12 -> 0.29211087 | H103: =H102/H$12 -> 0.15703704 | I103: =I102/I$12 -> 0.039776692 | J103: =J102/J$12 -> 0.02161933 | K103: =K102/K$12 -> 0.018948874 | L103: =MEDIAN(G103:K103) -> 0.039776692 | M103: =L103 -> 0.039776692 | N103: =M103 -> 0.039776692 | O103: =N103 -> 0.039776692 | P103: =O103 -> 0.039776692
A106: 5 | C106: Operating Working Capital Items
A108: x | C108: Current Operating Working Capital Assets
C110: Trade and Other Receivables | F110: USD Mns | G110: ='3FS'!D56 -> 172 | H110: ='3FS'!E56 -> 255 | I110: ='3FS'!F56 -> 187 | J110: ='3FS'!G56 -> 196 | K110: ='3FS'!H56 -> 206 | L110: =L$12/L111 -> 254.57993 | M110: =M$12/M111 -> 313.29269 | N110: =N$12/N111 -> 388.50177 | O110: =O$12/O111 -> 480.51975 | P110: =P$12/P111 -> 597.9069
C111: Receivables Turnover Ratio | G111: =G$12/G110 -> 2.7267442 | H111: =H$12/H110 -> 2.6470588 | I111: =I$12/I110 -> 7.6631016 | J111: =J$12/J110 -> 12.035714 | K111: =K$12/K110 -> 13.57767 | L111: =L$8/L112 -> 13.540572 | M111: =M$8/M112 -> 13.540572 | N111: =N$8/N112 -> 13.540572 | O111: =O$8/O112 -> 13.57767 | P111: =P$8/P112 -> 13.540572
C112: DSO | G112: =G$8/G111 -> 134.22601 | H112: =H$8/H111 -> 137.88889 | I112: =I$8/I111 -> 47.630844 | J112: =J$8/J111 -> 30.326409 | K112: =K$8/K111 -> 26.956024 | L112: =K112 -> 26.956024 | M112: =L112 -> 26.956024 | N112: =M112 -> 26.956024 | O112: =N112 -> 26.956024 | P112: =O112 -> 26.956024
C114: Inventories | F114: USD Mns | G114: ='3FS'!D58 -> 3 | H114: ='3FS'!E58 -> 4 | I114: ='3FS'!F58 -> 48 | J114: ='3FS'!G58 -> 49 | K114: ='3FS'!H58 -> 59 | L114: =L$12/L115 -> 112.68228 | M114: =M$12/M115 -> 138.66975 | N114: =N$12/N115 -> 171.95883 | O114: =O$12/O115 -> 212.68787 | P114: =P$12/P115 -> 264.64582
C115: Inventories Turnover Ratio | G115: =-G17/G114 -> 321 | H115: =-H17/H114 -> 267.5 | I115: =-I17/I114 -> 28.25 | J115: =-J17/J114 -> 30.591837 | K115: =-K17/K114 -> 27.508475 | L115: =L$8/L116 -> 30.591837 | M115: =M$8/M116 -> 30.591837 | N115: =N$8/N116 -> 30.591837 | O115: =O$8/O116 -> 30.67565 | P115: =P$8/P116 -> 30.591837
C116: DIO | G116: =G$8/G115 -> 1.1401869 | H116: =H$8/H115 -> 1.364486 | I116: =I$8/I115 -> 12.920354 | J116: =J$8/J115 -> 11.931288 | K116: =K$8/K115 -> 13.304991 | L116: =MEDIAN(G116:K116) -> 11.931288 | M116: =L116 -> 11.931288 | N116: =M116 -> 11.931288 | O116: =N116 -> 11.931288 | P116: =O116 -> 11.931288
C118: Prepayments and Other Assets | F118: USD Mns | G118: ='3FS'!D59 -> 109 | H118: ='3FS'!E59 -> 185 | I118: ='3FS'!F59 -> 0 | J118: ='3FS'!G59 -> 0 | K118: ='3FS'!H59 -> 0 | L118: =L119*L$12 -> 0 | M118: =M119*M$12 -> 0 | N118: =N119*N$12 -> 0 | O118: =O119*O$12 -> 0 | P118: =P119*P$12 -> 0
C119: % Revenue | G119: =G118/G$12 -> 0.23240938 | H119: =H118/H$12 -> 0.27407407 | I119: =I118/I$12 -> 0 | J119: =J118/J$12 -> 0 | K119: =K118/K$12 -> 0 | L119: =MEDIAN(G119:K119) -> 0 | M119: =L119 -> 0 | N119: =M119 -> 0 | O119: =N119 -> 0 | P119: =O119 -> 0
C121: Deposits Prepayments and Other Assets | F121: USD Mns | G121: ='3FS'!D55 -> 0 | H121: ='3FS'!E55 -> 0 | I121: ='3FS'!F55 -> 182 | J121: ='3FS'!G55 -> 208 | K121: ='3FS'!H55 -> 241 | L121: =L122*L$12 -> 297.02005 | M121: =M122*M$12 -> 365.52061 | N121: =N122*N$12 -> 453.26753 | O121: =O122*O$12 -> 562.16145 | P121: =P122*P$12 -> 697.58184
C122: % Revenue | G122: =G121/G$12 -> 0 | H122: =H121/H$12 -> 0 | I122: =I121/I$12 -> 0.12700628 | J122: =J121/J$12 -> 0.088172955 | K122: =K121/K$12 -> 0.086163747 | L122: =MEDIAN(G122:K122) -> 0.086163747 | M122: =L122 -> 0.086163747 | N122: =M122 -> 0.086163747 | O122: =N122 -> 0.086163747 | P122: =O122 -> 0.086163747
A124: x | C124: Current Operating Working Capital Liabilities
C126: Trade and Other Payables | F126: USD Mns | G126: ='3FS'!D77 -> 661 | H126: ='3FS'!E77 -> 844 | I126: ='3FS'!F77 -> 930 | J126: ='3FS'!G77 -> 925 | K126: ='3FS'!H77 -> 1169 | L126: =L$12/L127 -> 1444.6793 | M126: =M$12/M127 -> 1777.86 | N126: =N$12/N127 -> 2204.6533 | O126: =O$12/O127 -> 2726.8329 | P126: =P$12/P127 -> 3392.9765
C127: Payables Turnover Ratio | G127: =G$12/G126 -> 0.70953101 | H127: =H$12/H126 -> 0.79976303 | I127: =I$12/I126 -> 1.5408602 | J127: =J$12/J126 -> 2.5502703 | K127: =K$12/K126 -> 2.3926433 | L127: =L$8/L128 -> 2.386106 | M127: =M$8/M128 -> 2.386106 | N127: =N$8/N128 -> 2.386106 | O127: =O$8/O128 -> 2.3926433 | P127: =P$8/P128 -> 2.386106
C128: DSO | G128: =G$8/G127 -> 515.83369 | H128: =H$8/H127 -> 456.38519 | I128: =I$8/I127 -> 236.88067 | J128: =J$8/J127 -> 143.12209 | K128: =K$8/K127 -> 152.9689 | L128: =K128 -> 152.9689 | M128: =L128 -> 152.9689 | N128: =M128 -> 152.9689 | O128: =N128 -> 152.9689 | P128: =O128 -> 152.9689
C130: Provisions | F130: USD Mns | G130: ='3FS'!D80 -> 35 | H130: ='3FS'!E80 -> 35 | I130: ='3FS'!F80 -> 38 | J130: ='3FS'!G80 -> 39 | K130: ='3FS'!H80 -> 41 | L130: =L131*L$12 -> 91.411027 | M130: =M131*M$12 -> 112.49279 | N130: =N131*N$12 -> 139.49783 | O130: =O131*O$12 -> 173.01107 | P130: =P131*P$12 -> 214.68811
C131: % Revenue | G131: =G130/G$12 -> 0.074626866 | H131: =H130/H$12 -> 0.051851852 | I131: =I130/I$12 -> 0.026517795 | J131: =J130/J$12 -> 0.016532429 | K131: =K130/K$12 -> 0.014658563 | L131: =MEDIAN(G131:K131) -> 0.026517795 | M131: =L131 -> 0.026517795 | N131: =M131 -> 0.026517795 | O131: =N131 -> 0.026517795 | P131: =O131 -> 0.026517795
C133: Deposits from Customers in the Banking Business | F133: USD Mns | G133: ='3FS'!D81 -> 0 | H133: ='3FS'!E81 -> 0 | I133: ='3FS'!F81 -> 3 | J133: ='3FS'!G81 -> 374 | K133: ='3FS'!H81 -> 1225 | L133: =L134*L$12 -> 7.2166601 | M133: =M134*M$12 -> 8.88101 | N133: =N134*N$12 -> 11.012986 | O133: =O134*O$12 -> 13.658769 | P133: =P134*P$12 -> 16.949061
C134: % Revenue | G134: =G133/G$12 -> 0 | H134: =H133/H$12 -> 0 | I134: =I133/I$12 -> 0.0020935101 | J134: =J133/J$12 -> 0.15854175 | K134: =K133/K$12 -> 0.43796925 | L134: =MEDIAN(G134:K134) -> 0.0020935101 | M134: =L134 -> 0.0020935101 | N134: =M134 -> 0.0020935101 | O134: =N134 -> 0.0020935101 | P134: =O134 -> 0.0020935101
A136: 6 | C136: Other Balance Sheet Items
C138: Cash and Equivalents | F138: USD Mns | G138: ='3FS'!D53 -> 2173 | H138: ='3FS'!E53 -> 4991 | I138: ='3FS'!F53 -> 1952 | J138: ='3FS'!G53 -> 3138 | K138: ='3FS'!H53 -> 2964 | L138: ='3FS'!I53 -> 3387.2668 | M138: ='3FS'!J53 -> 3227.6697 | N138: ='3FS'!K53 -> 3232.7186 | ... P138: ='3FS'!M53 -> 2397.5071
...

Sheet PPE
C1: =Cover!$C$7&" ("&Cover!$C$8&": "&Cover!$C$9&")" -> Grab Holdings Limited (NASDAQ: GRAB)
C3: 12M Target Price: | F3: =Cover!$C$18 -> 7.2080319
C4: Scenario: | F4: =Cover!$C$11 -> Base Case
G5: Historical (31 Dec) | L5: Forecasted (31 Dec)
C6: ="In "&Cover!$C$10&", unless stated otherwise" -> In USD Mn, unless stated otherwise | F6: Units | G6: 20 | H6: =G6+1 -> 21 | I6: =H6+1 -> 22 | J6: =I6+1 -> 23 | K6: =J6+1 -> 24 | L6: =K6+1 -> 25 | M6: =L6+1 -> 26 | N6: =M6+1 -> 27 | O6: =N6+1 -> 28 | P6: =O6+1 -> 29 | Q6: Notes:
A10: 1 | C10: PPE
C12: Property, Plant & Equipment | G12: ='3FS'!D63 -> 384 | H12: ='3FS'!E63 -> 441 | I12: ='3FS'!F63 -> 492 | J12: ='3FS'!G63 -> 512 | K12: ='3FS'!H63 -> 567 | L12: =L26+K12+L88 -> 553.56588 | M12: =M26+L12+M88 -> 547.11344 | N12: =N26+M12+N88 -> 550.96528 | O12: =O26+N12+O88 -> 586.09443 | P12: =P26+O12+P88 -> 703.86684
C13: %yoy | H13: =H12/G12-1 -> 0.1484375 | I13: =I12/H12-1 -> 0.11564626 | J13: =J12/I12-1 -> 0.040650407 | K13: =K12/J12-1 -> 0.10742188 | L13: =L12/K12-1 -> -0.023693327 | M13: =M12/L12-1 -> -0.011656136 | N13: =N12/M12-1 -> 0.0070402809 | O13: =O12/N12-1 -> 0.063759288 | P13: =P12/O12-1 -> 0.20094443
A15: x | C15: Assumptions
C17: Useful Life : | D17: Min | E17: Max | F17: Average
C18: Computers | D18: 2 | E18: 3 | F18: =ROUNDUP(AVERAGE(D18:E18),0) -> 3
C19: Building and Renovation | D19: 3 | E19: 5 | F19: =ROUNDUP(AVERAGE(D19:E19),0) -> 4
C20: Motor Vehicles | D20: 5 | E20: 7 | F20: =ROUNDUP(AVERAGE(D20:E20),0) -> 6
C21: Office and Other Equipment | D21: 4 | E21: 5 | F21: =ROUNDUP(AVERAGE(D21:E21),0) -> 5
C23: Revenue | G23: ='3FS'!D12 -> 469 | H23: ='3FS'!E12 -> 675 | I23: ='3FS'!F12 -> 1433 | J23: ='3FS'!G12 -> 2359 | K23: ='3FS'!H12 -> 2797 | L23: ='3FS'!I12 -> 3447.158 | M23: ='3FS'!J12 -> 4242.1624 | N23: ='3FS'!K12 -> 5260.5364 | ... P23: ='3FS'!M12 -> 8096.0017
C24: %yoy | H24: =H23/G23-1 -> 0.43923241 | I24: =I23/H23-1 -> 1.122963 | J24: =J23/I23-1 -> 0.64619679 | K24: =K23/J23-1 -> 0.18567189 | L24: =L23/K23-1 -> 0.23244832 | M24: =M23/L23-1 -> 0.23062606 | N24: =N23/M23-1 -> 0.24006011 | O24: =O23/N23-1 -> 0.24024207 | P24: =P23/O23-1 -> 0.24089233
C26: PPE CapEx | G26: =-'3FS'!D134 -> 22 | H26: =-'3FS'!E134 -> 73 | I26: =-'3FS'!F134 -> 58 | J26: =-'3FS'!G134 -> 71 | K26: =-'3FS'!H134 -> 77 | L26: =L23*L27 -> 174.53511 | M26: =M23*M27 -> 214.78746 | N26: =N23*N27 -> 266.34936 | O26: =O23*O27 -> 330.33768 | P26: =P23*P27 -> 409.9135
C27: % Revenue | G27: =G26/G23 -> 0.046908316 | H27: =H26/H23 -> 0.10814815 | I27: =I26/I23 -> 0.040474529 | J27: =J26/J23 -> 0.030097499 | K27: =K26/K23 -> 0.027529496 | L27: =AVERAGE(G27:K27) -> 0.050631598 | M27: =L27+$R$27 -> 0.050631598 | N27: =M27+$R$27 -> 0.050631598 | O27: =N27+$R$27 -> 0.050631598 | P27: =O27+$R$27 -> 0.050631598
A29: x | C29: Capex Schedule and Allocation
C31: Gross PPE amount:
C32: Computers | G32: 47.2 | H32: 52.8 | I32: 66.2 | J32: 67.2 | K32: 67.6 | L32: =K32+L39 -> 77.792649 | M32: =L32+M39 -> 90.335988 | N32: =M32+N39 -> 105.89048 | O32: =N32+O39 -> 125.18182 | P32: =O32+P39 -> 149.1203
C33: Building and Renovation | G33: 121.8 | H33: 194.3 | I33: 237.7 | J33: 255.9 | K33: 270.2 | L33: =K33+L40 -> 317.8903 | M33: =L33+M40 -> 376.57923 | N33: =M33+N40 -> 449.35703 | O33: =N33+O40 -> 539.61912 | P33: =O33+P40 -> 651.62465
C34: Motor Vehicles | G34: 459 | H34: 400.6 | I34: 411.7 | J34: 510.1 | K34: 580.8 | L34: =K34+L41 -> 676.22673 | M34: =L34+M41 -> 793.66134 | N34: =M34+N41 -> 939.28732 | O34: =N34+O41 -> 1119.8988 | P34: =O34+P41 -> 1344.0182
C35: Office and Other Equipment | G35: 34 | H35: 33.2 | I35: 47.4 | J35: 57.7 | K35: 68.4 | L35: =K35+L42 -> 89.625438 | M35: =L35+M42 -> 115.74601 | N35: =M35+N42 -> 148.1371 | O35: =N35+O42 -> 188.30989 | P35: =O35+P42 -> 238.15999
C36: PPE, gross | G36: =SUM(G32:G35) -> 662 | H36: =SUM(H32:H35) -> 680.9 | I36: =SUM(I32:I35) -> 763 | J36: =SUM(J32:J35) -> 890.9 | K36: =SUM(K32:K35) -> 987 | L36: =SUM(L32:L35) -> 1161.5351 | M36: =SUM(M32:M35) -> 1376.3226 | N36: =SUM(N32:N35) -> 1642.6719 | ... P36: =SUM(P32:P35) -> 2382.9231
C38: PPE NET ADDITIONS:
C39: Computers | H39: =H32-G32 -> 5.6 | I39: =I32-H32 -> 13.4 | J39: =J32-I32 -> 1 | K39: =K32-J32 -> 0.4 | L39: =ABS(L46*L$26) -> 10.192649 | M39: =ABS(M46*M$26) -> 12.543339 | N39: =ABS(N46*N$26) -> 15.554495 | O39: =ABS(O46*O$26) -> 19.291339 | P39: =ABS(P46*P$26) -> 23.938474
C40: Building and Renovation | H40: =H33-G33 -> 72.5 | I40: =I33-H33 -> 43.4 | J40: =J33-I33 -> 18.2 | K40: =K33-J33 -> 14.3 | L40: =ABS(L47*L$26) -> 47.690302 | M40: =ABS(M47*M$26) -> 58.688929 | N40: =ABS(N47*N$26) -> 72.7778 | O40: =ABS(O47*O$26) -> 90.262089 | P40: =ABS(P47*P$26) -> 112.00553
C41: Motor Vehicles | H41: =H34-G34 -> -58.4 | I41: =I34-H34 -> 11.1 | J41: =J34-I34 -> 98.4 | K41: =K34-J34 -> 70.7 | L41: =ABS(L48*L$26) -> 95.426726 | M41: =ABS(M48*M$26) -> 117.43462 | N41: =ABS(N48*N$26) -> 145.62598 | O41: =ABS(O48*O$26) -> 180.61147 | P41: =ABS(P48*P$26) -> 224.11939
C42: Office and Other Equipment | H42: =H35-G35 -> -0.8 | I42: =I35-H35 -> 14.2 | J42: =J35-I35 -> 10.3 | K42: =K35-J35 -> 10.7 | L42: =ABS(L49*L$26) -> 21.225438 | M42: =ABS(M49*M$26) -> 26.120577 | N42: =ABS(N49*N$26) -> 32.391085 | O42: =ABS(O49*O$26) -> 40.172787 | P42: =ABS(P49*P$26) -> 49.850103
C43: Total Net Additions | H43: =SUM(H39:H42) -> 18.9 | I43: =SUM(I39:I42) -> 82.1 | J43: =SUM(J39:J42) -> 127.9 | K43: =SUM(K39:K42) -> 96.1 | L43: =SUM(L39:L42) -> 174.53511 | M43: =SUM(M39:M42) -> 214.78746 | N43: =SUM(N39:N42) -> 266.34936 | O43: =SUM(O39:O42) -> 330.33768 | P43: =SUM(P39:P42) -> 409.9135
C45: Capex Allocation (%net additions)
C46: Computers | H46: =H39/H$43 -> 0.2962963 | I46: =I39/I$43 -> 0.16321559 | J46: =J39/J$43 -> 0.0078186083 | K46: =K39/K$43 -> 0.0041623309 | L46: =AVERAGE(I46:K46) -> 0.058398843 | M46: =L46 -> 0.058398843 | N46: =M46 -> 0.058398843 | O46: =N46 -> 0.058398843 | P46: =O46 -> 0.058398843
C47: Building and Renovation | H47: =H40/H$43 -> 3.8359788 | I47: =I40/I$43 -> 0.52862363 | J47: =J40/J$43 -> 0.14229867 | K47: =K40/K$43 -> 0.14880333 | L47: =AVERAGE(I47:K47) -> 0.27324188 | M47: =L47 -> 0.27324188 | N47: =M47 -> 0.27324188 | O47: =N47 -> 0.27324188 | P47: =O47 -> 0.27324188
C48: Motor Vehicles | H48: =H41/H$43 -> -3.0899471 | I48: =I41/I$43 -> 0.13520097 | J48: =J41/J$43 -> 0.76935106 | K48: =K41/K$43 -> 0.73569199 | L48: =AVERAGE(I48:K48) -> 0.54674801 | M48: =L48 -> 0.54674801 | N48: =M48 -> 0.54674801 | O48: =N48 -> 0.54674801 | P48: =O48 -> 0.54674801
C49: Office and Other Equipment | H49: =H42/H$43 -> -0.042328042 | I49: =I42/I$43 -> 0.17295981 | J49: =J42/J$43 -> 0.080531665 | K49: =K42/K$43 -> 0.11134235 | L49: =AVERAGE(I49:K49) -> 0.12161127 | M49: =L49 -> 0.12161127 | N49: =M49 -> 0.12161127 | O49: =N49 -> 0.12161127 | P49: =O49 -> 0.12161127
C50: Total(%) | H50: =SUM(H46:H49) -> 1 | I50: =SUM(I46:I49) -> 1 | J50: =SUM(J46:J49) -> 1 | K50: =SUM(K46:K49) -> 1 | L50: =SUM(L46:L49) -> 1 | M50: =SUM(M46:M49) -> 1 | N50: =SUM(N46:N49) -> 1 | O50: =SUM(O46:O49) -> 1 | P50: =SUM(P46:P49) -> 1
A52: x | C52: Residual Value Calculation
C54: Gross PPE amount:
C55: Computers | G55: 47.2 | H55: 52.8 | I55: 66.2 | J55: 67.2 | K55: 67.6 | L55: =K55+L39 -> 77.792649 | M55: =L55+M39 -> 90.335988 | N55: =M55+N39 -> 105.89048 | O55: =N55+O39 -> 125.18182 | P55: =O55+P39 -> 149.1203
C56: Building and Renovation | G56: 121.8 | H56: 194.3 | I56: 237.7 | J56: 255.9 | K56: 270.2 | L56: =K56+L40 -> 317.8903 | M56: =L56+M40 -> 376.57923 | N56: =M56+N40 -> 449.35703 | O56: =N56+O40 -> 539.61912 | P56: =O56+P40 -> 651.62465
C57: Motor Vehicles | G57: 459 | H57: 400.6 | I57: 411.7 | J57: 510.1 | K57: 580.8 | L57: =K57+L41 -> 676.22673 | M57: =L57+M41 -> 793.66134 | N57: =M57+N41 -> 939.28732 | O57: =N57+O41 -> 1119.8988 | P57: =O57+P41 -> 1344.0182
C58: Office and Other Equipment | G58: 34 | H58: 33.2 | I58: 47.4 | J58: 57.7 | K58: 68.4 | L58: =K58+L42 -> 89.625438 | M58: =L58+M42 -> 115.74601 | N58: =M58+N42 -> 148.1371 | O58: =N58+O42 -> 188.30989 | P58: =O58+P42 -> 238.15999
C59: PPE, gross | G59: =SUM(G55:G58) -> 662 | H59: =SUM(H55:H58) -> 680.9 | I59: =SUM(I55:I58) -> 763 | J59: =SUM(J55:J58) -> 890.9 | K59: =SUM(K55:K58) -> 987 | L59: =SUM(L55:L58) -> 1161.5351 | M59: =SUM(M55:M58) -> 1376.3226 | N59: =SUM(N55:N58) -> 1642.6719 | ... P59: =SUM(P55:P58) -> 2382.9231
C61: Depreciation Amount:
C62: Computers | G62: 15 | H62: 16 | I62: 13 | J62: 12 | K62: 12
C63: Building and Renovation | G63: 39 | H63: 34 | I63: 48 | J63: 42 | K63: 44
C64: Motor Vehicles | G64: 65 | H64: 53 | I64: 58 | J64: 65 | K64: 57
C65: Office and Other Equipment | G65: 7 | H65: 6 | I65: 10 | J65: 9 | K65: 9
C67: Total Depreciation Over Useful Life: | D67: Average
C68: Computers | D68: =ROUNDUP(AVERAGE($D18:$E18),0) -> 3 | G68: =G62*$D68 -> 45 | H68: =H62*$D68 -> 48 | I68: =I62*$D68 -> 39 | J68: =J62*$D68 -> 36 | K68: =K62*$D68 -> 36
C69: Building and Renovation | D69: =ROUNDUP(AVERAGE($D19:$E19),0) -> 4 | G69: =G63*$D69 -> 156 | H69: =H63*$D69 -> 136 | I69: =I63*$D69 -> 192 | J69: =J63*$D69 -> 168 | K69: =K63*$D69 -> 176
C70: Motor Vehicles | D70: =ROUNDUP(AVERAGE($D20:$E20),0) -> 6 | G70: =G64*$D70 -> 390 | H70: =H64*$D70 -> 318 | I70: =I64*$D70 -> 348 | J70: =J64*$D70 -> 390 | K70: =K64*$D70 -> 342
C71: Office and Other Equipment | D71: =ROUNDUP(AVERAGE($D21:$E21),0) -> 5 | G71: =G65*$D71 -> 35 | H71: =H65*$D71 -> 30 | I71: =I65*$D71 -> 50 | J71: =J65*$D71 -> 45 | K71: =K65*$D71 -> 45
C73: Estimated Salvage Value:
C74: Computers | G74: =G55-G68 -> 2.2 | H74: =H55-H68 -> 4.8 | I74: =I55-I68 -> 27.2 | J74: =J55-J68 -> 31.2 | K74: =K55-K68 -> 31.6 | L74: =AVERAGE(G74:K74) -> 19.4 | M74: =L74 -> 19.4 | N74: =M74 -> 19.4 | O74: =N74 -> 19.4 | P74: =O74 -> 19.4
C75: Building and Renovation | G75: =G56-G69 -> -34.2 | H75: =H56-H69 -> 58.3 | I75: =I56-I69 -> 45.7 | J75: =J56-J69 -> 87.9 | K75: =K56-K69 -> 94.2 | L75: =AVERAGE(G75:K75) -> 50.38 | M75: =L75 -> 50.38 | N75: =M75 -> 50.38 | O75: =N75 -> 50.38 | P75: =O75 -> 50.38
C76: Motor Vehicles | G76: =G57-G70 -> 69 | H76: =H57-H70 -> 82.6 | I76: =I57-I70 -> 63.7 | J76: =J57-J70 -> 120.1 | K76: =K57-K70 -> 238.8 | L76: =AVERAGE(G76:K76) -> 114.84 | M76: =L76 -> 114.84 | N76: =M76 -> 114.84 | O76: =N76 -> 114.84 | P76: =O76 -> 114.84
C77: Office and Other Equipment | G77: =G58-G71 -> -1 | H77: =H58-H71 -> 3.2 | I77: =I58-I71 -> -2.6 | J77: =J58-J71 -> 12.7 | K77: =K58-K71 -> 23.4 | L77: =AVERAGE(G77:K77) -> 7.14 | M77: =L77 -> 7.14 | N77: =M77 -> 7.14 | O77: =N77 -> 7.14 | P77: =O77 -> 7.14
C79: % of Gross PPE, BOP:
C80: Computers | G80: =G74/G55 -> 0.046610169 | H80: =H74/H55 -> 0.090909091 | I80: =I74/I55 -> 0.41087613 | J80: =J74/J55 -> 0.46428571 | K80: =K74/K55 -> 0.46745562 | L80: =AVERAGE(G80:K80) -> 0.29602735 | M80: =L80 -> 0.29602735 | N80: =M80 -> 0.29602735 | O80: =N80 -> 0.29602735 | P80: =O80 -> 0.29602735
C81: Building and Renovation | G81: =G75/G56 -> -0.28078818 | H81: =H75/H56 -> 0.30005147 | I81: =I75/I56 -> 0.19225915 | J81: =J75/J56 -> 0.34349355 | K81: =K75/K56 -> 0.34863064 | L81: =AVERAGE(G81:K81) -> 0.18072933 | M81: =L81 -> 0.18072933 | N81: =M81 -> 0.18072933 | O81: =N81 -> 0.18072933 | P81: =O81 -> 0.18072933
C82: Motor Vehicles | G82: =G76/G57 -> 0.1503268 | H82: =H76/H57 -> 0.20619071 | I82: =I76/I57 -> 0.15472431 | J82: =J76/J57 -> 0.23544403 | K82: =K76/K57 -> 0.41115702 | L82: =AVERAGE(G82:K82) -> 0.23156858 | M82: =L82 -> 0.23156858 | N82: =M82 -> 0.23156858 | O82: =N82 -> 0.23156858 | P82: =O82 -> 0.23156858
C83: Office and Other Equipment | G83: =G77/G58 -> -0.029411765 | H83: =H77/H58 -> 0.096385542 | I83: =I77/I58 -> -0.054852321 | J83: =J77/J58 -> 0.22010399 | K83: =K77/K58 -> 0.34210526 | L83: =AVERAGE(G83:K83) -> 0.11486614 | M83: =L83 -> 0.11486614 | N83: =M83 -> 0.11486614 | O83: =N83 -> 0.11486614 | P83: =O83 -> 0.11486614
A85: x | C85: Depreciation Schedules
C86: ACCUMULATED DEPRECIATION:
C87: Beginning Accumulated Depreciation | L87: =K89 -> -558 | M87: =L89 -> -745.96923 | N87: =M89 -> -967.20913 | O87: =N89 -> -1229.7067 | P87: =O89 -> -1524.9152
C88: (+) Depreciation | L88: =SUM(L97,L120,L143,L166) -> -187.96923 | M88: =SUM(M97,M120,M143,M166) -> -221.2399 | N88: =SUM(N97,N120,N143,N166) -> -262.49753 | O88: =SUM(O97,O120,O143,O166) -> -295.20853 | P88: =SUM(P97,P120,P143,P166) -> -292.14109
C89: Ending Accumulated Depreciation | K89: -558 | L89: =SUM(L87:L88) -> -745.96923 | M89: =SUM(M87:M88) -> -967.20913 | N89: =SUM(N87:N88) -> -1229.7067 | O89: =SUM(O87:O88) -> -1524.9152 | P89: =SUM(P87:P88) -> -1817.0563
A91: x | C91: =C18 -> Computers
C93: Useful Life | F93: =F18 -> 3
C95: Beginning Balance | L95: =K32 -> 67.6 | M95: =L98 -> 59.3342 | N95: =M98 -> 50.475701 | O95: =N98 -> 40.978378 | P95: =O98 -> 49.14949
C96: (+) Additions | L96: =L39 -> 10.192649 | M96: =M39 -> 12.543339 | N96: =N39 -> 15.554495 | O96: =O39 -> 19.291339 | P96: =P39 -> 23.938474
C97: (-) Depreciation | L97: =L112 -> -18.458449 | M97: =M112 -> -21.401838 | N97: =N112 -> -25.051818 | O97: =O112 -> -11.120227 | P97: =P112 -> -13.794182
C98: Ending Balance, net | L98: =SUM(L95:L97) -> 59.3342 | M98: =SUM(M95:M97) -> 50.475701 | N98: =SUM(N95:N97) -> 40.978378 | O98: =SUM(O95:O97) -> 49.14949 | P98: =SUM(P95:P97) -> 59.293782
C100: % Gross PPE, BOP
C101: Additions | L101: =L39 -> 10.192649 | M101: =M39 -> 12.543339 | N101: =N39 -> 15.554495 | O101: =O39 -> 19.291339 | P101: =P39 -> 23.938474
C102: (-) Salvage Value | L102: =-L101*L80 -> -3.0173028 | M102: =-M101*M80 -> -3.7131714 | N102: =-N101*N80 -> -4.6045558 | O102: =-O101*O80 -> -5.7107638 | P102: =-P101*P80 -> -7.086443
C103: Depreciable Amount | L103: =SUM(L101:L102) -> 7.175346 | M103: =SUM(M101:M102) -> 8.8301678 | N103: =SUM(N101:N102) -> 10.949939 | O103: =SUM(O101:O102) -> 13.580575 | P103: =SUM(P101:P102) -> 16.852031
C105: Beginning Year | E105: Amount | F105: Final Year
C106: =[2]Projections!$L$7 -> 25 | E106: =L95-L74 -> 48.2 | F106: =C106+$F$93-1 -> 27 | L106: =IF(AND(L$6<=$F106,L$6>=$C106),IFERROR(-$E106/$F$93,0),0) -> -16.066667 | M106: =IF(AND(M$6<=$F106,M$6>=$C106),IFERROR(-$E106/$F$93,0),0) -> -16.066667 | N106: =IF(AND(N$6<=$F106,N$6>=$C106),IFERROR(-$E106/$F$93,0),0) -> -16.066667 | O106: =IF(AND(O$6<=$F106,O$6>=$C106),IFERROR(-$E106/$F$93,0),0) -> 0 | P106: =IF(AND(P$6<=$F106,P$6>=$C106),IFERROR(-$E106/$F$93,0),0) -> 0
C107: {=TRANSPOSE([2]Projections!$L$7:$P$7)} -> 25 | E107: {=TRANSPOSE(L103:P103)} -> 7.175346 | F107: =C107+$F$93-1 -> 27 | L107: =IF(AND(L$6<=$F107,L$6>=$C107),IFERROR(-$E107/$F$93,0),0) -> -2.391782 | M107: =IF(AND(M$6<=$F107,M$6>=$C107),IFERROR(-$E107/$F$93,0),0) -> -2.391782 | N107: =IF(AND(N$6<=$F107,N$6>=$C107),IFERROR(-$E107/$F$93,0),0) -> -2.391782 | O107: =IF(AND(O$6<=$F107,O$6>=$C107),IFERROR(-$E107/$F$93,0),0) -> 0 | P107: =IF(AND(P$6<=$F107,P$6>=$C107),IFERROR(-$E107/$F$93,0),0) -> 0
C108: 26 | E108: 8.8301678 | F108: =C108+$F$93-1 -> 28 | L108: =IF(AND(L$6<=$F108,L$6>=$C108),IFERROR(-$E108/$F$93,0),0) -> 0 | M108: =IF(AND(M$6<=$F108,M$6>=$C108),IFERROR(-$E108/$F$93,0),0) -> -2.9433893 | N108: =IF(AND(N$6<=$F108,N$6>=$C108),IFERROR(-$E108/$F$93,0),0) -> -2.9433893 | O108: =IF(AND(O$6<=$F108,O$6>=$C108),IFERROR(-$E108/$F$93,0),0) -> -2.9433893 | P108: =IF(AND(P$6<=$F108,P$6>=$C108),IFERROR(-$E108/$F$93,0),0) -> 0
C109: 27 | E109: 10.949939 | F109: =C109+$F$93-1 -> 29 | L109: =IF(AND(L$6<=$F109,L$6>=$C109),IFERROR(-$E109/$F$93,0),0) -> 0 | M109: =IF(AND(M$6<=$F109,M$6>=$C109),IFERROR(-$E109/$F$93,0),0) -> 0 | N109: =IF(AND(N$6<=$F109,N$6>=$C109),IFERROR(-$E109/$F$93,0),0) -> -3.6499796 | O109: =IF(AND(O$6<=$F109,O$6>=$C109),IFERROR(-$E109/$F$93,0),0) -> -3.6499796 | P109: =IF(AND(P$6<=$F109,P$6>=$C109),IFERROR(-$E109/$F$93,0),0) -> -3.6499796
C110: 28 | E110: 13.580575 | F110: =C110+$F$93-1 -> 30 | L110: =IF(AND(L$6<=$F110,L$6>=$C110),IFERROR(-$E110/$F$93,0),0) -> 0 | M110: =IF(AND(M$6<=$F110,M$6>=$C110),IFERROR(-$E110/$F$93,0),0) -> 0 | N110: =IF(AND(N$6<=$F110,N$6>=$C110),IFERROR(-$E110/$F$93,0),0) -> 0 | O110: =IF(AND(O$6<=$F110,O$6>=$C110),IFERROR(-$E110/$F$93,0),0) -> -4.5268583 | P110: =IF(AND(P$6<=$F110,P$6>=$C110),IFERROR(-$E110/$F$93,0),0) -> -4.5268583
C111: 29 | E111: 16.852031 | F111: =C111+$F$93-1 -> 31 | L111: =IF(AND(L$6<=$F111,L$6>=$C111),IFERROR(-$E111/$F$93,0),0) -> 0 | M111: =IF(AND(M$6<=$F111,M$6>=$C111),IFERROR(-$E111/$F$93,0),0) -> 0 | N111: =IF(AND(N$6<=$F111,N$6>=$C111),IFERROR(-$E111/$F$93,0),0) -> 0 | O111: =IF(AND(O$6<=$F111,O$6>=$C111),IFERROR(-$E111/$F$93,0),0) -> 0 | P111: =IF(AND(P$6<=$F111,P$6>=$C111),IFERROR(-$E111/$F$93,0),0) -> -5.6173437
C112: Total Depreciation | L112: =SUM(L106:L111) -> -18.458449 | M112: =SUM(M106:M111) -> -21.401838 | N112: =SUM(N106:N111) -> -25.051818 | O112: =SUM(O106:O111) -> -11.120227 | P112: =SUM(P106:P111) -> -13.794182
A114: x | C114: =C19 -> Building and Renovation
C116: Useful Life | F116: =F19 -> 4
C118: Beginning Balance | L118: =K33 -> 270.2 | M118: =L121 -> 254.27047 | N118: =M121 -> 238.67641 | O118: =N121 -> 223.94825 | P118: =O121 -> 210.30471
C119: (+) Additions | L119: =L40 -> 47.690302 | M119: =M40 -> 58.688929 | N119: =N40 -> 72.7778 | O119: =O40 -> 90.262089 | P119: =P40 -> 112.00553
C120: (-) Depreciation | L120: =L135 -> -63.619829 | M120: =M135 -> -74.282993 | N120: =N135 -> -87.505957 | O120: =O135 -> -103.90563 | P120: =P135 -> -60.636038
C121: Ending Balance, net | L121: =SUM(L118:L120) -> 254.27047 | M121: =SUM(M118:M120) -> 238.67641 | N121: =SUM(N118:N120) -> 223.94825 | O121: =SUM(O118:O120) -> 210.30471 | P121: =SUM(P118:P120) -> 261.6742
C123: % Gross PPE, BOP
C124: Additions | L124: =L40 -> 47.690302 | M124: =M40 -> 58.688929 | N124: =N40 -> 72.7778 | O124: =O40 -> 90.262089 | P124: =P40 -> 112.00553
C125: (-) Salvage Value | L125: =-L124*L47 -> -13.030988 | M125: =-M124*M47 -> -16.036273 | N125: =-N124*N47 -> -19.885943 | O125: =-O124*O47 -> -24.663382 | P125: =-P124*P47 -> -30.604602
C126: Depreciable Amount | L126: =SUM(L124:L125) -> 34.659314 | M126: =SUM(M124:M125) -> 42.652656 | N126: =SUM(N124:N125) -> 52.891857 | O126: =SUM(O124:O125) -> 65.598706 | P126: =SUM(P124:P125) -> 81.400931
C128: Beginning Year | E128: Amount | F128: Final Year
C129: =[2]Projections!$L$7 -> 25 | E129: =L118-L75 -> 219.82 | F129: =C129+$F$116-1 -> 28 | L129: =IF(AND(L$6<=$F129,L$6>=$C129),IFERROR(-$E129/$F$116,0),0) -> -54.955 | M129: =IF(AND(M$6<=$F129,M$6>=$C129),IFERROR(-$E129/$F$116,0),0) -> -54.955 | N129: =IF(AND(N$6<=$F129,N$6>=$C129),IFERROR(-$E129/$F$116,0),0) -> -54.955 | O129: =IF(AND(O$6<=$F129,O$6>=$C129),IFERROR(-$E129/$F$116,0),0) -> -54.955 | P129: =IF(AND(P$6<=$F129,P$6>=$C129),IFERROR(-$E129/$F$116,0),0) -> 0
C130: {=TRANSPOSE([2]Projections!$L$7:$P$7)} -> 25 | E130: {=TRANSPOSE(L126:P126)} -> 34.659314 | F130: =C130+$F$116-1 -> 28 | L130: =IF(AND(L$6<=$F130,L$6>=$C130),IFERROR(-$E130/$F$116,0),0) -> -8.6648286 | M130: =IF(AND(M$6<=$F130,M$6>=$C130),IFERROR(-$E130/$F$116,0),0) -> -8.6648286 | N130: =IF(AND(N$6<=$F130,N$6>=$C130),IFERROR(-$E130/$F$116,0),0) -> -8.6648286 | O130: =IF(AND(O$6<=$F130,O$6>=$C130),IFERROR(-$E130/$F$116,0),0) -> -8.6648286 | P130: =IF(AND(P$6<=$F130,P$6>=$C130),IFERROR(-$E130/$F$116,0),0) -> 0
...

Sheet Revenue Build
C1: =Cover!$C$7&" ("&Cover!$C$8&": "&Cover!$C$9&")" -> Grab Holdings Limited (NASDAQ: GRAB)
C3: 12M Target Price | E3: =Cover!$C$18 -> 7.2080319
C4: Scenario | E4: =Cover!$C$11 -> Base Case
F5: Historical (31 Dec) | K5: Forecasted (31 Dec)
C6: ="In "&Cover!$C$10&", unless stated otherwise" -> In USD Mn, unless stated otherwise | E6: Units | F6: 20 | G6: =F6+1 -> 21 | H6: =G6+1 -> 22 | I6: =H6+1 -> 23 | J6: =I6+1 -> 24 | K6: =J6+1 -> 25 | L6: =K6+1 -> 26 | M6: =L6+1 -> 27 | N6: =M6+1 -> 28 | O6: =N6+1 -> 29 | P6: Notes:
A8: 1 | C8: Live Case
C10: Revenue Segments
C11: Deliveries | E11: USD Mns | F11: 5 | G11: 148 | H11: 724 | I11: 1310 | J11: 1493 | K11: =K52 -> 1777.4296 | L11: =L52 -> 2109.9432 | M11: =M52 -> 2528.1524 | N11: =N52 -> 3029.4183 | O11: =O52 -> 3627.8214
C12: Mobility | E12: USD Mns | F12: 438 | G12: 456 | H12: 643 | I12: 871 | J12: 1047 | K12: =K186 -> 1346.1042 | L12: =L186 -> 1729.3739 | M12: =M186 -> 2236.1567 | N12: =N186 -> 2888.0171 | O12: =O186 -> 3724.1225
C13: Financial Services | E13: USD Mns | F13: -10 | G13: 27 | H13: 64 | I13: 177 | J13: 253 | K13: =K343 -> 317.85641 | L13: =L343 -> 394.52885 | M13: =M343 -> 484.23552 | N13: =N343 -> 589.61205 | O13: =O343 -> 719.12533
C14: Enterprise, Others and New Initiatives | E14: USD Mns | F14: 36 | G14: 44 | H14: 2 | I14: 1 | J14: 4 | K14: =K474 -> 5.7676768 | L14: =L474 -> 8.3165238 | M14: =M474 -> 11.991755 | N14: =N474 -> 17.291142 | O14: =O474 -> 24.93243
C15: Total Revenues | E15: USD Mns | F15: =SUM(F11:F14) -> 469 | G15: =SUM(G11:G14) -> 675 | H15: =SUM(H11:H14) -> 1433 | I15: =SUM(I11:I14) -> 2359 | J15: =SUM(J11:J14) -> 2797 | K15: =SUM(K11:K14) -> 3447.158 | L15: =SUM(L11:L14) -> 4242.1624 | M15: =SUM(M11:M14) -> 5260.5364 | ... O15: =SUM(O11:O14) -> 8096.0017
C16: %yoy | E16: % | G16: =(G15-F15)/F15 -> 0.43923241 | H16: =(H15-G15)/G15 -> 1.122963 | I16: =(I15-H15)/H15 -> 0.64619679 | J16: =(J15-I15)/I15 -> 0.18567189 | K16: =(K15-J15)/J15 -> 0.23244832 | L16: =(L15-K15)/K15 -> 0.23062606 | M16: =(M15-L15)/L15 -> 0.24006011 | N16: =(N15-M15)/M15 -> 0.24024207 | O16: =(O15-N15)/N15 -> 0.24089233
A18: 2 | C18: Summary
C20: Revenue Per Segment Growth Rate
C21: Deliveries | E21: % | G21: =(G11-F11)/F11 -> 28.6 | H21: =(H11-G11)/G11 -> 3.8918919 | I21: =(I11-H11)/H11 -> 0.80939227 | J21: =(J11-I11)/I11 -> 0.13969466 | K21: =(K11-J11)/J11 -> 0.19050879 | L21: =(L11-K11)/K11 -> 0.18707551 | M21: =(M11-L11)/L11 -> 0.19820878 | N21: =(N11-M11)/M11 -> 0.19827358 | O21: =(O11-N11)/N11 -> 0.19753072
C22: Mobility | E22: % | G22: =(G12-F12)/F12 -> 0.04109589 | H22: =(H12-G12)/G12 -> 0.41008772 | I22: =(I12-H12)/H12 -> 0.35458787 | J22: =(J12-I12)/I12 -> 0.20206659 | K22: =(K12-J12)/J12 -> 0.28567741 | L22: =(L12-K12)/K12 -> 0.28472507 | M22: =(M12-L12)/L12 -> 0.29304411 | N22: =(N12-M12)/M12 -> 0.29150926 | O22: =(O12-N12)/N12 -> 0.28950846
C23: Financial Services | E23: % | G23: =(G13-F13)/F13 -> -3.7 | H23: =(H13-G13)/G13 -> 1.3703704 | I23: =(I13-H13)/H13 -> 1.765625 | J23: =(J13-I13)/I13 -> 0.42937853 | K23: =(K13-J13)/J13 -> 0.25634946 | L23: =(L13-K13)/K13 -> 0.24121723 | M23: =(M13-L13)/L13 -> 0.2273767 | N23: =(N13-M13)/M13 -> 0.2176142 | O23: =(O13-N13)/N13 -> 0.21965847
C24: Enterprise and New Initiatives | E24: % | G24: =(G14-F14)/F14 -> 0.22222222 | H24: =(H14-G14)/G14 -> -0.95454545 | I24: =(I14-H14)/H14 -> -0.5 | J24: =(J14-I14)/I14 -> 3 | K24: =(K14-J14)/J14 -> 0.44191919 | L24: =(L14-K14)/K14 -> 0.44191919 | M24: =(M14-L14)/L14 -> 0.44191919 | N24: =(N14-M14)/M14 -> 0.44191919 | O24: =(O14-N14)/N14 -> 0.44191919
A26: 3 | C26: Geographic Segments
C28: Revenue By Geography
C29: Singapore | E29: USD Mns | F29: 246 | G29: 283 | H29: 302 | I29: 480 | J29: 578 | K29: =K38*K$15 -> 713.41544 | L29: =L38*L$15 -> 877.94764 | M29: =M38*M$15 -> 1088.7078 | N29: =N38*N$15 -> 1350.2613 | O29: =O38*O$15 -> 1675.5289
C30: Malaysia | E30: USD Mns | F30: 91 | G30: 108 | H30: 509 | I30: 673 | J30: 816 | K30: =K39*K$15 -> 1071.1818 | L30: =L39*L$15 -> 1318.2243 | M30: =M39*M$15 -> 1634.6773 | N30: =N39*N$15 -> 2027.3956 | O30: =O39*O$15 -> 2515.7797
C31: Indonesia | E31: USD Mns | F31: -61 | G31: 79 | H31: 275 | I31: 605 | J31: 643 | K31: =K40*K$15 -> 779.35515 | L31: =L40*L$15 -> 959.09476 | M31: =M40*M$15 -> 1189.3352 | N31: =N40*N$15 -> 1475.0635 | O31: =O40*O$15 -> 1830.395
C32: Philippines | E32: USD Mns | F32: 51 | G32: 81 | H32: 125 | I32: 200 | J32: 265 | K32: =K41*K$15 -> 306.51628 | L32: =L41*L$15 -> 377.20692 | M32: =M41*M$15 -> 467.75926 | N32: =N41*N$15 -> 580.13471 | O32: =O41*O$15 -> 719.88471
C33: Thailand | E33: USD Mns | F33: 57 | G33: 76 | H33: 109 | I33: 205 | J33: 252 | K33: =K42*K$15 -> 290.78152 | L33: =L42*L$15 -> 357.84332 | M33: =M42*M$15 -> 443.74722 | N33: =N42*N$15 -> 550.35397 | O33: =O42*O$15 -> 682.93002
C34: Vietnam | E34: USD Mns | F34: 0 | G34: 0 | H34: 108 | I34: 185 | J34: 228 | K34: =K43*K$15 -> 270.37822 | L34: =L43*L$15 -> 332.73448 | M34: =M43*M$15 -> 412.61076 | N34: =N43*N$15 -> 511.73722 | O34: =O43*O$15 -> 635.01079
C35: Rest of Southeast Asia | E35: USD Mns | F35: 85 | G35: 48 | H35: 5 | I35: 11 | J35: 15 | K35: =K44*K$15 -> 15.529521 | L35: =L44*L$15 -> 19.111034 | M35: =M44*M$15 -> 23.698831 | N35: =N44*N$15 -> 29.392287 | O35: =O44*O$15 -> 36.472663
C37: Proportion of Revenue By Geography
C38: Singapore | E38: % | F38: =F29/F$15 -> 0.52452026 | G38: =G29/G$15 -> 0.41925926 | H38: =H29/H$15 -> 0.21074669 | I38: =I29/I$15 -> 0.20347605 | J38: =J29/J$15 -> 0.20664998 | K38: =AVERAGE(H38:J38) -> 0.20695757 | L38: =K38 -> 0.20695757 | M38: =L38 -> 0.20695757 | N38: =M38 -> 0.20695757 | O38: =N38 -> 0.20695757
C39: Malaysia | E39: % | F39: =F30/F$15 -> 0.19402985 | G39: =G30/G$15 -> 0.16 | H39: =H30/H$15 -> 0.35519888 | I39: =I30/I$15 -> 0.28529038 | J39: =J30/J$15 -> 0.29174115 | K39: =AVERAGE(H39:J39) -> 0.31074347 | L39: =K39 -> 0.31074347 | M39: =L39 -> 0.31074347 | N39: =M39 -> 0.31074347 | O39: =N39 -> 0.31074347
C40: Indonesia | E40: % | F40: =F31/F$15 -> -0.13006397 | G40: =G31/G$15 -> 0.11703704 | H40: =H31/H$15 -> 0.19190509 | I40: =I31/I$15 -> 0.2564646 | J40: =J31/J$15 -> 0.22988917 | K40: =AVERAGE(H40:J40) -> 0.22608629 | L40: =K40 -> 0.22608629 | M40: =L40 -> 0.22608629 | N40: =M40 -> 0.22608629 | O40: =N40 -> 0.22608629
C41: Philippines | E41: % | F41: =F32/F$15 -> 0.108742 | G41: =G32/G$15 -> 0.12 | H41: =H32/H$15 -> 0.087229588 | I41: =I32/I$15 -> 0.084781687 | J41: =J32/J$15 -> 0.094744369 | K41: =AVERAGE(H41:J41) -> 0.088918548 | L41: =K41 -> 0.088918548 | M41: =L41 -> 0.088918548 | N41: =M41 -> 0.088918548 | O41: =N41 -> 0.088918548
C42: Thailand | E42: % | F42: =F33/F$15 -> 0.12153518 | G42: =G33/G$15 -> 0.11259259 | H42: =H33/H$15 -> 0.076064201 | I42: =I33/I$15 -> 0.086901229 | J42: =J33/J$15 -> 0.090096532 | K42: =AVERAGE(H42:J42) -> 0.084353987 | L42: =K42 -> 0.084353987 | M42: =L42 -> 0.084353987 | N42: =M42 -> 0.084353987 | O42: =N42 -> 0.084353987
C43: Vietnam | E43: % | F43: =F34/F$15 -> 0 | G43: =G34/G$15 -> 0 | H43: =H34/H$15 -> 0.075366364 | I43: =I34/I$15 -> 0.078423061 | J43: =J34/J$15 -> 0.08151591 | K43: =AVERAGE(H43:J43) -> 0.078435112 | L43: =K43 -> 0.078435112 | M43: =L43 -> 0.078435112 | N43: =M43 -> 0.078435112 | O43: =N43 -> 0.078435112
C44: Rest of Southeast Asia | E44: % | F44: =F35/F$15 -> 0.18123667 | G44: =G35/G$15 -> 0.071111111 | H44: =H35/H$15 -> 0.0034891835 | I44: =I35/I$15 -> 0.0046629928 | J44: =J35/J$15 -> 0.0053628888 | K44: =AVERAGE(H44:J44) -> 0.0045050217 | L44: =K44 -> 0.0045050217 | M44: =L44 -> 0.0045050217 | N44: =M44 -> 0.0045050217 | O44: =N44 -> 0.0045050217
A46: 3 | C46: Deliveries Revenue Build
C48: Assumptions: | F48: Operating Equation:
C49: Brand Premium | D49: 0.075 | F49: Deliveries GMV = GMV per MTU (ASP) x MTU (Volume) | J49: Volume Driven By Consumer Expenditure of Each Operating Geography
C50: Deliveries Take Rate Step | D50: 0.004 | F50: Deliveries Revenue = Take Rate x Deliveries GMV | J50: Price Driven By Inflation of Each Operating Geography
C52: Deliveries | E52: USD Mns | F52: =F11 -> 5 | G52: =G11 -> 148 | H52: =H11 -> 724 | I52: =I11 -> 1310 | J52: =J11 -> 1493 | K52: =K55*K58 -> 1777.4296 | L52: =L55*L58 -> 2109.9432 | M52: =M55*M58 -> 2528.1524 | N52: =N55*N58 -> 3029.4183 | O52: =O55*O58 -> 3627.8214
C53: %yoy | G53: =(G52-F52)/F52 -> 28.6 | H53: =(H52-G52)/G52 -> 3.8918919 | I53: =(I52-H52)/H52 -> 0.80939227 | J53: =(J52-I52)/I52 -> 0.13969466 | K53: =(K52-J52)/J52 -> 0.19050879 | L53: =(L52-K52)/K52 -> 0.18707551 | M53: =(M52-L52)/L52 -> 0.19820878 | N53: =(N52-M52)/M52 -> 0.19827358 | O53: =(O52-N52)/N52 -> 0.19753072
C55: Deliveries Gross Merchant Value (GMV) | E55: USD Mns | F55: 5468 | G55: 8530 | H55: 10007 | I55: 10365 | J55: 11724 | K55: =K62*K109 -> 13532.462 | L55: =L62*L109 -> 15589.298 | M55: =M62*M109 -> 18143.035 | N55: =N62*N109 -> 21133.665 | O55: =O62*O109 -> 24621.17
C56: %yoy | G56: =(G55-F55)/F55 -> 0.55998537 | H56: =(H55-G55)/G55 -> 0.17315358 | I56: =(I55-H55)/H55 -> 0.035774958 | J56: =(J55-I55)/I55 -> 0.13111433 | K56: =(K55-J55)/J55 -> 0.15425303 | L56: =(L55-K55)/K55 -> 0.15199272 | M56: =(M55-L55)/L55 -> 0.16381347 | N56: =(N55-M55)/M55 -> 0.16483625 | O56: =(O55-N55)/N55 -> 0.16502129
C58: Deliveries Take Rate | E58: % | F58: =F52/F55 -> 0.00091441112 | G58: =G52/G55 -> 0.017350528 | H58: =H52/H55 -> 0.072349355 | I58: =I52/I55 -> 0.12638688 | J58: =J52/J55 -> 0.12734562 | K58: =(J58+$D$50) -> 0.13134562 | L58: =K58+$D$50 -> 0.13534562 | M58: =L58+$D$50 -> 0.13934562 | N58: =M58+$D$50 -> 0.14334562 | O58: =N58+$D$50 -> 0.14734562
C60: Monthly Transacting Users (Volume)
C62: Overall MTUs | E62: Mns | F62: 14.8 | G62: 17.3 | H62: 19.4 | I62: 19.1 | J62: 21.7 | K62: =(K65+K71+K77+K83+K89+K95+K101) -> 24.496003 | L62: =(L65+L71+L77+L83+L89+L95+L101) -> 27.58381 | M62: =(M65+M71+M77+M83+M89+M95+M101) -> 31.371436 | N62: =(N65+N71+N77+N83+N89+N95+N101) -> 35.721126 | O62: =(O65+O71+O77+O83+O89+O95+O101) -> 40.678643
G63: =(G62-F62)/F62 -> 0.16891892 | H63: =(H62-G62)/G62 -> 0.12138728 | I63: =(I62-H62)/H62 -> -0.015463918 | J63: =(J62-I62)/I62 -> 0.13612565 | K63: =(K62-J62)/J62 -> 0.12884805 | L63: =(L62-K62)/K62 -> 0.12605353 | M63: =(M62-L62)/L62 -> 0.13731335 | N63: =(N62-M62)/M62 -> 0.1386513 | O63: =(O62-N62)/N62 -> 0.1387839
C65: Singapore | E65: Mns | F65: =_xlfn.XLOOKUP($C65,$C$38:$C$44,F$38:F$44)*F$62 -> 7.7628998 | G65: =_xlfn.XLOOKUP($C65,$C$38:$C$44,G$38:G$44)*G$62 -> 7.2531852 | H65: =_xlfn.XLOOKUP($C65,$C$38:$C$44,H$38:H$44)*H$62 -> 4.0884857 | I65: =_xlfn.XLOOKUP($C65,$C$38:$C$44,I$38:I$44)*I$62 -> 3.8863925 | J65: =_xlfn.XLOOKUP($C65,$C$38:$C$44,J$38:J$44)*J$62 -> 4.4843046 | K65: =J65*(1+K66) -> 4.9327351 | L65: =K65*(1+L66) -> 5.3717485 | M65: =L65*(1+M66) -> 6.0163583 | N65: =M65*(1+N66) -> 6.7383213 | O65: =N65*(1+O66) -> 7.5469199
C66: %yoy | G66: =(G65-F65)/F65 -> -0.065660335 | H66: =(H65-G65)/G65 -> -0.43631858 | I66: =(I65-H65)/H65 -> -0.049429831 | J66: =(J65-I65)/I65 -> 0.15384758 | K66: =_xlfn.XLOOKUP($E$4,$C67:$C69,K67:K69) -> 0.1 | L66: =_xlfn.XLOOKUP($E$4,$C67:$C69,L67:L69) -> 0.089 | M66: =_xlfn.XLOOKUP($E$4,$C67:$C69,M67:M69) -> 0.12 | N66: =_xlfn.XLOOKUP($E$4,$C67:$C69,N67:N69) -> 0.12 | O66: =_xlfn.XLOOKUP($E$4,$C67:$C69,O67:O69) -> 0.12
C67: Bull Case | D67: 0.01 | K67: =K68+$D67 -> 0.11 | L67: =L68+$D67 -> 0.099 | M67: =M68+$D67 -> 0.13 | N67: =N68+$D67 -> 0.13 | O67: =O68+$D67 -> 0.13
C68: Base Case | D68: 0 | K68: =_xlfn.XLOOKUP($C65,$C$169:$C$178,K$169:K$178)+$D$49 -> 0.1 | L68: =_xlfn.XLOOKUP($C65,$C$169:$C$178,L$169:L$178)+$D$49 -> 0.089 | M68: =_xlfn.XLOOKUP($C65,$C$169:$C$178,M$169:M$178)+$D$49 -> 0.12 | N68: =_xlfn.XLOOKUP($C65,$C$169:$C$178,N$169:N$178)+$D$49 -> 0.12 | O68: =_xlfn.XLOOKUP($C65,$C$169:$C$178,O$169:O$178)+$D$49 -> 0.12
C69: Bear Case | D69: -0.01 | K69: =K68+$D69 -> 0.09 | L69: =L68+$D69 -> 0.079 | M69: =M68+$D69 -> 0.11 | N69: =N68+$D69 -> 0.11 | O69: =O68+$D69 -> 0.11
C71: Malaysia | E71: Mns | F71: =_xlfn.XLOOKUP($C71,$C$38:$C$44,F$38:F$44)*F$62 -> 2.8716418 | G71: =_xlfn.XLOOKUP($C71,$C$38:$C$44,G$38:G$44)*G$62 -> 2.768 | H71: =_xlfn.XLOOKUP($C71,$C$38:$C$44,H$38:H$44)*H$62 -> 6.8908583 | I71: =_xlfn.XLOOKUP($C71,$C$38:$C$44,I$38:I$44)*I$62 -> 5.4490462 | J71: =_xlfn.XLOOKUP($C71,$C$38:$C$44,J$38:J$44)*J$62 -> 6.330783 | K71: =J71*(1+K72) -> 7.1791079 | L71: =K71*(1+L72) -> 8.1052128 | M71: =L71*(1+M72) -> 9.1669957 | N71: =M71*(1+N72) -> 10.395373 | O71: =N71*(1+O72) -> 11.798748
C72: %yoy | G72: =(G71-F71)/F71 -> -0.036091476 | H72: =(H71-G71)/G71 -> 1.4894719 | I72: =(I71-H71)/H71 -> -0.20923549 | J72: =(J71-I71)/I71 -> 0.16181488 | K72: =_xlfn.XLOOKUP($E$4,$C73:$C75,K73:K75) -> 0.134 | L72: =_xlfn.XLOOKUP($E$4,$C73:$C75,L73:L75) -> 0.129 | M72: =_xlfn.XLOOKUP($E$4,$C73:$C75,M73:M75) -> 0.131 | N72: =_xlfn.XLOOKUP($E$4,$C73:$C75,N73:N75) -> 0.134 | O72: =_xlfn.XLOOKUP($E$4,$C73:$C75,O73:O75) -> 0.135
