Workbook
Name Company_Name: '[1]lbo(yx)'!#REF!
Name Company_Name: 'LBO Val'!#REF!
Name Company_Name: #REF!
Name Hist_Year: 'LBO Val'!$E$20
Name Hist_Year: #REF!
Name IQ_CH: 110000
Name IQ_CQ: 5000
Name IQ_CY: 10000
Name IQ_DAILY: 500000
Name IQ_FH: 100000
Name IQ_FQ: 500
Name IQ_FY: 1000
Name IQ_LTM: 2000
Name IQ_MONTH: 15000
Name IQ_NTM: 6000
Name IQ_WEEK: 50000
Name IQ_YTD: 3000
Name LTM_EBITDA: '[1]lbo(yx)'!$E$12
Name LTM_EBITDA: 'LBO Val'!$E$12
Name LTM_EBITDA: #REF!
Name Mezz_Equity_Pct: '[1]lbo(yx)'!#REF!
Name Mezz_Equity_Pct: 'LBO Val'!#REF!
Name Mezz_Equity_Pct: #REF!
Name Mezz_Investment: '[1]lbo(yx)'!#REF!
Name Mezz_Investment: 'LBO Val'!#REF!
Name Mezz_Investment: #REF!
Name Mgmt_Option_Pool: '[1]lbo(yx)'!#REF!
Name Mgmt_Option_Pool: 'LBO Val'!#REF!
Name Mgmt_Option_Pool: #REF!
Name Min_Cash: '[1]lbo(yx)'!$E$31
Name Min_Cash: 'LBO Val'!$E$29
Name Min_Cash: #REF!
Name Purchase_Multiple: 'LBO Val'!$K$17
Name Purchase_Multiple: #REF!
Name Sponsor_Equity: '[1]lbo(yx)'!$D$46
Name Sponsor_Equity: 'LBO Val'!$D$44
Name Sponsor_Equity: #REF!
Name Units: 'LBO Val'!#REF!
Name Units: #REF!

Sheet Cover Page
C3: =$E$9 -> Coinbase Global Inc., (NASDAQ: COIN)
C4: Financial Model
C8: Description | N8: Color Codes
C9: Company | E9: Coinbase Global Inc., (NASDAQ: COIN)
C10: Last updated: | E10: =NOW() -> 46130.691 | O10: X | P10: Hardcoded
C11: Project: | E11: PEC Case | O11: X | P11: Linked to other tab
C12: Short description: | E12: Financial Projections | O12: X | P12: Formula
C13: Operating Case | E13: Base Case | O13: X | P13: For Inputs
C14: Owner | E14: dillon.hj@u.nus.edu

Sheet Valuation>

Sheet 3FS
A1: ='Cover Page'!$C$3 -> Coinbase Global Inc., (NASDAQ: COIN) | E1: 2021 | F1: =E1+1 -> 2022 | G1: =F1+1 -> 2023 | H1: =G1+1 -> 2024 | I1: =H1+1 -> 2025 | J1: =I1+1 -> 2026 | K1: =J1+1 -> 2027 | L1: =K1+1 -> 2028 | M1: =L1+1 -> 2029 | N1: =M1+1 -> 2030 | P1: 2021 | Q1: =P1 -> 2021 | R1: =Q1 -> 2021 | S1: =R1 -> 2021 | T1: =S1+1 -> 2022 | U1: =T1 -> 2022 | V1: =U1 -> 2022 | W1: =V1 -> 2022 | X1: =W1+1 -> 2023 | Y1: =X1 -> 2023 | Z1: =Y1 -> 2023 | AA1: =Z1 -> 2023 | AB1: =AA1+1 -> 2024 | AC1: =AB1 -> 2024 | AD1: =AC1 -> 2024 | AE1: =AD1 -> 2024 | AF1: =AE1+1 -> 2025 | AG1: =AF1 -> 2025 | AH1: =AG1 -> 2025 | AI1: =AH1 -> 2025 | AJ1: =AI1+1 -> 2026 | AK1: =AJ1 -> 2026 | AL1: =AK1 -> 2026 | AM1: =AL1 -> 2026 | AN1: =AM1+1 -> 2027 | AO1: =AN1 -> 2027 | AP1: =AO1 -> 2027 | AQ1: =AP1 -> 2027 | AR1: =AQ1+1 -> 2028 | AS1: =AR1 -> 2028 | AT1: =AS1 -> 2028 | AU1: =AT1 -> 2028 | AV1: =AU1+1 -> 2029 | AW1: =AV1 -> 2029 | AX1: =AW1 -> 2029 | AY1: =AX1 -> 2029 | AZ1: =AY1+1 -> 2030 | BA1: =AZ1 -> 2030 | BB1: =BA1 -> 2030 | BC1: =BB1 -> 2030
A2: 3 Financial Statements | E2: Q4 | F2: Q4 | G2: Q4 | H2: Q4 | I2: Q4 | J2: Q4 | K2: Q4 | L2: Q4 | M2: Q4 | N2: Q4 | P2: Q1 | Q2: Q2 | R2: Q3 | S2: Q4 | T2: Q1 | U2: Q2 | V2: Q3 | W2: Q4 | X2: Q1 | Y2: Q2 | Z2: Q3 | AA2: Q4 | AB2: Q1 | AC2: Q2 | AD2: Q3 | AE2: Q4 | AF2: Q1 | AG2: Q2 | AH2: Q3 | AI2: Q4 | AJ2: Q1 | AK2: Q2 | AL2: Q3 | AM2: Q4 | AN2: Q1 | AO2: Q2 | AP2: Q3 | AQ2: Q4 | AR2: Q1 | AS2: Q2 | AT2: Q3 | AU2: Q4 | AV2: Q1 | AW2: Q2 | AX2: Q3 | AY2: Q4 | AZ2: Q1 | BA2: Q2 | BB2: Q3 | BC2: Q4
E3: 12 | F3: 12 | G3: 12 | H3: 12 | I3: 12 | J3: 12 | K3: 12 | L3: 12 | M3: 12 | N3: 12 | P3: 3 | Q3: 3 | R3: 3 | S3: 3 | T3: 3 | U3: 3 | V3: 3 | W3: 3 | X3: 3 | Y3: 3 | Z3: 3 | AA3: 3 | AB3: 3 | AC3: 3 | AD3: 3 | AE3: 3 | AF3: 3 | AG3: 3 | AH3: 3 | AI3: 3 | AJ3: 3 | AK3: 3 | AL3: 3 | AM3: 3 | AN3: 3 | AO3: 3 | AP3: 3 | AQ3: 3 | AR3: 3 | AS3: 3 | AT3: 3 | AU3: 3 | AV3: 3 | AW3: 3 | AX3: 3 | AY3: 3 | AZ3: 3 | BA3: 3 | BB3: 3 | BC3: 3
E4: 365 | F4: 365 | G4: 365 | H4: 366 | I4: 365 | J4: 365 | K4: 365 | L4: 366 | M4: 365 | N4: 365 | P4: 90 | Q4: =Q6-P6 -> 91 | R4: =R6-Q6 -> 92 | S4: =S6-R6 -> 92 | T4: =T6-S6 -> 90 | U4: =U6-T6 -> 91 | V4: =V6-U6 -> 92 | W4: =W6-V6 -> 92 | X4: =X6-W6 -> 90 | ... BC4: =BC6-BB6 -> 92
E5: Actuals | F5: Actuals | G5: Actuals | H5: Actuals | I5: Actuals | J5: Forecasted | K5: Forecasted | L5: Forecasted | M5: Forecasted | N5: Forecasted | P5: Actuals | Q5: Actuals | R5: Actuals | S5: Actuals | T5: Actuals | U5: Actuals | V5: Actuals | W5: Actuals | X5: Actuals | Y5: Actuals | Z5: Actuals | AA5: Actuals | AB5: Actuals | AC5: Actuals | AD5: Actuals | AE5: Actuals | AF5: Actuals | AG5: Actuals | AH5: Actuals | AI5: Actuals | AJ5: Forecasted | AK5: Forecasted | AL5: Forecasted | AM5: Forecasted | AN5: Forecasted | AO5: Forecasted | AP5: Forecasted | AQ5: Forecasted | AR5: Forecasted | AS5: Forecasted | AT5: Forecasted | AU5: Forecasted | AV5: Forecasted | AW5: Forecasted | AX5: Forecasted | AY5: Forecasted | AZ5: Forecasted | BA5: Forecasted | BB5: Forecasted | BC5: Forecasted
A6: In USD '000s, Unless Stated Otherwise | E6: 44561 | F6: =EOMONTH(E6,12) -> 44926 | G6: =EOMONTH(F6,12) -> 45291 | H6: =EOMONTH(G6,12) -> 45657 | I6: =EOMONTH(H6,12) -> 46022 | J6: =EOMONTH(I6,12) -> 46387 | K6: =EOMONTH(J6,12) -> 46752 | L6: =EOMONTH(K6,12) -> 47118 | M6: =EOMONTH(L6,12) -> 47483 | N6: =EOMONTH(M6,12) -> 47848 | P6: 44286 | Q6: =EOMONTH(P6,3) -> 44377 | R6: =EOMONTH(Q6,3) -> 44469 | S6: =EOMONTH(R6,3) -> 44561 | T6: =EOMONTH(S6,3) -> 44651 | U6: =EOMONTH(T6,3) -> 44742 | V6: =EOMONTH(U6,3) -> 44834 | W6: =EOMONTH(V6,3) -> 44926 | X6: =EOMONTH(W6,3) -> 45016 | ... BC6: =EOMONTH(BB6,3) -> 47848
A8: x | B8: P&L | D8: Units | E8: 21 | F8: =E8+1 -> 22 | G8: =F8+1 -> 23 | H8: =G8+1 -> 24 | I8: =H8+1 -> 25 | J8: =I8+1 -> 26 | K8: =J8+1 -> 27 | L8: =K8+1 -> 28 | M8: =L8+1 -> 29 | N8: =M8+1 -> 30 | P8: =P6 -> 44286 | Q8: =Q6 -> 44377 | R8: =R6 -> 44469 | S8: =S6 -> 44561 | T8: =T6 -> 44651 | U8: =U6 -> 44742 | V8: =V6 -> 44834 | W8: =W6 -> 44926 | ... BC8: =BC6 -> 47848
B10: Sales
B12: Revenues
B13: Net Revenues | D13: USD '000s | E13: =SUMIF($P$1:$AI$1,E$1,$P13:$AI13) -> 7354754 | F13: =SUMIF($P$1:$AI$1,F$1,$P13:$AI13) -> 3148815 | G13: =SUMIF($P$1:$AI$1,G$1,$P13:$AI13) -> 2926540 | H13: =SUMIF($P$1:$AI$1,H$1,$P13:$AI13) -> 6293246 | I13: =SUMIF($P$1:$AI$1,I$1,$P13:$AI13) -> 6883438 | J13: =SUMIFS($AJ13:$BC13,$AJ$1:$BC$1,J$1) -> 7476596.4 | K13: =SUMIFS($AJ13:$BC13,$AJ$1:$BC$1,K$1) -> 8407060.3 | L13: =SUMIFS($AJ13:$BC13,$AJ$1:$BC$1,L$1) -> 9466956 | M13: =SUMIFS($AJ13:$BC13,$AJ$1:$BC$1,M$1) -> 11048606 | N13: =SUMIFS($AJ13:$BC13,$AJ$1:$BC$1,N$1) -> 13606441 | P13: 1596981 | Q13: 2033011 | R13: 1234736 | S13: 2490026 | T13: 1164891 | U13: 802603 | V13: 576375 | W13: 604946 | X13: 736398 | Y13: 662500 | Z13: 623004 | AA13: 904638 | AB13: 1587677 | AC13: 1379942 | AD13: 1128597 | AE13: 2197030 | AF13: 1960319 | AG13: 1420096 | AH13: 1792984 | AI13: 1710039 | AJ13: =SUM('Revenue Build'!AI24) -> 1793000 | AK13: =SUM('Revenue Build'!AJ24) -> 1710000 | AL13: =SUM('Revenue Build'!AK24) -> 2301680.4 | AM13: =SUM('Revenue Build'!AL24) -> 1671916 | AN13: =SUM('Revenue Build'!AM24) -> 1877501.6 | AO13: =SUM('Revenue Build'!AN24) -> 1958998.9 | AP13: =SUM('Revenue Build'!AO24) -> 2670524.5 | AQ13: =SUM('Revenue Build'!AP24) -> 1900035.5 | ... BC13: =SUM('Revenue Build'!BB24) -> 3107259.8
B14: Other Revenues | D14: USD '000s | E14: =SUMIF($P$1:$AI$1,E$1,$P14:$AI14) -> 484691 | F14: =SUMIF($P$1:$AI$1,F$1,$P14:$AI14) -> 45393 | G14: =SUMIF($P$1:$AI$1,G$1,$P14:$AI14) -> 181843 | H14: =SUMIF($P$1:$AI$1,H$1,$P14:$AI14) -> 270782 | I14: =SUMIF($P$1:$AI$1,I$1,$P14:$AI14) -> 297887 | J14: =SUMIFS($AJ14:$BC14,$AJ$1:$BC$1,J$1) -> 283923.46 | K14: =SUMIFS($AJ14:$BC14,$AJ$1:$BC$1,K$1) -> 270602.65 | L14: =SUMIFS($AJ14:$BC14,$AJ$1:$BC$1,L$1) -> 257906.82 | M14: =SUMIFS($AJ14:$BC14,$AJ$1:$BC$1,M$1) -> 245806.63 | N14: =SUMIFS($AJ14:$BC14,$AJ$1:$BC$1,N$1) -> 234274.15 | P14: 204131 | Q14: 194951 | R14: 77172 | S14: 8437 | T14: 1545 | U14: 5722 | V14: 13964 | W14: 24162 | X14: 36131 | Y14: 45411 | Z14: 51144 | AA14: 49157 | AB14: 49893 | AC14: 69686 | AD14: 76596 | AE14: 74607 | AF14: 73976 | AG14: 77112 | AH14: 75709 | AI14: 71090 | AJ14: ='Revenue Build'!AK26 -> 70528.15 | AK14: ='Revenue Build'!AL26 -> 73482.708 | AL14: ='Revenue Build'!AM26 -> 72148.391 | AM14: ='Revenue Build'!AN26 -> 67764.209 | AN14: ='Revenue Build'!AO26 -> 67219.189 | AO14: ='Revenue Build'!AP26 -> 70035.128 | AP14: ='Revenue Build'!AQ26 -> 68763.413 | AQ14: ='Revenue Build'!AR26 -> 64584.923 | ... BC14: ='Revenue Build'!BD26 -> 55914.374
B15: Total Revenues | D15: USD '000s | E15: =SUM(E13:E14) -> 7839445 | F15: =SUM(F13:F14) -> 3194208 | G15: =SUM(G13:G14) -> 3108383 | H15: =SUM(H13:H14) -> 6564028 | I15: =SUM(I13:I14) -> 7181325 | J15: =SUM(J13:J14) -> 7760519.9 | K15: =SUM(K13:K14) -> 8677663 | L15: =SUM(L13:L14) -> 9724862.8 | ... N15: =SUM(N13:N14) -> 13840715 | P15: =SUM(P13:P14) -> 1801112 | Q15: =SUM(Q13:Q14) -> 2227962 | R15: =SUM(R13:R14) -> 1311908 | S15: =SUM(S13:S14) -> 2498463 | T15: =SUM(T13:T14) -> 1166436 | U15: =SUM(U13:U14) -> 808325 | V15: =SUM(V13:V14) -> 590339 | W15: =SUM(W13:W14) -> 629108 | ... BC15: =SUM(BC13:BC14) -> 3163174.1
B17: Net Revenues | D17: % | E17: =E13/E$15 -> 0.93817279 | F17: =F13/F$15 -> 0.98578897 | G17: =G13/G$15 -> 0.94149917 | H17: =H13/H$15 -> 0.95874759 | I17: =I13/I$15 -> 0.95851921 | J17: =J13/J$15 -> 0.96341438 | K17: =K13/K$15 -> 0.96881618 | L17: =L13/L$15 -> 0.97347964 | ... N17: =N13/N$15 -> 0.98307355 | P17: =P13/P$15 -> 0.88666391 | Q17: =Q13/Q$15 -> 0.91249806 | R17: =R13/R$15 -> 0.94117575 | S17: =S13/S$15 -> 0.99662312 | T17: =T13/T$15 -> 0.99867545 | U17: =U13/U$15 -> 0.99292116 | V17: =V13/V$15 -> 0.97634579 | W17: =W13/W$15 -> 0.96159324 | ... BC17: =BC13/BC$15 -> 0.98232333
B18: Other Revenues | D18: % | E18: =E14/E$15 -> 0.061827208 | F18: =F14/F$15 -> 0.014211034 | G18: =G14/G$15 -> 0.058500835 | H18: =H14/H$15 -> 0.041252414 | I18: =I14/I$15 -> 0.041480785 | J18: =J14/J$15 -> 0.036585624 | K18: =K14/K$15 -> 0.031183817 | L18: =L14/L$15 -> 0.026520355 | ... N18: =N14/N$15 -> 0.016926448 | P18: =P14/P$15 -> 0.11333609 | Q18: =Q14/Q$15 -> 0.087501941 | R18: =R14/R$15 -> 0.058824247 | S18: =S14/S$15 -> 0.0033768761 | T18: =T14/T$15 -> 0.0013245476 | U18: =U14/U$15 -> 0.0070788359 | V18: =V14/V$15 -> 0.023654205 | W18: =W14/W$15 -> 0.03840676 | ... BC18: =BC14/BC$15 -> 0.017676666
B20: Cost of Goods Sold | D20: USD '000s | E20: =SUMIF($P$1:$AI$1,E$1,$P20:$AI20) -> 0 | F20: =SUMIF($P$1:$AI$1,F$1,$P20:$AI20) -> 0 | G20: =SUMIF($P$1:$AI$1,G$1,$P20:$AI20) -> -125559 | H20: =SUMIF($P$1:$AI$1,H$1,$P20:$AI20) -> 0 | I20: =SUMIF($P$1:$AI$1,I$1,$P20:$AI20) -> 0 | J20: =SUMIFS($AJ20:$BC20,$AJ$1:$BC$1,J$1) -> 0 | K20: =SUMIFS($AJ20:$BC20,$AJ$1:$BC$1,K$1) -> 0 | L20: =SUMIFS($AJ20:$BC20,$AJ$1:$BC$1,L$1) -> 0 | M20: =SUMIFS($AJ20:$BC20,$AJ$1:$BC$1,M$1) -> 0 | N20: =SUMIFS($AJ20:$BC20,$AJ$1:$BC$1,N$1) -> 0 | P20: 0 | Q20: 0 | R20: 0 | S20: 0 | T20: 0 | U20: 0 | V20: 0 | W20: 0 | X20: 0 | Y20: 0 | Z20: 0 | AA20: -125559 | AB20: 0 | AC20: 0 | AD20: 0 | AE20: 0 | AF20: 0 | AG20: 0 | AH20: 0 | AI20: 0 | AJ20: =_xlfn.XLOOKUP($B20,'IS & BS Projections'!$B:$B,'IS & BS Projections'!AK:AK) -> 0 | AK20: =_xlfn.XLOOKUP($B20,'IS & BS Projections'!$B:$B,'IS & BS Projections'!AL:AL) -> 0 | AL20: =_xlfn.XLOOKUP($B20,'IS & BS Projections'!$B:$B,'IS & BS Projections'!AM:AM) -> 0 | AM20: =_xlfn.XLOOKUP($B20,'IS & BS Projections'!$B:$B,'IS & BS Projections'!AN:AN) -> 0 | AN20: =_xlfn.XLOOKUP($B20,'IS & BS Projections'!$B:$B,'IS & BS Projections'!AO:AO) -> 0 | AO20: =_xlfn.XLOOKUP($B20,'IS & BS Projections'!$B:$B,'IS & BS Projections'!AP:AP) -> 0 | AP20: =_xlfn.XLOOKUP($B20,'IS & BS Projections'!$B:$B,'IS & BS Projections'!AQ:AQ) -> 0 | AQ20: =_xlfn.XLOOKUP($B20,'IS & BS Projections'!$B:$B,'IS & BS Projections'!AR:AR) -> 0 | AR20: =_xlfn.XLOOKUP($B20,'IS & BS Projections'!$B:$B,'IS & BS Projections'!AS:AS) -> 0 | AS20: =_xlfn.XLOOKUP($B20,'IS & BS Projections'!$B:$B,'IS & BS Projections'!AT:AT) -> 0 | AT20: =_xlfn.XLOOKUP($B20,'IS & BS Projections'!$B:$B,'IS & BS Projections'!AU:AU) -> 0 | AU20: =_xlfn.XLOOKUP($B20,'IS & BS Projections'!$B:$B,'IS & BS Projections'!AV:AV) -> 0 | AV20: =_xlfn.XLOOKUP($B20,'IS & BS Projections'!$B:$B,'IS & BS Projections'!AW:AW) -> 0 | AW20: =_xlfn.XLOOKUP($B20,'IS & BS Projections'!$B:$B,'IS & BS Projections'!AX:AX) -> 0 | AX20: =_xlfn.XLOOKUP($B20,'IS & BS Projections'!$B:$B,'IS & BS Projections'!AY:AY) -> 0 | AY20: =_xlfn.XLOOKUP($B20,'IS & BS Projections'!$B:$B,'IS & BS Projections'!AZ:AZ) -> 0 | AZ20: =_xlfn.XLOOKUP($B20,'IS & BS Projections'!$B:$B,'IS & BS Projections'!BA:BA) -> 0 | BA20: =_xlfn.XLOOKUP($B20,'IS & BS Projections'!$B:$B,'IS & BS Projections'!BB:BB) -> 0 | BB20: =_xlfn.XLOOKUP($B20,'IS & BS Projections'!$B:$B,'IS & BS Projections'!BC:BC) -> 0 | BC20: =_xlfn.XLOOKUP($B20,'IS & BS Projections'!$B:$B,'IS & BS Projections'!BD:BD) -> 0
B22: Gross Profit | D22: USD '000s | E22: =SUM(E15,E20) -> 7839445 | F22: =SUM(F15,F20) -> 3194208 | G22: =SUM(G15,G20) -> 2982824 | H22: =SUM(H15,H20) -> 6564028 | I22: =SUM(I15,I20) -> 7181325 | J22: =SUM(J15,J20) -> 7760519.9 | K22: =SUM(K15,K20) -> 8677663 | L22: =SUM(L15,L20) -> 9724862.8 | ... N22: =SUM(N15,N20) -> 13840715 | P22: =SUM(P15,P20) -> 1801112 | Q22: =SUM(Q15,Q20) -> 2227962 | R22: =SUM(R15,R20) -> 1311908 | S22: =SUM(S15,S20) -> 2498463 | T22: =SUM(T15,T20) -> 1166436 | U22: =SUM(U15,U20) -> 808325 | V22: =SUM(V15,V20) -> 590339 | W22: =SUM(W15,W20) -> 629108 | ... BC22: =SUM(BC15,BC20) -> 3163174.1
B23: Gross Profit Margin | D23: % | E23: =E22/E$15 -> 1 | F23: =F22/F$15 -> 1 | G23: =G22/G$15 -> 0.95960633 | H23: =H22/H$15 -> 1 | I23: =I22/I$15 -> 1 | J23: =J22/J$15 -> 1 | K23: =K22/K$15 -> 1 | L23: =L22/L$15 -> 1 | ... N23: =N22/N$15 -> 1 | P23: =P22/P$15 -> 1 | Q23: =Q22/Q$15 -> 1 | R23: =R22/R$15 -> 1 | S23: =S22/S$15 -> 1 | T23: =T22/T$15 -> 1 | U23: =U22/U$15 -> 1 | V23: =V22/V$15 -> 1 | W23: =W22/W$15 -> 1 | ... BC23: =BC22/BC$15 -> 1
B25: Transaction Expenses | D25: USD '000s | E25: =SUMIF($P$1:$AI$1,E$1,$P25:$AI25) -> -1267924 | F25: =SUMIF($P$1:$AI$1,F$1,$P25:$AI25) -> -629880 | G25: =SUMIF($P$1:$AI$1,G$1,$P25:$AI25) -> -295146 | H25: =SUMIF($P$1:$AI$1,H$1,$P25:$AI25) -> -897707 | I25: =SUMIF($P$1:$AI$1,I$1,$P25:$AI25) -> -1020230 | J25: =SUMIFS($AJ25:$BC25,$AJ$1:$BC$1,J$1) -> -1087847.8 | K25: =SUMIFS($AJ25:$BC25,$AJ$1:$BC$1,K$1) -> -1217922.3 | L25: =SUMIFS($AJ25:$BC25,$AJ$1:$BC$1,L$1) -> -1366029.7 | M25: =SUMIFS($AJ25:$BC25,$AJ$1:$BC$1,M$1) -> -1588200.3 | N25: =SUMIFS($AJ25:$BC25,$AJ$1:$BC$1,N$1) -> -1948753.5 | P25: -234066 | Q25: -335426 | R25: -197251 | S25: -501181 | T25: -277826 | U25: -167187 | V25: -101876 | W25: -82991 | X25: -96369 | Y25: -108200 | Z25: -90577 | AA25: 0 | AB25: -217407 | AC25: -191477 | AD25: -171781 | AE25: -317042 | AF25: -303026 | AG25: -245261 | AH25: -253318 | AI25: -218625 | AJ25: =_xlfn.XLOOKUP($B25,'IS & BS Projections'!$B:$B,'IS & BS Projections'!AK:AK) -> -247405.65 | AK25: =_xlfn.XLOOKUP($B25,'IS & BS Projections'!$B:$B,'IS & BS Projections'!AL:AL) -> -272594.76 | AL25: =_xlfn.XLOOKUP($B25,'IS & BS Projections'!$B:$B,'IS & BS Projections'!AM:AM) -> -338351.35 | AM25: =_xlfn.XLOOKUP($B25,'IS & BS Projections'!$B:$B,'IS & BS Projections'!AN:AN) -> -229496.05 | AN25: =_xlfn.XLOOKUP($B25,'IS & BS Projections'!$B:$B,'IS & BS Projections'!AO:AO) -> -258184.93 | AO25: =_xlfn.XLOOKUP($B25,'IS & BS Projections'!$B:$B,'IS & BS Projections'!AP:AP) -> -310125.82 | AP25: =_xlfn.XLOOKUP($B25,'IS & BS Projections'!$B:$B,'IS & BS Projections'!AQ:AQ) -> -390441.7 | AQ25: =_xlfn.XLOOKUP($B25,'IS & BS Projections'!$B:$B,'IS & BS Projections'!AR:AR) -> -259169.83 | AR25: =_xlfn.XLOOKUP($B25,'IS & BS Projections'!$B:$B,'IS & BS Projections'!AS:AS) -> -281050.65 | AS25: =_xlfn.XLOOKUP($B25,'IS & BS Projections'!$B:$B,'IS & BS Projections'!AT:AT) -> -354884.3 | AT25: =_xlfn.XLOOKUP($B25,'IS & BS Projections'!$B:$B,'IS & BS Projections'!AU:AU) -> -439978.54 | AU25: =_xlfn.XLOOKUP($B25,'IS & BS Projections'!$B:$B,'IS & BS Projections'!AV:AV) -> -290116.24 | AV25: =_xlfn.XLOOKUP($B25,'IS & BS Projections'!$B:$B,'IS & BS Projections'!AW:AW) -> -310314.72 | AW25: =_xlfn.XLOOKUP($B25,'IS & BS Projections'!$B:$B,'IS & BS Projections'!AX:AX) -> -422069.8 | AX25: =_xlfn.XLOOKUP($B25,'IS & BS Projections'!$B:$B,'IS & BS Projections'!AY:AY) -> -516966.32 | AY25: =_xlfn.XLOOKUP($B25,'IS & BS Projections'!$B:$B,'IS & BS Projections'!AZ:AZ) -> -338849.5 | AZ25: =_xlfn.XLOOKUP($B25,'IS & BS Projections'!$B:$B,'IS & BS Projections'!BA:BA) -> -356531.68 | BA25: =_xlfn.XLOOKUP($B25,'IS & BS Projections'!$B:$B,'IS & BS Projections'!BB:BB) -> -530759.49 | BB25: =_xlfn.XLOOKUP($B25,'IS & BS Projections'!$B:$B,'IS & BS Projections'!BC:BC) -> -644181.04 | BC25: =_xlfn.XLOOKUP($B25,'IS & BS Projections'!$B:$B,'IS & BS Projections'!BD:BD) -> -417281.27
B26: Sales and Marketing | D26: USD '000s | E26: =SUMIF($P$1:$AI$1,E$1,$P26:$AI26) -> -663690 | F26: =SUMIF($P$1:$AI$1,F$1,$P26:$AI26) -> -510089 | G26: =SUMIF($P$1:$AI$1,G$1,$P26:$AI26) -> -332312 | H26: =SUMIF($P$1:$AI$1,H$1,$P26:$AI26) -> -654444 | I26: =SUMIF($P$1:$AI$1,I$1,$P26:$AI26) -> -1058577 | J26: =SUMIFS($AJ26:$BC26,$AJ$1:$BC$1,J$1) -> -787027.43 | K26: =SUMIFS($AJ26:$BC26,$AJ$1:$BC$1,K$1) -> -877038.44 | L26: =SUMIFS($AJ26:$BC26,$AJ$1:$BC$1,L$1) -> -975567.07 | M26: =SUMIFS($AJ26:$BC26,$AJ$1:$BC$1,M$1) -> -1126367.8 | N26: =SUMIFS($AJ26:$BC26,$AJ$1:$BC$1,N$1) -> -1373485.3 | P26: -117990 | Q26: -195733 | R26: -105395 | S26: -244572 | T26: -200204 | U26: -140894 | V26: -75888 | W26: -93103 | X26: -63976 | Y26: -83853 | Z26: -78178 | AA26: -106305 | AB26: -98585 | AC26: -165262 | AD26: -164770 | AE26: -225827 | AF26: -247283 | AG26: -236245 | AH26: -260272 | AI26: -314777 | AJ26: =_xlfn.XLOOKUP($B26,'IS & BS Projections'!$B:$B,'IS & BS Projections'!AK:AK) -> -135690.42 | AK26: =_xlfn.XLOOKUP($B26,'IS & BS Projections'!$B:$B,'IS & BS Projections'!AL:AL) -> -193421.07 | AL26: =_xlfn.XLOOKUP($B26,'IS & BS Projections'!$B:$B,'IS & BS Projections'!AM:AM) -> -281417.08 | AM26: =_xlfn.XLOOKUP($B26,'IS & BS Projections'!$B:$B,'IS & BS Projections'!AN:AN) -> -176498.85 | AN26: =_xlfn.XLOOKUP($B26,'IS & BS Projections'!$B:$B,'IS & BS Projections'!AO:AO) -> -139657.63 | AO26: =_xlfn.XLOOKUP($B26,'IS & BS Projections'!$B:$B,'IS & BS Projections'!AP:AP) -> -218022.4 | AP26: =_xlfn.XLOOKUP($B26,'IS & BS Projections'!$B:$B,'IS & BS Projections'!AQ:AQ) -> -322002.92 | AQ26: =_xlfn.XLOOKUP($B26,'IS & BS Projections'!$B:$B,'IS & BS Projections'!AR:AR) -> -197355.48 | AR26: =_xlfn.XLOOKUP($B26,'IS & BS Projections'!$B:$B,'IS & BS Projections'!AS:AS) -> -149909.22 | AS26: =_xlfn.XLOOKUP($B26,'IS & BS Projections'!$B:$B,'IS & BS Projections'!AT:AT) -> -247166.31 | AT26: =_xlfn.XLOOKUP($B26,'IS & BS Projections'!$B:$B,'IS & BS Projections'!AU:AU) -> -359769.84 | AU26: =_xlfn.XLOOKUP($B26,'IS & BS Projections'!$B:$B,'IS & BS Projections'!AV:AV) -> -218721.69 | AV26: =_xlfn.XLOOKUP($B26,'IS & BS Projections'!$B:$B,'IS & BS Projections'!AW:AW) -> -163180.97 | AW26: =_xlfn.XLOOKUP($B26,'IS & BS Projections'!$B:$B,'IS & BS Projections'!AX:AX) -> -291197.57 | AX26: =_xlfn.XLOOKUP($B26,'IS & BS Projections'!$B:$B,'IS & BS Projections'!AY:AY) -> -419095.67 | AY26: =_xlfn.XLOOKUP($B26,'IS & BS Projections'!$B:$B,'IS & BS Projections'!AZ:AZ) -> -252893.59 | AZ26: =_xlfn.XLOOKUP($B26,'IS & BS Projections'!$B:$B,'IS & BS Projections'!BA:BA) -> -184798.95 | BA26: =_xlfn.XLOOKUP($B26,'IS & BS Projections'!$B:$B,'IS & BS Projections'!BB:BB) -> -362713.02 | BB26: =_xlfn.XLOOKUP($B26,'IS & BS Projections'!$B:$B,'IS & BS Projections'!BC:BC) -> -517706.96 | BC26: =_xlfn.XLOOKUP($B26,'IS & BS Projections'!$B:$B,'IS & BS Projections'!BD:BD) -> -308266.4
B27: General and Administrative | D27: USD '000s | E27: =SUMIF($P$1:$AI$1,E$1,$P27:$AI27) -> -909392 | F27: =SUMIF($P$1:$AI$1,F$1,$P27:$AI27) -> -1600586 | G27: =SUMIF($P$1:$AI$1,G$1,$P27:$AI27) -> -1074308 | H27: =SUMIF($P$1:$AI$1,H$1,$P27:$AI27) -> -1300257 | I27: =SUMIF($P$1:$AI$1,I$1,$P27:$AI27) -> -1619642 | J27: =SUMIFS($AJ27:$BC27,$AJ$1:$BC$1,J$1) -> -1875931 | K27: =SUMIFS($AJ27:$BC27,$AJ$1:$BC$1,K$1) -> -2107093.6 | L27: =SUMIFS($AJ27:$BC27,$AJ$1:$BC$1,L$1) -> -2364618.1 | M27: =SUMIFS($AJ27:$BC27,$AJ$1:$BC$1,M$1) -> -2753249.1 | N27: =SUMIFS($AJ27:$BC27,$AJ$1:$BC$1,N$1) -> -3384661.7 | P27: -121231 | Q27: -248195 | R27: -242642 | S27: -297324 | T27: -413578 | U27: -470169 | V27: -339157 | W27: -377682 | X27: -248761 | Y27: -258988 | Z27: -252630 | AA27: -313929 | AB27: -287236 | AC27: -320115 | AD27: -330387 | AE27: -362519 | AF27: -394346 | AG27: -353707 | AH27: -418446 | AI27: -453143 | AJ27: =_xlfn.XLOOKUP($B27,'IS & BS Projections'!$B:$B,'IS & BS Projections'!AK:AK) -> -361243.02 | AK27: =_xlfn.XLOOKUP($B27,'IS & BS Projections'!$B:$B,'IS & BS Projections'!AL:AL) -> -421337.8 | AL27: =_xlfn.XLOOKUP($B27,'IS & BS Projections'!$B:$B,'IS & BS Projections'!AM:AM) -> -650752.34 | AM27: =_xlfn.XLOOKUP($B27,'IS & BS Projections'!$B:$B,'IS & BS Projections'!AN:AN) -> -442597.88 | AN27: =_xlfn.XLOOKUP($B27,'IS & BS Projections'!$B:$B,'IS & BS Projections'!AO:AO) -> -376982.12 | AO27: =_xlfn.XLOOKUP($B27,'IS & BS Projections'!$B:$B,'IS & BS Projections'!AP:AP) -> -479347.91 | AP27: =_xlfn.XLOOKUP($B27,'IS & BS Projections'!$B:$B,'IS & BS Projections'!AQ:AQ) -> -750937.9 | AQ27: =_xlfn.XLOOKUP($B27,'IS & BS Projections'!$B:$B,'IS & BS Projections'!AR:AR) -> -499825.66 | AR27: =_xlfn.XLOOKUP($B27,'IS & BS Projections'!$B:$B,'IS & BS Projections'!AS:AS) -> -410368.92 | AS27: =_xlfn.XLOOKUP($B27,'IS & BS Projections'!$B:$B,'IS & BS Projections'!AT:AT) -> -548529.14 | AT27: =_xlfn.XLOOKUP($B27,'IS & BS Projections'!$B:$B,'IS & BS Projections'!AU:AU) -> -846212.27 | AU27: =_xlfn.XLOOKUP($B27,'IS & BS Projections'!$B:$B,'IS & BS Projections'!AV:AV) -> -559507.81 | AV27: =_xlfn.XLOOKUP($B27,'IS & BS Projections'!$B:$B,'IS & BS Projections'!AW:AW) -> -453098.09 | AW27: =_xlfn.XLOOKUP($B27,'IS & BS Projections'!$B:$B,'IS & BS Projections'!AX:AX) -> -652374.83 | AX27: =_xlfn.XLOOKUP($B27,'IS & BS Projections'!$B:$B,'IS & BS Projections'!AY:AY) -> -994283.13 | AY27: =_xlfn.XLOOKUP($B27,'IS & BS Projections'!$B:$B,'IS & BS Projections'!AZ:AZ) -> -653493.04 | AZ27: =_xlfn.XLOOKUP($B27,'IS & BS Projections'!$B:$B,'IS & BS Projections'!BA:BA) -> -520580.6 | BA27: =_xlfn.XLOOKUP($B27,'IS & BS Projections'!$B:$B,'IS & BS Projections'!BB:BB) -> -820371.73 | BB27: =_xlfn.XLOOKUP($B27,'IS & BS Projections'!$B:$B,'IS & BS Projections'!BC:BC) -> -1238955.7 | BC27: =_xlfn.XLOOKUP($B27,'IS & BS Projections'!$B:$B,'IS & BS Projections'!BD:BD) -> -804753.74
B28: Technology Development | D28: USD '000s | E28: =SUMIF($P$1:$AI$1,E$1,$P28:$AI28) -> -1291561 | F28: =SUMIF($P$1:$AI$1,F$1,$P28:$AI28) -> -2326354 | G28: =SUMIF($P$1:$AI$1,G$1,$P28:$AI28) -> -1324541 | H28: =SUMIF($P$1:$AI$1,H$1,$P28:$AI28) -> -1468252 | I28: =SUMIF($P$1:$AI$1,I$1,$P28:$AI28) -> -1670605 | J28: =SUMIFS($AJ28:$BC28,$AJ$1:$BC$1,J$1) -> -1515771.2 | K28: =SUMIFS($AJ28:$BC28,$AJ$1:$BC$1,K$1) -> -1683819.7 | L28: =SUMIFS($AJ28:$BC28,$AJ$1:$BC$1,L$1) -> -1866088.7 | M28: =SUMIFS($AJ28:$BC28,$AJ$1:$BC$1,M$1) -> -2146482.3 | N28: =SUMIFS($AJ28:$BC28,$AJ$1:$BC$1,N$1) -> -2607377.5 | P28: -184225 | Q28: -291461 | R28: -356264 | S28: -459611 | T28: -570664 | U28: -609249 | V28: -556338 | W28: -590103 | X28: -358031 | Y28: -320667 | Z28: -322756 | AA28: -323087 | AB28: -357863 | AC28: -364258 | AD28: -377440 | AE28: -368691 | AF28: -355368 | AG28: -387322 | AH28: -430585 | AI28: -497330 | AJ28: =_xlfn.XLOOKUP($B28,'IS & BS Projections'!$B:$B,'IS & BS Projections'!AK:AK) -> -267477.69 | AK28: =_xlfn.XLOOKUP($B28,'IS & BS Projections'!$B:$B,'IS & BS Projections'!AL:AL) -> -327618.97 | AL28: =_xlfn.XLOOKUP($B28,'IS & BS Projections'!$B:$B,'IS & BS Projections'!AM:AM) -> -565393.92 | AM28: =_xlfn.XLOOKUP($B28,'IS & BS Projections'!$B:$B,'IS & BS Projections'!AN:AN) -> -355280.59 | AN28: =_xlfn.XLOOKUP($B28,'IS & BS Projections'!$B:$B,'IS & BS Projections'!AO:AO) -> -274269.7 | AO28: =_xlfn.XLOOKUP($B28,'IS & BS Projections'!$B:$B,'IS & BS Projections'!AP:AP) -> -367653.22 | AP28: =_xlfn.XLOOKUP($B28,'IS & BS Projections'!$B:$B,'IS & BS Projections'!AQ:AQ) -> -645590.04 | AQ28: =_xlfn.XLOOKUP($B28,'IS & BS Projections'!$B:$B,'IS & BS Projections'!AR:AR) -> -396306.71 | AR28: =_xlfn.XLOOKUP($B28,'IS & BS Projections'!$B:$B,'IS & BS Projections'!AS:AS) -> -293267.56 | AS28: =_xlfn.XLOOKUP($B28,'IS & BS Projections'!$B:$B,'IS & BS Projections'!AT:AT) -> -414909.59 | AT28: =_xlfn.XLOOKUP($B28,'IS & BS Projections'!$B:$B,'IS & BS Projections'!AU:AU) -> -719781.44 | AU28: =_xlfn.XLOOKUP($B28,'IS & BS Projections'!$B:$B,'IS & BS Projections'!AV:AV) -> -438130.07 | AV28: =_xlfn.XLOOKUP($B28,'IS & BS Projections'!$B:$B,'IS & BS Projections'!AW:AW) -> -317960.25 | AW28: =_xlfn.XLOOKUP($B28,'IS & BS Projections'!$B:$B,'IS & BS Projections'!AX:AX) -> -486555.27 | AX28: =_xlfn.XLOOKUP($B28,'IS & BS Projections'!$B:$B,'IS & BS Projections'!AY:AY) -> -836661.92 | AY28: =_xlfn.XLOOKUP($B28,'IS & BS Projections'!$B:$B,'IS & BS Projections'!AZ:AZ) -> -505304.89 | AZ28: =_xlfn.XLOOKUP($B28,'IS & BS Projections'!$B:$B,'IS & BS Projections'!BA:BA) -> -358602.17 | BA28: =_xlfn.XLOOKUP($B28,'IS & BS Projections'!$B:$B,'IS & BS Projections'!BB:BB) -> -603169.61 | BB28: =_xlfn.XLOOKUP($B28,'IS & BS Projections'!$B:$B,'IS & BS Projections'!BC:BC) -> -1031248.4 | BC28: =_xlfn.XLOOKUP($B28,'IS & BS Projections'!$B:$B,'IS & BS Projections'!BD:BD) -> -614357.29
B29: Other Operating (Expenses)/income | D29: USD '000s | E29: =SUMIF($P$1:$AI$1,E$1,$P29:$AI29) -> 0 | F29: =SUMIF($P$1:$AI$1,F$1,$P29:$AI29) -> 0 | G29: =SUMIF($P$1:$AI$1,G$1,$P29:$AI29) -> 34675 | H29: =SUMIF($P$1:$AI$1,H$1,$P29:$AI29) -> 0 | I29: =SUMIF($P$1:$AI$1,I$1,$P29:$AI29) -> 0 | J29: =SUMIFS($AJ29:$BC29,$AJ$1:$BC$1,J$1) -> 0 | K29: =SUMIFS($AJ29:$BC29,$AJ$1:$BC$1,K$1) -> 0 | L29: =SUMIFS($AJ29:$BC29,$AJ$1:$BC$1,L$1) -> 0 | M29: =SUMIFS($AJ29:$BC29,$AJ$1:$BC$1,M$1) -> 0 | N29: =SUMIFS($AJ29:$BC29,$AJ$1:$BC$1,N$1) -> 0 | P29: 0 | Q29: 0 | R29: 0 | S29: 0 | T29: 0 | U29: 0 | V29: 0 | W29: 0 | X29: -17962 | Y29: 8053 | Z29: -7180 | AA29: 51764 | AB29: 0 | AC29: 0 | AD29: 0 | AE29: 0 | AF29: 0 | AG29: 0 | AH29: 0 | AI29: 0 | AJ29: =_xlfn.XLOOKUP($B29,'IS & BS Projections'!$B:$B,'IS & BS Projections'!AK:AK) -> 0 | AK29: =_xlfn.XLOOKUP($B29,'IS & BS Projections'!$B:$B,'IS & BS Projections'!AL:AL) -> 0 | AL29: =_xlfn.XLOOKUP($B29,'IS & BS Projections'!$B:$B,'IS & BS Projections'!AM:AM) -> 0 | AM29: =_xlfn.XLOOKUP($B29,'IS & BS Projections'!$B:$B,'IS & BS Projections'!AN:AN) -> 0 | AN29: =_xlfn.XLOOKUP($B29,'IS & BS Projections'!$B:$B,'IS & BS Projections'!AO:AO) -> 0 | AO29: =_xlfn.XLOOKUP($B29,'IS & BS Projections'!$B:$B,'IS & BS Projections'!AP:AP) -> 0 | AP29: =_xlfn.XLOOKUP($B29,'IS & BS Projections'!$B:$B,'IS & BS Projections'!AQ:AQ) -> 0 | AQ29: =_xlfn.XLOOKUP($B29,'IS & BS Projections'!$B:$B,'IS & BS Projections'!AR:AR) -> 0 | AR29: =_xlfn.XLOOKUP($B29,'IS & BS Projections'!$B:$B,'IS & BS Projections'!AS:AS) -> 0 | AS29: =_xlfn.XLOOKUP($B29,'IS & BS Projections'!$B:$B,'IS & BS Projections'!AT:AT) -> 0 | AT29: =_xlfn.XLOOKUP($B29,'IS & BS Projections'!$B:$B,'IS & BS Projections'!AU:AU) -> 0 | AU29: =_xlfn.XLOOKUP($B29,'IS & BS Projections'!$B:$B,'IS & BS Projections'!AV:AV) -> 0 | AV29: =_xlfn.XLOOKUP($B29,'IS & BS Projections'!$B:$B,'IS & BS Projections'!AW:AW) -> 0 | AW29: =_xlfn.XLOOKUP($B29,'IS & BS Projections'!$B:$B,'IS & BS Projections'!AX:AX) -> 0 | AX29: =_xlfn.XLOOKUP($B29,'IS & BS Projections'!$B:$B,'IS & BS Projections'!AY:AY) -> 0 | AY29: =_xlfn.XLOOKUP($B29,'IS & BS Projections'!$B:$B,'IS & BS Projections'!AZ:AZ) -> 0 | AZ29: =_xlfn.XLOOKUP($B29,'IS & BS Projections'!$B:$B,'IS & BS Projections'!BA:BA) -> 0 | BA29: =_xlfn.XLOOKUP($B29,'IS & BS Projections'!$B:$B,'IS & BS Projections'!BB:BB) -> 0 | BB29: =_xlfn.XLOOKUP($B29,'IS & BS Projections'!$B:$B,'IS & BS Projections'!BC:BC) -> 0 | BC29: =_xlfn.XLOOKUP($B29,'IS & BS Projections'!$B:$B,'IS & BS Projections'!BD:BD) -> 0
B30: Other Operating Income/expense, Net | D30: USD '000s | E30: =SUMIF($P$1:$AI$1,E$1,$P30:$AI30) -> -630308 | F30: =SUMIF($P$1:$AI$1,F$1,$P30:$AI30) -> -717405 | G30: =SUMIF($P$1:$AI$1,G$1,$P30:$AI30) -> -10260 | H30: =SUMIF($P$1:$AI$1,H$1,$P30:$AI30) -> -28203 | I30: =SUMIF($P$1:$AI$1,I$1,$P30:$AI30) -> -363406 | J30: =SUMIFS($AJ30:$BC30,$AJ$1:$BC$1,J$1) -> -306627.45 | K30: =SUMIFS($AJ30:$BC30,$AJ$1:$BC$1,K$1) -> -349856.44 | L30: =SUMIFS($AJ30:$BC30,$AJ$1:$BC$1,L$1) -> -398624.15 | M30: =SUMIFS($AJ30:$BC30,$AJ$1:$BC$1,M$1) -> -472377.49 | N30: =SUMIFS($AJ30:$BC30,$AJ$1:$BC$1,N$1) -> -592293.71 | P30: -155887 | Q30: -282422 | R30: -118548 | S30: -73451 | T30: -258627 | U30: -422762 | V30: -62646 | W30: 26630 | X30: 33184 | Y30: -18866 | Z30: -3512 | AA30: -21066 | AB30: -2376 | AC30: -34383 | AD30: 8556 | AE30: 0 | AF30: 5899 | AG30: -308025 | AH30: -61280 | AI30: 0 | AJ30: =_xlfn.XLOOKUP($B30,'IS & BS Projections'!$B:$B,'IS & BS Projections'!AK:AK) -> -2703.8495 | AK30: =_xlfn.XLOOKUP($B30,'IS & BS Projections'!$B:$B,'IS & BS Projections'!AL:AL) -> -226078.7 | AL30: =_xlfn.XLOOKUP($B30,'IS & BS Projections'!$B:$B,'IS & BS Projections'!AM:AM) -> -77844.904 | AM30: =_xlfn.XLOOKUP($B30,'IS & BS Projections'!$B:$B,'IS & BS Projections'!AN:AN) -> 0 | AN30: =_xlfn.XLOOKUP($B30,'IS & BS Projections'!$B:$B,'IS & BS Projections'!AO:AO) -> -2821.6543 | AO30: =_xlfn.XLOOKUP($B30,'IS & BS Projections'!$B:$B,'IS & BS Projections'!AP:AP) -> -257205.39 | AP30: =_xlfn.XLOOKUP($B30,'IS & BS Projections'!$B:$B,'IS & BS Projections'!AQ:AQ) -> -89829.394 | AQ30: =_xlfn.XLOOKUP($B30,'IS & BS Projections'!$B:$B,'IS & BS Projections'!AR:AR) -> 0 | AR30: =_xlfn.XLOOKUP($B30,'IS & BS Projections'!$B:$B,'IS & BS Projections'!AS:AS) -> -3071.5494 | AS30: =_xlfn.XLOOKUP($B30,'IS & BS Projections'!$B:$B,'IS & BS Projections'!AT:AT) -> -294326.2 | AT30: =_xlfn.XLOOKUP($B30,'IS & BS Projections'!$B:$B,'IS & BS Projections'!AU:AU) -> -101226.39 | AU30: =_xlfn.XLOOKUP($B30,'IS & BS Projections'!$B:$B,'IS & BS Projections'!AV:AV) -> 0 | AV30: =_xlfn.XLOOKUP($B30,'IS & BS Projections'!$B:$B,'IS & BS Projections'!AW:AW) -> -3391.3709 | AW30: =_xlfn.XLOOKUP($B30,'IS & BS Projections'!$B:$B,'IS & BS Projections'!AX:AX) -> -350047.05 | AX30: =_xlfn.XLOOKUP($B30,'IS & BS Projections'!$B:$B,'IS & BS Projections'!AY:AY) -> -118939.06 | AY30: =_xlfn.XLOOKUP($B30,'IS & BS Projections'!$B:$B,'IS & BS Projections'!AZ:AZ) -> 0 | AZ30: =_xlfn.XLOOKUP($B30,'IS & BS Projections'!$B:$B,'IS & BS Projections'!BA:BA) -> -3896.4673 | BA30: =_xlfn.XLOOKUP($B30,'IS & BS Projections'!$B:$B,'IS & BS Projections'!BB:BB) -> -440189.74 | BB30: =_xlfn.XLOOKUP($B30,'IS & BS Projections'!$B:$B,'IS & BS Projections'!BC:BC) -> -148207.51 | BC30: =_xlfn.XLOOKUP($B30,'IS & BS Projections'!$B:$B,'IS & BS Projections'!BD:BD) -> 0
B31: Ther Operating Income and Expenses, Net | D31: USD '000s | E31: =SUMIF($P$1:$AI$1,E$1,$P31:$AI31) -> 0 | F31: =SUMIF($P$1:$AI$1,F$1,$P31:$AI31) -> 0 | G31: =SUMIF($P$1:$AI$1,G$1,$P31:$AI31) -> 0 | H31: =SUMIF($P$1:$AI$1,H$1,$P31:$AI31) -> 20270 | I31: =SUMIF($P$1:$AI$1,I$1,$P31:$AI31) -> 7280 | J31: =SUMIFS($AJ31:$BC31,$AJ$1:$BC$1,J$1) -> 0 | K31: =SUMIFS($AJ31:$BC31,$AJ$1:$BC$1,K$1) -> 0 | L31: =SUMIFS($AJ31:$BC31,$AJ$1:$BC$1,L$1) -> 0 | M31: =SUMIFS($AJ31:$BC31,$AJ$1:$BC$1,M$1) -> 0 | N31: =SUMIFS($AJ31:$BC31,$AJ$1:$BC$1,N$1) -> 0 | P31: 0 | Q31: 0 | R31: 0 | S31: 0 | T31: 0 | U31: 0 | V31: 0 | W31: 0 | X31: 0 | Y31: 0 | Z31: 0 | AA31: 0 | AB31: 0 | AC31: 0 | AD31: 0 | AE31: 20270 | AF31: 0 | AG31: 0 | AH31: 0 | AI31: 7280 | AJ31: =_xlfn.XLOOKUP($B31,'IS & BS Projections'!$B:$B,'IS & BS Projections'!AK:AK) -> 0 | AK31: =_xlfn.XLOOKUP($B31,'IS & BS Projections'!$B:$B,'IS & BS Projections'!AL:AL) -> 0 | AL31: =_xlfn.XLOOKUP($B31,'IS & BS Projections'!$B:$B,'IS & BS Projections'!AM:AM) -> 0 | AM31: =_xlfn.XLOOKUP($B31,'IS & BS Projections'!$B:$B,'IS & BS Projections'!AN:AN) -> 0 | AN31: =_xlfn.XLOOKUP($B31,'IS & BS Projections'!$B:$B,'IS & BS Projections'!AO:AO) -> 0 | AO31: =_xlfn.XLOOKUP($B31,'IS & BS Projections'!$B:$B,'IS & BS Projections'!AP:AP) -> 0 | AP31: =_xlfn.XLOOKUP($B31,'IS & BS Projections'!$B:$B,'IS & BS Projections'!AQ:AQ) -> 0 | AQ31: =_xlfn.XLOOKUP($B31,'IS & BS Projections'!$B:$B,'IS & BS Projections'!AR:AR) -> 0 | AR31: =_xlfn.XLOOKUP($B31,'IS & BS Projections'!$B:$B,'IS & BS Projections'!AS:AS) -> 0 | AS31: =_xlfn.XLOOKUP($B31,'IS & BS Projections'!$B:$B,'IS & BS Projections'!AT:AT) -> 0 | AT31: =_xlfn.XLOOKUP($B31,'IS & BS Projections'!$B:$B,'IS & BS Projections'!AU:AU) -> 0 | AU31: =_xlfn.XLOOKUP($B31,'IS & BS Projections'!$B:$B,'IS & BS Projections'!AV:AV) -> 0 | AV31: =_xlfn.XLOOKUP($B31,'IS & BS Projections'!$B:$B,'IS & BS Projections'!AW:AW) -> 0 | AW31: =_xlfn.XLOOKUP($B31,'IS & BS Projections'!$B:$B,'IS & BS Projections'!AX:AX) -> 0 | AX31: =_xlfn.XLOOKUP($B31,'IS & BS Projections'!$B:$B,'IS & BS Projections'!AY:AY) -> 0 | AY31: =_xlfn.XLOOKUP($B31,'IS & BS Projections'!$B:$B,'IS & BS Projections'!AZ:AZ) -> 0 | AZ31: =_xlfn.XLOOKUP($B31,'IS & BS Projections'!$B:$B,'IS & BS Projections'!BA:BA) -> 0 | BA31: =_xlfn.XLOOKUP($B31,'IS & BS Projections'!$B:$B,'IS & BS Projections'!BB:BB) -> 0 | BB31: =_xlfn.XLOOKUP($B31,'IS & BS Projections'!$B:$B,'IS & BS Projections'!BC:BC) -> 0 | BC31: =_xlfn.XLOOKUP($B31,'IS & BS Projections'!$B:$B,'IS & BS Projections'!BD:BD) -> 0
B32: Total OPEX | D32: USD '000s | E32: =SUM(E25:E31) -> -4762875 | F32: =SUM(F25:F31) -> -5784314 | G32: =SUM(G25:G31) -> -3001892 | H32: =SUM(H25:H31) -> -4328593 | I32: =SUM(I25:I31) -> -5725180 | J32: =SUM(J25:J31) -> -5573204.9 | K32: =SUM(K25:K31) -> -6235730.4 | L32: =SUM(L25:L31) -> -6970927.8 | ... N32: =SUM(N25:N31) -> -9906571.7 | P32: =SUM(P25:P31) -> -813399 | Q32: =SUM(Q25:Q31) -> -1353237 | R32: =SUM(R25:R31) -> -1020100 | S32: =SUM(S25:S31) -> -1576139 | T32: =SUM(T25:T31) -> -1720899 | U32: =SUM(U25:U31) -> -1810261 | V32: =SUM(V25:V31) -> -1135905 | W32: =SUM(W25:W31) -> -1117249 | ... BC32: =SUM(BC25:BC31) -> -2144658.7
B34: Asset Write-downs | D34: USD '000s | E34: =SUMIF($P$1:$AI$1,E$1,$P34:$AI34) -> 0 | F34: =SUMIF($P$1:$AI$1,F$1,$P34:$AI34) -> -79399 | G34: =SUMIF($P$1:$AI$1,G$1,$P34:$AI34) -> 0 | H34: =SUMIF($P$1:$AI$1,H$1,$P34:$AI34) -> 0 | I34: =SUMIF($P$1:$AI$1,I$1,$P34:$AI34) -> 0 | J34: =SUMIFS($AJ34:$BC34,$AJ$1:$BC$1,J$1) -> 0 | K34: =SUMIFS($AJ34:$BC34,$AJ$1:$BC$1,K$1) -> 0 | L34: =SUMIFS($AJ34:$BC34,$AJ$1:$BC$1,L$1) -> 0 | M34: =SUMIFS($AJ34:$BC34,$AJ$1:$BC$1,M$1) -> 0 | N34: =SUMIFS($AJ34:$BC34,$AJ$1:$BC$1,N$1) -> 0 | P34: 0 | Q34: 0 | R34: 0 | S34: 0 | T34: 0 | U34: 0 | V34: -12150 | W34: -67249 | X34: 0 | Y34: 0 | Z34: 0 | AA34: 0 | AB34: 0 | AC34: 0 | AD34: 0 | AE34: 0 | AF34: 0 | AG34: 0 | AH34: 0 | AI34: 0 | AJ34: =_xlfn.XLOOKUP($B34,'IS & BS Projections'!$B:$B,'IS & BS Projections'!AK:AK) -> 0 | AK34: =_xlfn.XLOOKUP($B34,'IS & BS Projections'!$B:$B,'IS & BS Projections'!AL:AL) -> 0 | AL34: =_xlfn.XLOOKUP($B34,'IS & BS Projections'!$B:$B,'IS & BS Projections'!AM:AM) -> 0 | AM34: =_xlfn.XLOOKUP($B34,'IS & BS Projections'!$B:$B,'IS & BS Projections'!AN:AN) -> 0 | AN34: =_xlfn.XLOOKUP($B34,'IS & BS Projections'!$B:$B,'IS & BS Projections'!AO:AO) -> 0 | AO34: =_xlfn.XLOOKUP($B34,'IS & BS Projections'!$B:$B,'IS & BS Projections'!AP:AP) -> 0 | AP34: =_xlfn.XLOOKUP($B34,'IS & BS Projections'!$B:$B,'IS & BS Projections'!AQ:AQ) -> 0 | AQ34: =_xlfn.XLOOKUP($B34,'IS & BS Projections'!$B:$B,'IS & BS Projections'!AR:AR) -> 0 | AR34: =_xlfn.XLOOKUP($B34,'IS & BS Projections'!$B:$B,'IS & BS Projections'!AS:AS) -> 0 | AS34: =_xlfn.XLOOKUP($B34,'IS & BS Projections'!$B:$B,'IS & BS Projections'!AT:AT) -> 0 | AT34: =_xlfn.XLOOKUP($B34,'IS & BS Projections'!$B:$B,'IS & BS Projections'!AU:AU) -> 0 | AU34: =_xlfn.XLOOKUP($B34,'IS & BS Projections'!$B:$B,'IS & BS Projections'!AV:AV) -> 0 | AV34: =_xlfn.XLOOKUP($B34,'IS & BS Projections'!$B:$B,'IS & BS Projections'!AW:AW) -> 0 | AW34: =_xlfn.XLOOKUP($B34,'IS & BS Projections'!$B:$B,'IS & BS Projections'!AX:AX) -> 0 | AX34: =_xlfn.XLOOKUP($B34,'IS & BS Projections'!$B:$B,'IS & BS Projections'!AY:AY) -> 0 | AY34: =_xlfn.XLOOKUP($B34,'IS & BS Projections'!$B:$B,'IS & BS Projections'!AZ:AZ) -> 0 | AZ34: =_xlfn.XLOOKUP($B34,'IS & BS Projections'!$B:$B,'IS & BS Projections'!BA:BA) -> 0 | BA34: =_xlfn.XLOOKUP($B34,'IS & BS Projections'!$B:$B,'IS & BS Projections'!BB:BB) -> 0 | BB34: =_xlfn.XLOOKUP($B34,'IS & BS Projections'!$B:$B,'IS & BS Projections'!BC:BC) -> 0 | BC34: =_xlfn.XLOOKUP($B34,'IS & BS Projections'!$B:$B,'IS & BS Projections'!BD:BD) -> 0
B35: Restructurings | D35: USD '000s | E35: =SUMIF($P$1:$AI$1,E$1,$P35:$AI35) -> 0 | F35: =SUMIF($P$1:$AI$1,F$1,$P35:$AI35) -> -40703 | G35: =SUMIF($P$1:$AI$1,G$1,$P35:$AI35) -> -142594 | H35: =SUMIF($P$1:$AI$1,H$1,$P35:$AI35) -> 0 | I35: =SUMIF($P$1:$AI$1,I$1,$P35:$AI35) -> 0 | J35: =SUMIFS($AJ35:$BC35,$AJ$1:$BC$1,J$1) -> 0 | K35: =SUMIFS($AJ35:$BC35,$AJ$1:$BC$1,K$1) -> 0 | L35: =SUMIFS($AJ35:$BC35,$AJ$1:$BC$1,L$1) -> 0 | M35: =SUMIFS($AJ35:$BC35,$AJ$1:$BC$1,M$1) -> 0 | N35: =SUMIFS($AJ35:$BC35,$AJ$1:$BC$1,N$1) -> 0 | P35: 0 | Q35: 0 | R35: 0 | S35: 0 | T35: 0 | U35: -42453 | V35: 1232 | W35: 518 | X35: -144489 | Y35: 1035 | Z35: 860 | AA35: 0 | AB35: 0 | AC35: 0 | AD35: 0 | AE35: 0 | AF35: 0 | AG35: 0 | AH35: 0 | AI35: 0 | AJ35: =_xlfn.XLOOKUP($B35,'IS & BS Projections'!$B:$B,'IS & BS Projections'!AK:AK) -> 0 | AK35: =_xlfn.XLOOKUP($B35,'IS & BS Projections'!$B:$B,'IS & BS Projections'!AL:AL) -> 0 | AL35: =_xlfn.XLOOKUP($B35,'IS & BS Projections'!$B:$B,'IS & BS Projections'!AM:AM) -> 0 | AM35: =_xlfn.XLOOKUP($B35,'IS & BS Projections'!$B:$B,'IS & BS Projections'!AN:AN) -> 0 | AN35: =_xlfn.XLOOKUP($B35,'IS & BS Projections'!$B:$B,'IS & BS Projections'!AO:AO) -> 0 | AO35: =_xlfn.XLOOKUP($B35,'IS & BS Projections'!$B:$B,'IS & BS Projections'!AP:AP) -> 0 | AP35: =_xlfn.XLOOKUP($B35,'IS & BS Projections'!$B:$B,'IS & BS Projections'!AQ:AQ) -> 0 | AQ35: =_xlfn.XLOOKUP($B35,'IS & BS Projections'!$B:$B,'IS & BS Projections'!AR:AR) -> 0 | AR35: =_xlfn.XLOOKUP($B35,'IS & BS Projections'!$B:$B,'IS & BS Projections'!AS:AS) -> 0 | AS35: =_xlfn.XLOOKUP($B35,'IS & BS Projections'!$B:$B,'IS & BS Projections'!AT:AT) -> 0 | AT35: =_xlfn.XLOOKUP($B35,'IS & BS Projections'!$B:$B,'IS & BS Projections'!AU:AU) -> 0 | AU35: =_xlfn.XLOOKUP($B35,'IS & BS Projections'!$B:$B,'IS & BS Projections'!AV:AV) -> 0 | AV35: =_xlfn.XLOOKUP($B35,'IS & BS Projections'!$B:$B,'IS & BS Projections'!AW:AW) -> 0 | AW35: =_xlfn.XLOOKUP($B35,'IS & BS Projections'!$B:$B,'IS & BS Projections'!AX:AX) -> 0 | AX35: =_xlfn.XLOOKUP($B35,'IS & BS Projections'!$B:$B,'IS & BS Projections'!AY:AY) -> 0 | AY35: =_xlfn.XLOOKUP($B35,'IS & BS Projections'!$B:$B,'IS & BS Projections'!AZ:AZ) -> 0 | AZ35: =_xlfn.XLOOKUP($B35,'IS & BS Projections'!$B:$B,'IS & BS Projections'!BA:BA) -> 0 | BA35: =_xlfn.XLOOKUP($B35,'IS & BS Projections'!$B:$B,'IS & BS Projections'!BB:BB) -> 0 | BB35: =_xlfn.XLOOKUP($B35,'IS & BS Projections'!$B:$B,'IS & BS Projections'!BC:BC) -> 0 | BC35: =_xlfn.XLOOKUP($B35,'IS & BS Projections'!$B:$B,'IS & BS Projections'!BD:BD) -> 0
B36: Interest Expense | D36: USD '000s | E36: =SUMIF($P$1:$AI$1,E$1,$P36:$AI36) -> -29160 | F36: =SUMIF($P$1:$AI$1,F$1,$P36:$AI36) -> -88901 | G36: =SUMIF($P$1:$AI$1,G$1,$P36:$AI36) -> -82766 | H36: =SUMIF($P$1:$AI$1,H$1,$P36:$AI36) -> -80645 | I36: =SUMIF($P$1:$AI$1,I$1,$P36:$AI36) -> -85413 | J36: =SUMIFS($AJ36:$BC36,$AJ$1:$BC$1,J$1) -> -84947.393 | K36: =SUMIFS($AJ36:$BC36,$AJ$1:$BC$1,K$1) -> -78709.629 | L36: =SUMIFS($AJ36:$BC36,$AJ$1:$BC$1,L$1) -> -78709.629 | M36: =SUMIFS($AJ36:$BC36,$AJ$1:$BC$1,M$1) -> -43009.629 | N36: =SUMIFS($AJ36:$BC36,$AJ$1:$BC$1,N$1) -> -34280.879 | P36: 0 | Q36: -748 | R36: -6972 | S36: -21440 | T36: -22138 | U36: -23656 | V36: -21507 | W36: -21600 | X36: -21536 | Y36: -21672 | Z36: -20821 | AA36: -18737 | AB36: -19071 | AC36: -20507 | AD36: -20530 | AE36: -20537 | AF36: -20511 | AG36: -20535 | AH36: -21774 | AI36: -22593 | AJ36: ='D&E Schedule'!AC109 -> -22796.289 | AK36: ='D&E Schedule'!AD109 -> -22796.289 | AL36: ='D&E Schedule'!AE109 -> -19677.407 | AM36: ='D&E Schedule'!AF109 -> -19677.407 | AN36: ='D&E Schedule'!AG109 -> -19677.407 | AO36: ='D&E Schedule'!AH109 -> -19677.407 | AP36: ='D&E Schedule'!AI109 -> -19677.407 | AQ36: ='D&E Schedule'!AJ109 -> -19677.407 | ... BC36: ='D&E Schedule'!AV109 -> -7700.5322
B37: Other Income/expense-net | D37: USD '000s | E37: =SUMIF($P$1:$AI$1,E$1,$P37:$AI37) -> -20463 | F37: =SUMIF($P$1:$AI$1,F$1,$P37:$AI37) -> -265473 | G37: =SUMIF($P$1:$AI$1,G$1,$P37:$AI37) -> 167583 | H37: =SUMIF($P$1:$AI$1,H$1,$P37:$AI37) -> 29074 | I37: =SUMIF($P$1:$AI$1,I$1,$P37:$AI37) -> 700894 | J37: =SUMIFS($AJ37:$BC37,$AJ$1:$BC$1,J$1) -> -29529.68 | K37: =SUMIFS($AJ37:$BC37,$AJ$1:$BC$1,K$1) -> -33519.545 | L37: =SUMIFS($AJ37:$BC37,$AJ$1:$BC$1,L$1) -> -37673.1 | M37: =SUMIFS($AJ37:$BC37,$AJ$1:$BC$1,M$1) -> -43933.772 | N37: =SUMIFS($AJ37:$BC37,$AJ$1:$BC$1,N$1) -> -54245.35 | P37: 8953 | Q37: -5096 | R37: -13976 | S37: -10344 | T37: -32844 | U37: -172524 | V37: -65699 | W37: 5594 | X37: -20265 | Y37: 16564 | Z37: 135307 | AA37: 35977 | AB37: 45605 | AC37: -63827 | AD37: 40105 | AE37: 7191 | AF37: -6188 | AG37: 1506905 | AH37: -380518 | AI37: -419305 | AJ37: =_xlfn.XLOOKUP($B37,'IS & BS Projections'!$B:$B,'IS & BS Projections'!AK:AK) -> -5668.5546 | AK37: =_xlfn.XLOOKUP($B37,'IS & BS Projections'!$B:$B,'IS & BS Projections'!AL:AL) -> -4079.346 | AL37: =_xlfn.XLOOKUP($B37,'IS & BS Projections'!$B:$B,'IS & BS Projections'!AM:AM) -> -25288.839 | AM37: =_xlfn.XLOOKUP($B37,'IS & BS Projections'!$B:$B,'IS & BS Projections'!AN:AN) -> 5507.0597 | AN37: =_xlfn.XLOOKUP($B37,'IS & BS Projections'!$B:$B,'IS & BS Projections'!AO:AO) -> -5915.5295 | AO37: =_xlfn.XLOOKUP($B37,'IS & BS Projections'!$B:$B,'IS & BS Projections'!AP:AP) -> -4640.9935 | AP37: =_xlfn.XLOOKUP($B37,'IS & BS Projections'!$B:$B,'IS & BS Projections'!AQ:AQ) -> -29182.143 | AQ37: =_xlfn.XLOOKUP($B37,'IS & BS Projections'!$B:$B,'IS & BS Projections'!AR:AR) -> 6219.1209 | AR37: =_xlfn.XLOOKUP($B37,'IS & BS Projections'!$B:$B,'IS & BS Projections'!AS:AS) -> -6439.4284 | AS37: =_xlfn.XLOOKUP($B37,'IS & BS Projections'!$B:$B,'IS & BS Projections'!AT:AT) -> -5310.7985 | AT37: =_xlfn.XLOOKUP($B37,'IS & BS Projections'!$B:$B,'IS & BS Projections'!AU:AU) -> -32884.594 | AU37: =_xlfn.XLOOKUP($B37,'IS & BS Projections'!$B:$B,'IS & BS Projections'!AV:AV) -> 6961.7209 | AV37: =_xlfn.XLOOKUP($B37,'IS & BS Projections'!$B:$B,'IS & BS Projections'!AW:AW) -> -7109.9263 | AW37: =_xlfn.XLOOKUP($B37,'IS & BS Projections'!$B:$B,'IS & BS Projections'!AX:AX) -> -6316.221 | AX37: =_xlfn.XLOOKUP($B37,'IS & BS Projections'!$B:$B,'IS & BS Projections'!AY:AY) -> -38638.765 | AY37: =_xlfn.XLOOKUP($B37,'IS & BS Projections'!$B:$B,'IS & BS Projections'!AZ:AZ) -> 8131.1396 | AZ37: =_xlfn.XLOOKUP($B37,'IS & BS Projections'!$B:$B,'IS & BS Projections'!BA:BA) -> -8168.8486 | BA37: =_xlfn.XLOOKUP($B37,'IS & BS Projections'!$B:$B,'IS & BS Projections'!BB:BB) -> -7942.7484 | BB37: =_xlfn.XLOOKUP($B37,'IS & BS Projections'!$B:$B,'IS & BS Projections'!BC:BC) -> -48146.966 | BC37: =_xlfn.XLOOKUP($B37,'IS & BS Projections'!$B:$B,'IS & BS Projections'!BD:BD) -> 10013.213
B38: Gain/Loss on Crypto assets held for investment, net | D38: USD '000s | E38: =SUMIF($P$1:$AI$1,E$1,$P38:$AI38) -> 0 | F38: =SUMIF($P$1:$AI$1,F$1,$P38:$AI38) -> 0 | G38: =SUMIF($P$1:$AI$1,G$1,$P38:$AI38) -> 0 | H38: =SUMIF($P$1:$AI$1,H$1,$P38:$AI38) -> 687055 | I38: =SUMIF($P$1:$AI$1,I$1,$P38:$AI38) -> -528857 | J38: =SUMIFS($AJ38:$BC38,$AJ$1:$BC$1,J$1) -> 0 | K38: =SUMIFS($AJ38:$BC38,$AJ$1:$BC$1,K$1) -> 0 | L38: =SUMIFS($AJ38:$BC38,$AJ$1:$BC$1,L$1) -> 0 | M38: =SUMIFS($AJ38:$BC38,$AJ$1:$BC$1,M$1) -> 0 | N38: =SUMIFS($AJ38:$BC38,$AJ$1:$BC$1,N$1) -> 0 | P38: 0 | Q38: 0 | R38: 0 | S38: 0 | T38: 0 | U38: 0 | V38: 0 | W38: 0 | X38: 0 | Y38: 0 | Z38: 0 | AA38: 0 | AB38: 650429 | AC38: -319020 | AD38: -120507 | AE38: 476153 | AF38: -596651 | AG38: 362053 | AH38: 423903 | AI38: -718162 | AJ38: =_xlfn.XLOOKUP($B38,'IS & BS Projections'!$B:$B,'IS & BS Projections'!AK:AK) -> 0 | AK38: =_xlfn.XLOOKUP($B38,'IS & BS Projections'!$B:$B,'IS & BS Projections'!AL:AL) -> 0 | AL38: =_xlfn.XLOOKUP($B38,'IS & BS Projections'!$B:$B,'IS & BS Projections'!AM:AM) -> 0 | AM38: =_xlfn.XLOOKUP($B38,'IS & BS Projections'!$B:$B,'IS & BS Projections'!AN:AN) -> 0 | AN38: =_xlfn.XLOOKUP($B38,'IS & BS Projections'!$B:$B,'IS & BS Projections'!AO:AO) -> 0 | AO38: =_xlfn.XLOOKUP($B38,'IS & BS Projections'!$B:$B,'IS & BS Projections'!AP:AP) -> 0 | AP38: =_xlfn.XLOOKUP($B38,'IS & BS Projections'!$B:$B,'IS & BS Projections'!AQ:AQ) -> 0 | AQ38: =_xlfn.XLOOKUP($B38,'IS & BS Projections'!$B:$B,'IS & BS Projections'!AR:AR) -> 0 | AR38: =_xlfn.XLOOKUP($B38,'IS & BS Projections'!$B:$B,'IS & BS Projections'!AS:AS) -> 0 | AS38: =_xlfn.XLOOKUP($B38,'IS & BS Projections'!$B:$B,'IS & BS Projections'!AT:AT) -> 0 | AT38: =_xlfn.XLOOKUP($B38,'IS & BS Projections'!$B:$B,'IS & BS Projections'!AU:AU) -> 0 | AU38: =_xlfn.XLOOKUP($B38,'IS & BS Projections'!$B:$B,'IS & BS Projections'!AV:AV) -> 0 | AV38: =_xlfn.XLOOKUP($B38,'IS & BS Projections'!$B:$B,'IS & BS Projections'!AW:AW) -> 0 | AW38: =_xlfn.XLOOKUP($B38,'IS & BS Projections'!$B:$B,'IS & BS Projections'!AX:AX) -> 0 | AX38: =_xlfn.XLOOKUP($B38,'IS & BS Projections'!$B:$B,'IS & BS Projections'!AY:AY) -> 0 | AY38: =_xlfn.XLOOKUP($B38,'IS & BS Projections'!$B:$B,'IS & BS Projections'!AZ:AZ) -> 0 | AZ38: =_xlfn.XLOOKUP($B38,'IS & BS Projections'!$B:$B,'IS & BS Projections'!BA:BA) -> 0 | BA38: =_xlfn.XLOOKUP($B38,'IS & BS Projections'!$B:$B,'IS & BS Projections'!BB:BB) -> 0 | BB38: =_xlfn.XLOOKUP($B38,'IS & BS Projections'!$B:$B,'IS & BS Projections'!BC:BC) -> 0 | BC38: =_xlfn.XLOOKUP($B38,'IS & BS Projections'!$B:$B,'IS & BS Projections'!BD:BD) -> 0
B40: Earnings Before Taxes (EBT) | D40: USD '000s | E40: =SUM(E32,E34:E38,E22) -> 3026947 | F40: =SUM(F32,F34:F38,F22) -> -3064582 | G40: =SUM(G32,G34:G38,G22) -> -76845 | H40: =SUM(H32,H34:H38,H22) -> 2870919 | I40: =SUM(I32,I34:I38,I22) -> 1542769 | J40: =SUM(J32,J34:J38,J22) -> 2072837.9 | K40: =SUM(K32,K34:K38,K22) -> 2329703.4 | L40: =SUM(L32,L34:L38,L22) -> 2637552.3 | ... N40: =SUM(N32,N34:N38,N22) -> 3845617.1 | P40: =SUM(P32,P34:P38,P22) -> 996666 | Q40: =SUM(Q32,Q34:Q38,Q22) -> 868881 | R40: =SUM(R32,R34:R38,R22) -> 270860 | S40: =SUM(S32,S34:S38,S22) -> 890540 | T40: =SUM(T32,T34:T38,T22) -> -609445 | U40: =SUM(U32,U34:U38,U22) -> -1240569 | V40: =SUM(V32,V34:V38,V22) -> -643690 | W40: =SUM(W32,W34:W38,W22) -> -570878 | ... BC40: =SUM(BC32,BC34:BC38,BC22) -> 1020828.1
B41: EBT Margin | D41: % | E41: =E40/E$22 -> 0.38611751 | F41: =F40/F$22 -> -0.95941842 | G41: =G40/G$22 -> -0.025762499 | H41: =H40/H$22 -> 0.43737153 | I41: =I40/I$22 -> 0.21483069 | J41: =J40/J$22 -> 0.26710039 | K41: =K40/K$22 -> 0.26847129 | L41: =L40/L$22 -> 0.27121743 | ... N41: =N40/N$22 -> 0.27784815 | P41: =P40/P$22 -> 0.55336148 | Q41: =Q40/Q$22 -> 0.38998915 | R41: =R40/R$22 -> 0.20646265 | S41: =S40/S$22 -> 0.35643514 | T41: =T40/T$22 -> -0.52248473 | U41: =U40/U$22 -> -1.5347404 | V41: =V40/V$22 -> -1.0903735 | W41: =W40/W$22 -> -0.90744038 | ... BC41: =BC40/BC$22 -> 0.32272271
B43: Earnings Before Interest & Taxes (EBIT) | D43: USD '000s | E43: =E40-E36 -> 3056107 | F43: =F40-F36 -> -2975681 | G43: =G40-G36 -> 5921 | H43: =H40-H36 -> 2951564 | I43: =I40-I36 -> 1628182 | J43: =J40-J36 -> 2157785.3 | K43: =K40-K36 -> 2408413 | L43: =L40-L36 -> 2716261.9 | ... N43: =N40-N36 -> 3879897.9 | P43: =SUM(P35,P37:P41,P25) -> 771553.55 | Q43: =SUM(Q35,Q37:Q41,Q25) -> 528359.39 | R43: =SUM(R35,R37:R41,R25) -> 59633.206 | S43: =SUM(S35,S37:S41,S25) -> 379015.36 | T43: =SUM(T35,T37:T41,T25) -> -920115.52 | U43: =SUM(U35,U37:U41,U25) -> -1622734.5 | V43: =SUM(V35,V37:V41,V25) -> -810034.09 | W43: =SUM(W35,W37:W41,W25) -> -647757.91 | ... BC43: =SUM(BC35,BC37:BC41,BC25) -> 613560.38
B44: EBIT Margin | D44: % | E44: =E43/E$22 -> 0.38983716 | F44: =F43/F$22 -> -0.93158648 | G44: =G43/G$22 -> 0.0019850316 | H44: =H43/H$22 -> 0.44965744 | I44: =I43/I$22 -> 0.22672446 | J44: =J43/J$22 -> 0.27804649 | K44: =K43/K$22 -> 0.27754166 | L44: =L43/L$22 -> 0.27931108 | ... N44: =N43/N$22 -> 0.28032496 | P44: =P43/P$22 -> 0.42837622 | Q44: =Q43/Q$22 -> 0.23714919 | R44: =R43/R$22 -> 0.045455326 | S44: =S43/S$22 -> 0.15169941 | T44: =T43/T$22 -> -0.78882641 | U44: =U43/U$22 -> -2.0075273 | V44: =V43/V$22 -> -1.3721507 | W44: =W43/W$22 -> -1.029645 | ... BC44: =BC43/BC$22 -> 0.19396984
B46: Earnings Before Interest, Taxes, Depreciation & Amortization (EBITDA) | D46: USD '000s | E46: =E43+SUM(E142:E143) -> 3119758 | F46: =F43+SUM(F142:F143) -> -2821612 | G46: =G43+SUM(G142:G143) -> 145563 | H46: =H43+SUM(H142:H143) -> 3079082 | I46: =I43+SUM(I142:I143) -> 1816610 | J46: =J43+SUM(J142:J143) -> 2422168.6 | K46: =K43+SUM(K142:K143) -> 2709341.9 | L46: =L43+SUM(L142:L143) -> 3058146.7 | ... N46: =N43+SUM(N142:N143) -> 4327638.2 | P46: =P43+SUM(P142:P143) -> 782475.55 | Q46: =Q43+SUM(Q142:Q143) -> 540971.39 | R46: =R43+SUM(R142:R143) -> 76732.206 | S46: =S43+SUM(S142:S143) -> 402033.36 | T46: =T43+SUM(T142:T143) -> -888535.52 | U46: =U43+SUM(U142:U143) -> -1580707.5 | V46: =V43+SUM(V142:V143) -> -769920.09 | W46: =W43+SUM(W142:W143) -> -607409.91 | ... BC46: =BC43+SUM(BC142:BC143) -> 725495.46
B47: EBITDA Margin | D47: % | E47: =E46/E$22 -> 0.39795649 | F47: =F46/F$22 -> -0.88335262 | G47: =G46/G$22 -> 0.048800399 | H47: =H46/H$22 -> 0.46908423 | I47: =I46/I$22 -> 0.25296307 | J47: =J46/J$22 -> 0.31211421 | K47: =K46/K$22 -> 0.31222023 | L47: =L46/L$22 -> 0.31446682 | ... N47: =N46/N$22 -> 0.31267447 | P47: =P46/P$22 -> 0.43444025 | Q47: =Q46/Q$22 -> 0.24280997 | R47: =R46/R$22 -> 0.058489015 | S47: =S46/S$22 -> 0.16091227 | T47: =T46/T$22 -> -0.76175249 | U47: =U46/U$22 -> -1.9555346 | V47: =V46/V$22 -> -1.3041999 | W47: =W46/W$22 -> -0.96550975 | ... BC47: =BC46/BC$22 -> 0.22935679
B49: Provision For Income Tax | D49: USD '000s | E49: =SUMIF($P$1:$AI$1,E$1,$P49:$AI49) -> 597173 | F49: =SUMIF($P$1:$AI$1,F$1,$P49:$AI49) -> 439633 | G49: =SUMIF($P$1:$AI$1,G$1,$P49:$AI49) -> 171716 | H49: =SUMIF($P$1:$AI$1,H$1,$P49:$AI49) -> -363578 | I49: =SUMIF($P$1:$AI$1,I$1,$P49:$AI49) -> -261738 | J49: =SUMIFS($AJ49:$BC49,$AJ$1:$BC$1,J$1) -> 155144.09 | K49: =SUMIFS($AJ49:$BC49,$AJ$1:$BC$1,K$1) -> 177856.93 | L49: =SUMIFS($AJ49:$BC49,$AJ$1:$BC$1,L$1) -> 203069.91 | M49: =SUMIFS($AJ49:$BC49,$AJ$1:$BC$1,M$1) -> 241719.07 | N49: =SUMIFS($AJ49:$BC49,$AJ$1:$BC$1,N$1) -> 304353.49 | P49: -225203 | Q49: 737468 | R49: 135240 | S49: -50332 | T49: 179786 | U49: 146915 | V49: 99055 | W49: 13877 | X49: 86780 | Y49: -18722 | Z49: -36926 | AA49: 140584 | AB49: -261179 | AC49: 96387 | AD49: 6914 | AE49: -205700 | AF49: -16848 | AG49: -394873 | AH49: -69591 | AI49: 219574 | AJ49: =_xlfn.XLOOKUP($B49,'IS & BS Projections'!$B:$B,'IS & BS Projections'!AK:AK) -> -15433.712 | AK49: =_xlfn.XLOOKUP($B49,'IS & BS Projections'!$B:$B,'IS & BS Projections'!AL:AL) -> 118585.28 | AL49: =_xlfn.XLOOKUP($B49,'IS & BS Projections'!$B:$B,'IS & BS Projections'!AM:AM) -> 13618.277 | AM49: =_xlfn.XLOOKUP($B49,'IS & BS Projections'!$B:$B,'IS & BS Projections'!AN:AN) -> 38374.242 | AN49: =_xlfn.XLOOKUP($B49,'IS & BS Projections'!$B:$B,'IS & BS Projections'!AO:AO) -> -16106.147 | AO49: =_xlfn.XLOOKUP($B49,'IS & BS Projections'!$B:$B,'IS & BS Projections'!AP:AP) -> 134912.2 | AP49: =_xlfn.XLOOKUP($B49,'IS & BS Projections'!$B:$B,'IS & BS Projections'!AQ:AQ) -> 15714.858 | AQ49: =_xlfn.XLOOKUP($B49,'IS & BS Projections'!$B:$B,'IS & BS Projections'!AR:AR) -> 43336.02 | AR49: =_xlfn.XLOOKUP($B49,'IS & BS Projections'!$B:$B,'IS & BS Projections'!AS:AS) -> -17532.561 | AS49: =_xlfn.XLOOKUP($B49,'IS & BS Projections'!$B:$B,'IS & BS Projections'!AT:AT) -> 154383.21 | AT49: =_xlfn.XLOOKUP($B49,'IS & BS Projections'!$B:$B,'IS & BS Projections'!AU:AU) -> 17708.662 | AU49: =_xlfn.XLOOKUP($B49,'IS & BS Projections'!$B:$B,'IS & BS Projections'!AV:AV) -> 48510.599 | AV49: =_xlfn.XLOOKUP($B49,'IS & BS Projections'!$B:$B,'IS & BS Projections'!AW:AW) -> -19358.119 | AW49: =_xlfn.XLOOKUP($B49,'IS & BS Projections'!$B:$B,'IS & BS Projections'!AX:AX) -> 183610.53 | AX49: =_xlfn.XLOOKUP($B49,'IS & BS Projections'!$B:$B,'IS & BS Projections'!AY:AY) -> 20807.337 | AY49: =_xlfn.XLOOKUP($B49,'IS & BS Projections'!$B:$B,'IS & BS Projections'!AZ:AZ) -> 56659.331 | AZ49: =_xlfn.XLOOKUP($B49,'IS & BS Projections'!$B:$B,'IS & BS Projections'!BA:BA) -> -22241.235 | BA49: =_xlfn.XLOOKUP($B49,'IS & BS Projections'!$B:$B,'IS & BS Projections'!BB:BB) -> 230893.16 | BB49: =_xlfn.XLOOKUP($B49,'IS & BS Projections'!$B:$B,'IS & BS Projections'!BC:BC) -> 25927.592 | BC49: =_xlfn.XLOOKUP($B49,'IS & BS Projections'!$B:$B,'IS & BS Projections'!BD:BD) -> 69773.978
B51: Net Income | D51: USD '000s | E51: =SUM(E40,E49) -> 3624120 | F51: =SUM(F40,F49) -> -2624949 | G51: =SUM(G40,G49) -> 94871 | H51: =SUM(H40,H49) -> 2507341 | I51: =SUM(I40,I49) -> 1281031 | J51: =SUM(J40,J49) -> 2227982 | K51: =SUM(K40,K49) -> 2507560.3 | L51: =SUM(L40,L49) -> 2840622.2 | ... N51: =SUM(N40,N49) -> 4149970.6 | P51: =SUM(P40,P49) -> 771463 | Q51: =SUM(Q40,Q49) -> 1606349 | R51: =SUM(R40,R49) -> 406100 | S51: =SUM(S40,S49) -> 840208 | T51: =SUM(T40,T49) -> -429659 | U51: =SUM(U40,U49) -> -1093654 | V51: =SUM(V40,V49) -> -544635 | W51: =SUM(W40,W49) -> -557001 | ... BC51: =SUM(BC40,BC49) -> 1090602.1
B52: Net Income Margin | D52: % | E52: =E51/E$22 -> 0.46229293 | F52: =F51/F$22 -> -0.82178399 | G52: =G51/G$22 -> 0.031805765 | H52: =H51/H$22 -> 0.38198207 | I52: =I51/I$22 -> 0.17838365 | J52: =J51/J$22 -> 0.28709185 | K52: =K51/K$22 -> 0.28896724 | L52: =L51/L$22 -> 0.29209895 | ... N52: =N51/N$22 -> 0.29983787 | P52: =P51/P$22 -> 0.42832595 | Q52: =Q51/Q$22 -> 0.72099479 | R52: =R51/R$22 -> 0.30954915 | S52: =S51/S$22 -> 0.33628995 | T52: =T51/T$22 -> -0.36835197 | U52: =U51/U$22 -> -1.352988 | V52: =V51/V$22 -> -0.92258008 | W52: =W51/W$22 -> -0.88538216 | ... BC52: =BC51/BC$22 -> 0.34478092
A54: x | B54: Balance Sheet | D54: Units | E54: 21 | F54: =E54+1 -> 22 | G54: =F54+1 -> 23 | H54: =G54+1 -> 24 | I54: =H54+1 -> 25 | J54: =I54+1 -> 26 | K54: =J54+1 -> 27 | L54: =K54+1 -> 28 | M54: =L54+1 -> 29 | N54: =M54+1 -> 30 | P54: 44286 | Q54: 44377 | R54: 44469 | S54: 44561 | T54: 44651 | U54: 44742 | V54: 44834 | W54: 44926 | X54: 45016 | Y54: 45107 | Z54: 45199 | AA54: 45291 | AB54: 45382 | AC54: 45473 | AD54: 45565 | AE54: 45657 | AF54: 45747 | AG54: 45838 | AH54: 45930 | AI54: 46022 | AJ54: 46112 | AK54: 46203 | AL54: 46295 | AM54: 46387 | AN54: 46477 | AO54: 46568 | AP54: 46660 | AQ54: 46752 | AR54: 46843 | AS54: 46934 | AT54: 47026 | AU54: 47118 | AV54: 47208 | AW54: 47299 | AX54: 47391 | AY54: 47483 | AZ54: 47573 | BA54: 47664 | BB54: 47756 | BC54: 47848
B56: Assets
B58: Current Assets:
B59: Cash and Cash Equivalents | D59: USD '000s | E59: =S59 -> 7123478 | F59: =W59 -> 4425021 | G59: =AA59 -> 5139351 | H59: =AE59 -> 9308266 | I59: =AI59 -> 11285452 | J59: =AM59 -> 16507513 | K59: =AQ59 -> 18457012 | L59: =AU59 -> 19725501 | M59: =AY59 -> 20646417 | N59: =BC59 -> 21953778 | P59: 1983318 | Q59: 4365982 | R59: 6352775 | S59: 7123478 | T59: 6116388 | U59: 5682068 | V59: 5006584 | W59: 4425021 | X59: 5018409 | Y59: 5166733 | Z59: 5100799 | AA59: 5139351 | AB59: 6711400 | AC59: 7225535 | AD59: 7723806 | AE59: 9308266 | AF59: 8051169 | AG59: 7539388 | AH59: 8676275 | AI59: 11285452 | AJ59: =AJ208 -> 11810479 | AK59: =AK208 -> 17329814 | AL59: =AL208 -> 12853036 | AM59: =AM208 -> 16507513 | AN59: =AN208 -> 12462711 | AO59: =AO208 -> 19325574 | AP59: =AP208 -> 14124269 | AQ59: =AQ208 -> 18457012 | ... BC59: =BC208 -> 21953778 | BD59: =AI59-AJ59 -> -525027.2 | BE59: =IF(ISNUMBER(MATCH(BD59,$AJ$136:$AJ$1048576,0)),"YES","NO") -> NO
B60: Marketable Investments | D60: USD '000s | E60: =S60 -> 0 | F60: =W60 -> 0 | G60: =AA60 -> 0 | H60: =AE60 -> 0 | I60: =AI60 -> 309765 | J60: =AM60 -> 0 | K60: =AQ60 -> 0 | L60: =AU60 -> 0 | M60: =AY60 -> 0 | N60: =BC60 -> 0 | P60: 0 | Q60: 0 | R60: 0 | S60: 0 | T60: 0 | U60: 0 | V60: 0 | W60: 0 | X60: 0 | Y60: 0 | Z60: 0 | AA60: 0 | AB60: 0 | AC60: 0 | AD60: 0 | AE60: 0 | AF60: 0 | AG60: 0 | AH60: 1093395 | AI60: 309765 | AJ60: =_xlfn.XLOOKUP($B60,'IS & BS Projections'!$B:$B,'IS & BS Projections'!AK:AK) -> 0 | AK60: =_xlfn.XLOOKUP($B60,'IS & BS Projections'!$B:$B,'IS & BS Projections'!AL:AL) -> 0 | AL60: =_xlfn.XLOOKUP($B60,'IS & BS Projections'!$B:$B,'IS & BS Projections'!AM:AM) -> 0 | AM60: =_xlfn.XLOOKUP($B60,'IS & BS Projections'!$B:$B,'IS & BS Projections'!AN:AN) -> 0 | AN60: =_xlfn.XLOOKUP($B60,'IS & BS Projections'!$B:$B,'IS & BS Projections'!AO:AO) -> 0 | AO60: =_xlfn.XLOOKUP($B60,'IS & BS Projections'!$B:$B,'IS & BS Projections'!AP:AP) -> 0 | AP60: =_xlfn.XLOOKUP($B60,'IS & BS Projections'!$B:$B,'IS & BS Projections'!AQ:AQ) -> 0 | AQ60: =_xlfn.XLOOKUP($B60,'IS & BS Projections'!$B:$B,'IS & BS Projections'!AR:AR) -> 0 | AR60: =_xlfn.XLOOKUP($B60,'IS & BS Projections'!$B:$B,'IS & BS Projections'!AS:AS) -> 0 | AS60: =_xlfn.XLOOKUP($B60,'IS & BS Projections'!$B:$B,'IS & BS Projections'!AT:AT) -> 0 | AT60: =_xlfn.XLOOKUP($B60,'IS & BS Projections'!$B:$B,'IS & BS Projections'!AU:AU) -> 0 | AU60: =_xlfn.XLOOKUP($B60,'IS & BS Projections'!$B:$B,'IS & BS Projections'!AV:AV) -> 0 | AV60: =_xlfn.XLOOKUP($B60,'IS & BS Projections'!$B:$B,'IS & BS Projections'!AW:AW) -> 0 | AW60: =_xlfn.XLOOKUP($B60,'IS & BS Projections'!$B:$B,'IS & BS Projections'!AX:AX) -> 0 | AX60: =_xlfn.XLOOKUP($B60,'IS & BS Projections'!$B:$B,'IS & BS Projections'!AY:AY) -> 0 | AY60: =_xlfn.XLOOKUP($B60,'IS & BS Projections'!$B:$B,'IS & BS Projections'!AZ:AZ) -> 0 | AZ60: =_xlfn.XLOOKUP($B60,'IS & BS Projections'!$B:$B,'IS & BS Projections'!BA:BA) -> 0 | BA60: =_xlfn.XLOOKUP($B60,'IS & BS Projections'!$B:$B,'IS & BS Projections'!BB:BB) -> 0 | BB60: =_xlfn.XLOOKUP($B60,'IS & BS Projections'!$B:$B,'IS & BS Projections'!BC:BC) -> 0 | BC60: =_xlfn.XLOOKUP($B60,'IS & BS Projections'!$B:$B,'IS & BS Projections'!BD:BD) -> 0 | BD60: =AI60-AJ60 -> 309765 | BE60: =IF(ISNUMBER(MATCH(BD60,$AJ$136:$AJ$1048576,0)),"YES","NO") -> YES
B61: Accounts Receivable, Net of Allowance | D61: USD '000s | E61: =S61 -> 0 | F61: =W61 -> 0 | G61: =AA61 -> 0 | H61: =AE61 -> 0 | I61: =AI61 -> 0 | J61: =AM61 -> 0 | K61: =AQ61 -> 0 | L61: =AU61 -> 0 | M61: =AY61 -> 0 | N61: =BC61 -> 0 | P61: 0 | Q61: 0 | R61: 0 | S61: 0 | T61: 0 | U61: 0 | V61: 0 | W61: 0 | X61: 0 | Y61: 0 | Z61: 0 | AA61: 0 | AB61: 280357 | AC61: 236444 | AD61: 187004 | AE61: 0 | AF61: 245112 | AG61: 222996 | AH61: 308423 | AI61: 0 | AJ61: =_xlfn.XLOOKUP($B61,'IS & BS Projections'!$B:$B,'IS & BS Projections'!AK:AK) -> 0 | AK61: =_xlfn.XLOOKUP($B61,'IS & BS Projections'!$B:$B,'IS & BS Projections'!AL:AL) -> 0 | AL61: =_xlfn.XLOOKUP($B61,'IS & BS Projections'!$B:$B,'IS & BS Projections'!AM:AM) -> 0 | AM61: =_xlfn.XLOOKUP($B61,'IS & BS Projections'!$B:$B,'IS & BS Projections'!AN:AN) -> 0 | AN61: =_xlfn.XLOOKUP($B61,'IS & BS Projections'!$B:$B,'IS & BS Projections'!AO:AO) -> 0 | AO61: =_xlfn.XLOOKUP($B61,'IS & BS Projections'!$B:$B,'IS & BS Projections'!AP:AP) -> 0 | AP61: =_xlfn.XLOOKUP($B61,'IS & BS Projections'!$B:$B,'IS & BS Projections'!AQ:AQ) -> 0 | AQ61: =_xlfn.XLOOKUP($B61,'IS & BS Projections'!$B:$B,'IS & BS Projections'!AR:AR) -> 0 | AR61: =_xlfn.XLOOKUP($B61,'IS & BS Projections'!$B:$B,'IS & BS Projections'!AS:AS) -> 0 | AS61: =_xlfn.XLOOKUP($B61,'IS & BS Projections'!$B:$B,'IS & BS Projections'!AT:AT) -> 0 | AT61: =_xlfn.XLOOKUP($B61,'IS & BS Projections'!$B:$B,'IS & BS Projections'!AU:AU) -> 0 | AU61: =_xlfn.XLOOKUP($B61,'IS & BS Projections'!$B:$B,'IS & BS Projections'!AV:AV) -> 0 | AV61: =_xlfn.XLOOKUP($B61,'IS & BS Projections'!$B:$B,'IS & BS Projections'!AW:AW) -> 0 | AW61: =_xlfn.XLOOKUP($B61,'IS & BS Projections'!$B:$B,'IS & BS Projections'!AX:AX) -> 0 | AX61: =_xlfn.XLOOKUP($B61,'IS & BS Projections'!$B:$B,'IS & BS Projections'!AY:AY) -> 0 | AY61: =_xlfn.XLOOKUP($B61,'IS & BS Projections'!$B:$B,'IS & BS Projections'!AZ:AZ) -> 0 | AZ61: =_xlfn.XLOOKUP($B61,'IS & BS Projections'!$B:$B,'IS & BS Projections'!BA:BA) -> 0 | BA61: =_xlfn.XLOOKUP($B61,'IS & BS Projections'!$B:$B,'IS & BS Projections'!BB:BB) -> 0 | BB61: =_xlfn.XLOOKUP($B61,'IS & BS Projections'!$B:$B,'IS & BS Projections'!BC:BC) -> 0 | BC61: =_xlfn.XLOOKUP($B61,'IS & BS Projections'!$B:$B,'IS & BS Projections'!BD:BD) -> 0 | BD61: =AI61-AJ61 -> 0 | BE61: =IF(ISNUMBER(MATCH(BD61,$AJ$136:$AJ$1048576,0)),"YES","NO") -> YES
B62: Accounts Receivable, Net | D62: USD '000s | E62: =S62 -> 0 | F62: =W62 -> 0 | G62: =AA62 -> 168290 | H62: =AE62 -> 265251 | I62: =AI62 -> 307119 | J62: =AM62 -> 203136.3 | K62: =AQ62 -> 229401.76 | L62: =AU62 -> 256793.69 | M62: =AY62 -> 299929.48 | N62: =BC62 -> 369352.63 | P62: 0 | Q62: 0 | R62: 0 | S62: 0 | T62: 0 | U62: 0 | V62: 0 | W62: 0 | X62: 0 | Y62: 0 | Z62: 0 | AA62: 168290 | AB62: 0 | AC62: 0 | AD62: 0 | AE62: 265251 | AF62: 0 | AG62: 0 | AH62: 0 | AI62: 307119 | AJ62: =_xlfn.XLOOKUP($B62,'IS & BS Projections'!$B:$B,'IS & BS Projections'!AK:AK) -> 0 | AK62: =_xlfn.XLOOKUP($B62,'IS & BS Projections'!$B:$B,'IS & BS Projections'!AL:AL) -> 0 | AL62: =_xlfn.XLOOKUP($B62,'IS & BS Projections'!$B:$B,'IS & BS Projections'!AM:AM) -> 0 | AM62: =_xlfn.XLOOKUP($B62,'IS & BS Projections'!$B:$B,'IS & BS Projections'!AN:AN) -> 203136.3 | AN62: =_xlfn.XLOOKUP($B62,'IS & BS Projections'!$B:$B,'IS & BS Projections'!AO:AO) -> 0 | AO62: =_xlfn.XLOOKUP($B62,'IS & BS Projections'!$B:$B,'IS & BS Projections'!AP:AP) -> 0 | AP62: =_xlfn.XLOOKUP($B62,'IS & BS Projections'!$B:$B,'IS & BS Projections'!AQ:AQ) -> 0 | AQ62: =_xlfn.XLOOKUP($B62,'IS & BS Projections'!$B:$B,'IS & BS Projections'!AR:AR) -> 229401.76 | AR62: =_xlfn.XLOOKUP($B62,'IS & BS Projections'!$B:$B,'IS & BS Projections'!AS:AS) -> 0 | AS62: =_xlfn.XLOOKUP($B62,'IS & BS Projections'!$B:$B,'IS & BS Projections'!AT:AT) -> 0 | AT62: =_xlfn.XLOOKUP($B62,'IS & BS Projections'!$B:$B,'IS & BS Projections'!AU:AU) -> 0 | AU62: =_xlfn.XLOOKUP($B62,'IS & BS Projections'!$B:$B,'IS & BS Projections'!AV:AV) -> 256793.69 | AV62: =_xlfn.XLOOKUP($B62,'IS & BS Projections'!$B:$B,'IS & BS Projections'!AW:AW) -> 0 | AW62: =_xlfn.XLOOKUP($B62,'IS & BS Projections'!$B:$B,'IS & BS Projections'!AX:AX) -> 0 | AX62: =_xlfn.XLOOKUP($B62,'IS & BS Projections'!$B:$B,'IS & BS Projections'!AY:AY) -> 0 | AY62: =_xlfn.XLOOKUP($B62,'IS & BS Projections'!$B:$B,'IS & BS Projections'!AZ:AZ) -> 299929.48 | AZ62: =_xlfn.XLOOKUP($B62,'IS & BS Projections'!$B:$B,'IS & BS Projections'!BA:BA) -> 0 | BA62: =_xlfn.XLOOKUP($B62,'IS & BS Projections'!$B:$B,'IS & BS Projections'!BB:BB) -> 0 | BB62: =_xlfn.XLOOKUP($B62,'IS & BS Projections'!$B:$B,'IS & BS Projections'!BC:BC) -> 0 | BC62: =_xlfn.XLOOKUP($B62,'IS & BS Projections'!$B:$B,'IS & BS Projections'!BD:BD) -> 369352.63 | BD62: =AI62-AJ62 -> 307119 | BE62: =IF(ISNUMBER(MATCH(BD62,$AJ$136:$AJ$1048576,0)),"YES","NO") -> YES
B63: Accounts and Loans Receivable, Net of Allowance | D63: USD '000s | E63: =S63 -> 304706 | F63: =W63 -> 404376 | G63: =AA63 -> 0 | H63: =AE63 -> 0 | I63: =AI63 -> 0 | J63: =AM63 -> 0 | K63: =AQ63 -> 0 | L63: =AU63 -> 0 | M63: =AY63 -> 0 | N63: =BC63 -> 0 | P63: 208828 | Q63: 184579 | R63: 237131 | S63: 304706 | T63: 346048 | U63: 245616 | V63: 240354 | W63: 404376 | X63: 480404 | Y63: 427210 | Z63: 397466 | AA63: 0 | AB63: 0 | AC63: 0 | AD63: 0 | AE63: 0 | AF63: 0 | AG63: 0 | AH63: 0 | AI63: 0 | AJ63: =_xlfn.XLOOKUP($B63,'IS & BS Projections'!$B:$B,'IS & BS Projections'!AK:AK) -> 216064.77 | AK63: =_xlfn.XLOOKUP($B63,'IS & BS Projections'!$B:$B,'IS & BS Projections'!AL:AL) -> 147755.42 | AL63: =_xlfn.XLOOKUP($B63,'IS & BS Projections'!$B:$B,'IS & BS Projections'!AM:AM) -> 429076.12 | AM63: =_xlfn.XLOOKUP($B63,'IS & BS Projections'!$B:$B,'IS & BS Projections'!AN:AN) -> 0 | AN63: =_xlfn.XLOOKUP($B63,'IS & BS Projections'!$B:$B,'IS & BS Projections'!AO:AO) -> 225478.56 | AO63: =_xlfn.XLOOKUP($B63,'IS & BS Projections'!$B:$B,'IS & BS Projections'!AP:AP) -> 168098.5 | AP63: =_xlfn.XLOOKUP($B63,'IS & BS Projections'!$B:$B,'IS & BS Projections'!AQ:AQ) -> 495133.86 | AQ63: =_xlfn.XLOOKUP($B63,'IS & BS Projections'!$B:$B,'IS & BS Projections'!AR:AR) -> 0 | AR63: =_xlfn.XLOOKUP($B63,'IS & BS Projections'!$B:$B,'IS & BS Projections'!AS:AS) -> 242750.47 | AS63: =_xlfn.XLOOKUP($B63,'IS & BS Projections'!$B:$B,'IS & BS Projections'!AT:AT) -> 192359.08 | AT63: =_xlfn.XLOOKUP($B63,'IS & BS Projections'!$B:$B,'IS & BS Projections'!AU:AU) -> 557953.39 | AU63: =_xlfn.XLOOKUP($B63,'IS & BS Projections'!$B:$B,'IS & BS Projections'!AV:AV) -> 0 | AV63: =_xlfn.XLOOKUP($B63,'IS & BS Projections'!$B:$B,'IS & BS Projections'!AW:AW) -> 271004.64 | AW63: =_xlfn.XLOOKUP($B63,'IS & BS Projections'!$B:$B,'IS & BS Projections'!AX:AX) -> 228775.86 | AX63: =_xlfn.XLOOKUP($B63,'IS & BS Projections'!$B:$B,'IS & BS Projections'!AY:AY) -> 655584.49 | AY63: =_xlfn.XLOOKUP($B63,'IS & BS Projections'!$B:$B,'IS & BS Projections'!AZ:AZ) -> 0 | AZ63: =_xlfn.XLOOKUP($B63,'IS & BS Projections'!$B:$B,'IS & BS Projections'!BA:BA) -> 311366.93 | BA63: =_xlfn.XLOOKUP($B63,'IS & BS Projections'!$B:$B,'IS & BS Projections'!BB:BB) -> 287689.28 | BB63: =_xlfn.XLOOKUP($B63,'IS & BS Projections'!$B:$B,'IS & BS Projections'!BC:BC) -> 816910.28 | BC63: =_xlfn.XLOOKUP($B63,'IS & BS Projections'!$B:$B,'IS & BS Projections'!BD:BD) -> 0 | BD63: =AI63-AJ63 -> -216064.77 | BE63: =IF(ISNUMBER(MATCH(BD63,$AJ$136:$AJ$1048576,0)),"YES","NO") -> YES
B64: Income Tax Receivable | D64: USD '000s | E64: =S64 -> 61231 | F64: =W64 -> 60441 | G64: =AA64 -> 0 | H64: =AE64 -> 0 | I64: =AI64 -> 0 | J64: =AM64 -> 0 | K64: =AQ64 -> 0 | L64: =AU64 -> 0 | M64: =AY64 -> 0 | N64: =BC64 -> 0 | P64: 0 | Q64: 435096 | R64: 94689 | S64: 61231 | T64: 56767 | U64: 62406 | V64: 60522 | W64: 60441 | X64: 67947 | Y64: 64759 | Z64: 69727 | AA64: 0 | AB64: 0 | AC64: 0 | AD64: 0 | AE64: 0 | AF64: 0 | AG64: 0 | AH64: 0 | AI64: 0 | AJ64: =_xlfn.XLOOKUP($B64,'IS & BS Projections'!$B:$B,'IS & BS Projections'!AK:AK) -> 0 | AK64: =_xlfn.XLOOKUP($B64,'IS & BS Projections'!$B:$B,'IS & BS Projections'!AL:AL) -> 137692.17 | AL64: =_xlfn.XLOOKUP($B64,'IS & BS Projections'!$B:$B,'IS & BS Projections'!AM:AM) -> 171334.78 | AM64: =_xlfn.XLOOKUP($B64,'IS & BS Projections'!$B:$B,'IS & BS Projections'!AN:AN) -> 0 | AN64: =_xlfn.XLOOKUP($B64,'IS & BS Projections'!$B:$B,'IS & BS Projections'!AO:AO) -> 0 | AO64: =_xlfn.XLOOKUP($B64,'IS & BS Projections'!$B:$B,'IS & BS Projections'!AP:AP) -> 156649.73 | AP64: =_xlfn.XLOOKUP($B64,'IS & BS Projections'!$B:$B,'IS & BS Projections'!AQ:AQ) -> 197712.36 | AQ64: =_xlfn.XLOOKUP($B64,'IS & BS Projections'!$B:$B,'IS & BS Projections'!AR:AR) -> 0 | AR64: =_xlfn.XLOOKUP($B64,'IS & BS Projections'!$B:$B,'IS & BS Projections'!AS:AS) -> 0 | AS64: =_xlfn.XLOOKUP($B64,'IS & BS Projections'!$B:$B,'IS & BS Projections'!AT:AT) -> 179257.99 | AT64: =_xlfn.XLOOKUP($B64,'IS & BS Projections'!$B:$B,'IS & BS Projections'!AU:AU) -> 222796.89 | AU64: =_xlfn.XLOOKUP($B64,'IS & BS Projections'!$B:$B,'IS & BS Projections'!AV:AV) -> 0 | AV64: =_xlfn.XLOOKUP($B64,'IS & BS Projections'!$B:$B,'IS & BS Projections'!AW:AW) -> 0 | AW64: =_xlfn.XLOOKUP($B64,'IS & BS Projections'!$B:$B,'IS & BS Projections'!AX:AX) -> 213194.51 | AX64: =_xlfn.XLOOKUP($B64,'IS & BS Projections'!$B:$B,'IS & BS Projections'!AY:AY) -> 261782.05 | AY64: =_xlfn.XLOOKUP($B64,'IS & BS Projections'!$B:$B,'IS & BS Projections'!AZ:AZ) -> 0 | AZ64: =_xlfn.XLOOKUP($B64,'IS & BS Projections'!$B:$B,'IS & BS Projections'!BA:BA) -> 0 | BA64: =_xlfn.XLOOKUP($B64,'IS & BS Projections'!$B:$B,'IS & BS Projections'!BB:BB) -> 268095.49 | BB64: =_xlfn.XLOOKUP($B64,'IS & BS Projections'!$B:$B,'IS & BS Projections'!BC:BC) -> 326201.2 | BC64: =_xlfn.XLOOKUP($B64,'IS & BS Projections'!$B:$B,'IS & BS Projections'!BD:BD) -> 0 | BD64: =AI64-AJ64 -> 0 | BE64: =IF(ISNUMBER(MATCH(BD64,$AJ$136:$AJ$1048576,0)),"YES","NO") -> YES
B65: Loans Receivable | D65: USD '000s | E65: =S65 -> 0 | F65: =W65 -> 0 | G65: =AA65 -> 193425 | H65: =AE65 -> 644165 | I65: =AI65 -> 1354692 | J65: =AM65 -> 352798.72 | K65: =AQ65 -> 398415.49 | L65: =AU65 -> 445988.66 | M65: =AY65 -> 520905.12 | N65: =BC65 -> 641476.37 | P65: 0 | Q65: 0 | R65: 0 | S65: 0 | T65: 0 | U65: 0 | V65: 0 | W65: 0 | X65: 0 | Y65: 0 | Z65: 0 | AA65: 193425 | AB65: 529143 | AC65: 440351 | AD65: 398239 | AE65: 644165 | AF65: 454473 | AG65: 803366 | AH65: 859056 | AI65: 1354692 | AJ65: =_xlfn.XLOOKUP($B65,'IS & BS Projections'!$B:$B,'IS & BS Projections'!AK:AK) -> 0 | AK65: =_xlfn.XLOOKUP($B65,'IS & BS Projections'!$B:$B,'IS & BS Projections'!AL:AL) -> 0 | AL65: =_xlfn.XLOOKUP($B65,'IS & BS Projections'!$B:$B,'IS & BS Projections'!AM:AM) -> 0 | AM65: =_xlfn.XLOOKUP($B65,'IS & BS Projections'!$B:$B,'IS & BS Projections'!AN:AN) -> 352798.72 | AN65: =_xlfn.XLOOKUP($B65,'IS & BS Projections'!$B:$B,'IS & BS Projections'!AO:AO) -> 0 | AO65: =_xlfn.XLOOKUP($B65,'IS & BS Projections'!$B:$B,'IS & BS Projections'!AP:AP) -> 0 | AP65: =_xlfn.XLOOKUP($B65,'IS & BS Projections'!$B:$B,'IS & BS Projections'!AQ:AQ) -> 0 | AQ65: =_xlfn.XLOOKUP($B65,'IS & BS Projections'!$B:$B,'IS & BS Projections'!AR:AR) -> 398415.49 | AR65: =_xlfn.XLOOKUP($B65,'IS & BS Projections'!$B:$B,'IS & BS Projections'!AS:AS) -> 0 | AS65: =_xlfn.XLOOKUP($B65,'IS & BS Projections'!$B:$B,'IS & BS Projections'!AT:AT) -> 0 | AT65: =_xlfn.XLOOKUP($B65,'IS & BS Projections'!$B:$B,'IS & BS Projections'!AU:AU) -> 0 | AU65: =_xlfn.XLOOKUP($B65,'IS & BS Projections'!$B:$B,'IS & BS Projections'!AV:AV) -> 445988.66 | AV65: =_xlfn.XLOOKUP($B65,'IS & BS Projections'!$B:$B,'IS & BS Projections'!AW:AW) -> 0 | AW65: =_xlfn.XLOOKUP($B65,'IS & BS Projections'!$B:$B,'IS & BS Projections'!AX:AX) -> 0 | AX65: =_xlfn.XLOOKUP($B65,'IS & BS Projections'!$B:$B,'IS & BS Projections'!AY:AY) -> 0 | AY65: =_xlfn.XLOOKUP($B65,'IS & BS Projections'!$B:$B,'IS & BS Projections'!AZ:AZ) -> 520905.12 | AZ65: =_xlfn.XLOOKUP($B65,'IS & BS Projections'!$B:$B,'IS & BS Projections'!BA:BA) -> 0 | BA65: =_xlfn.XLOOKUP($B65,'IS & BS Projections'!$B:$B,'IS & BS Projections'!BB:BB) -> 0 | BB65: =_xlfn.XLOOKUP($B65,'IS & BS Projections'!$B:$B,'IS & BS Projections'!BC:BC) -> 0 | BC65: =_xlfn.XLOOKUP($B65,'IS & BS Projections'!$B:$B,'IS & BS Projections'!BD:BD) -> 641476.37 | BD65: =AI65-AJ65 -> 1354692 | BE65: =IF(ISNUMBER(MATCH(BD65,$AJ$136:$AJ$1048576,0)),"YES","NO") -> YES
B66: Prepaid Expenses and Other Current Assets | D66: USD '000s | E66: =S66 -> 135849 | F66: =W66 -> 217048 | G66: =AA66 -> 0 | H66: =AE66 -> 0 | I66: =AI66 -> 0 | J66: =AM66 -> 0 | K66: =AQ66 -> 0 | L66: =AU66 -> 0 | M66: =AY66 -> 0 | N66: =BC66 -> 0 | P66: 55662 | Q66: 114751 | R66: 105165 | S66: 135849 | T66: 191068 | U66: 146463 | V66: 277044 | W66: 217048 | X66: 219075 | Y66: 175399 | Z66: 157714 | AA66: 0 | AB66: 0 | AC66: 0 | AD66: 0 | AE66: 0 | AF66: 0 | AG66: 0 | AH66: 0 | AI66: 0 | AJ66: =_xlfn.XLOOKUP($B66,'IS & BS Projections'!$B:$B,'IS & BS Projections'!AK:AK) -> 57590.924 | AK66: =_xlfn.XLOOKUP($B66,'IS & BS Projections'!$B:$B,'IS & BS Projections'!AL:AL) -> 91858.131 | AL66: =_xlfn.XLOOKUP($B66,'IS & BS Projections'!$B:$B,'IS & BS Projections'!AM:AM) -> 190290.56 | AM66: =_xlfn.XLOOKUP($B66,'IS & BS Projections'!$B:$B,'IS & BS Projections'!AN:AN) -> 0 | AN66: =_xlfn.XLOOKUP($B66,'IS & BS Projections'!$B:$B,'IS & BS Projections'!AO:AO) -> 60100.119 | AO66: =_xlfn.XLOOKUP($B66,'IS & BS Projections'!$B:$B,'IS & BS Projections'!AP:AP) -> 104505.23 | AP66: =_xlfn.XLOOKUP($B66,'IS & BS Projections'!$B:$B,'IS & BS Projections'!AQ:AQ) -> 219586.44 | AQ66: =_xlfn.XLOOKUP($B66,'IS & BS Projections'!$B:$B,'IS & BS Projections'!AR:AR) -> 0 | AR66: =_xlfn.XLOOKUP($B66,'IS & BS Projections'!$B:$B,'IS & BS Projections'!AS:AS) -> 65422.786 | AS66: =_xlfn.XLOOKUP($B66,'IS & BS Projections'!$B:$B,'IS & BS Projections'!AT:AT) -> 119587.8 | AT66: =_xlfn.XLOOKUP($B66,'IS & BS Projections'!$B:$B,'IS & BS Projections'!AU:AU) -> 247446.21 | AU66: =_xlfn.XLOOKUP($B66,'IS & BS Projections'!$B:$B,'IS & BS Projections'!AV:AV) -> 0 | AV66: =_xlfn.XLOOKUP($B66,'IS & BS Projections'!$B:$B,'IS & BS Projections'!AW:AW) -> 72234.856 | AW66: =_xlfn.XLOOKUP($B66,'IS & BS Projections'!$B:$B,'IS & BS Projections'!AX:AX) -> 142227.76 | AX66: =_xlfn.XLOOKUP($B66,'IS & BS Projections'!$B:$B,'IS & BS Projections'!AY:AY) -> 290744.54 | AY66: =_xlfn.XLOOKUP($B66,'IS & BS Projections'!$B:$B,'IS & BS Projections'!AZ:AZ) -> 0 | AZ66: =_xlfn.XLOOKUP($B66,'IS & BS Projections'!$B:$B,'IS & BS Projections'!BA:BA) -> 82993.209 | BA66: =_xlfn.XLOOKUP($B66,'IS & BS Projections'!$B:$B,'IS & BS Projections'!BB:BB) -> 178853.67 | BB66: =_xlfn.XLOOKUP($B66,'IS & BS Projections'!$B:$B,'IS & BS Projections'!BC:BC) -> 362290.76 | BC66: =_xlfn.XLOOKUP($B66,'IS & BS Projections'!$B:$B,'IS & BS Projections'!BD:BD) -> 0 | BD66: =AI66-AJ66 -> -57590.924 | BE66: =IF(ISNUMBER(MATCH(BD66,$AJ$136:$AJ$1048576,0)),"YES","NO") -> YES
B67: Restricted Cash | D67: USD '000s | E67: =S67 -> 30951 | F67: =W67 -> 25873 | G67: =AA67 -> 0 | H67: =AE67 -> 0 | I67: =AI67 -> 0 | J67: =AM67 -> 0 | K67: =AQ67 -> 0 | L67: =AU67 -> 0 | M67: =AY67 -> 0 | N67: =BC67 -> 0 | P67: 30841 | Q67: 30842 | R67: 30884 | S67: 30951 | T67: 27111 | U67: 28962 | V67: 23113 | W67: 25873 | X67: 26712 | Y67: 20697 | Z67: 26319 | AA67: 0 | AB67: 33499 | AC67: 34282 | AD67: 31881 | AE67: 0 | AF67: 55672 | AG67: 69190 | AH67: 78867 | AI67: 0 | AJ67: =_xlfn.XLOOKUP($B67,'IS & BS Projections'!$B:$B,'IS & BS Projections'!AK:AK) -> 43313.231 | AK67: =_xlfn.XLOOKUP($B67,'IS & BS Projections'!$B:$B,'IS & BS Projections'!AL:AL) -> 52143.195 | AL67: =_xlfn.XLOOKUP($B67,'IS & BS Projections'!$B:$B,'IS & BS Projections'!AM:AM) -> 92675.198 | AM67: =_xlfn.XLOOKUP($B67,'IS & BS Projections'!$B:$B,'IS & BS Projections'!AN:AN) -> 0 | AN67: =_xlfn.XLOOKUP($B67,'IS & BS Projections'!$B:$B,'IS & BS Projections'!AO:AO) -> 45200.358 | AO67: =_xlfn.XLOOKUP($B67,'IS & BS Projections'!$B:$B,'IS & BS Projections'!AP:AP) -> 59322.311 | AP67: =_xlfn.XLOOKUP($B67,'IS & BS Projections'!$B:$B,'IS & BS Projections'!AQ:AQ) -> 106942.86 | AQ67: =_xlfn.XLOOKUP($B67,'IS & BS Projections'!$B:$B,'IS & BS Projections'!AR:AR) -> 0 | AR67: =_xlfn.XLOOKUP($B67,'IS & BS Projections'!$B:$B,'IS & BS Projections'!AS:AS) -> 49203.452 | AS67: =_xlfn.XLOOKUP($B67,'IS & BS Projections'!$B:$B,'IS & BS Projections'!AT:AT) -> 67883.922 | AT67: =_xlfn.XLOOKUP($B67,'IS & BS Projections'!$B:$B,'IS & BS Projections'!AU:AU) -> 120511.11 | AU67: =_xlfn.XLOOKUP($B67,'IS & BS Projections'!$B:$B,'IS & BS Projections'!AV:AV) -> 0 | AV67: =_xlfn.XLOOKUP($B67,'IS & BS Projections'!$B:$B,'IS & BS Projections'!AW:AW) -> 54326.703 | AW67: =_xlfn.XLOOKUP($B67,'IS & BS Projections'!$B:$B,'IS & BS Projections'!AX:AX) -> 80735.477 | AX67: =_xlfn.XLOOKUP($B67,'IS & BS Projections'!$B:$B,'IS & BS Projections'!AY:AY) -> 141598.24 | AY67: =_xlfn.XLOOKUP($B67,'IS & BS Projections'!$B:$B,'IS & BS Projections'!AZ:AZ) -> 0 | AZ67: =_xlfn.XLOOKUP($B67,'IS & BS Projections'!$B:$B,'IS & BS Projections'!BA:BA) -> 62417.891 | BA67: =_xlfn.XLOOKUP($B67,'IS & BS Projections'!$B:$B,'IS & BS Projections'!BB:BB) -> 101526.15 | BB67: =_xlfn.XLOOKUP($B67,'IS & BS Projections'!$B:$B,'IS & BS Projections'!BC:BC) -> 176442.64 | BC67: =_xlfn.XLOOKUP($B67,'IS & BS Projections'!$B:$B,'IS & BS Projections'!BD:BD) -> 0 | BD67: =AI67-AJ67 -> -43313.231 | BE67: =IF(ISNUMBER(MATCH(BD67,$AJ$136:$AJ$1048576,0)),"YES","NO") -> YES
B68: Restricted: Cash and Cash Equivalents | D68: USD '000s | E68: =S68 -> 0 | F68: =W68 -> 0 | G68: =AA68 -> 22992 | H68: =AE68 -> 347169 | I68: =AI68 -> 334318 | J68: =AM68 -> 41936.4 | K68: =AQ68 -> 47358.764 | L68: =AU68 -> 53013.682 | M68: =AY68 -> 61918.835 | N68: =BC68 -> 76250.871 | P68: 0 | Q68: 0 | R68: 0 | S68: 0 | T68: 0 | U68: 0 | V68: 0 | W68: 0 | X68: 0 | Y68: 0 | Z68: 0 | AA68: 22992 | AB68: 0 | AC68: 0 | AD68: 0 | AE68: 347169 | AF68: 0 | AG68: 0 | AH68: 0 | AI68: 334318 | AJ68: =_xlfn.XLOOKUP($B68,'IS & BS Projections'!$B:$B,'IS & BS Projections'!AK:AK) -> 0 | AK68: =_xlfn.XLOOKUP($B68,'IS & BS Projections'!$B:$B,'IS & BS Projections'!AL:AL) -> 0 | AL68: =_xlfn.XLOOKUP($B68,'IS & BS Projections'!$B:$B,'IS & BS Projections'!AM:AM) -> 0 | AM68: =_xlfn.XLOOKUP($B68,'IS & BS Projections'!$B:$B,'IS & BS Projections'!AN:AN) -> 41936.4 | AN68: =_xlfn.XLOOKUP($B68,'IS & BS Projections'!$B:$B,'IS & BS Projections'!AO:AO) -> 0 | AO68: =_xlfn.XLOOKUP($B68,'IS & BS Projections'!$B:$B,'IS & BS Projections'!AP:AP) -> 0 | AP68: =_xlfn.XLOOKUP($B68,'IS & BS Projections'!$B:$B,'IS & BS Projections'!AQ:AQ) -> 0 | AQ68: =_xlfn.XLOOKUP($B68,'IS & BS Projections'!$B:$B,'IS & BS Projections'!AR:AR) -> 47358.764 | AR68: =_xlfn.XLOOKUP($B68,'IS & BS Projections'!$B:$B,'IS & BS Projections'!AS:AS) -> 0 | AS68: =_xlfn.XLOOKUP($B68,'IS & BS Projections'!$B:$B,'IS & BS Projections'!AT:AT) -> 0 | AT68: =_xlfn.XLOOKUP($B68,'IS & BS Projections'!$B:$B,'IS & BS Projections'!AU:AU) -> 0 | AU68: =_xlfn.XLOOKUP($B68,'IS & BS Projections'!$B:$B,'IS & BS Projections'!AV:AV) -> 53013.682 | AV68: =_xlfn.XLOOKUP($B68,'IS & BS Projections'!$B:$B,'IS & BS Projections'!AW:AW) -> 0 | AW68: =_xlfn.XLOOKUP($B68,'IS & BS Projections'!$B:$B,'IS & BS Projections'!AX:AX) -> 0 | AX68: =_xlfn.XLOOKUP($B68,'IS & BS Projections'!$B:$B,'IS & BS Projections'!AY:AY) -> 0 | AY68: =_xlfn.XLOOKUP($B68,'IS & BS Projections'!$B:$B,'IS & BS Projections'!AZ:AZ) -> 61918.835 | AZ68: =_xlfn.XLOOKUP($B68,'IS & BS Projections'!$B:$B,'IS & BS Projections'!BA:BA) -> 0 | BA68: =_xlfn.XLOOKUP($B68,'IS & BS Projections'!$B:$B,'IS & BS Projections'!BB:BB) -> 0 | BB68: =_xlfn.XLOOKUP($B68,'IS & BS Projections'!$B:$B,'IS & BS Projections'!BC:BC) -> 0 | BC68: =_xlfn.XLOOKUP($B68,'IS & BS Projections'!$B:$B,'IS & BS Projections'!BD:BD) -> 76250.871 | BD68: =AI68-AJ68 -> 334318 | BE68: =IF(ISNUMBER(MATCH(BD68,$AJ$136:$AJ$1048576,0)),"YES","NO") -> YES
B69: Other Current Assets | D69: USD '000s | E69: =S69 -> 0 | F69: =W69 -> 0 | G69: =AA69 -> 212540 | H69: =AE69 -> 277536 | I69: =AI69 -> 187164 | J69: =AM69 -> 182808.5 | K69: =AQ69 -> 206445.58 | L69: =AU69 -> 231096.41 | M69: =AY69 -> 269915.61 | N69: =BC69 -> 332391.6 | P69: 0 | Q69: 0 | R69: 0 | S69: 0 | T69: 0 | U69: 0 | V69: 0 | W69: 0 | X69: 0 | Y69: 0 | Z69: 0 | AA69: 212540 | AB69: 379537 | AC69: 253226 | AD69: 255975 | AE69: 277536 | AF69: 151977 | AG69: 279230 | AH69: 184160 | AI69: 187164 | AJ69: =_xlfn.XLOOKUP($B69,'IS & BS Projections'!$B:$B,'IS & BS Projections'!AK:AK) -> 0 | AK69: =_xlfn.XLOOKUP($B69,'IS & BS Projections'!$B:$B,'IS & BS Projections'!AL:AL) -> 0 | AL69: =_xlfn.XLOOKUP($B69,'IS & BS Projections'!$B:$B,'IS & BS Projections'!AM:AM) -> 0 | AM69: =_xlfn.XLOOKUP($B69,'IS & BS Projections'!$B:$B,'IS & BS Projections'!AN:AN) -> 182808.5 | AN69: =_xlfn.XLOOKUP($B69,'IS & BS Projections'!$B:$B,'IS & BS Projections'!AO:AO) -> 0 | AO69: =_xlfn.XLOOKUP($B69,'IS & BS Projections'!$B:$B,'IS & BS Projections'!AP:AP) -> 0 | AP69: =_xlfn.XLOOKUP($B69,'IS & BS Projections'!$B:$B,'IS & BS Projections'!AQ:AQ) -> 0 | AQ69: =_xlfn.XLOOKUP($B69,'IS & BS Projections'!$B:$B,'IS & BS Projections'!AR:AR) -> 206445.58 | AR69: =_xlfn.XLOOKUP($B69,'IS & BS Projections'!$B:$B,'IS & BS Projections'!AS:AS) -> 0 | AS69: =_xlfn.XLOOKUP($B69,'IS & BS Projections'!$B:$B,'IS & BS Projections'!AT:AT) -> 0 | AT69: =_xlfn.XLOOKUP($B69,'IS & BS Projections'!$B:$B,'IS & BS Projections'!AU:AU) -> 0 | AU69: =_xlfn.XLOOKUP($B69,'IS & BS Projections'!$B:$B,'IS & BS Projections'!AV:AV) -> 231096.41 | AV69: =_xlfn.XLOOKUP($B69,'IS & BS Projections'!$B:$B,'IS & BS Projections'!AW:AW) -> 0 | AW69: =_xlfn.XLOOKUP($B69,'IS & BS Projections'!$B:$B,'IS & BS Projections'!AX:AX) -> 0 | AX69: =_xlfn.XLOOKUP($B69,'IS & BS Projections'!$B:$B,'IS & BS Projections'!AY:AY) -> 0 | AY69: =_xlfn.XLOOKUP($B69,'IS & BS Projections'!$B:$B,'IS & BS Projections'!AZ:AZ) -> 269915.61 | AZ69: =_xlfn.XLOOKUP($B69,'IS & BS Projections'!$B:$B,'IS & BS Projections'!BA:BA) -> 0 | BA69: =_xlfn.XLOOKUP($B69,'IS & BS Projections'!$B:$B,'IS & BS Projections'!BB:BB) -> 0 | BB69: =_xlfn.XLOOKUP($B69,'IS & BS Projections'!$B:$B,'IS & BS Projections'!BC:BC) -> 0 | BC69: =_xlfn.XLOOKUP($B69,'IS & BS Projections'!$B:$B,'IS & BS Projections'!BD:BD) -> 332391.6 | BD69: =AI69-AJ69 -> 187164 | BE69: =IF(ISNUMBER(MATCH(BD69,$AJ$136:$AJ$1048576,0)),"YES","NO") -> YES
B70: Customer Custodial Funds | D70: USD '000s | E70: =S70 -> 10617552 | F70: =W70 -> 5041119 | G70: =AA70 -> 4570845 | H70: =AE70 -> 6158949 | I70: =AI70 -> 5347428 | J70: =AM70 -> 7393003.4 | K70: =AQ70 -> 8348916.6 | L70: =AU70 -> 9345826.8 | M70: =AY70 -> 10915724 | N70: =BC70 -> 13442331 | P70: 6291776 | Q70: 8961812 | R70: 8956966 | S70: 10617552 | T70: 10023385 | U70: 0 | V70: 0 | W70: 5041119 | X70: 5370658 | Y70: 3848078 | Z70: 3474489 | AA70: 4570845 | AB70: 5201906 | AC70: 4197837 | AD70: 4035045 | AE70: 6158949 | AF70: 5369865 | AG70: 5121640 | AH70: 5672037 | AI70: 5347428 | AJ70: =_xlfn.XLOOKUP($B70,'IS & BS Projections'!$B:$B,'IS & BS Projections'!AK:AK) -> 6509812.7 | AK70: =_xlfn.XLOOKUP($B70,'IS & BS Projections'!$B:$B,'IS & BS Projections'!AL:AL) -> 6100926.8 | AL70: =_xlfn.XLOOKUP($B70,'IS & BS Projections'!$B:$B,'IS & BS Projections'!AM:AM) -> 7947694.6 | AM70: =_xlfn.XLOOKUP($B70,'IS & BS Projections'!$B:$B,'IS & BS Projections'!AN:AN) -> 7393003.4 | AN70: =_xlfn.XLOOKUP($B70,'IS & BS Projections'!$B:$B,'IS & BS Projections'!AO:AO) -> 6793440.6 | AO70: =_xlfn.XLOOKUP($B70,'IS & BS Projections'!$B:$B,'IS & BS Projections'!AP:AP) -> 6940907.1 | AP70: =_xlfn.XLOOKUP($B70,'IS & BS Projections'!$B:$B,'IS & BS Projections'!AQ:AQ) -> 9171269.5 | AQ70: =_xlfn.XLOOKUP($B70,'IS & BS Projections'!$B:$B,'IS & BS Projections'!AR:AR) -> 8348916.6 | AR70: =_xlfn.XLOOKUP($B70,'IS & BS Projections'!$B:$B,'IS & BS Projections'!AS:AS) -> 7395090.3 | AS70: =_xlfn.XLOOKUP($B70,'IS & BS Projections'!$B:$B,'IS & BS Projections'!AT:AT) -> 7942644 | AT70: =_xlfn.XLOOKUP($B70,'IS & BS Projections'!$B:$B,'IS & BS Projections'!AU:AU) -> 10334864 | AU70: =_xlfn.XLOOKUP($B70,'IS & BS Projections'!$B:$B,'IS & BS Projections'!AV:AV) -> 9345826.8 | AV70: =_xlfn.XLOOKUP($B70,'IS & BS Projections'!$B:$B,'IS & BS Projections'!AW:AW) -> 8165095.3 | AW70: =_xlfn.XLOOKUP($B70,'IS & BS Projections'!$B:$B,'IS & BS Projections'!AX:AX) -> 9446318.6 | AX70: =_xlfn.XLOOKUP($B70,'IS & BS Projections'!$B:$B,'IS & BS Projections'!AY:AY) -> 12143266 | AY70: =_xlfn.XLOOKUP($B70,'IS & BS Projections'!$B:$B,'IS & BS Projections'!AZ:AZ) -> 10915724 | AZ70: =_xlfn.XLOOKUP($B70,'IS & BS Projections'!$B:$B,'IS & BS Projections'!BA:BA) -> 9381170 | BA70: =_xlfn.XLOOKUP($B70,'IS & BS Projections'!$B:$B,'IS & BS Projections'!BB:BB) -> 11878896 | BB70: =_xlfn.XLOOKUP($B70,'IS & BS Projections'!$B:$B,'IS & BS Projections'!BC:BC) -> 15131472 | BC70: =_xlfn.XLOOKUP($B70,'IS & BS Projections'!$B:$B,'IS & BS Projections'!BD:BD) -> 13442331 | BD70: =AI70-AJ70 -> -1162384.7 | BE70: =IF(ISNUMBER(MATCH(BD70,$AJ$136:$AJ$1048576,0)),"YES","NO") -> YES
B71: Usdc | D71: USD '000s | E71: =S71 -> 100096 | F71: =W71 -> 861149 | G71: =AA71 -> 576028 | H71: =AE71 -> 0 | I71: =AI71 -> 0 | J71: =AM71 -> 69696.863 | K71: =AQ71 -> 78708.647 | L71: =AU71 -> 88106.927 | M71: =AY71 -> 102906.99 | N71: =BC71 -> 126726.34 | P71: 102118 | Q71: 144993 | R71: 92107 | S71: 100096 | T71: 179885 | U71: 361714 | V71: 368121 | W71: 861149 | X71: 302851 | Y71: 315508 | Z71: 400799 | AA71: 576028 | AB71: 860669 | AC71: 1056648 | AD71: 871425 | AE71: 0 | AF71: 2225054 | AG71: 2153824 | AH71: 3696441 | AI71: 0 | AJ71: =_xlfn.XLOOKUP($B71,'IS & BS Projections'!$B:$B,'IS & BS Projections'!AK:AK) -> 730550.39 | AK71: =_xlfn.XLOOKUP($B71,'IS & BS Projections'!$B:$B,'IS & BS Projections'!AL:AL) -> 798083.28 | AL71: =_xlfn.XLOOKUP($B71,'IS & BS Projections'!$B:$B,'IS & BS Projections'!AM:AM) -> 1480261.7 | AM71: =_xlfn.XLOOKUP($B71,'IS & BS Projections'!$B:$B,'IS & BS Projections'!AN:AN) -> 69696.863 | AN71: =_xlfn.XLOOKUP($B71,'IS & BS Projections'!$B:$B,'IS & BS Projections'!AO:AO) -> 762379.95 | AO71: =_xlfn.XLOOKUP($B71,'IS & BS Projections'!$B:$B,'IS & BS Projections'!AP:AP) -> 907964 | AP71: =_xlfn.XLOOKUP($B71,'IS & BS Projections'!$B:$B,'IS & BS Projections'!AQ:AQ) -> 1708153.1 | AQ71: =_xlfn.XLOOKUP($B71,'IS & BS Projections'!$B:$B,'IS & BS Projections'!AR:AR) -> 78708.647 | AR71: =_xlfn.XLOOKUP($B71,'IS & BS Projections'!$B:$B,'IS & BS Projections'!AS:AS) -> 829898.86 | AS71: =_xlfn.XLOOKUP($B71,'IS & BS Projections'!$B:$B,'IS & BS Projections'!AT:AT) -> 1039004.7 | AT71: =_xlfn.XLOOKUP($B71,'IS & BS Projections'!$B:$B,'IS & BS Projections'!AU:AU) -> 1924873 | AU71: =_xlfn.XLOOKUP($B71,'IS & BS Projections'!$B:$B,'IS & BS Projections'!AV:AV) -> 88106.927 | AV71: =_xlfn.XLOOKUP($B71,'IS & BS Projections'!$B:$B,'IS & BS Projections'!AW:AW) -> 916311.09 | AW71: =_xlfn.XLOOKUP($B71,'IS & BS Projections'!$B:$B,'IS & BS Projections'!AX:AX) -> 1235705.5 | AX71: =_xlfn.XLOOKUP($B71,'IS & BS Projections'!$B:$B,'IS & BS Projections'!AY:AY) -> 2261688.8 | AY71: =_xlfn.XLOOKUP($B71,'IS & BS Projections'!$B:$B,'IS & BS Projections'!AZ:AZ) -> 102906.99 | AZ71: =_xlfn.XLOOKUP($B71,'IS & BS Projections'!$B:$B,'IS & BS Projections'!BA:BA) -> 1052782.6 | BA71: =_xlfn.XLOOKUP($B71,'IS & BS Projections'!$B:$B,'IS & BS Projections'!BB:BB) -> 1553919.4 | BB71: =_xlfn.XLOOKUP($B71,'IS & BS Projections'!$B:$B,'IS & BS Projections'!BC:BC) -> 2818243.6 | BC71: =_xlfn.XLOOKUP($B71,'IS & BS Projections'!$B:$B,'IS & BS Projections'!BD:BD) -> 126726.34 | BD71: =AI71-AJ71 -> -730550.39 | BE71: =IF(ISNUMBER(MATCH(BD71,$AJ$136:$AJ$1048576,0)),"YES","NO") -> YES
... B77: Crypto assets held for operations | D77: USD '000s | E77: =S77 -> 0 | F77: =W77 -> 0 | G77: =AA77 -> 74103 | H77: =AE77 -> 82781 | I77: =AI77 -> 120831 | J77: =AM77 -> 63395.899 | K77: =AQ77 -> 71592.97 | L77: =AU77 -> 80141.597 | M77: =AY77 -> 93603.653 | N77: =BC77 -> 115269.61 | P77: 0 | Q77: 0 | R77: 0 | S77: 0 | T77: 0 | U77: 0 | V77: 0 | W77: 0 | X77: 0 | Y77: 0 | Z77: 0 | AA77: 74103 | AB77: 0 | AC77: 0 | AD77: 0 | AE77: 82781 | AF77: 67485 | AG77: 125974 | AH77: 161145 | AI77: 120831 | AJ77: =_xlfn.XLOOKUP($B77,'IS & BS Projections'!$B:$B,'IS & BS Projections'!AK:AK) -> 0 | AK77: =_xlfn.XLOOKUP($B77,'IS & BS Projections'!$B:$B,'IS & BS Projections'!AL:AL) -> 0 | AL77: =_xlfn.XLOOKUP($B77,'IS & BS Projections'!$B:$B,'IS & BS Projections'!AM:AM) -> 0 | AM77: =_xlfn.XLOOKUP($B77,'IS & BS Projections'!$B:$B,'IS & BS Projections'!AN:AN) -> 63395.899 | AN77: =_xlfn.XLOOKUP($B77,'IS & BS Projections'!$B:$B,'IS & BS Projections'!AO:AO) -> 0 | AO77: =_xlfn.XLOOKUP($B77,'IS & BS Projections'!$B:$B,'IS & BS Projections'!AP:AP) -> 0 | AP77: =_xlfn.XLOOKUP($B77,'IS & BS Projections'!$B:$B,'IS & BS Projections'!AQ:AQ) -> 0 | AQ77: =_xlfn.XLOOKUP($B77,'IS & BS Projections'!$B:$B,'IS & BS Projections'!AR:AR) -> 71592.97 | AR77: =_xlfn.XLOOKUP($B77,'IS & BS Projections'!$B:$B,'IS & BS Projections'!AS:AS) -> 0 | AS77: =_xlfn.XLOOKUP($B77,'IS & BS Projections'!$B:$B,'IS & BS Projections'!AT:AT) -> 0 | AT77: =_xlfn.XLOOKUP($B77,'IS & BS Projections'!$B:$B,'IS & BS Projections'!AU:AU) -> 0 | AU77: =_xlfn.XLOOKUP($B77,'IS & BS Projections'!$B:$B,'IS & BS Projections'!AV:AV) -> 80141.597 | AV77: =_xlfn.XLOOKUP($B77,'IS & BS Projections'!$B:$B,'IS & BS Projections'!AW:AW) -> 0 | AW77: =_xlfn.XLOOKUP($B77,'IS & BS Projections'!$B:$B,'IS & BS Projections'!AX:AX) -> 0 | AX77: =_xlfn.XLOOKUP($B77,'IS & BS Projections'!$B:$B,'IS & BS Projections'!AY:AY) -> 0 | AY77: =_xlfn.XLOOKUP($B77,'IS & BS Projections'!$B:$B,'IS & BS Projections'!AZ:AZ) -> 93603.653 | AZ77: =_xlfn.XLOOKUP($B77,'IS & BS Projections'!$B:$B,'IS & BS Projections'!BA:BA) -> 0 | BA77: =_xlfn.XLOOKUP($B77,'IS & BS Projections'!$B:$B,'IS & BS Projections'!BB:BB) -> 0 | BB77: =_xlfn.XLOOKUP($B77,'IS & BS Projections'!$B:$B,'IS & BS Projections'!BC:BC) -> 0 | BC77: =_xlfn.XLOOKUP($B77,'IS & BS Projections'!$B:$B,'IS & BS Projections'!BD:BD) -> 115269.61 | BD77: =AI77-AJ77 -> 120831 | BE77: =IF(ISNUMBER(MATCH(BD77,$AJ$136:$AJ$1048576,0)),"YES","NO") -> YES
B78: Total Current Assets | D78: USD '000s | E78: =SUM(E59:E77) -> 18373863 | F78: =SUM(F59:F77) -> 86448215 | G78: =SUM(G59:G77) -> 11356794 | H78: =SUM(H59:H77) -> 18112653 | I78: =SUM(I59:I77) -> 20388445 | J78: =SUM(J59:J77) -> 25484513 | K78: =SUM(K59:K77) -> 28594736 | L78: =SUM(L59:L77) -> 31073730 | ... N78: =SUM(N59:N77) -> 38276212 | P78: =SUM(P59:P77) -> 8672543 | Q78: =SUM(Q59:Q77) -> 14238055 | R78: =SUM(R59:R77) -> 15869717 | S78: =SUM(S59:S77) -> 18373863 | T78: =SUM(T59:T77) -> 16940652 | U78: =SUM(U59:U77) -> 102162250 | V78: =SUM(V59:V77) -> 107679967 | W78: =SUM(W59:W77) -> 86448215 | ... BC78: =SUM(BC59:BC77) -> 38276212
B80: Non-Current Assets:
B81: Lease Right-of-use Assets | D81: USD '000s | E81: =S81 -> 98385 | F81: =W81 -> 69357 | G81: =AA81 -> 0 | H81: =AE81 -> 0 | I81: =AI81 -> 0 | J81: =AM81 -> 0 | K81: =AQ81 -> 0 | L81: =AU81 -> 0 | M81: =AY81 -> 0 | N81: =BC81 -> 0 | P81: 110791 | Q81: 105296 | R81: 105583 | S81: 98385 | T81: 91431 | U81: 85972 | V81: 76465 | W81: 69357 | X81: 38864 | Y81: 18210 | Z81: 15412 | AA81: 0 | AB81: 0 | AC81: 0 | AD81: 0 | AE81: 0 | AF81: 0 | AG81: 0 | AH81: 0 | AI81: 0 | AJ81: =_xlfn.XLOOKUP($B81,'IS & BS Projections'!$B:$B,'IS & BS Projections'!AK:AK) -> 93749.436 | AK81: =_xlfn.XLOOKUP($B81,'IS & BS Projections'!$B:$B,'IS & BS Projections'!AL:AL) -> 45877.547 | AL81: =_xlfn.XLOOKUP($B81,'IS & BS Projections'!$B:$B,'IS & BS Projections'!AM:AM) -> 54269.165 | AM81: =_xlfn.XLOOKUP($B81,'IS & BS Projections'!$B:$B,'IS & BS Projections'!AN:AN) -> 0 | AN81: =_xlfn.XLOOKUP($B81,'IS & BS Projections'!$B:$B,'IS & BS Projections'!AO:AO) -> 97834.032 | AO81: =_xlfn.XLOOKUP($B81,'IS & BS Projections'!$B:$B,'IS & BS Projections'!AP:AP) -> 52194.003 | AP81: =_xlfn.XLOOKUP($B81,'IS & BS Projections'!$B:$B,'IS & BS Projections'!AQ:AQ) -> 62624.089 | AQ81: =_xlfn.XLOOKUP($B81,'IS & BS Projections'!$B:$B,'IS & BS Projections'!AR:AR) -> 0 | AR81: =_xlfn.XLOOKUP($B81,'IS & BS Projections'!$B:$B,'IS & BS Projections'!AS:AS) -> 106498.54 | AS81: =_xlfn.XLOOKUP($B81,'IS & BS Projections'!$B:$B,'IS & BS Projections'!AT:AT) -> 59726.831 | AT81: =_xlfn.XLOOKUP($B81,'IS & BS Projections'!$B:$B,'IS & BS Projections'!AU:AU) -> 70569.448 | AU81: =_xlfn.XLOOKUP($B81,'IS & BS Projections'!$B:$B,'IS & BS Projections'!AV:AV) -> 0 | AV81: =_xlfn.XLOOKUP($B81,'IS & BS Projections'!$B:$B,'IS & BS Projections'!AW:AW) -> 117587.57 | AW81: =_xlfn.XLOOKUP($B81,'IS & BS Projections'!$B:$B,'IS & BS Projections'!AX:AX) -> 71034.113 | AX81: =_xlfn.XLOOKUP($B81,'IS & BS Projections'!$B:$B,'IS & BS Projections'!AY:AY) -> 82917.743 | AY81: =_xlfn.XLOOKUP($B81,'IS & BS Projections'!$B:$B,'IS & BS Projections'!AZ:AZ) -> 0 | AZ81: =_xlfn.XLOOKUP($B81,'IS & BS Projections'!$B:$B,'IS & BS Projections'!BA:BA) -> 135100.57 | BA81: =_xlfn.XLOOKUP($B81,'IS & BS Projections'!$B:$B,'IS & BS Projections'!BB:BB) -> 89326.528 | BB81: =_xlfn.XLOOKUP($B81,'IS & BS Projections'!$B:$B,'IS & BS Projections'!BC:BC) -> 103322.08 | BC81: =_xlfn.XLOOKUP($B81,'IS & BS Projections'!$B:$B,'IS & BS Projections'!BD:BD) -> 0 | BD81: =AI81-AJ81 -> -93749.436 | BE81: =IF(ISNUMBER(MATCH(BD81,$AJ$136:$AJ$1048576,0)),"YES","NO") -> YES
B82: Software and Equipment, Net | D82: USD '000s | E82: =S82 -> 0 | F82: =W82 -> 0 | G82: =AA82 -> 0 | H82: =AE82 -> 0 | I82: =AI82 -> 264573 | J82: =AM82 -> 326749.46 | K82: =AQ82 -> 376528.36 | L82: =AU82 -> 412867.62 | M82: =AY82 -> 441876.79 | N82: =BC82 -> 476497.8 | P82: 0 | Q82: 0 | R82: 0 | S82: 0 | T82: 0 | U82: 0 | V82: 0 | W82: 0 | X82: 0 | Y82: 0 | Z82: 0 | AA82: 0 | AB82: 0 | AC82: 0 | AD82: 0 | AE82: 0 | AF82: 0 | AG82: 0 | AH82: 0 | AI82: 264573 | AJ82: =AI82-AJ187-AJ142 -> 280117.11 | AK82: =AJ82-AK187-AK142 -> 295661.23 | AL82: =AK82-AL187-AL142 -> 311205.34 | AM82: =AL82-AM187-AM142 -> 326749.46 | AN82: =AM82-AN187-AN142 -> 339194.18 | AO82: =AN82-AO187-AO142 -> 351638.91 | AP82: =AO82-AP187-AP142 -> 364083.63 | AQ82: =AP82-AQ187-AQ142 -> 376528.36 | ... BC82: =BB82-BC187-BC142 -> 476497.8
B83: Property and Equipment, net | D83: USD '000s | E83: =S83 -> 59230 | F83: =W83 -> 171853 | G83: =AA83 -> 192550 | H83: =AE83 -> 200080 | I83: =AI83 -> 0 | J83: =AM83 -> 0 | K83: =AQ83 -> 0 | L83: =AU83 -> 0 | M83: =AY83 -> 0 | N83: =BC83 -> 0 | P83: 50331 | Q83: 52175 | R83: 55632 | S83: 59230 | T83: 65861 | U83: 142209 | V83: 170922 | W83: 171853 | X83: 172843 | Y83: 186046 | Z83: 202274 | AA83: 192550 | AB83: 0 | AC83: 0 | AD83: 0 | AE83: 200080 | AF83: 0 | AG83: 0 | AH83: 0 | AI83: 0 | AJ83: =AI83 -> 0 | AK83: =AJ83 -> 0 | AL83: =AK83 -> 0 | AM83: =AL83 -> 0 | AN83: =AM83 -> 0 | AO83: =AN83 -> 0 | AP83: =AO83 -> 0 | AQ83: =AP83 -> 0 | ... BC83: =BB83 -> 0
B84: Strategic Investments | D84: USD '000s | E84: =S84 -> 0 | F84: =W84 -> 0 | G84: =AA84 -> 0 | H84: =AE84 -> 374161 | I84: =AI84 -> 622985 | J84: =AM84 -> 0 | K84: =AQ84 -> 0 | L84: =AU84 -> 0 | M84: =AY84 -> 0 | N84: =BC84 -> 0 | P84: 0 | Q84: 0 | R84: 0 | S84: 0 | T84: 0 | U84: 0 | V84: 0 | W84: 0 | X84: 0 | Y84: 0 | Z84: 0 | AA84: 0 | AB84: 0 | AC84: 0 | AD84: 0 | AE84: 374161 | AF84: 0 | AG84: 1933843 | AH84: 401728 | AI84: 622985 | AJ84: =_xlfn.XLOOKUP($B84,'IS & BS Projections'!$B:$B,'IS & BS Projections'!AK:AK) -> 0 | AK84: =_xlfn.XLOOKUP($B84,'IS & BS Projections'!$B:$B,'IS & BS Projections'!AL:AL) -> 0 | AL84: =_xlfn.XLOOKUP($B84,'IS & BS Projections'!$B:$B,'IS & BS Projections'!AM:AM) -> 0 | AM84: =_xlfn.XLOOKUP($B84,'IS & BS Projections'!$B:$B,'IS & BS Projections'!AN:AN) -> 0 | AN84: =_xlfn.XLOOKUP($B84,'IS & BS Projections'!$B:$B,'IS & BS Projections'!AO:AO) -> 0 | AO84: =_xlfn.XLOOKUP($B84,'IS & BS Projections'!$B:$B,'IS & BS Projections'!AP:AP) -> 0 | AP84: =_xlfn.XLOOKUP($B84,'IS & BS Projections'!$B:$B,'IS & BS Projections'!AQ:AQ) -> 0 | AQ84: =_xlfn.XLOOKUP($B84,'IS & BS Projections'!$B:$B,'IS & BS Projections'!AR:AR) -> 0 | AR84: =_xlfn.XLOOKUP($B84,'IS & BS Projections'!$B:$B,'IS & BS Projections'!AS:AS) -> 0 | AS84: =_xlfn.XLOOKUP($B84,'IS & BS Projections'!$B:$B,'IS & BS Projections'!AT:AT) -> 0 | AT84: =_xlfn.XLOOKUP($B84,'IS & BS Projections'!$B:$B,'IS & BS Projections'!AU:AU) -> 0 | AU84: =_xlfn.XLOOKUP($B84,'IS & BS Projections'!$B:$B,'IS & BS Projections'!AV:AV) -> 0 | AV84: =_xlfn.XLOOKUP($B84,'IS & BS Projections'!$B:$B,'IS & BS Projections'!AW:AW) -> 0 | AW84: =_xlfn.XLOOKUP($B84,'IS & BS Projections'!$B:$B,'IS & BS Projections'!AX:AX) -> 0 | AX84: =_xlfn.XLOOKUP($B84,'IS & BS Projections'!$B:$B,'IS & BS Projections'!AY:AY) -> 0 | AY84: =_xlfn.XLOOKUP($B84,'IS & BS Projections'!$B:$B,'IS & BS Projections'!AZ:AZ) -> 0 | AZ84: =_xlfn.XLOOKUP($B84,'IS & BS Projections'!$B:$B,'IS & BS Projections'!BA:BA) -> 0 | BA84: =_xlfn.XLOOKUP($B84,'IS & BS Projections'!$B:$B,'IS & BS Projections'!BB:BB) -> 0 | BB84: =_xlfn.XLOOKUP($B84,'IS & BS Projections'!$B:$B,'IS & BS Projections'!BC:BC) -> 0 | BC84: =_xlfn.XLOOKUP($B84,'IS & BS Projections'!$B:$B,'IS & BS Projections'!BD:BD) -> 0
B85: Deferred Tax Assets | D85: USD '000s | E85: =S85 -> 0 | F85: =W85 -> 1046791 | G85: =AA85 -> 1272233 | H85: =AE85 -> 941298 | I85: =AI85 -> 570819 | J85: =AM85 -> 720871.13 | K85: =AQ85 -> 814079.56 | L85: =AU85 -> 911285.5 | M85: =AY85 -> 1064361.8 | N85: =BC85 -> 1310724.2 | P85: 0 | Q85: 0 | R85: 0 | S85: 0 | T85: 0 | U85: 0 | V85: 0 | W85: 1046791 | X85: 0 | Y85: 0 | Z85: 0 | AA85: 1272233 | AB85: 879671 | AC85: 1010154 | AD85: 1032959 | AE85: 941298 | AF85: 995529 | AG85: 541354 | AH85: 324096 | AI85: 570819 | AJ85: =_xlfn.XLOOKUP($B85,'IS & BS Projections'!$B:$B,'IS & BS Projections'!AK:AK) -> 0 | AK85: =_xlfn.XLOOKUP($B85,'IS & BS Projections'!$B:$B,'IS & BS Projections'!AL:AL) -> 0 | AL85: =_xlfn.XLOOKUP($B85,'IS & BS Projections'!$B:$B,'IS & BS Projections'!AM:AM) -> 0 | AM85: =_xlfn.XLOOKUP($B85,'IS & BS Projections'!$B:$B,'IS & BS Projections'!AN:AN) -> 720871.13 | AN85: =_xlfn.XLOOKUP($B85,'IS & BS Projections'!$B:$B,'IS & BS Projections'!AO:AO) -> 0 | AO85: =_xlfn.XLOOKUP($B85,'IS & BS Projections'!$B:$B,'IS & BS Projections'!AP:AP) -> 0 | AP85: =_xlfn.XLOOKUP($B85,'IS & BS Projections'!$B:$B,'IS & BS Projections'!AQ:AQ) -> 0 | AQ85: =_xlfn.XLOOKUP($B85,'IS & BS Projections'!$B:$B,'IS & BS Projections'!AR:AR) -> 814079.56 | AR85: =_xlfn.XLOOKUP($B85,'IS & BS Projections'!$B:$B,'IS & BS Projections'!AS:AS) -> 0 | AS85: =_xlfn.XLOOKUP($B85,'IS & BS Projections'!$B:$B,'IS & BS Projections'!AT:AT) -> 0 | AT85: =_xlfn.XLOOKUP($B85,'IS & BS Projections'!$B:$B,'IS & BS Projections'!AU:AU) -> 0 | AU85: =_xlfn.XLOOKUP($B85,'IS & BS Projections'!$B:$B,'IS & BS Projections'!AV:AV) -> 911285.5 | AV85: =_xlfn.XLOOKUP($B85,'IS & BS Projections'!$B:$B,'IS & BS Projections'!AW:AW) -> 0 | AW85: =_xlfn.XLOOKUP($B85,'IS & BS Projections'!$B:$B,'IS & BS Projections'!AX:AX) -> 0 | AX85: =_xlfn.XLOOKUP($B85,'IS & BS Projections'!$B:$B,'IS & BS Projections'!AY:AY) -> 0 | AY85: =_xlfn.XLOOKUP($B85,'IS & BS Projections'!$B:$B,'IS & BS Projections'!AZ:AZ) -> 1064361.8 | AZ85: =_xlfn.XLOOKUP($B85,'IS & BS Projections'!$B:$B,'IS & BS Projections'!BA:BA) -> 0 | BA85: =_xlfn.XLOOKUP($B85,'IS & BS Projections'!$B:$B,'IS & BS Projections'!BB:BB) -> 0 | BB85: =_xlfn.XLOOKUP($B85,'IS & BS Projections'!$B:$B,'IS & BS Projections'!BC:BC) -> 0 | BC85: =_xlfn.XLOOKUP($B85,'IS & BS Projections'!$B:$B,'IS & BS Projections'!BD:BD) -> 1310724.2
B86: Goodwill | D86: USD '000s | E86: =S86 -> 625758 | F86: =W86 -> 1073906 | G86: =AA86 -> 1139670 | H86: =AE86 -> 1139670 | I86: =AI86 -> 4168967 | J86: =AM86 -> 2078708.1 | K86: =AQ86 -> 2347484.4 | L86: =AU86 -> 2627788 | M86: =AY86 -> 3069199.6 | N86: =BC86 -> 3779611.6 | P86: 481379 | Q86: 501259 | R86: 567420 | S86: 625758 | T86: 1080176 | U86: 1073906 | V86: 1073906 | W86: 1073906 | X86: 1139670 | Y86: 1139670 | Z86: 1139670 | AA86: 1139670 | AB86: 1139670 | AC86: 1139670 | AD86: 1139670 | AE86: 1139670 | AF86: 1153621 | AG86: 1153621 | AH86: 4004112 | AI86: 4168967 | AJ86: =_xlfn.XLOOKUP($B86,'IS & BS Projections'!$B:$B,'IS & BS Projections'!AK:AK) -> 1296926 | AK86: =_xlfn.XLOOKUP($B86,'IS & BS Projections'!$B:$B,'IS & BS Projections'!AL:AL) -> 1402140.2 | AL86: =_xlfn.XLOOKUP($B86,'IS & BS Projections'!$B:$B,'IS & BS Projections'!AM:AM) -> 4013037.8 | AM86: =_xlfn.XLOOKUP($B86,'IS & BS Projections'!$B:$B,'IS & BS Projections'!AN:AN) -> 2078708.1 | AN86: =_xlfn.XLOOKUP($B86,'IS & BS Projections'!$B:$B,'IS & BS Projections'!AO:AO) -> 1353432.2 | AO86: =_xlfn.XLOOKUP($B86,'IS & BS Projections'!$B:$B,'IS & BS Projections'!AP:AP) -> 1595188 | AP86: =_xlfn.XLOOKUP($B86,'IS & BS Projections'!$B:$B,'IS & BS Projections'!AQ:AQ) -> 4630858.8 | AQ86: =_xlfn.XLOOKUP($B86,'IS & BS Projections'!$B:$B,'IS & BS Projections'!AR:AR) -> 2347484.4 | AR86: =_xlfn.XLOOKUP($B86,'IS & BS Projections'!$B:$B,'IS & BS Projections'!AS:AS) -> 1473296.6 | AS86: =_xlfn.XLOOKUP($B86,'IS & BS Projections'!$B:$B,'IS & BS Projections'!AT:AT) -> 1825411.3 | AT86: =_xlfn.XLOOKUP($B86,'IS & BS Projections'!$B:$B,'IS & BS Projections'!AU:AU) -> 5218393.6 | AU86: =_xlfn.XLOOKUP($B86,'IS & BS Projections'!$B:$B,'IS & BS Projections'!AV:AV) -> 2627788 | AV86: =_xlfn.XLOOKUP($B86,'IS & BS Projections'!$B:$B,'IS & BS Projections'!AW:AW) -> 1626701.9 | AW86: =_xlfn.XLOOKUP($B86,'IS & BS Projections'!$B:$B,'IS & BS Projections'!AX:AX) -> 2170992 | AX86: =_xlfn.XLOOKUP($B86,'IS & BS Projections'!$B:$B,'IS & BS Projections'!AY:AY) -> 6131512.1 | AY86: =_xlfn.XLOOKUP($B86,'IS & BS Projections'!$B:$B,'IS & BS Projections'!AZ:AZ) -> 3069199.6 | AZ86: =_xlfn.XLOOKUP($B86,'IS & BS Projections'!$B:$B,'IS & BS Projections'!BA:BA) -> 1868976 | BA86: =_xlfn.XLOOKUP($B86,'IS & BS Projections'!$B:$B,'IS & BS Projections'!BB:BB) -> 2730057 | BB86: =_xlfn.XLOOKUP($B86,'IS & BS Projections'!$B:$B,'IS & BS Projections'!BC:BC) -> 7640350.4 | BC86: =_xlfn.XLOOKUP($B86,'IS & BS Projections'!$B:$B,'IS & BS Projections'!BD:BD) -> 3779611.6
B87: Intangible Assets, Net | D87: USD '000s | E87: =S87 -> 176689 | F87: =W87 -> 135429 | G87: =AA87 -> 86422 | H87: =AE87 -> 46804 | I87: =AI87 -> 1397794 | J87: =AM87 -> 1280338.2 | K87: =AQ87 -> 1163446.4 | L87: =AU87 -> 1047254.8 | M87: =AY87 -> 933118.12 | N87: =BC87 -> 823689.06 | P87: 93032 | Q87: 119889 | R87: 142183 | S87: 176689 | T87: 219128 | U87: 189508 | V87: 161669 | W87: 135429 | X87: 129692 | Y87: 108134 | Z87: 94935 | AA87: 86422 | AB87: 0 | AC87: 0 | AD87: 0 | AE87: 46804 | AF87: 0 | AG87: 0 | AH87: 1417823 | AI87: 1397794 | AJ87: =AI87-AJ188-AJ143 -> 1368430.1 | AK87: =AJ87-AK188-AK143 -> 1339066.1 | AL87: =AK87-AL188-AL143 -> 1309702.2 | AM87: =AL87-AM188-AM143 -> 1280338.2 | AN87: =AM87-AN188-AN143 -> 1251115.3 | AO87: =AN87-AO188-AO143 -> 1221892.3 | AP87: =AO87-AP188-AP143 -> 1192669.4 | AQ87: =AP87-AQ188-AQ143 -> 1163446.4 | ... BC87: =BB87-BC188-BC143 -> 823689.06
B88: Other Non-current Assets | D88: USD '000s | E88: =S88 -> 952307 | F88: =W88 -> 354929 | G88: =AA88 -> 375622 | H88: =AE88 -> 174290 | I88: =AI88 -> 259378 | J88: =AM88 -> 663091.54 | K88: =AQ88 -> 748829.08 | L88: =AU88 -> 838243.72 | M88: =AY88 -> 979050.56 | N88: =BC88 -> 1205666.4 | P88: 141680 | Q88: 187688 | R88: 879973 | S88: 952307 | T88: 1164613 | U88: 1274715 | V88: 1382361 | W88: 354929 | X88: 1462343 | Y88: 1451197 | Z88: 1478096 | AA88: 375622 | AB88: 653862 | AC88: 688559 | AD88: 699694 | AE88: 174290 | AF88: 860067 | AG88: 517833 | AH88: 513142 | AI88: 259378 | AJ88: =_xlfn.XLOOKUP($B88,'IS & BS Projections'!$B:$B,'IS & BS Projections'!AK:AK) -> 787869.54 | AK88: =_xlfn.XLOOKUP($B88,'IS & BS Projections'!$B:$B,'IS & BS Projections'!AL:AL) -> 847136.69 | AL88: =_xlfn.XLOOKUP($B88,'IS & BS Projections'!$B:$B,'IS & BS Projections'!AM:AM) -> 1592265 | AM88: =_xlfn.XLOOKUP($B88,'IS & BS Projections'!$B:$B,'IS & BS Projections'!AN:AN) -> 663091.54 | AN88: =_xlfn.XLOOKUP($B88,'IS & BS Projections'!$B:$B,'IS & BS Projections'!AO:AO) -> 822196.46 | AO88: =_xlfn.XLOOKUP($B88,'IS & BS Projections'!$B:$B,'IS & BS Projections'!AP:AP) -> 963771.13 | AP88: =_xlfn.XLOOKUP($B88,'IS & BS Projections'!$B:$B,'IS & BS Projections'!AQ:AQ) -> 1837399.7 | AQ88: =_xlfn.XLOOKUP($B88,'IS & BS Projections'!$B:$B,'IS & BS Projections'!AR:AR) -> 748829.08 | AR88: =_xlfn.XLOOKUP($B88,'IS & BS Projections'!$B:$B,'IS & BS Projections'!AS:AS) -> 895012.91 | AS88: =_xlfn.XLOOKUP($B88,'IS & BS Projections'!$B:$B,'IS & BS Projections'!AT:AT) -> 1102866.1 | AT88: =_xlfn.XLOOKUP($B88,'IS & BS Projections'!$B:$B,'IS & BS Projections'!AU:AU) -> 2070517.6 | AU88: =_xlfn.XLOOKUP($B88,'IS & BS Projections'!$B:$B,'IS & BS Projections'!AV:AV) -> 838243.72 | AV88: =_xlfn.XLOOKUP($B88,'IS & BS Projections'!$B:$B,'IS & BS Projections'!AW:AW) -> 988205.07 | AW88: =_xlfn.XLOOKUP($B88,'IS & BS Projections'!$B:$B,'IS & BS Projections'!AX:AX) -> 1311657 | AX88: =_xlfn.XLOOKUP($B88,'IS & BS Projections'!$B:$B,'IS & BS Projections'!AY:AY) -> 2432818.4 | AY88: =_xlfn.XLOOKUP($B88,'IS & BS Projections'!$B:$B,'IS & BS Projections'!AZ:AZ) -> 979050.56 | AZ88: =_xlfn.XLOOKUP($B88,'IS & BS Projections'!$B:$B,'IS & BS Projections'!BA:BA) -> 1135384.1 | BA88: =_xlfn.XLOOKUP($B88,'IS & BS Projections'!$B:$B,'IS & BS Projections'!BB:BB) -> 1649429.5 | BB88: =_xlfn.XLOOKUP($B88,'IS & BS Projections'!$B:$B,'IS & BS Projections'!BC:BC) -> 3031484.7 | BC88: =_xlfn.XLOOKUP($B88,'IS & BS Projections'!$B:$B,'IS & BS Projections'!BD:BD) -> 1205666.4
B89: Crypto Assets Held | D89: USD '000s | E89: =S89 -> 0 | F89: =W89 -> 0 | G89: =AA89 -> 0 | H89: =AE89 -> 0 | I89: =AI89 -> 0 | J89: =AM89 -> 0 | K89: =AQ89 -> 0 | L89: =AU89 -> 0 | M89: =AY89 -> 0 | N89: =BC89 -> 0 | P89: 651356 | Q89: 585846 | R89: 833763 | S89: 0 | T89: 1333333 | U89: 539683 | V89: 623073 | W89: 0 | X89: 514502 | Y89: 485347 | Z89: 455986 | AA89: 0 | AB89: 0 | AC89: 0 | AD89: 0 | AE89: 0 | AF89: 0 | AG89: 0 | AH89: 0 | AI89: 0 | AJ89: =_xlfn.XLOOKUP($B89,'IS & BS Projections'!$B:$B,'IS & BS Projections'!AK:AK) -> 673928.24 | AK89: =_xlfn.XLOOKUP($B89,'IS & BS Projections'!$B:$B,'IS & BS Projections'!AL:AL) -> 468969.49 | AL89: =_xlfn.XLOOKUP($B89,'IS & BS Projections'!$B:$B,'IS & BS Projections'!AM:AM) -> 1508650.4 | AM89: =_xlfn.XLOOKUP($B89,'IS & BS Projections'!$B:$B,'IS & BS Projections'!AN:AN) -> 0 | AN89: =_xlfn.XLOOKUP($B89,'IS & BS Projections'!$B:$B,'IS & BS Projections'!AO:AO) -> 703290.82 | AO89: =_xlfn.XLOOKUP($B89,'IS & BS Projections'!$B:$B,'IS & BS Projections'!AP:AP) -> 533537.58 | AP89: =_xlfn.XLOOKUP($B89,'IS & BS Projections'!$B:$B,'IS & BS Projections'!AQ:AQ) -> 1740912.4 | AQ89: =_xlfn.XLOOKUP($B89,'IS & BS Projections'!$B:$B,'IS & BS Projections'!AR:AR) -> 0 | AR89: =_xlfn.XLOOKUP($B89,'IS & BS Projections'!$B:$B,'IS & BS Projections'!AS:AS) -> 765576.59 | AS89: =_xlfn.XLOOKUP($B89,'IS & BS Projections'!$B:$B,'IS & BS Projections'!AT:AT) -> 610539.65 | AT89: =_xlfn.XLOOKUP($B89,'IS & BS Projections'!$B:$B,'IS & BS Projections'!AU:AU) -> 1961788.6 | AU89: =_xlfn.XLOOKUP($B89,'IS & BS Projections'!$B:$B,'IS & BS Projections'!AV:AV) -> 0 | AV89: =_xlfn.XLOOKUP($B89,'IS & BS Projections'!$B:$B,'IS & BS Projections'!AW:AW) -> 845291.35 | AW89: =_xlfn.XLOOKUP($B89,'IS & BS Projections'!$B:$B,'IS & BS Projections'!AX:AX) -> 726124.97 | AX89: =_xlfn.XLOOKUP($B89,'IS & BS Projections'!$B:$B,'IS & BS Projections'!AY:AY) -> 2305063.8 | AY89: =_xlfn.XLOOKUP($B89,'IS & BS Projections'!$B:$B,'IS & BS Projections'!AZ:AZ) -> 0 | AZ89: =_xlfn.XLOOKUP($B89,'IS & BS Projections'!$B:$B,'IS & BS Projections'!BA:BA) -> 971185.46 | BA89: =_xlfn.XLOOKUP($B89,'IS & BS Projections'!$B:$B,'IS & BS Projections'!BB:BB) -> 913113.7 | BB89: =_xlfn.XLOOKUP($B89,'IS & BS Projections'!$B:$B,'IS & BS Projections'!BC:BC) -> 2872292.4 | BC89: =_xlfn.XLOOKUP($B89,'IS & BS Projections'!$B:$B,'IS & BS Projections'!BD:BD) -> 0
B90: Crypto assets held for investment | D90: USD '000s | E90: =S90 -> 988193 | F90: =W90 -> 424393 | G90: =AA90 -> 330610 | H90: =AE90 -> 1552995 | I90: =AI90 -> 1998871 | J90: =AM90 -> 1173579.3 | K90: =AQ90 -> 1325322.7 | L90: =AU90 -> 1483574.2 | M90: =AY90 -> 1732782.6 | N90: =BC90 -> 2133860.9 | P90: 0 | Q90: 0 | R90: 0 | S90: 988193 | T90: 0 | U90: 0 | V90: 0 | W90: 424393 | X90: 0 | Y90: 0 | Z90: 0 | AA90: 330610 | AB90: 1522328 | AC90: 1234158 | AD90: 1260718 | AE90: 1552995 | AF90: 1268001 | AG90: 1838887 | AH90: 2597277 | AI90: 1998871 | AJ90: =_xlfn.XLOOKUP($B90,'IS & BS Projections'!$B:$B,'IS & BS Projections'!AK:AK) -> 0 | AK90: =_xlfn.XLOOKUP($B90,'IS & BS Projections'!$B:$B,'IS & BS Projections'!AL:AL) -> 0 | AL90: =_xlfn.XLOOKUP($B90,'IS & BS Projections'!$B:$B,'IS & BS Projections'!AM:AM) -> 0 | AM90: =_xlfn.XLOOKUP($B90,'IS & BS Projections'!$B:$B,'IS & BS Projections'!AN:AN) -> 1173579.3 | AN90: =_xlfn.XLOOKUP($B90,'IS & BS Projections'!$B:$B,'IS & BS Projections'!AO:AO) -> 0 | AO90: =_xlfn.XLOOKUP($B90,'IS & BS Projections'!$B:$B,'IS & BS Projections'!AP:AP) -> 0 | AP90: =_xlfn.XLOOKUP($B90,'IS & BS Projections'!$B:$B,'IS & BS Projections'!AQ:AQ) -> 0 | AQ90: =_xlfn.XLOOKUP($B90,'IS & BS Projections'!$B:$B,'IS & BS Projections'!AR:AR) -> 1325322.7 | AR90: =_xlfn.XLOOKUP($B90,'IS & BS Projections'!$B:$B,'IS & BS Projections'!AS:AS) -> 0 | AS90: =_xlfn.XLOOKUP($B90,'IS & BS Projections'!$B:$B,'IS & BS Projections'!AT:AT) -> 0 | AT90: =_xlfn.XLOOKUP($B90,'IS & BS Projections'!$B:$B,'IS & BS Projections'!AU:AU) -> 0 | AU90: =_xlfn.XLOOKUP($B90,'IS & BS Projections'!$B:$B,'IS & BS Projections'!AV:AV) -> 1483574.2 | AV90: =_xlfn.XLOOKUP($B90,'IS & BS Projections'!$B:$B,'IS & BS Projections'!AW:AW) -> 0 | AW90: =_xlfn.XLOOKUP($B90,'IS & BS Projections'!$B:$B,'IS & BS Projections'!AX:AX) -> 0 | AX90: =_xlfn.XLOOKUP($B90,'IS & BS Projections'!$B:$B,'IS & BS Projections'!AY:AY) -> 0 | AY90: =_xlfn.XLOOKUP($B90,'IS & BS Projections'!$B:$B,'IS & BS Projections'!AZ:AZ) -> 1732782.6 | AZ90: =_xlfn.XLOOKUP($B90,'IS & BS Projections'!$B:$B,'IS & BS Projections'!BA:BA) -> 0 | BA90: =_xlfn.XLOOKUP($B90,'IS & BS Projections'!$B:$B,'IS & BS Projections'!BB:BB) -> 0 | BB90: =_xlfn.XLOOKUP($B90,'IS & BS Projections'!$B:$B,'IS & BS Projections'!BC:BC) -> 0 | BC90: =_xlfn.XLOOKUP($B90,'IS & BS Projections'!$B:$B,'IS & BS Projections'!BD:BD) -> 2133860.9
B91: Total Non-Current Assets | D91: USD '000s | E91: =SUM(E81:E90) -> 2900562 | F91: =SUM(F81:F90) -> 3276658 | G91: =SUM(G81:G90) -> 3397107 | H91: =SUM(H81:H90) -> 4429298 | I91: =SUM(I81:I90) -> 9283387 | J91: =SUM(J81:J90) -> 6243337.7 | K91: =SUM(K81:K90) -> 6775690.6 | L91: =SUM(L81:L90) -> 7321013.8 | ... N91: =SUM(N81:N90) -> 9730049.9 | P91: =SUM(P81:P90) -> 1528569 | Q91: =SUM(Q81:Q90) -> 1552153 | R91: =SUM(R81:R90) -> 2584554 | S91: =SUM(S81:S90) -> 2900562 | T91: =SUM(T81:T90) -> 3954542 | U91: =SUM(U81:U90) -> 3305993 | V91: =SUM(V81:V90) -> 3488396 | W91: =SUM(W81:W90) -> 3276658 | ... BC91: =SUM(BC81:BC90) -> 9730049.9
B93: Total Assets | D93: USD '000s | E93: =SUM(E91,E78) -> 21274425 | F93: =SUM(F91,F78) -> 89724873 | G93: =SUM(G91,G78) -> 14753901 | H93: =SUM(H91,H78) -> 22541951 | I93: =SUM(I91,I78) -> 29671832 | J93: =SUM(J91,J78) -> 31727851 | K93: =SUM(K91,K78) -> 35370427 | L93: =SUM(L91,L78) -> 38394743 | ... N93: =SUM(N91,N78) -> 48006261 | P93: =SUM(P91,P78) -> 10201112 | Q93: =SUM(Q91,Q78) -> 15790208 | R93: =SUM(R91,R78) -> 18454271 | S93: =SUM(S91,S78) -> 21274425 | T93: =SUM(T91,T78) -> 20895194 | U93: =SUM(U91,U78) -> 105468243 | V93: =SUM(V91,V78) -> 111168363 | W93: =SUM(W91,W78) -> 89724873 | ... BC93: =SUM(BC91,BC78) -> 48006261
B95: Liabilities
B97: Current Liabilities:
B98: Accounts Payable | D98: USD '000s | E98: =S98 -> 39833 | F98: =W98 -> 56043 | G98: =AA98 -> 39294 | H98: =AE98 -> 63316 | I98: =AI98 -> 117605 | J98: =AM98 -> 71670.532 | K98: =AQ98 -> 80937.511 | L98: =AU98 -> 90601.931 | M98: =AY98 -> 105821.1 | N98: =BC98 -> 130314.97 | P98: 0 | Q98: 0 | R98: 0 | S98: 39833 | T98: 12650 | U98: 40745 | V98: 61514 | W98: 56043 | X98: 23694 | Y98: 27983 | Z98: 36744 | AA98: 39294 | AB98: 0 | AC98: 0 | AD98: 0 | AE98: 63316 | AF98: 0 | AG98: 0 | AH98: 0 | AI98: 117605 | AJ98: ='IS & BS Projections'!AK211 -> 0 | AK98: ='IS & BS Projections'!AL211 -> 0 | AL98: ='IS & BS Projections'!AM211 -> 0 | AM98: ='IS & BS Projections'!AN211 -> 71670.532 | AN98: ='IS & BS Projections'!AO211 -> 0 | AO98: ='IS & BS Projections'!AP211 -> 0 | AP98: ='IS & BS Projections'!AQ211 -> 0 | AQ98: ='IS & BS Projections'!AR211 -> 80937.511 | ... BC98: ='IS & BS Projections'!BD211 -> 130314.97
B99: Accounts Payable and Accrued Expenses | D99: USD '000s | E99: =S99 -> 0 | F99: =W99 -> 0 | G99: =AA99 -> 0 | H99: =AE99 -> 0 | I99: =AI99 -> 0 | J99: =AM99 -> 0 | K99: =AQ99 -> 0 | L99: =AU99 -> 0 | M99: =AY99 -> 0 | N99: =BC99 -> 0 | P99: 373955 | Q99: 266655 | R99: 290471 | S99: 0 | T99: 0 | U99: 0 | V99: 0 | W99: 0 | X99: 0 | Y99: 0 | Z99: 0 | AA99: 0 | AB99: 0 | AC99: 0 | AD99: 0 | AE99: 0 | AF99: 0 | AG99: 0 | AH99: 0 | AI99: 0 | AJ99: =_xlfn.XLOOKUP($B99,'IS & BS Projections'!$B:$B,'IS & BS Projections'!AK:AK) -> 0 | AK99: =_xlfn.XLOOKUP($B99,'IS & BS Projections'!$B:$B,'IS & BS Projections'!AL:AL) -> 0 | AL99: =_xlfn.XLOOKUP($B99,'IS & BS Projections'!$B:$B,'IS & BS Projections'!AM:AM) -> 0 | AM99: =_xlfn.XLOOKUP($B99,'IS & BS Projections'!$B:$B,'IS & BS Projections'!AN:AN) -> 0 | AN99: =_xlfn.XLOOKUP($B99,'IS & BS Projections'!$B:$B,'IS & BS Projections'!AO:AO) -> 0 | AO99: =_xlfn.XLOOKUP($B99,'IS & BS Projections'!$B:$B,'IS & BS Projections'!AP:AP) -> 0 | AP99: =_xlfn.XLOOKUP($B99,'IS & BS Projections'!$B:$B,'IS & BS Projections'!AQ:AQ) -> 0 | AQ99: =_xlfn.XLOOKUP($B99,'IS & BS Projections'!$B:$B,'IS & BS Projections'!AR:AR) -> 0 | AR99: =_xlfn.XLOOKUP($B99,'IS & BS Projections'!$B:$B,'IS & BS Projections'!AS:AS) -> 0 | AS99: =_xlfn.XLOOKUP($B99,'IS & BS Projections'!$B:$B,'IS & BS Projections'!AT:AT) -> 0 | AT99: =_xlfn.XLOOKUP($B99,'IS & BS Projections'!$B:$B,'IS & BS Projections'!AU:AU) -> 0 | AU99: =_xlfn.XLOOKUP($B99,'IS & BS Projections'!$B:$B,'IS & BS Projections'!AV:AV) -> 0 | AV99: =_xlfn.XLOOKUP($B99,'IS & BS Projections'!$B:$B,'IS & BS Projections'!AW:AW) -> 0 | AW99: =_xlfn.XLOOKUP($B99,'IS & BS Projections'!$B:$B,'IS & BS Projections'!AX:AX) -> 0 | AX99: =_xlfn.XLOOKUP($B99,'IS & BS Projections'!$B:$B,'IS & BS Projections'!AY:AY) -> 0 | AY99: =_xlfn.XLOOKUP($B99,'IS & BS Projections'!$B:$B,'IS & BS Projections'!AZ:AZ) -> 0 | AZ99: =_xlfn.XLOOKUP($B99,'IS & BS Projections'!$B:$B,'IS & BS Projections'!BA:BA) -> 0 | BA99: =_xlfn.XLOOKUP($B99,'IS & BS Projections'!$B:$B,'IS & BS Projections'!BB:BB) -> 0 | BB99: =_xlfn.XLOOKUP($B99,'IS & BS Projections'!$B:$B,'IS & BS Projections'!BC:BC) -> 0 | BC99: =_xlfn.XLOOKUP($B99,'IS & BS Projections'!$B:$B,'IS & BS Projections'!BD:BD) -> 0
B100: Accrued Expenses and Other Current Liabilities | D100: USD '000s | E100: =S100 -> 439559 | F100: =W100 -> 331236 | G100: =AA100 -> 456889 | H100: =AE100 -> 552662 | I100: =AI100 -> 687676 | J100: =AM100 -> 671673.05 | K100: =AQ100 -> 758520.18 | L100: =AU100 -> 849092 | M100: =AY100 -> 991721.11 | N100: =BC100 -> 1221269.7 | P100: 0 | Q100: 0 | R100: 0 | S100: 439559 | T100: 647960 | U100: 457399 | V100: 298101 | W100: 331236 | X100: 274983 | Y100: 262251 | Z100: 374374 | AA100: 456889 | AB100: 438321 | AC100: 448170 | AD100: 500603 | AE100: 552662 | AF100: 662042 | AG100: 601354 | AH100: 835468 | AI100: 687676 | AJ100: =_xlfn.XLOOKUP($B100,'IS & BS Projections'!$B:$B,'IS & BS Projections'!AK:AK) -> 606467.55 | AK100: =_xlfn.XLOOKUP($B100,'IS & BS Projections'!$B:$B,'IS & BS Projections'!AL:AL) -> 660704.7 | AL100: =_xlfn.XLOOKUP($B100,'IS & BS Projections'!$B:$B,'IS & BS Projections'!AM:AM) -> 1061307.5 | AM100: =_xlfn.XLOOKUP($B100,'IS & BS Projections'!$B:$B,'IS & BS Projections'!AN:AN) -> 671673.05 | AN100: =_xlfn.XLOOKUP($B100,'IS & BS Projections'!$B:$B,'IS & BS Projections'!AO:AO) -> 632890.91 | AO100: =_xlfn.XLOOKUP($B100,'IS & BS Projections'!$B:$B,'IS & BS Projections'!AP:AP) -> 751671.03 | AP100: =_xlfn.XLOOKUP($B100,'IS & BS Projections'!$B:$B,'IS & BS Projections'!AQ:AQ) -> 1224699.5 | AQ100: =_xlfn.XLOOKUP($B100,'IS & BS Projections'!$B:$B,'IS & BS Projections'!AR:AR) -> 758520.18 | AR100: =_xlfn.XLOOKUP($B100,'IS & BS Projections'!$B:$B,'IS & BS Projections'!AS:AS) -> 688941.84 | AS100: =_xlfn.XLOOKUP($B100,'IS & BS Projections'!$B:$B,'IS & BS Projections'!AT:AT) -> 860154.92 | AT100: =_xlfn.XLOOKUP($B100,'IS & BS Projections'!$B:$B,'IS & BS Projections'!AU:AU) -> 1380081.8 | AU100: =_xlfn.XLOOKUP($B100,'IS & BS Projections'!$B:$B,'IS & BS Projections'!AV:AV) -> 849092 | AV100: =_xlfn.XLOOKUP($B100,'IS & BS Projections'!$B:$B,'IS & BS Projections'!AW:AW) -> 760677.09 | AW100: =_xlfn.XLOOKUP($B100,'IS & BS Projections'!$B:$B,'IS & BS Projections'!AX:AX) -> 1022996.6 | AX100: =_xlfn.XLOOKUP($B100,'IS & BS Projections'!$B:$B,'IS & BS Projections'!AY:AY) -> 1621569.6 | AY100: =_xlfn.XLOOKUP($B100,'IS & BS Projections'!$B:$B,'IS & BS Projections'!AZ:AZ) -> 991721.11 | AZ100: =_xlfn.XLOOKUP($B100,'IS & BS Projections'!$B:$B,'IS & BS Projections'!BA:BA) -> 873969.11 | BA100: =_xlfn.XLOOKUP($B100,'IS & BS Projections'!$B:$B,'IS & BS Projections'!BB:BB) -> 1286434.4 | BB100: =_xlfn.XLOOKUP($B100,'IS & BS Projections'!$B:$B,'IS & BS Projections'!BC:BC) -> 2020604.3 | BC100: =_xlfn.XLOOKUP($B100,'IS & BS Projections'!$B:$B,'IS & BS Projections'!BD:BD) -> 1221269.7
B101: Short-term Borrowings | D101: USD '000s | E101: =S101 -> 0 | F101: =W101 -> 0 | G101: =AA101 -> 0 | H101: =AE101 -> 374268 | I101: =AI101 -> 452105 | J101: =AM101 -> 0 | K101: =AQ101 -> 0 | L101: =AU101 -> 0 | M101: =AY101 -> 0 | N101: =BC101 -> 0 | P101: 0 | Q101: 0 | R101: 0 | S101: 0 | T101: 0 | U101: 0 | V101: 0 | W101: 0 | X101: 0 | Y101: 0 | Z101: 0 | AA101: 0 | AB101: 0 | AC101: 0 | AD101: 0 | AE101: 374268 | AF101: 0 | AG101: 0 | AH101: 0 | AI101: 452105 | AJ101: =_xlfn.XLOOKUP($B101,'IS & BS Projections'!$B:$B,'IS & BS Projections'!AK:AK) -> 0 | AK101: =_xlfn.XLOOKUP($B101,'IS & BS Projections'!$B:$B,'IS & BS Projections'!AL:AL) -> 0 | AL101: =_xlfn.XLOOKUP($B101,'IS & BS Projections'!$B:$B,'IS & BS Projections'!AM:AM) -> 0 | AM101: =_xlfn.XLOOKUP($B101,'IS & BS Projections'!$B:$B,'IS & BS Projections'!AN:AN) -> 0 | AN101: =_xlfn.XLOOKUP($B101,'IS & BS Projections'!$B:$B,'IS & BS Projections'!AO:AO) -> 0 | AO101: =_xlfn.XLOOKUP($B101,'IS & BS Projections'!$B:$B,'IS & BS Projections'!AP:AP) -> 0 | AP101: =_xlfn.XLOOKUP($B101,'IS & BS Projections'!$B:$B,'IS & BS Projections'!AQ:AQ) -> 0 | AQ101: =_xlfn.XLOOKUP($B101,'IS & BS Projections'!$B:$B,'IS & BS Projections'!AR:AR) -> 0 | AR101: =_xlfn.XLOOKUP($B101,'IS & BS Projections'!$B:$B,'IS & BS Projections'!AS:AS) -> 0 | AS101: =_xlfn.XLOOKUP($B101,'IS & BS Projections'!$B:$B,'IS & BS Projections'!AT:AT) -> 0 | AT101: =_xlfn.XLOOKUP($B101,'IS & BS Projections'!$B:$B,'IS & BS Projections'!AU:AU) -> 0 | AU101: =_xlfn.XLOOKUP($B101,'IS & BS Projections'!$B:$B,'IS & BS Projections'!AV:AV) -> 0 | AV101: =_xlfn.XLOOKUP($B101,'IS & BS Projections'!$B:$B,'IS & BS Projections'!AW:AW) -> 0 | AW101: =_xlfn.XLOOKUP($B101,'IS & BS Projections'!$B:$B,'IS & BS Projections'!AX:AX) -> 0 | AX101: =_xlfn.XLOOKUP($B101,'IS & BS Projections'!$B:$B,'IS & BS Projections'!AY:AY) -> 0 | AY101: =_xlfn.XLOOKUP($B101,'IS & BS Projections'!$B:$B,'IS & BS Projections'!AZ:AZ) -> 0 | AZ101: =_xlfn.XLOOKUP($B101,'IS & BS Projections'!$B:$B,'IS & BS Projections'!BA:BA) -> 0 | BA101: =_xlfn.XLOOKUP($B101,'IS & BS Projections'!$B:$B,'IS & BS Projections'!BB:BB) -> 0 | BB101: =_xlfn.XLOOKUP($B101,'IS & BS Projections'!$B:$B,'IS & BS Projections'!BC:BC) -> 0 | BC101: =_xlfn.XLOOKUP($B101,'IS & BS Projections'!$B:$B,'IS & BS Projections'!BD:BD) -> 0
B102: Crypto Asset Borrowings | D102: USD '000s | E102: =S102 -> 426665 | F102: =W102 -> 151505 | G102: =AA102 -> 62980 | H102: =AE102 -> 0 | I102: =AI102 -> 0 | J102: =AM102 -> 114872.76 | K102: =AQ102 -> 129725.77 | L102: =AU102 -> 145215.8 | M102: =AY102 -> 169608.92 | N102: =BC102 -> 208867.43 | P102: 543820 | Q102: 366991 | R102: 445172 | S102: 426665 | T102: 485564 | U102: 136548 | V102: 209678 | W102: 151505 | X102: 167823 | Y102: 144503 | Z102: 109255 | AA102: 62980 | AB102: 272805 | AC102: 237474 | AD102: 265259 | AE102: 0 | AF102: 272608 | AG102: 268550 | AH102: 386823 | AI102: 0 | AJ102: =_xlfn.XLOOKUP($B102,'IS & BS Projections'!$B:$B,'IS & BS Projections'!AK:AK) -> 404829.96 | AK102: =_xlfn.XLOOKUP($B102,'IS & BS Projections'!$B:$B,'IS & BS Projections'!AL:AL) -> 301278.57 | AL102: =_xlfn.XLOOKUP($B102,'IS & BS Projections'!$B:$B,'IS & BS Projections'!AM:AM) -> 522471.87 | AM102: =_xlfn.XLOOKUP($B102,'IS & BS Projections'!$B:$B,'IS & BS Projections'!AN:AN) -> 114872.76 | AN102: =_xlfn.XLOOKUP($B102,'IS & BS Projections'!$B:$B,'IS & BS Projections'!AO:AO) -> 422468.11 | AO102: =_xlfn.XLOOKUP($B102,'IS & BS Projections'!$B:$B,'IS & BS Projections'!AP:AP) -> 342758.83 | AP102: =_xlfn.XLOOKUP($B102,'IS & BS Projections'!$B:$B,'IS & BS Projections'!AQ:AQ) -> 602908.21 | AQ102: =_xlfn.XLOOKUP($B102,'IS & BS Projections'!$B:$B,'IS & BS Projections'!AR:AR) -> 129725.77 | AR102: =_xlfn.XLOOKUP($B102,'IS & BS Projections'!$B:$B,'IS & BS Projections'!AS:AS) -> 459883.3 | AS102: =_xlfn.XLOOKUP($B102,'IS & BS Projections'!$B:$B,'IS & BS Projections'!AT:AT) -> 392227.03 | AT102: =_xlfn.XLOOKUP($B102,'IS & BS Projections'!$B:$B,'IS & BS Projections'!AU:AU) -> 679401.49 | AU102: =_xlfn.XLOOKUP($B102,'IS & BS Projections'!$B:$B,'IS & BS Projections'!AV:AV) -> 145215.8 | AV102: =_xlfn.XLOOKUP($B102,'IS & BS Projections'!$B:$B,'IS & BS Projections'!AW:AW) -> 507768.1 | AW102: =_xlfn.XLOOKUP($B102,'IS & BS Projections'!$B:$B,'IS & BS Projections'!AX:AX) -> 466482.13 | AX102: =_xlfn.XLOOKUP($B102,'IS & BS Projections'!$B:$B,'IS & BS Projections'!AY:AY) -> 798283.68 | AY102: =_xlfn.XLOOKUP($B102,'IS & BS Projections'!$B:$B,'IS & BS Projections'!AZ:AZ) -> 169608.92 | AZ102: =_xlfn.XLOOKUP($B102,'IS & BS Projections'!$B:$B,'IS & BS Projections'!BA:BA) -> 583392.93 | BA102: =_xlfn.XLOOKUP($B102,'IS & BS Projections'!$B:$B,'IS & BS Projections'!BB:BB) -> 586608.7 | BB102: =_xlfn.XLOOKUP($B102,'IS & BS Projections'!$B:$B,'IS & BS Projections'!BC:BC) -> 994724.78 | BC102: =_xlfn.XLOOKUP($B102,'IS & BS Projections'!$B:$B,'IS & BS Projections'!BD:BD) -> 208867.43
B103: Current Portion of Long-term Debt | D103: USD '000s | E103: =S103 -> 0 | F103: =W103 -> 0 | G103: =AA103 -> 0 | H103: =AE103 -> 0 | I103: =AI103 -> 1269585 | J103: =AM103 -> 0 | K103: =AQ103 -> 0 | L103: =AU103 -> 1000000 | M103: =AY103 -> 1500000 | N103: =BC103 -> 0 | P103: 0 | Q103: 0 | R103: 0 | S103: 0 | T103: 0 | U103: 0 | V103: 0 | W103: 0 | X103: 0 | Y103: 0 | Z103: 0 | AA103: 0 | AB103: 0 | AC103: 0 | AD103: 0 | AE103: 0 | AF103: 0 | AG103: 1266577 | AH103: 1268081 | AI103: 1269585 | AJ103: ='D&E Schedule'!AC10 -> 0 | AK103: ='D&E Schedule'!AD10 -> 1273013 | AL103: ='D&E Schedule'!AE10 -> 0 | AM103: ='D&E Schedule'!AF10 -> 0 | AN103: ='D&E Schedule'!AG10 -> 0 | AO103: ='D&E Schedule'!AH10 -> 0 | AP103: ='D&E Schedule'!AI10 -> 0 | AQ103: ='D&E Schedule'!AJ10 -> 0 | ... BC103: ='D&E Schedule'!AV10 -> 0
B104: Lease Liabilities, Current | D104: USD '000s | E104: =S104 -> 32366 | F104: =W104 -> 33734 | G104: =AA104 -> 0 | H104: =AE104 -> 0 | I104: =AI104 -> 0 | J104: =AM104 -> 0 | K104: =AQ104 -> 0 | L104: =AU104 -> 0 | M104: =AY104 -> 0 | N104: =BC104 -> 0 | P104: 29695 | Q104: 30933 | R104: 31854 | S104: 32366 | T104: 32688 | U104: 34174 | V104: 33025 | W104: 33734 | X104: 12776 | Y104: 12350 | Z104: 12015 | AA104: 0 | AB104: 0 | AC104: 0 | AD104: 0 | AE104: 0 | AF104: 0 | AG104: 0 | AH104: 0 | AI104: 0 | AJ104: =_xlfn.XLOOKUP($B104,'IS & BS Projections'!$B:$B,'IS & BS Projections'!AK:AK) -> 30724.057 | AK104: =_xlfn.XLOOKUP($B104,'IS & BS Projections'!$B:$B,'IS & BS Projections'!AL:AL) -> 24761.854 | AL104: =_xlfn.XLOOKUP($B104,'IS & BS Projections'!$B:$B,'IS & BS Projections'!AM:AM) -> 42307.554 | AM104: =_xlfn.XLOOKUP($B104,'IS & BS Projections'!$B:$B,'IS & BS Projections'!AN:AN) -> 0 | AN104: =_xlfn.XLOOKUP($B104,'IS & BS Projections'!$B:$B,'IS & BS Projections'!AO:AO) -> 32062.683 | AO104: =_xlfn.XLOOKUP($B104,'IS & BS Projections'!$B:$B,'IS & BS Projections'!AP:AP) -> 28171.086 | AP104: =_xlfn.XLOOKUP($B104,'IS & BS Projections'!$B:$B,'IS & BS Projections'!AQ:AQ) -> 48820.947 | AQ104: =_xlfn.XLOOKUP($B104,'IS & BS Projections'!$B:$B,'IS & BS Projections'!AR:AR) -> 0 | AR104: =_xlfn.XLOOKUP($B104,'IS & BS Projections'!$B:$B,'IS & BS Projections'!AS:AS) -> 34902.261 | AS104: =_xlfn.XLOOKUP($B104,'IS & BS Projections'!$B:$B,'IS & BS Projections'!AT:AT) -> 32236.839 | AT104: =_xlfn.XLOOKUP($B104,'IS & BS Projections'!$B:$B,'IS & BS Projections'!AU:AU) -> 55015.048 | AU104: =_xlfn.XLOOKUP($B104,'IS & BS Projections'!$B:$B,'IS & BS Projections'!AV:AV) -> 0 | AV104: =_xlfn.XLOOKUP($B104,'IS & BS Projections'!$B:$B,'IS & BS Projections'!AW:AW) -> 38536.417 | AW104: =_xlfn.XLOOKUP($B104,'IS & BS Projections'!$B:$B,'IS & BS Projections'!AX:AX) -> 38339.809 | AX104: =_xlfn.XLOOKUP($B104,'IS & BS Projections'!$B:$B,'IS & BS Projections'!AY:AY) -> 64641.622 | AY104: =_xlfn.XLOOKUP($B104,'IS & BS Projections'!$B:$B,'IS & BS Projections'!AZ:AZ) -> 0 | AZ104: =_xlfn.XLOOKUP($B104,'IS & BS Projections'!$B:$B,'IS & BS Projections'!BA:BA) -> 44275.868 | BA104: =_xlfn.XLOOKUP($B104,'IS & BS Projections'!$B:$B,'IS & BS Projections'!BB:BB) -> 48212.919 | BB104: =_xlfn.XLOOKUP($B104,'IS & BS Projections'!$B:$B,'IS & BS Projections'!BC:BC) -> 80548.589 | BC104: =_xlfn.XLOOKUP($B104,'IS & BS Projections'!$B:$B,'IS & BS Projections'!BD:BD) -> 0
B105: Other Current Liabilities | D105: USD '000s | E105: =S105 -> 0 | F105: =W105 -> 0 | G105: =AA105 -> 0 | H105: =AE105 -> 0 | I105: =AI105 -> 0 | J105: =AM105 -> 0 | K105: =AQ105 -> 0 | L105: =AU105 -> 0 | M105: =AY105 -> 0 | N105: =BC105 -> 0 | P105: 84832 | Q105: 44480 | R105: 39684 | S105: 0 | T105: 0 | U105: 0 | V105: 0 | W105: 0 | X105: 0 | Y105: 0 | Z105: 0 | AA105: 0 | AB105: 0 | AC105: 0 | AD105: 0 | AE105: 0 | AF105: 0 | AG105: 0 | AH105: 0 | AI105: 0 | AJ105: =_xlfn.XLOOKUP($B105,'IS & BS Projections'!$B:$B,'IS & BS Projections'!AK:AK) -> 0 | AK105: =_xlfn.XLOOKUP($B105,'IS & BS Projections'!$B:$B,'IS & BS Projections'!AL:AL) -> 0 | AL105: =_xlfn.XLOOKUP($B105,'IS & BS Projections'!$B:$B,'IS & BS Projections'!AM:AM) -> 0 | AM105: =_xlfn.XLOOKUP($B105,'IS & BS Projections'!$B:$B,'IS & BS Projections'!AN:AN) -> 0 | AN105: =_xlfn.XLOOKUP($B105,'IS & BS Projections'!$B:$B,'IS & BS Projections'!AO:AO) -> 0 | AO105: =_xlfn.XLOOKUP($B105,'IS & BS Projections'!$B:$B,'IS & BS Projections'!AP:AP) -> 0 | AP105: =_xlfn.XLOOKUP($B105,'IS & BS Projections'!$B:$B,'IS & BS Projections'!AQ:AQ) -> 0 | AQ105: =_xlfn.XLOOKUP($B105,'IS & BS Projections'!$B:$B,'IS & BS Projections'!AR:AR) -> 0 | AR105: =_xlfn.XLOOKUP($B105,'IS & BS Projections'!$B:$B,'IS & BS Projections'!AS:AS) -> 0 | AS105: =_xlfn.XLOOKUP($B105,'IS & BS Projections'!$B:$B,'IS & BS Projections'!AT:AT) -> 0 | AT105: =_xlfn.XLOOKUP($B105,'IS & BS Projections'!$B:$B,'IS & BS Projections'!AU:AU) -> 0 | AU105: =_xlfn.XLOOKUP($B105,'IS & BS Projections'!$B:$B,'IS & BS Projections'!AV:AV) -> 0 | AV105: =_xlfn.XLOOKUP($B105,'IS & BS Projections'!$B:$B,'IS & BS Projections'!AW:AW) -> 0 | AW105: =_xlfn.XLOOKUP($B105,'IS & BS Projections'!$B:$B,'IS & BS Projections'!AX:AX) -> 0 | AX105: =_xlfn.XLOOKUP($B105,'IS & BS Projections'!$B:$B,'IS & BS Projections'!AY:AY) -> 0 | AY105: =_xlfn.XLOOKUP($B105,'IS & BS Projections'!$B:$B,'IS & BS Projections'!AZ:AZ) -> 0 | AZ105: =_xlfn.XLOOKUP($B105,'IS & BS Projections'!$B:$B,'IS & BS Projections'!BA:BA) -> 0 | BA105: =_xlfn.XLOOKUP($B105,'IS & BS Projections'!$B:$B,'IS & BS Projections'!BB:BB) -> 0 | BB105: =_xlfn.XLOOKUP($B105,'IS & BS Projections'!$B:$B,'IS & BS Projections'!BC:BC) -> 0 | BC105: =_xlfn.XLOOKUP($B105,'IS & BS Projections'!$B:$B,'IS & BS Projections'!BD:BD) -> 0
B106: Obligation to Return Collateral | D106: USD '000s | E106: =S106 -> 0 | F106: =W106 -> 0 | G106: =AA106 -> 355071 | H106: =AE106 -> 792125 | I106: =AI106 -> 826883 | J106: =AM106 -> 606630.47 | K106: =AQ106 -> 685067.61 | L106: =AU106 -> 766868.75 | M106: =AY106 -> 895686.13 | N106: =BC106 -> 1103006 | P106: 0 | Q106: 0 | R106: 0 | S106: 0 | T106: 0 | U106: 0 | V106: 0 | W106: 0 | X106: 0 | Y106: 0 | Z106: 0 | AA106: 355071 | AB106: 315090 | AC106: 272171 | AD106: 118224 | AE106: 792125 | AF106: 628854 | AG106: 972661 | AH106: 1026945 | AI106: 826883 | AJ106: =_xlfn.XLOOKUP($B106,'IS & BS Projections'!$B:$B,'IS & BS Projections'!AK:AK) -> 0 | AK106: =_xlfn.XLOOKUP($B106,'IS & BS Projections'!$B:$B,'IS & BS Projections'!AL:AL) -> 0 | AL106: =_xlfn.XLOOKUP($B106,'IS & BS Projections'!$B:$B,'IS & BS Projections'!AM:AM) -> 0 | AM106: =_xlfn.XLOOKUP($B106,'IS & BS Projections'!$B:$B,'IS & BS Projections'!AN:AN) -> 606630.47 | AN106: =_xlfn.XLOOKUP($B106,'IS & BS Projections'!$B:$B,'IS & BS Projections'!AO:AO) -> 0 | AO106: =_xlfn.XLOOKUP($B106,'IS & BS Projections'!$B:$B,'IS & BS Projections'!AP:AP) -> 0 | AP106: =_xlfn.XLOOKUP($B106,'IS & BS Projections'!$B:$B,'IS & BS Projections'!AQ:AQ) -> 0 | AQ106: =_xlfn.XLOOKUP($B106,'IS & BS Projections'!$B:$B,'IS & BS Projections'!AR:AR) -> 685067.61 | AR106: =_xlfn.XLOOKUP($B106,'IS & BS Projections'!$B:$B,'IS & BS Projections'!AS:AS) -> 0 | AS106: =_xlfn.XLOOKUP($B106,'IS & BS Projections'!$B:$B,'IS & BS Projections'!AT:AT) -> 0 | AT106: =_xlfn.XLOOKUP($B106,'IS & BS Projections'!$B:$B,'IS & BS Projections'!AU:AU) -> 0 | AU106: =_xlfn.XLOOKUP($B106,'IS & BS Projections'!$B:$B,'IS & BS Projections'!AV:AV) -> 766868.75 | AV106: =_xlfn.XLOOKUP($B106,'IS & BS Projections'!$B:$B,'IS & BS Projections'!AW:AW) -> 0 | AW106: =_xlfn.XLOOKUP($B106,'IS & BS Projections'!$B:$B,'IS & BS Projections'!AX:AX) -> 0 | AX106: =_xlfn.XLOOKUP($B106,'IS & BS Projections'!$B:$B,'IS & BS Projections'!AY:AY) -> 0 | AY106: =_xlfn.XLOOKUP($B106,'IS & BS Projections'!$B:$B,'IS & BS Projections'!AZ:AZ) -> 895686.13 | AZ106: =_xlfn.XLOOKUP($B106,'IS & BS Projections'!$B:$B,'IS & BS Projections'!BA:BA) -> 0 | BA106: =_xlfn.XLOOKUP($B106,'IS & BS Projections'!$B:$B,'IS & BS Projections'!BB:BB) -> 0 | BB106: =_xlfn.XLOOKUP($B106,'IS & BS Projections'!$B:$B,'IS & BS Projections'!BC:BC) -> 0 | BC106: =_xlfn.XLOOKUP($B106,'IS & BS Projections'!$B:$B,'IS & BS Projections'!BD:BD) -> 1103006
B107: Custodial Funds Due to Customers | D107: USD '000s | E107: =S107 -> 10480612 | F107: =W107 -> 4829587 | G107: =AA107 -> 4570845 | H107: =AE107 -> 6158949 | I107: =AI107 -> 0 | J107: =AM107 -> 7297652.1 | K107: =AQ107 -> 8241236.3 | L107: =AU107 -> 9225288.9 | M107: =AY107 -> 10774938 | N107: =BC107 -> 13268958 | P107: 6223846 | Q107: 8968505 | R107: 8807978 | S107: 10480612 | T107: 9742961 | U107: 0 | V107: 0 | W107: 4829587 | X107: 0 | Y107: 0 | Z107: 0 | AA107: 4570845 | AB107: 0 | AC107: 0 | AD107: 0 | AE107: 6158949 | AF107: 0 | AG107: 0 | AH107: 0 | AI107: 0 | AJ107: =_xlfn.XLOOKUP($B107,'IS & BS Projections'!$B:$B,'IS & BS Projections'!AK:AK) -> 0 | AK107: =_xlfn.XLOOKUP($B107,'IS & BS Projections'!$B:$B,'IS & BS Projections'!AL:AL) -> 0 | AL107: =_xlfn.XLOOKUP($B107,'IS & BS Projections'!$B:$B,'IS & BS Projections'!AM:AM) -> 0 | AM107: =_xlfn.XLOOKUP($B107,'IS & BS Projections'!$B:$B,'IS & BS Projections'!AN:AN) -> 7297652.1 | AN107: =_xlfn.XLOOKUP($B107,'IS & BS Projections'!$B:$B,'IS & BS Projections'!AO:AO) -> 0 | AO107: =_xlfn.XLOOKUP($B107,'IS & BS Projections'!$B:$B,'IS & BS Projections'!AP:AP) -> 0 | AP107: =_xlfn.XLOOKUP($B107,'IS & BS Projections'!$B:$B,'IS & BS Projections'!AQ:AQ) -> 0 | AQ107: =_xlfn.XLOOKUP($B107,'IS & BS Projections'!$B:$B,'IS & BS Projections'!AR:AR) -> 8241236.3 | AR107: =_xlfn.XLOOKUP($B107,'IS & BS Projections'!$B:$B,'IS & BS Projections'!AS:AS) -> 0 | AS107: =_xlfn.XLOOKUP($B107,'IS & BS Projections'!$B:$B,'IS & BS Projections'!AT:AT) -> 0 | AT107: =_xlfn.XLOOKUP($B107,'IS & BS Projections'!$B:$B,'IS & BS Projections'!AU:AU) -> 0 | AU107: =_xlfn.XLOOKUP($B107,'IS & BS Projections'!$B:$B,'IS & BS Projections'!AV:AV) -> 9225288.9 | AV107: =_xlfn.XLOOKUP($B107,'IS & BS Projections'!$B:$B,'IS & BS Projections'!AW:AW) -> 0 | AW107: =_xlfn.XLOOKUP($B107,'IS & BS Projections'!$B:$B,'IS & BS Projections'!AX:AX) -> 0 | AX107: =_xlfn.XLOOKUP($B107,'IS & BS Projections'!$B:$B,'IS & BS Projections'!AY:AY) -> 0 | AY107: =_xlfn.XLOOKUP($B107,'IS & BS Projections'!$B:$B,'IS & BS Projections'!AZ:AZ) -> 10774938 | AZ107: =_xlfn.XLOOKUP($B107,'IS & BS Projections'!$B:$B,'IS & BS Projections'!BA:BA) -> 0 | BA107: =_xlfn.XLOOKUP($B107,'IS & BS Projections'!$B:$B,'IS & BS Projections'!BB:BB) -> 0 | BB107: =_xlfn.XLOOKUP($B107,'IS & BS Projections'!$B:$B,'IS & BS Projections'!BC:BC) -> 0 | BC107: =_xlfn.XLOOKUP($B107,'IS & BS Projections'!$B:$B,'IS & BS Projections'!BD:BD) -> 13268958
B108: Customer Crypto liabilities | D108: USD '000s | E108: =S108 -> 0 | F108: =W108 -> 0 | G108: =AA108 -> 0 | H108: =AE108 -> 0 | I108: =AI108 -> 0 | J108: =AM108 -> 0 | K108: =AQ108 -> 0 | L108: =AU108 -> 0 | M108: =AY108 -> 0 | N108: =BC108 -> 0 | P108: 0 | Q108: 0 | R108: 0 | S108: 0 | T108: 0 | U108: 88453873 | V108: 95113124 | W108: 0 | X108: 124357889 | Y108: 124243587 | Z108: 0 | AA108: 0 | AB108: 0 | AC108: 0 | AD108: 0 | AE108: 0 | AF108: 0 | AG108: 0 | AH108: 0 | AI108: 0 | AJ108: =_xlfn.XLOOKUP($B108,'IS & BS Projections'!$B:$B,'IS & BS Projections'!AK:AK) -> 0 | AK108: =_xlfn.XLOOKUP($B108,'IS & BS Projections'!$B:$B,'IS & BS Projections'!AL:AL) -> 0 | AL108: =_xlfn.XLOOKUP($B108,'IS & BS Projections'!$B:$B,'IS & BS Projections'!AM:AM) -> 0 | AM108: =_xlfn.XLOOKUP($B108,'IS & BS Projections'!$B:$B,'IS & BS Projections'!AN:AN) -> 0 | AN108: =_xlfn.XLOOKUP($B108,'IS & BS Projections'!$B:$B,'IS & BS Projections'!AO:AO) -> 0 | AO108: =_xlfn.XLOOKUP($B108,'IS & BS Projections'!$B:$B,'IS & BS Projections'!AP:AP) -> 0 | AP108: =_xlfn.XLOOKUP($B108,'IS & BS Projections'!$B:$B,'IS & BS Projections'!AQ:AQ) -> 0 | AQ108: =_xlfn.XLOOKUP($B108,'IS & BS Projections'!$B:$B,'IS & BS Projections'!AR:AR) -> 0 | AR108: =_xlfn.XLOOKUP($B108,'IS & BS Projections'!$B:$B,'IS & BS Projections'!AS:AS) -> 0 | AS108: =_xlfn.XLOOKUP($B108,'IS & BS Projections'!$B:$B,'IS & BS Projections'!AT:AT) -> 0 | AT108: =_xlfn.XLOOKUP($B108,'IS & BS Projections'!$B:$B,'IS & BS Projections'!AU:AU) -> 0 | AU108: =_xlfn.XLOOKUP($B108,'IS & BS Projections'!$B:$B,'IS & BS Projections'!AV:AV) -> 0 | AV108: =_xlfn.XLOOKUP($B108,'IS & BS Projections'!$B:$B,'IS & BS Projections'!AW:AW) -> 0 | AW108: =_xlfn.XLOOKUP($B108,'IS & BS Projections'!$B:$B,'IS & BS Projections'!AX:AX) -> 0 | AX108: =_xlfn.XLOOKUP($B108,'IS & BS Projections'!$B:$B,'IS & BS Projections'!AY:AY) -> 0 | AY108: =_xlfn.XLOOKUP($B108,'IS & BS Projections'!$B:$B,'IS & BS Projections'!AZ:AZ) -> 0 | AZ108: =_xlfn.XLOOKUP($B108,'IS & BS Projections'!$B:$B,'IS & BS Projections'!BA:BA) -> 0 | BA108: =_xlfn.XLOOKUP($B108,'IS & BS Projections'!$B:$B,'IS & BS Projections'!BB:BB) -> 0 | BB108: =_xlfn.XLOOKUP($B108,'IS & BS Projections'!$B:$B,'IS & BS Projections'!BC:BC) -> 0 | BC108: =_xlfn.XLOOKUP($B108,'IS & BS Projections'!$B:$B,'IS & BS Projections'!BD:BD) -> 0
B109: Customer Custodial Cash liabilities | D109: USD '000s | E109: =S109 -> 0 | F109: =W109 -> 0 | G109: =AA109 -> 0 | H109: =AE109 -> 0 | I109: =AI109 -> 0 | J109: =AM109 -> 0 | K109: =AQ109 -> 0 | L109: =AU109 -> 0 | M109: =AY109 -> 0 | N109: =BC109 -> 0 | P109: 0 | Q109: 0 | R109: 0 | S109: 0 | T109: 0 | U109: 7071557 | V109: 6357657 | W109: 0 | X109: 5365658 | Y109: 3848078 | Z109: 3474489 | AA109: 0 | AB109: 5201906 | AC109: 4197837 | AD109: 4035045 | AE109: 0 | AF109: 0 | AG109: 5121640 | AH109: 5672037 | AI109: 0 | AJ109: =_xlfn.XLOOKUP($B109,'IS & BS Projections'!$B:$B,'IS & BS Projections'!AK:AK) -> 0 | AK109: =_xlfn.XLOOKUP($B109,'IS & BS Projections'!$B:$B,'IS & BS Projections'!AL:AL) -> 6100926.8 | AL109: =_xlfn.XLOOKUP($B109,'IS & BS Projections'!$B:$B,'IS & BS Projections'!AM:AM) -> 7947694.6 | AM109: =_xlfn.XLOOKUP($B109,'IS & BS Projections'!$B:$B,'IS & BS Projections'!AN:AN) -> 0 | AN109: =_xlfn.XLOOKUP($B109,'IS & BS Projections'!$B:$B,'IS & BS Projections'!AO:AO) -> 0 | AO109: =_xlfn.XLOOKUP($B109,'IS & BS Projections'!$B:$B,'IS & BS Projections'!AP:AP) -> 6940907.1 | AP109: =_xlfn.XLOOKUP($B109,'IS & BS Projections'!$B:$B,'IS & BS Projections'!AQ:AQ) -> 9171269.5 | AQ109: =_xlfn.XLOOKUP($B109,'IS & BS Projections'!$B:$B,'IS & BS Projections'!AR:AR) -> 0 | AR109: =_xlfn.XLOOKUP($B109,'IS & BS Projections'!$B:$B,'IS & BS Projections'!AS:AS) -> 0 | AS109: =_xlfn.XLOOKUP($B109,'IS & BS Projections'!$B:$B,'IS & BS Projections'!AT:AT) -> 7942644 | AT109: =_xlfn.XLOOKUP($B109,'IS & BS Projections'!$B:$B,'IS & BS Projections'!AU:AU) -> 10334864 | AU109: =_xlfn.XLOOKUP($B109,'IS & BS Projections'!$B:$B,'IS & BS Projections'!AV:AV) -> 0 | AV109: =_xlfn.XLOOKUP($B109,'IS & BS Projections'!$B:$B,'IS & BS Projections'!AW:AW) -> 0 | AW109: =_xlfn.XLOOKUP($B109,'IS & BS Projections'!$B:$B,'IS & BS Projections'!AX:AX) -> 9446318.6 | AX109: =_xlfn.XLOOKUP($B109,'IS & BS Projections'!$B:$B,'IS & BS Projections'!AY:AY) -> 12143266 | AY109: =_xlfn.XLOOKUP($B109,'IS & BS Projections'!$B:$B,'IS & BS Projections'!AZ:AZ) -> 0 | AZ109: =_xlfn.XLOOKUP($B109,'IS & BS Projections'!$B:$B,'IS & BS Projections'!BA:BA) -> 0 | BA109: =_xlfn.XLOOKUP($B109,'IS & BS Projections'!$B:$B,'IS & BS Projections'!BB:BB) -> 11878896 | BB109: =_xlfn.XLOOKUP($B109,'IS & BS Projections'!$B:$B,'IS & BS Projections'!BC:BC) -> 15131472 | BC109: =_xlfn.XLOOKUP($B109,'IS & BS Projections'!$B:$B,'IS & BS Projections'!BD:BD) -> 0
B110: Safeguarding Customer Crypto liabilities | D110: USD '000s | E110: =S110 -> 0 | F110: =W110 -> 75413188 | G110: =AA110 -> 0 | H110: =AE110 -> 0 | I110: =AI110 -> 0 | J110: =AM110 -> 0 | K110: =AQ110 -> 0 | L110: =AU110 -> 0 | M110: =AY110 -> 0 | N110: =BC110 -> 0 | P110: 0 | Q110: 0 | R110: 0 | S110: 0 | T110: 0 | U110: 0 | V110: 0 | W110: 75413188 | X110: 0 | Y110: 0 | Z110: 114291909 | AA110: 0 | AB110: 329506477 | AC110: 269198067 | AD110: 272669307 | AE110: 0 | AF110: 0 | AG110: 0 | AH110: 0 | AI110: 0 | AJ110: =_xlfn.XLOOKUP($B110,'IS & BS Projections'!$B:$B,'IS & BS Projections'!AK:AK) -> 0 | AK110: =_xlfn.XLOOKUP($B110,'IS & BS Projections'!$B:$B,'IS & BS Projections'!AL:AL) -> 0 | AL110: =_xlfn.XLOOKUP($B110,'IS & BS Projections'!$B:$B,'IS & BS Projections'!AM:AM) -> 0 | AM110: =_xlfn.XLOOKUP($B110,'IS & BS Projections'!$B:$B,'IS & BS Projections'!AN:AN) -> 0 | AN110: =_xlfn.XLOOKUP($B110,'IS & BS Projections'!$B:$B,'IS & BS Projections'!AO:AO) -> 0 | AO110: =_xlfn.XLOOKUP($B110,'IS & BS Projections'!$B:$B,'IS & BS Projections'!AP:AP) -> 0 | AP110: =_xlfn.XLOOKUP($B110,'IS & BS Projections'!$B:$B,'IS & BS Projections'!AQ:AQ) -> 0 | AQ110: =_xlfn.XLOOKUP($B110,'IS & BS Projections'!$B:$B,'IS & BS Projections'!AR:AR) -> 0 | AR110: =_xlfn.XLOOKUP($B110,'IS & BS Projections'!$B:$B,'IS & BS Projections'!AS:AS) -> 0 | AS110: =_xlfn.XLOOKUP($B110,'IS & BS Projections'!$B:$B,'IS & BS Projections'!AT:AT) -> 0 | AT110: =_xlfn.XLOOKUP($B110,'IS & BS Projections'!$B:$B,'IS & BS Projections'!AU:AU) -> 0 | AU110: =_xlfn.XLOOKUP($B110,'IS & BS Projections'!$B:$B,'IS & BS Projections'!AV:AV) -> 0 | AV110: =_xlfn.XLOOKUP($B110,'IS & BS Projections'!$B:$B,'IS & BS Projections'!AW:AW) -> 0 | AW110: =_xlfn.XLOOKUP($B110,'IS & BS Projections'!$B:$B,'IS & BS Projections'!AX:AX) -> 0 | AX110: =_xlfn.XLOOKUP($B110,'IS & BS Projections'!$B:$B,'IS & BS Projections'!AY:AY) -> 0 | AY110: =_xlfn.XLOOKUP($B110,'IS & BS Projections'!$B:$B,'IS & BS Projections'!AZ:AZ) -> 0 | AZ110: =_xlfn.XLOOKUP($B110,'IS & BS Projections'!$B:$B,'IS & BS Projections'!BA:BA) -> 0 | BA110: =_xlfn.XLOOKUP($B110,'IS & BS Projections'!$B:$B,'IS & BS Projections'!BB:BB) -> 0 | BB110: =_xlfn.XLOOKUP($B110,'IS & BS Projections'!$B:$B,'IS & BS Projections'!BC:BC) -> 0 | BC110: =_xlfn.XLOOKUP($B110,'IS & BS Projections'!$B:$B,'IS & BS Projections'!BD:BD) -> 0
B111: Customer Custodial fund liabilities | D111: USD '000s | E111: =S111 -> 0 | F111: =W111 -> 0 | G111: =AA111 -> 0 | H111: =AE111 -> 0 | I111: =AI111 -> 5347428 | J111: =AM111 -> 0 | K111: =AQ111 -> 0 | L111: =AU111 -> 0 | M111: =AY111 -> 0 | N111: =BC111 -> 0 | P111: 0 | Q111: 0 | R111: 0 | S111: 0 | T111: 0 | U111: 0 | V111: 0 | W111: 0 | X111: 0 | Y111: 0 | Z111: 0 | AA111: 0 | AB111: 0 | AC111: 0 | AD111: 0 | AE111: 0 | AF111: 5369865 | AG111: 0 | AH111: 0 | AI111: 5347428 | AJ111: =_xlfn.XLOOKUP($B111,'IS & BS Projections'!$B:$B,'IS & BS Projections'!AK:AK) -> 0 | AK111: =_xlfn.XLOOKUP($B111,'IS & BS Projections'!$B:$B,'IS & BS Projections'!AL:AL) -> 0 | AL111: =_xlfn.XLOOKUP($B111,'IS & BS Projections'!$B:$B,'IS & BS Projections'!AM:AM) -> 0 | AM111: =_xlfn.XLOOKUP($B111,'IS & BS Projections'!$B:$B,'IS & BS Projections'!AN:AN) -> 0 | AN111: =_xlfn.XLOOKUP($B111,'IS & BS Projections'!$B:$B,'IS & BS Projections'!AO:AO) -> 0 | AO111: =_xlfn.XLOOKUP($B111,'IS & BS Projections'!$B:$B,'IS & BS Projections'!AP:AP) -> 0 | AP111: =_xlfn.XLOOKUP($B111,'IS & BS Projections'!$B:$B,'IS & BS Projections'!AQ:AQ) -> 0 | AQ111: =_xlfn.XLOOKUP($B111,'IS & BS Projections'!$B:$B,'IS & BS Projections'!AR:AR) -> 0 | AR111: =_xlfn.XLOOKUP($B111,'IS & BS Projections'!$B:$B,'IS & BS Projections'!AS:AS) -> 0 | AS111: =_xlfn.XLOOKUP($B111,'IS & BS Projections'!$B:$B,'IS & BS Projections'!AT:AT) -> 0 | AT111: =_xlfn.XLOOKUP($B111,'IS & BS Projections'!$B:$B,'IS & BS Projections'!AU:AU) -> 0 | AU111: =_xlfn.XLOOKUP($B111,'IS & BS Projections'!$B:$B,'IS & BS Projections'!AV:AV) -> 0 | AV111: =_xlfn.XLOOKUP($B111,'IS & BS Projections'!$B:$B,'IS & BS Projections'!AW:AW) -> 0 | AW111: =_xlfn.XLOOKUP($B111,'IS & BS Projections'!$B:$B,'IS & BS Projections'!AX:AX) -> 0 | AX111: =_xlfn.XLOOKUP($B111,'IS & BS Projections'!$B:$B,'IS & BS Projections'!AY:AY) -> 0 | AY111: =_xlfn.XLOOKUP($B111,'IS & BS Projections'!$B:$B,'IS & BS Projections'!AZ:AZ) -> 0 | AZ111: =_xlfn.XLOOKUP($B111,'IS & BS Projections'!$B:$B,'IS & BS Projections'!BA:BA) -> 0 | BA111: =_xlfn.XLOOKUP($B111,'IS & BS Projections'!$B:$B,'IS & BS Projections'!BB:BB) -> 0 | BB111: =_xlfn.XLOOKUP($B111,'IS & BS Projections'!$B:$B,'IS & BS Projections'!BC:BC) -> 0 | BC111: =_xlfn.XLOOKUP($B111,'IS & BS Projections'!$B:$B,'IS & BS Projections'!BD:BD) -> 0
B112: Total Current Liabilities | D112: USD '000s | E112: =SUM(E98:E111) -> 11419035 | F112: =SUM(F98:F111) -> 80815293 | G112: =SUM(G98:G111) -> 5485079 | H112: =SUM(H98:H111) -> 7941320 | I112: =SUM(I98:I111) -> 8701282 | J112: =SUM(J98:J111) -> 8762498.9 | K112: =SUM(K98:K111) -> 9895487.4 | L112: =SUM(L98:L111) -> 12077067 | ... N112: =SUM(N98:N111) -> 15932416 | P112: =SUM(P98:P111) -> 7256148 | Q112: =SUM(Q98:Q111) -> 9677564 | R112: =SUM(R98:R111) -> 9615159 | S112: =SUM(S98:S111) -> 11419035 | T112: =SUM(T98:T111) -> 10921823 | U112: =SUM(U98:U111) -> 96194296 | V112: =SUM(V98:V111) -> 102073099 | W112: =SUM(W98:W111) -> 80815293 | ... BC112: =SUM(BC98:BC111) -> 15932416
B114: Non-Current Liabilities:
B115: Long-term Debt | D115: USD '000s | E115: =S115 -> 3384795 | F115: =W115 -> 3393448 | G115: =AA115 -> 2979957 | H115: =AE115 -> 4234081 | I115: =AI115 -> 5937034 | J115: =AM115 -> 5933606 | K115: =AQ115 -> 5933606 | L115: =AU115 -> 3933606 | M115: =AY115 -> 1933606 | N115: =BC115 -> 2168606 | P115: 0 | Q115: 0 | R115: 3382185 | S115: 3384795 | T115: 3386865 | U115: 3389033 | V115: 3391237 | W115: 3393448 | X115: 3395613 | Y115: 3334257 | Z115: 3076599 | AA115: 2979957 | AB115: 4225014 | AC115: 4228019 | AD115: 4231047 | AE115: 4234081 | AF115: 4237090 | AG115: 2973545 | AH115: 5933447 | AI115: 5937034 | AJ115: ='D&E Schedule'!AC11 -> 7206619 | AK115: ='D&E Schedule'!AD11 -> 4660593 | AL115: ='D&E Schedule'!AE11 -> 5933606 | AM115: ='D&E Schedule'!AF11 -> 5933606 | AN115: ='D&E Schedule'!AG11 -> 5933606 | AO115: ='D&E Schedule'!AH11 -> 5933606 | AP115: ='D&E Schedule'!AI11 -> 5933606 | AQ115: ='D&E Schedule'!AJ11 -> 5933606 | ... BC115: ='D&E Schedule'!AV11 -> 2168606
B116: Convertible Senior Notes, Net Non-current | D116: USD '000s | E116: =S116 -> 0 | F116: =W116 -> 0 | G116: =AA116 -> 0 | H116: =AE116 -> 0 | I116: =AI116 -> 0 | J116: =AM116 -> 0 | K116: =AQ116 -> 0 | L116: =AU116 -> 0 | M116: =AY116 -> 0 | N116: =BC116 -> 0 | P116: 0 | Q116: 1406927 | R116: 0 | S116: 0 | T116: 0 | U116: 0 | V116: 0 | W116: 0 | X116: 0 | Y116: 0 | Z116: 0 | AA116: 0 | AB116: 0 | AC116: 0 | AD116: 0 | AE116: 0 | AF116: 0 | AG116: 0 | AH116: 0 | AI116: 0 | AJ116: =_xlfn.XLOOKUP($B116,'IS & BS Projections'!$B:$B,'IS & BS Projections'!AK:AK) -> 0 | AK116: =_xlfn.XLOOKUP($B116,'IS & BS Projections'!$B:$B,'IS & BS Projections'!AL:AL) -> 0 | AL116: =_xlfn.XLOOKUP($B116,'IS & BS Projections'!$B:$B,'IS & BS Projections'!AM:AM) -> 0 | AM116: =_xlfn.XLOOKUP($B116,'IS & BS Projections'!$B:$B,'IS & BS Projections'!AN:AN) -> 0 | AN116: =_xlfn.XLOOKUP($B116,'IS & BS Projections'!$B:$B,'IS & BS Projections'!AO:AO) -> 0 | AO116: =_xlfn.XLOOKUP($B116,'IS & BS Projections'!$B:$B,'IS & BS Projections'!AP:AP) -> 0 | AP116: =_xlfn.XLOOKUP($B116,'IS & BS Projections'!$B:$B,'IS & BS Projections'!AQ:AQ) -> 0 | AQ116: =_xlfn.XLOOKUP($B116,'IS & BS Projections'!$B:$B,'IS & BS Projections'!AR:AR) -> 0 | AR116: =_xlfn.XLOOKUP($B116,'IS & BS Projections'!$B:$B,'IS & BS Projections'!AS:AS) -> 0 | AS116: =_xlfn.XLOOKUP($B116,'IS & BS Projections'!$B:$B,'IS & BS Projections'!AT:AT) -> 0 | AT116: =_xlfn.XLOOKUP($B116,'IS & BS Projections'!$B:$B,'IS & BS Projections'!AU:AU) -> 0 | AU116: =_xlfn.XLOOKUP($B116,'IS & BS Projections'!$B:$B,'IS & BS Projections'!AV:AV) -> 0 | AV116: =_xlfn.XLOOKUP($B116,'IS & BS Projections'!$B:$B,'IS & BS Projections'!AW:AW) -> 0 | AW116: =_xlfn.XLOOKUP($B116,'IS & BS Projections'!$B:$B,'IS & BS Projections'!AX:AX) -> 0 | AX116: =_xlfn.XLOOKUP($B116,'IS & BS Projections'!$B:$B,'IS & BS Projections'!AY:AY) -> 0 | AY116: =_xlfn.XLOOKUP($B116,'IS & BS Projections'!$B:$B,'IS & BS Projections'!AZ:AZ) -> 0 | AZ116: =_xlfn.XLOOKUP($B116,'IS & BS Projections'!$B:$B,'IS & BS Projections'!BA:BA) -> 0 | BA116: =_xlfn.XLOOKUP($B116,'IS & BS Projections'!$B:$B,'IS & BS Projections'!BB:BB) -> 0 | BB116: =_xlfn.XLOOKUP($B116,'IS & BS Projections'!$B:$B,'IS & BS Projections'!BC:BC) -> 0 | BC116: =_xlfn.XLOOKUP($B116,'IS & BS Projections'!$B:$B,'IS & BS Projections'!BD:BD) -> 0
B117: Lease Liabilities (non-current) | D117: USD '000s | E117: =S117 -> 74078 | F117: =W117 -> 42044 | G117: =AA117 -> 0 | H117: =AE117 -> 0 | I117: =AI117 -> 0 | J117: =AM117 -> 0 | K117: =AQ117 -> 0 | L117: =AU117 -> 0 | M117: =AY117 -> 0 | N117: =BC117 -> 0 | P117: 88519 | Q117: 82292 | R117: 81602 | S117: 74078 | T117: 66425 | U117: 59317 | V117: 50167 | W117: 42044 | X117: 11289 | Y117: 8611 | Z117: 5690 | AA117: 0 | AB117: 0 | AC117: 0 | AD117: 0 | AE117: 0 | AF117: 0 | AG117: 0 | AH117: 0 | AI117: 0 | AJ117: =_xlfn.XLOOKUP($B117,'IS & BS Projections'!$B:$B,'IS & BS Projections'!AK:AK) -> 27231.818 | AK117: =_xlfn.XLOOKUP($B117,'IS & BS Projections'!$B:$B,'IS & BS Projections'!AL:AL) -> 21694.21 | AL117: =_xlfn.XLOOKUP($B117,'IS & BS Projections'!$B:$B,'IS & BS Projections'!AM:AM) -> 20035.787 | AM117: =_xlfn.XLOOKUP($B117,'IS & BS Projections'!$B:$B,'IS & BS Projections'!AN:AN) -> 0 | AN117: =_xlfn.XLOOKUP($B117,'IS & BS Projections'!$B:$B,'IS & BS Projections'!AO:AO) -> 28418.289 | AO117: =_xlfn.XLOOKUP($B117,'IS & BS Projections'!$B:$B,'IS & BS Projections'!AP:AP) -> 24681.085 | AP117: =_xlfn.XLOOKUP($B117,'IS & BS Projections'!$B:$B,'IS & BS Projections'!AQ:AQ) -> 23120.365 | AQ117: =_xlfn.XLOOKUP($B117,'IS & BS Projections'!$B:$B,'IS & BS Projections'!AR:AR) -> 0 | AR117: =_xlfn.XLOOKUP($B117,'IS & BS Projections'!$B:$B,'IS & BS Projections'!AS:AS) -> 30935.108 | AS117: =_xlfn.XLOOKUP($B117,'IS & BS Projections'!$B:$B,'IS & BS Projections'!AT:AT) -> 28243.149 | AT117: =_xlfn.XLOOKUP($B117,'IS & BS Projections'!$B:$B,'IS & BS Projections'!AU:AU) -> 26053.735 | AU117: =_xlfn.XLOOKUP($B117,'IS & BS Projections'!$B:$B,'IS & BS Projections'!AV:AV) -> 0 | AV117: =_xlfn.XLOOKUP($B117,'IS & BS Projections'!$B:$B,'IS & BS Projections'!AW:AW) -> 34156.189 | AW117: =_xlfn.XLOOKUP($B117,'IS & BS Projections'!$B:$B,'IS & BS Projections'!AX:AX) -> 33590.047 | AX117: =_xlfn.XLOOKUP($B117,'IS & BS Projections'!$B:$B,'IS & BS Projections'!AY:AY) -> 30612.637 | AY117: =_xlfn.XLOOKUP($B117,'IS & BS Projections'!$B:$B,'IS & BS Projections'!AZ:AZ) -> 0 | AZ117: =_xlfn.XLOOKUP($B117,'IS & BS Projections'!$B:$B,'IS & BS Projections'!BA:BA) -> 39243.267 | BA117: =_xlfn.XLOOKUP($B117,'IS & BS Projections'!$B:$B,'IS & BS Projections'!BB:BB) -> 42240.018 | BB117: =_xlfn.XLOOKUP($B117,'IS & BS Projections'!$B:$B,'IS & BS Projections'!BC:BC) -> 38145.774 | BC117: =_xlfn.XLOOKUP($B117,'IS & BS Projections'!$B:$B,'IS & BS Projections'!BD:BD) -> 0
B118: Preferred Stock Convertible | D118: USD '000s | E118: =S118 -> 0 | F118: =W118 -> 0 | G118: =AA118 -> 0 | H118: =AE118 -> 0 | I118: =AI118 -> 0 | J118: =AM118 -> 0 | K118: =AQ118 -> 0 | L118: =AU118 -> 0 | M118: =AY118 -> 0 | N118: =BC118 -> 0 | P118: 552037 | Q118: 0 | R118: 0 | S118: 0 | T118: 0 | U118: 0 | V118: 0 | W118: 0 | X118: 0 | Y118: 0 | Z118: 0 | AA118: 0 | AB118: 0 | AC118: 0 | AD118: 0 | AE118: 0 | AF118: 0 | AG118: 0 | AH118: 0 | AI118: 0 | AJ118: =_xlfn.XLOOKUP($B118,'IS & BS Projections'!$B:$B,'IS & BS Projections'!AK:AK) -> 0 | AK118: =_xlfn.XLOOKUP($B118,'IS & BS Projections'!$B:$B,'IS & BS Projections'!AL:AL) -> 0 | AL118: =_xlfn.XLOOKUP($B118,'IS & BS Projections'!$B:$B,'IS & BS Projections'!AM:AM) -> 0 | AM118: =_xlfn.XLOOKUP($B118,'IS & BS Projections'!$B:$B,'IS & BS Projections'!AN:AN) -> 0 | AN118: =_xlfn.XLOOKUP($B118,'IS & BS Projections'!$B:$B,'IS & BS Projections'!AO:AO) -> 0 | AO118: =_xlfn.XLOOKUP($B118,'IS & BS Projections'!$B:$B,'IS & BS Projections'!AP:AP) -> 0 | AP118: =_xlfn.XLOOKUP($B118,'IS & BS Projections'!$B:$B,'IS & BS Projections'!AQ:AQ) -> 0 | AQ118: =_xlfn.XLOOKUP($B118,'IS & BS Projections'!$B:$B,'IS & BS Projections'!AR:AR) -> 0 | AR118: =_xlfn.XLOOKUP($B118,'IS & BS Projections'!$B:$B,'IS & BS Projections'!AS:AS) -> 0 | AS118: =_xlfn.XLOOKUP($B118,'IS & BS Projections'!$B:$B,'IS & BS Projections'!AT:AT) -> 0 | AT118: =_xlfn.XLOOKUP($B118,'IS & BS Projections'!$B:$B,'IS & BS Projections'!AU:AU) -> 0 | AU118: =_xlfn.XLOOKUP($B118,'IS & BS Projections'!$B:$B,'IS & BS Projections'!AV:AV) -> 0 | AV118: =_xlfn.XLOOKUP($B118,'IS & BS Projections'!$B:$B,'IS & BS Projections'!AW:AW) -> 0 | AW118: =_xlfn.XLOOKUP($B118,'IS & BS Projections'!$B:$B,'IS & BS Projections'!AX:AX) -> 0 | AX118: =_xlfn.XLOOKUP($B118,'IS & BS Projections'!$B:$B,'IS & BS Projections'!AY:AY) -> 0 | AY118: =_xlfn.XLOOKUP($B118,'IS & BS Projections'!$B:$B,'IS & BS Projections'!AZ:AZ) -> 0 | AZ118: =_xlfn.XLOOKUP($B118,'IS & BS Projections'!$B:$B,'IS & BS Projections'!BA:BA) -> 0 | BA118: =_xlfn.XLOOKUP($B118,'IS & BS Projections'!$B:$B,'IS & BS Projections'!BB:BB) -> 0 | BB118: =_xlfn.XLOOKUP($B118,'IS & BS Projections'!$B:$B,'IS & BS Projections'!BC:BC) -> 0 | BC118: =_xlfn.XLOOKUP($B118,'IS & BS Projections'!$B:$B,'IS & BS Projections'!BD:BD) -> 0
B119: Other Non-current Liabilities | D119: USD '000s | E119: =S119 -> 14828 | F119: =W119 -> 19531 | G119: =AA119 -> 7216 | H119: =AE119 -> 89708 | I119: =AI119 -> 240458 | J119: =AM119 -> 54009.319 | K119: =AQ119 -> 60992.708 | L119: =AU119 -> 68275.6 | M119: =AY119 -> 79744.426 | N119: =BC119 -> 98202.461 | P119: 0 | Q119: 0 | R119: 14828 | S119: 14828 | T119: 23988 | U119: 12208 | V119: 27545 | W119: 19531 | X119: 17188 | Y119: 14252 | Z119: 3395 | AA119: 7216 | AB119: 5870 | AC119: 6666 | AD119: 11001 | AE119: 89708 | AF119: 92307 | AG119: 176822 | AH119: 205342 | AI119: 240458 | AJ119: =_xlfn.XLOOKUP($B119,'IS & BS Projections'!$B:$B,'IS & BS Projections'!AK:AK) -> 38323.846 | AK119: =_xlfn.XLOOKUP($B119,'IS & BS Projections'!$B:$B,'IS & BS Projections'!AL:AL) -> 26935.647 | AL119: =_xlfn.XLOOKUP($B119,'IS & BS Projections'!$B:$B,'IS & BS Projections'!AM:AM) -> 26830.489 | AM119: =_xlfn.XLOOKUP($B119,'IS & BS Projections'!$B:$B,'IS & BS Projections'!AN:AN) -> 54009.319 | AN119: =_xlfn.XLOOKUP($B119,'IS & BS Projections'!$B:$B,'IS & BS Projections'!AO:AO) -> 39993.588 | AO119: =_xlfn.XLOOKUP($B119,'IS & BS Projections'!$B:$B,'IS & BS Projections'!AP:AP) -> 30644.168 | AP119: =_xlfn.XLOOKUP($B119,'IS & BS Projections'!$B:$B,'IS & BS Projections'!AQ:AQ) -> 30961.135 | AQ119: =_xlfn.XLOOKUP($B119,'IS & BS Projections'!$B:$B,'IS & BS Projections'!AR:AR) -> 60992.708 | AR119: =_xlfn.XLOOKUP($B119,'IS & BS Projections'!$B:$B,'IS & BS Projections'!AS:AS) -> 43535.554 | AS119: =_xlfn.XLOOKUP($B119,'IS & BS Projections'!$B:$B,'IS & BS Projections'!AT:AT) -> 35066.845 | AT119: =_xlfn.XLOOKUP($B119,'IS & BS Projections'!$B:$B,'IS & BS Projections'!AU:AU) -> 34889.293 | AU119: =_xlfn.XLOOKUP($B119,'IS & BS Projections'!$B:$B,'IS & BS Projections'!AV:AV) -> 68275.6 | AV119: =_xlfn.XLOOKUP($B119,'IS & BS Projections'!$B:$B,'IS & BS Projections'!AW:AW) -> 48068.642 | AW119: =_xlfn.XLOOKUP($B119,'IS & BS Projections'!$B:$B,'IS & BS Projections'!AX:AX) -> 41705.582 | AX119: =_xlfn.XLOOKUP($B119,'IS & BS Projections'!$B:$B,'IS & BS Projections'!AY:AY) -> 40994.247 | AY119: =_xlfn.XLOOKUP($B119,'IS & BS Projections'!$B:$B,'IS & BS Projections'!AZ:AZ) -> 79744.426 | AZ119: =_xlfn.XLOOKUP($B119,'IS & BS Projections'!$B:$B,'IS & BS Projections'!BA:BA) -> 55227.781 | BA119: =_xlfn.XLOOKUP($B119,'IS & BS Projections'!$B:$B,'IS & BS Projections'!BB:BB) -> 52445.433 | BB119: =_xlfn.XLOOKUP($B119,'IS & BS Projections'!$B:$B,'IS & BS Projections'!BC:BC) -> 51082.084 | BC119: =_xlfn.XLOOKUP($B119,'IS & BS Projections'!$B:$B,'IS & BS Projections'!BD:BD) -> 98202.461
B120: Total Non-Current Liabilities | D120: USD '000s | E120: =SUM(E115:E119) -> 3473701 | F120: =SUM(F115:F119) -> 3455023 | G120: =SUM(G115:G119) -> 2987173 | H120: =SUM(H115:H119) -> 4323789 | I120: =SUM(I115:I119) -> 6177492 | J120: =SUM(J115:J119) -> 5987615.3 | K120: =SUM(K115:K119) -> 5994598.7 | L120: =SUM(L115:L119) -> 4001881.6 | ... N120: =SUM(N115:N119) -> 2266808.5 | P120: =SUM(P115:P119) -> 640556 | Q120: =SUM(Q115:Q119) -> 1489219 | R120: =SUM(R115:R119) -> 3478615 | S120: =SUM(S115:S119) -> 3473701 | T120: =SUM(T115:T119) -> 3477278 | U120: =SUM(U115:U119) -> 3460558 | V120: =SUM(V115:V119) -> 3468949 | W120: =SUM(W115:W119) -> 3455023 | ... BC120: =SUM(BC115:BC119) -> 2266808.5
B122: Total Liabilities | D122: USD '000s | E122: =SUM(E120,E112) -> 14892736 | F122: =SUM(F120,F112) -> 84270316 | G122: =SUM(G120,G112) -> 8472252 | H122: =SUM(H120,H112) -> 12265109 | I122: =SUM(I120,I112) -> 14878774 | J122: =SUM(J120,J112) -> 14750114 | K122: =SUM(K120,K112) -> 15890086 | L122: =SUM(L120,L112) -> 16078949 | ... N122: =SUM(N120,N112) -> 18199225 | P122: =SUM(P120,P112) -> 7896704 | Q122: =SUM(Q120,Q112) -> 11166783 | R122: =SUM(R120,R112) -> 13093774 | S122: =SUM(S120,S112) -> 14892736 | T122: =SUM(T120,T112) -> 14399101 | U122: =SUM(U120,U112) -> 99654854 | V122: =SUM(V120,V112) -> 105542048 | W122: =SUM(W120,W112) -> 84270316 | ... BC122: =SUM(BC120,BC112) -> 18199225
B124: Shareholders' Equity
B126: Common Stock - Par Value | D126: USD '000s | E126: =S126 -> 2 | F126: =W126 -> 2 | G126: =AA126 -> 2 | H126: =AE126 -> 2 | I126: =AI126 -> 3 | J126: =AM126 -> 3 | K126: =AQ126 -> 3 | L126: =AU126 -> 3 | M126: =AY126 -> 3 | N126: =BC126 -> 3 | P126: 0 | Q126: 1 | R126: 1 | S126: 2 | T126: 2 | U126: 2 | V126: 2 | W126: 2 | X126: 2 | Y126: 2 | Z126: 2 | AA126: 2 | AB126: 2 | AC126: 2 | AD126: 2 | AE126: 2 | AF126: 2 | AG126: 2 | AH126: 3 | AI126: 3 | AJ126: =AI126 -> 3 | AK126: =AJ126 -> 3 | AL126: =AK126 -> 3 | AM126: =AL126 -> 3 | AN126: =AM126 -> 3 | AO126: =AN126 -> 3 | AP126: =AO126 -> 3 | AQ126: =AP126 -> 3 | ... BC126: =BB126 -> 3
B127: Common Stock - Par Value | D127: USD '000s | E127: =S127 -> 0 | F127: =W127 -> 0 | G127: =AA127 -> 0 | H127: =AE127 -> 0 | I127: =AI127 -> 0 | J127: =AM127 -> 0 | K127: =AQ127 -> 0 | L127: =AU127 -> 0 | M127: =AY127 -> 0 | N127: =BC127 -> 0 | P127: 0 | Q127: 1 | R127: 1 | S127: 0 | T127: 0 | U127: 0 | V127: 0 | W127: 0 | X127: 0 | Y127: 0 | Z127: 0 | AA127: 0 | AB127: 0 | AC127: 0 | AD127: 0 | AE127: 0 | AF127: 0 | AG127: 0 | AH127: 0 | AI127: 0 | AJ127: =AI127 -> 0 | AK127: =AJ127 -> 0 | AL127: =AK127 -> 0 | AM127: =AL127 -> 0 | AN127: =AM127 -> 0 | AO127: =AN127 -> 0 | AP127: =AO127 -> 0 | AQ127: =AP127 -> 0 | ... BC127: =BB127 -> 0
B128: Additional Paid in Capital | D128: USD '000s | E128: =S128 -> 2034658 | F128: =W128 -> 3767686 | G128: =AA128 -> 4491571 | H128: =AE128 -> 5365990 | I128: =AI128 -> 8566854 | J128: =AM128 -> 8566854 | K128: =AQ128 -> 8566854 | L128: =AU128 -> 8566854 | M128: =AY128 -> 8566854 | N128: =BC128 -> 8566854 | P128: 804523 | Q128: 1516533 | R128: 1850711 | S128: 2034658 | T128: 2579216 | U128: 3004459 | V128: 3380330 | W128: 3767686 | X128: 4056774 | Y128: 4239319 | Z128: 4418327 | AA128: 4491571 | AB128: 4550408 | AC128: 4816808 | AD128: 5087238 | AE128: 5365990 | AF128: 5483821 | AG128: 5639538 | AH128: 9131722 | AI128: 8566854 | AJ128: ='D&E Schedule'!AC124 -> 8566854 | AK128: ='D&E Schedule'!AD124 -> 8566854 | AL128: ='D&E Schedule'!AE124 -> 8566854 | AM128: ='D&E Schedule'!AF124 -> 8566854 | AN128: ='D&E Schedule'!AG124 -> 8566854 | AO128: ='D&E Schedule'!AH124 -> 8566854 | AP128: ='D&E Schedule'!AI124 -> 8566854 | AQ128: ='D&E Schedule'!AJ124 -> 8566854 | ... BC128: ='D&E Schedule'!AV124 -> 8566854
B129: Retained Earnings | D129: USD '000s | E129: =S129 -> 4350424 | F129: =W129 -> 1725475 | G129: =AA129 -> 1820346 | H129: =AE129 -> 4960901 | I129: =AI129 -> 6221228 | J129: =AM129 -> 8449210 | K129: =AQ129 -> 10956770 | L129: =AU129 -> 13797393 | M129: =AY129 -> 17159903 | N129: =BC129 -> 21309874 | P129: 1497767 | Q129: 3104116 | R129: 3510216 | S129: 4350424 | T129: 3920765 | U129: 2827111 | V129: 2282476 | W129: 1725475 | X129: 1646579 | Y129: 1549174 | Z129: 1546909 | AA129: 1820346 | AB129: 3558080 | AC129: 3594230 | AD129: 3669725 | AE129: 4960901 | AF129: 5026509 | AG129: 6455409 | AH129: 6887961 | AI129: 6221228 | AJ129: ='D&E Schedule'!AC118 -> 7026337 | AK129: ='D&E Schedule'!AD118 -> 7460478 | AL129: ='D&E Schedule'!AE118 -> 7889199.2 | AM129: ='D&E Schedule'!AF118 -> 8449210 | AN129: ='D&E Schedule'!AG118 -> 9300315.6 | AO129: ='D&E Schedule'!AH118 -> 9807588.7 | AP129: ='D&E Schedule'!AI118 -> 10314930 | AQ129: ='D&E Schedule'!AJ118 -> 10956770 | ... BC129: ='D&E Schedule'!AV118 -> 21309874
...

Sheet Debt
A1: ='Cover Page'!$C$3 -> Coinbase Global Inc., (NASDAQ: COIN) | F1: 2021 | G1: =F1+1 -> 2022 | H1: =G1+1 -> 2023 | I1: =H1+1 -> 2024 | J1: =I1+1 -> 2025 | K1: =J1+1 -> 2026 | L1: =K1+1 -> 2027 | M1: =L1+1 -> 2028 | N1: =M1+1 -> 2029 | O1: =N1+1 -> 2030
A2: Property, Plant & Equipment Projections | F2: Q4 | G2: Q4 | H2: Q4 | I2: Q4 | J2: Q4 | K2: Q4 | L2: Q4 | M2: Q4 | N2: Q4 | O2: Q4
F3: 12 | G3: 12 | H3: 12 | I3: 12 | J3: 12 | K3: 12 | L3: 12 | M3: 12 | N3: 12 | O3: 12
F4: 365 | G4: 365 | H4: 365 | I4: 366 | J4: 365 | K4: 365 | L4: 365 | M4: 366 | N4: 365 | O4: 365
F5: Actuals | G5: Actuals | H5: Actuals | I5: Actuals | J5: Actuals | K5: Forecasted | L5: Forecasted | M5: Forecasted | N5: Forecasted | O5: Forecasted
A6: In USD '000s, Unless Stated Otherwise | F6: 44561 | G6: =EOMONTH(F6,12) -> 44926 | H6: =EOMONTH(G6,12) -> 45291 | I6: =EOMONTH(H6,12) -> 45657 | J6: =EOMONTH(I6,12) -> 46022 | K6: =EOMONTH(J6,12) -> 46387 | L6: =EOMONTH(K6,12) -> 46752 | M6: =EOMONTH(L6,12) -> 47118 | N6: =EOMONTH(M6,12) -> 47483 | O6: =EOMONTH(N6,12) -> 47848
A8: x | B8: Cash Available for Debt Service | E8: Units | F8: 21 | G8: =F8+1 -> 22 | H8: =G8+1 -> 23 | I8: =H8+1 -> 24 | J8: =I8+1 -> 25 | K8: =J8+1 -> 26 | L8: =K8+1 -> 27 | M8: =L8+1 -> 28 | N8: =M8+1 -> 29 | O8: =N8+1 -> 30
B10: Beginning Cash Balance | E10: USD '000s | K10: ='3FS'!J207 -> 11285452 | L10: ='3FS'!K207 -> 16507513 | M10: ='3FS'!L207 -> 18457012 | N10: ='3FS'!M207 -> 19725501 | O10: ='3FS'!N207 -> 20646417
B11: Cash Flow Available for Debt Service | E11: USD '000s | K11: ='3FS'!J183+'3FS'!J187+'3FS'!J188 -> 5384029.1 | L11: ='3FS'!K183+'3FS'!K187+'3FS'!K188 -> 2086390.2 | M11: ='3FS'!L183+'3FS'!L187+'3FS'!L188 -> 2411250.1 | N11: ='3FS'!M183+'3FS'!M187+'3FS'!M188 -> 2645730.8 | O11: ='3FS'!N183+'3FS'!N187+'3FS'!N188 -> 2934180.9
B12: Cash Available for Debt Service | E12: USD '000s | K12: =SUM(K10:K11) -> 16669481 | L12: =SUM(L10:L11) -> 18593903 | M12: =SUM(M10:M11) -> 20868262 | N12: =SUM(N10:N11) -> 22371232 | O12: =SUM(O10:O11) -> 23580597
A14: x | B14: Mandated Repayments | E14: Units | F14: 21 | G14: =F14+1 -> 22 | H14: =G14+1 -> 23 | I14: =H14+1 -> 24 | J14: =I14+1 -> 25 | K14: =J14+1 -> 26 | L14: =K14+1 -> 27 | M14: =L14+1 -> 28 | N14: =M14+1 -> 29 | O14: =N14+1 -> 30
B16: Mandated Repayments Amount - Term Loan A | E16: USD '000s
B17: Mandated Repayments Amount - Term Loan B | E17: USD '000s

Sheet WACC
A1: ='Cover Page'!$C$3 -> Coinbase Global Inc., (NASDAQ: COIN) | F1: 2021 | G1: =F1+1 -> 2022 | H1: =G1+1 -> 2023 | I1: =H1+1 -> 2024 | J1: =I1+1 -> 2025 | K1: =J1+1 -> 2026 | L1: =K1+1 -> 2027 | M1: =L1+1 -> 2028 | N1: =M1+1 -> 2029 | O1: =N1+1 -> 2030
A2: Property, Plant & Equipment Projections | F2: Q4 | G2: Q4 | H2: Q4 | I2: Q4 | J2: Q4 | K2: Q4 | L2: Q4 | M2: Q4 | N2: Q4 | O2: Q4
F3: 12 | G3: 12 | H3: 12 | I3: 12 | J3: 12 | K3: 12 | L3: 12 | M3: 12 | N3: 12 | O3: 12
F4: 365 | G4: 365 | H4: 365 | I4: 366 | J4: 365 | K4: 365 | L4: 365 | M4: 366 | N4: 365 | O4: 365
F5: Actuals | G5: Actuals | H5: Actuals | I5: Actuals | J5: Actuals | K5: Forecasted | L5: Forecasted | M5: Forecasted | N5: Forecasted | O5: Forecasted
A6: In USD '000s, Unless Stated Otherwise | F6: 44561 | G6: =EOMONTH(F6,12) -> 44926 | H6: =EOMONTH(G6,12) -> 45291 | I6: =EOMONTH(H6,12) -> 45657 | J6: =EOMONTH(I6,12) -> 46022 | K6: =EOMONTH(J6,12) -> 46387 | L6: =EOMONTH(K6,12) -> 46752 | M6: =EOMONTH(L6,12) -> 47118 | N6: =EOMONTH(M6,12) -> 47483 | O6: =EOMONTH(N6,12) -> 47848
A8: x | B8: Cost of Equity
B10: Capital Asset Pricing Model (CAPM)
B11: Risk Free Rate | D11: 0.0435
B12: Levered Beta | D12: =O39 -> 2.7506394
B13: Equity Risk Premium | D13: =O47 -> 0.055134434
B14: Country Risk Premium | D14: =O55 -> 0.013034434
B15: Cost of Equity | D15: =D11+D12*D13+D14 -> 0.20818938
B17: Levered Beta
B18: 2 | C18: 6 | F18: 161 | G18: 155 | L18: 16 | M18: 8 | N18: 9 | O18: 9
B19: Identified Peer Group
F21: Levered | G21: BV | H21: Cost of | I21: Debt | J21: Interest | K21: MV | L21: Market | M21: D/E | N21: Tax | O21: Unlevered
B22: Country | C22: Name | E22: Ticker | F22: Beta | G22: Debt | H22: Debt | I22: Maturity | J22: Expense | K22: Debt | L22: Capitalisation | M22: Ratio | N22: Rate | O22: Beta
B23: =_xlfn.XLOOKUP($E23,'Trading Comps_Raw'!$B$20:$B$26,'Trading Comps_Raw'!$I$20:$I$26) -> United States | C23: =_xlfn.XLOOKUP($E23,'Trading Comps_Raw'!$B$20:$B$26,'Trading Comps_Raw'!$E$20:$E$26) -> Gemini Space Station, Inc. | E23: NASDAQ:GEMI | F23: 0.80987929 | G23: =_xlfn.XLOOKUP($E23,'Trading Comps_Raw'!$B$20:$B$26,'Trading Comps_Raw'!$EC$20:$EC$26) -> 654.026 | L23: =_xlfn.XLOOKUP($E23,'Trading Comps_Raw'!$B$20:$B$26,'Trading Comps_Raw'!$S$20:$S$26) -> 519.15457 | M23: =G23/L23 -> 1.2597905 | N23: =Damodaran!$H$59 -> 0.25 | O23: =F23/(1+M23*(1-N23)) -> 0.41642402
B24: =_xlfn.XLOOKUP($E24,'Trading Comps_Raw'!$B$20:$B$26,'Trading Comps_Raw'!$I$20:$I$26) -> Cayman Islands | C24: =_xlfn.XLOOKUP($E24,'Trading Comps_Raw'!$B$20:$B$26,'Trading Comps_Raw'!$E$20:$E$26) -> Bullish | E24: NYSE:BLSH | F24: -2.4793146 | G24: =_xlfn.XLOOKUP($E24,'Trading Comps_Raw'!$B$20:$B$26,'Trading Comps_Raw'!$EC$20:$EC$26) -> 581.085 | L24: =_xlfn.XLOOKUP($E24,'Trading Comps_Raw'!$B$20:$B$26,'Trading Comps_Raw'!$S$20:$S$26) -> 5370.2979 | M24: =G24/L24 -> 0.10820349 | N24: =Damodaran!$H$59 -> 0.25 | O24: =F24/(1+M24*(1-N24)) -> -2.2932143
B25: =_xlfn.XLOOKUP($E25,'Trading Comps_Raw'!$B$20:$B$26,'Trading Comps_Raw'!$I$20:$I$26) -> United States | C25: =_xlfn.XLOOKUP($E25,'Trading Comps_Raw'!$B$20:$B$26,'Trading Comps_Raw'!$E$20:$E$26) -> Circle Internet Group, Inc. | E25: NYSE:CRCL | F25: -3.1950266 | G25: =_xlfn.XLOOKUP($E25,'Trading Comps_Raw'!$B$20:$B$26,'Trading Comps_Raw'!$EC$20:$EC$26) -> 51.485 | L25: =_xlfn.XLOOKUP($E25,'Trading Comps_Raw'!$B$20:$B$26,'Trading Comps_Raw'!$S$20:$S$26) -> 23101.013 | M25: =G25/L25 -> 0.0022286901 | N25: =Damodaran!$H$59 -> 0.25 | O25: =F25/(1+M25*(1-N25)) -> -3.1896949
B26: =_xlfn.XLOOKUP($E26,'Trading Comps_Raw'!$B$20:$B$26,'Trading Comps_Raw'!$I$20:$I$26) -> United States | C26: =_xlfn.XLOOKUP($E26,'Trading Comps_Raw'!$B$20:$B$26,'Trading Comps_Raw'!$E$20:$E$26) -> Robinhood Markets, Inc. | E26: NASDAQ:HOOD | F26: 4.2087777 | G26: =_xlfn.XLOOKUP($E26,'Trading Comps_Raw'!$B$20:$B$26,'Trading Comps_Raw'!$EC$20:$EC$26) -> 12449 | L26: =_xlfn.XLOOKUP($E26,'Trading Comps_Raw'!$B$20:$B$26,'Trading Comps_Raw'!$S$20:$S$26) -> 62391.371 | M26: =G26/L26 -> 0.1995308 | N26: =Damodaran!$H$59 -> 0.25 | O26: =F26/(1+M26*(1-N26)) -> 3.6609269
B27: =_xlfn.XLOOKUP($E27,'Trading Comps_Raw'!$B$20:$B$26,'Trading Comps_Raw'!$I$20:$I$26) -> United States | C27: =_xlfn.XLOOKUP($E27,'Trading Comps_Raw'!$B$20:$B$26,'Trading Comps_Raw'!$E$20:$E$26) -> Galaxy Digital Inc. | E27: NASDAQ:GLXY | F27: 3.7874679 | G27: =_xlfn.XLOOKUP($E27,'Trading Comps_Raw'!$B$20:$B$26,'Trading Comps_Raw'!$EC$20:$EC$26) -> 5343.428 | L27: =_xlfn.XLOOKUP($E27,'Trading Comps_Raw'!$B$20:$B$26,'Trading Comps_Raw'!$S$20:$S$26) -> 3555.3346 | M27: =G27/L27 -> 1.5029325 | N27: =Damodaran!$H$59 -> 0.25 | O27: =F27/(1+M27*(1-N27)) -> 1.780495
B28: =_xlfn.XLOOKUP($E28,'Trading Comps_Raw'!$B$20:$B$26,'Trading Comps_Raw'!$I$20:$I$26) -> Israel | C28: =_xlfn.XLOOKUP($E28,'Trading Comps_Raw'!$B$20:$B$26,'Trading Comps_Raw'!$E$20:$E$26) -> eToro Group Ltd. | E28: NASDAQ:ETOR | F28: -0.15111892 | G28: =_xlfn.XLOOKUP($E28,'Trading Comps_Raw'!$B$20:$B$26,'Trading Comps_Raw'!$EC$20:$EC$26) -> 54.463 | L28: =_xlfn.XLOOKUP($E28,'Trading Comps_Raw'!$B$20:$B$26,'Trading Comps_Raw'!$S$20:$S$26) -> 2488.0282 | M28: =G28/L28 -> 0.021890025 | N28: =Damodaran!$H$59 -> 0.25 | O28: =F28/(1+M28*(1-N28)) -> -0.148678
B29: =_xlfn.XLOOKUP($E29,'Trading Comps_Raw'!$B$20:$B$26,'Trading Comps_Raw'!$I$20:$I$26) -> United States | C29: =_xlfn.XLOOKUP($E29,'Trading Comps_Raw'!$B$20:$B$26,'Trading Comps_Raw'!$E$20:$E$26) -> Interactive Brokers Group, Inc. | E29: NASDAQ:IBKR | F29: 1.7174007 | G29: =_xlfn.XLOOKUP($E29,'Trading Comps_Raw'!$B$20:$B$26,'Trading Comps_Raw'!$EC$20:$EC$26) -> 25453 | L29: =_xlfn.XLOOKUP($E29,'Trading Comps_Raw'!$B$20:$B$26,'Trading Comps_Raw'!$S$20:$S$26) -> 29887.524 | M29: =G29/L29 -> 0.85162625 | N29: =Damodaran!$H$59 -> 0.25 | O29: =F29/(1+M29*(1-N29)) -> 1.0480137
B30: Average | F30: =AVERAGE(F23:F29) -> 0.67115221 | M30: =AVERAGE(M23:M29) -> 0.56374318 | O30: =AVERAGE(O23:O29) -> 0.18203893
B31: Median | F31: =MEDIAN(F23:F29) -> 0.80987929 | M31: =MEDIAN(M23:M29) -> 0.1995308 | O31: =MEDIAN(O23:O29) -> 0.41642402
B33: =_xlfn.XLOOKUP($E33,'Trading Comps_Raw'!$B$20:$B$27,'Trading Comps_Raw'!$I$20:$I$27) -> United States | C33: =_xlfn.XLOOKUP($E33,'Trading Comps_Raw'!$B$20:$B$27,'Trading Comps_Raw'!$E$20:$E$27) -> Coinbase Global, Inc. | E33: NASDAQ:COIN | F33: =_xlfn.XLOOKUP(E$33,'Trading Comps_Raw'!$B$20:$B$27,'Trading Comps_Raw'!$O$20:$O$27) -> 5.0225377 | G33: ='Trading Comps_Raw'!EC27 -> 7857.989 | H33: =D4 -> 0 | I33: 2 | J33: ='3FS'!I36/1000 -> -85.413 | K33: =PV(H33,I33,J33,-G33) -> 8028.815 | L33: ='Trading Comps_Raw'!S27 -> 46110.165 | M33: =K33/L33 -> 0.17412245 | N33: 0.25 | O33: =F33/(1+M33*(1-N33)) -> 4.4423969
N34: =N65 -> 0
K35: Weightage | L35: Unlevered | M35: D/E | N35: Tax Rate | O35: Levered
B36: Capital Structure | K36: (%) | L36: Beta | M36: Ratio | N36: (%) | O36: Beta
B37: Target Capital Structure - Current D/E | K37: 0.5 | L37: =O33 -> 4.4423969 | M37: =M33 -> 0.17412245 | N37: =N33 -> 0.25 | O37: =L37*(1+M37*(1-N37)) -> 5.0225377
B38: Target Capital Structure - Median Comps D/E | K38: 0.5 | L38: =O31 -> 0.41642402 | M38: =M31 -> 0.1995308 | N38: =N29 -> 0.25 | O38: =L38*(1+M38*(1-N38)) -> 0.47874108
B39: Levered Beta | O39: =SUMPRODUCT(O37:O38,K37:K38) -> 2.7506394
B41: Equity Risk Premium
M43: Revenue | N43: Weightage | O43: ERP
B44: Country/Region | M44: US$ Bn | N44: (%) | O44: (%)
B45: US | M45: 5.46 | N45: =M45/$M$47 -> 0.83231707 | O45: =Damodaran!F59 -> 0.046132886
B46: International | M46: 1.1 | N46: =M46/$M$47 -> 0.16768293 | O46: =AVERAGE(Damodaran!F58,Damodaran!F60:F214) -> 0.09981484
B47: Equity Risk Premium | M47: =SUM(M45:M46) -> 6.56 | N47: =SUM(N45:N46) -> 1 | O47: =SUMPRODUCT(O45:O46,N45:N46) -> 0.055134434
B49: Country Risk Premium
M51: Revenue | N51: Weightage | O51: CRP
B52: Country | M52: US$Bn | N52: (%) | O52: (%)
B53: US | M53: =M45 -> 5.46 | N53: =N45 -> 0.83231707 | O53: =Damodaran!G59 -> 0.0040328865
B54: International | M54: =M46 -> 1.1 | N54: =N46 -> 0.16768293 | O54: =AVERAGE(Damodaran!G58,Damodaran!G60:G214) -> 0.05771484
B55: Country Risk Premium | M55: =SUM(M53:M54) -> 6.56 | N55: =SUM(N53:N54) -> 1 | O55: =SUMPRODUCT(O53:O54,N53:N54) -> 0.013034434

Sheet LBO
A1: ='Cover Page'!$C$3 -> Coinbase Global Inc., (NASDAQ: COIN) | F1: 2021 | G1: =F1+1 -> 2022 | H1: =G1+1 -> 2023 | I1: =H1+1 -> 2024 | J1: =I1+1 -> 2025 | K1: =J1+1 -> 2026 | L1: =K1+1 -> 2027 | M1: =L1+1 -> 2028 | N1: =M1+1 -> 2029 | O1: =N1+1 -> 2030
A2: Property, Plant & Equipment Projections | F2: Q4 | G2: Q4 | H2: Q4 | I2: Q4 | J2: Q4 | K2: Q4 | L2: Q4 | M2: Q4 | N2: Q4 | O2: Q4
F3: 12 | G3: 12 | H3: 12 | I3: 12 | J3: 12 | K3: 12 | L3: 12 | M3: 12 | N3: 12 | O3: 12
F4: 365 | G4: 365 | H4: 365 | I4: 366 | J4: 365 | K4: 365 | L4: 365 | M4: 366 | N4: 365 | O4: 365
F5: Actuals | G5: Actuals | H5: Actuals | I5: Actuals | J5: Actuals | K5: Forecasted | L5: Forecasted | M5: Forecasted | N5: Forecasted | O5: Forecasted
A6: In USD '000s, Unless Stated Otherwise | F6: 44561 | G6: =EOMONTH(F6,12) -> 44926 | H6: =EOMONTH(G6,12) -> 45291 | I6: =EOMONTH(H6,12) -> 45657 | J6: =EOMONTH(I6,12) -> 46022 | K6: =EOMONTH(J6,12) -> 46387 | L6: =EOMONTH(K6,12) -> 46752 | M6: =EOMONTH(L6,12) -> 47118 | N6: =EOMONTH(M6,12) -> 47483 | O6: =EOMONTH(N6,12) -> 47848
A8: x | B8: Free Cash Flows | E8: Units | F8: 21 | G8: =F8+1 -> 22 | H8: =G8+1 -> 23 | I8: =H8+1 -> 24 | J8: =I8+1 -> 25 | K8: =J8+1 -> 26 | L8: =K8+1 -> 27 | M8: =L8+1 -> 28 | N8: =M8+1 -> 29 | O8: =N8+1 -> 30
B10: EBIT | E10: USD '000s | F10: ='3FS'!E43 -> 3056107 | G10: ='3FS'!F43 -> -2975681 | H10: ='3FS'!G43 -> 5921 | I10: ='3FS'!H43 -> 2951564 | J10: ='3FS'!I43 -> 1628182 | K10: ='3FS'!J43 -> 2157785.3 | L10: ='3FS'!K43 -> 2408413 | M10: ='3FS'!L43 -> 2716261.9 | ... O10: ='3FS'!N43 -> 3879897.9
B11: Cash Tax on EBIT | E11: USD '000s | F11: =F10*Damodaran!$H$59 -> 764026.75 | G11: =G10*Damodaran!$H$59 -> -743920.25 | H11: =H10*Damodaran!$H$59 -> 1480.25 | I11: =I10*Damodaran!$H$59 -> 737891 | J11: =J10*Damodaran!$H$59 -> 407045.5 | K11: =K10*Damodaran!$H$59 -> 539446.32 | L11: =L10*Damodaran!$H$59 -> 602103.25 | M11: =M10*Damodaran!$H$59 -> 679065.48 | ... O11: =O10*Damodaran!$H$59 -> 969974.48
B12: NOPAT | E12: USD '000s | F12: =SUM(F10:F11) -> 3820133.8 | G12: =SUM(G10:G11) -> -3719601.2 | H12: =SUM(H10:H11) -> 7401.25 | I12: =SUM(I10:I11) -> 3689455 | J12: =SUM(J10:J11) -> 2035227.5 | K12: =SUM(K10:K11) -> 2697231.6 | L12: =SUM(L10:L11) -> 3010516.3 | M12: =SUM(M10:M11) -> 3395327.4 | ... O12: =SUM(O10:O11) -> 4849872.4
B13: Depreciation & Amortization | E13: USD '000s | F13: ='3FS'!E142+'3FS'!E143 -> 63651 | G13: ='3FS'!F142+'3FS'!F143 -> 154069 | H13: ='3FS'!G142+'3FS'!G143 -> 139642 | I13: ='3FS'!H142+'3FS'!H143 -> 127518 | J13: ='3FS'!I142+'3FS'!I143 -> 188428 | K13: ='3FS'!J142+'3FS'!J143 -> 264383.27 | L13: ='3FS'!K142+'3FS'!K143 -> 300928.89 | M13: ='3FS'!L142+'3FS'!L143 -> 341884.75 | ... O13: ='3FS'!N142+'3FS'!N143 -> 447740.31
B14: CapEx | E14: USD '000s | F14: ='3FS'!E187 -> -387313 | G14: ='3FS'!F187 -> 0 | H14: ='3FS'!G187 -> -18835 | I14: ='3FS'!H187 -> -59915 | J14: ='3FS'!I187 -> -377426 | K14: ='3FS'!J187 -> -181828.15 | L14: ='3FS'!K187 -> -203316.71 | M14: ='3FS'!L187 -> -227852.49 | ... O14: ='3FS'!N187 -> -324286.46
B15: Changes in Operating Working Capital | E15: USD '000s | K15: =SUM('3FS'!J145:J150) -> 42045.289 | L15: =SUM('3FS'!K145:K150) -> 69848.643 | M15: =SUM('3FS'!L145:L150) -> 72844.307 | N15: =SUM('3FS'!M145:M150) -> 114712.48 | O15: =SUM('3FS'!N145:N150) -> 184619.35
B16: Free Cash Flows | E16: USD '000s | K16: =SUM(K12:K15) -> 2821832 | L16: =SUM(L12:L15) -> 3177977.1 | M16: =SUM(M12:M15) -> 3582204 | N16: =SUM(N12:N15) -> 4194288.2 | O16: =SUM(O12:O15) -> 5157945.6
A18: x | B18: Terminal Value | E18: Units | F18: 21 | G18: =F18+1 -> 22 | H18: =G18+1 -> 23 | I18: =H18+1 -> 24 | J18: =I18+1 -> 25 | K18: =J18+1 -> 26 | L18: =K18+1 -> 27 | M18: =L18+1 -> 28 | N18: =M18+1 -> 29 | O18: =N18+1 -> 30
B20: Weighted Average Cost of Equity | D20: =WACC!D15 -> 0.20818938
B21: Terminal EBITDA Multiple | D21: 30
B22: Terminal Value | E22: USD '000s | O22: =D21*SUM(O10,O13) -> 1.2982915e+08
B24: Total Free Cash Flows & Terminal Value | E24: USD '000s | K24: =SUM(K16,K22) -> 2821832 | L24: =SUM(L16,L22) -> 3177977.1 | M24: =SUM(M16,M22) -> 3582204 | N24: =SUM(N16,N22) -> 4194288.2 | O24: =SUM(O16,O22) -> 1.3498709e+08
A26: x | B26: Discounting Model | E26: Units | F26: 21 | G26: =F26+1 -> 22 | H26: =G26+1 -> 23 | I26: =H26+1 -> 24 | J26: =I26+1 -> 25 | K26: =J26+1 -> 26 | L26: =K26+1 -> 27 | M26: =L26+1 -> 28 | N26: =M26+1 -> 29 | O26: =N26+1 -> 30
B28: Year Count | E28: Years | K28: 1 | L28: =K28+1 -> 2 | M28: =L28+1 -> 3 | N28: =M28+1 -> 4 | O28: =N28+1 -> 5
B29: Discount Factor | E29: % | K29: =1/(1+$D$20)^K28 -> 0.82768481 | L29: =1/(1+$D$20)^L28 -> 0.68506215 | M29: =1/(1+$D$20)^M28 -> 0.56701554 | N29: =1/(1+$D$20)^N28 -> 0.46931015 | O29: =1/(1+$D$20)^O28 -> 0.38844088
B30: Present Value of Free Cash Flows | E30: USD '000s | K30: =K29*K16 -> 2335587.5 | L30: =L29*L16 -> 2177111.8 | M30: =M29*M16 -> 2031165.3 | N30: =N29*N16 -> 1968422 | O30: =O29*O16 -> 2003557
A32: x | B32: Net Present Value | E32: Value | F32: %NPV
B34: Total Present Value of Free Cash Flows | E34: =SUM(K30:O30) -> 10515844 | F34: =E34/$E$36 -> 0.17254138
B35: Present Value of Terminal Value | E35: =O29*O22 -> 50430949 | F35: =E35/$E$36 -> 0.82745862
B36: Net Present Value | E36: =SUM(E34:E35) -> 60946792
A38: x | B38: DCF Valuation of the Operating Phase | E38: Value | F38: %NPV
B40: Total Present Value of Free Cash Flows
B41: Present Value of Terminal Value
B42: Enterprise Value

Sheet LBO Val
A1: Coinbase Global Inc., (NASDAQ: COIN)
A2: LBO Valuation
A3: In USD '000s, Unless Stated Otherwise
B5: Transaction Assumptions: | D5: Units:
C6: EBITDA Multiples:
C7: Entry TEV/ EBITDA Multiple: | D7: x | E7: ='[2]Precedent Transactions Export'!K12 -> 15 | G7: Purchase Enterprise Value: | J7: $ M | K7: =E13 -> 46796370
C8: Exit TEV/ EBITDA Multiple: | D8: x | E8: =E7 -> 15 | G8: (+) Cash & Investments: | J8: $ M | K8: ='[2]Reference (Capital Structure)'!U20*1000 -> 11929535
G9: (-) Debt: | J9: $ M | K9: =-'[2]Reference (Capital Structure)'!U19*1000 -> -7658724
C10: Enterprise Value: | G10: (-) Total Preferred Equity | J10: $ M | K10: =-'[2]Reference (Capital Structure)'!U21*1000 -> 0
C11: Entry TEV/ EBITDA Multiple: | D11: x | E11: =E7 -> 15 | G11: (+) In-the-Money Convertible Debt & Prefs | J11: $ M | K11: ='[2]Reference (Capital Structure)'!U22*1000 -> 0
C12: LTM EBITDA: | D12: $ M | E12: ='[2]3FS'!E46 -> 3119758 | G12: (+) Investments in Unconsolidated Subs | J12: $ M | K12: ='[2]Reference (Capital Structure)'!U23*1000 -> 622985
C13: Enterprise Value: | D13: $ M | E13: =E11*LTM_EBITDA -> 46796370 | G13: (-) Non-controlling Interest | J13: $ M | K13: =-'[2]Reference (Capital Structure)'!U24*1000 -> 0
G14: (-) Pension Liabilities | J14: $ M | K14: =-'[2]Reference (Capital Structure)'!U25*1000 -> 0
G15: Purchase Equity Value: | J15: $ M | K15: =SUM(K7:K14) -> 51690166
C16: Share Price: | D16: $ as Stated | E16: ='[2]Reference (Capital Structure)'!U17/'[2]Reference (Capital Structure)'!U15 -> 161.14
C17: Premium Paid: | D17: % | E17: =E18/E16-1 -> 0.1303919 | G17: Purchase TEV / EBITDA Multiple: | J17: x | K17: =K21/LTM_EBITDA -> 0
C18: Offer Price per Share: | D18: $ as Stated | E18: =K15/E19 -> 182.15135
C19: Diluted Share Count: | D19: Thousand Shares | E19: ='[2]Reference (Capital Structure)'!U15*1000 -> 283775.91
C20: Last Historical Year: | D20: Date | E20: ='[2]Reference (Capital Structure)'!N2 -> 46022
C22: Prepayment Penalty on Existing Debt (%): | D22: % | E22: 0.01
C23: Transaction Fee %: | D23: % | E23: 0.03
C24: Term Loan A Upfront Financing Fee %: | E24: 0.02
C25: Term Loan B Upfront Financing Fee %: | E25: 0.03
C26: Subordinated Loan Upfront Financing Fee %: | E26: 0.04
C27: Debt Issuance Fee %: | D27: % | E27: 0.02
C29: Minimum Cash Balance: | D29: % | E29: 0.05
C30: Initial Minimum Cash Balance | D30: M Shares | E30: =K8*Min_Cash -> 596476.75
C31: US corporate tax rate | D31: % | E31: 0.2
C32: Revolving Credit Line (Maximum capacity) | D32: % | E32: 0.5
C33: Revenue | D33: $ M | E33: ='[2]3FS'!I15 -> 7181325
C34: Revolving Credit Line (Maximum capacity) | D34: $ M | E34: =E32*E33 -> 3590662.5
B36: Sources & Uses Schedule:
C38: Sources of Funds: | D38: ¥ M | E38: x EBITDA | F38: % Sources | H38: Uses of Funds: | K38: ¥ M | L38: x EBITDA
C39: Revolver: | D39: =E39*LTM_EBITDA -> 1559879 | E39: 0.5 | F39: =D39/$D$45 -> 0.025386943 | H39: Purchase Equity Value: | K39: =K15 -> 51690166 | L39: =K39/LTM_EBITDA -> 16.568646
C40: Term Loan A | D40: =E40*LTM_EBITDA -> 3119758 | E40: 1 | F40: =D40/$D$45 -> 0.050773885 | H40: Assume/Replace Existing Debt: | K40: =-K9 -> 7658724 | L40: =K40/LTM_EBITDA -> 2.4549096
C41: Term Loan B | D41: =E41*LTM_EBITDA -> 9359274 | E41: 3 | F41: =D41/$D$45 -> 0.15232166 | H41: Prepayment Penalty on Existing Debt: | K41: =-E22*K9 -> 76587.24 | L41: =K41/LTM_EBITDA -> 0.024549096
C42: Subordinated Notes: | D42: =E42*LTM_EBITDA -> 3119758 | E42: 1 | F42: =D42/$D$45 -> 0.050773885 | H42: Financing Fees: | K42: =E24*D40+E25*D41+E26*D42 -> 467963.7 | L42: =K42/LTM_EBITDA -> 0.15
C43: Excess Cash: | D43: =K8-E30 -> 11333058 | E43: =D43/LTM_EBITDA -> 3.6326722 | F43: =D43/$D$45 -> 0.18444488 | H43: Transaction Fees: | K43: =E23*K15 -> 1550705 | L43: =K43/LTM_EBITDA -> 0.49705938
C44: Investor Equity: | D44: =K44-SUM(D39:D43) -> 32952419 | E44: =D44/LTM_EBITDA -> 10.562492 | F44: =D44/$D$45 -> 0.53629875 | H44: Total Uses: | K44: =SUM(K39:K43) -> 61444146 | L44: =SUM(L39:L43) -> 19.695164
C45: Total Sources: | D45: =SUM(D39:D44) -> 61444146 | E45: =SUM(E39:E44) -> 19.695164 | F45: =SUM(F39:F44) -> 1
E47: =SUM(E39:E42) -> 5.5
B48: Debt and Cash Assumptions:
E50: Upfront | F50: PIK | G50: Annual | H50: Commitment Fee | I50: Cash Flow
C51: Tranche Name: | E51: Financing Fee | F51: Margin: | G51: Amort: | H51: Undrawn Portion | I51: Sweep %:
C52: Revolver: | H52: 0.01 | P52: Amortisation here refers to %BOP Debt Balance being paid down each year. Only applicable for term loans in this model
C53: =C40 -> Term Loan A | G53: 0.2 | I53: 0.5 | P53: A 20% of original principal per year paid annually
C54: =C41 -> Term Loan B | G54: 0.05 | I54: 0.5 | P54: A 5% of original principal per year, paid annually, with a final balloon repayment at maturity
C55: =+$C$42 -> Subordinated Notes: | E55: 0.04 | F55: 0.03 | P55: Bullet Repayment at maturity (year 5)
E57: Historical | J57: Forecast
B58: Debt Schedule: | D58: =$D$5 -> Units: | E58: 21 | F58: =E58+1 -> 22 | G58: =F58+1 -> 23 | H58: =G58+1 -> 24 | I58: =H58+1 -> 25 | J58: =I58+1 -> 26 | K58: =J58+1 -> 27 | L58: =K58+1 -> 28 | M58: =L58+1 -> 29 | N58: =M58+1 -> 30
E59: 0 | F59: On
C60: Circuit Breaker | D60: 0 | E60: 1 | F60: Off
C62: Cash Interest Rates:
C63: SOFR: | J63: 0.035 | K63: 0.035 | L63: 0.0375 | M63: 0.04 | N63: 0.0425
C64: =+$C$39 -> Revolver: | D64: % | J64: =MAX(J63,1%)+1% -> 0.045 | K64: =MAX(K63,1%)+1% -> 0.045 | L64: =MAX(L63,1%)+1% -> 0.0475 | M64: =MAX(M63,1%)+1% -> 0.05 | N64: =MAX(N63,1%)+1% -> 0.0525
C65: =+$C$40 -> Term Loan A | D65: % | J65: 0.05 | K65: 0.05 | L65: 0.05 | M65: 0.05 | N65: 0.0525
C66: =+C54 -> Term Loan B | D66: % | J66: =J63+3% -> 0.065 | K66: =K63+3% -> 0.065 | L66: =L63+3% -> 0.0675 | M66: =M63+3% -> 0.07 | N66: =N63+3% -> 0.0725
C67: =+$C$42 -> Subordinated Notes: | D67: % | J67: =J63+5% -> 0.085 | K67: =K63+5% -> 0.085 | L67: =L63+5% -> 0.0875 | M67: =M63+5% -> 0.09 | N67: =N63+5% -> 0.0925
C68: Cash: | D68: % | J68: 0.005 | K68: 0.005 | L68: 0.005 | M68: 0.005 | N68: 0.005
C70: Cash Flow and Revolver Calculations:
C71: Cash - Beginning of Period: | D71: $ M | J71: =J135 -> 596476.75 | K71: =K135 -> 128513.05 | L71: =L135 -> 826622.17 | M71: =M135 -> 2048408 | N71: =N135 -> 5255266.8
C72: (+) Free Cash Flow: | D72: $ M | J72: =J133 -> 1514134.6 | K72: =K133 -> 1912484 | L72: =L133 -> 2173726.6 | M72: =M133 -> 2560387 | N72: =N133 -> 3163214.4
C73: (-) Amortization: | D73: $ M | J73: =J95 -> -623951.6 | K73: =K95 -> -155987.9 | L73: =L95 -> -155987.9 | M73: =M95 -> -155987.9 | N73: =N95 -> 0
C74: (-) Minimum Cash: | D74: $ M | J74: =-$E$30 -> -596476.75 | K74: =-$E$30 -> -596476.75 | L74: =-$E$30 -> -596476.75 | M74: =-$E$30 -> -596476.75 | N74: =-$E$30 -> -596476.75
C75: Cash Flow Surplus / (Shortfall): | D75: $ M | J75: =IF($D$60="ON",0,SUM(J71:J74)) -> 890183 | K75: =IF($D$60="ON",0,SUM(K71:K74)) -> 1288532.4 | L75: =IF($D$60="ON",0,SUM(L71:L74)) -> 2247884.2 | M75: =IF($D$60="ON",0,SUM(M71:M74)) -> 3856330.4 | N75: =IF($D$60="ON",0,SUM(N71:N74)) -> 7822004.4
C77: Revolver (Drawn):
C78: BoP Revolver: | D78: $ M | J78: =I80 -> 1559879 | K78: =J80 -> 669696 | L78: =K80 -> 0 | M78: =L80 -> 0 | N78: =M80 -> 0
C79: Revolver (Repayments) / Drawdowns: | D79: $ M | J79: =IF(J75>0,-MIN(J75,J78),-J75) -> -890183 | K79: =IF(K75>0,-MIN(K75,K78),-K75) -> -669696 | L79: =IF(L75>0,-MIN(L75,L78),-L75) -> 0 | M79: =IF(M75>0,-MIN(M75,M78),-M75) -> 0 | N79: =IF(N75>0,-MIN(N75,N78),-N75) -> 0
C80: EoP Revolver: | D80: $ M | I80: =D39 -> 1559879 | J80: =SUM(J78:J79) -> 669696 | K80: =SUM(K78:K79) -> 0 | L80: =SUM(L78:L79) -> 0 | M80: =SUM(M78:M79) -> 0 | N80: =SUM(N78:N79) -> 0
C82: Cash Interest Rates | D82: % | J82: =J64 -> 0.045 | K82: =K64 -> 0.045 | L82: =L64 -> 0.0475 | M82: =M64 -> 0.05 | N82: =N64 -> 0.0525 | O82: =O64 -> 0
C83: Cash Interest Expense: | D83: $ M | J83: =J78*J64 -> 70194.555 | K83: =K78*K64 -> 30136.32 | L83: =L78*L64 -> 0 | M83: =M78*M64 -> 0 | N83: =N78*N64 -> 0
C85: BoP Revolver (Undrawn): | G85: Maximum
C86: BoP Revolver: | D86: $ M | G86: =E34 -> 3590662.5 | J86: =I88 -> 2030783.5 | K86: =J88 -> 2920966.5 | L86: =K88 -> 3590662.5 | M86: =L88 -> 3590662.5 | N86: =M88 -> 3590662.5
C87: Revolver (Repayments) / Drawdowns: | D87: $ M | J87: =-J79 -> 890183 | K87: =-K79 -> 669696 | L87: =-L79 -> 0 | M87: =-M79 -> 0 | N87: =-N79 -> 0
C88: EoP Revolver: | D88: $ M | I88: =G86-I80 -> 2030783.5 | J88: =SUM(J86:J87) -> 2920966.5 | K88: =SUM(K86:K87) -> 3590662.5 | L88: =SUM(L86:L87) -> 3590662.5 | M88: =SUM(M86:M87) -> 3590662.5 | N88: =SUM(N86:N87) -> 3590662.5
C90: Revolver Standby Fee Rate | D90: % | J90: =$H$52 -> 0.01 | K90: =$H$52 -> 0.01 | L90: =$H$52 -> 0.01 | M90: =$H$52 -> 0.01 | N90: =$H$52 -> 0.01 | O90: =$H$52 -> 0.01
C91: Revolver Standby Fee | D91: $ M | J91: =J88*J90 -> 29209.665 | K91: =K88*K90 -> 35906.625 | L91: =L88*L90 -> 35906.625 | M91: =M88*M90 -> 35906.625 | N91: =N88*N90 -> 35906.625 | O91: =O88*O90 -> 0
C93: Term Loan A:
C94: BoP Term Loans: | D94: $ M | J94: =I97 -> 3119758 | K94: =J97 -> 2495806.4 | L94: =K97 -> 2030400.3 | M94: =L97 -> 750470.34 | N94: =M97 -> 0
C95: (-) Amortization: | D95: $ M | J95: =-MIN(J94,$I$97*$G$53) -> -623951.6 | K95: =-MIN(K94,$I$97*$G$54) -> -155987.9 | L95: =-MIN(L94,$I$97*$G$54) -> -155987.9 | M95: =-MIN(M94,$I$97*$G$54) -> -155987.9 | N95: =-MIN(N94,$I$97*$G$54) -> 0
C96: (-) Cash Flow Sweep: | D96: $ M | J96: =IF(J75+J79>0,-MIN((J75+J79)*$I$54,SUM(J94:J95)),0) -> 0 | K96: =IF(K75+K79>0,-MIN((K75+K79)*$I$54,SUM(K94:K95)),0) -> -309418.18 | L96: =IF(L75+L79>0,-MIN((L75+L79)*$I$54,SUM(L94:L95)),0) -> -1123942.1 | M96: =IF(M75+M79>0,-MIN((M75+M79)*$I$54,SUM(M94:M95)),0) -> -594482.44 | N96: =IF(N75+N79>0,-MIN((N75+N79)*$I$54,SUM(N94:N95)),0) -> 0
C97: EoP Term Loans: | D97: $ M | I97: =D40 -> 3119758 | J97: =SUM(J94:J96) -> 2495806.4 | K97: =SUM(K94:K96) -> 2030400.3 | L97: =SUM(L94:L96) -> 750470.34 | M97: =SUM(M94:M96) -> 0 | N97: =SUM(N94:N96) -> 0
C99: Cash Interest Rates: | D99: $ M | J99: =J65 -> 0.05 | K99: =K65 -> 0.05 | L99: =L65 -> 0.05 | M99: =M65 -> 0.05 | N99: =N65 -> 0.0525
C100: Cash Interest Expense: | D100: $ M | J100: =IF($D$60=0,AVERAGE(J94,J97)*J99,J94*J99) -> 140389.11 | K100: =IF($D$60=0,AVERAGE(K94,K97)*K99,K94*K99) -> 113155.17 | L100: =IF($D$60=0,AVERAGE(L94,L97)*L99,L94*L99) -> 69521.767 | M100: =IF($D$60=0,AVERAGE(M94,M97)*M99,M94*M99) -> 18761.759 | N100: =IF($D$60=0,AVERAGE(N94,N97)*N99,N94*N99) -> 0
C102: Term Loan B:
C103: BoP Term Loans: | D103: $ M | J103: =I106 -> 9359274 | K103: =J106 -> 8891310.3 | L103: =K106 -> 8812037.5 | M103: =L106 -> 9140026.7 | N103: =M106 -> 10536969
C104: (-) Amortization: | D104: $ M | J104: =-MIN(J103,$I$106*$G$54) -> -467963.7 | K104: =-MIN(K103,$I$97*$G$54) -> -155987.9 | L104: =-MIN(L103,$I$97*$G$54) -> -155987.9 | M104: =-MIN(M103,$I$97*$G$54) -> -155987.9 | N104: =-MIN(N103,$I$97*$G$54) -> -155987.9
C105: (-) Cash Flow Sweep: | D105: $ M | J105: =IF(J75+J79+J95+J96>0,-MIN((J75+J79+J95+J96)*$I$54,SUM(J103:J104)),0) -> 0 | K105: =IF(K75+K79+K95+K96>0,MIN((K75+K79+K95+K96)*$I$54,SUM(K103:K104)),0) -> 76715.14 | L105: =IF(L75+L79+L95+L96>0,MIN((L75+L79+L95+L96)*$I$54,SUM(L103:L104)),0) -> 483977.09 | M105: =IF(M75+M79+M95+M96>0,MIN((M75+M79+M95+M96)*$I$54,SUM(M103:M104)),0) -> 1552930 | N105: =IF(N75+N79+N95+N96>0,MIN((N75+N79+N95+N96)*$I$54,SUM(N103:N104)),0) -> 3911002.2
C106: EoP Term Loans: | D106: $ M | I106: =D41 -> 9359274 | J106: =SUM(J103:J105) -> 8891310.3 | K106: =SUM(K103:K105) -> 8812037.5 | L106: =SUM(L103:L105) -> 9140026.7 | M106: =SUM(M103:M105) -> 10536969 | N106: =SUM(N103:N105) -> 14291983
C108: Cash Interest Rates: | D108: % | J108: =J66 -> 0.065 | K108: =K66 -> 0.065 | L108: =L66 -> 0.0675 | M108: =M66 -> 0.07 | N108: =N66 -> 0.0725
C109: Cash Interest Expense: | D109: $ M | J109: =IF($D$60=0,AVERAGE(J103,J106)*J108,J103*J108) -> 593143.99 | K109: =IF($D$60=0,AVERAGE(K103,K106)*K108,K103*K108) -> 575358.8 | L109: =IF($D$60=0,AVERAGE(L103,L106)*L108,L103*L108) -> 605882.17 | M109: =IF($D$60=0,AVERAGE(M103,M106)*M108,M103*M108) -> 688694.84 | N109: =IF($D$60=0,AVERAGE(N103,N106)*N108,N103*N108) -> 900049.51
C111: Subordinated Notes:
C112: BoP Subordinated Notes: | D112: $ M | J112: =I114 -> 3119758 | K112: =J114 -> 3213350.7 | L112: =K114 -> 3309751.3 | M112: =L114 -> 3409043.8 | N112: =M114 -> 3511315.1
C113: (+) PIK Interest: | D113: $ M | J113: =J112*$F$55 -> 93592.74 | K113: =K112*$F$55 -> 96400.522 | L113: =L112*$F$55 -> 99292.538 | M113: =M112*$F$55 -> 102271.31 | N113: =N112*$F$55 -> 105339.45
C114: EoP Subordinated Notes: | D114: $ M | I114: =D42 -> 3119758 | J114: =SUM(J112:J113) -> 3213350.7 | K114: =SUM(K112:K113) -> 3309751.3 | L114: =SUM(L112:L113) -> 3409043.8 | M114: =SUM(M112:M113) -> 3511315.1 | N114: =SUM(N112:N113) -> 3616654.6
C116: Cash Interest Rates: | D116: % | J116: =J67 -> 0.085 | K116: =K67 -> 0.085 | L116: =L67 -> 0.0875 | M116: =M67 -> 0.09 | N116: =N67 -> 0.0925
C117: Cash Interest Expense: | D117: $ M | J117: =IF($D$60=0,AVERAGE(J112,J114)*J116,J112*J116) -> 269157.12 | K117: =IF($D$60=0,AVERAGE(K112,K114)*K116,K112*K116) -> 277231.84 | L117: =IF($D$60=0,AVERAGE(L112,L114)*L116,L112*L116) -> 293947.28 | M117: =IF($D$60=0,AVERAGE(M112,M114)*M116,M112*M116) -> 311416.15 | N117: =IF($D$60=0,AVERAGE(N112,N114)*N116,N112*N116) -> 329668.6
C119: Total:
C120: Debt (Repayment) / Drawdown: | D120: $ M | J120: =J79+J95+J96+J104+J105 -> -1982098.3 | K120: =K79+K95+K96+K104+K105 -> -1214374.8 | L120: =L79+L95+L96+L104+L105 -> -951940.79 | M120: =M79+M95+M96+M104+M105 -> 646471.77 | N120: =N79+N95+N96+N104+N105 -> 3755014.3
C121: Cash Interest Expense: | D121: $ M | J121: =-(J83+J91+J100+J109) -> -832937.32 | K121: =K83+K91+K100+K109 -> 754556.92 | L121: =L83+L91+L100+L109 -> 711310.56 | M121: =M83+M91+M100+M109 -> 743363.23 | N121: =N83+N91+N100+N109 -> 935956.13
...

Sheet Projections>

Sheet Revenue Build
A1: ='Cover Page'!$C$3 -> Coinbase Global Inc., (NASDAQ: COIN) | F1: 2021 | G1: =F1+1 -> 2022 | H1: =G1+1 -> 2023 | I1: =H1+1 -> 2024 | J1: =I1+1 -> 2025 | K1: =J1+1 -> 2026 | L1: =K1+1 -> 2027 | M1: =L1+1 -> 2028 | N1: =M1+1 -> 2029 | O1: =N1+1 -> 2030 | Q1: 2021 | R1: =Q1 -> 2021 | S1: =R1 -> 2021 | T1: =S1 -> 2021 | U1: =T1+1 -> 2022 | V1: =U1 -> 2022 | W1: =V1 -> 2022 | X1: =W1 -> 2022 | Y1: =X1+1 -> 2023 | Z1: =Y1 -> 2023 | AA1: =Z1 -> 2023 | AB1: =AA1 -> 2023 | AC1: =AB1+1 -> 2024 | AD1: =AC1 -> 2024 | AE1: =AD1 -> 2024 | AF1: =AE1 -> 2024 | AG1: =AF1+1 -> 2025 | AH1: =AG1 -> 2025 | AI1: =AH1 -> 2025 | AJ1: =AI1 -> 2025 | AK1: =AJ1+1 -> 2026 | AL1: =AK1 -> 2026 | AM1: =AL1 -> 2026 | AN1: =AM1 -> 2026 | AO1: =AN1+1 -> 2027 | AP1: =AO1 -> 2027 | AQ1: =AP1 -> 2027 | AR1: =AQ1 -> 2027 | AS1: =AR1+1 -> 2028 | AT1: =AS1 -> 2028 | AU1: =AT1 -> 2028 | AV1: =AU1 -> 2028 | AW1: =AV1+1 -> 2029 | AX1: =AW1 -> 2029 | AY1: =AX1 -> 2029 | AZ1: =AY1 -> 2029 | BA1: =AZ1+1 -> 2030 | BB1: =BA1 -> 2030 | BC1: =BB1 -> 2030 | BD1: =BC1 -> 2030
A2: Revenue Build | F2: Q4 | G2: Q4 | H2: Q4 | I2: Q4 | J2: Q4 | K2: Q4 | L2: Q4 | M2: Q4 | N2: Q4 | O2: Q4 | Q2: Q1 | R2: Q2 | S2: Q3 | T2: Q4 | U2: Q1 | V2: Q2 | W2: Q3 | X2: Q4 | Y2: Q1 | Z2: Q2 | AA2: Q3 | AB2: Q4 | AC2: Q1 | AD2: Q2 | AE2: Q3 | AF2: Q4 | AG2: Q1 | AH2: Q2 | AI2: Q3 | AJ2: Q4 | AK2: Q1 | AL2: Q2 | AM2: Q3 | AN2: Q4 | AO2: Q1 | AP2: Q2 | AQ2: Q3 | AR2: Q4 | AS2: Q1 | AT2: Q2 | AU2: Q3 | AV2: Q4 | AW2: Q1 | AX2: Q2 | AY2: Q3 | AZ2: Q4 | BA2: Q1 | BB2: Q2 | BC2: Q3 | BD2: Q4
F3: 12 | G3: 12 | H3: 12 | I3: 12 | J3: 12 | K3: 12 | L3: 12 | M3: 12 | N3: 12 | O3: 12 | Q3: 3 | R3: 3 | S3: 3 | T3: 3 | U3: 3 | V3: 3 | W3: 3 | X3: 3 | Y3: 3 | Z3: 3 | AA3: 3 | AB3: 3 | AC3: 3 | AD3: 3 | AE3: 3 | AF3: 3 | AG3: 3 | AH3: 3 | AI3: 3 | AJ3: 3 | AK3: 3 | AL3: 3 | AM3: 3 | AN3: 3 | AO3: 3 | AP3: 3 | AQ3: 3 | AR3: 3 | AS3: 3 | AT3: 3 | AU3: 3 | AV3: 3 | AW3: 3 | AX3: 3 | AY3: 3 | AZ3: 3 | BA3: 3 | BB3: 3 | BC3: 3 | BD3: 3
F4: 365 | G4: 365 | H4: 365 | I4: 366 | J4: 365 | K4: 365 | L4: 365 | M4: 366 | N4: 365 | O4: 365 | Q4: 90 | R4: =R6-Q6 -> 91 | S4: =S6-R6 -> 92 | T4: =T6-S6 -> 92 | U4: =U6-T6 -> 90 | V4: =V6-U6 -> 91 | W4: =W6-V6 -> 92 | X4: =X6-W6 -> 92 | Y4: =Y6-X6 -> 90 | ... BD4: =BD6-BC6 -> 92
F5: Actuals | G5: Actuals | H5: Actuals | I5: Actuals | J5: Actuals | K5: Forecasted | L5: Forecasted | M5: Forecasted | N5: Forecasted | O5: Forecasted | Q5: Actuals | R5: Actuals | S5: Actuals | T5: Actuals | U5: Actuals | V5: Actuals | W5: Actuals | X5: Actuals | Y5: Actuals | Z5: Actuals | AA5: Actuals | AB5: Actuals | AC5: Actuals | AD5: Actuals | AE5: Actuals | AF5: Actuals | AG5: Actuals | AH5: Actuals | AI5: Actuals | AJ5: Actuals | AK5: Forecasted | AL5: Forecasted | AM5: Forecasted | AN5: Forecasted | AO5: Forecasted | AP5: Forecasted | AQ5: Forecasted | AR5: Forecasted | AS5: Forecasted | AT5: Forecasted | AU5: Forecasted | AV5: Forecasted | AW5: Forecasted | AX5: Forecasted | AY5: Forecasted | AZ5: Forecasted | BA5: Forecasted | BB5: Forecasted | BC5: Forecasted | BD5: Forecasted
A6: In USD '000s, Unless Stated Otherwise | F6: 44561 | G6: =EOMONTH(F6,12) -> 44926 | H6: =EOMONTH(G6,12) -> 45291 | I6: =EOMONTH(H6,12) -> 45657 | J6: =EOMONTH(I6,12) -> 46022 | K6: =EOMONTH(J6,12) -> 46387 | L6: =EOMONTH(K6,12) -> 46752 | M6: =EOMONTH(L6,12) -> 47118 | N6: =EOMONTH(M6,12) -> 47483 | O6: =EOMONTH(N6,12) -> 47848 | Q6: 44286 | R6: =EOMONTH(Q6,3) -> 44377 | S6: =EOMONTH(R6,3) -> 44469 | T6: =EOMONTH(S6,3) -> 44561 | U6: =EOMONTH(T6,3) -> 44651 | V6: =EOMONTH(U6,3) -> 44742 | W6: =EOMONTH(V6,3) -> 44834 | X6: =EOMONTH(W6,3) -> 44926 | Y6: =EOMONTH(X6,3) -> 45016 | ... BD6: =EOMONTH(BC6,3) -> 47848
A8: x | B8: Sales Summary | E8: Units | F8: 21 | G8: =F8+1 -> 22 | H8: =G8+1 -> 23 | I8: =H8+1 -> 24 | J8: =I8+1 -> 25 | K8: =J8+1 -> 26 | L8: =K8+1 -> 27 | M8: =L8+1 -> 28 | N8: =M8+1 -> 29 | O8: =N8+1 -> 30 | Q8: 44286 | R8: 44377 | S8: 44469 | T8: 44561 | U8: 44651 | V8: 44742 | W8: 44834 | X8: 44926 | Y8: 45016 | Z8: 45107 | AA8: 45199 | AB8: 45291 | AC8: 45382 | AD8: 45473 | AE8: 45565 | AF8: 45657 | AG8: 45747 | AH8: 45838 | AI8: 45930 | AJ8: 46022 | AK8: 46112 | AL8: 46203 | AM8: 46295 | AN8: 46387 | AO8: 46477 | AP8: 46568 | AQ8: 46660 | AR8: 46752 | AS8: 46843 | AT8: 46934 | AU8: 47026 | AV8: 47118 | AW8: 47208 | AX8: 47299 | AY8: 47391 | AZ8: 47483 | BA8: 47573 | BB8: 47664 | BC8: 47756 | BD8: 47848
B10: TRANSACTION REVENUE
B11: Consumer, net | E11: USD '000s | F11: =SUMIFS($Q11:$BD11,$Q$1:$BD$1,F$1) -> 6533700 | G11: =SUMIFS($Q11:$BD11,$Q$1:$BD$1,G$1) -> 2236900 | H11: =SUMIFS($Q11:$BD11,$Q$1:$BD$1,H$1) -> 1457500 | I11: =SUMIFS($Q11:$BD11,$Q$1:$BD$1,I$1) -> 3430400 | J11: =SUMIFS($Q11:$BD11,$Q$1:$BD$1,J$1) -> 3322800 | K11: =SUMIFS($Q11:$BD11,$Q$1:$BD$1,K$1) -> 3356914.4 | L11: =SUMIFS($Q11:$BD11,$Q$1:$BD$1,L$1) -> 3774086.3 | M11: =SUMIFS($Q11:$BD11,$Q$1:$BD$1,M$1) -> 4671798.4 | ... O11: =SUMIFS($Q11:$BD11,$Q$1:$BD$1,O$1) -> 8996525.9 | Q11: 1497900 | R11: 1828000 | S11: 1022000 | T11: 2185800 | U11: 965800 | V11: 616200 | W11: 346100 | X11: 308800 | Y11: 361700 | Z11: 352400 | AA11: 274500 | AB11: 468900 | AC11: 935200 | AD11: 664800 | AE11: 483300 | AF11: 1347100 | AG11: 1095500 | AH11: 649900 | AI11: 843500 | AJ11: 733900 | AK11: =AK65 -> 1054697.8 | AL11: =AL65 -> 664409.29 | AM11: =AM65 -> 810889.83 | AN11: =AN65 -> 826917.51 | AO11: =AO65 -> 1166110.3 | AP11: =AP65 -> 743945.18 | AQ11: =AQ65 -> 852158.08 | AR11: =AR65 -> 1011872.7 | ... BD11: =BD65 -> 2961211.2
B12: Institutional, net | E12: USD '000s | F12: =SUMIFS($Q12:$BD12,$Q$1:$BD$1,F$1) -> 346300 | G12: =SUMIFS($Q12:$BD12,$Q$1:$BD$1,G$1) -> 119400 | H12: =SUMIFS($Q12:$BD12,$Q$1:$BD$1,H$1) -> 96000 | I12: =SUMIFS($Q12:$BD12,$Q$1:$BD$1,I$1) -> 345600 | J12: =SUMIFS($Q12:$BD12,$Q$1:$BD$1,J$1) -> 479700 | K12: =SUMIFS($Q12:$BD12,$Q$1:$BD$1,K$1) -> 519600.79 | L12: =SUMIFS($Q12:$BD12,$Q$1:$BD$1,L$1) -> 562932.71 | M12: =SUMIFS($Q12:$BD12,$Q$1:$BD$1,M$1) -> 614615 | ... O12: =SUMIFS($Q12:$BD12,$Q$1:$BD$1,O$1) -> 749104.37 | Q12: 85400 | R12: 102400 | S12: 67700 | T12: 90800 | U12: 47200 | V12: 39000 | W12: 19800 | X12: 13400 | Y12: 22300 | Z12: 23000 | AA12: 14000 | AB12: 36700 | AC12: 85400 | AD12: 63600 | AE12: 55300 | AF12: 141300 | AG12: 98900 | AH12: 60800 | AI12: 135000 | AJ12: 185000 | AK12: =AK90 -> 98007.873 | AL12: =AL90 -> 63069.62 | AM12: =AM90 -> 114086.36 | AN12: =AN90 -> 244436.94 | AO12: =AO90 -> 93354.63 | AP12: =AP90 -> 64857.386 | AQ12: =AQ90 -> 115927.43 | AR12: =AR90 -> 288793.27 | ... BD12: =BD90 -> 476263.98
B13: Other transaction revenue, net | E13: USD '000s | F13: =SUMIFS($Q13:$BD13,$Q$1:$BD$1,F$1) -> 0 | G13: =SUMIFS($Q13:$BD13,$Q$1:$BD$1,G$1) -> 0 | H13: =SUMIFS($Q13:$BD13,$Q$1:$BD$1,H$1) -> 23600 | I13: =SUMIFS($Q13:$BD13,$Q$1:$BD$1,I$1) -> 210200 | J13: =SUMIFS($Q13:$BD13,$Q$1:$BD$1,J$1) -> 252800 | K13: =SUMIFS($Q13:$BD13,$Q$1:$BD$1,K$1) -> 256010.31 | L13: =SUMIFS($Q13:$BD13,$Q$1:$BD$1,L$1) -> 266582.21 | M13: =SUMIFS($Q13:$BD13,$Q$1:$BD$1,M$1) -> 285267.43 | ... O13: =SUMIFS($Q13:$BD13,$Q$1:$BD$1,O$1) -> 352264.33 | Q13: 0 | R13: 0 | S13: 0 | T13: 0 | U13: 0 | V13: 0 | W13: 0 | X13: 0 | Y13: 0 | Z13: 0 | AA13: 0 | AB13: 23600 | AC13: 56100 | AD13: 52500 | AE13: 34000 | AF13: 67600 | AG13: 67800 | AH13: 53500 | AI13: 67700 | AJ13: 63800 | AK13: =AK104 -> 68000.592 | AL13: =AL104 -> 42216.077 | AM13: =AM104 -> 85668.972 | AN13: =AN104 -> 60124.668 | AO13: =AO104 -> 68201.777 | AP13: =AP104 -> 33312.096 | AQ13: =AQ104 -> 108407.28 | AR13: =AR104 -> 56661.061 | ... BD13: =BD104 -> 47422.094
B14: Total Transaction Revenue | E14: USD '000s | F14: =SUM(F11:F13) -> 6880000 | G14: =SUM(G11:G13) -> 2356300 | H14: =SUM(H11:H13) -> 1577100 | I14: =SUM(I11:I13) -> 3986200 | J14: =SUM(J11:J13) -> 4055300 | K14: =SUM(K11:K13) -> 4132525.5 | L14: =SUM(L11:L13) -> 4603601.2 | M14: =SUM(M11:M13) -> 5571680.9 | ... O14: =SUM(O11:O13) -> 10097895 | Q14: =SUM(Q11:Q13) -> 1583300 | R14: =SUM(R11:R13) -> 1930400 | S14: =SUM(S11:S13) -> 1089700 | T14: =SUM(T11:T13) -> 2276600 | U14: =SUM(U11:U13) -> 1013000 | V14: =SUM(V11:V13) -> 655200 | W14: =SUM(W11:W13) -> 365900 | X14: =SUM(X11:X13) -> 322200 | ... BD14: =SUM(BD11:BD13) -> 3484897.3
J15: =J11/J14 -> 0.81937218 | K15: =J12/J14 -> 0.11828965
B16: SUBSCRIPTION & SERVICES
B17: Stablecoin revenue | E17: USD '000s | F17: =SUMIFS($Q17:$BD17,$Q$1:$BD$1,F$1) -> 0 | G17: =SUMIFS($Q17:$BD17,$Q$1:$BD$1,G$1) -> 593000 | H17: =SUMIFS($Q17:$BD17,$Q$1:$BD$1,H$1) -> 693600 | I17: =SUMIFS($Q17:$BD17,$Q$1:$BD$1,I$1) -> 910500 | J17: =SUMIFS($Q17:$BD17,$Q$1:$BD$1,J$1) -> 1348800 | K17: =SUMIFS($Q17:$BD17,$Q$1:$BD$1,K$1) -> 1577801.3 | L17: =SUMIFS($Q17:$BD17,$Q$1:$BD$1,L$1) -> 2019356 | M17: =SUMIFS($Q17:$BD17,$Q$1:$BD$1,M$1) -> 2122214 | ... O17: =SUMIFS($Q17:$BD17,$Q$1:$BD$1,O$1) -> 2390793.8 | Q17: 0 | R17: 0 | S17: 0 | T17: 0 | U17: 82000 | V17: 147000 | W17: 182000 | X17: 182000 | Y17: 199000 | Z17: 151000 | AA17: 172000 | AB17: 171600 | AC17: 197300 | AD17: 240400 | AE17: 246900 | AF17: 225900 | AG17: 297500 | AH17: 332500 | AI17: 354700 | AJ17: 364100 | AK17: =AK130*AK137*1000000 -> 446296.06 | AL17: =AL130*AL137*1000000 -> 378928.72 | AM17: =AM130*AM137*1000000 -> 377418.97 | AN17: =AN130*AN137*1000000 -> 375157.6 | AO17: =AO130*AO137*1000000 -> 633184.96 | AP17: =AP130*AP137*1000000 -> 503639.14 | AQ17: =AQ130*AQ137*1000000 -> 460013.14 | AR17: =AR130*AR137*1000000 -> 422518.75 | ... BD17: =BD130*BD137*1000000 -> 497526.52
B18: Blockchain rewards | E18: USD '000s | F18: =SUMIFS($Q18:$BD18,$Q$1:$BD$1,F$1) -> 223200 | G18: =SUMIFS($Q18:$BD18,$Q$1:$BD$1,G$1) -> 275500 | H18: =SUMIFS($Q18:$BD18,$Q$1:$BD$1,H$1) -> 305100 | I18: =SUMIFS($Q18:$BD18,$Q$1:$BD$1,I$1) -> 705700 | J18: =SUMIFS($Q18:$BD18,$Q$1:$BD$1,J$1) -> 677300 | K18: =SUMIFS($Q18:$BD18,$Q$1:$BD$1,K$1) -> 1094839.7 | L18: =SUMIFS($Q18:$BD18,$Q$1:$BD$1,L$1) -> 1131520.5 | M18: =SUMIFS($Q18:$BD18,$Q$1:$BD$1,M$1) -> 1256802.7 | ... O18: =SUMIFS($Q18:$BD18,$Q$1:$BD$1,O$1) -> 1408713.6 | Q18: 0 | R18: 39000 | S18: 81500 | T18: 102700 | U18: 81900 | V18: 68400 | W18: 62800 | X18: 62400 | Y18: 74000 | Z18: 74000 | AA18: 62000 | AB18: 95100 | AC18: 150900 | AD18: 185100 | AE18: 154800 | AF18: 214900 | AG18: 196600 | AH18: 144500 | AI18: 184600 | AJ18: 151600 | AK18: =AK131*AK138*1000000 -> 326547.27 | AL18: =AL131*AL138*1000000 -> 277255.73 | AM18: =AM131*AM138*1000000 -> 258551.23 | AN18: =AN131*AN138*1000000 -> 232485.48 | AO18: =AO131*AO138*1000000 -> 358642.98 | AP18: =AP131*AP138*1000000 -> 277541.45 | AQ18: =AQ131*AQ138*1000000 -> 255814.78 | AR18: =AR131*AR138*1000000 -> 239521.28 | ... BD18: =BD131*BD138*1000000 -> 296533.76
B19: Interest & finance fee income | E19: USD '000s | F19: =SUMIFS($Q19:$BD19,$Q$1:$BD$1,F$1) -> 22500 | G19: =SUMIFS($Q19:$BD19,$Q$1:$BD$1,G$1) -> 327000 | H19: =SUMIFS($Q19:$BD19,$Q$1:$BD$1,H$1) -> 119900 | I19: =SUMIFS($Q19:$BD19,$Q$1:$BD$1,I$1) -> 265800 | J19: =SUMIFS($Q19:$BD19,$Q$1:$BD$1,J$1) -> 247100 | K19: =SUMIFS($Q19:$BD19,$Q$1:$BD$1,K$1) -> 450893.47 | L19: =SUMIFS($Q19:$BD19,$Q$1:$BD$1,L$1) -> 548607.65 | M19: =SUMIFS($Q19:$BD19,$Q$1:$BD$1,M$1) -> 518406.55 | ... O19: =SUMIFS($Q19:$BD19,$Q$1:$BD$1,O$1) -> 595223.88 | Q19: 0 | R19: 6500 | S19: 8400 | T19: 7600 | U19: 32500 | V19: 10500 | W19: 101800 | X19: 182200 | Y19: 17000 | Z19: 26000 | AA19: 28000 | AB19: 48900 | AC19: 66700 | AD19: 69400 | AE19: 64000 | AF19: 65700 | AG19: 63100 | AH19: 59300 | AI19: 64800 | AJ19: 59900 | AK19: =AK132*AK139*1000000 -> 129908.69 | AL19: =AL132*AL139*1000000 -> 110299.28 | AM19: =AM132*AM139*1000000 -> 106926.51 | AN19: =AN132*AN139*1000000 -> 103758.98 | AO19: =AO132*AO139*1000000 -> 172625.75 | AP19: =AP132*AP139*1000000 -> 135097.17 | AQ19: =AQ132*AQ139*1000000 -> 128705.85 | AR19: =AR132*AR139*1000000 -> 112178.88 | ... BD19: =BD132*BD139*1000000 -> 126681.86
B20: Custodial fee revenue | E20: USD '000s | F20: =SUMIFS($Q20:$BD20,$Q$1:$BD$1,F$1) -> 136300 | G20: =SUMIFS($Q20:$BD20,$Q$1:$BD$1,G$1) -> 79800 | H20: =SUMIFS($Q20:$BD20,$Q$1:$BD$1,H$1) -> 19700 | I20: =SUMIFS($Q20:$BD20,$Q$1:$BD$1,I$1) -> 141600 | J20: =SUMIFS($Q20:$BD20,$Q$1:$BD$1,J$1) -> 0 | K20: =SUMIFS($Q20:$BD20,$Q$1:$BD$1,K$1) -> 0 | L20: =SUMIFS($Q20:$BD20,$Q$1:$BD$1,L$1) -> 0 | M20: =SUMIFS($Q20:$BD20,$Q$1:$BD$1,M$1) -> 0 | ... O20: =SUMIFS($Q20:$BD20,$Q$1:$BD$1,O$1) -> 0 | Q20: 23500 | R20: 31700 | S20: 31500 | T20: 49600 | U20: 31700 | V20: 22200 | W20: 14500 | X20: 11400 | Y20: 0 | Z20: 0 | AA20: 0 | AB20: 19700 | AC20: 32300 | AD20: 34500 | AE20: 31700 | AF20: 43100 | AG20: 0 | AH20: 0 | AI20: 0 | AJ20: 0 | AK20: =AK133*AK140*1000000 -> 0 | AL20: =AL133*AL140*1000000 -> 0 | AM20: =AM133*AM140*1000000 -> 0 | AN20: =AN133*AN140*1000000 -> 0 | AO20: =AO133*AO140*1000000 -> 0 | AP20: =AP133*AP140*1000000 -> 0 | AQ20: =AQ133*AQ140*1000000 -> 0 | AR20: =AR133*AR140*1000000 -> 0 | ... BD20: =BD133*BD140*1000000 -> 0
B21: Other subscription & services | E21: USD '000s | F21: =SUMIFS($Q21:$BD21,$Q$1:$BD$1,F$1) -> 113100 | G21: =SUMIFS($Q21:$BD21,$Q$1:$BD$1,G$1) -> 111300 | H21: =SUMIFS($Q21:$BD21,$Q$1:$BD$1,H$1) -> 120100 | I21: =SUMIFS($Q21:$BD21,$Q$1:$BD$1,I$1) -> 283400 | J21: =SUMIFS($Q21:$BD21,$Q$1:$BD$1,J$1) -> 554800 | K21: =SUMIFS($Q21:$BD21,$Q$1:$BD$1,K$1) -> 554036.83 | L21: =SUMIFS($Q21:$BD21,$Q$1:$BD$1,L$1) -> 575483.04 | M21: =SUMIFS($Q21:$BD21,$Q$1:$BD$1,M$1) -> 663983.33 | ... O21: =SUMIFS($Q21:$BD21,$Q$1:$BD$1,O$1) -> 798073.25 | Q21: 11100 | R21: 24900 | S21: 23600 | T21: 53500 | U21: 24300 | V21: 27800 | W21: 31400 | X21: 27800 | Y21: 24000 | Z21: 24000 | AA21: 32000 | AB21: 40100 | AC21: 63700 | AD21: 69600 | AE21: 58700 | AF21: 91400 | AG21: 140900 | AH21: 119500 | AI21: 142700 | AJ21: 151700 | AK21: =AK134*AK141*1000000 -> 178222.13 | AL21: =AL134*AL141*1000000 -> 135737.32 | AM21: =AM134*AM141*1000000 -> 123959.69 | AN21: =AN134*AN141*1000000 -> 116117.68 | AO21: =AO134*AO141*1000000 -> 178404.03 | AP21: =AP134*AP141*1000000 -> 141643.05 | AQ21: =AQ134*AQ141*1000000 -> 131859.66 | AR21: =AR134*AR141*1000000 -> 123576.3 | ... BD21: =BD134*BD141*1000000 -> 163140.62
