Workbook
Name IQ_CH: 110000
Name IQ_CQ: 5000
Name IQ_CY: 10000
Name IQ_DAILY: 500000
Name IQ_FH: 100000
Name IQ_FQ: 500
Name IQ_FY: 1000
Name IQ_LTM: 2000
Name IQ_MONTH: 15000
Name IQ_NTM: 6000
Name IQ_WEEK: 50000
Name IQ_YTD: 3000

Sheet Cover
B2: EOS Energy Enterprise
B4: Last Updated: | C4: =TODAY() -> 45990
B5: COMPANY INFORMATION
B7: Company Name: | C7: EOS Energy Enterprise
B8: Exchange: | C8: NASDAQ
B9: Ticker: | C9: EOSE
B10: Applied Currency: | C10: USD Mn
B11: Scenario: | C11: Base Case
B13: BUSINESS DESCRIPTION
B14: Eos Energy Enterprises is a U.S.-based clean energy company that designs, manufactures, and markets zinc-based battery energy storage systems (BESS) for utility-scale, microgrid, and commercial/industrial applications. Their flagship product, the Eos Znyth™ DC system, is a safe, non-flammable, and scalable alternative to lithium-ion technology for long-duration energy storage, typically from 4 to 16+ hours. The company, founded in 2008 and headquartered in Edison, New Jersey, also provides services like project management and long-term maintenance.
B20: STYLE GUIDE
B22: Number Format | F22: General Format | G22: Colour Format
B23: _(0.0%_);(0.0%);- | C23: 0.105 | F23: Hardcoded Numbers | G23: #0000FF
B24: _(* #,##0.0_);_(* (#,##0.0);_(* "-"??_);_(@_) | C24: -100000 | F24: Assumptions | G24: #FFFFCC
B25: #,##0.0);(#,##0.0) | C25: 10 | F25: From Another Sheet | G25: #00B050
B26: #,##0.0;(#,##0.0);- | C26: -20334.1 | F26: Formula | G26: #000000
C117: Adjustments:

Sheet DuPont Analysis
C1: EOS Energy Enterprises, Inc. (NASDAQ: EOSE)
C3: 12M Target Price
C4: Scenario | D4: =Cover!C11 -> Base Case
F5: Historical | K5: Forecasted
C6: In USD Mns, unless stated otherwise | F6: 20 | G6: =F6+1 -> 21 | H6: =G6+1 -> 22 | I6: =H6+1 -> 23 | J6: =I6+1 -> 24 | K6: =J6+1 -> 25 | L6: =K6+1 -> 26 | M6: =L6+1 -> 27 | N6: =M6+1 -> 28 | O6: =N6+1 -> 29
C8: Days
C10: Income Statement
C11: Total Revenue | F11: ='3FS'!E13 -> 0.219 | G11: ='3FS'!F13 -> 4.598 | H11: ='3FS'!G13 -> 17.924 | I11: ='3FS'!H13 -> 16.378 | J11: ='3FS'!I13 -> 15.606 | K11: ='3FS'!J13 -> 174.94326 | L11: ='3FS'!K13 -> 769.7381 | M11: ='3FS'!L13 -> 1641.2176 | ... O11: ='3FS'!N13 -> 2543.7125
C12: Capex | F12: =PPE!H29 -> 3.605 | G12: =PPE!I29 -> 15.589 | H12: =PPE!J29 -> 20.072 | I12: =PPE!K29 -> 29.323 | J12: =PPE!L29 -> 33.152 | K12: =PPE!M29 -> 46.628408 | L12: =PPE!N29 -> 91.642169 | M12: =PPE!O29 -> 180.71687 | ... O12: =PPE!Q29 -> 621.58758
F13: =F12/F11 -> 16.461187 | G13: =G12/G11 -> 3.3903871 | H13: =H12/H11 -> 1.1198393 | I13: =I12/I11 -> 1.7903895 | J13: =J12/J11 -> 2.1243112 | K13: =K12/K11 -> 0.26653446 | L13: =L12/L11 -> 0.1190563 | M13: =M12/M11 -> 0.11011146 | ... O13: =O12/O11 -> 0.24436236
C14: EBITDA | F14: ='3FS'!E29 -> 0 | G14: ='3FS'!F29 -> -101.693 | H14: ='3FS'!G29 -> -207.598 | I14: ='3FS'!H29 -> -136.07 | J14: ='3FS'!I29 -> -158.217 | K14: ='3FS'!J29 -> -0.43026561 | L14: ='3FS'!K29 -> 64.326751 | M14: ='3FS'!L29 -> 361.55404 | ... O14: ='3FS'!N29 -> 1397.583
C15: EBT | F15: ='3FS'!E37 -> -70.643 | G15: ='3FS'!F37 -> -124.266 | H15: ='3FS'!G37 -> -229.716 | I15: ='3FS'!H37 -> -229.516 | J15: ='3FS'!I37 -> -685.816 | K15: ='3FS'!J37 -> -39.45218 | L15: ='3FS'!K37 -> 9.1605309 | M15: ='3FS'!L37 -> 290.05615 | ... O15: ='3FS'!N37 -> 1153.564
C16: Operating Income | F16: ='3FS'!E26 -> -37.417 | G16: ='3FS'!F26 -> -104.306 | H16: ='3FS'!G26 -> -214.412 | I16: ='3FS'!H26 -> -145.778 | J16: ='3FS'!I26 -> -166.066 | K16: ='3FS'!J26 -> -17.494326 | L16: ='3FS'!K26 -> 30.789524 | M16: ='3FS'!L26 -> 295.41917 | ... O16: ='3FS'!N26 -> 1170.1077
C18: Net Income/(Loss) | F18: ='3FS'!E40 -> -70.643 | G18: ='3FS'!F40 -> -124.266 | H18: ='3FS'!G40 -> -229.767 | I18: ='3FS'!H40 -> -229.547 | J18: ='3FS'!I40 -> -685.837 | K18: ='3FS'!J40 -> -39.453388 | L18: ='3FS'!K40 -> 9.1608114 | M18: ='3FS'!L40 -> 290.06504 | ... O18: ='3FS'!N40 -> 1153.5993
C21: Balance Sheet
C22: Total Asset (EOP) | F22: ='3FS'!E67 -> 138.264 | G22: ='3FS'!F67 -> 169.175 | H22: ='3FS'!G67 -> 106.788 | I22: ='3FS'!H67 -> 186.492 | J22: ='3FS'!I67 -> 260.318 | K22: ='3FS'!J67 -> 340.72589 | L22: ='3FS'!K67 -> 1980.9592 | M22: ='3FS'!L67 -> 5643.7823 | ... O22: ='3FS'!N67 -> 13436.195
C23: Average Asset | G23: =AVERAGE(F22:G22) -> 153.7195 | H23: =AVERAGE(G22:H22) -> 137.9815 | I23: =AVERAGE(H22:I22) -> 146.64 | J23: =AVERAGE(I22:J22) -> 223.405 | K23: =AVERAGE(J22:K22) -> 300.52194 | L23: =AVERAGE(K22:L22) -> 1160.8425 | M23: =AVERAGE(L22:M22) -> 3812.3707 | N23: =AVERAGE(M22:N22) -> 7621.1824 | O23: =AVERAGE(N22:O22) -> 11517.389
C25: Total Equity (EOP) | F25: ='3FS'!E95 -> 120.785 | G25: ='3FS'!F95 -> 32.447 | H25: ='3FS'!G95 -> -132.711 | I25: ='3FS'!H95 -> -110.8 | J25: ='3FS'!I95 -> -581.767 | K25: ='3FS'!J95 -> -486.61008 | L25: ='3FS'!K95 -> 114.92784 | M25: ='3FS'!L95 -> 1668.0455 | ... O25: ='3FS'!N95 -> 7230.6631
C26: Average Equity | G26: =AVERAGE(F25:G25) -> 76.616 | H26: =AVERAGE(G25:H25) -> -50.132 | I26: =AVERAGE(H25:I25) -> -121.7555 | J26: =AVERAGE(I25:J25) -> -346.2835 | K26: =AVERAGE(J25:K25) -> -534.18854 | L26: =AVERAGE(K25:L25) -> -185.84112 | M26: =AVERAGE(L25:M25) -> 891.48669 | N26: =AVERAGE(M25:N25) -> 2893.7561 | O26: =AVERAGE(N25:O25) -> 5675.0649
C30: Extended DuPont ROE
C31: Interest Burden Ratio | F31: =F15/F16 -> 1.8879921 | G31: =G15/G16 -> 1.19136 | H31: =H15/H16 -> 1.0713766 | I31: =I15/I16 -> 1.5744214 | J31: =J15/J16 -> 4.1297797 | K31: =K15/K16 -> 2.2551414 | L31: =L15/L16 -> 0.29752103 | M31: =M15/M16 -> 0.98184607 | ... O31: =O15/O16 -> 0.98586132
C32: Tax Burden Ratio | F32: =F18/F15 -> 1 | G32: =G18/G15 -> 1 | H32: =H18/H15 -> 1.000222 | I32: =I18/I15 -> 1.0001351 | J32: =J18/J15 -> 1.0000306 | K32: =K18/K15 -> 1.0000306 | L32: =L18/L15 -> 1.0000306 | M32: =M18/M15 -> 1.0000306 | ... O32: =O18/O15 -> 1.0000306
C33: Operating Profit Margin | F33: =F16/F11 -> -170.85388 | G33: =G16/G11 -> -22.68508 | H33: =H16/H11 -> -11.962285 | I33: =I16/I11 -> -8.9008426 | J33: =J16/J11 -> -10.641164 | K33: =K16/K11 -> -0.1 | L33: =L16/L11 -> 0.04 | M33: =M16/M11 -> 0.18 | ... O33: =O16/O11 -> 0.46
C34: Asset Turnover | G34: =G11/G23 -> 0.029911625 | H34: =H11/H23 -> 0.12990147 | I34: =I11/I23 -> 0.11168849 | J34: =J11/J23 -> 0.069855196 | K34: =K11/K23 -> 0.5821314 | L34: =L11/L23 -> 0.66308571 | M34: =M11/M23 -> 0.43049791 | N34: =N11/N23 -> 0.29653942 | O34: =O11/O23 -> 0.22085843
C35: Financial Leverage | G35: =G23/G26 -> 2.0063629 | H35: =H23/H26 -> -2.7523638 | I35: =I23/I26 -> -1.2043809 | J35: =J23/J26 -> -0.64515058 | K35: =K23/K26 -> -0.56257655 | L35: =L23/L26 -> -6.2464244 | M35: =M23/M26 -> 4.2764192 | N35: =N23/N26 -> 2.6336644 | O35: =O23/O26 -> 2.0294726
C37: ROE | G37: =G31*G32*G33*G35*G34 -> -1.6219328 | H37: =H31*H32*H33*H35*H34 -> 4.5832402 | I37: =I31*I32*I33*I35*I34 -> 1.8853111 | J37: =J31*J32*J33*J35*J34 -> 1.9805651 | K37: =K31*K32*K33*K35*K34 -> 0.073856672 | L37: =L31*L32*L33*L35*L34 -> -0.04929378 | M37: =M31*M32*M33*M35*M34 -> 0.32537226 | N37: =N31*N32*N33*N35*N34 -> 0.24610883 | O37: =O31*O32*O33*O35*O34 -> 0.20327508

Sheet Valuation>

Sheet DCF
D2: EOS Energy Enterprises, Inc. (NASDAQ: EOSE)
D4: EOS Energy Enterprises, Inc. (NASDAQ: EOSE)
D6: 12M Target Price
D7: Scenario | F7: =Cover!C11 -> Base Case
H8: Historical | M8: Forecasted
D9: In USD, unless stated otherwise | E9: Units | H9: 20 | I9: =H9+1 -> 21 | J9: =I9+1 -> 22 | K9: =J9+1 -> 23 | L9: =K9+1 -> 24 | M9: =L9+1 -> 25 | N9: =M9+1 -> 26 | O9: =N9+1 -> 27 | P9: =O9+1 -> 28 | Q9: =P9+1 -> 29 | S9: Notes:
B11: 1 | D11: Assumptions | R11: Notes:
D13: Tax Rate | E13: % | F13: 0.21 | G13: US Marginal Tax Rate
D14: Weighted ERP | E14: % | F14: 0.09 | G14: US Market ERP 5% (Kroll) + Size Premium 4% (Damodaran)
D15: Relevered Beta | E15: x | F15: =Comps!I23 -> 2.1920846 | G15: Relevered the Unlevered beta taken from the average of competitors
D17: US 10Y Treasury Yield | E17: % | F17: 0.041
D19: Unit | E19: USD | F19: 1000000
D21: LTM Total Interest Expense (Average of Forecasted) | F21: =AVERAGE('3FS'!J33:N33) -> -15.306086
D22: Interest Coverage Ratio | F22: =-F21/(AVERAGE(M42:Q42)) -> 0.034754711
D23: Credit Rating | F23: ='Synthetic Rating'!C19 -> D2/D | G23: Average of Forecasted Interest Expense / Average of Forecasted EBIT
D24: Synthetic Credit Spread | E24: % | F24: ='Synthetic Rating'!D19 -> 0.19
D26: Total Cash | F26: =$F$19*'3FS'!I48 -> 74292000
D27: Total Debt | E27: USD | F27: =$F$19*('3FS'!I80+'3FS'!I73+'3FS'!I81+'3FS'!I74+'3FS'!I94) -> 809187000
D28: NOSH | E28: x | F28: 279200000
D29: Last Closed Share Price | E29: USD | F29: 15.29
D30: Shareholder's Equity | E30: USD | F30: =F28*F29 -> 4268968000 | G30: Share Price as of 7th Nov, 2025
D31: Debt + Equity | F31: =F30+F27 -> 5078155000
D33: Cost of Debt | E33: % | F33: =F17+F24*(1-F13) -> 0.1911
D34: Cost of Equity | E34: % | F34: =F15*F14+F17 -> 0.23828761
D35: WACC | E35: % | F35: =F27/F31*F33+F30/F31*F34 -> 0.23076842
D36: Valuation Date | F36: =TODAY() -> 45990
B38: 2 | D38: 3FS
D40: Depreciation & Amortization | H40: ='3FS'!E107 -> 1.558 | I40: ='3FS'!F107 -> 3.537 | J40: ='3FS'!G107 -> 7.679 | K40: ='3FS'!H107 -> 10.731 | L40: ='3FS'!I107 -> 9.082 | M40: ='3FS'!J107 -> 17.06406 | N40: ='3FS'!K107 -> 33.537227 | O40: ='3FS'!L107 -> 66.134868 | ... Q40: ='3FS'!N107 -> 227.47523
D42: EBIT | H42: ='3FS'!E26 -> -37.417 | I42: ='3FS'!F26 -> -104.306 | J42: ='3FS'!G26 -> -214.412 | K42: ='3FS'!H26 -> -145.778 | L42: ='3FS'!I26 -> -166.066 | M42: ='3FS'!J26 -> -17.494326 | N42: ='3FS'!K26 -> 30.789524 | O42: ='3FS'!L26 -> 295.41917 | ... Q42: ='3FS'!N26 -> 1170.1077
D44: CapEx | H44: =-PPE!H29 -> -3.605 | I44: =-PPE!I29 -> -15.589 | J44: =-PPE!J29 -> -20.072 | K44: =-PPE!K29 -> -29.323 | L44: =-PPE!L29 -> -33.152 | M44: =-PPE!M29 -> -46.628408 | N44: =-PPE!N29 -> -91.642169 | O44: =-PPE!O29 -> -180.71687 | ... Q44: =-PPE!Q29 -> -621.58758
D46: Net Change in Working Capital | I46: =I48-H48 -> -1.127 | J46: =J48-I48 -> -118.084 | K46: =K48-J48 -> 66.89 | L46: =L48-K48 -> 53.476 | M46: =M48-L48 -> -703.28892 | N46: =N48-M48 -> 434.29871 | O46: =O48-N48 -> 1279.0199 | P46: =P48-O48 -> 2131.1568 | Q46: =Q48-P48 -> 2936.1048
D48: Net Working Capital | H48: ='3FS'!E56-'3FS'!E77 -> 113.782 | I48: ='3FS'!F56-'3FS'!F77 -> 112.655 | J48: ='3FS'!G56-'3FS'!G77 -> -5.429 | K48: ='3FS'!H56-'3FS'!H77 -> 61.461 | L48: ='3FS'!I56-'3FS'!I77 -> 114.937 | M48: ='3FS'!J56-'3FS'!J77 -> -588.35192 | N48: ='3FS'!K56-'3FS'!K77 -> -154.05322 | O48: ='3FS'!L56-'3FS'!L77 -> 1124.9666 | ... Q48: ='3FS'!N56-'3FS'!N77 -> 6192.2282
B50: 3 | D50: DCF
D52: NOPAT | H52: =H42*(1-$F$13) -> -29.55943 | I52: =I42*(1-$F$13) -> -82.40174 | J52: =J42*(1-$F$13) -> -169.38548 | K52: =K42*(1-$F$13) -> -115.16462 | L52: =L42*(1-$F$13) -> -131.19214 | M52: =M42*(1-$F$13) -> -13.820518 | N52: =N42*(1-$F$13) -> 24.323724 | O52: =O42*(1-$F$13) -> 233.38115 | ... Q52: =Q42*(1-$F$13) -> 924.38511
D53: (+) D&A | H53: =H40 -> 1.558 | I53: =I40 -> 3.537 | J53: =J40 -> 7.679 | K53: =K40 -> 10.731 | L53: =L40 -> 9.082 | M53: =M40 -> 17.06406 | N53: =N40 -> 33.537227 | O53: =O40 -> 66.134868 | ... Q53: =Q40 -> 227.47523
D54: (-) CapEx | H54: =H44 -> -3.605 | I54: =I44 -> -15.589 | J54: =J44 -> -20.072 | K54: =K44 -> -29.323 | L54: =L44 -> -33.152 | M54: =M44 -> -46.628408 | N54: =N44 -> -91.642169 | O54: =O44 -> -180.71687 | ... Q54: =Q44 -> -621.58758
D55: (-) Net Change in Working Capital | H55: =H46 -> 0 | I55: =I46 -> -1.127 | J55: =J46 -> -118.084 | K55: =K46 -> 66.89 | L55: =L46 -> 53.476 | M55: =M46 -> -703.28892 | N55: =N46 -> 434.29871 | O55: =O46 -> 1279.0199 | ... Q55: =Q46 -> 2936.1048
D56: Unlevered Free Cash Flow (FCFF) | H56: =SUM(H52:H55) -> -31.60643 | I56: =SUM(I52:I55) -> -95.58074 | J56: =SUM(J52:J55) -> -299.86248 | K56: =SUM(K52:K55) -> -66.86662 | L56: =SUM(L52:L55) -> -101.78614 | M56: =SUM(M52:M55) -> -746.67379 | N56: =SUM(N52:N55) -> 400.51749 | O56: =SUM(O52:O55) -> 1397.819 | ... Q56: =SUM(Q52:Q55) -> 3466.3776
D58: Discount Factor | M58: =(1+$F$35)^(M9-$L$9) -> 1.2307684 | N58: =(1+$F$35)^(N9-$L$9) -> 1.5147909 | O58: =(1+$F$35)^(O9-$L$9) -> 1.8643568 | P58: =(1+$F$35)^(P9-$L$9) -> 2.2945915 | Q58: =(1+$F$35)^(Q9-$L$9) -> 2.8241108
D59: Present Value of FCFE | M59: =M56/M58 -> -606.67285 | N59: =N56/N58 -> 264.40447 | O59: =O56/O58 -> 749.75937 | P59: =P56/P58 -> 1085.3176 | Q59: =Q56/Q58 -> 1227.4227
B61: 4 | D61: Valuation
D63: DCF
D65: Baseline Terminal Growth Rate | E65: 0.025
D66: 2029 FCF * (1+g) | E66: =Q59*(1+E65)*$F$19 -> 1.2581082e+09
D67: Terminal Value in 2029 | E67: =E66/(F35-E65) -> 6.1141948e+09
D68: PV of Terminal Value | E68: =E67/Q58 -> 2.1649982e+09
D69: PV of Stage 1 Cash Flows | E69: =SUM(M59:Q59)*$F$19 -> 2.7202313e+09
D70: Total Enterprise Value | E70: =E68+E69 -> 4.8852295e+09
D71: (-) Debt | E71: =F27 -> 809187000
D72: (+) Cash | E72: =F26 -> 74292000
D73: Total Equity Value | E73: =E70-E71+E72 -> 4.1503345e+09
D74: Common Shares Outstanding | E74: =F28 -> 279200000
E75: Base Case | F75: Downside | G75: Upside
D76: Implied Share Price | E76: =E73/E74 -> 14.865095 | F76: 5.64 | G76: 28.03
D78: Comparables
D81: Industry EV/Sales | E81: =Comps!H20 -> 3.4
D82: 2029 Sales (Forecasted) | E82: =F19*'3FS'!N13 -> 2.5437125e+09
D83: Terminal Value in 2029 | E83: =E81*E82 -> 8.6486224e+09
D84: PV of Terminal Value | E84: =E83/Q58 -> 3.0624232e+09
D85: PV of Stage 1 Cash Flows | E85: =SUM(M59:Q59)*F19 -> 2.7202313e+09
D86: Total Enterprise Value | E86: =E84+E85 -> 5.7826545e+09
D87: (-) Debt | E87: =F27 -> 809187000
D88: (+) Cash | E88: =F26 -> 74292000
D89: Total Equity Value | E89: =E86-E87+E88 -> 5.0477595e+09
D90: Common Shares Outstanding | E90: =F28 -> 279200000
E91: Base Case | F91: Downside | G91: Upside
D92: Implied Share Price | E92: =E89/E90 -> 18.079368 | F92: 9.59 | G92: 29.39
D94: Total Blended Value | E94: Base Case | F94: Bear Case | G94: Bull Case
E95: =AVERAGE(E76,E92) -> 16.472231 | F95: =AVERAGE(F76,F92) -> 7.615 | G95: =AVERAGE(G76,G92) -> 28.71
B97: 5 | D97: Sensitivity Analysis
F99: Target Share Price - Discounted Cash Flow
E101: WACC | F101: Terminal Growth Rate
E102: =E76 -> 14.865095 | F102: =G102-0.005 -> 0.015 | G102: =H102-0.005 -> 0.02 | H102: =0.025 -> 0.025 | I102: =H102+0.005 -> 0.03 | J102: =I102+0.005 -> 0.035
E103: =E104+0.01 -> 0.2508 | F103: 12.106214 | G103: 12.25843 | H103: 12.417387 | I103: 12.583543 | J103: 12.757399
E104: =E105+0.01 -> 0.2408 | F104: 13.201315 | G104: 13.379919 | H104: 13.566799 | I104: 13.762545 | J104: 13.967802
E105: =23.08% -> 0.2308 | F105: 14.429457 | G105: 14.639991 | H105: 14.860754 | I105: 15.092512 | J105: 15.336106
E106: =E105-0.01 -> 0.2208 | F106: 15.813788 | G106: 16.063202 | H106: 16.325354 | I106: 16.601246 | J106: 16.891986
E107: =E106-0.01 -> 0.2108 | F107: 17.382672 | G107: 17.679761 | H107: 17.992841 | I107: 18.323237 | J107: 18.672427
F109: Target Share Price - Comparables
E111: WACC | F111: EV/Sales Multiple
E112: =E92 -> 18.079368 | F112: =G112-0.5 -> 2.4 | G112: =H112-0.5 -> 2.9 | H112: 3.4 | I112: =H112+0.5 -> 3.9 | J112: =I112+0.5 -> 4.4
E113: =E114+0.01 -> 0.2508 | F113: 13.546595 | G113: 15.034528 | H113: 16.522461 | I113: 18.010393 | J113: 19.498326
E114: =E115+0.01 -> 0.2408 | F114: 14.184012 | G114: 15.732878 | H114: 17.281743 | I114: 18.830608 | J114: 20.379474
E115: =23.08% -> 0.2308 | F115: 14.851164 | G115: 16.463981 | H115: 18.076799 | I115: 19.689616 | J115: 21.302433
E116: =E115-0.01 -> 0.2208 | F116: 15.549708 | G116: 17.229672 | H116: 18.909636 | I116: 20.5896 | J116: 22.269564
E117: =E116-0.01 -> 0.2108 | F117: 16.281408 | G117: 18.031901 | H117: 19.782395 | I117: 21.532889 | J117: 23.283382

Sheet Comps
D2: EOS Energy Enterprises, Inc. (NASDAQ: EOSE)
D4: 12M Target Price
D5: Scenario | G5: =[1]Cover!C11 -> Base Case
D7: In USD Mns, unless stated otherwise | S7: Notes:
B9: 1 | D9: Peer Companies - Unlevered Beta Calculation
D11: Peer Companies | E11: Ticker | F11: Industry | G11: Location | H11: EV/Sales | I11: Levered Beta | J11: Debt | K11: % Debt | L11: Preferred Stock | M11: % Preferred | N11: Equity Value | O11: % Equity | P11: Tax Rate | Q11: Unlevered Beta
D12: Fluence Energy, Inc. | E12: FLNC | F12: Utilities | G12: USA | H12: 0.2 | I12: 2.8 | J12: =390356/10^3 -> 390.356 | K12: =J12/(J12+L12+N12) -> 0.4283996 | L12: 0 | M12: =L12/(J12+L12+N12) -> 0 | N12: 520.84 | O12: =N12/(N12+L12+J12) -> 0.5716004 | P12: 0.21 | Q12: =I12/(1+(1-P12)*(J12+L12)/N12) -> 1.7587007
D13: Solid Power | E13: SLDP | F13: Industrials | G13: USA | H13: 16.1 | I13: 1.85 | J13: 8.8 | K13: =J13/(J13+L13+N13) -> 0.023184129 | L13: 0 | M13: =L13/(J13+L13+N13) -> 0 | N13: 370.77 | O13: =N13/(N13+L13+J13) -> 0.97681587 | P13: 0.21 | Q13: =I13/(1+(1-P13)*(J13+L13)/N13) -> 1.8159506
D14: Plug Power | E14: PLUG | F14: Industrials | G14: USA | H14: 3.4 | I14: 2.24 | J14: =655.56 -> 655.56 | K14: =J14/(J14+L14+N14) -> 0.27139049 | L14: 0 | M14: =L14/(J14+L14+N14) -> 0 | N14: 1760 | O14: =N14/(N14+L14+J14) -> 0.72860951 | P14: 0.21 | Q14: =I14/(1+(1-P14)*(J14+L14)/N14) -> 1.7307227
D15: Microvast | E15: MVST | F15: Industrials | G15: USA | H15: 4.85 | I15: 3.36 | J15: 403.28 | K15: =J15/(J15+L15+N15) -> 0.53434386 | L15: 0 | M15: =L15/(J15+L15+N15) -> 0 | N15: 351.44 | O15: =N15/(N15+L15+J15) -> 0.46565614 | P15: 0.21 | Q15: =I15/(1+(1-P15)*(J15+L15)/N15) -> 1.7623633
D16: FuelCell Energy | E16: FCEL | F16: Industrials | G16: USA | H16: 1.2 | I16: 4.27 | J16: 135 | K16: =J16/(J16+L16+N16) -> 0.17974668 | L16: 59.857 | M16: =L16/(J16+L16+N16) -> 0.079697014 | N16: 556.2 | O16: =N16/(N16+L16+J16) -> 0.74055631 | P16: 0.21 | Q16: =I16/(1+(1-P16)*(J16+L16)/N16) -> 3.3443883
D19: Average | H19: =AVERAGE(H12,H13:H16) -> 5.15 | I19: =AVERAGE(I12:I16) -> 2.904 | J19: =AVERAGE(J12:J16) -> 318.5992 | K19: =AVERAGE(K12:K16) -> 0.28741295 | L19: =AVERAGE(L12:L16) -> 11.9714 | M19: =AVERAGE(M12:M16) -> 0.015939403 | N19: =AVERAGE(N12:N16) -> 711.85 | O19: =AVERAGE(O12:O16) -> 0.69664765 | P19: =AVERAGE(P12:P16) -> 0.21 | Q19: =AVERAGE(Q12:Q16) -> 2.0824251
D20: Median | H20: =MEDIAN(H12:H16) -> 3.4 | I20: =MEDIAN(I12:I16) -> 2.8 | J20: =MEDIAN(J12:J16) -> 390.356 | K20: =MEDIAN(K12:K16) -> 0.27139049 | L20: =MEDIAN(L12:L16) -> 0 | M20: =MEDIAN(M12:M16) -> 0 | N20: =MEDIAN(N12:N16) -> 520.84 | O20: =MEDIAN(O12:O16) -> 0.72860951 | ... Q20: =MEDIAN(Q12:Q16) -> 1.7623633
D22: EOSE Energy Enterprise, Inc - Levered Beta Calculation
D23: EOS Energy Enterprise, Inc | E23: EOSE | F23: Industrials | G23: USA | I23: =Q23*(1+(1-P23)*((J23+L23)/N23)) -> 2.1920846 | J23: =AVERAGE('[1]Debt & Equity'!M13:Q13) -> 22736.573 | K23: =J23/(J23+L23+N23) -> 0.062492018 | M23: =L23/(J23+L23+N23) -> 0 | N23: =AVERAGE('[1]3FS'!J95:N95) -> 341095.06 | O23: =N23/(N23+L23+J23) -> 0.93750798 | P23: 0.21 | Q23: =Q19 -> 2.0824251
G24: DON’T USE Forecasted | I24: =Q24*(1+(1-P24)*((J24+L24)/N24)) -> 1.863524 | J24: =[1]DCF!G24 -> 316.896 | K24: =J24/(J24+L24+N24) -> 0.067737246 | L24: 0 | M24: =L24/(J24+L24+N24) -> 0 | N24: =[1]DCF!G27 -> 4361.4164 | O24: =N24/(N24+L24+J24) -> 0.93226275 | P24: 0.21 | Q24: =Q20 -> 1.7623633 | R24: not sure if we should use forecasted year average total debt and equity or the last actual year

Sheet Balance>

Sheet 3FS
C1: EOS Energy Enterprises, Inc. (NASDAQ: EOSE)
C3: 12M Target Price
C4: Scenario | D4: =[2]Cover!C11 -> Base Case
E5: Historical | J5: Forecasted
C6: In USD Mns, unless stated otherwise | E6: 20 | F6: =E6+1 -> 21 | G6: =F6+1 -> 22 | H6: =G6+1 -> 23 | I6: =H6+1 -> 24 | J6: =I6+1 -> 25 | K6: =J6+1 -> 26 | L6: =K6+1 -> 27 | M6: =L6+1 -> 28 | N6: =M6+1 -> 29
B8: x
C9: Income Statement | E9: FY20A | F9: FY21A | G9: FY22A | H9: FY23A | I9: FY24A | J9: FY25E | K9: FY26E | L9: FY27E | M9: FY28E | N9: FY29E
C11: Product Revenue | E11: 0.184 | F11: 4.562 | G11: 17.429 | H11: 16.151 | I11: 14.503 | J11: ='Revenue Build'!L12 -> 162.57863 | K11: ='Revenue Build'!M12 -> 715.33459 | L11: ='Revenue Build'!N12 -> 1525.2197 | M11: ='Revenue Build'!O12 -> 2100.2502 | N11: ='Revenue Build'!P12 -> 2363.9281
C12: Service Revenue | E12: 0.035 | F12: 0.036 | G12: 0.495 | H12: 0.227 | I12: 1.103 | J12: ='Revenue Build'!L13 -> 12.36463 | K12: ='Revenue Build'!M13 -> 54.403506 | L12: ='Revenue Build'!N13 -> 115.99789 | M12: ='Revenue Build'!O13 -> 159.73081 | N12: ='Revenue Build'!P13 -> 179.78437
C13: Total Revenue | E13: =SUM(E11:E12) -> 0.219 | F13: =SUM(F11:F12) -> 4.598 | G13: =SUM(G11:G12) -> 17.924 | H13: =SUM(H11:H12) -> 16.378 | I13: =SUM(I11:I12) -> 15.606 | J13: =SUM(J11:J12) -> 174.94326 | K13: =SUM(K11:K12) -> 769.7381 | L13: =SUM(L11:L12) -> 1641.2176 | ... N13: =SUM(N11:N12) -> 2543.7125
C14: %yoy | F14: =(F13-E13)/E13 -> 19.995434 | G14: =(G13-F13)/F13 -> 2.8982166 | H14: =(H13-G13)/G13 -> -0.086253069 | I14: =(I13-H13)/H13 -> -0.047136402 | J14: =(J13-I13)/I13 -> 10.21 | K14: =(K13-J13)/J13 -> 3.39993 | L14: =(L13-K13)/K13 -> 1.1321767 | M14: =(M13-L13)/L13 -> 0.37701484 | N14: =(N13-M13)/M13 -> 0.12554594
C16: Cost of Goods Sold | E16: -5.509 | F16: -46.483 | G16: -153.26 | H16: -89.798 | I16: -98.867 | J16: =Projections!K17 -> -104.96596 | K16: =Projections!L17 -> -442.59941 | L16: =Projections!M17 -> -902.6697 | M16: =Projections!N17 -> -1186.49 | N16: =Projections!O17 -> -1271.8562
C17: Gross Profit | E17: =SUM(E13,E16) -> -5.29 | F17: =SUM(F13,F16) -> -41.885 | G17: =SUM(G13,G16) -> -135.336 | H17: =SUM(H13,H16) -> -73.42 | I17: =SUM(I13,I16) -> -83.261 | J17: =SUM(J13,J16) -> 69.977304 | K17: =SUM(K13,K16) -> 327.13869 | L17: =SUM(L13,L16) -> 738.54793 | ... N17: =SUM(N13,N16) -> 1271.8562
C18: %revenue | E18: =E16/E13 -> -25.155251 | F18: =F16/F13 -> -10.109395 | G18: =G16/G13 -> -8.5505468 | H18: =H16/H13 -> -5.4828428 | I18: =I16/I13 -> -6.3351916 | J18: =J16/J13 -> -0.6 | K18: =K16/K13 -> -0.575 | L18: =L16/L13 -> -0.55 | ... N18: =N16/N13 -> -0.5
C19: Gross Profit Margin | E19: =E17/E13 -> -24.155251 | F19: =F17/F13 -> -9.1093954 | G19: =G17/G13 -> -7.5505468 | H19: =H17/H13 -> -4.4828428 | I19: =I17/I13 -> -5.3351916 | J19: =J17/J13 -> 0.4 | K19: =K17/K13 -> 0.425 | L19: =L17/L13 -> 0.45 | ... N19: =N17/N13 -> 0.5
B21: x | C21: OPERATING ITEMS:
C22: SG&A | E22: -17.621 | F22: -42.998 | G22: -60.623 | H22: -53.65 | I22: -60.047 | J22: =Projections!K27 -> -69.977304 | K22: =Projections!L27 -> -238.61881 | L22: =Projections!M27 -> -361.06788 | M22: =Projections!N27 -> -293.79753 | N22: =Projections!O27 -> -101.7485
C23: R&D | E23: -13.593 | F23: -19.154 | G23: -18.469 | H23: -18.708 | I23: -22.758 | J23: =Projections!K33 -> -17.494326 | K23: =Projections!L33 -> -57.730357 | L23: =Projections!M33 -> -82.060881 | M23: =Projections!N33 -> -56.499526 | N23: =Projections!O33 -> 0 | S23: 477 | T23: 785 | U23: 924 | V23: 843 | W23: 836
C24: Other Operating Expenses | E24: -0.913 | F24: -0.269 | G24: =--0.016 -> 0.016 | H24: 0 | I24: 0 | J24: =Projections!K39 -> 0 | K24: =Projections!L39 -> 0 | L24: =Projections!M39 -> 0 | M24: =Projections!N39 -> 0 | N24: =Projections!O39 -> 0 | S24: - | T24: - | U24: 20 | V24: 26 | W24: 31
C25: Total Operating Expenses | E25: =SUM(E22:E24) -> -32.127 | F25: =SUM(F22:F24) -> -62.421 | G25: =SUM(G22:G24) -> -79.076 | H25: =SUM(H22:H24) -> -72.358 | I25: =SUM(I22:I24) -> -82.805 | J25: =SUM(J22:J24) -> -87.47163 | K25: =SUM(K22:K24) -> -296.34917 | L25: =SUM(L22:L24) -> -443.12876 | ... N25: =SUM(N22:N24) -> -101.7485 | S25: 257 | T25: 356 | U25: 465 | V25: 421 | W25: 410
C26: Operating Income (EBIT) | E26: =E17+E25 -> -37.417 | F26: =F17+F25 -> -104.306 | G26: =G17+G25 -> -214.412 | H26: =H17+H25 -> -145.778 | I26: =I17+I25 -> -166.066 | J26: =J17+J25 -> -17.494326 | K26: =K17+K25 -> 30.789524 | L26: =L17+L25 -> 295.41917 | ... N26: =N17+N25 -> 1170.1077
C27: %revenue | E27: =E26/E13 -> -170.85388 | F27: =F26/F13 -> -22.68508 | G27: =G26/G13 -> -11.962285 | H27: =H26/H13 -> -8.9008426 | I27: =I26/I13 -> -10.641164 | J27: =J26/J13 -> -0.1 | K27: =K26/K13 -> 0.04 | L27: =L26/L13 -> 0.18 | ... N27: =N26/N13 -> 0.46
C29: EBITDA | F29: -101.693 | G29: -207.598 | H29: -136.07 | I29: -158.217 | J29: =J26+J105+J106 -> -0.43026561 | K29: =K26+K105+K106 -> 64.326751 | L29: =L26+L105+L106 -> 361.55404 | M29: =M26+M105+M106 -> 845.6258 | N29: =N26+N105+N106 -> 1397.583
C30: %revenue | E30: =E29/E13 -> 0 | F30: =F29/F13 -> -22.11679 | G30: =G29/G13 -> -11.582125 | H30: =H29/H13 -> -8.3080962 | I30: =I29/I13 -> -10.138216 | J30: =J29/J13 -> -0.0024594581 | K30: =K29/K13 -> 0.08356966 | L30: =L29/L13 -> 0.22029622 | ... N30: =N29/N13 -> 0.54942647
B32: x | C32: NON-OPERATING ITEMS
C33: Net Interest Exp. | E33: -23.821 | F33: -5.201 | G33: -18.813 | H33: -56.236 | I33: -28.217 | J33: ='Debt & Equity'!M64+Projections!K131 -> -21.957854 | K33: ='Debt & Equity'!N64+Projections!L131 -> -21.628993 | L33: ='Debt & Equity'!O64+Projections!M131 -> -5.3630191 | M33: ='Debt & Equity'!P64+Projections!N131 -> -11.036791 | N33: ='Debt & Equity'!Q64+Projections!O131 -> -16.543775
C34: Income/(Loss) from Affiliates | E34: 0.077 | F34: 14.436 | G34: 11.251 | H34: -16.792 | I34: -584.734 | J34: =Projections!K52 -> 0 | K34: =Projections!L52 -> 0 | L34: =Projections!M52 -> 0 | M34: =Projections!N52 -> 0 | N34: =Projections!O52 -> 0
C35: Asset Writedown | E35: - | F35: -0.1 | G35: -6.8 | H35: -7.2 | I35: -9.1 | J35: =Projections!K55 -> 0 | K35: =Projections!L55 -> 0 | L35: =Projections!M55 -> 0 | M35: =Projections!N55 -> 0 | N35: =Projections!O55 -> 0
C36: Other Unusual Items | E36: -9.482 | F36: -29.095 | G36: -0.942 | H36: -3.51 | I36: 102.301 | J36: =Projections!K58 -> 0 | K36: =Projections!L58 -> 0 | L36: =Projections!M58 -> 0 | M36: =Projections!N58 -> 0 | N36: =Projections!O58 -> 0
C37: Earnings Before Taxes | E37: =SUM(E26,E33:E36) -> -70.643 | F37: =SUM(F26,F33:F36) -> -124.266 | G37: =SUM(G26,G33:G36) -> -229.716 | H37: =SUM(H26,H33:H36) -> -229.516 | I37: =SUM(I26,I33:I36) -> -685.816 | J37: =SUM(J26,J33:J36) -> -39.45218 | K37: =SUM(K26,K33:K36) -> 9.1605309 | L37: =SUM(L26,L33:L36) -> 290.05615 | ... N37: =SUM(N26,N33:N36) -> 1153.564
C38: Income Tax Expense | E38: 0 | F38: 0 | G38: 0.051 | H38: 0.031 | I38: 0.021 | J38: =Projections!K65 -> 0.0012080438 | K38: =Projections!L65 -> -0.00028049965 | L38: =Projections!M65 -> -0.0088816523 | M38: =Projections!N65 -> -0.021806578 | N38: =Projections!O65 -> -0.035322657
C39: Minority Interest in Earnings | J39: =Projections!K68 -> 0 | K39: =Projections!L68 -> 0 | L39: =Projections!M68 -> 0 | M39: =Projections!N68 -> 0 | N39: =Projections!O68 -> 0
C40: Net Income/(Loss) | E40: =E37-E38+E39 -> -70.643 | F40: =F37-F38+F39 -> -124.266 | G40: =G37-G38+G39 -> -229.767 | H40: =H37-H38+H39 -> -229.547 | I40: =I37-I38+I39 -> -685.837 | J40: =J37-J38+J39 -> -39.453388 | K40: =K37-K38+K39 -> 9.1608114 | L40: =L37-L38+L39 -> 290.06504 | ... N40: =N37-N38+N39 -> 1153.5993
C41: %revenue
B43: x
C44: Balance Sheet | E44: FY20A | F44: FY21A | G44: FY22A | H44: FY23A | I44: FY24A | J44: FY25E | K44: FY26E | L44: FY27E | M44: FY28E | N44: FY29E
C46: ASSETS:
C47: Current Assets
C48: Cash And Equivalents | E48: 121.853 | F48: 104.831 | G48: 17.076 | H48: 69.473 | I48: 74.292 | J48: =J147 -> 32.036765 | K48: =K147 -> 813.55452 | L48: =L147 -> 3188.699 | M48: =M147 -> 6100.6289 | N48: =N147 -> 9155.6914
C49: Restricted Cash | E49: 0 | F49: 0.861 | G49: 2.725 | H49: 3.439 | I49: 14.07 | J49: =Projections!K190 -> 0 | K49: =Projections!L190 -> 0 | L49: =Projections!M190 -> 0 | M49: =Projections!N190 -> 0 | N49: =Projections!O190 -> 0
C50: Accounts Receivable | E50: 0 | F50: 3.285 | G50: 3.525 | H50: 9.773 | I50: 16.134 | J50: =Projections!K79 -> 34.404987 | K50: =Projections!L79 -> 151.37954 | L50: =Projections!M79 -> 322.76792 | M50: =Projections!N79 -> 443.24185 | N50: =Projections!O79 -> 500.25588
C51: Other Receivables | E51: 0.432 | F51: 1.02 | G51: 0.263 | H51: 10.756 | I51: 2.283 | J51: =Projections!K83 -> 2.5669537 | K51: =Projections!L83 -> 11.294416 | L51: =Projections!M83 -> 24.081691 | M51: =Projections!N83 -> 33.070243 | N51: =Projections!O83 -> 37.324056
C52: Notes Receivable | E52: 0 | F52: 0.103 | G52: 0 | H52: 0 | I52: 21.731 | J52: =Projections!K87 -> 58.649523 | K52: =Projections!L87 -> 258.0538 | L52: =Projections!M87 -> 550.21629 | M52: =Projections!N87 -> 755.58589 | N52: =Projections!O87 -> 852.77663
C53: Inventory | E53: 0.214 | F53: 12.976 | G53: 23.26 | H53: 17.07 | I53: 32.826 | J53: =Projections!K75 -> 4.0886288 | K53: =Projections!L75 -> 17.240111 | L53: =Projections!M75 -> 35.160746 | M53: =Projections!N75 -> 46.089829 | N53: =Projections!O75 -> 49.541283
C54: Prepaid Exp. | E54: 2.274 | F54: 2.595 | G54: 2.289 | H54: 1.082 | I54: 0.938 | J54: =Projections!K91 -> 10.51498 | K54: =Projections!L91 -> 46.265176 | L54: =Projections!M91 -> 98.64553 | M54: =Projections!N91 -> 135.83636 | N54: =Projections!O91 -> 152.89006
C55: Other Current Assets | E55: 2.594 | F55: 16.901 | G55: 6.009 | H55: 10.738 | I55: 17.638 | J55: =Projections!K193 -> 58.649523 | K55: =Projections!L193 -> 258.0538 | L55: =Projections!M193 -> 550.21629 | M55: =Projections!N193 -> 757.65599 | N55: =Projections!O193 -> 852.77663
B56: x | C56: Total Current Assets | E56: =SUM(E48:E55) -> 127.367 | F56: =SUM(F48:F55) -> 142.572 | G56: =SUM(G48:G55) -> 55.147 | H56: =SUM(H48:H55) -> 122.331 | I56: =SUM(I48:I55) -> 179.912 | J56: =SUM(J48:J55) -> 200.91136 | K56: =SUM(K48:K55) -> 1555.8414 | L56: =SUM(L48:L55) -> 4769.7875 | ... N56: =SUM(N48:N55) -> 11601.256
C58: Non Current Assets
C59: Net Property, Plant and Equipment | E59: 5.653 | F59: 16.358 | G59: 31.485 | H59: 41.888 | I59: 48.569 | J59: =PPE!M10 -> 68.43575 | K59: =PPE!N10 -> 127.50239 | L59: =PPE!O10 -> 244.54776 | M59: =PPE!P10 -> 460.98097 | N59: =PPE!Q10 -> 861.03025
C60: Long-term Investments | E60: 3.736 | F60: 0 | G60: 0 | H60: 0 | I60: 0 | J60: =Projections!K198 -> 0 | K60: =Projections!L198 -> 0 | L60: =Projections!M198 -> 0 | M60: =Projections!N198 -> 0 | N60: =Projections!O198 -> 0
C61: Goodwill | E61: 0 | F61: 4.331 | G61: 4.331 | H61: 4.331 | I61: 4.331 | J61: =I61 -> 4.331 | K61: =J61 -> 4.331 | L61: =K61 -> 4.331 | M61: =L61 -> 4.331 | N61: =M61 -> 4.331
C62: Other Intangibles | E62: 0.32 | F62: 0.28 | G62: 0.24 | H62: 0.295 | I62: 0.24 | J62: =Intangibles!M10 -> 0.84480468 | K62: =Intangibles!N10 -> 1.9959872 | L62: =Intangibles!O10 -> 4.0376442 | M62: =Intangibles!P10 -> 5.9273359 | N62: =Intangibles!Q10 -> 6.9727053
C63: Loans Receivable Long-Term | E63: 0.1 | F63: 3.894 | G63: 1.612 | H63: 1.936 | I63: 0.963 | J63: =Projections!K204 -> 0 | K63: =Projections!L204 -> 0 | L63: =Projections!M204 -> 0 | M63: =Projections!N204 -> 0 | N63: =Projections!O204 -> 0
C64: Other Long-Term Assets | E64: 1.088 | F64: 1.74 | G64: 13.973 | H64: 15.711 | I64: 26.303 | J64: =Projections!K207 -> 66.202974 | K64: =Projections!L207 -> 291.28845 | L64: =Projections!M207 -> 621.07844 | M64: =Projections!N207 -> 855.23423 | N64: =Projections!O207 -> 962.60542
C65: Total Non Current Assets | E65: =SUM(E59:E64) -> 10.897 | F65: =SUM(F59:F64) -> 26.603 | G65: =SUM(G59:G64) -> 51.641 | H65: =SUM(H59:H64) -> 64.161 | I65: =SUM(I59:I64) -> 80.406 | J65: =SUM(J59:J64) -> 139.81453 | K65: =SUM(K59:K64) -> 425.11782 | L65: =SUM(L59:L64) -> 873.99484 | ... N65: =SUM(N59:N64) -> 1834.9394
B67: x | C67: Total Assets | E67: =SUM(E65,E56) -> 138.264 | F67: =SUM(F65,F56) -> 169.175 | G67: =SUM(G65,G56) -> 106.788 | H67: =SUM(H65,H56) -> 186.492 | I67: =SUM(I65,I56) -> 260.318 | J67: =SUM(J65,J56) -> 340.72589 | K67: =SUM(K65,K56) -> 1980.9592 | L67: =SUM(L65,L56) -> 5643.7823 | ... N67: =SUM(N65,N56) -> 13436.195
C69: LIABILITIES
C70: Current Liabilities
C71: Accounts Payable | E71: 3.378 | F71: 13.731 | G71: 34.669 | H71: 20.54 | I71: 16.723 | J71: =Projections!K96 -> 187.97843 | K71: =Projections!L96 -> 827.09194 | L71: =Projections!M96 -> 1763.5062 | M71: =Projections!N96 -> 2421.7393 | N71: =Projections!O96 -> 2733.2467
C72: Accrued Exp. | E72: 4.095 | F72: 5.562 | G72: 8.962 | H72: 22.784 | I72: 12.206 | J72: =Projections!K100 -> 87.47163 | K72: =Projections!L100 -> 384.86905 | L72: =Projections!M100 -> 820.60881 | M72: =Projections!N100 -> 1129.9905 | N72: =Projections!O100 -> 1271.8562
C73: Curr. Port. of LT Debt | E73: 0.924 | F73: 6.57 | G73: 5.56 | H73: 3.332 | I73: 2.014 | J73: ='Debt & Equity'!M11 -> 416.87314 | K73: ='Debt & Equity'!N11 -> 76.97381 | L73: ='Debt & Equity'!O11 -> 164.12176 | M73: ='Debt & Equity'!P11 -> 225.9981 | N73: ='Debt & Equity'!Q11 -> 0
C74: Curr. Port. of Leases | E74: 0 | F74: 1.092 | G74: 1.138 | H74: 1.596 | I74: 1.921 | J74: =Projections!K121 -> 2.2010836 | K74: =Projections!L121 -> 4.1148129 | L74: =Projections!M121 -> 7.7970011 | M74: =Projections!N121 -> 14.384742 | N74: =Projections!O121 -> 26.399483
C75: Unearned Revenue, Current | E75: 1.213 | F75: 0.849 | G75: 3.85 | H75: 3.07 | I75: 22.039 | J75: =Projections!K103 -> 32.302485 | K75: =Projections!L103 -> 142.12867 | L75: =Projections!M103 -> 303.04345 | M75: =Projections!N103 -> 417.29532 | N75: =Projections!O103 -> 469.68506
C76: Other Current Liabilities | E76: 3.975 | F76: 2.113 | G76: 6.397 | H76: 9.548 | I76: 10.072 | J76: =Projections!K106 -> 62.436512 | K76: =Projections!L106 -> 274.71628 | L76: =Projections!M106 -> 585.74365 | M76: =Projections!N106 -> 806.5777 | N76: =Projections!O106 -> 907.84025
C77: Total Current Liabilities | E77: =SUM(E71:E76) -> 13.585 | F77: =SUM(F71:F76) -> 29.917 | G77: =SUM(G71:G76) -> 60.576 | H77: =SUM(H71:H76) -> 60.87 | I77: =SUM(I71:I76) -> 64.975 | J77: =SUM(J71:J76) -> 789.26328 | K77: =SUM(K71:K76) -> 1709.8946 | L77: =SUM(L71:L76) -> 3644.8208 | ... N77: =SUM(N71:N76) -> 5409.0277
C79: Non Current Liabilities
C80: Long-Term Debt | E80: 0.427 | F80: 102.644 | G80: 170.271 | H80: 200.527 | I80: 314.882 | J80: ='Debt & Equity'!M12 -> 0 | K80: ='Debt & Equity'!N12 -> 0 | L80: ='Debt & Equity'!O12 -> 0 | M80: ='Debt & Equity'!P12 -> 0 | N80: ='Debt & Equity'!Q12 -> 254.37125
C81: Long-Term Leases | E81: 0 | F81: 3.241 | G81: 4.256 | H81: 3.438 | I81: 1.674 | J81: =Projections!K122 -> 4.4973253 | K81: =Projections!L122 -> 8.4075188 | L81: =Projections!M122 -> 15.931085 | M81: =Projections!N122 -> 29.391371 | N81: =Projections!O122 -> 53.940277
C82: Unearned Revenue, Non-Current | E82: 0 | F82: 0 | G82: 0.956 | H82: 3.54 | I82: 4.31 | J82: =Projections!K212 -> 0 | K82: =Projections!L212 -> 0 | L82: =Projections!M212 -> 0 | M82: =Projections!N212 -> 0 | N82: =Projections!O212 -> 0
C83: Other Non-Current Liabilities | E83: 3.467 | F83: 0.926 | G83: 3.44 | H83: 28.917 | I83: 456.244 | J83: =Projections!K215 -> 33.575363 | K83: =Projections!L215 -> 147.72925 | L83: =Projections!M215 -> 314.98486 | M83: =Projections!N215 -> 433.73883 | N83: =Projections!O215 -> 488.19298
C84: Total Non Current Liabilities | E84: =SUM(E80:E83) -> 3.894 | F84: =SUM(F80:F83) -> 106.811 | G84: =SUM(G80:G83) -> 178.923 | H84: =SUM(H80:H83) -> 236.422 | I84: =SUM(I80:I83) -> 777.11 | J84: =SUM(J80:J83) -> 38.072689 | K84: =SUM(K80:K83) -> 156.13677 | L84: =SUM(L80:L83) -> 330.91595 | ... N84: =SUM(N80:N83) -> 796.5045
C86: Total Liabilities | E86: =E77+E84 -> 17.479 | F86: =F77+F84 -> 136.728 | G86: =G77+G84 -> 239.499 | H86: =H77+H84 -> 297.292 | I86: =I77+I84 -> 842.085 | J86: =J77+J84 -> 827.33597 | K86: =K77+K84 -> 1866.0313 | L86: =L77+L84 -> 3975.7368 | ... N86: =N77+N84 -> 6205.5322
C88: SHAREHOLDERS' EQUITY:
C89: Common Stock | E89: 0.005 | F89: 0.005 | G89: 0.009 | H89: 0.021 | I89: 0.023 | J89: 0 | K89: 0 | L89: 0 | M89: 0 | N89: 0
C90: Additional Paid In Capital | E90: 395.491 | F90: 448.969 | G90: 513.614 | H90: 765.018 | I90: 534.726 | J90: ='Debt & Equity'!M87 -> 669.3593 | K90: ='Debt & Equity'!N87 -> 1261.7364 | L90: ='Debt & Equity'!O87 -> 2524.7891 | M90: ='Debt & Equity'!P87 -> 4264.0313 | N90: ='Debt & Equity'!Q87 -> 6221.6284
C91: Retained Earnings | E91: -292.311 | F91: -416.527 | G91: -646.34 | H91: -875.846 | I91: -1561.716 | J91: ='Debt & Equity'!M72 -> -1601.1694 | K91: ='Debt & Equity'!N72 -> -1592.0086 | L91: ='Debt & Equity'!O72 -> -1301.9435 | M91: ='Debt & Equity'!P72 -> -589.7646 | N91: ='Debt & Equity'!Q72 -> 563.83469
C92: Comprehensive Inc. and Other | E92: 17.6 | F92: 0 | G92: 0.006 | H92: 0.007 | I92: -43.496 | J92: =I92 -> -43.496 | K92: =J92 -> -43.496 | L92: =K92 -> -43.496 | M92: =L92 -> -43.496 | N92: =M92 -> -43.496
C93: Total Common Equity | E93: =SUM(E89:E92) -> 120.785 | F93: =SUM(F89:F92) -> 32.447 | G93: =SUM(G89:G92) -> -132.711 | H93: =SUM(H89:H92) -> -110.8 | I93: =SUM(I89:I92) -> -1070.463 | J93: =SUM(J89:J92) -> -975.30608 | K93: =SUM(K89:K92) -> -373.76816 | L93: =SUM(L89:L92) -> 1179.3495 | ... N93: =SUM(N89:N92) -> 6741.9671
C94: Minority Interest | E94: 0 | F94: 0 | G94: 0 | H94: 0 | I94: 488.696 | J94: =I94 -> 488.696 | K94: =J94 -> 488.696 | L94: =K94 -> 488.696 | M94: =L94 -> 488.696 | N94: =M94 -> 488.696
C95: Total Equity | E95: =SUM(E93,E94) -> 120.785 | F95: =SUM(F93,F94) -> 32.447 | G95: =SUM(G93,G94) -> -132.711 | H95: =SUM(H93,H94) -> -110.8 | I95: =SUM(I93,I94) -> -581.767 | J95: =SUM(J93,J94) -> -486.61008 | K95: =SUM(K93,K94) -> 114.92784 | L95: =SUM(L93,L94) -> 1668.0455 | ... N95: =SUM(N93,N94) -> 7230.6631
C97: Total Liabilities & Shareholders Equity | E97: =SUM(E86,E95) -> 138.264 | F97: =SUM(F86,F95) -> 169.175 | G97: =SUM(G86,G95) -> 106.788 | H97: =SUM(H86,H95) -> 186.492 | I97: =SUM(I86,I95) -> 260.318 | J97: =SUM(J86,J95) -> 340.72589 | K97: =SUM(K86,K95) -> 1980.9592 | L97: =SUM(L86,L95) -> 5643.7823 | ... N97: =SUM(N86,N95) -> 13436.195
C98: Balance Check | E98: =IF(ROUND(ABS(E67-E97),4)=0,"BALANCED",E67-E97) -> BALANCED | F98: =IF(ROUND(ABS(F67-F97),4)=0,"BALANCED",F67-F97) -> BALANCED | G98: =IF(ROUND(ABS(G67-G97),4)=0,"BALANCED",G67-G97) -> BALANCED | H98: =IF(ROUND(ABS(H67-H97),4)=0,"BALANCED",H67-H97) -> BALANCED | I98: =IF(ROUND(ABS(I67-I97),4)=0,"BALANCED",I67-I97) -> BALANCED | J98: =IF(ROUND(ABS(J67-J97),4)=0,"BALANCED",J67-J97) -> BALANCED | K98: =IF(ROUND(ABS(K67-K97),4)=0,"BALANCED",K67-K97) -> BALANCED | L98: =IF(ROUND(ABS(L67-L97),4)=0,"BALANCED",L67-L97) -> BALANCED | ... N98: =IF(ROUND(ABS(N67-N97),4)=0,"BALANCED",N67-N97) -> BALANCED
C101: Statement of Cash Flows | E101: FY20A | F101: FY21A | G101: FY22A | H101: FY23A | I101: FY24A | J101: FY25E | K101: FY26E | L101: FY27E | M101: FY28E | N101: FY29E
C103: CASH FLOWS FROM OPERATING ACTIVITIES:
C104: Net Income | E104: -70.643 | F104: -124.216 | G104: -229.813 | H104: -229.506 | I104: -685.87 | J104: =J40 -> -39.453388 | K104: =K40 -> 9.1608114 | L104: =L40 -> 290.06504 | M104: =M40 -> 712.17894 | N104: =N40 -> 1153.5993
C105: Depreciation | J105: =-PPE!M68 -> 16.806658 | K105: =-PPE!N68 -> 32.575533 | L105: =-PPE!O68 -> 63.671497 | M105: =-PPE!P68 -> 118.11807 | N105: =-PPE!Q68 -> 221.53829
C106: Amortization of Goodwill & Intangibles | J106: =-Intangibles!M47 -> 0.25740234 | K106: =-Intangibles!N47 -> 0.96169477 | L106: =-Intangibles!O47 -> 2.4633707 | M106: =-Intangibles!P47 -> 4.3137983 | N106: =-Intangibles!Q47 -> 5.9369436
C107: Depreciation & Amortization Total | E107: 1.558 | F107: 3.537 | G107: 7.679 | H107: 10.731 | I107: 9.082 | J107: =(SUM(J105:J106)) -> 17.06406 | K107: =(SUM(K105:K106)) -> 33.537227 | L107: =(SUM(L105:L106)) -> 66.134868 | M107: =(SUM(M105:M106)) -> 122.43187 | N107: =(SUM(N105:N106)) -> 227.47523
C108: Stock-Based Compensation | E108: 5.081 | F108: 15.058 | G108: 13.794 | H108: 14.057 | I108: 18.78 | J108: =Projections!K223 -> 134.6333 | K108: =Projections!L223 -> 592.37711 | L108: =Projections!M223 -> 1263.0527 | M108: =Projections!N223 -> 1739.2423 | N108: =Projections!O223 -> 1957.5971
C109: Change in Net Working Capital:
C110: (Increase)/Decrease in in Acc. Receivable | J110: =I50-J50 -> -18.270987 | K110: =J50-K50 -> -116.97455 | L110: =K50-L50 -> -171.38838 | M110: =L50-M50 -> -120.47393 | N110: =M50-N50 -> -57.014034
C111: (Increase)/Decrease in Inventories | J111: =I53-J53 -> 28.737371 | K111: =J53-K53 -> -13.151482 | L111: =K53-L53 -> -17.920636 | M111: =L53-M53 -> -10.929083 | N111: =M53-N53 -> -3.4514535
C112: Increase/(Decrease) in Acc. Payable | J112: =J71-I71 -> 171.25543 | K112: =K71-J71 -> 639.11351 | L112: =L71-K71 -> 936.41422 | M112: =M71-L71 -> 658.23309 | N112: =N71-M71 -> 311.50742
C113: Change in Other Operating Items
C114: Increase/(Decrease) in Other Receivables | J114: =I51-J51 -> -0.28395366 | K114: =J51-K51 -> -8.7274628 | L114: =K51-L51 -> -12.787275 | M114: =L51-M51 -> -8.9885516 | N114: =M51-N51 -> -4.2538131
C115: (Increase)/Decrease in Notes Receivable | J115: =I52-J52 -> -36.918523 | K115: =J52-K52 -> -199.40427 | L115: =K52-L52 -> -292.16249 | M115: =L52-M52 -> -205.36961 | N115: =M52-N52 -> -97.190733
C116: (Increase)/Decrease in Prepaid Expenses | J116: =I54-J54 -> -9.57698 | K116: =J54-K54 -> -35.750196 | L116: =K54-L54 -> -52.380354 | M116: =L54-M54 -> -37.190828 | N116: =M54-N54 -> -17.053703
C117: (Increase)/Decrease in Other Current Assets | J117: =I55-J55 -> -41.011523 | K117: =J55-K55 -> -199.40427 | L117: =K55-L55 -> -292.16249 | M117: =L55-M55 -> -207.4397 | N117: =M55-N55 -> -95.120634
C118: (Increase)/Decrease in Accrued Expenses | J118: =J72-I72 -> 75.26563 | K118: =K72-J72 -> 297.39742 | L118: =L72-K72 -> 435.73977 | M118: =M72-L72 -> 309.3817 | N118: =N72-M72 -> 141.86572
C119: Increase/(Decrease) in Unearned Revenue, Current | J119: =J75-I75 -> 10.263485 | K119: =K75-J75 -> 109.82619 | L119: =L75-K75 -> 160.91477 | M119: =M75-L75 -> 114.25188 | N119: =N75-M75 -> 52.389734
...

Sheet Projections
C1: EOS Energy Enterprises, Inc. (NASDAQ: EOSE)
C3: 12M Target Price
C4: Scenario | D4: =Cover!C11 -> Base Case
F5: Historical | K5: Forecasted
C6: In USD Mns, unless stated otherwise | F6: 20 | G6: =F6+1 -> 21 | H6: =G6+1 -> 22 | I6: =H6+1 -> 23 | J6: =I6+1 -> 24 | K6: =J6+1 -> 25 | L6: =K6+1 -> 26 | M6: =L6+1 -> 27 | N6: =M6+1 -> 28 | O6: =N6+1 -> 29
C7: Fiscal Year End Date
C8: Days | F8: 366 | G8: 365 | H8: 365 | I8: 365 | J8: 366 | K8: 365 | L8: 365 | M8: 365 | N8: 366 | O8: 365
C10: Revenue Build
C12: Total Revenue | F12: ='3FS'!E13 -> 0.219 | G12: ='3FS'!F13 -> 4.598 | H12: ='3FS'!G13 -> 17.924 | I12: ='3FS'!H13 -> 16.378 | J12: ='3FS'!I13 -> 15.606 | K12: ='3FS'!J13 -> 174.94326 | L12: ='3FS'!K13 -> 769.7381 | M12: ='3FS'!L13 -> 1641.2176 | ... O12: ='3FS'!N13 -> 2543.7125
C13: %yoy | G13: =G12/F12-1 -> 19.995434 | H13: =H12/G12-1 -> 2.8982166 | I13: =I12/H12-1 -> -0.086253069 | J13: =J12/I12-1 -> -0.047136402 | K13: =K12/J12-1 -> 10.21 | L13: =L12/K12-1 -> 3.39993 | M13: =M12/L12-1 -> 1.1321767 | N13: =N12/M12-1 -> 0.37701484 | O13: =O12/N12-1 -> 0.12554594
C15: COGS
C17: Cost of Sales | F17: ='3FS'!E16 -> -5.509 | G17: ='3FS'!F16 -> -46.483 | H17: ='3FS'!G16 -> -153.26 | I17: ='3FS'!H16 -> -89.798 | J17: ='3FS'!I16 -> -98.867 | K17: =K18*K$12 -> -104.96596 | L17: =L18*L$12 -> -442.59941 | M17: =M18*M$12 -> -902.6697 | N17: =N18*N$12 -> -1186.49 | O17: =O18*O$12 -> -1271.8562
C18: %Revenue | F18: =F17/F12 -> -25.155251 | G18: =G17/G12 -> -10.109395 | H18: =H17/H12 -> -8.5505468 | I18: =I17/I12 -> -5.4828428 | J18: =J17/J12 -> -6.3351916 | K18: =_xlfn.XLOOKUP($D$4,$C19:$C21,K19:K21) -> -0.6 | L18: =_xlfn.XLOOKUP($D$4,$C19:$C21,L19:L21) -> -0.575 | M18: =_xlfn.XLOOKUP($D$4,$C19:$C21,M19:M21) -> -0.55 | N18: =_xlfn.XLOOKUP($D$4,$C19:$C21,N19:N21) -> -0.525 | O18: =_xlfn.XLOOKUP($D$4,$C19:$C21,O19:O21) -> -0.5
C19: Bull Case | E19: 0.02 | K19: =K20+$E19 -> -0.58 | L19: =L20+$E19 -> -0.555 | M19: =M20+$E19 -> -0.53 | N19: =N20+$E19 -> -0.505 | O19: =O20+$E19 -> -0.48
C20: Base Case | E20: 0.025 | K20: -0.6 | L20: =K18+$E20 -> -0.575 | M20: =L18+$E20 -> -0.55 | N20: =M18+$E20 -> -0.525 | O20: =N18+$E20 -> -0.5
C21: Bear Case | E21: -0.02 | K21: =K20+$E21 -> -0.62 | L21: =L20+$E21 -> -0.595 | M21: =M20+$E21 -> -0.57 | N21: =N20+$E21 -> -0.545 | O21: =O20+$E21 -> -0.52
C23: Operating Expenses
C25: Total Operating Expenses | F25: ='3FS'!E25 -> -32.127 | G25: ='3FS'!F25 -> -62.421 | H25: ='3FS'!G25 -> -79.076 | I25: ='3FS'!H25 -> -72.358 | J25: ='3FS'!I25 -> -82.805 | K25: =SUM(K27,K39,K33) -> -87.47163 | L25: =SUM(L27,L39,L33) -> -296.34917 | M25: =SUM(M27,M39,M33) -> -443.12876 | N25: =SUM(N27,N39,N33) -> -350.29706 | O25: =SUM(O27,O39,O33) -> -101.7485
C27: SG&A | F27: ='3FS'!E22 -> -17.621 | G27: ='3FS'!F22 -> -42.998 | H27: ='3FS'!G22 -> -60.623 | I27: ='3FS'!H22 -> -53.65 | J27: ='3FS'!I22 -> -60.047 | K27: =K28*K$12 -> -69.977304 | L27: =L28*L$12 -> -238.61881 | M27: =M28*M$12 -> -361.06788 | N27: =N28*N$12 -> -293.79753 | O27: =O28*O$12 -> -101.7485
C28: %Revenue | F28: =F27/F12 -> -80.461187 | G28: =G27/G12 -> -9.3514572 | H28: =H27/H12 -> -3.3822249 | I28: =I27/I12 -> -3.2757357 | J28: =J27/J12 -> -3.8476868 | K28: =_xlfn.XLOOKUP($D$4,$C29:$C31,K29:K31) -> -0.4 | L28: =_xlfn.XLOOKUP($D$4,$C29:$C31,L29:L31) -> -0.31 | M28: =_xlfn.XLOOKUP($D$4,$C29:$C31,M29:M31) -> -0.22 | N28: =_xlfn.XLOOKUP($D$4,$C29:$C31,N29:N31) -> -0.13 | O28: =_xlfn.XLOOKUP($D$4,$C29:$C31,O29:O31) -> -0.04
C29: Bull Case | E29: 0.01 | K29: =K30+$E29 -> -0.39 | L29: =L30+$E29 -> -0.3 | M29: =M30+$E29 -> -0.21 | N29: =N30+$E29 -> -0.12 | O29: =O30+$E29 -> -0.03
C30: Base Case | E30: 0.09 | K30: -0.4 | L30: =K28+$E30 -> -0.31 | M30: =L28+$E30 -> -0.22 | N30: =M28+$E30 -> -0.13 | O30: =N28+$E30 -> -0.04
C31: Bear Case | E31: -0.01 | K31: =K30+$E31 -> -0.41 | L31: =L30+$E31 -> -0.32 | M31: =M30+$E31 -> -0.23 | N31: =N30+$E31 -> -0.14 | O31: =O30+$E31 -> -0.05
C33: R&D | F33: ='3FS'!E23 -> -13.593 | G33: ='3FS'!F23 -> -19.154 | H33: ='3FS'!G23 -> -18.469 | I33: ='3FS'!H23 -> -18.708 | J33: ='3FS'!I23 -> -22.758 | K33: =K34*K$12 -> -17.494326 | L33: =L34*L$12 -> -57.730357 | M33: =M34*M$12 -> -82.060881 | N33: =N34*N$12 -> -56.499526 | O33: =O34*O$12 -> 0
C34: %Revenue | F34: =F33/F12 -> -62.068493 | G34: =G33/G12 -> -4.1657242 | H34: =H33/H12 -> -1.0304062 | I34: =I33/I12 -> -1.142264 | J34: =J33/J12 -> -1.4582853 | K34: =_xlfn.XLOOKUP($D$4,$C35:$C37,K35:K37) -> -0.1 | L34: =_xlfn.XLOOKUP($D$4,$C35:$C37,L35:L37) -> -0.075 | M34: =_xlfn.XLOOKUP($D$4,$C35:$C37,M35:M37) -> -0.05 | N34: =_xlfn.XLOOKUP($D$4,$C35:$C37,N35:N37) -> -0.025 | O34: =_xlfn.XLOOKUP($D$4,$C35:$C37,O35:O37) -> 0
C35: Bull Case | E35: 0.005 | K35: =K36+$E35 -> -0.095 | L35: =L36+$E35 -> -0.07 | M35: =M36+$E35 -> -0.045 | N35: =N36+$E35 -> -0.02 | O35: =O36+$E35 -> 0.005
C36: Base Case | E36: 0.025 | K36: -0.1 | L36: =K34+$E36 -> -0.075 | M36: =L34+$E36 -> -0.05 | N36: =M34+$E36 -> -0.025 | O36: =N34+$E36 -> 0
C37: Bear Case | E37: -0.005 | K37: =K36+$E37 -> -0.105 | L37: =L36+$E37 -> -0.08 | M37: =M36+$E37 -> -0.055 | N37: =N36+$E37 -> -0.03 | O37: =O36+$E37 -> -0.005
C39: Other Operating Expenses/(Income) | F39: ='3FS'!E24 -> -0.913 | G39: ='3FS'!F24 -> -0.269 | H39: ='3FS'!G24 -> 0.016 | I39: ='3FS'!H24 -> 0 | J39: ='3FS'!I24 -> 0 | K39: =K40*K$12 -> 0 | L39: =L40*L$12 -> 0 | M39: =M40*M$12 -> 0 | N39: =N40*N$12 -> 0 | O39: =O40*O$12 -> 0
C40: %Revenue | F40: =F39/F12 -> -4.1689498 | G40: =G39/G12 -> -0.058503697 | H40: =H39/H12 -> 0.00089265789 | I40: 0 | J40: 0 | K40: =_xlfn.XLOOKUP($D$4,$C41:$C43,K41:K43) -> 0 | L40: =_xlfn.XLOOKUP($D$4,$C41:$C43,L41:L43) -> 0 | M40: =_xlfn.XLOOKUP($D$4,$C41:$C43,M41:M43) -> 0 | N40: =_xlfn.XLOOKUP($D$4,$C41:$C43,N41:N43) -> 0 | O40: =_xlfn.XLOOKUP($D$4,$C41:$C43,O41:O43) -> 0
C41: Bull Case | E41: 0.01 | K41: =K42+$E$41 -> 0.01 | L41: =L42+$E$41 -> 0.01 | M41: =M42+$E$41 -> 0.01 | N41: =N42+$E$41 -> 0.01 | O41: =O42+$E$41 -> 0.01
C42: Base Case | E42: 0 | K42: =MEDIAN($F$40:$J$40) -> 0 | L42: =K42 -> 0 | M42: =L42 -> 0 | N42: =M42 -> 0 | O42: =N42 -> 0
C43: Bear Case | E43: -0.01 | K43: =K42+$E$43 -> -0.01 | L43: =L42+$E$43 -> -0.01 | M43: =M42+$E$43 -> -0.01 | N43: =N42+$E$43 -> -0.01 | O43: =O42+$E$43 -> -0.01
C45: Non-Operating Expenses
C47: Before Tax Items
C49: Net Interest Expense | F49: ='3FS'!E33 -> -23.821 | G49: ='3FS'!F33 -> -5.201 | H49: ='3FS'!G33 -> -18.813 | I49: ='3FS'!H33 -> -56.236 | J49: ='3FS'!I33 -> -28.217 | K49: =K50*K12 -> -316.31257 | L49: =L50*L12 -> -1391.7532 | M49: =M50*M12 -> -2967.4637 | N49: =N50*N12 -> -4086.2415 | O49: =O50*O12 -> -4599.2525
C50: %Revenue | F50: =F49/F12 -> -108.77169 | G50: =G49/G12 -> -1.131144 | H50: =H49/H12 -> -1.0495983 | I50: =I49/I12 -> -3.4336305 | J50: =J49/J12 -> -1.8080866 | K50: =MEDIAN(F50:J50) -> -1.8080866 | L50: =MEDIAN(G50:K50) -> -1.8080866 | M50: =MEDIAN(H50:L50) -> -1.8080866 | N50: =MEDIAN(I50:M50) -> -1.8080866 | O50: =MEDIAN(J50:N50) -> -1.8080866
C52: Income/(Loss) from Affiliates | F52: ='3FS'!E34 -> 0.077 | G52: ='3FS'!F34 -> 14.436 | H52: ='3FS'!G34 -> 11.251 | I52: ='3FS'!H34 -> -16.792 | J52: ='3FS'!I34 -> -584.734 | K52: =K53*K12 -> 0 | L52: =L53*L12 -> 0 | M52: =M53*M12 -> 0 | N52: =N53*N12 -> 0 | O52: =O53*O12 -> 0
C53: %Revenue | F53: =F52/F12 -> 0.35159817 | G53: =G52/G12 -> 3.1396259 | H53: =H52/H12 -> 0.62770587 | I53: =I52/I12 -> -1.0252778 | J53: =J52/J12 -> -37.468538 | K53: 0 | L53: =K53 -> 0 | M53: =L53 -> 0 | N53: =M53 -> 0 | O53: =N53 -> 0
C55: Asset Writedown | F55: ='3FS'!E35 -> - | G55: ='3FS'!F35 -> -0.1 | H55: ='3FS'!G35 -> -6.8 | I55: ='3FS'!H35 -> -7.2 | J55: ='3FS'!I35 -> -9.1 | K55: =K56*K18 -> 0 | L55: =L56*L18 -> 0 | M55: =M56*M18 -> 0 | N55: =N56*N18 -> 0 | O55: =O56*O18 -> 0
C56: %Revenue | F56: 0 | G56: 0 | H56: =H55/H12 -> -0.3793796 | I56: 0 | J56: 0 | K56: =MEDIAN($F$56:$J$56) -> 0 | L56: =MEDIAN($F$56:$J$56) -> 0 | M56: =MEDIAN($F$56:$J$56) -> 0 | N56: =MEDIAN($F$56:$J$56) -> 0 | O56: =MEDIAN($F$56:$J$56) -> 0
C58: Other Unusual Items | F58: ='3FS'!E36 -> -9.482 | G58: ='3FS'!F36 -> -29.095 | H58: ='3FS'!G36 -> -0.942 | I58: ='3FS'!H36 -> -3.51 | J58: ='3FS'!I36 -> 102.301 | K58: =K59*K12 -> 0 | L58: =L59*L12 -> 0 | M58: =M59*M12 -> 0 | N58: =N59*N12 -> 0 | O58: =O59*O12 -> 0
C59: %Revenue | F59: =F58/F12 -> -43.296804 | G59: =G58/G12 -> -6.3277512 | H59: =H58/H12 -> -0.052555233 | I59: =I58/I12 -> -0.21431188 | J59: 0 | K59: 0 | L59: =K59 -> 0 | M59: =L59 -> 0 | N59: =M59 -> 0 | O59: =N59 -> 0
C61: After Tax Items
C63: Earnings before Taxes | F63: ='3FS'!E37 -> -70.643 | G63: ='3FS'!F37 -> -124.266 | H63: ='3FS'!G37 -> -229.716 | I63: ='3FS'!H37 -> -229.516 | J63: ='3FS'!I37 -> -685.816 | K63: ='3FS'!J37 -> -39.45218 | L63: ='3FS'!K37 -> 9.1605309 | M63: ='3FS'!L37 -> 290.05615 | ... O63: ='3FS'!N37 -> 1153.564
C65: Provision for Income Tax | F65: ='3FS'!E38 -> 0 | G65: ='3FS'!F38 -> 0 | H65: ='3FS'!G38 -> 0.051 | I65: ='3FS'!H38 -> 0.031 | J65: ='3FS'!I38 -> 0.021 | K65: =K66*K63 -> 0.0012080438 | L65: =L66*L63 -> -0.00028049965 | M65: =M66*M63 -> -0.0088816523 | N65: =N66*N63 -> -0.021806578 | O65: =O66*O63 -> -0.035322657
C66: %Effective Tax Rate | F66: =F65/F63 -> 0 | G66: =G65/G63 -> 0 | H66: =H65/H63 -> -0.00022201327 | I66: =I65/I63 -> -0.00013506684 | J66: =J65/J63 -> -3.0620458e-05 | K66: =MEDIAN(F66:J66) -> -3.0620458e-05 | L66: =MEDIAN(G66:K66) -> -3.0620458e-05 | M66: =MEDIAN(H66:L66) -> -3.0620458e-05 | N66: =MEDIAN(I66:M66) -> -3.0620458e-05 | O66: =MEDIAN(J66:N66) -> -3.0620458e-05
C68: Minority Interest (After Tax) | F68: ='3FS'!E39 -> 0 | G68: ='3FS'!F39 -> 0 | H68: ='3FS'!G39 -> 0 | I68: ='3FS'!H39 -> 0 | J68: ='3FS'!I39 -> 0 | K68: =K69*K12 -> 0 | L68: =L69*L12 -> 0 | M68: =M69*M12 -> 0 | N68: =N69*N12 -> 0 | O68: =O69*O12 -> 0
C69: %Revenue | F69: =F68/F12 -> 0 | G69: =G68/G12 -> 0 | H69: =H68/H12 -> 0 | I69: =I68/I12 -> 0 | J69: =J68/J12 -> 0 | K69: =MEDIAN($F$69:$J$69) -> 0 | L69: =MEDIAN($F$69:$J$69) -> 0 | M69: =MEDIAN($F$69:$J$69) -> 0 | N69: =MEDIAN($F$69:$J$69) -> 0 | O69: =MEDIAN($F$69:$J$69) -> 0
C71: Operating Working Capital Items
C73: Current Operating Working Capital Assets
C75: Inventories | F75: ='3FS'!E53 -> 0.214 | G75: ='3FS'!F53 -> 12.976 | H75: ='3FS'!G53 -> 23.26 | I75: ='3FS'!H53 -> 17.07 | J75: ='3FS'!I53 -> 32.826 | K75: =-K17/K76 -> 4.0886288 | L75: =-L17/L76 -> 17.240111 | M75: =-M17/M76 -> 35.160746 | N75: =-N17/N76 -> 46.089829 | O75: =-O17/O76 -> 49.541283
C76: Inventory Turnover Ratio | F76: =-F17/F75 -> 25.742991 | G76: =-G17/G75 -> 3.5822287 | H76: =-H17/H75 -> 6.588994 | I76: =-I17/I75 -> 5.2605741 | J76: =-J17/J75 -> 3.0118504 | K76: =K8/K77 -> 25.672655 | L76: =L8/L77 -> 25.672655 | M76: =M8/M77 -> 25.672655 | N76: =N8/N77 -> 25.742991 | O76: =O8/O77 -> 25.672655
C77: DIO | F77: =F8/F76 -> 14.217462 | G77: =G8/G76 -> 101.89187 | H77: =H8/H76 -> 55.395406 | I77: =I8/I76 -> 69.384062 | J77: =J8/J76 -> 121.51998 | K77: =MIN($F77:$J77) -> 14.217462 | L77: =K77 -> 14.217462 | M77: =L77 -> 14.217462 | N77: =M77 -> 14.217462 | O77: =N77 -> 14.217462
C79: Accounts Receivables | F79: ='3FS'!E50 -> 0 | G79: ='3FS'!F50 -> 3.285 | H79: ='3FS'!G50 -> 3.525 | I79: ='3FS'!H50 -> 9.773 | J79: ='3FS'!I50 -> 16.134 | K79: =K12/K80 -> 34.404987 | L79: =L12/L80 -> 151.37954 | M79: =M12/M80 -> 322.76792 | N79: =N12/N80 -> 443.24185 | O79: =O12/O80 -> 500.25588
C80: Receivables Turnover Ratio | G80: =G12/G79 -> 1.3996956 | H80: =H12/H79 -> 5.0848227 | I80: =I12/I79 -> 1.6758416 | J80: =J12/J79 -> 0.96727408 | K80: =K8/K81 -> 5.0848227 | L80: =L8/L81 -> 5.0848227 | M80: =M8/M81 -> 5.0848227 | N80: =N8/N81 -> 5.0987537 | O80: =O8/O81 -> 5.0848227
C81: DSO | G81: =G8/G80 -> 260.77099 | H81: =H8/H80 -> 71.782247 | I81: =I8/I80 -> 217.80101 | J81: =J8/J80 -> 378.38293 | K81: =MIN($F81:$J81) -> 71.782247 | L81: =K81 -> 71.782247 | M81: =L81 -> 71.782247 | N81: =M81 -> 71.782247 | O81: =N81 -> 71.782247
C83: Other Receivables | F83: ='3FS'!E51 -> 0.432 | G83: ='3FS'!F51 -> 1.02 | H83: ='3FS'!G51 -> 0.263 | I83: ='3FS'!H51 -> 10.756 | J83: ='3FS'!I51 -> 2.283 | K83: =K12/K84 -> 2.5669537 | L83: =L12/L84 -> 11.294416 | M83: =M12/M84 -> 24.081691 | N83: =N12/N84 -> 33.070243 | O83: =O12/O84 -> 37.324056
C84: Receivables Turnover Ratio | F84: =F12/F83 -> 0.50694444 | G84: =G12/G83 -> 4.5078431 | H84: =H12/H83 -> 68.152091 | I84: =I12/I83 -> 1.522685 | J84: =J12/J83 -> 6.8357424 | K84: =K8/K85 -> 68.152091 | L84: =L8/L85 -> 68.152091 | M84: =M8/M85 -> 68.152091 | N84: =N8/N85 -> 68.338809 | O84: =O8/O85 -> 68.152091
C85: DSO | F85: =F8/F84 -> 721.9726 | G85: =G8/G84 -> 80.969987 | H85: =H8/H84 -> 5.3556684 | I85: =I8/I84 -> 239.70815 | J85: =J8/J84 -> 53.542099 | K85: =MIN($F85:$J85) -> 5.3556684 | L85: =K85 -> 5.3556684 | M85: =L85 -> 5.3556684 | N85: =M85 -> 5.3556684 | O85: =N85 -> 5.3556684
C87: Notes Receivable | F87: ='3FS'!E55 -> 2.594 | G87: ='3FS'!F55 -> 16.901 | H87: ='3FS'!G55 -> 6.009 | I87: ='3FS'!H55 -> 10.738 | J87: ='3FS'!I55 -> 17.638 | K87: =K12/K88 -> 58.649523 | L87: =L12/L88 -> 258.0538 | M87: =M12/M88 -> 550.21629 | N87: =N12/N88 -> 755.58589 | O87: =O12/O88 -> 852.77663
C88: Receivables Turnover Ratio | F88: =F12/F87 -> 0.084425598 | G88: =G12/G87 -> 0.27205491 | H88: =H12/H87 -> 2.982859 | I88: =I12/I87 -> 1.5252375 | J88: =J12/J87 -> 0.88479419 | K88: =K8/K89 -> 2.982859 | L88: =L8/L89 -> 2.982859 | M88: =M8/M89 -> 2.982859 | N88: =N8/N89 -> 2.9910313 | O88: =O8/O89 -> 2.982859
C89: DSO | F89: =F8/F88 -> 4335.1781 | G89: =G8/G88 -> 1341.6409 | H89: =H8/H88 -> 122.36582 | I89: =I8/I88 -> 239.307 | J89: =J8/J88 -> 413.65552 | K89: =MIN($F89:$J89) -> 122.36582 | L89: =K89 -> 122.36582 | M89: =L89 -> 122.36582 | N89: =M89 -> 122.36582 | O89: =N89 -> 122.36582
C91: Prepaid Expenses | F91: ='3FS'!E54 -> 2.274 | G91: ='3FS'!F54 -> 2.595 | H91: ='3FS'!G54 -> 2.289 | I91: ='3FS'!H54 -> 1.082 | J91: ='3FS'!I54 -> 0.938 | K91: =K92*K12 -> 10.51498 | L91: =L92*L12 -> 46.265176 | M91: =M92*M12 -> 98.64553 | N91: =N92*N12 -> 135.83636 | O91: =O92*O12 -> 152.89006
C92: %Revenue | F92: =F91/F$12 -> 10.383562 | G92: =G91/G$12 -> 0.56437582 | H92: =H91/H$12 -> 0.12770587 | I92: =I91/I$12 -> 0.066064233 | J92: =J91/J$12 -> 0.060105088 | K92: =MIN($F92:$J92) -> 0.060105088 | L92: =K92 -> 0.060105088 | M92: =L92 -> 0.060105088 | N92: =M92 -> 0.060105088 | O92: =N92 -> 0.060105088
C94: Current Operating Working Capital Liabilities
C96: Accounts Payable | F96: ='3FS'!E71 -> 3.378 | G96: ='3FS'!F71 -> 13.731 | H96: ='3FS'!G71 -> 34.669 | I96: ='3FS'!H71 -> 20.54 | J96: ='3FS'!I71 -> 16.723 | K96: =K12/K97 -> 187.97843 | L96: =L12/L97 -> 827.09194 | M96: =M12/M97 -> 1763.5062 | N96: =N12/N97 -> 2421.7393 | O96: =O12/O97 -> 2733.2467
C97: Payable Turnover Ratio | F97: =F12/F96 -> 0.064831261 | G97: =G12/G96 -> 0.33486272 | H97: =H12/H96 -> 0.51700366 | I97: =I12/I96 -> 0.79737098 | J97: =J12/J96 -> 0.93320576 | K97: =K8/K98 -> 0.93065602 | L97: =L8/L98 -> 0.93065602 | M97: =M8/M98 -> 0.93065602 | N97: =N8/N98 -> 0.93320576 | O97: =O8/O98 -> 0.93065602
C98: DPO | F98: =F8/F97 -> 5645.4247 | G98: =G8/G97 -> 1089.9989 | H98: =H8/H97 -> 705.99113 | I98: =I8/I97 -> 457.7543 | J98: =J8/J97 -> 392.19646 | K98: =MIN($F98:$J98) -> 392.19646 | L98: =K98 -> 392.19646 | M98: =L98 -> 392.19646 | N98: =M98 -> 392.19646 | O98: =N98 -> 392.19646
C100: Accrued Expenses | F100: ='3FS'!E72 -> 4.095 | G100: ='3FS'!F72 -> 5.562 | H100: ='3FS'!G72 -> 8.962 | I100: ='3FS'!H72 -> 22.784 | J100: ='3FS'!I72 -> 12.206 | K100: =K101*K$12 -> 87.47163 | L100: =L101*L$12 -> 384.86905 | M100: =M101*M$12 -> 820.60881 | N100: =N101*N$12 -> 1129.9905 | O100: =O101*O$12 -> 1271.8562
C101: %Revenue | F101: =F100/F$12 -> 18.69863 | G101: =G100/G$12 -> 1.2096564 | H101: =H100/H$12 -> 0.5 | I101: =I100/I$12 -> 1.3911344 | J101: =J100/J$12 -> 0.78213508 | K101: =MIN(F101:J101) -> 0.5 | L101: =K101 -> 0.5 | M101: =L101 -> 0.5 | N101: =M101 -> 0.5 | O101: =N101 -> 0.5
C103: Unearned Revenue, Current | F103: ='3FS'!E75 -> 1.213 | G103: ='3FS'!F75 -> 0.849 | H103: ='3FS'!G75 -> 3.85 | I103: ='3FS'!H75 -> 3.07 | J103: ='3FS'!I75 -> 22.039 | K103: =K104*K$12 -> 32.302485 | L103: =L104*L$12 -> 142.12867 | M103: =M104*M$12 -> 303.04345 | N103: =N104*N$12 -> 417.29532 | O103: =O104*O$12 -> 469.68506
C104: %Revenue | F104: =F103/F$12 -> 5.5388128 | G104: =G103/G$12 -> 0.1846455 | H104: =H103/H$12 -> 0.2147958 | I104: =I103/I$12 -> 0.18744657 | J104: =J103/J$12 -> 1.4122133 | K104: =MIN(F104:J104) -> 0.1846455 | L104: =K104 -> 0.1846455 | M104: =L104 -> 0.1846455 | N104: =M104 -> 0.1846455 | O104: =N104 -> 0.1846455
C106: Other Current Liabilities | F106: ='3FS'!E76 -> 3.975 | G106: ='3FS'!F76 -> 2.113 | H106: ='3FS'!G76 -> 6.397 | I106: ='3FS'!H76 -> 9.548 | J106: ='3FS'!I76 -> 10.072 | K106: =K107*K$12 -> 62.436512 | L106: =L107*L$12 -> 274.71628 | M106: =M107*M$12 -> 585.74365 | N106: =N107*N$12 -> 806.5777 | O106: =O107*O$12 -> 907.84025
C107: %Revenue | F107: =F106/F$12 -> 18.150685 | G107: =G106/G$12 -> 0.45954763 | H107: =H106/H$12 -> 0.35689578 | I107: =I106/I$12 -> 0.58297716 | J107: =J106/J$12 -> 0.6453928 | K107: =MIN(F107:J107) -> 0.35689578 | L107: =K107 -> 0.35689578 | M107: =L107 -> 0.35689578 | N107: =M107 -> 0.35689578 | O107: =N107 -> 0.35689578
C109: Lease
C111: Finance Lease Liabilities
C113: Assumptions
C115: Weighted-Average Discount Rate (%) | D115: 0.05
D116: 5
C117: Face Value | D117: =J123 -> 3.595
C118: Existing Lease Payments | D118: =PMT(D115,D167,D117,0) -> -0.8303544
C120: Finance Lease Liabilities:
C121: Current Portion of Finance Leases, Existing | F121: ='3FS'!E74 -> 0 | G121: ='3FS'!F74 -> 1.092 | H121: ='3FS'!G74 -> 1.138 | I121: ='3FS'!H74 -> 1.596 | J121: ='3FS'!I74 -> 1.921 | K121: =K127*K123 -> 2.2010836 | L121: =L127*L123 -> 4.1148129 | M121: =M127*M123 -> 7.7970011 | N121: =N127*N123 -> 14.384742 | O121: =O127*O123 -> 26.399483
C122: Long-Term Finance Leases, Existing | F122: ='3FS'!E81 -> 0 | G122: ='3FS'!F81 -> 3.241 | H122: ='3FS'!G81 -> 4.256 | I122: ='3FS'!H81 -> 3.438 | J122: ='3FS'!I81 -> 1.674 | K122: =K128*K123 -> 4.4973253 | L122: =L128*L123 -> 8.4075188 | M122: =M128*M123 -> 15.931085 | N122: =N128*N123 -> 29.391371 | O122: =O128*O123 -> 53.940277
C123: Total Finance Lease Liabiltiies | F123: =SUM(F121:F122) -> 0 | G123: =SUM(G121:G122) -> 4.333 | H123: =SUM(H121:H122) -> 5.394 | I123: =SUM(I121:I122) -> 5.034 | J123: =SUM(J121:J122) -> 3.595 | K123: =SUM(K140,K147) -> 6.6984089 | L123: =SUM(L140,L147) -> 12.522332 | M123: =SUM(M140,M147) -> 23.728086 | N123: =SUM(N140,N147) -> 43.776114 | O123: =SUM(O140,O147) -> 80.339759
C124: %yoy | H124: =H123/G123-1 -> 0.24486499 | I124: =I123/H123-1 -> -0.066740823 | J124: =J123/I123-1 -> -0.28585618 | K124: =K123/J123-1 -> 0.863257 | L124: =L123/K123-1 -> 0.86944867 | M124: =M123/L123-1 -> 0.89486165 | N124: =N123/M123-1 -> 0.84490707 | O124: =O123/N123-1 -> 0.83524193
C126: %Breakdown
C127: %Current Portion of Leases | G127: =G121/G$123 -> 0.25201939 | H127: =H121/H$123 -> 0.21097516 | I127: =I121/I$123 -> 0.3170441 | J127: =J121/J$123 -> 0.53435327 | K127: =AVERAGE(F127:J127) -> 0.32859798 | L127: =K127 -> 0.32859798 | M127: =L127 -> 0.32859798 | N127: =M127 -> 0.32859798 | O127: =N127 -> 0.32859798
C128: %Long-Term Leases | G128: =G122/G$123 -> 0.74798061 | H128: =H122/H$123 -> 0.78902484 | I128: =I122/I$123 -> 0.6829559 | J128: =J122/J$123 -> 0.46564673 | K128: =AVERAGE(F128:J128) -> 0.67140202 | L128: =K128 -> 0.67140202 | M128: =L128 -> 0.67140202 | N128: =M128 -> 0.67140202 | O128: =N128 -> 0.67140202
C129: Total | G129: =SUM(G127:G128) -> 1 | H129: =SUM(H127:H128) -> 1 | I129: =SUM(I127:I128) -> 1 | J129: =SUM(J127:J128) -> 1 | K129: =SUM(K127:K128) -> 1 | L129: =SUM(L127:L128) -> 1 | M129: =SUM(M127:M128) -> 1 | N129: =SUM(N127:N128) -> 1 | O129: =SUM(O127:O128) -> 1
C131: Total Interest Payments | K131: =-SUM(K138,K145) -> -0.40892569 | L131: =-SUM(L138,L145) -> -0.78533594 | M131: =-SUM(M138,M145) -> -1.5143286 | N131: =-SUM(N138,N145) -> -2.8307028 | O131: =-SUM(O138,O145) -> -5.2438695
C132: Total Principal Repayments | K132: =K133-K131 -> -1.4801049 | L132: =L133-L131 -> -3.1843872 | M132: =M133-M131 -> -6.5584865 | N132: =N133-N131 -> -12.837943 | O132: =O133-O131 -> -24.537631
C133: Total Finance Lease Repayments | K133: =K139+K146 -> -1.8890306 | L133: =L139+L146 -> -3.9697231 | M133: =M139+M146 -> -8.0728151 | N133: =N139+N146 -> -15.668645 | O133: =O139+O146 -> -29.7815
C134: Total Additions to Finance Lease Liabilities | K134: =SUM(K144) -> 4.5835138 | L134: =SUM(L144) -> 9.0083099 | M134: =SUM(M144) -> 17.764241 | N134: =SUM(N144) -> 32.88597 | O134: =SUM(O144) -> 61.101277
C136: Existing Lease Liabilities
C137: Existing Finance Lease liabilities, BOP | K137: =J123 -> 3.595 | L137: =K140 -> 2.9443956 | M137: =L140 -> 2.261261 | N137: =M140 -> 1.5439696 | O137: =N140 -> 0.79081371
C138: (+) Interest | K138: =K137*$D$115 -> 0.17975 | L138: =L137*$D$115 -> 0.14721978 | M138: =M137*$D$115 -> 0.11306305 | N138: =N137*$D$115 -> 0.077198482 | O138: =O137*$D$115 -> 0.039540686
C139: (-) Lease Payments | K139: =$D$118 -> -0.8303544 | L139: =$D$118 -> -0.8303544 | M139: =$D$118 -> -0.8303544 | N139: =$D$118 -> -0.8303544 | O139: =$D$118 -> -0.8303544
C140: Existing Finance Lease Liabilties, EOP | K140: =SUM(K137:K139) -> 2.9443956 | L140: =SUM(L137:L139) -> 2.261261 | M140: =SUM(M137:M139) -> 1.5439696 | N140: =SUM(N137:N139) -> 0.79081371 | O140: =SUM(O137:O139) -> 0
...

Sheet Drivers>
C118: Adjustments:

Sheet Debt & Equity
C1: EOS Energy Enterprises, Inc. (NASDAQ: EOSE)
C3: 12M Target Price
C4: Scenario | G4: =Cover!C11 -> Base Case
H5: Historical (31 Jan) | M5: Forecast (31 Jan)
C6: In USD Mns, unless stated otherwise | H6: 20 | I6: 21 | J6: 22 | K6: 23 | L6: 24 | M6: 25 | N6: 26 | O6: 27 | P6: 28 | Q6: 29
C7: Fiscal year end date | H7: 44227 | I7: 44592 | J7: 44957 | K7: 45322 | L7: 45688 | M7: 46053 | N7: 46418 | O7: 46783 | P7: 47149 | Q7: 47514
A9: 1 | C9: Debt Schedule | H9: 20 | I9: 21 | J9: 22 | K9: 23 | L9: 24 | M9: 25 | N9: 26 | O9: 27 | P9: 28 | Q9: 29
C11: Financial Debt, Current | H11: ='3FS'!E73 -> 0.924 | I11: ='3FS'!F73 -> 6.57 | J11: ='3FS'!G73 -> 5.56 | K11: ='3FS'!H73 -> 3.332 | L11: ='3FS'!I73 -> 2.014 | M11: =-N17 -> 416.87314 | N11: =-O17 -> 76.97381 | O11: =-P17 -> 164.12176 | P11: =-Q17 -> 225.9981 | Q11: =-R17 -> 0
C12: Financial Debt, Non-Current | H12: ='3FS'!E80 -> 0.427 | I12: ='3FS'!F80 -> 102.644 | J12: ='3FS'!G80 -> 170.271 | K12: ='3FS'!H80 -> 200.527 | L12: ='3FS'!I80 -> 314.882 | M12: =M18-M11 -> 0 | N12: =N18-N11 -> 0 | O12: =O18-O11 -> 0 | P12: =P18-P11 -> 0 | Q12: =Q18-Q11 -> 254.37125
C13: Total Debt | H13: =H11+H12 -> 1.351 | I13: =I11+I12 -> 109.214 | J13: =J11+J12 -> 175.831 | K13: =K11+K12 -> 203.859 | L13: =L11+L12 -> 316.896 | M13: =M11+M12 -> 416.87314 | N13: =N11+N12 -> 76.97381 | O13: =O11+O12 -> 164.12176 | ... Q13: =Q11+Q12 -> 254.37125
C15: Total Debt, BOP | M15: =L13 -> 316.896 | N15: =M13 -> 416.87314 | O15: =N13 -> 76.97381 | P15: =O13 -> 164.12176 | Q15: =P13 -> 225.9981 | R15: =Q13 -> 254.37125
C16: (+) Borrowings | M16: =M38+M40 -> 416.87314 | N16: =N38+N40 -> 76.97381 | O16: =O38+O40 -> 164.12176 | P16: =P38+P40 -> 225.9981 | Q16: =Q38+Q40 -> 254.37125 | R16: =R38+R40 -> 0
C17: (-) Repayments | M17: =M39+M50 -> -316.896 | N17: =N39+N50 -> -416.87314 | O17: =O39+O50 -> -76.97381 | P17: =P39+P50 -> -164.12176 | Q17: =Q39+Q50 -> -225.9981 | R17: =R39+R50 -> 0
C18: Total Debt, EOP | M18: =SUM(M15:M17) -> 416.87314 | N18: =SUM(N15:N17) -> 76.97381 | O18: =SUM(O15:O17) -> 164.12176 | P18: =SUM(P15:P17) -> 225.9981 | Q18: =SUM(Q15:Q17) -> 254.37125 | R18: =SUM(R15:R17) -> 254.37125
C20: Revolver Needs Analysis | H20: 20 | I20: 21 | J20: 22 | K20: 23 | L20: 24 | M20: 25 | N20: 26 | O20: 27 | P20: 28 | Q20: 29
C22: CIRCULARITY | F22: off
C24: Revenue | H24: ='3FS'!E13 -> 0.219 | I24: ='3FS'!F13 -> 4.598 | J24: ='3FS'!G13 -> 17.924 | K24: ='3FS'!H13 -> 16.378 | L24: ='3FS'!I13 -> 15.606 | M24: ='3FS'!J13 -> 174.94326 | N24: ='3FS'!K13 -> 769.7381 | O24: ='3FS'!L13 -> 1641.2176 | ... Q24: ='3FS'!N13 -> 2543.7125 | R24: =Q24 -> 2543.7125
C26: Beginning Cash and Equivalents | M26: ='3FS'!I48 -> 74.292 | N26: ='3FS'!J48 -> 32.036765 | O26: ='3FS'!K48 -> 813.55452 | P26: ='3FS'!L48 -> 3188.699 | Q26: ='3FS'!M48 -> 6100.6289 | R26: =Q26 -> 6100.6289
C27: (+) Cash Flow from Operations + Investing | M27: ='3FS'!J125+'3FS'!J132 -> -154.88579 | N27: ='3FS'!K125+'3FS'!K132 -> 1115.5932 | O27: ='3FS'!L125+'3FS'!L132 -> 2276.7908 | P27: ='3FS'!M125+'3FS'!M132 -> 2830.0055 | Q27: ='3FS'!N125+'3FS'!N132 -> 2990.1257 | R27: =Q27 -> 2990.1257
C28: (-) Debt Principal Repayment | M28: =M50 -> -316.896 | N28: =N50 -> 0 | O28: =O50 -> 0 | P28: =P50 -> 0 | Q28: =Q50 -> 0 | R28: =Q28 -> 0
C29: (-) Mandatory Lease Repayments | M29: =Projections!K133 -> -1.8890306 | N29: =Projections!L133 -> -3.9697231 | O29: =Projections!M133 -> -8.0728151 | P29: =Projections!N133 -> -15.668645 | Q29: =Projections!O133 -> -29.7815 | R29: =Q29 -> -29.7815
C30: (-) Dividends | M30: =-M76 -> 0 | N30: =-N76 -> 0 | O30: =-O76 -> 0 | P30: =-P76 -> 0 | Q30: =-Q76 -> 0 | R30: =Q30 -> 0
C31: (-) Minimum Cash Balance | F31: 0.1 | M31: =-$F$31*'Debt & Equity'!M24 -> -17.494326 | N31: =-$F$31*'Debt & Equity'!N24 -> -76.97381 | O31: =-$F$31*'Debt & Equity'!O24 -> -164.12176 | P31: =-$F$31*'Debt & Equity'!P24 -> -225.9981 | Q31: =-$F$31*'Debt & Equity'!Q24 -> -254.37125 | R31: =Q31 -> -254.37125
C32: Cash Surplus/(Required Fundraise) | M32: =IF($F$22="OFF",SUM(M26:M31),0) -> -416.87314 | N32: =IF($F$22="OFF",SUM(N26:N31),0) -> 1066.6864 | O32: =IF($F$22="OFF",SUM(O26:O31),0) -> 2918.1507 | P32: =IF($F$22="OFF",SUM(P26:P31),0) -> 5777.0378 | Q32: =IF($F$22="OFF",SUM(Q26:Q31),0) -> 8806.6018 | R32: =IF($F$22="OFF",SUM(R26:R31),0) -> 8806.6018
C34: Assumptions:
C35: Discretionary Borrowing as % revenue | G35: 0.1
C37: Credit Revolver, BOP | M37: 0 | N37: =M41 -> 416.87314 | O37: =N41 -> 76.97381 | P37: =O41 -> 164.12176 | Q37: =P41 -> 225.9981
C38: (+) Draw | M38: =-MIN(M32,0) -> 416.87314 | N38: =-MIN(N32,0) -> 0 | O38: =-MIN(O32,0) -> 0 | P38: =-MIN(P32,0) -> 0 | Q38: =-MIN(Q32,0) -> 0
C39: (-) Paydown | M39: =IF(M32>0,-MIN(M37,M32),0) -> 0 | N39: =IF(N32>0,-MIN(N37,N32),0) -> -416.87314 | O39: =IF(O32>0,-MIN(O37,O32),0) -> -76.97381 | P39: =IF(P32>0,-MIN(P37,P32),0) -> -164.12176 | Q39: =IF(Q32>0,-MIN(Q37,Q32),0) -> -225.9981
C40: (+) Discretionary Borrowing | M40: =IF($G$35*M$24<SUM(M37:M39),0,$G$35*M$24-SUM(M37:M39)) -> 0 | N40: =IF($G$35*N$24<SUM(N37:N39),0,$G$35*N$24-SUM(N37:N39)) -> 76.97381 | O40: =IF($G$35*O$24<SUM(O37:O39),0,$G$35*O$24-SUM(O37:O39)) -> 164.12176 | P40: =IF($G$35*P$24<SUM(P37:P39),0,$G$35*P$24-SUM(P37:P39)) -> 225.9981 | Q40: =IF($G$35*Q$24<SUM(Q37:Q39),0,$G$35*Q$24-SUM(Q37:Q39)) -> 254.37125
C41: Credit Revolver, EOP | M41: =SUM(M37:M40) -> 416.87314 | N41: =SUM(N37:N40) -> 76.97381 | O41: =SUM(O37:O40) -> 164.12176 | P41: =SUM(P37:P40) -> 225.9981 | Q41: =SUM(Q37:Q40) -> 254.37125
C43: Repayment Schedule
C45: Principal Repayments
C47: Loans from banks | E47: Principal | F47: Effective Rate | G47: Maturity
C48: Financial Debt | E48: =L13 -> 316.896 | F48: 0.068 | G48: 25 | M48: =IF(M$6=$G$48,-E48,0) -> -316.896 | N48: =IF(N$6=$G$48,-F48,0) -> 0 | O48: =IF(O$6=$G$48,-G48,0) -> 0 | P48: =IF(P$6=$G$48,-H48,0) -> 0 | Q48: =IF(Q$6=$G$48,-I48,0) -> 0 | R48: =IF(R$6=$G$48,-J48,0) -> 0
C50: Total Principal Repayments | M50: =SUM(M48) -> -316.896 | N50: =SUM(N48) -> 0 | O50: =SUM(O48) -> 0 | P50: =SUM(P48) -> 0 | Q50: =SUM(Q48) -> 0 | R50: =SUM(R48) -> 0
C52: Interest Schedule
C54: Loans from banks | E54: Principal | F54: Effective Rate | G54: Maturity
C55: Financial Debt | E55: =L13 -> 316.896 | F55: 0.068 | G55: 25 | M55: =IF(M$6=$G$55,-$E$55*$F$55,0) -> -21.548928 | N55: =IF(N$6=$G$55,-$E$55*$F$55,0) -> 0 | O55: =IF(O$6=$G$55,-$E$55*$F$55,0) -> 0 | P55: =IF(P$6=$G$55,-$E$55*$F$55,0) -> 0 | Q55: =IF(Q$6=$G$55,-$E$55*$F$55,0) -> 0
C57: Credit Revolver | E57: Principal | F57: Interest Rate | G57: Maturity
C58: 25 | E58: {=TRANSPOSE(M41:Q41)} -> 416.87314 | F58: 0.05 | G58: =C58+1 -> 26 | M58: =IF(AND(M$9>=$G58, M$9<=$G58), -$E58*$F58,0) -> 0 | N58: =IF(AND(N$9>=$G58, N$9<=$G58), -$E58*$F58,0) -> -20.843657 | O58: =IF(AND(O$9>=$G58, O$9<=$G58), -$E58*$F58,0) -> 0 | P58: =IF(AND(P$9>=$G58, P$9<=$G58), -$E58*$F58,0) -> 0 | Q58: =IF(AND(Q$9>=$G58, Q$9<=$G58), -$E58*$F58,0) -> 0
C59: 26 | E59: 76.97381 | F59: 0.05 | G59: =C59+1 -> 27 | M59: =IF(AND(M$9>=$G59, M$9<=$G59), -$E59*$F59,0) -> 0 | N59: =IF(AND(N$9>=$G59, N$9<=$G59), -$E59*$F59,0) -> 0 | O59: =IF(AND(O$9>=$G59, O$9<=$G59), -$E59*$F59,0) -> -3.8486905 | P59: =IF(AND(P$9>=$G59, P$9<=$G59), -$E59*$F59,0) -> 0 | Q59: =IF(AND(Q$9>=$G59, Q$9<=$G59), -$E59*$F59,0) -> 0
C60: 27 | E60: 164.12176 | F60: 0.05 | G60: =C60+1 -> 28 | M60: =IF(AND(M$9>=$G60, M$9<=$G60), -$E60*$F60,0) -> 0 | N60: =IF(AND(N$9>=$G60, N$9<=$G60), -$E60*$F60,0) -> 0 | O60: =IF(AND(O$9>=$G60, O$9<=$G60), -$E60*$F60,0) -> 0 | P60: =IF(AND(P$9>=$G60, P$9<=$G60), -$E60*$F60,0) -> -8.2060881 | Q60: =IF(AND(Q$9>=$G60, Q$9<=$G60), -$E60*$F60,0) -> 0
C61: 28 | E61: 225.9981 | F61: 0.05 | G61: =C61+1 -> 29 | M61: =IF(AND(M$9>=$G61, M$9<=$G61), -$E61*$F61,0) -> 0 | N61: =IF(AND(N$9>=$G61, N$9<=$G61), -$E61*$F61,0) -> 0 | O61: =IF(AND(O$9>=$G61, O$9<=$G61), -$E61*$F61,0) -> 0 | P61: =IF(AND(P$9>=$G61, P$9<=$G61), -$E61*$F61,0) -> 0 | Q61: =IF(AND(Q$9>=$G61, Q$9<=$G61), -$E61*$F61,0) -> -11.299905
C62: 29 | E62: 254.37125 | F62: 0.05 | G62: =C62+1 -> 30 | M62: =IF(AND(M$9>=$G62, M$9<=$G62), -$E62*$F62,0) -> 0 | N62: =IF(AND(N$9>=$G62, N$9<=$G62), -$E62*$F62,0) -> 0 | O62: =IF(AND(O$9>=$G62, O$9<=$G62), -$E62*$F62,0) -> 0 | P62: =IF(AND(P$9>=$G62, P$9<=$G62), -$E62*$F62,0) -> 0 | Q62: =IF(AND(Q$9>=$G62, Q$9<=$G62), -$E62*$F62,0) -> 0
C64: Total Interest Expense | M64: =SUM(M55,M58:M62) -> -21.548928 | N64: =SUM(N55,N58:N62) -> -20.843657 | O64: =SUM(O55,O58:O62) -> -3.8486905 | P64: =SUM(P55,P58:P62) -> -8.2060881 | Q64: =SUM(Q55,Q58:Q62) -> -11.299905
A66: 2 | C66: Equity Schedule
C68: Retained Earnings
C69: Retained Earnings BOP | M69: =L72 -> -1561.716 | N69: =M72 -> -1601.1694 | O69: =N72 -> -1592.0086 | P69: =O72 -> -1301.9435 | Q69: =P72 -> -589.7646
C70: (+) Net Income | H70: ='3FS'!E40 -> -70.643 | I70: ='3FS'!F40 -> -124.266 | J70: ='3FS'!G40 -> -229.767 | K70: ='3FS'!H40 -> -229.547 | L70: ='3FS'!I40 -> -685.837 | M70: ='3FS'!J40 -> -39.453388 | N70: ='3FS'!K40 -> 9.1608114 | O70: ='3FS'!L40 -> 290.06504 | ... Q70: ='3FS'!N40 -> 1153.5993
C71: (-) Dividends | M71: =-M76 -> 0 | N71: =-N76 -> 0 | O71: =-O76 -> 0 | P71: =-P76 -> 0 | Q71: =-Q76 -> 0
C72: Retained Earnings (EOP) | H72: ='3FS'!E91 -> -292.311 | I72: ='3FS'!F91 -> -416.527 | J72: ='3FS'!G91 -> -646.34 | K72: ='3FS'!H91 -> -875.846 | L72: ='3FS'!I91 -> -1561.716 | M72: =SUM(M69:M71) -> -1601.1694 | N72: =SUM(N69:N71) -> -1592.0086 | O72: =SUM(O69:O71) -> -1301.9435 | P72: =SUM(P69:P71) -> -589.7646 | Q72: =SUM(Q69:Q71) -> 563.83469
C74: Dividend Schedule
C76: Dividends | M76: =M77*M78 -> 0 | N76: =N77*N78 -> 0 | O76: =O77*O78 -> 0 | P76: =P77*P78 -> 0 | Q76: =Q77*Q78 -> 0
C77: Common Shares (Basic) | H77: 3740 | I77: 3840 | J77: 3930 | K77: 4070 | L77: 4037 | M77: =L77 -> 4037 | N77: =M77 -> 4037 | O77: =N77 -> 4037 | P77: =O77 -> 4037 | Q77: =P77 -> 4037
C78: Dividends Per Share ($) | H78: 0 | I78: 0 | J78: 0 | K78: 0 | L78: 0 | M78: =M79*M80 -> 0 | N78: =N79*N80 -> 0 | O78: =O79*O80 -> 0 | P78: =P79*P80 -> 0 | Q78: =Q79*Q80 -> 0
C79: Earnings Per Share ($) | H79: =H70/H77 -> -0.018888503 | I79: =I70/I77 -> -0.032360937 | J79: =J70/J77 -> -0.058464885 | K79: =K70/K77 -> -0.056399754 | L79: =L70/L77 -> -0.16988779 | M79: =M70/M77 -> -0.0097729472 | N79: =N70/N77 -> 0.0022692126 | O79: =O70/O77 -> 0.071851631 | ... Q79: =Q70/Q77 -> 0.28575657
C80: Payout Ratio | H80: 0 | I80: 0 | J80: 0 | K80: 0 | L80: 0 | M80: =AVERAGE(H80:L80) -> 0 | N80: =M80 -> 0 | O80: =N80 -> 0 | P80: =O80 -> 0 | Q80: =P80 -> 0
C82: Stock Based Compensation
C84: APIC Opening | I84: =H87 -> 395.491 | J84: =I87 -> 448.969 | K84: =J87 -> 513.614 | L84: =K87 -> 765.018 | M84: =L87 -> 534.726 | N84: =M87 -> 669.3593 | O84: =N87 -> 1261.7364 | P84: =O87 -> 2524.7891 | Q84: =P87 -> 4264.0313
C85: SBC Expense | H85: ='3FS'!E108 -> 5.081 | I85: ='3FS'!F108 -> 15.058 | J85: ='3FS'!G108 -> 13.794 | K85: ='3FS'!H108 -> 14.057 | L85: ='3FS'!I108 -> 18.78 | M85: ='3FS'!J108 -> 134.6333 | N85: ='3FS'!K108 -> 592.37711 | O85: ='3FS'!L108 -> 1263.0527 | ... Q85: ='3FS'!N108 -> 1957.5971
C86: Cash Equity Issuance | H86: ='3FS'!E137 -> 0 | I86: ='3FS'!F137 -> 0 | J86: ='3FS'!G137 -> 0 | K86: ='3FS'!H137 -> 0 | L86: ='3FS'!I137 -> 0 | M86: 0 | N86: 0 | O86: 0 | P86: 0 | Q86: 0
C87: APIC Closing | H87: ='3FS'!E90 -> 395.491 | I87: ='3FS'!F90 -> 448.969 | J87: ='3FS'!G90 -> 513.614 | K87: ='3FS'!H90 -> 765.018 | L87: ='3FS'!I90 -> 534.726 | M87: =SUM(M84:M86) -> 669.3593 | N87: =SUM(N84:N86) -> 1261.7364 | O87: =SUM(O84:O86) -> 2524.7891 | P87: =SUM(P84:P86) -> 4264.0313 | Q87: =SUM(Q84:Q86) -> 6221.6284

Sheet PPE
D1: EOS Energy Enterprises, Inc. (NASDAQ: EOSE)
D3: 12M Target Price
D4: Scenario | E4: =Cover!C11 -> Base Case
H5: Historical | M5: Forecasted
D6: In USD Mns, unless stated otherwise | G6: Units | H6: 20 | I6: =H6+1 -> 21 | J6: =I6+1 -> 22 | K6: =J6+1 -> 23 | L6: =K6+1 -> 24 | M6: =L6+1 -> 25 | N6: =M6+1 -> 26 | O6: =N6+1 -> 27 | P6: =O6+1 -> 28 | Q6: =P6+1 -> 29
B8: 1 | D8: PPE
D10: Property, Plant & Equipment | G10: USD Mns | H10: ='3FS'!E59 -> 5.653 | I10: ='3FS'!F59 -> 16.358 | J10: ='3FS'!G59 -> 31.485 | K10: ='3FS'!H59 -> 41.888 | L10: ='3FS'!I59 -> 48.569 | M10: =SUM(M42,M69) -> 68.43575 | N10: =SUM(N42,N69) -> 127.50239 | O10: =SUM(O42,O69) -> 244.54776 | P10: =SUM(P42,P69) -> 460.98097 | Q10: =SUM(Q42,Q69) -> 861.03025
D11: %yoy | G11: % | I11: =I10/H10-1 -> 1.8936848 | J11: =J10/I10-1 -> 0.9247463 | K11: =K10/J10-1 -> 0.33041131 | L11: =L10/K10-1 -> 0.15949675 | M11: =M10/L10-1 -> 0.40904177 | N11: =N10/M10-1 -> 0.86309622 | O11: =O10/N10-1 -> 0.91798574 | P11: =P10/O10-1 -> 0.88503452 | Q11: =Q10/P10-1 -> 0.8678217
B13: x | D13: Assumptions
D15: Useful Life : | E15: Min | F15: Max | G15: Average
D16: ROU Asset | E16: 5 | F16: 5 | G16: =ROUNDUP(AVERAGE(E16:F16),0) -> 5
D17: Equipment | E17: 5 | F17: 10 | G17: =ROUNDUP(AVERAGE(E17:F17),0) -> 8
D18: Finance Lease | E18: 5 | F18: 5 | G18: =ROUNDUP(AVERAGE(E18:F18),0) -> 5
D19: Furniture | E19: 5 | F19: 10 | G19: =ROUNDUP(AVERAGE(E19:F19),0) -> 8
D20: Leasehold Improvements | E20: 0 | F20: 0 | G20: =ROUNDUP(AVERAGE(E20:F20),0) -> 0
D21: Tooling | E21: 2 | F21: 3 | G21: =ROUNDUP(AVERAGE(E21:F21),0) -> 3
D22: Construction In Progress | E22: 0 | F22: 0 | G22: =ROUNDUP(AVERAGE(E22:F22),0) -> 0
D24: Revenue | G24: USD Mns | H24: ='3FS'!E13 -> 0.219 | I24: ='3FS'!F13 -> 4.598 | J24: ='3FS'!G13 -> 17.924 | K24: ='3FS'!H13 -> 16.378 | L24: ='3FS'!I13 -> 15.606 | M24: ='3FS'!J13 -> 174.94326 | N24: ='3FS'!K13 -> 769.7381 | O24: ='3FS'!L13 -> 1641.2176 | ... Q24: ='3FS'!N13 -> 2543.7125
D25: %yoy | G25: % | I25: =I24/H24-1 -> 19.995434 | J25: =J24/I24-1 -> 2.8982166 | K25: =K24/J24-1 -> -0.086253069 | L25: =L24/K24-1 -> -0.047136402 | M25: =M24/L24-1 -> 10.21 | N25: =N24/M24-1 -> 3.39993 | O25: =O24/N24-1 -> 1.1321767 | P25: =P24/O24-1 -> 0.37701484 | Q25: =Q24/P24-1 -> 0.12554594
D27: Depreciation | G27: USD Mns | H27: ='3FS'!E107 -> 1.558 | I27: ='3FS'!F107 -> 3.537 | J27: ='3FS'!G107 -> 7.679 | K27: ='3FS'!H107 -> 10.731 | L27: ='3FS'!I107 -> 9.082 | M27: ='3FS'!J107 -> 17.06406 | N27: ='3FS'!K107 -> 33.537227 | O27: ='3FS'!L107 -> 66.134868 | ... Q27: ='3FS'!N107 -> 227.47523
D29: PPE CapEx | G29: USD Mns | H29: 3.605 | I29: 15.589 | J29: 20.072 | K29: 29.323 | L29: 33.152 | M29: =M27/M30 -> 46.628408 | N29: =N27/N30 -> 91.642169 | O29: =O27/O30 -> 180.71687 | P29: =P27/P30 -> 334.55128 | Q29: =Q27/Q30 -> 621.58758
D30: Depreciation/Capex Ratio | G30: % | H30: =H27/H29 -> 0.43217753 | I30: =I27/I29 -> 0.22689076 | J30: =J27/J29 -> 0.38257274 | K30: =K27/K29 -> 0.36595846 | L30: =L27/L29 -> 0.27395029 | M30: =MEDIAN($H$30:$L$30) -> 0.36595846 | N30: =M30 -> 0.36595846 | O30: =N30 -> 0.36595846 | P30: =O30 -> 0.36595846 | Q30: =P30 -> 0.36595846
B32: x | D32: Capex Schedule and Allocation
D34: COST ALLOCATION:
D35: ROU Asset | H35: 0 | I35: 3.468 | J35: 4.316 | K35: 4.033 | L35: 2.909 | M35: =L35+M45 -> 7.4925138 | N35: =M35+N45 -> 16.500824 | O35: =N35+O45 -> 34.265065 | P35: =O35+P45 -> 67.151035 | Q35: =P35+Q45 -> 128.25231
D36: Equipment | G36: USD Mns | H36: 7.055 | I36: 13.489 | J36: 23.653 | K36: 20.559 | L36: 51.874 | M36: =L36+M46 -> 91.903486 | N36: =M36+N46 -> 170.57632 | O36: =N36+O46 -> 325.71787 | P36: =O36+P46 -> 612.92296 | Q36: =P36+Q46 -> 1146.5425
D37: Finance Lease | G37: USD Mns | H37: 0.201 | I37: 0.226 | J37: 0.379 | K37: 0.504 | L37: 0.504 | M37: =L37+M47 -> 0.74391515 | N37: =M37+N47 -> 1.2154377 | O37: =N37+O47 -> 2.1452725 | P37: =O37+P47 -> 3.8666249 | Q37: =P37+Q47 -> 7.0648529
D38: Furniture | G38: USD Mns | H38: 0.211 | I38: 0.808 | J38: 1.868 | K38: 2.103 | L38: 2.369 | M38: =L38+M48 -> 4.4140125 | N38: =M38+N48 -> 8.4332229 | O38: =N38+O48 -> 16.359041 | P38: =O38+P48 -> 31.031675 | Q38: =P38+Q48 -> 58.293047
D39: Leasehold Improvements | G39: USD Mns | H39: 2.732 | I39: 2.933 | J39: 6.303 | K39: 7.718 | L39: 9.674 | M39: =L39+M50 -> 15.072066 | N39: =M39+N50 -> 25.681274 | O39: =N39+O50 -> 46.602459 | P39: =O39+P50 -> 85.332708 | Q39: =P39+Q50 -> 157.2925
D40: Tooling | H40: 2.732 | I40: 3.053 | J40: 6.926 | K40: 7.045 | L40: 9.955
D41: Construction In Progress | G41: USD Mns | H41: 2.732 | I41: 0 | J41: 0 | K41: 17.958 | L41: 0 | M41: =L41+M51 -> -5.6675857 | N41: =M41+N51 -> -16.8065 | O41: =N41+O51 -> -38.772259 | P41: =O41+P51 -> -79.436269 | Q41: =P41+Q51 -> -154.98894
D42: PPE, gross | G42: USD Mns | H42: =SUM(H35:H41) -> 15.663 | I42: =SUM(I35:I41) -> 23.977 | J42: =SUM(J35:J41) -> 43.445 | K42: =SUM(K35:K41) -> 59.92 | L42: =SUM(L35:L41) -> 77.285 | M42: =SUM(M35:M41) -> 113.95841 | N42: =SUM(N35:N41) -> 205.60058 | O42: =SUM(O35:O41) -> 386.31745 | ... Q42: =SUM(Q35:Q41) -> 1342.4563
D44: PPE NET ADDITIONS:
D45: ROU Asset | I45: =I35-H35 -> 3.468 | J45: =J35-I35 -> 0.848 | K45: =K35-J35 -> -0.283 | L45: =L35-K35 -> -1.124 | M45: =M55*$M$29 -> 4.5835138 | N45: =$N$29*N55 -> 9.0083099 | O45: =$O$29*O55 -> 17.764241 | P45: =P55*$P$29 -> 32.88597 | Q45: =$Q$29*Q55 -> 61.101277
D46: Equipment | G46: USD Mns | I46: =I36-H36 -> 6.434 | J46: =J36-I36 -> 10.164 | K46: =K36-J36 -> -3.094 | L46: =L36-K36 -> 31.315 | M46: =M56*$M$29 -> 40.029486 | N46: =$N$29*N56 -> 78.672833 | O46: =$O$29*O56 -> 155.14155 | P46: =P56*$P$29 -> 287.20509 | Q46: =$Q$29*Q56 -> 533.61958
D47: Finance Lease | G47: USD Mns | I47: =I37-H37 -> 0.025 | J47: =J37-I37 -> 0.153 | K47: =K37-J37 -> 0.125 | L47: =L37-K37 -> 0 | M47: =M57*$M$29 -> 0.23991515 | N47: =$N$29*N57 -> 0.47152253 | O47: =$O$29*O57 -> 0.92983478 | P47: =P57*$P$29 -> 1.7213524 | Q47: =$Q$29*Q57 -> 3.198228
D48: Furniture | G48: USD Mns | I48: =I38-H38 -> 0.597 | J48: =J38-I38 -> 1.06 | K48: =K38-J38 -> 0.235 | L48: =L38-K38 -> 0.266 | M48: =M59*$M$29 -> 2.0450125 | N48: =$N$29*N59 -> 4.0192104 | O48: =$O$29*O59 -> 7.9258177 | P48: =P59*$P$29 -> 14.672634 | Q48: =$Q$29*Q59 -> 27.261372
D49: Leasehold Improvements
D50: Tooling | G50: USD Mns | I50: =I39-H39 -> 0.201 | J50: =J39-I39 -> 3.37 | K50: =K39-J39 -> 1.415 | L50: =L39-K39 -> 1.956 | M50: =M60*$M$29 -> 5.3980658 | N50: =$N$29*N60 -> 10.609208 | O50: =$O$29*O60 -> 20.921185 | P50: =P60*$P$29 -> 38.730249 | Q50: =$Q$29*Q60 -> 71.959795
D51: Construction In Progress | G51: USD Mns | I51: =I41-H41 -> -2.732 | J51: =J41-I41 -> 0 | K51: =K41-J41 -> 17.958 | L51: =L41-K41 -> -17.958 | M51: =M29*M61 -> -5.6675857 | N51: =N29*N61 -> -11.138915 | O51: =O29*O61 -> -21.965759 | P51: =P29*P61 -> -40.664011 | Q51: =Q29*Q61 -> -75.552674
D52: Total Net Additions | G52: USD Mns | I52: =SUM(I45:I51) -> 7.993 | J52: =SUM(J45:J51) -> 15.595 | K52: =SUM(K45:K51) -> 16.356 | L52: =SUM(L45:L51) -> 14.455 | M52: =SUM(M45:M51) -> 46.628408 | N52: =SUM(N45:N51) -> 91.642169 | O52: =SUM(O45:O51) -> 180.71687 | P52: =SUM(P45:P51) -> 334.55128 | Q52: =SUM(Q45:Q51) -> 621.58758
D54: % OF ADDITIONS:
D55: ROU Asset | G55: USD Mns | I55: =I45/$I$52 -> 0.43387964 | J55: =J45/$J$52 -> 0.054376403 | K55: =K45/$K$52 -> -0.017302519 | L55: =L45/$L$52 -> -0.077758561 | M55: =AVERAGE(I55:L55) -> 0.098298742 | N55: =M55 -> 0.098298742 | O55: =N55 -> 0.098298742 | P55: =O55 -> 0.098298742 | Q55: =P55 -> 0.098298742
D56: Equipment | G56: USD Mns | I56: =I46/$I$52 -> 0.80495434 | J56: =J46/$J$52 -> 0.65174735 | K56: =K46/$K$52 -> -0.18916606 | L56: =L46/$L$52 -> 2.1663784 | M56: =AVERAGE(I56:L56) -> 0.85847851 | N56: =M56 -> 0.85847851 | O56: =N56 -> 0.85847851 | P56: =O56 -> 0.85847851 | Q56: =P56 -> 0.85847851
D57: Finance Lease | G57: USD Mns | I57: =I47/$I$52 -> 0.0031277368 | J57: =J47/$J$52 -> 0.0098108368 | K57: =K47/$K$52 -> 0.0076424554 | L57: =L47/$L$52 -> 0 | M57: =AVERAGE(I57:L57) -> 0.0051452572 | N57: =M57 -> 0.0051452572 | O57: =N57 -> 0.0051452572 | P57: =O57 -> 0.0051452572 | Q57: =P57 -> 0.0051452572
D58: Furniture
D59: Leasehold Improvements | G59: USD Mns | I59: =I48/$I$52 -> 0.074690354 | J59: =J48/$J$52 -> 0.067970503 | K59: =K48/$K$52 -> 0.014367816 | L59: =L48/$L$52 -> 0.018401937 | M59: =AVERAGE(I59:L59) -> 0.043857653 | N59: =M59 -> 0.043857653 | O59: =N59 -> 0.043857653 | P59: =O59 -> 0.043857653 | Q59: =P59 -> 0.043857653
D60: Tooling | G60: USD Mns | I60: =I50/$I$52 -> 0.025147004 | J60: =J50/$J$52 -> 0.2160949 | K60: =K50/$K$52 -> 0.086512595 | L60: =L50/$L$52 -> 0.1353165 | M60: =AVERAGE(I60:L60) -> 0.11576775 | N60: =M60 -> 0.11576775 | O60: =N60 -> 0.11576775 | P60: =O60 -> 0.11576775 | Q60: =P60 -> 0.11576775
D61: Construction In Progress | G61: USD Mns | I61: =I51/I52 -> -0.34179907 | J61: =J51/J52 -> 0 | K61: =K51/K52 -> 1.0979457 | L61: =L51/L52 -> -1.2423383 | M61: =AVERAGE($I$61:$L$61) -> -0.12154791 | N61: =M61 -> -0.12154791 | O61: =N61 -> -0.12154791 | P61: =O61 -> -0.12154791 | Q61: =P61 -> -0.12154791
D62: Total(%) | G62: USD Mns | I62: =SUM(I55:I61) -> 1 | J62: =SUM(J55:J61) -> 1 | K62: =SUM(K55:K61) -> 1 | L62: =SUM(L55:L61) -> 1 | M62: =SUM(M55:M61) -> 1 | N62: =SUM(N55:N61) -> 1 | O62: =SUM(O55:O61) -> 1 | P62: =SUM(P55:P61) -> 1 | Q62: =SUM(Q55:Q61) -> 1
B65: x | D65: Depreciation Schedules
D66: ACCUMULATED DEPRECIATION:
D67: Beginning Accumulated Depreciation | G67: USD Mns | M67: =L69 -> -28.716 | N67: =M69 -> -45.522658 | O67: =N69 -> -78.098191 | P67: =O69 -> -141.76969 | Q67: =P69 -> -259.88776
D68: (+) Depreciation | G68: USD Mns | M68: =SUM(M87,M105,M123,M141,M168) -> -16.806658 | N68: =SUM(N87,N105,N123,N141,N168) -> -32.575533 | O68: =SUM(O87,O105,O123,O141,O168) -> -63.671497 | P68: =SUM(P87,P105,P123,P141,P168) -> -118.11807 | Q68: =SUM(Q87,Q105,Q123,Q141,Q168) -> -221.53829
D69: Ending Accumulated Depreciation | G69: USD Mns | H69: -5.069 | I69: -7.619 | J69: -11.96 | K69: -18.032 | L69: -28.716 | M69: =SUM(M67:M68) -> -45.522658 | N69: =SUM(N67:N68) -> -78.098191 | O69: =SUM(O67:O68) -> -141.76969 | P69: =SUM(P67:P68) -> -259.88776 | Q69: =SUM(Q67:Q68) -> -481.42605
D71: ROU Asset
D73: Useful Life | G73: =G16 -> 5
D75: Beginning Balance | G75: USD Mns | M75: =L78 -> 2.909 | N75: =M78 -> 5.994011 | O75: =N78 -> 11.702156 | P75: =O78 -> 22.613384 | Q75: =P78 -> 42.069147
D76: (+) Additions | G76: USD Mns | M76: =M45 -> 4.5835138 | N76: =N45 -> 9.0083099 | O76: =O45 -> 17.764241 | P76: =P45 -> 32.88597 | Q76: =Q45 -> 61.101277
D77: (-) Depreciation | G77: USD Mns | M77: =M87 -> -1.4985028 | N77: =N87 -> -3.3001647 | O77: =O87 -> -6.8530129 | P77: =P87 -> -13.430207 | Q77: =Q87 -> -25.650462
D78: Finance ROU Asset, BOP | G78: USD Mns | H78: =H35 -> 0 | I78: =I35 -> 3.468 | J78: =J35 -> 4.316 | K78: =K35 -> 4.033 | L78: =L35 -> 2.909 | M78: =SUM(M75:M77) -> 5.994011 | N78: =SUM(N75:N77) -> 11.702156 | O78: =SUM(O75:O77) -> 22.613384 | P78: =SUM(P75:P77) -> 42.069147 | Q78: =SUM(Q75:Q77) -> 77.519962
D80: Beginning Year | F80: Amount | G80: Final Year
D81: 25 | F81: =M75 -> 2.909 | G81: =D81+$G$73-1 -> 29 | M81: =IF(AND(M$6<=$G81,M$6>=$D81),IFERROR(-$F81/$G$73,0),0) -> -0.5818 | N81: =IF(AND(N$6<=$G81,N$6>=$D81),IFERROR(-$F81/$G$73,0),0) -> -0.5818 | O81: =IF(AND(O$6<=$G81,O$6>=$D81),IFERROR(-$F81/$G$73,0),0) -> -0.5818 | P81: =IF(AND(P$6<=$G81,P$6>=$D81),IFERROR(-$F81/$G$73,0),0) -> -0.5818 | Q81: =IF(AND(Q$6<=$G81,Q$6>=$D81),IFERROR(-$F81/$G$73,0),0) -> -0.5818
D82: 25 | F82: {=TRANSPOSE(M76:Q76)} -> 4.5835138 | G82: =D82+$G$73-1 -> 29 | M82: =IF(AND(M$6<=$G82,M$6>=$D82),IFERROR(-$F82/$G$73,0),0) -> -0.91670276 | N82: =IF(AND(N$6<=$G82,N$6>=$D82),IFERROR(-$F82/$G$73,0),0) -> -0.91670276 | O82: =IF(AND(O$6<=$G82,O$6>=$D82),IFERROR(-$F82/$G$73,0),0) -> -0.91670276 | P82: =IF(AND(P$6<=$G82,P$6>=$D82),IFERROR(-$F82/$G$73,0),0) -> -0.91670276 | Q82: =IF(AND(Q$6<=$G82,Q$6>=$D82),IFERROR(-$F82/$G$73,0),0) -> -0.91670276
D83: 26 | F83: 9.0083099 | G83: =D83+$G$73-1 -> 30 | M83: =IF(AND(M$6<=$G83,M$6>=$D83),IFERROR(-$F83/$G$73,0),0) -> 0 | N83: =IF(AND(N$6<=$G83,N$6>=$D83),IFERROR(-$F83/$G$73,0),0) -> -1.801662 | O83: =IF(AND(O$6<=$G83,O$6>=$D83),IFERROR(-$F83/$G$73,0),0) -> -1.801662 | P83: =IF(AND(P$6<=$G83,P$6>=$D83),IFERROR(-$F83/$G$73,0),0) -> -1.801662 | Q83: =IF(AND(Q$6<=$G83,Q$6>=$D83),IFERROR(-$F83/$G$73,0),0) -> -1.801662
D84: 27 | F84: 17.764241 | G84: =D84+$G$73-1 -> 31 | M84: =IF(AND(M$6<=$G84,M$6>=$D84),IFERROR(-$F84/$G$73,0),0) -> 0 | N84: =IF(AND(N$6<=$G84,N$6>=$D84),IFERROR(-$F84/$G$73,0),0) -> 0 | O84: =IF(AND(O$6<=$G84,O$6>=$D84),IFERROR(-$F84/$G$73,0),0) -> -3.5528482 | P84: =IF(AND(P$6<=$G84,P$6>=$D84),IFERROR(-$F84/$G$73,0),0) -> -3.5528482 | Q84: =IF(AND(Q$6<=$G84,Q$6>=$D84),IFERROR(-$F84/$G$73,0),0) -> -3.5528482
D85: 28 | F85: 32.88597 | G85: =D85+$G$73-1 -> 32 | M85: =IF(AND(M$6<=$G85,M$6>=$D85),IFERROR(-$F85/$G$73,0),0) -> 0 | N85: =IF(AND(N$6<=$G85,N$6>=$D85),IFERROR(-$F85/$G$73,0),0) -> 0 | O85: =IF(AND(O$6<=$G85,O$6>=$D85),IFERROR(-$F85/$G$73,0),0) -> 0 | P85: =IF(AND(P$6<=$G85,P$6>=$D85),IFERROR(-$F85/$G$73,0),0) -> -6.577194 | Q85: =IF(AND(Q$6<=$G85,Q$6>=$D85),IFERROR(-$F85/$G$73,0),0) -> -6.577194
D86: 29 | F86: 61.101277 | G86: =D86+$G$73-1 -> 33 | M86: =IF(AND(M$6<=$G86,M$6>=$D86),IFERROR(-$F86/$G$73,0),0) -> 0 | N86: =IF(AND(N$6<=$G86,N$6>=$D86),IFERROR(-$F86/$G$73,0),0) -> 0 | O86: =IF(AND(O$6<=$G86,O$6>=$D86),IFERROR(-$F86/$G$73,0),0) -> 0 | P86: =IF(AND(P$6<=$G86,P$6>=$D86),IFERROR(-$F86/$G$73,0),0) -> 0 | Q86: =IF(AND(Q$6<=$G86,Q$6>=$D86),IFERROR(-$F86/$G$73,0),0) -> -12.220255
D87: Total Depreciation | G87: USD Mns | M87: =SUM(M81:M86) -> -1.4985028 | N87: =SUM(N81:N86) -> -3.3001647 | O87: =SUM(O81:O86) -> -6.8530129 | P87: =SUM(P81:P86) -> -13.430207 | Q87: =SUM(Q81:Q86) -> -25.650462
B89: x | D89: Equipment
D91: Useful Life | G91: =G17 -> 8
D93: Beginning Balance | G93: USD Mns | M93: =L96 -> 51.874 | N93: =M96 -> 80.41555 | O93: =N96 -> 137.76634 | P93: =O96 -> 252.19316 | Q93: =P96 -> 462.78288
D94: (+) Additions | G94: USD Mns | M94: =M46 -> 40.029486 | N94: =N46 -> 78.672833 | O94: =O46 -> 155.14155 | P94: =P46 -> 287.20509 | Q94: =Q46 -> 533.61958
D95: (-) Depreciation | G95: USD Mns | M95: =M105 -> -11.487936 | N95: =N105 -> -21.32204 | O95: =O105 -> -40.714734 | P95: =P105 -> -76.615369 | Q95: =Q105 -> -143.31782
D96: Ending Balance, net | G96: USD Mns | H96: =H36 -> 7.055 | I96: =I36 -> 13.489 | J96: =J36 -> 23.653 | K96: =K36 -> 20.559 | L96: =L36 -> 51.874 | M96: =SUM(M93:M95) -> 80.41555 | N96: =SUM(N93:N95) -> 137.76634 | O96: =SUM(O93:O95) -> 252.19316 | P96: =SUM(P93:P95) -> 462.78288 | Q96: =SUM(Q93:Q95) -> 853.08464
D98: Beginning Year | F98: Amount | G98: Final Year
D99: 25 | F99: =M93 -> 51.874 | G99: =D99+$G$91-1 -> 32 | M99: =IF(AND(M$6<=$G99,M$6>=$D99),IFERROR(-$F99/$G$91,0),0) -> -6.48425 | N99: =IF(AND(N$6<=$G99,N$6>=$D99),IFERROR(-$F99/$G$91,0),0) -> -6.48425 | O99: =IF(AND(O$6<=$G99,O$6>=$D99),IFERROR(-$F99/$G$91,0),0) -> -6.48425 | P99: =IF(AND(P$6<=$G99,P$6>=$D99),IFERROR(-$F99/$G$91,0),0) -> -6.48425 | Q99: =IF(AND(Q$6<=$G99,Q$6>=$D99),IFERROR(-$F99/$G$91,0),0) -> -6.48425
D100: 25 | F100: {=TRANSPOSE(M94:Q94)} -> 40.029486 | G100: =D100+$G$91-1 -> 32 | M100: =IF(AND(M$6<=$G100,M$6>=$D100),IFERROR(-$F100/$G$91,0),0) -> -5.0036858 | N100: =IF(AND(N$6<=$G100,N$6>=$D100),IFERROR(-$F100/$G$91,0),0) -> -5.0036858 | O100: =IF(AND(O$6<=$G100,O$6>=$D100),IFERROR(-$F100/$G$91,0),0) -> -5.0036858 | P100: =IF(AND(P$6<=$G100,P$6>=$D100),IFERROR(-$F100/$G$91,0),0) -> -5.0036858 | Q100: =IF(AND(Q$6<=$G100,Q$6>=$D100),IFERROR(-$F100/$G$91,0),0) -> -5.0036858
D101: 26 | F101: 78.672833 | G101: =D101+$G$91-1 -> 33 | M101: =IF(AND(M$6<=$G101,M$6>=$D101),IFERROR(-$F101/$G$91,0),0) -> 0 | N101: =IF(AND(N$6<=$G101,N$6>=$D101),IFERROR(-$F101/$G$91,0),0) -> -9.8341041 | O101: =IF(AND(O$6<=$G101,O$6>=$D101),IFERROR(-$F101/$G$91,0),0) -> -9.8341041 | P101: =IF(AND(P$6<=$G101,P$6>=$D101),IFERROR(-$F101/$G$91,0),0) -> -9.8341041 | Q101: =IF(AND(Q$6<=$G101,Q$6>=$D101),IFERROR(-$F101/$G$91,0),0) -> -9.8341041
D102: 27 | F102: 155.14155 | G102: =D102+$G$91-1 -> 34 | M102: =IF(AND(M$6<=$G102,M$6>=$D102),IFERROR(-$F102/$G$91,0),0) -> 0 | N102: =IF(AND(N$6<=$G102,N$6>=$D102),IFERROR(-$F102/$G$91,0),0) -> 0 | O102: =IF(AND(O$6<=$G102,O$6>=$D102),IFERROR(-$F102/$G$91,0),0) -> -19.392694 | P102: =IF(AND(P$6<=$G102,P$6>=$D102),IFERROR(-$F102/$G$91,0),0) -> -19.392694 | Q102: =IF(AND(Q$6<=$G102,Q$6>=$D102),IFERROR(-$F102/$G$91,0),0) -> -19.392694
D103: 28 | F103: 287.20509 | G103: =D103+$G$91-1 -> 35 | M103: =IF(AND(M$6<=$G103,M$6>=$D103),IFERROR(-$F103/$G$91,0),0) -> 0 | N103: =IF(AND(N$6<=$G103,N$6>=$D103),IFERROR(-$F103/$G$91,0),0) -> 0 | O103: =IF(AND(O$6<=$G103,O$6>=$D103),IFERROR(-$F103/$G$91,0),0) -> 0 | P103: =IF(AND(P$6<=$G103,P$6>=$D103),IFERROR(-$F103/$G$91,0),0) -> -35.900636 | Q103: =IF(AND(Q$6<=$G103,Q$6>=$D103),IFERROR(-$F103/$G$91,0),0) -> -35.900636
D104: 29 | F104: 533.61958 | G104: =D104+$G$91-1 -> 36 | M104: =IF(AND(M$6<=$G104,M$6>=$D104),IFERROR(-$F104/$G$91,0),0) -> 0 | N104: =IF(AND(N$6<=$G104,N$6>=$D104),IFERROR(-$F104/$G$91,0),0) -> 0 | O104: =IF(AND(O$6<=$G104,O$6>=$D104),IFERROR(-$F104/$G$91,0),0) -> 0 | P104: =IF(AND(P$6<=$G104,P$6>=$D104),IFERROR(-$F104/$G$91,0),0) -> 0 | Q104: =IF(AND(Q$6<=$G104,Q$6>=$D104),IFERROR(-$F104/$G$91,0),0) -> -66.702447
D105: Total Depreciation | G105: USD Mns | M105: =SUM(M99:M104) -> -11.487936 | N105: =SUM(N99:N104) -> -21.32204 | O105: =SUM(O99:O104) -> -40.714734 | P105: =SUM(P99:P104) -> -76.615369 | Q105: =SUM(Q99:Q104) -> -143.31782
B107: x | D107: Finance Lease
D109: Useful Life | G109: =G18 -> 5
D111: Beginning Balance | G111: USD Mns | M111: =L114 -> 0.504 | N111: =M114 -> 0.74391515 | O111: =N114 -> 1.2154377 | P111: =O114 -> 2.1452725 | Q111: =P114 -> 3.8666249
D112: (+) Additions | G112: USD Mns | M112: =M47 -> 0.23991515 | N112: =N47 -> 0.47152253 | O112: =O47 -> 0.92983478 | P112: =P47 -> 1.7213524 | Q112: =Q47 -> 3.198228
D113: (-) Depreciation | G113: USD Mns | M113: =M123 -> -0.14878303 | N113: =N123 -> -0.24308754 | O113: =O123 -> -0.42905449 | P113: =P123 -> -0.77332497 | Q113: =Q123 -> -1.4129706
D114: Ending Balance, net | G114: USD Mns | H114: =H37 -> 0.201 | I114: =I37 -> 0.226 | J114: =J37 -> 0.379 | K114: =K37 -> 0.504 | L114: =L37 -> 0.504 | M114: =SUM(M111:M112) -> 0.74391515 | N114: =SUM(N111:N112) -> 1.2154377 | O114: =SUM(O111:O112) -> 2.1452725 | P114: =SUM(P111:P112) -> 3.8666249 | Q114: =SUM(Q111:Q112) -> 7.0648529
D116: Beginning Year | F116: Amount | G116: Final Year
D117: 25 | F117: =M111 -> 0.504 | G117: =D117+$G$109-1 -> 29 | M117: =IF(AND(M$6<=$G117,M$6>=$D117),IFERROR(-$F117/$G$109,0),0) -> -0.1008 | N117: =IF(AND(N$6<=$G117,N$6>=$D117),IFERROR(-$F117/$G$109,0),0) -> -0.1008 | O117: =IF(AND(O$6<=$G117,O$6>=$D117),IFERROR(-$F117/$G$109,0),0) -> -0.1008 | P117: =IF(AND(P$6<=$G117,P$6>=$D117),IFERROR(-$F117/$G$109,0),0) -> -0.1008 | Q117: =IF(AND(Q$6<=$G117,Q$6>=$D117),IFERROR(-$F117/$G$109,0),0) -> -0.1008
D118: 25 | F118: {=TRANSPOSE(M112:Q112)} -> 0.23991515 | G118: =D118+$G$109-1 -> 29 | M118: =IF(AND(M$6<=$G118,M$6>=$D118),IFERROR(-$F118/$G$109,0),0) -> -0.04798303 | N118: =IF(AND(N$6<=$G118,N$6>=$D118),IFERROR(-$F118/$G$109,0),0) -> -0.04798303 | O118: =IF(AND(O$6<=$G118,O$6>=$D118),IFERROR(-$F118/$G$109,0),0) -> -0.04798303 | P118: =IF(AND(P$6<=$G118,P$6>=$D118),IFERROR(-$F118/$G$109,0),0) -> -0.04798303 | Q118: =IF(AND(Q$6<=$G118,Q$6>=$D118),IFERROR(-$F118/$G$109,0),0) -> -0.04798303
D119: 26 | F119: 0.47152253 | G119: =D119+$G$109-1 -> 30 | M119: =IF(AND(M$6<=$G119,M$6>=$D119),IFERROR(-$F119/$G$109,0),0) -> 0 | N119: =IF(AND(N$6<=$G119,N$6>=$D119),IFERROR(-$F119/$G$109,0),0) -> -0.094304507 | O119: =IF(AND(O$6<=$G119,O$6>=$D119),IFERROR(-$F119/$G$109,0),0) -> -0.094304507 | P119: =IF(AND(P$6<=$G119,P$6>=$D119),IFERROR(-$F119/$G$109,0),0) -> -0.094304507 | Q119: =IF(AND(Q$6<=$G119,Q$6>=$D119),IFERROR(-$F119/$G$109,0),0) -> -0.094304507
D120: 27 | F120: 0.92983478 | G120: =D120+$G$109-1 -> 31 | M120: =IF(AND(M$6<=$G120,M$6>=$D120),IFERROR(-$F120/$G$109,0),0) -> 0 | N120: =IF(AND(N$6<=$G120,N$6>=$D120),IFERROR(-$F120/$G$109,0),0) -> 0 | O120: =IF(AND(O$6<=$G120,O$6>=$D120),IFERROR(-$F120/$G$109,0),0) -> -0.18596696 | P120: =IF(AND(P$6<=$G120,P$6>=$D120),IFERROR(-$F120/$G$109,0),0) -> -0.18596696 | Q120: =IF(AND(Q$6<=$G120,Q$6>=$D120),IFERROR(-$F120/$G$109,0),0) -> -0.18596696
D121: 28 | F121: 1.7213524 | G121: =D121+$G$109-1 -> 32 | M121: =IF(AND(M$6<=$G121,M$6>=$D121),IFERROR(-$F121/$G$109,0),0) -> 0 | N121: =IF(AND(N$6<=$G121,N$6>=$D121),IFERROR(-$F121/$G$109,0),0) -> 0 | O121: =IF(AND(O$6<=$G121,O$6>=$D121),IFERROR(-$F121/$G$109,0),0) -> 0 | P121: =IF(AND(P$6<=$G121,P$6>=$D121),IFERROR(-$F121/$G$109,0),0) -> -0.34427048 | Q121: =IF(AND(Q$6<=$G121,Q$6>=$D121),IFERROR(-$F121/$G$109,0),0) -> -0.34427048
D122: 29 | F122: 3.198228 | G122: =D122+$G$109-1 -> 33 | M122: =IF(AND(M$6<=$G122,M$6>=$D122),IFERROR(-$F122/$G$109,0),0) -> 0 | N122: =IF(AND(N$6<=$G122,N$6>=$D122),IFERROR(-$F122/$G$109,0),0) -> 0 | O122: =IF(AND(O$6<=$G122,O$6>=$D122),IFERROR(-$F122/$G$109,0),0) -> 0 | P122: =IF(AND(P$6<=$G122,P$6>=$D122),IFERROR(-$F122/$G$109,0),0) -> 0 | Q122: =IF(AND(Q$6<=$G122,Q$6>=$D122),IFERROR(-$F122/$G$109,0),0) -> -0.6396456
D123: Total Depreciation | G123: USD Mns | M123: =SUM(M117:M122) -> -0.14878303 | N123: =SUM(N117:N122) -> -0.24308754 | O123: =SUM(O117:O122) -> -0.42905449 | P123: =SUM(P117:P122) -> -0.77332497 | Q123: =SUM(Q117:Q122) -> -1.4129706
B125: x | D125: Furniture
D127: Useful Life | G127: =G19 -> 8
D129: Beginning Balance | G129: USD Mns | M129: =L132 -> 2.369 | N129: =M132 -> 3.8622609 | O129: =N132 -> 6.8273185 | P129: =O132 -> 12.708256 | Q129: =P132 -> 23.501931
...

Sheet Intangibles
D1: EOS Energy Enterprises, Inc. (NASDAQ: EOSE)
D3: 12M Target Price
D4: Scenario | E4: =Cover!C11 -> Base Case
H5: Historical | M5: Forecasted
D6: In USD Mns, unless stated otherwise | G6: Units | H6: 20 | I6: =H6+1 -> 21 | J6: =I6+1 -> 22 | K6: =J6+1 -> 23 | L6: =K6+1 -> 24 | M6: =L6+1 -> 25 | N6: =M6+1 -> 26 | O6: =N6+1 -> 27 | P6: =O6+1 -> 28 | Q6: =P6+1 -> 29
B8: 1 | D8: Intangibles
B10: 1 | D10: Intangibles | G10: USD Mns | H10: ='3FS'!E62 -> 0.32 | I10: ='3FS'!F62 -> 0.28 | J10: ='3FS'!G62 -> 0.24 | K10: ='3FS'!H62 -> 0.295 | L10: ='3FS'!I62 -> 0.24 | M10: =M31+M48 -> 0.84480468 | N10: =N31+N48 -> 1.9959872 | O10: =O31+O48 -> 4.0376442 | P10: =P31+P48 -> 5.9273359 | Q10: =Q31+Q48 -> 6.9727053
D11: %yoy | G11: % | I11: =I10/H10-1 -> -0.125 | J11: =J10/I10-1 -> -0.14285714 | K11: =K10/J10-1 -> 0.22916667 | L11: =L10/K10-1 -> -0.18644068 | M11: =M10/L10-1 -> 2.5200195 | N11: =N10/M10-1 -> 1.3626611 | O11: =O10/N10-1 -> 1.0228808 | P11: =P10/O10-1 -> 0.46801837 | Q11: =Q10/P10-1 -> 0.17636413
B13: x | D13: Assumptions
D15: Useful Life : | E15: Min | F15: Max | G15: Average
D16: Patent | E16: 10 | F16: 10 | G16: 10
D17: Software | E17: 3 | F17: 3 | G17: 3
E18: 3 | F18: 3 | G18: =AVERAGE(E18:F18) -> 3
D20: Revenue | G20: USD Mns | H20: ='3FS'!E13 -> 0.219 | I20: ='3FS'!F13 -> 4.598 | J20: ='3FS'!G13 -> 17.924 | K20: ='3FS'!H13 -> 16.378 | L20: ='3FS'!I13 -> 15.606 | M20: ='3FS'!J13 -> 174.94326 | N20: ='3FS'!K13 -> 769.7381 | O20: ='3FS'!L13 -> 1641.2176 | ... Q20: ='3FS'!N13 -> 2543.7125
D21: %yoy | G21: % | I21: =I20/H20-1 -> 19.995434 | J21: =J20/I20-1 -> 2.8982166 | K21: =K20/J20-1 -> -0.086253069 | L21: =L20/K20-1 -> -0.047136402 | M21: =M20/L20-1 -> 10.21 | N21: =N20/M20-1 -> 3.39993 | O21: =O20/N20-1 -> 1.1321767 | P21: =P20/O20-1 -> 0.37701484 | Q21: =Q20/P20-1 -> 0.12554594
B23: 2 | D23: Addition to Intangible Assets | G23: USD Mns | I23: =I36 -> 0 | J23: =J36 -> 0 | K23: =K36 -> 0.0138 | L23: =L36 -> 0.1582 | M23: =M20*M24 -> 0.48020702 | N23: =N20*N24 -> 2.1128773 | O23: =O20*O24 -> 4.5050277 | P23: =P20*P24 -> 6.20349 | Q23: =Q20*Q24 -> 6.982313
D24: % Revenue | I24: =I23/I20 -> 0 | J24: =J23/J20 -> 0 | K24: =K23/K20 -> 0.00084259372 | L24: =L23/L20 -> 0.010137127 | M24: =AVERAGE(I24:L24) -> 0.0027449301 | N24: =M24 -> 0.0027449301 | O24: =N24 -> 0.0027449301 | P24: =O24 -> 0.0027449301 | Q24: =P24 -> 0.0027449301
D26: CAPEX Schedule and Allocation
D28: Cost Allocation
D29: Trademark | H29: 0.4 | I29: 0.4 | J29: 0.4 | K29: 0.4 | L29: 0.4 | M29: =L29+M34 -> 0.4 | N29: =M29+N34 -> 0.4 | O29: =N29+O34 -> 0.4 | P29: =O29+P34 -> 0.4 | Q29: =P29+Q34 -> 0.4
D30: Non-Compete Agreement | H30: 0 | I30: 0 | J30: 0 | K30: 0.0138 | L30: 0.172 | M30: =L30+M35 -> 0.65220702 | N30: =M30+N35 -> 2.7650843 | O30: =N30+O35 -> 7.270112 | P30: =O30+P35 -> 13.473602 | Q30: =P30+Q35 -> 20.455915
D31: Intangible Assets, Gross | H31: =SUM(H29:H30) -> 0.4 | I31: =SUM(I29:I30) -> 0.4 | J31: =SUM(J29:J30) -> 0.4 | K31: =SUM(K29:K30) -> 0.4138 | L31: =SUM(L29:L30) -> 0.572 | M31: =SUM(M29:M30) -> 1.052207 | N31: =SUM(N29:N30) -> 3.1650843 | O31: =SUM(O29:O30) -> 7.670112 | ... Q31: =SUM(Q29:Q30) -> 20.855915
D33: Net Addition
D34: Trademark | I34: =I29-H29 -> 0 | J34: =J29-I29 -> 0 | K34: =K29-J29 -> 0 | L34: =L29-K29 -> 0 | M34: =M$23*M39 -> 0 | N34: =N$23*N39 -> 0 | O34: =O$23*O39 -> 0 | P34: =P$23*P39 -> 0 | Q34: =Q$23*Q39 -> 0
D35: Non-Compete Agreement | I35: =I30-H30 -> 0 | J35: =J30-I30 -> 0 | K35: =K30-J30 -> 0.0138 | L35: =L30-K30 -> 0.1582 | M35: =M$23*M40 -> 0.48020702 | N35: =N$23*N40 -> 2.1128773 | O35: =O$23*O40 -> 4.5050277 | P35: =P$23*P40 -> 6.20349 | Q35: =Q$23*Q40 -> 6.982313
D36: Total Net Addition | I36: =SUM(I34:I35) -> 0 | J36: =SUM(J34:J35) -> 0 | K36: =SUM(K34:K35) -> 0.0138 | L36: =SUM(L34:L35) -> 0.1582 | M36: =SUM(M34:M35) -> 0.48020702 | N36: =SUM(N34:N35) -> 2.1128773 | O36: =SUM(O34:O35) -> 4.5050277 | P36: =SUM(P34:P35) -> 6.20349 | Q36: =SUM(Q34:Q35) -> 6.982313
D38: % of Addition
D39: Trademark | K39: =K34/K$36 -> 0 | L39: =L34/L$36 -> 0 | M39: =AVERAGE(I39:L39) -> 0 | N39: =M39 -> 0 | O39: =N39 -> 0 | P39: =O39 -> 0 | Q39: =P39 -> 0
D40: Non-Compete Agreement | K40: =K35/K$36 -> 1 | L40: =L35/L$36 -> 1 | M40: =AVERAGE(I40:L40) -> 1 | N40: =M40 -> 1 | O40: =N40 -> 1 | P40: =O40 -> 1 | Q40: =P40 -> 1
D41: Total (%) | I41: =SUM(I39:I40) -> 0 | J41: =SUM(J39:J40) -> 0 | K41: =SUM(K39:K40) -> 1 | L41: =SUM(L39:L40) -> 1 | M41: =SUM(M39:M40) -> 1 | N41: =SUM(N39:N40) -> 1 | O41: =SUM(O39:O40) -> 1 | P41: =SUM(P39:P40) -> 1 | Q41: =SUM(Q39:Q40) -> 1
D43: Depreciation Schedule
D45: Total Amortization
D46: Beginning Accumulated Amortization | M46: =L48 -> 0.05 | N46: =M48 -> -0.20740234 | O46: =N48 -> -1.1690971 | P46: =O48 -> -3.6324678 | Q46: =P48 -> -7.9462661
D47: (+) Amortization | M47: =SUM(M66,M84) -> -0.25740234 | N47: =SUM(N66,N84) -> -0.96169477 | O47: =SUM(O66,O84) -> -2.4633707 | P47: =SUM(P66,P84) -> -4.3137983 | Q47: =SUM(Q66,Q84) -> -5.9369436
D48: Ending Accumulated Amortization | L48: 0.05 | M48: =SUM(M46:M47) -> -0.20740234 | N48: =SUM(N46:N47) -> -1.1690971 | O48: =SUM(O46:O47) -> -3.6324678 | P48: =SUM(P46:P47) -> -7.9462661 | Q48: =SUM(Q46:Q47) -> -13.88321
D50: Patent
D52: Useful Life | G52: =G16 -> 10
D54: Beginning Balance | M54: =L29 -> 0.4 | N54: =M29 -> 0.4 | O54: =N29 -> 0.4 | P54: =O29 -> 0.4 | Q54: =P29 -> 0.4
D55: (+) Additions | M55: =M34 -> 0 | N55: =N34 -> 0 | O55: =O34 -> 0 | P55: =P34 -> 0 | Q55: =Q34 -> 0
D56: (-) Depreciation | M56: =M66 -> -0.04 | N56: =N66 -> -0.04 | O56: =O66 -> -0.04 | P56: =P66 -> -0.04 | Q56: =Q66 -> -0.04
D57: Ending Balance, net | M57: =SUM(M54:M56) -> 0.36 | N57: =SUM(N54:N56) -> 0.36 | O57: =SUM(O54:O56) -> 0.36 | P57: =SUM(P54:P56) -> 0.36 | Q57: =SUM(Q54:Q56) -> 0.36
D59: Beginning Year | F59: Amount | G59: Final Year
D60: 25 | F60: =M54 -> 0.4 | G60: =D60+$G$52-1 -> 34 | M60: =IF(AND(M$6<=$G60,M$6>=$D60),IFERROR(-$F60/$G$52,0),0) -> -0.04 | N60: =IF(AND(N$6<=$G60,N$6>=$D60),IFERROR(-$F60/$G$52,0),0) -> -0.04 | O60: =IF(AND(O$6<=$G60,O$6>=$D60),IFERROR(-$F60/$G$52,0),0) -> -0.04 | P60: =IF(AND(P$6<=$G60,P$6>=$D60),IFERROR(-$F60/$G$52,0),0) -> -0.04 | Q60: =IF(AND(Q$6<=$G60,Q$6>=$D60),IFERROR(-$F60/$G$52,0),0) -> -0.04
D61: 25 | F61: {=TRANSPOSE(M55:Q55)} -> 0 | G61: =D61+$G$52-1 -> 34 | M61: =IF(AND(M$6<=$G61,M$6>=$D61),IFERROR(-$F61/$G$52,0),0) -> 0 | N61: =IF(AND(N$6<=$G61,N$6>=$D61),IFERROR(-$F61/$G$52,0),0) -> 0 | O61: =IF(AND(O$6<=$G61,O$6>=$D61),IFERROR(-$F61/$G$52,0),0) -> 0 | P61: =IF(AND(P$6<=$G61,P$6>=$D61),IFERROR(-$F61/$G$52,0),0) -> 0 | Q61: =IF(AND(Q$6<=$G61,Q$6>=$D61),IFERROR(-$F61/$G$52,0),0) -> 0
D62: 26 | F62: 0 | G62: =D62+$G$52-1 -> 35 | M62: =IF(AND(M$6<=$G62,M$6>=$D62),IFERROR(-$F62/$G$52,0),0) -> 0 | N62: =IF(AND(N$6<=$G62,N$6>=$D62),IFERROR(-$F62/$G$52,0),0) -> 0 | O62: =IF(AND(O$6<=$G62,O$6>=$D62),IFERROR(-$F62/$G$52,0),0) -> 0 | P62: =IF(AND(P$6<=$G62,P$6>=$D62),IFERROR(-$F62/$G$52,0),0) -> 0 | Q62: =IF(AND(Q$6<=$G62,Q$6>=$D62),IFERROR(-$F62/$G$52,0),0) -> 0
D63: 27 | F63: 0 | G63: =D63+$G$52-1 -> 36 | M63: =IF(AND(M$6<=$G63,M$6>=$D63),IFERROR(-$F63/$G$52,0),0) -> 0 | N63: =IF(AND(N$6<=$G63,N$6>=$D63),IFERROR(-$F63/$G$52,0),0) -> 0 | O63: =IF(AND(O$6<=$G63,O$6>=$D63),IFERROR(-$F63/$G$52,0),0) -> 0 | P63: =IF(AND(P$6<=$G63,P$6>=$D63),IFERROR(-$F63/$G$52,0),0) -> 0 | Q63: =IF(AND(Q$6<=$G63,Q$6>=$D63),IFERROR(-$F63/$G$52,0),0) -> 0
D64: 28 | F64: 0 | G64: =D64+$G$52-1 -> 37 | M64: =IF(AND(M$6<=$G64,M$6>=$D64),IFERROR(-$F64/$G$52,0),0) -> 0 | N64: =IF(AND(N$6<=$G64,N$6>=$D64),IFERROR(-$F64/$G$52,0),0) -> 0 | O64: =IF(AND(O$6<=$G64,O$6>=$D64),IFERROR(-$F64/$G$52,0),0) -> 0 | P64: =IF(AND(P$6<=$G64,P$6>=$D64),IFERROR(-$F64/$G$52,0),0) -> 0 | Q64: =IF(AND(Q$6<=$G64,Q$6>=$D64),IFERROR(-$F64/$G$52,0),0) -> 0
D65: 29 | F65: 0 | G65: =D65+$G$52-1 -> 38 | M65: =IF(AND(M$6<=$G65,M$6>=$D65),IFERROR(-$F65/$G$52,0),0) -> 0 | N65: =IF(AND(N$6<=$G65,N$6>=$D65),IFERROR(-$F65/$G$52,0),0) -> 0 | O65: =IF(AND(O$6<=$G65,O$6>=$D65),IFERROR(-$F65/$G$52,0),0) -> 0 | P65: =IF(AND(P$6<=$G65,P$6>=$D65),IFERROR(-$F65/$G$52,0),0) -> 0 | Q65: =IF(AND(Q$6<=$G65,Q$6>=$D65),IFERROR(-$F65/$G$52,0),0) -> 0
D66: Total Amortization | M66: =SUM(M60:M65) -> -0.04 | N66: =SUM(N60:N65) -> -0.04 | O66: =SUM(O60:O65) -> -0.04 | P66: =SUM(P60:P65) -> -0.04 | Q66: =SUM(Q60:Q65) -> -0.04
D68: Software
D70: Useful Life | G70: =G18 -> 3
D72: Beginning Balance | M72: =L30 -> 0.172 | N72: =M30 -> 0.65220702 | O72: =N30 -> 2.7650843 | P72: =O30 -> 7.270112 | Q72: =P30 -> 13.473602
D73: (+) Additions | M73: =M35 -> 0.48020702 | N73: =N35 -> 2.1128773 | O73: =O35 -> 4.5050277 | P73: =P35 -> 6.20349 | Q73: =Q35 -> 6.982313
D74: (-) Depreciation | M74: =M84 -> -0.21740234 | N74: =N84 -> -0.92169477 | O74: =O84 -> -2.4233707 | P74: =P84 -> -4.2737983 | Q74: =Q84 -> -5.8969436
D75: Ending Balance, net | M75: =SUM(M72:M74) -> 0.43480468 | N75: =SUM(N72:N74) -> 1.8433895 | O75: =SUM(O72:O74) -> 4.8467413 | P75: =SUM(P72:P74) -> 9.1998037 | Q75: =SUM(Q72:Q74) -> 14.558971
D77: Beginning Year | F77: Amount | G77: Final Year
D78: 25 | F78: =M72 -> 0.172 | G78: =D78+$G$70-1 -> 27 | M78: =IF(AND(M$6<=$G78,M$6>=$D78),IFERROR(-$F78/$G$70,0),0) -> -0.057333333 | N78: =IF(AND(N$6<=$G78,N$6>=$D78),IFERROR(-$F78/$G$70,0),0) -> -0.057333333 | O78: =IF(AND(O$6<=$G78,O$6>=$D78),IFERROR(-$F78/$G$70,0),0) -> -0.057333333 | P78: =IF(AND(P$6<=$G78,P$6>=$D78),IFERROR(-$F78/$G$70,0),0) -> 0 | Q78: =IF(AND(Q$6<=$G78,Q$6>=$D78),IFERROR(-$F78/$G$70,0),0) -> 0
D79: 25 | F79: {=TRANSPOSE(M73:Q73)} -> 0.48020702 | G79: =D79+$G$70-1 -> 27 | M79: =IF(AND(M$6<=$G79,M$6>=$D79),IFERROR(-$F79/$G$70,0),0) -> -0.16006901 | N79: =IF(AND(N$6<=$G79,N$6>=$D79),IFERROR(-$F79/$G$70,0),0) -> -0.16006901 | O79: =IF(AND(O$6<=$G79,O$6>=$D79),IFERROR(-$F79/$G$70,0),0) -> -0.16006901 | P79: =IF(AND(P$6<=$G79,P$6>=$D79),IFERROR(-$F79/$G$70,0),0) -> 0 | Q79: =IF(AND(Q$6<=$G79,Q$6>=$D79),IFERROR(-$F79/$G$70,0),0) -> 0
D80: 26 | F80: 2.1128773 | G80: =D80+$G$70-1 -> 28 | M80: =IF(AND(M$6<=$G80,M$6>=$D80),IFERROR(-$F80/$G$70,0),0) -> 0 | N80: =IF(AND(N$6<=$G80,N$6>=$D80),IFERROR(-$F80/$G$70,0),0) -> -0.70429243 | O80: =IF(AND(O$6<=$G80,O$6>=$D80),IFERROR(-$F80/$G$70,0),0) -> -0.70429243 | P80: =IF(AND(P$6<=$G80,P$6>=$D80),IFERROR(-$F80/$G$70,0),0) -> -0.70429243 | Q80: =IF(AND(Q$6<=$G80,Q$6>=$D80),IFERROR(-$F80/$G$70,0),0) -> 0
D81: 27 | F81: 4.5050277 | G81: =D81+$G$70-1 -> 29 | M81: =IF(AND(M$6<=$G81,M$6>=$D81),IFERROR(-$F81/$G$70,0),0) -> 0 | N81: =IF(AND(N$6<=$G81,N$6>=$D81),IFERROR(-$F81/$G$70,0),0) -> 0 | O81: =IF(AND(O$6<=$G81,O$6>=$D81),IFERROR(-$F81/$G$70,0),0) -> -1.5016759 | P81: =IF(AND(P$6<=$G81,P$6>=$D81),IFERROR(-$F81/$G$70,0),0) -> -1.5016759 | Q81: =IF(AND(Q$6<=$G81,Q$6>=$D81),IFERROR(-$F81/$G$70,0),0) -> -1.5016759
D82: 28 | F82: 6.20349 | G82: =D82+$G$70-1 -> 30 | M82: =IF(AND(M$6<=$G82,M$6>=$D82),IFERROR(-$F82/$G$70,0),0) -> 0 | N82: =IF(AND(N$6<=$G82,N$6>=$D82),IFERROR(-$F82/$G$70,0),0) -> 0 | O82: =IF(AND(O$6<=$G82,O$6>=$D82),IFERROR(-$F82/$G$70,0),0) -> 0 | P82: =IF(AND(P$6<=$G82,P$6>=$D82),IFERROR(-$F82/$G$70,0),0) -> -2.06783 | Q82: =IF(AND(Q$6<=$G82,Q$6>=$D82),IFERROR(-$F82/$G$70,0),0) -> -2.06783
D83: 29 | F83: 6.982313 | G83: =D83+$G$70-1 -> 31 | M83: =IF(AND(M$6<=$G83,M$6>=$D83),IFERROR(-$F83/$G$70,0),0) -> 0 | N83: =IF(AND(N$6<=$G83,N$6>=$D83),IFERROR(-$F83/$G$70,0),0) -> 0 | O83: =IF(AND(O$6<=$G83,O$6>=$D83),IFERROR(-$F83/$G$70,0),0) -> 0 | P83: =IF(AND(P$6<=$G83,P$6>=$D83),IFERROR(-$F83/$G$70,0),0) -> 0 | Q83: =IF(AND(Q$6<=$G83,Q$6>=$D83),IFERROR(-$F83/$G$70,0),0) -> -2.3274377
D84: Total Amortization | M84: =SUM(M78:M83) -> -0.21740234 | N84: =SUM(N78:N83) -> -0.92169477 | O84: =SUM(O78:O83) -> -2.4233707 | P84: =SUM(P78:P83) -> -4.2737983 | Q84: =SUM(Q78:Q83) -> -5.8969436

Sheet Revenue Build
D2: EOS Energy Enterprises, Inc. (NASDAQ: EOSE)
D4: 12M Target Price
D5: Scenario | F5: =Cover!C11 -> Base Case
G6: Historical | L6: Forecasted
D7: In USD Mns, unless stated otherwise | F7: Units | G7: 20 | H7: =G7+1 -> 21 | I7: =H7+1 -> 22 | J7: =I7+1 -> 23 | K7: =J7+1 -> 24 | L7: =K7+1 -> 25 | M7: =L7+1 -> 26 | N7: =M7+1 -> 27 | O7: =N7+1 -> 28 | P7: =O7+1 -> 29
B9: 1 | D9: Live Case
D11: Revenue Segments
D12: Product | F12: USD Mns | G12: 0.184 | H12: 4.562 | I12: 17.429 | J12: 16.151 | K12: 14.503 | L12: =L24 -> 162.57863 | M12: =M24 -> 715.33459 | N12: =N24 -> 1525.2197 | O12: =O24 -> 2100.2502 | P12: =P24 -> 2363.9281
D13: Service | F13: USD Mns | G13: 0.035 | H13: 0.036 | I13: 0.495 | J13: 0.227 | K13: 1.103 | L13: =L31 -> 12.36463 | M13: =M31 -> 54.403506 | N13: =N31 -> 115.99789 | O13: =O31 -> 159.73081 | P13: =P31 -> 179.78437
D14: Total Revenue | F14: USD Mns | G14: =SUM(G12:G13) -> 0.219 | H14: =SUM(H12:H13) -> 4.598 | I14: =SUM(I12:I13) -> 17.924 | J14: =SUM(J12:J13) -> 16.378 | K14: =SUM(K12:K13) -> 15.606 | L14: =SUM(L12:L13) -> 174.94326 | M14: =SUM(M12:M13) -> 769.7381 | N14: =SUM(N12:N13) -> 1641.2176 | ... P14: =SUM(P12:P13) -> 2543.7125
D15: %yoy | F15: % | H15: =H14/G14-1 -> 19.995434 | I15: =I14/H14-1 -> 2.8982166 | J15: =J14/I14-1 -> -0.086253069 | K15: =K14/J14-1 -> -0.047136402 | L15: =L14/K14-1 -> 10.21 | M15: =M14/L14-1 -> 3.39993 | N15: =N14/M14-1 -> 1.1321767 | O15: =O14/N14-1 -> 0.37701484 | P15: =P14/O14-1 -> 0.12554594
B17: 2 | D17: Assumptions
D19: Revenue Per Segment Growth Rate
D20: Product | F20: % | H20: =(H12-G12)/G12 -> 23.793478 | I20: =(I12-H12)/H12 -> 2.8204735 | J20: =(J12-I12)/I12 -> -0.073326066 | K20: =(K12-J12)/J12 -> -0.10203703 | L20: =(L12-K12)/K12 -> 10.21 | M20: =(M12-L12)/L12 -> 3.39993 | N20: =(N12-M12)/M12 -> 1.1321767 | O20: =(O12-N12)/N12 -> 0.37701484 | P20: =(P12-O12)/O12 -> 0.12554594
D21: Service | F21: % | H21: =(H13-G13)/G13 -> 0.028571429 | I21: =(I13-H13)/H13 -> 12.75 | J21: =(J13-I13)/I13 -> -0.54141414 | K21: =(K13-J13)/J13 -> 3.8590308 | L21: =(L13-K13)/K13 -> 10.21 | M21: =(M13-L13)/L13 -> 3.39993 | N21: =(N13-M13)/M13 -> 1.1321767 | O21: =(O13-N13)/N13 -> 0.37701484 | P21: =(P13-O13)/O13 -> 0.12554594
B23: 3 | D23: Product Revenue Breakdown
D24: Revenue | F24: USD Mns | G24: =G12 -> 0.184 | H24: =H12 -> 4.562 | I24: =I12 -> 17.429 | J24: =J12 -> 16.151 | K24: =K12 -> 14.503 | L24: =(1+L25)*K24 -> 162.57863 | M24: =(1+M25)*L24 -> 715.33459 | N24: =(1+N25)*M24 -> 1525.2197 | O24: =(1+O25)*N24 -> 2100.2502 | P24: =(1+P25)*O24 -> 2363.9281
D25: %yoy | F25: % | H25: =(H24-G24)/G24 -> 23.793478 | I25: =(I24-H24)/H24 -> 2.8204735 | J25: =(J24-I24)/I24 -> -0.073326066 | K25: =(K24-J24)/J24 -> -0.10203703 | L25: =_xlfn.XLOOKUP($F$5, $D26:$D28, L26:L28) -> 10.21 | M25: =_xlfn.XLOOKUP($F$5, $D26:$D28, M26:M28) -> 3.39993 | N25: =_xlfn.XLOOKUP($F$5, $D26:$D28, N26:N28) -> 1.1321767 | O25: =_xlfn.XLOOKUP($F$5, $D26:$D28, O26:O28) -> 0.37701484 | P25: =_xlfn.XLOOKUP($F$5, $D26:$D28, P26:P28) -> 0.12554594
D26: Bull Case | E26: 0.143 | L26: =L27+$E$26 -> 10.353 | M26: =M27+$E$26 -> 3.54293 | N26: =N27+$E$26 -> 1.2751767 | O26: =O27+$E$26 -> 0.52001484 | P26: =P27+$E$26 -> 0.26854594
D27: Base Case | E27: 0.667 | L27: 10.21 | M27: =L27*(1-$E$27) -> 3.39993 | N27: =M27*(1-$E$27) -> 1.1321767 | O27: =N27*(1-$E$27) -> 0.37701484 | P27: =O27*(1-$E$27) -> 0.12554594
D28: Bear Case | E28: -0.143 | L28: =L27+$E$28 -> 10.067 | M28: =M27+$E$28 -> 3.25693 | N28: =N27+$E$28 -> 0.98917669 | O28: =O27+$E$28 -> 0.23401484 | P28: =P27+$E$28 -> -0.017454059
B30: 4 | D30: Service Revenue Breakdown
D31: Revenue | F31: USD Mns | G31: =G13 -> 0.035 | H31: =H13 -> 0.036 | I31: =I13 -> 0.495 | J31: =J13 -> 0.227 | K31: =K13 -> 1.103 | L31: =(1+L32)*K31 -> 12.36463 | M31: =(1+M32)*L31 -> 54.403506 | N31: =(1+N32)*M31 -> 115.99789 | O31: =(1+O32)*N31 -> 159.73081 | P31: =(1+P32)*O31 -> 179.78437
D32: %yoy | F32: % | H32: =(H31-G31)/G31 -> 0.028571429 | I32: =(I31-H31)/H31 -> 12.75 | J32: =(J31-I31)/I31 -> -0.54141414 | K32: =(K31-J31)/J31 -> 3.8590308 | L32: =_xlfn.XLOOKUP($F$5, $D33:$D35, L33:L35) -> 10.21 | M32: =_xlfn.XLOOKUP($F$5, $D33:$D35, M33:M35) -> 3.39993 | N32: =_xlfn.XLOOKUP($F$5, $D33:$D35, N33:N35) -> 1.1321767 | O32: =_xlfn.XLOOKUP($F$5, $D33:$D35, O33:O35) -> 0.37701484 | P32: =_xlfn.XLOOKUP($F$5, $D33:$D35, P33:P35) -> 0.12554594
D33: Bull Case | E33: 0.143 | L33: =L34+$E$33 -> 10.353 | M33: =M34+$E$26 -> 3.54293 | N33: =N34+$E$26 -> 1.2751767 | O33: =O34+$E$26 -> 0.52001484 | P33: =P34+$E$26 -> 0.26854594
D34: Base Case | E34: 0.667 | L34: 10.21 | M34: =L34*(1-$E$34) -> 3.39993 | N34: =M34*(1-$E$34) -> 1.1321767 | O34: =N34*(1-$E$34) -> 0.37701484 | P34: =O34*(1-$E$34) -> 0.12554594
D35: Bear Case | E35: -0.143 | L35: =L34+$E$35 -> 10.067 | M35: =M34+$E$35 -> 3.25693 | N35: =N34+$E$35 -> 0.98917669 | O35: =O34+$E$35 -> 0.23401484 | P35: =P34+$E$35 -> -0.017454059
C99: Adjustments:

Sheet References>

Sheet For Graphs
D2: EOS Energy Enterprises, Inc. (NASDAQ: EOSE) | S2: EOS Energy Enterprises, Inc. (NASDAQ: EOSE)
D4: 12M Target Price | S4: 12M Target Price
D5: Scenario | E5: =Cover!C11 -> Base Case | S5: Scenario | T5: =Cover!R11 -> 0
F6: Historical | K6: Forecasted | U6: Historical | Z6: Forecasted
E7: Units | F7: 20 | G7: =F7+1 -> 21 | H7: =G7+1 -> 22 | I7: =H7+1 -> 23 | J7: =I7+1 -> 24 | K7: =J7+1 -> 25 | L7: =K7+1 -> 26 | M7: =L7+1 -> 27 | N7: =M7+1 -> 28 | O7: =N7+1 -> 29 | T7: Units | U7: 20 | V7: =U7+1 -> 21 | W7: =V7+1 -> 22 | X7: =W7+1 -> 23 | Y7: =X7+1 -> 24 | Z7: =Y7+1 -> 25 | AA7: =Z7+1 -> 26 | AB7: =AA7+1 -> 27 | AC7: =AB7+1 -> 28 | AD7: =AC7+1 -> 29
B9: 1 | D9: Live Case | Q9: 1 | S9: Live Case
D11: Total Revenue | F11: ='3FS'!E13 -> 0.219 | G11: ='3FS'!F13 -> 4.598 | H11: ='3FS'!G13 -> 17.924 | I11: ='3FS'!H13 -> 16.378 | J11: ='3FS'!I13 -> 15.606 | K11: ='3FS'!J13 -> 174.94326 | L11: ='3FS'!K13 -> 769.7381 | M11: ='3FS'!L13 -> 1641.2176 | ... O11: ='3FS'!N13 -> 2543.7125 | S11: Total Revenue | U11: ='3FS'!E13 -> 0.219 | V11: ='3FS'!F13 -> 4.598 | W11: ='3FS'!G13 -> 17.924 | X11: ='3FS'!H13 -> 16.378 | Y11: ='3FS'!I13 -> 15.606 | Z11: ='3FS'!J13 -> 174.94326 | AA11: ='3FS'!K13 -> 769.7381 | AB11: ='3FS'!L13 -> 1641.2176 | ... AD11: ='3FS'!N13 -> 2543.7125
D12: %YoY | G12: =(G11-F11)/F11 -> 19.995434 | H12: =(H11-G11)/G11 -> 2.8982166 | I12: =(I11-H11)/H11 -> -0.086253069 | J12: =(J11-I11)/I11 -> -0.047136402 | K12: =(K11-J11)/J11 -> 10.21 | L12: =(L11-K11)/K11 -> 3.39993 | M12: =(M11-L11)/L11 -> 1.1321767 | N12: =(N11-M11)/M11 -> 0.37701484 | O12: =(O11-N11)/N11 -> 0.12554594 | S12: Gross Profit | U12: ='3FS'!E17 -> -5.29 | V12: ='3FS'!F17 -> -41.885 | W12: ='3FS'!G17 -> -135.336 | X12: ='3FS'!H17 -> -73.42 | Y12: ='3FS'!I17 -> -83.261 | Z12: ='3FS'!J17 -> 69.977304 | AA12: ='3FS'!K17 -> 327.13869 | AB12: ='3FS'!L17 -> 738.54793 | ... AD12: ='3FS'!N17 -> 1271.8562
D13: Gross Profit | F13: ='3FS'!E17 -> -5.29 | G13: ='3FS'!F17 -> -41.885 | H13: ='3FS'!G17 -> -135.336 | I13: ='3FS'!H17 -> -73.42 | J13: ='3FS'!I17 -> -83.261 | K13: ='3FS'!J17 -> 69.977304 | L13: ='3FS'!K17 -> 327.13869 | M13: ='3FS'!L17 -> 738.54793 | ... O13: ='3FS'!N17 -> 1271.8562 | S13: EBITDA | U13: ='3FS'!E29 -> 0 | V13: ='3FS'!F29 -> -101.693 | W13: ='3FS'!G29 -> -207.598 | X13: ='3FS'!H29 -> -136.07 | Y13: ='3FS'!I29 -> -158.217 | Z13: ='3FS'!J29 -> -0.43026561 | AA13: ='3FS'!K29 -> 64.326751 | AB13: ='3FS'!L29 -> 361.55404 | ... AD13: ='3FS'!N29 -> 1397.583
D14: %Revenue | F14: =F13/F$11 -> -24.155251 | G14: =G13/G$11 -> -9.1093954 | H14: =H13/H$11 -> -7.5505468 | I14: =I13/I$11 -> -4.4828428 | J14: =J13/J$11 -> -5.3351916 | K14: =K13/K$11 -> 0.4 | L14: =L13/L$11 -> 0.425 | M14: =M13/M$11 -> 0.45 | ... O14: =O13/O$11 -> 0.5 | S14: Operating Income (EBIT) | U14: ='3FS'!E26 -> -37.417 | V14: ='3FS'!F26 -> -104.306 | W14: ='3FS'!G26 -> -214.412 | X14: ='3FS'!H26 -> -145.778 | Y14: ='3FS'!I26 -> -166.066 | Z14: ='3FS'!J26 -> -17.494326 | AA14: ='3FS'!K26 -> 30.789524 | AB14: ='3FS'!L26 -> 295.41917 | ... AD14: ='3FS'!N26 -> 1170.1077
D15: EBITDA | F15: ='3FS'!E29 -> 0 | G15: ='3FS'!F29 -> -101.693 | H15: ='3FS'!G29 -> -207.598 | I15: ='3FS'!H29 -> -136.07 | J15: ='3FS'!I29 -> -158.217 | K15: ='3FS'!J29 -> -0.43026561 | L15: ='3FS'!K29 -> 64.326751 | M15: ='3FS'!L29 -> 361.55404 | ... O15: ='3FS'!N29 -> 1397.583 | S15: Net Income/(Loss) | U15: ='3FS'!E40 -> -70.643 | V15: ='3FS'!F40 -> -124.266 | W15: ='3FS'!G40 -> -229.767 | X15: ='3FS'!H40 -> -229.547 | Y15: ='3FS'!I40 -> -685.837 | Z15: ='3FS'!J40 -> -39.453388 | AA15: ='3FS'!K40 -> 9.1608114 | AB15: ='3FS'!L40 -> 290.06504 | ... AD15: ='3FS'!N40 -> 1153.5993
D16: %Revenue | F16: =F15/F$11 -> 0 | G16: =G15/G$11 -> -22.11679 | H16: =H15/H$11 -> -11.582125 | I16: =I15/I$11 -> -8.3080962 | J16: =J15/J$11 -> -10.138216 | K16: =K15/K$11 -> -0.0024594581 | L16: =L15/L$11 -> 0.08356966 | M16: =M15/M$11 -> 0.22029622 | ... O16: =O15/O$11 -> 0.54942647
D17: Operating Income (EBIT) | F17: ='3FS'!E26 -> -37.417 | G17: ='3FS'!F26 -> -104.306 | H17: ='3FS'!G26 -> -214.412 | I17: ='3FS'!H26 -> -145.778 | J17: ='3FS'!I26 -> -166.066 | K17: ='3FS'!J26 -> -17.494326 | L17: ='3FS'!K26 -> 30.789524 | M17: ='3FS'!L26 -> 295.41917 | ... O17: ='3FS'!N26 -> 1170.1077 | S17: Operating Income (EBIT) | U17: ='3FS'!T26 -> 0
D18: %Revenue | F18: =F17/F$11 -> -170.85388 | G18: =G17/G$11 -> -22.68508 | H18: =H17/H$11 -> -11.962285 | I18: =I17/I$11 -> -8.9008426 | J18: =J17/J$11 -> -10.641164 | K18: =K17/K$11 -> -0.1 | L18: =L17/L$11 -> 0.04 | M18: =M17/M$11 -> 0.18 | ... O18: =O17/O$11 -> 0.46
D19: Net Income/(Loss) | F19: ='3FS'!E40 -> -70.643 | G19: ='3FS'!F40 -> -124.266 | H19: ='3FS'!G40 -> -229.767 | I19: ='3FS'!H40 -> -229.547 | J19: ='3FS'!I40 -> -685.837 | K19: ='3FS'!J40 -> -39.453388 | L19: ='3FS'!K40 -> 9.1608114 | M19: ='3FS'!L40 -> 290.06504 | ... O19: ='3FS'!N40 -> 1153.5993 | U19: ='3FS'!T40 -> 0
D20: %Revenue | F20: =F19/F$11 -> -322.57078 | G20: =G19/G$11 -> -27.026098 | H20: =H19/H$11 -> -12.818958 | I20: =I19/I$11 -> -14.01557 | J20: =J19/J$11 -> -43.947008 | K20: =K19/K$11 -> -0.22552105 | L20: =L19/L$11 -> 0.011901206 | M20: =M19/M$11 -> 0.1767377 | ... O20: =O19/O$11 -> 0.4535101
K22: 2024
K23: 1 | L23: =K23+1 -> 2 | M23: =L23+1 -> 3 | N23: =M23+1 -> 4
J24: Earnings | K24: 6.6 | L24: 0.9 | M24: 0.85 | N24: 7.3 | O24: =SUM(K24:N24) -> 15.65
K25: 2025 | Q25: 2025
K26: 1 | L26: =K26+1 -> 2 | M26: =L26+1 -> 3 | N26: =M26+1 -> 4 | Q26: 1 | R26: =Q26+1 -> 2 | S26: =R26+1 -> 3 | T26: =S26+1 -> 4
J27: Earnings | K27: 10.5 | L27: 15.2 | M27: 30.5 | N27: 93.5 | P27: Revenue | Q27: 10.5 | R27: 15.2 | S27: 30.5 | T27: 93.5
J28: YoY% | K28: =K27/K24-1 -> 0.59090909 | L28: =L27/L24-1 -> 15.888889 | M28: =M27/M24-1 -> 34.882353 | N28: =N27/N24-1 -> 11.808219 | P28: COGS | Q28: 35 | R28: 31 | S28: 33.9
P29: Profit | Q29: =Q27-Q28 -> -24.5 | R29: =R27-R28 -> -15.8 | S29: =S27-S28 -> -3.4
P30: Profit Margin | Q30: =Q29/Q27 -> -2.3333333 | R30: =R29/R27 -> -1.0394737 | S30: =S29/S27 -> -0.11147541
H32: Commercial Pipeline | L32: Supply Capacity Target
H33: Date | I33: Pipeline (USD bn) | J33: Pipeline (Gwh) | K33: Date | L33: Pipeline (Gwh)
H34: 2024 Q1 | I34: 13 | K34: 2023 Q4 | L34: 1.25
H35: 2024 Q3 | I35: 14.2 | J35: 59 | K35: 2024 Q2 | L35: 2
H36: 2025 Q1 | I36: 14.4 | J36: 52 | K36: 2024 Q4 | L36: 8
H37: 2025 Q3 | I37: 22.6 | J37: 91
C79: Adjustments:

Sheet Stock Price
C6: Date | D6: Open | E6: High | F6: Low | G6: Close | H6: Volume
C7: 45966 | D7: 14.4 | E7: 15.38 | F7: 13.89 | G7: 14.86 | H7: 16463330 | I7: =MAX(G7/G8,1.1) -> 1.1
C8: 45965 | D8: 14.74 | E8: 15.01 | F8: 13.99 | G8: 14.1 | H8: 17362100 | I8: =MAX(G8/G9,1.1) -> 1.1
C9: 45964 | D9: 16.09 | E9: 16.6 | F9: 15.52 | G9: 15.62 | H9: 16526199 | I9: =MAX(G9/G10,1.1) -> 1.1
C10: 45961 | D10: 14.65 | E10: 16.29 | F10: 14.53 | G10: 16.03 | H10: 24103590 | I10: =MAX(G10/G11,1.1) -> 1.1194134
C11: 45960 | D11: 13.26 | E11: 14.77 | F11: 13.15 | G11: 14.32 | H11: 24661090 | I11: =MAX(G11/G12,1.1) -> 1.1
C12: 45959 | D12: 14.83 | E12: 15.46 | F12: 13.9 | G12: 14.37 | H12: 20825580 | I12: =MAX(G12/G13,1.1) -> 1.1
C13: 45958 | D13: 15.2 | E13: 16.04 | F13: 14.64 | G13: 15.01 | H13: 16255820 | I13: =MAX(G13/G14,1.1) -> 1.1
C14: 45957 | D14: 16.24 | E14: 16.95 | F14: 15.24 | G14: 15.38 | H14: 21176471 | I14: =MAX(G14/G15,1.1) -> 1.1
C15: 45954 | D15: 15.05 | E15: 16.36 | F15: 14.96 | G15: 16.06 | H15: 21351971 | I15: =MAX(G15/G16,1.1) -> 1.1183844
C16: 45953 | D16: 15.2 | E16: 15.9 | F16: 14.32 | G16: 14.36 | H16: 16645330 | I16: =MAX(G16/G17,1.1) -> 1.1
C17: 45952 | D17: 15.6 | E17: 16.34 | F17: 14.19 | G17: 15.06 | H17: 27469650 | I17: =MAX(G17/G18,1.1) -> 1.1
C18: 45951 | D18: 17.03 | E18: 17.33 | F18: 15.64 | G18: 16.3 | H18: 50357398 | I18: =MAX(G18/G19,1.1) -> 1.1
... C99: 45834 | D99: 4.25 | E99: 4.59 | F99: 4.22 | G99: 4.54 | H99: 9260714 | I99: =MAX(G99/G100,1.1) -> 1.1
C100: 45833 | D100: 4.42 | E100: 4.44 | F100: 4.2 | G100: 4.21 | H100: 7293183
C101: 45832 | D101: 4.24 | E101: 4.43 | F101: 4.21 | G101: 4.37 | H101: 8160380
C102: 45831 | D102: 4.39 | E102: 4.57 | F102: 4.18 | G102: 4.19 | H102: 13319640
C103: 45828 | D103: 4.79 | E103: 4.87 | F103: 4.48 | G103: 4.49 | H103: 13016780
C104: 45826 | D104: 4.47 | E104: 4.78 | F104: 4.43 | G104: 4.58 | H104: 9195775
C105: 45825 | D105: 4.55 | E105: 4.75 | F105: 4.39 | G105: 4.43 | H105: 9533376
C106: 45824 | D106: 4.2 | E106: 4.66 | F106: 4.2 | G106: 4.63 | H106: 21377160
C107: 45821 | D107: 4.04 | E107: 4.16 | F107: 3.96 | G107: 4.03 | H107: 9493170
C108: 45820 | D108: 4.04 | E108: 4.29 | F108: 4 | G108: 4.16 | H108: 10136020
C109: 45819 | D109: 4.08 | E109: 4.14 | F109: 3.88 | G109: 4.01 | H109: 8419362
C110: 45818 | D110: 4.24 | E110: 4.33 | F110: 4.04 | G110: 4.07 | H110: 12979210
C111: 45817 | D111: 3.94 | E111: 4.35 | F111: 3.92 | G111: 4.18 | H111: 21946461
... C218: 45659 | D218: 4.98 | E218: 5.7 | F218: 4.94 | G218: 5.53 | H218: 13367250

Sheet Synthetic Rating
A1: Inputs for synthetic rating estimation | O1: Yes | P1: 1
A2: Please read the special cases worksheet (see below) before you use this spreadsheet. | O2: No | P2: 2
A3: Before you use this spreadsheet, make sure that the iteration box (under calculation options in excel) is checked. | P3: 3
A4: Enter the type of firm = | C4: 2 | D4: (Enter 1 if large manufacturing firm, 2 if smaller or riskier firm, 3 if financial service firm) | I4: Small: <$5 billion
A5: Do you have any operating lease or rental commitments? | F5: No | G5: Yes or No
A6: Enter current Earnings before interest and taxes (EBIT) = | F6: 50 | G6: (Add back only long term interest expense for financial firms)
A7: Enter current interest expenses = | F7: 8 | G7: (Use only long term interest expense for financial firms)
A8: Enter current long term government bond rate = | F8: 0.03
A9: Output
A10: Interest coverage ratio = | D10: =IF(F5="Yes",'[3]Synthetic Rating '!F32/('[4]Synthetic Rating '!F7+'[3]Synthetic Rating '!C29*'[4]Synthetic Rating '!D13),IF('[4]Synthetic Rating '!F7>0,'[4]Synthetic Rating '!F6/'[4]Synthetic Rating '!F7,100000)) -> 6.25
A11: Estimated Bond Rating = | D11: =IF(C4=1,VLOOKUP(D10,A19:D33,3),(IF(C4=2,VLOOKUP(D10,A38:D52,3),VLOOKUP(D10,F19:I33,3)))) -> A2/A | F11: Note: If you get REF! All over the place, set the operating lease commitment question in cell F5
A12: Estimated Default Spread = | D12: =IF(C4=1,VLOOKUP(D10,A19:D33,4),(IF(C4=2,VLOOKUP(D10,A38:D52,4),VLOOKUP(D10,F19:I33,4)))) -> 0.0085 | F12: to No, and then reset it to Yes. It should work.
A13: Estimated Cost of Debt = | D13: =F8+D12 -> 0.0385
A15: If you want to update the spreads listed below, please visit http://www.bondsonline.com
A16: For large non-financial service firms | F16: For financial service firms (default spreads are slighty different)
A17: If interest coverage ratio is | F17: If long term interest coverage ratio is
A18: > | B18: ≤ to | C18: Rating is | D18: Spread is | F18: greater than | G18: ≤ to | H18: Rating is | I18: Spread is
A19: -100000 | B19: 0.199999 | C19: D2/D | D19: 0.19 | F19: -100000 | G19: 0.049999 | H19: D2/D | I19: 0.19
A20: 0.2 | B20: 0.649999 | C20: C2/C | D20: 0.155 | F20: 0.05 | G20: 0.099999 | H20: C2/C | I20: 0.155
A21: 0.65 | B21: 0.799999 | C21: Ca2/CC | D21: 0.101 | F21: 0.1 | G21: 0.199999 | H21: Ca2/CC | I21: 0.101
A22: 0.8 | B22: 1.249999 | C22: Caa/CCC | D22: 0.0728 | F22: 0.2 | G22: 0.299999 | H22: Caa/CCC | I22: 0.0728
A23: 1.25 | B23: 1.499999 | C23: B3/B- | D23: 0.0442 | F23: 0.3 | G23: 0.399999 | H23: B3/B- | I23: 0.0442
A24: 1.5 | B24: 1.749999 | C24: B2/B | D24: 0.03 | F24: 0.4 | G24: 0.499999 | H24: B2/B | I24: 0.03
A25: 1.75 | B25: 1.999999 | C25: B1/B+ | D25: 0.0261 | F25: 0.5 | G25: 0.599999 | H25: B1/B+ | I25: 0.0261
A26: 2 | B26: 2.2499999 | C26: Ba2/BB | D26: 0.0183 | F26: 0.6 | G26: 0.749999 | H26: Ba2/BB | I26: 0.0183
A27: 2.25 | B27: 2.49999 | C27: Ba1/BB+ | D27: 0.0155 | F27: 0.75 | G27: 0.899999 | H27: Ba1/BB+ | I27: 0.0155
A28: 2.5 | B28: 2.999999 | C28: Baa2/BBB | D28: 0.012 | F28: 0.9 | G28: 1.199999 | H28: Baa2/BBB | I28: 0.012
A29: 3 | B29: 4.249999 | C29: A3/A- | D29: 0.0095 | F29: 1.2 | G29: 1.49999 | H29: A3/A- | I29: 0.0095
A30: 4.25 | B30: 5.499999 | C30: A2/A | D30: 0.0085 | F30: 1.5 | G30: 1.99999 | H30: A2/A | I30: 0.0085
... A33: 8.5 | B33: 100000 | C33: Aaa/AAA | D33: 0.0045 | F33: 3 | G33: 100000 | H33: Aaa/AAA | I33: 0.0045
A35: For smaller and riskier firms
A36: If interest coverage ratio is
A37: greater than | B37: ≤ to | C37: Rating is | D37: Spread is
A38: -100000 | B38: 0.499999 | C38: D2/D | D38: 0.19
A39: 0.5 | B39: 0.799999 | C39: C2/C | D39: 0.155
A40: 0.8 | B40: 1.249999 | C40: Ca2/CC | D40: 0.101
A41: 1.25 | B41: 1.499999 | C41: Caa/CCC | D41: 0.0728
A42: 1.5 | B42: 1.999999 | C42: B3/B- | D42: 0.0442
A43: 2 | B43: 2.499999 | C43: B2/B | D43: 0.03
A44: 2.5 | B44: 2.999999 | C44: B1/B+ | D44: 0.0261
A45: 3 | B45: 3.499999 | C45: Ba2/BB | D45: 0.0183
A46: 3.5 | B46: 3.9999999 | C46: Ba1/BB+ | D46: 0.0155
A47: 4 | B47: 4.499999 | C47: Baa2/BBB | D47: 0.012
A48: 4.5 | B48: 5.999999 | C48: A3/A- | D48: 0.0095
A49: 6 | B49: 7.499999 | C49: A2/A | D49: 0.0085
... A52: 12.5 | B52: 100000 | C52: Aaa/AAA | D52: 0.0045
