Workbook
Name BoxPlot: "BoxPlot"
Name Bubble: "Bubble"
Name Candlestick: "Candlestick"
Name Chart: "Chart"
Name ChartImage: "ChartImage"
Name ColumnRange: "ColumnRange"
Name DB: "WIREHKPROD"
Name Dumbbell: "Dumbbell"
Name Heatmap: "Heatmap"
Name Histogram: "Histogram"
Name LastActual: Summary!$C$7
Name Map: "Map"
Name OHLC: "OHLC"
Name PieChart: "PieChart"
Name Scatter: "Scatter"
Name Series: "Series"
Name Stripe: "Stripe"
Name Table: "Table"
Name Template.WIRE.DBAccess.CalcMode: "Async"
Name TreeMap: "TreeMap"
Name Waterfall: "Waterfall"

Sheet Legend
B2: Owner: | D2: Odyssey Capital - In Gyu Song
B4: Legend
B5: BLUE | D5: Hardcode / Historicals
B6: BLUE | D6: Assumptions
B7: RED | D7: Core assumptions
B8: GREEN | D8: Links to other sheet
B9: BLACK | D9: Formula
B10: PURPLE | D10: External data

Sheet Summary
B2: Name | C2: Nitto Boseki | D2: Recommendation
B3: Ticker | C3: TYO: 3110 | D3: SELL
B5: Valuation Date | C5: =TODAY() -> 46313 | D5: Stock Price | E5: 2989
B6: FY26 Ending | C6: 46112 | D6: Target Price | E6: =Valuation!Q17 -> 2391.6398
B7: Last quarter-end | C7: 46203 | D7: Upside | E7: =(E6-E5)/E5 -> -0.19985286
B8: Unit | C8: JPY M | D8: Time Horizon | E8: 1 year
B9: Case | C9: 2 | D9: IRR
B13: Thesis

Sheet 3FS
A1: =Summary!C2 -> Nitto Boseki
A2: =Summary!C3 -> TYO: 3110 | F2: Case | G2: =Summary!C9 -> 2
B4: FQ | H4: A | I4: A | J4: A | K4: A | L4: A | M4: A | N4: A | O4: A | P4: E | Q4: E | R4: E | S4: E | T4: E | Y4: 1 | Z4: 2 | AA4: 3 | AB4: 4 | AC4: =Y4 -> 1 | AD4: =Z4 -> 2 | AE4: =AA4 -> 3 | AF4: =AB4 -> 4 | AG4: =AC4 -> 1 | AH4: =AD4 -> 2 | AI4: =AE4 -> 3 | AJ4: =AF4 -> 4 | ... BX4: =BT4 -> 4
B5: FY | H5: 2019 | I5: =H5+1 -> 2020 | J5: =I5+1 -> 2021 | K5: =J5+1 -> 2022 | L5: =K5+1 -> 2023 | M5: =L5+1 -> 2024 | N5: =M5+1 -> 2025 | O5: =N5+1 -> 2026 | P5: =O5+1 -> 2027 | ... T5: =S5+1 -> 2031 | Y5: 2019 | Z5: 2019 | AA5: 2019 | AB5: 2019 | AC5: =Y5+1 -> 2020 | AD5: =Z5+1 -> 2020 | AE5: =AA5+1 -> 2020 | AF5: =AB5+1 -> 2020 | AG5: =AC5+1 -> 2021 | AH5: =AD5+1 -> 2021 | AI5: =AE5+1 -> 2021 | AJ5: =AF5+1 -> 2021 | ... BX5: =BT5+1 -> 2031
B6: FY End | G6: Units | H6: 43555 | I6: =EOMONTH(J6,-12) -> 43921 | J6: =EOMONTH(K6,-12) -> 44286 | K6: =EOMONTH(L6,-12) -> 44651 | L6: =EOMONTH(M6,-12) -> 45016 | M6: =EOMONTH(N6,-12) -> 45382 | N6: =EOMONTH(O6,-12) -> 45747 | O6: =Summary!$C$6 -> 46112 | P6: =EOMONTH(O6,12) -> 46477 | Q6: =EOMONTH(P6,12) -> 46843 | R6: =EOMONTH(Q6,12) -> 47208 | S6: =EOMONTH(R6,12) -> 47573 | T6: =EOMONTH(S6,12) -> 47938 | Y6: 43281 | Z6: 43373 | AA6: 43465 | AB6: 43555 | AC6: =EOMONTH(AD6,-3) -> 43646 | AD6: =EOMONTH(AE6,-3) -> 43738 | AE6: =EOMONTH(AF6,-3) -> 43830 | AF6: =EOMONTH(AG6,-3) -> 43921 | AG6: =EOMONTH(AH6,-3) -> 44012 | AH6: =EOMONTH(AI6,-3) -> 44104 | AI6: =EOMONTH(AJ6,-3) -> 44196 | AJ6: =EOMONTH(AK6,-3) -> 44286 | ... BC6: =EOMONTH(BD6,-3) -> 46022 | BD6: =Summary!C6 -> 46112 | BE6: =EOMONTH(BD6,3) -> 46203 | BF6: =EOMONTH(BE6,3) -> 46295 | BG6: =EOMONTH(BF6,3) -> 46387 | BH6: =EOMONTH(BG6,3) -> 46477 | BI6: =EOMONTH(BH6,3) -> 46568 | BJ6: =EOMONTH(BI6,3) -> 46660 | BK6: =EOMONTH(BJ6,3) -> 46752 | BL6: =EOMONTH(BK6,3) -> 46843 | ... BX6: =EOMONTH(BW6,3) -> 47938
A8: x | B8: SUMMARY
B10: Revenue | G10: =Summary!C8 -> JPY M | H10: =+SUMIF($X$5:$BY$5,H$5,$X10:$BY10) -> 82292 | I10: =+SUMIF($X$5:$BY$5,I$5,$X10:$BY10) -> 85722 | J10: =+SUMIF($X$5:$BY$5,J$5,$X10:$BY10) -> 78727 | K10: =+SUMIF($X$5:$BY$5,K$5,$X10:$BY10) -> 84051 | L10: =+SUMIF($X$5:$BY$5,L$5,$X10:$BY10) -> 87529 | M10: =+SUMIF($X$5:$BY$5,M$5,$X10:$BY10) -> 93253 | N10: =+SUMIF($X$5:$BY$5,N$5,$X10:$BY10) -> 109035 | O10: =+SUMIF($X$5:$BY$5,O$5,$X10:$BY10) -> 118229 | ... T10: =+SUMIF($X$5:$BY$5,T$5,$X10:$BY10) -> 193564.08 | Y10: =Y82 -> 20450 | Z10: =Z82 -> 21052 | AA10: =AA82 -> 21679 | AB10: =AB82 -> 19111 | AC10: =AC82 -> 20621 | AD10: =AD82 -> 22141 | AE10: =AE82 -> 21299 | AF10: =AF82 -> 21661 | ... BE10: =BE82 -> 34033 | BF10: =SUM(BF11:BF16) -> 34065.465 | BG10: =SUM(BG11:BG16) -> 34825.505 | BH10: =SUM(BH11:BH16) -> 35704.673 | BI10: =SUM(BI11:BI16) -> 37806.795 | BJ10: =SUM(BJ11:BJ16) -> 38507.806 | BK10: =SUM(BK11:BK16) -> 39750.777 | BL10: =SUM(BL11:BL16) -> 40940.616 | BM10: =SUM(BM11:BM16) -> 41906.919 | ... BX10: =SUM(BX11:BX16) -> 49018.055
B11: Electronic Materials | G11: =G$10 -> JPY M | H11: =+SUMIF($X$5:$BY$5,H$5,$X11:$BY11) -> 19786.95 | I11: =+SUMIF($X$5:$BY$5,I$5,$X11:$BY11) -> 23638.2 | J11: =+SUMIF($X$5:$BY$5,J$5,$X11:$BY11) -> 23371.65 | K11: =+SUMIF($X$5:$BY$5,K$5,$X11:$BY11) -> 25381.75 | L11: =+SUMIF($X$5:$BY$5,L$5,$X11:$BY11) -> 25538.3 | M11: =+SUMIF($X$5:$BY$5,M$5,$X11:$BY11) -> 29812.85 | N11: =+SUMIF($X$5:$BY$5,N$5,$X11:$BY11) -> 40911 | O11: =+SUMIF($X$5:$BY$5,O$5,$X11:$BY11) -> 49265 | ... T11: =+SUMIF($X$5:$BY$5,T$5,$X11:$BY11) -> 94669.213 | Y11: =0.35*Y20+0.75*Y21 -> 4915.4 | Z11: =0.35*Z20+0.75*Z21 -> 4969.3 | AA11: =0.35*AA20+0.75*AA21 -> 5242.25 | AB11: =0.35*AB20+0.75*AB21 -> 4660 | AC11: =0.35*AC20+0.75*AC21 -> 5033.1 | AD11: =0.35*AD20+0.75*AD21 -> 6130.35 | AE11: =0.35*AE20+0.75*AE21 -> 6084.75 | AF11: =0.35*AF20+0.75*AF21 -> 6390 | ... AV11: =0.35*AV20+0.75*AV21 -> 8598 | AW11: 9627 | AX11: 10004 | AY11: 10568 | AZ11: 10712 | BA11: 11265 | BB11: 12153 | BC11: 12669 | BD11: 13178 | BE11: 14589 | BF11: =Revenue!BF11 -> 15134.711 | BG11: =Revenue!BG11 -> 15438.299 | BH11: =Revenue!BH11 -> 16392.44 | BI11: =Revenue!BI11 -> 17139.195 | BJ11: =Revenue!BJ11 -> 18369.786 | BK11: =Revenue!BK11 -> 19144.496 | BL11: =Revenue!BL11 -> 20394.819 | BM11: =Revenue!BM11 -> 19946.043 | ... BX11: =Revenue!BX11 -> 24187.021
B12: Medical | G12: =G$10 -> JPY M | H12: =+SUMIF($X$5:$BY$5,H$5,$X12:$BY12) -> 12048.96 | I12: =+SUMIF($X$5:$BY$5,I$5,$X12:$BY12) -> 13245.76 | J12: =+SUMIF($X$5:$BY$5,J$5,$X12:$BY12) -> 11880 | K12: =+SUMIF($X$5:$BY$5,K$5,$X12:$BY12) -> 13983.2 | L12: =+SUMIF($X$5:$BY$5,L$5,$X12:$BY12) -> 14747.92 | M12: =+SUMIF($X$5:$BY$5,M$5,$X12:$BY12) -> 12703.68 | N12: =+SUMIF($X$5:$BY$5,N$5,$X12:$BY12) -> 13603 | O12: =+SUMIF($X$5:$BY$5,O$5,$X12:$BY12) -> 13850 | ... T12: =+SUMIF($X$5:$BY$5,T$5,$X12:$BY12) -> 18004.023 | Y12: =Y23*0.88 -> 3166.24 | Z12: =Z23*0.88 -> 3158.32 | AA12: =AA23*0.88 -> 2966.48 | AB12: =AB23*0.88 -> 2757.92 | AC12: =AC23*0.88 -> 3387.12 | AD12: =AD23*0.88 -> 3511.2 | AE12: =AE23*0.88 -> 3119.6 | AF12: =AF23*0.88 -> 3227.84 | ... AV12: =AV23*0.88 -> 3275.36 | AW12: 3399 | AX12: 3588 | AY12: 3326 | AZ12: 3290 | BA12: 3573 | BB12: 3187 | BC12: 3562 | BD12: 3528 | BE12: 3818 | BF12: =Revenue!BF12 -> 3409.3346 | BG12: =Revenue!BG12 -> 3810.4957 | BH12: =Revenue!BH12 -> 3774.1237 | BI12: =Revenue!BI12 -> 4008.9 | BJ12: =Revenue!BJ12 -> 3579.8013 | BK12: =Revenue!BK12 -> 4001.0205 | BL12: =Revenue!BL12 -> 3962.8299 | BM12: =Revenue!BM12 -> 4209.345 | ... BX12: =Revenue!BX12 -> 4587.471
B13: Composite Materials | G13: =G$10 -> JPY M | H13: =+SUMIF($X$5:$BY$5,H$5,$X13:$BY13) -> 12692.16 | I13: =+SUMIF($X$5:$BY$5,I$5,$X13:$BY13) -> 12008.16 | J13: =+SUMIF($X$5:$BY$5,J$5,$X13:$BY13) -> 11099.52 | K13: =+SUMIF($X$5:$BY$5,K$5,$X13:$BY13) -> 11205.6 | L13: =+SUMIF($X$5:$BY$5,L$5,$X13:$BY13) -> 11504.64 | M13: =+SUMIF($X$5:$BY$5,M$5,$X13:$BY13) -> 12571.68 | N13: =+SUMIF($X$5:$BY$5,N$5,$X13:$BY13) -> 13474 | O13: =+SUMIF($X$5:$BY$5,O$5,$X13:$BY13) -> 13401 | ... T13: =+SUMIF($X$5:$BY$5,T$5,$X13:$BY13) -> 16402.9 | Y13: =Y20*0.48 -> 3249.12 | Z13: =Z20*0.48 -> 3287.04 | AA13: =AA20*0.48 -> 3316.8 | AB13: =AB20*0.48 -> 2839.2 | AC13: =AC20*0.48 -> 3156.48 | AD13: =AD20*0.48 -> 3142.08 | AE13: =AE20*0.48 -> 2779.2 | AF13: =AF20*0.48 -> 2930.4 | ... AV13: =AV20*0.48 -> 3477.6 | AW13: 3289 | AX13: 3238 | AY13: 3492 | AZ13: 3455 | BA13: 3305 | BB13: 3551 | BC13: 3184 | BD13: 3361 | BE13: 3830 | BF13: =Revenue!BF13 -> 3977.12 | BG13: =Revenue!BG13 -> 3502.4 | BH13: =Revenue!BH13 -> 3697.1 | BI13: =Revenue!BI13 -> 3944.9 | BJ13: =Revenue!BJ13 -> 4096.4336 | BK13: =Revenue!BK13 -> 3607.472 | BL13: =Revenue!BL13 -> 3808.013 | BM13: =Revenue!BM13 -> 4023.798 | ... BX13: =Revenue!BX13 -> 4041.0939
B14: Materials Solution | G14: =G$10 -> JPY M | H14: =+SUMIF($X$5:$BY$5,H$5,$X14:$BY14) -> 11515.59 | I14: =+SUMIF($X$5:$BY$5,I$5,$X14:$BY14) -> 10343.32 | J14: =+SUMIF($X$5:$BY$5,J$5,$X14:$BY14) -> 8142.57 | K14: =+SUMIF($X$5:$BY$5,K$5,$X14:$BY14) -> 8658.47 | L14: =+SUMIF($X$5:$BY$5,L$5,$X14:$BY14) -> 9050.09 | M14: =+SUMIF($X$5:$BY$5,M$5,$X14:$BY14) -> 9094.83 | N14: =+SUMIF($X$5:$BY$5,N$5,$X14:$BY14) -> 9431 | O14: =+SUMIF($X$5:$BY$5,O$5,$X14:$BY14) -> 9515 | ... T14: =+SUMIF($X$5:$BY$5,T$5,$X14:$BY14) -> 11590.355 | Y14: =Y23*0.12+Y22*0.23+Y19 -> 2894.22 | Z14: =Z23*0.12+Z22*0.23+Z19 -> 2901.21 | AA14: =AA23*0.12+AA22*0.23+AA19 -> 3080.24 | AB14: =AB23*0.12+AB22*0.23+AB19 -> 2639.92 | AC14: =AC23*0.12+AC22*0.23+AC19 -> 2799.48 | AD14: =AD23*0.12+AD22*0.23+AD19 -> 2598.08 | AE14: =AE23*0.12+AE22*0.23+AE19 -> 2603.62 | AF14: =AF23*0.12+AF22*0.23+AF19 -> 2342.14 | ... AV14: =AV23*0.12+AV22*0.23+AV19 -> 2186.43 | AW14: 2211 | AX14: 2338 | AY14: 2614 | AZ14: 2268 | BA14: 2267 | BB14: 2247 | BC14: 2515 | BD14: 2486 | BE14: 2615 | BF14: =Revenue!BF14 -> 2381.82 | BG14: =Revenue!BG14 -> 2665.9 | BH14: =Revenue!BH14 -> 2635.16 | BI14: =Revenue!BI14 -> 2693.45 | BJ14: =Revenue!BJ14 -> 2453.2746 | BK14: =Revenue!BK14 -> 2745.877 | BL14: =Revenue!BL14 -> 2714.2148 | BM14: =Revenue!BM14 -> 2774.2535 | ... BX14: =Revenue!BX14 -> 2965.8958
B15: Insulation Materials | G15: =G$10 -> JPY M | H15: =+SUMIF($X$5:$BY$5,H$5,$X15:$BY15) -> 14813.8 | I15: =+SUMIF($X$5:$BY$5,I$5,$X15:$BY15) -> 14549.28 | J15: =+SUMIF($X$5:$BY$5,J$5,$X15:$BY15) -> 12620.12 | K15: =+SUMIF($X$5:$BY$5,K$5,$X15:$BY15) -> 12531.72 | L15: =+SUMIF($X$5:$BY$5,L$5,$X15:$BY15) -> 13931.16 | M15: =+SUMIF($X$5:$BY$5,M$5,$X15:$BY15) -> 14713.16 | N15: =+SUMIF($X$5:$BY$5,N$5,$X15:$BY15) -> 15320 | O15: =+SUMIF($X$5:$BY$5,O$5,$X15:$BY15) -> 15136 | ... T15: =+SUMIF($X$5:$BY$5,T$5,$X15:$BY15) -> 21552.081 | Y15: =Y22*0.68 -> 3469.36 | Z15: =Z22*0.68 -> 3679.48 | AA15: =AA22*0.68 -> 4055.52 | AB15: =AB22*0.68 -> 3609.44 | AC15: =AC22*0.68 -> 3549.6 | AD15: =AD22*0.68 -> 3696.48 | AE15: =AE22*0.68 -> 3681.52 | AF15: =AF22*0.68 -> 3621.68 | ... AV15: =AV22*0.68 -> 3653.64 | AW15: 3736 | AX15: 3807 | AY15: 4190 | AZ15: 3587 | BA15: 3543 | BB15: 3751 | BC15: 4126 | BD15: 3716 | BE15: 4399 | BF15: =Revenue!BF15 -> 4313.65 | BG15: =Revenue!BG15 -> 4744.9 | BH15: =Revenue!BH15 -> 4273.4 | BI15: =Revenue!BI15 -> 4618.95 | BJ15: =Revenue!BJ15 -> 4529.3325 | BK15: =Revenue!BK15 -> 4982.145 | BL15: =Revenue!BL15 -> 4487.07 | BM15: =Revenue!BM15 -> 4849.8975 | ... BX15: =Revenue!BX15 -> 5194.3444
B16: Other Business | G16: =G$10 -> JPY M | H16: =+SUMIF($X$5:$BY$5,H$5,$X16:$BY16) -> 11432.54 | I16: =+SUMIF($X$5:$BY$5,I$5,$X16:$BY16) -> 11935.28 | J16: =+SUMIF($X$5:$BY$5,J$5,$X16:$BY16) -> 11611.14 | K16: =+SUMIF($X$5:$BY$5,K$5,$X16:$BY16) -> 12288.26 | L16: =+SUMIF($X$5:$BY$5,L$5,$X16:$BY16) -> 12755.89 | M16: =+SUMIF($X$5:$BY$5,M$5,$X16:$BY16) -> 14353.8 | N16: =+SUMIF($X$5:$BY$5,N$5,$X16:$BY16) -> 16294 | O16: =+SUMIF($X$5:$BY$5,O$5,$X16:$BY16) -> 17059 | ... T16: =+SUMIF($X$5:$BY$5,T$5,$X16:$BY16) -> 31345.513 | Y16: =0.17*Y20+0.25*Y21+0.09*Y22+Y24 -> 2752.66 | Z16: =0.17*Z20+0.25*Z21+0.09*Z22+Z24 -> 3058.65 | AA16: =0.17*AA20+0.25*AA21+0.09*AA22+AA24 -> 3015.71 | AB16: =0.17*AB20+0.25*AB21+0.09*AB22+AB24 -> 2605.52 | AC16: =0.17*AC20+0.25*AC21+0.09*AC22+AC24 -> 2694.22 | AD16: =0.17*AD20+0.25*AD21+0.09*AD22+AD24 -> 3061.81 | AE16: =0.17*AE20+0.25*AE21+0.09*AE22+AE24 -> 3028.31 | AF16: =0.17*AF20+0.25*AF21+0.09*AF22+AF24 -> 3150.94 | ... AV16: =0.17*AV20+0.25*AV21+0.09*AV22+AV24 -> 4020.97 | AW16: 3851 | AX16: 3961 | AY16: 4278 | AZ16: 4204 | BA16: 4276 | BB16: 4291 | BC16: 4127 | BD16: 4365 | BE16: 4780 | BF16: =Revenue!BF16 -> 4848.83 | BG16: =Revenue!BG16 -> 4663.51 | BH16: =Revenue!BH16 -> 4932.45 | BI16: =Revenue!BI16 -> 5401.4 | BJ16: =Revenue!BJ16 -> 5479.1779 | BK16: =Revenue!BK16 -> 5269.7663 | BL16: =Revenue!BL16 -> 5573.6685 | BM16: =Revenue!BM16 -> 6103.582 | ... BX16: =Revenue!BX16 -> 8042.2296
B18: Revenue (Previous Disclosure) | G18: =G$10 -> JPY M | H18: =+SUMIF($X$5:$BY$5,H$5,$X18:$BY18) -> 82290 | I18: =+SUMIF($X$5:$BY$5,I$5,$X18:$BY18) -> 85720 | J18: =+SUMIF($X$5:$BY$5,J$5,$X18:$BY18) -> 78725 | K18: =+SUMIF($X$5:$BY$5,K$5,$X18:$BY18) -> 84049 | L18: =+SUMIF($X$5:$BY$5,L$5,$X18:$BY18) -> 87528 | M18: =+SUMIF($X$5:$BY$5,M$5,$X18:$BY18) -> 93250 | N18: =+SUMIF($X$5:$BY$5,N$5,$X18:$BY18) -> 0 | O18: =+SUMIF($X$5:$BY$5,O$5,$X18:$BY18) -> 0 | ... T18: =+SUMIF($X$5:$BY$5,T$5,$X18:$BY18) -> 0 | Y18: =SUM(Y19:Y24) -> 20447 | Z18: =SUM(Z19:Z24) -> 21054 | AA18: =SUM(AA19:AA24) -> 21677 | AB18: =SUM(AB19:AB24) -> 19112 | AC18: =SUM(AC19:AC24) -> 20620 | AD18: =SUM(AD19:AD24) -> 22140 | AE18: =SUM(AE19:AE24) -> 21297 | AF18: =SUM(AF19:AF24) -> 21663 | ... AV18: =SUM(AV19:AV24) -> 25212
B19: Textile | G19: =G$10 -> JPY M | H19: =+SUMIF($X$5:$BY$5,H$5,$X19:$BY19) -> 4862 | I19: =+SUMIF($X$5:$BY$5,I$5,$X19:$BY19) -> 3616 | J19: =+SUMIF($X$5:$BY$5,J$5,$X19:$BY19) -> 2254 | K19: =+SUMIF($X$5:$BY$5,K$5,$X19:$BY19) -> 2513 | L19: =+SUMIF($X$5:$BY$5,L$5,$X19:$BY19) -> 2327 | M19: =+SUMIF($X$5:$BY$5,M$5,$X19:$BY19) -> 2386 | N19: =+SUMIF($X$5:$BY$5,N$5,$X19:$BY19) -> 0 | O19: =+SUMIF($X$5:$BY$5,O$5,$X19:$BY19) -> 0 | ... T19: =+SUMIF($X$5:$BY$5,T$5,$X19:$BY19) -> 0 | Y19: 1289 | Z19: 1226 | AA19: 1304 | AB19: 1043 | AC19: 1137 | AD19: 869 | AE19: 933 | AF19: 677 | AG19: 552 | AH19: 514 | AI19: 651 | AJ19: 537 | AK19: 668 | AL19: 591 | AM19: 747 | AN19: 507 | AO19: 606 | AP19: 553 | AQ19: 674 | AR19: 494 | AS19: 639 | AT19: 581 | AU19: 662 | AV19: 504
B20: Glass Fiber Yarn | G20: =G$10 -> JPY M | H20: =+SUMIF($X$5:$BY$5,H$5,$X20:$BY20) -> 26442 | I20: =+SUMIF($X$5:$BY$5,I$5,$X20:$BY20) -> 25017 | J20: =+SUMIF($X$5:$BY$5,J$5,$X20:$BY20) -> 23124 | K20: =+SUMIF($X$5:$BY$5,K$5,$X20:$BY20) -> 23345 | L20: =+SUMIF($X$5:$BY$5,L$5,$X20:$BY20) -> 23968 | M20: =+SUMIF($X$5:$BY$5,M$5,$X20:$BY20) -> 26191 | N20: =+SUMIF($X$5:$BY$5,N$5,$X20:$BY20) -> 0 | O20: =+SUMIF($X$5:$BY$5,O$5,$X20:$BY20) -> 0 | ... T20: =+SUMIF($X$5:$BY$5,T$5,$X20:$BY20) -> 0 | Y20: 6769 | Z20: 6848 | AA20: 6910 | AB20: 5915 | AC20: 6576 | AD20: 6546 | AE20: 5790 | AF20: 6105 | AG20: 5686 | AH20: 5120 | AI20: 6266 | AJ20: 6052 | AK20: 5734 | AL20: 5468 | AM20: 5989 | AN20: 6154 | AO20: 6888 | AP20: 6052 | AQ20: 5798 | AR20: 5230 | AS20: 5748 | AT20: 6077 | AU20: 7121 | AV20: 7245
B21: Glass Fiber Cloth | G21: =G$10 -> JPY M | H21: =+SUMIF($X$5:$BY$5,H$5,$X21:$BY21) -> 14043 | I21: =+SUMIF($X$5:$BY$5,I$5,$X21:$BY21) -> 19843 | J21: =+SUMIF($X$5:$BY$5,J$5,$X21:$BY21) -> 20371 | K21: =+SUMIF($X$5:$BY$5,K$5,$X21:$BY21) -> 22948 | L21: =+SUMIF($X$5:$BY$5,L$5,$X21:$BY21) -> 22866 | M21: =+SUMIF($X$5:$BY$5,M$5,$X21:$BY21) -> 27528 | N21: =+SUMIF($X$5:$BY$5,N$5,$X21:$BY21) -> 0 | O21: =+SUMIF($X$5:$BY$5,O$5,$X21:$BY21) -> 0 | ... T21: =+SUMIF($X$5:$BY$5,T$5,$X21:$BY21) -> 0 | Y21: 3395 | Z21: 3430 | AA21: 3765 | AB21: 3453 | AC21: 3642 | AD21: 5119 | AE21: 5411 | AF21: 5671 | AG21: 5538 | AH21: 4517 | AI21: 4789 | AJ21: 5527 | AK21: 5600 | AL21: 5502 | AM21: 5373 | AN21: 6473 | AO21: 6979 | AP21: 6503 | AQ21: 5137 | AR21: 4247 | AS21: 5423 | AT21: 6545 | AU21: 7477 | AV21: 8083
B22: Glass Fiber for Industrial Materials | G22: =G$10 -> JPY M | H22: =+SUMIF($X$5:$BY$5,H$5,$X22:$BY22) -> 21785 | I22: =+SUMIF($X$5:$BY$5,I$5,$X22:$BY22) -> 21396 | J22: =+SUMIF($X$5:$BY$5,J$5,$X22:$BY22) -> 18559 | K22: =+SUMIF($X$5:$BY$5,K$5,$X22:$BY22) -> 18429 | L22: =+SUMIF($X$5:$BY$5,L$5,$X22:$BY22) -> 20487 | M22: =+SUMIF($X$5:$BY$5,M$5,$X22:$BY22) -> 21637 | N22: =+SUMIF($X$5:$BY$5,N$5,$X22:$BY22) -> 0 | O22: =+SUMIF($X$5:$BY$5,O$5,$X22:$BY22) -> 0 | ... T22: =+SUMIF($X$5:$BY$5,T$5,$X22:$BY22) -> 0 | Y22: 5102 | Z22: 5411 | AA22: 5964 | AB22: 5308 | AC22: 5220 | AD22: 5436 | AE22: 5414 | AF22: 5326 | AG22: 4397 | AH22: 4639 | AI22: 4910 | AJ22: 4613 | AK22: 4179 | AL22: 4598 | AM22: 4967 | AN22: 4685 | AO22: 4588 | AP22: 5235 | AQ22: 5489 | AR22: 5175 | AS22: 4936 | AT22: 5386 | AU22: 5942 | AV22: 5373
B23: Life Science | G23: =G$10 -> JPY M | H23: =+SUMIF($X$5:$BY$5,H$5,$X23:$BY23) -> 13692 | I23: =+SUMIF($X$5:$BY$5,I$5,$X23:$BY23) -> 15052 | J23: =+SUMIF($X$5:$BY$5,J$5,$X23:$BY23) -> 13500 | K23: =+SUMIF($X$5:$BY$5,K$5,$X23:$BY23) -> 15890 | L23: =+SUMIF($X$5:$BY$5,L$5,$X23:$BY23) -> 16759 | M23: =+SUMIF($X$5:$BY$5,M$5,$X23:$BY23) -> 14436 | N23: =+SUMIF($X$5:$BY$5,N$5,$X23:$BY23) -> 0 | O23: =+SUMIF($X$5:$BY$5,O$5,$X23:$BY23) -> 0 | ... T23: =+SUMIF($X$5:$BY$5,T$5,$X23:$BY23) -> 0 | Y23: 3598 | Z23: 3589 | AA23: 3371 | AB23: 3134 | AC23: 3849 | AD23: 3990 | AE23: 3545 | AF23: 3668 | AG23: 3229 | AH23: 3625 | AI23: 3218 | AJ23: 3428 | AK23: 4154 | AL23: 4163 | AM23: 3734 | AN23: 3839 | AO23: 4459 | AP23: 4641 | AQ23: 4374 | AR23: 3285 | AS23: 3240 | AT23: 3615 | AU23: 3859 | AV23: 3722
B24: Others | G24: =G$10 -> JPY M | H24: =+SUMIF($X$5:$BY$5,H$5,$X24:$BY24) -> 1466 | I24: =+SUMIF($X$5:$BY$5,I$5,$X24:$BY24) -> 796 | J24: =+SUMIF($X$5:$BY$5,J$5,$X24:$BY24) -> 917 | K24: =+SUMIF($X$5:$BY$5,K$5,$X24:$BY24) -> 924 | L24: =+SUMIF($X$5:$BY$5,L$5,$X24:$BY24) -> 1121 | M24: =+SUMIF($X$5:$BY$5,M$5,$X24:$BY24) -> 1072 | N24: =+SUMIF($X$5:$BY$5,N$5,$X24:$BY24) -> 0 | O24: =+SUMIF($X$5:$BY$5,O$5,$X24:$BY24) -> 0 | ... T24: =+SUMIF($X$5:$BY$5,T$5,$X24:$BY24) -> 0 | Y24: 294 | Z24: 550 | AA24: 363 | AB24: 259 | AC24: 196 | AD24: 180 | AE24: 204 | AF24: 216 | AG24: 179 | AH24: 282 | AI24: 262 | AJ24: 194 | AK24: 181 | AL24: 246 | AM24: 223 | AN24: 274 | AO24: 304 | AP24: 226 | AQ24: 253 | AR24: 338 | AS24: 309 | AT24: 232 | AU24: 246 | AV24: 285
B26: Mix
B27: =B11 -> Electronic Materials | G27: % | H27: =IFERROR(H11/H$10,"nm") -> 0.24044804 | I27: =IFERROR(I11/I$10,"nm") -> 0.27575418 | J27: =IFERROR(J11/J$10,"nm") -> 0.29686956 | K27: =IFERROR(K11/K$10,"nm") -> 0.30198035 | L27: =IFERROR(L11/L$10,"nm") -> 0.29176958 | M27: =IFERROR(M11/M$10,"nm") -> 0.31969856 | N27: =IFERROR(N11/N$10,"nm") -> 0.3752098 | O27: =IFERROR(O11/O$10,"nm") -> 0.41669134 | ... T27: =IFERROR(T11/T$10,"nm") -> 0.4890846 | Y27: =IFERROR(Y11/Y$10,"nm") -> 0.24036186 | Z27: =IFERROR(Z11/Z$10,"nm") -> 0.23604883 | AA27: =IFERROR(AA11/AA$10,"nm") -> 0.24181235 | AB27: =IFERROR(AB11/AB$10,"nm") -> 0.24383863 | AC27: =IFERROR(AC11/AC$10,"nm") -> 0.24407643 | AD27: =IFERROR(AD11/AD$10,"nm") -> 0.27687774 | AE27: =IFERROR(AE11/AE$10,"nm") -> 0.28568243 | AF27: =IFERROR(AF11/AF$10,"nm") -> 0.29500023 | ... BX27: =IFERROR(BX11/BX$10,"nm") -> 0.49343085
B28: =B12 -> Medical | G28: % | H28: =IFERROR(H12/H$10,"nm") -> 0.14641715 | I28: =IFERROR(I12/I$10,"nm") -> 0.15451996 | J28: =IFERROR(J12/J$10,"nm") -> 0.15090122 | K28: =IFERROR(K12/K$10,"nm") -> 0.16636566 | L28: =IFERROR(L12/L$10,"nm") -> 0.16849181 | M28: =IFERROR(M12/M$10,"nm") -> 0.13622811 | N28: =IFERROR(N12/N$10,"nm") -> 0.12475811 | O28: =IFERROR(O12/O$10,"nm") -> 0.11714554 | ... T28: =IFERROR(T12/T$10,"nm") -> 0.093013241 | Y28: =IFERROR(Y12/Y$10,"nm") -> 0.15482836 | Z28: =IFERROR(Z12/Z$10,"nm") -> 0.1500247 | AA28: =IFERROR(AA12/AA$10,"nm") -> 0.13683657 | AB28: =IFERROR(AB12/AB$10,"nm") -> 0.14431061 | AC28: =IFERROR(AC12/AC$10,"nm") -> 0.16425586 | AD28: =IFERROR(AD12/AD$10,"nm") -> 0.15858362 | AE28: =IFERROR(AE12/AE$10,"nm") -> 0.14646697 | AF28: =IFERROR(AF12/AF$10,"nm") -> 0.1490162 | ... BX28: =IFERROR(BX12/BX$10,"nm") -> 0.093587373
B29: =B13 -> Composite Materials | G29: % | H29: =IFERROR(H13/H$10,"nm") -> 0.15423322 | I29: =IFERROR(I13/I$10,"nm") -> 0.14008259 | J29: =IFERROR(J13/J$10,"nm") -> 0.14098746 | K29: =IFERROR(K13/K$10,"nm") -> 0.13331906 | L29: =IFERROR(L13/L$10,"nm") -> 0.13143804 | M29: =IFERROR(M13/M$10,"nm") -> 0.13481261 | N29: =IFERROR(N13/N$10,"nm") -> 0.123575 | O29: =IFERROR(O13/O$10,"nm") -> 0.11334782 | ... T29: =IFERROR(T13/T$10,"nm") -> 0.084741442 | Y29: =IFERROR(Y13/Y$10,"nm") -> 0.15888117 | Z29: =IFERROR(Z13/Z$10,"nm") -> 0.15613908 | AA29: =IFERROR(AA13/AA$10,"nm") -> 0.15299599 | AB29: =IFERROR(AB13/AB$10,"nm") -> 0.14856365 | AC29: =IFERROR(AC13/AC$10,"nm") -> 0.15307114 | AD29: =IFERROR(AD13/AD$10,"nm") -> 0.14191229 | AE29: =IFERROR(AE13/AE$10,"nm") -> 0.130485 | AF29: =IFERROR(AF13/AF$10,"nm") -> 0.13528461 | ... BX29: =IFERROR(BX13/BX$10,"nm") -> 0.082440926
B30: =B14 -> Materials Solution | G30: % | H30: =IFERROR(H14/H$10,"nm") -> 0.13993572 | I30: =IFERROR(I14/I$10,"nm") -> 0.12066121 | J30: =IFERROR(J14/J$10,"nm") -> 0.10342792 | K30: =IFERROR(K14/K$10,"nm") -> 0.10301448 | L30: =IFERROR(L14/L$10,"nm") -> 0.10339533 | M30: =IFERROR(M14/M$10,"nm") -> 0.097528551 | N30: =IFERROR(N14/N$10,"nm") -> 0.086495162 | O30: =IFERROR(O14/O$10,"nm") -> 0.080479409 | ... T30: =IFERROR(T14/T$10,"nm") -> 0.059878643 | Y30: =IFERROR(Y14/Y$10,"nm") -> 0.14152665 | Z30: =IFERROR(Z14/Z$10,"nm") -> 0.13781161 | AA30: =IFERROR(AA14/AA$10,"nm") -> 0.14208404 | AB30: =IFERROR(AB14/AB$10,"nm") -> 0.13813615 | AC30: =IFERROR(AC14/AC$10,"nm") -> 0.13575869 | AD30: =IFERROR(AD14/AD$10,"nm") -> 0.11734249 | AE30: =IFERROR(AE14/AE$10,"nm") -> 0.12224142 | AF30: =IFERROR(AF14/AF$10,"nm") -> 0.10812705 | ... BX30: =IFERROR(BX14/BX$10,"nm") -> 0.060506191
B31: =B15 -> Insulation Materials | G31: % | H31: =IFERROR(H15/H$10,"nm") -> 0.18001507 | I31: =IFERROR(I15/I$10,"nm") -> 0.16972632 | J31: =IFERROR(J15/J$10,"nm") -> 0.16030231 | K31: =IFERROR(K15/K$10,"nm") -> 0.14909662 | L31: =IFERROR(L15/L$10,"nm") -> 0.15916051 | M31: =IFERROR(M15/M$10,"nm") -> 0.1577768 | N31: =IFERROR(N15/N$10,"nm") -> 0.14050534 | O31: =IFERROR(O15/O$10,"nm") -> 0.12802274 | ... T31: =IFERROR(T15/T$10,"nm") -> 0.11134339 | Y31: =IFERROR(Y15/Y$10,"nm") -> 0.16965086 | Z31: =IFERROR(Z15/Z$10,"nm") -> 0.17478054 | AA31: =IFERROR(AA15/AA$10,"nm") -> 0.18707136 | AB31: =IFERROR(AB15/AB$10,"nm") -> 0.18886714 | AC31: =IFERROR(AC15/AC$10,"nm") -> 0.1721352 | AD31: =IFERROR(AD15/AD$10,"nm") -> 0.16695181 | AE31: =IFERROR(AE15/AE$10,"nm") -> 0.17284943 | AF31: =IFERROR(AF15/AF$10,"nm") -> 0.16719819 | ... BX31: =IFERROR(BX15/BX$10,"nm") -> 0.10596798
B32: =B16 -> Other Business | G32: % | H32: =IFERROR(H16/H$10,"nm") -> 0.13892651 | I32: =IFERROR(I16/I$10,"nm") -> 0.1392324 | J32: =IFERROR(J16/J$10,"nm") -> 0.14748612 | K32: =IFERROR(K16/K$10,"nm") -> 0.14620005 | L32: =IFERROR(L16/L$10,"nm") -> 0.1457333 | M32: =IFERROR(M16/M$10,"nm") -> 0.1539232 | N32: =IFERROR(N16/N$10,"nm") -> 0.14943825 | O32: =IFERROR(O16/O$10,"nm") -> 0.14428778 | ... T32: =IFERROR(T16/T$10,"nm") -> 0.16193868 | Y32: =IFERROR(Y16/Y$10,"nm") -> 0.1346044 | Z32: =IFERROR(Z16/Z$10,"nm") -> 0.14529023 | AA32: =IFERROR(AA16/AA$10,"nm") -> 0.13910743 | AB32: =IFERROR(AB16/AB$10,"nm") -> 0.13633614 | AC32: =IFERROR(AC16/AC$10,"nm") -> 0.13065419 | AD32: =IFERROR(AD16/AD$10,"nm") -> 0.13828689 | AE32: =IFERROR(AE16/AE$10,"nm") -> 0.14218085 | AF32: =IFERROR(AF16/AF$10,"nm") -> 0.14546604 | ... BX32: =IFERROR(BX16/BX$10,"nm") -> 0.16406668
B34: Y/Y | I34: =IFERROR(I10/H10-1,"nm") -> 0.041680844 | J34: =IFERROR(J10/I10-1,"nm") -> -0.081600989 | K34: =IFERROR(K10/J10-1,"nm") -> 0.0676261 | L34: =IFERROR(L10/K10-1,"nm") -> 0.041379639 | M34: =IFERROR(M10/L10-1,"nm") -> 0.065395469 | N34: =IFERROR(N10/M10-1,"nm") -> 0.16923852 | O34: =IFERROR(O10/N10-1,"nm") -> 0.084321548 | P34: =IFERROR(P10/O10-1,"nm") -> 0.17254348 | ... T34: =IFERROR(T10/S10-1,"nm") -> 0.064201151
B35: =B11 -> Electronic Materials | G35: % | I35: =IFERROR(I11/H11-1,"nm") -> 0.19463586 | J35: =IFERROR(J11/I11-1,"nm") -> -0.011276239 | K35: =IFERROR(K11/J11-1,"nm") -> 0.086005909 | L35: =IFERROR(L11/K11-1,"nm") -> 0.0061678174 | M35: =IFERROR(M11/L11-1,"nm") -> 0.16737802 | N35: =IFERROR(N11/M11-1,"nm") -> 0.37226062 | O35: =IFERROR(O11/N11-1,"nm") -> 0.20419936 | P35: =IFERROR(P11/O11-1,"nm") -> 0.24945599 | ... T35: =IFERROR(T11/S11-1,"nm") -> 0.06201855 | AC35: =IFERROR(AC11/Y11-1,"nm") -> 0.023945152 | AD35: =IFERROR(AD11/Z11-1,"nm") -> 0.23364458 | AE35: =IFERROR(AE11/AA11-1,"nm") -> 0.16071343 | AF35: =IFERROR(AF11/AB11-1,"nm") -> 0.37124464 | AG35: =IFERROR(AG11/AC11-1,"nm") -> 0.22063937 | AH35: =IFERROR(AH11/AD11-1,"nm") -> -0.15506456 | AI35: =IFERROR(AI11/AE11-1,"nm") -> -0.049287152 | AJ35: =IFERROR(AJ11/AF11-1,"nm") -> -0.019804382 | ... BX35: =IFERROR(BX11/BT11-1,"nm") -> 0.059641915
B36: =B12 -> Medical | G36: % | I36: =IFERROR(I12/H12-1,"nm") -> 0.099328075 | J36: =IFERROR(J12/I12-1,"nm") -> -0.10310922 | K36: =IFERROR(K12/J12-1,"nm") -> 0.17703704 | L36: =IFERROR(L12/K12-1,"nm") -> 0.054688483 | M36: =IFERROR(M12/L12-1,"nm") -> -0.13861209 | N36: =IFERROR(N12/M12-1,"nm") -> 0.070792085 | O36: =IFERROR(O12/N12-1,"nm") -> 0.018157759 | P36: =IFERROR(P12/O12-1,"nm") -> 0.069455163 | ... T36: =IFERROR(T12/S12-1,"nm") -> 0.05 | AC36: =IFERROR(AC12/Y12-1,"nm") -> 0.069760978 | AD36: =IFERROR(AD12/Z12-1,"nm") -> 0.11173029 | AE36: =IFERROR(AE12/AA12-1,"nm") -> 0.051616731 | AF36: =IFERROR(AF12/AB12-1,"nm") -> 0.17038928 | AG36: =IFERROR(AG12/AC12-1,"nm") -> -0.1610808 | AH36: =IFERROR(AH12/AD12-1,"nm") -> -0.091478697 | AI36: =IFERROR(AI12/AE12-1,"nm") -> -0.092242595 | AJ36: =IFERROR(AJ12/AF12-1,"nm") -> -0.065430752 | ... BX36: =IFERROR(BX12/BT12-1,"nm") -> 0.05
B37: =B13 -> Composite Materials | G37: % | I37: =IFERROR(I13/H13-1,"nm") -> -0.053891536 | J37: =IFERROR(J13/I13-1,"nm") -> -0.075668545 | K37: =IFERROR(K13/J13-1,"nm") -> 0.00955717 | L37: =IFERROR(L13/K13-1,"nm") -> 0.026686657 | M37: =IFERROR(M13/L13-1,"nm") -> 0.092748665 | N37: =IFERROR(N13/M13-1,"nm") -> 0.071774019 | O37: =IFERROR(O13/N13-1,"nm") -> -0.0054178418 | P37: =IFERROR(P13/O13-1,"nm") -> 0.11981345 | ... T37: =IFERROR(T13/S13-1,"nm") -> 0.02 | AC37: =IFERROR(AC13/Y13-1,"nm") -> -0.028512336 | AD37: =IFERROR(AD13/Z13-1,"nm") -> -0.044100467 | AE37: =IFERROR(AE13/AA13-1,"nm") -> -0.16208394 | AF37: =IFERROR(AF13/AB13-1,"nm") -> 0.032121724 | AG37: =IFERROR(AG13/AC13-1,"nm") -> -0.13534063 | AH37: =IFERROR(AH13/AD13-1,"nm") -> -0.21784296 | AI37: =IFERROR(AI13/AE13-1,"nm") -> 0.082210708 | AJ37: =IFERROR(AJ13/AF13-1,"nm") -> -0.0086814087 | ... BX37: =IFERROR(BX13/BT13-1,"nm") -> 0.02
B38: =B14 -> Materials Solution | G38: % | I38: =IFERROR(I14/H14-1,"nm") -> -0.10179852 | J38: =IFERROR(J14/I14-1,"nm") -> -0.21277017 | K38: =IFERROR(K14/J14-1,"nm") -> 0.063358375 | L38: =IFERROR(L14/K14-1,"nm") -> 0.0452297 | M38: =IFERROR(M14/L14-1,"nm") -> 0.0049435972 | N38: =IFERROR(N14/M14-1,"nm") -> 0.036962758 | O38: =IFERROR(O14/N14-1,"nm") -> 0.0089067967 | P38: =IFERROR(P14/O14-1,"nm") -> 0.082278508 | ... T38: =IFERROR(T14/S14-1,"nm") -> 0.03 | AC38: =IFERROR(AC14/Y14-1,"nm") -> -0.032734208 | AD38: =IFERROR(AD14/Z14-1,"nm") -> -0.10448399 | AE38: =IFERROR(AE14/AA14-1,"nm") -> -0.1547347 | AF38: =IFERROR(AF14/AB14-1,"nm") -> -0.11279887 | AG38: =IFERROR(AG14/AC14-1,"nm") -> -0.30315987 | AH38: =IFERROR(AH14/AD14-1,"nm") -> -0.22405392 | AI38: =IFERROR(AI14/AE14-1,"nm") -> -0.16790469 | AJ38: =IFERROR(AJ14/AF14-1,"nm") -> -0.142088 | ... BX38: =IFERROR(BX14/BT14-1,"nm") -> 0.03
B39: =B15 -> Insulation Materials | G39: % | I39: =IFERROR(I15/H15-1,"nm") -> -0.017856323 | J39: =IFERROR(J15/I15-1,"nm") -> -0.13259488 | K39: =IFERROR(K15/J15-1,"nm") -> -0.0070046878 | L39: =IFERROR(L15/K15-1,"nm") -> 0.11167182 | M39: =IFERROR(M15/L15-1,"nm") -> 0.056133158 | N39: =IFERROR(N15/M15-1,"nm") -> 0.041244709 | O39: =IFERROR(O15/N15-1,"nm") -> -0.012010444 | P39: =IFERROR(P15/O15-1,"nm") -> 0.17144226 | ... T39: =IFERROR(T15/S15-1,"nm") -> 0.05 | AC39: =IFERROR(AC15/Y15-1,"nm") -> 0.023128185 | AD39: =IFERROR(AD15/Z15-1,"nm") -> 0.0046202181 | AE39: =IFERROR(AE15/AA15-1,"nm") -> -0.092219987 | AF39: =IFERROR(AF15/AB15-1,"nm") -> 0.0033911078 | AG39: =IFERROR(AG15/AC15-1,"nm") -> -0.15766284 | AH39: =IFERROR(AH15/AD15-1,"nm") -> -0.14661516 | AI39: =IFERROR(AI15/AE15-1,"nm") -> -0.093091984 | AJ39: =IFERROR(AJ15/AF15-1,"nm") -> -0.13387157 | ... BX39: =IFERROR(BX15/BT15-1,"nm") -> 0.05
B40: =B16 -> Other Business | G40: % | I40: =IFERROR(I16/H16-1,"nm") -> 0.04397448 | J40: =IFERROR(J16/I16-1,"nm") -> -0.02715814 | K40: =IFERROR(K16/J16-1,"nm") -> 0.05831641 | L40: =IFERROR(L16/K16-1,"nm") -> 0.038055022 | M40: =IFERROR(M16/L16-1,"nm") -> 0.12526841 | N40: =IFERROR(N16/M16-1,"nm") -> 0.13516978 | O40: =IFERROR(O16/N16-1,"nm") -> 0.046949797 | P40: =IFERROR(P16/O16-1,"nm") -> 0.12695879 | ... T40: =IFERROR(T16/S16-1,"nm") -> 0.13 | AC40: =IFERROR(AC16/Y16-1,"nm") -> -0.021230374 | AD40: =IFERROR(AD16/Z16-1,"nm") -> 0.0010331355 | AE40: =IFERROR(AE16/AA16-1,"nm") -> 0.0041781206 | AF40: =IFERROR(AF16/AB16-1,"nm") -> 0.20933249 | AG40: =IFERROR(AG16/AC16-1,"nm") -> 0.085972935 | AH40: =IFERROR(AH16/AD16-1,"nm") -> -0.11844301 | AI40: =IFERROR(AI16/AE16-1,"nm") -> -0.020453652 | AJ40: =IFERROR(AJ16/AF16-1,"nm") -> -0.041632021 | ... BX40: =IFERROR(BX16/BT16-1,"nm") -> 0.13
B42: Operating profit | G42: =G$10 -> JPY M | H42: =+SUMIF($X$5:$BY$5,H$5,$X42:$BY42) -> 8198 | I42: =+SUMIF($X$5:$BY$5,I$5,$X42:$BY42) -> 8160 | J42: =+SUMIF($X$5:$BY$5,J$5,$X42:$BY42) -> 5964 | K42: =+SUMIF($X$5:$BY$5,K$5,$X42:$BY42) -> 7268 | L42: =+SUMIF($X$5:$BY$5,L$5,$X42:$BY42) -> 4880 | M42: =+SUMIF($X$5:$BY$5,M$5,$X42:$BY42) -> 8387 | N42: =+SUMIF($X$5:$BY$5,N$5,$X42:$BY42) -> 16445 | O42: =+SUMIF($X$5:$BY$5,O$5,$X42:$BY42) -> 20819 | ... T42: =+SUMIF($X$5:$BY$5,T$5,$X42:$BY42) -> 39963.536 | Y42: =Y87 -> 2126 | Z42: =Z87 -> 2266 | AA42: =AA87 -> 2473 | AB42: =AB87 -> 1333 | AC42: =AC87 -> 1698 | AD42: =AD87 -> 1696 | AE42: =AE87 -> 1846 | AF42: =AF87 -> 2920 | ... BE42: =BE87 -> 7943 | BF42: =SUM(BF43:BF49) -> 7496.5965 | BG42: =SUM(BG43:BG49) -> 7539.7792 | BH42: =SUM(BH43:BH49) -> 7964.9171 | BI42: =SUM(BI43:BI49) -> 7895.5525 | BJ42: =SUM(BJ43:BJ49) -> 7877.769 | BK42: =SUM(BK43:BK49) -> 8860.3039 | BL42: =SUM(BL43:BL49) -> 10085.001 | BM42: =SUM(BM43:BM49) -> 8903.9173 | ... BX42: =SUM(BX43:BX49) -> 10466.666
B43: =B11 -> Electronic Materials | G43: =G$10 -> JPY M | H43: =+SUMIF($X$5:$BY$5,H$5,$X43:$BY43) -> 1970.07 | I43: =+SUMIF($X$5:$BY$5,I$5,$X43:$BY43) -> 2831.43 | J43: =+SUMIF($X$5:$BY$5,J$5,$X43:$BY43) -> 2547.22 | K43: =+SUMIF($X$5:$BY$5,K$5,$X43:$BY43) -> 2973.05 | L43: =+SUMIF($X$5:$BY$5,L$5,$X43:$BY43) -> 3373.66 | M43: =+SUMIF($X$5:$BY$5,M$5,$X43:$BY43) -> 5382 | N43: =+SUMIF($X$5:$BY$5,N$5,$X43:$BY43) -> 13880 | O43: =+SUMIF($X$5:$BY$5,O$5,$X43:$BY43) -> 19391 | ... T43: =+SUMIF($X$5:$BY$5,T$5,$X43:$BY43) -> 36494.34 | Y43: =0.97*Y54 -> 541.26 | Z43: =0.97*Z54 -> 481.12 | AA43: =0.97*AA54 -> 538.35 | AB43: =0.97*AB54 -> 409.34 | AC43: =0.97*AC54 -> 574.24 | AD43: =0.97*AD54 -> 615.95 | AE43: =0.97*AE54 -> 696.46 | AF43: =0.97*AF54 -> 944.78 | ... AR43: =0.97*AR54 -> 59.17 | AS43: 755 | AT43: 1316 | AU43: 1098 | AV43: 2213 | AW43: 3545 | AX43: 2865 | AY43: 3496 | AZ43: 3974 | BA43: 4139 | BB43: 4847 | BC43: 4841 | BD43: 5564 | BE43: 7036 | BF43: =Revenue!BF35 -> 7240.8159 | BG43: =Revenue!BG35 -> 6670.3097 | BH43: =Revenue!BH35 -> 7196.3575 | BI43: =Revenue!BI35 -> 7048.888 | BJ43: =Revenue!BJ35 -> 7602.3859 | BK43: =Revenue!BK35 -> 7973.2005 | BL43: =Revenue!BL35 -> 9304.7129 | BM43: =Revenue!BM35 -> 8022.5672 | ... BX43: =Revenue!BX35 -> 9498.0834
B44: =B12 -> Medical | G44: =G$10 -> JPY M | H44: =+SUMIF($X$5:$BY$5,H$5,$X44:$BY44) -> 553.52 | I44: =+SUMIF($X$5:$BY$5,I$5,$X44:$BY44) -> 390.72 | J44: =+SUMIF($X$5:$BY$5,J$5,$X44:$BY44) -> 270.16 | K44: =+SUMIF($X$5:$BY$5,K$5,$X44:$BY44) -> 224.4 | L44: =+SUMIF($X$5:$BY$5,L$5,$X44:$BY44) -> 97.68 | M44: =+SUMIF($X$5:$BY$5,M$5,$X44:$BY44) -> 2389 | N44: =+SUMIF($X$5:$BY$5,N$5,$X44:$BY44) -> 2381 | O44: =+SUMIF($X$5:$BY$5,O$5,$X44:$BY44) -> 2431 | ... T44: =+SUMIF($X$5:$BY$5,T$5,$X44:$BY44) -> 3537.773 | Y44: =Y55*0.88 -> -28.16 | Z44: =Z55*0.88 -> 192.72 | AA44: =AA55*0.88 -> 324.72 | AB44: =AB55*0.88 -> 64.24 | AC44: =AC55*0.88 -> -96.8 | AD44: =AD55*0.88 -> 161.04 | AE44: =AE55*0.88 -> 218.24 | AF44: =AF55*0.88 -> 108.24 | ... AR44: =AR55*0.88 -> -58.08 | AS44: 403 | AT44: 511 | AU44: 808 | AV44: 667 | AW44: 685 | AX44: 679 | AY44: 369 | AZ44: 648 | BA44: 422 | BB44: 664 | BC44: 770 | BD44: 575 | BE44: 705 | BF44: =Revenue!BF36 -> 669.93093 | BG44: =Revenue!BG36 -> 748.7587 | BH44: =Revenue!BH36 -> 741.61165 | BI44: =Revenue!BI36 -> 787.74496 | BJ44: =Revenue!BJ36 -> 703.42748 | BK44: =Revenue!BK36 -> 786.19664 | BL44: =Revenue!BL36 -> 778.69223 | BM44: =Revenue!BM36 -> 827.1322 | ... BX44: =Revenue!BX36 -> 901.4336
B45: =B13 -> Composite Materials | G45: =G$10 -> JPY M | H45: =+SUMIF($X$5:$BY$5,H$5,$X45:$BY45) -> 3937 | I45: =+SUMIF($X$5:$BY$5,I$5,$X45:$BY45) -> 3091 | J45: =+SUMIF($X$5:$BY$5,J$5,$X45:$BY45) -> 2368 | K45: =+SUMIF($X$5:$BY$5,K$5,$X45:$BY45) -> 1733 | L45: =+SUMIF($X$5:$BY$5,L$5,$X45:$BY45) -> -1680 | M45: =+SUMIF($X$5:$BY$5,M$5,$X45:$BY45) -> -731 | N45: =+SUMIF($X$5:$BY$5,N$5,$X45:$BY45) -> -900 | O45: =+SUMIF($X$5:$BY$5,O$5,$X45:$BY45) -> -122 | ... T45: =+SUMIF($X$5:$BY$5,T$5,$X45:$BY45) -> -57.462009 | Y45: =Y53 -> 1054 | Z45: =Z53 -> 1126 | AA45: =AA53 -> 974 | AB45: =AB53 -> 783 | AC45: =AC53 -> 659 | AD45: =AD53 -> 396 | AE45: =AE53 -> 659 | AF45: =AF53 -> 1377 | ... AR45: =AR53 -> -1566 | AS45: -340 | AT45: -11 | AU45: 32 | AV45: -412 | AW45: -368 | AX45: -300 | AY45: -63 | AZ45: -169 | BA45: -15 | BB45: -122 | BC45: -48 | BD45: 63 | BE45: 0 | BF45: =Revenue!BF37 -> -113.4776 | BG45: =Revenue!BG37 -> -41.632 | BH45: =Revenue!BH37 -> 69.722 | BI45: =Revenue!BI37 -> 2.298 | BJ45: =Revenue!BJ37 -> -111.09133 | BK45: =Revenue!BK37 -> -39.53056 | BL45: =Revenue!BL37 -> 71.94026 | BM45: =Revenue!BM37 -> 3.87596 | ... BX45: =Revenue!BX37 -> 76.601877
B46: =B14 -> Materials Solution | G46: =G$10 -> JPY M | H46: =+SUMIF($X$5:$BY$5,H$5,$X46:$BY46) -> 542.61 | I46: =+SUMIF($X$5:$BY$5,I$5,$X46:$BY46) -> 724.65 | J46: =+SUMIF($X$5:$BY$5,J$5,$X46:$BY46) -> 640.82 | K46: =+SUMIF($X$5:$BY$5,K$5,$X46:$BY46) -> 735.55 | L46: =+SUMIF($X$5:$BY$5,L$5,$X46:$BY46) -> 813.26 | M46: =+SUMIF($X$5:$BY$5,M$5,$X46:$BY46) -> 824 | N46: =+SUMIF($X$5:$BY$5,N$5,$X46:$BY46) -> 839 | O46: =+SUMIF($X$5:$BY$5,O$5,$X46:$BY46) -> 588 | ... T46: =+SUMIF($X$5:$BY$5,T$5,$X46:$BY46) -> 579.51773 | Y46: =Y55*0.12+Y54*0.23+Y51 -> 124.5 | Z46: =Z55*0.12+Z54*0.23+Z51 -> 140.36 | AA46: =AA55*0.12+AA54*0.23+AA51 -> 171.93 | AB46: =AB55*0.12+AB54*0.23+AB51 -> 105.82 | AC46: =AC55*0.12+AC54*0.23+AC51 -> 122.96 | AD46: =AD55*0.12+AD54*0.23+AD51 -> 168.01 | AE46: =AE55*0.12+AE54*0.23+AE51 -> 194.9 | AF46: =AF55*0.12+AF54*0.23+AF51 -> 238.78 | ... AR46: =AR55*0.12+AR54*0.23+AR51 -> 6.11 | AS46: 222 | AT46: 206 | AU46: 224 | AV46: 172 | AW46: 159 | AX46: 109 | AY46: 294 | AZ46: 277 | BA46: 109 | BB46: 115 | BC46: 162 | BD46: 202 | BE46: 222 | BF46: =Revenue!BF38 -> 119.091 | BG46: =Revenue!BG38 -> 133.295 | BH46: =Revenue!BH38 -> 131.758 | BI46: =Revenue!BI38 -> 134.6725 | BJ46: =Revenue!BJ38 -> 122.66373 | BK46: =Revenue!BK38 -> 137.29385 | BL46: =Revenue!BL38 -> 135.71074 | BM46: =Revenue!BM38 -> 138.71268 | ... BX46: =Revenue!BX38 -> 148.29479
B47: =B15 -> Insulation Materials | G47: =G$10 -> JPY M | H47: =+SUMIF($X$5:$BY$5,H$5,$X47:$BY47) -> 1381.08 | I47: =+SUMIF($X$5:$BY$5,I$5,$X47:$BY47) -> 1984.92 | J47: =+SUMIF($X$5:$BY$5,J$5,$X47:$BY47) -> 1785.68 | K47: =+SUMIF($X$5:$BY$5,K$5,$X47:$BY47) -> 2084.2 | L47: =+SUMIF($X$5:$BY$5,L$5,$X47:$BY47) -> 2365.04 | M47: =+SUMIF($X$5:$BY$5,M$5,$X47:$BY47) -> 914 | N47: =+SUMIF($X$5:$BY$5,N$5,$X47:$BY47) -> 693 | O47: =+SUMIF($X$5:$BY$5,O$5,$X47:$BY47) -> 202 | ... T47: =+SUMIF($X$5:$BY$5,T$5,$X47:$BY47) -> 1059.0081 | Y47: =Y54*0.68 -> 379.44 | Z47: =Z54*0.68 -> 337.28 | AA47: =AA54*0.68 -> 377.4 | AB47: =AB54*0.68 -> 286.96 | AC47: =AC54*0.68 -> 402.56 | AD47: =AD54*0.68 -> 431.8 | AE47: =AE54*0.68 -> 488.24 | AF47: =AF54*0.68 -> 662.32 | ... AR47: =AR54*0.68 -> 41.48 | AS47: -26 | AT47: 267 | AU47: 469 | AV47: 204 | AW47: 166 | AX47: 186 | AY47: 382 | AZ47: -41 | BA47: -50 | BB47: -159 | BC47: 303 | BD47: 108 | BE47: 251 | BF47: =Revenue!BF39 -> -102.735 | BG47: =Revenue!BG39 -> 364.89 | BH47: =Revenue!BH39 -> 163.74 | BI47: =Revenue!BI39 -> 272.995 | BJ47: =Revenue!BJ39 -> -81.16675 | BK47: =Revenue!BK39 -> 388.6145 | BL47: =Revenue!BL39 -> 185.107 | BM47: =Revenue!BM39 -> 296.08975 | ... BX47: =Revenue!BX39 -> 255.83444
B48: =B16 -> Other Business | G48: =G$10 -> JPY M | H48: =+SUMIF($X$5:$BY$5,H$5,$X48:$BY48) -> 328.54 | I48: =+SUMIF($X$5:$BY$5,I$5,$X48:$BY48) -> 594.53 | J48: =+SUMIF($X$5:$BY$5,J$5,$X48:$BY48) -> 400.41 | K48: =+SUMIF($X$5:$BY$5,K$5,$X48:$BY48) -> 570.9 | L48: =+SUMIF($X$5:$BY$5,L$5,$X48:$BY48) -> 244.33 | M48: =+SUMIF($X$5:$BY$5,M$5,$X48:$BY48) -> 447 | N48: =+SUMIF($X$5:$BY$5,N$5,$X48:$BY48) -> 409 | O48: =+SUMIF($X$5:$BY$5,O$5,$X48:$BY48) -> 488 | ... T48: =+SUMIF($X$5:$BY$5,T$5,$X48:$BY48) -> 1253.8205 | Y48: =0.03*Y54+0.09*Y55+Y57 -> 115.86 | Z48: =0.03*Z54+0.09*Z55+Z57 -> 72.59 | AA48: =0.03*AA54+0.09*AA55+AA57 -> 57.86 | AB48: =0.03*AB54+0.09*AB55+AB57 -> 82.23 | AC48: =0.03*AC54+0.09*AC55+AC57 -> 137.86 | AD48: =0.03*AD54+0.09*AD55+AD57 -> 186.52 | AE48: =0.03*AE54+0.09*AE55+AE57 -> 214.86 | AF48: =0.03*AF54+0.09*AF55+AF57 -> 55.29 | ... AR48: =0.03*AR54+0.09*AR55+AR57 -> 50.89 | AS48: 134 | AT48: 106 | AU48: 102 | AV48: 105 | AW48: 75 | AX48: 138 | AY48: 110 | AZ48: 86 | BA48: 112 | BB48: 167 | BC48: 156 | BD48: 53 | BE48: 213 | BF48: =Revenue!BF40 -> 193.9532 | BG48: =Revenue!BG40 -> 186.5404 | BH48: =Revenue!BH40 -> 197.298 | BI48: =Revenue!BI40 -> 216.056 | BJ48: =Revenue!BJ40 -> 219.16712 | BK48: =Revenue!BK40 -> 210.79065 | BL48: =Revenue!BL40 -> 222.94674 | BM48: =Revenue!BM40 -> 244.14328 | ... BX48: =Revenue!BX40 -> 321.68918
B49: Adjustments | G49: =G$10 -> JPY M | H49: =+SUMIF($X$5:$BY$5,H$5,$X49:$BY49) -> -514.82 | I49: =+SUMIF($X$5:$BY$5,I$5,$X49:$BY49) -> -1457.25 | J49: =+SUMIF($X$5:$BY$5,J$5,$X49:$BY49) -> -2048.29 | K49: =+SUMIF($X$5:$BY$5,K$5,$X49:$BY49) -> -1053.1 | L49: =+SUMIF($X$5:$BY$5,L$5,$X49:$BY49) -> -333.97 | M49: =+SUMIF($X$5:$BY$5,M$5,$X49:$BY49) -> -839 | N49: =+SUMIF($X$5:$BY$5,N$5,$X49:$BY49) -> -858 | O49: =+SUMIF($X$5:$BY$5,O$5,$X49:$BY49) -> -2160 | ... T49: =+SUMIF($X$5:$BY$5,T$5,$X49:$BY49) -> -2903.4612 | Y49: =Y42-SUM(Y43:Y48) -> -60.9 | Z49: =Z42-SUM(Z43:Z48) -> -84.07 | AA49: =AA42-SUM(AA43:AA48) -> 28.74 | AB49: =AB42-SUM(AB43:AB48) -> -398.59 | AC49: =AC42-SUM(AC43:AC48) -> -101.82 | AD49: =AD42-SUM(AD43:AD48) -> -263.32 | AE49: =AE42-SUM(AE43:AE48) -> -625.7 | AF49: =AF42-SUM(AF43:AF48) -> -466.41 | ... AR49: =AR42-SUM(AR43:AR48) -> 501.43 | AS49: -263 | AT49: -163 | AU49: -147 | AV49: -266 | AW49: -357 | AX49: -238 | AY49: -122 | AZ49: -141 | BA49: -417 | BB49: -358 | BC49: -706 | BD49: -679 | BE49: -486 | BF49: =Revenue!BF41 -> -510.98198 | BG49: =Revenue!BG41 -> -522.38257 | BH49: =Revenue!BH41 -> -535.5701 | BI49: =Revenue!BI41 -> -567.10193 | BJ49: =Revenue!BJ41 -> -577.61709 | BK49: =Revenue!BK41 -> -596.26166 | BL49: =Revenue!BL41 -> -614.10924 | BM49: =Revenue!BM41 -> -628.60378 | ... BX49: =Revenue!BX41 -> -735.27083
B51: Operating profit (before) | G51: =G$10 -> JPY M | H51: =+SUMIF($X$5:$BY$5,H$5,$X51:$BY51) -> 0 | I51: =+SUMIF($X$5:$BY$5,I$5,$X51:$BY51) -> 0 | J51: =+SUMIF($X$5:$BY$5,J$5,$X51:$BY51) -> 0 | K51: =+SUMIF($X$5:$BY$5,K$5,$X51:$BY51) -> 0 | L51: =+SUMIF($X$5:$BY$5,L$5,$X51:$BY51) -> 0 | M51: =+SUMIF($X$5:$BY$5,M$5,$X51:$BY51) -> 0 | N51: =+SUMIF($X$5:$BY$5,N$5,$X51:$BY51) -> 0 | O51: =+SUMIF($X$5:$BY$5,O$5,$X51:$BY51) -> 0 | ... T51: =+SUMIF($X$5:$BY$5,T$5,$X51:$BY51) -> 0
B52: Textile | G52: =G$10 -> JPY M | H52: =+SUMIF($X$5:$BY$5,H$5,$X52:$BY52) -> -373 | I52: =+SUMIF($X$5:$BY$5,I$5,$X52:$BY52) -> -221 | J52: =+SUMIF($X$5:$BY$5,J$5,$X52:$BY52) -> -718 | K52: =+SUMIF($X$5:$BY$5,K$5,$X52:$BY52) -> -131 | L52: =+SUMIF($X$5:$BY$5,L$5,$X52:$BY52) -> 95 | M52: =+SUMIF($X$5:$BY$5,M$5,$X52:$BY52) -> 24 | N52: =+SUMIF($X$5:$BY$5,N$5,$X52:$BY52) -> 0 | O52: =+SUMIF($X$5:$BY$5,O$5,$X52:$BY52) -> 0 | ... T52: =+SUMIF($X$5:$BY$5,T$5,$X52:$BY52) -> 0 | Y52: -80 | Z52: -81 | AA52: -63 | AB52: -149 | AC52: -89 | AD52: -26 | AE52: -15 | AF52: -91 | AG52: -148 | AH52: -271 | AI52: -145 | AJ52: -154 | AK52: -19 | AL52: -28 | AM52: -21 | AN52: -63 | AO52: 42 | AP52: 23 | AQ52: 59 | AR52: -29 | AS52: 36 | AT52: 13 | AU52: 6 | AV52: -31
B53: Glass Fiber Yarn | G53: =G$10 -> JPY M | H53: =+SUMIF($X$5:$BY$5,H$5,$X53:$BY53) -> 3937 | I53: =+SUMIF($X$5:$BY$5,I$5,$X53:$BY53) -> 3091 | J53: =+SUMIF($X$5:$BY$5,J$5,$X53:$BY53) -> 2368 | K53: =+SUMIF($X$5:$BY$5,K$5,$X53:$BY53) -> 1733 | L53: =+SUMIF($X$5:$BY$5,L$5,$X53:$BY53) -> -1680 | M53: =+SUMIF($X$5:$BY$5,M$5,$X53:$BY53) -> -458 | N53: =+SUMIF($X$5:$BY$5,N$5,$X53:$BY53) -> 0 | O53: =+SUMIF($X$5:$BY$5,O$5,$X53:$BY53) -> 0 | ... T53: =+SUMIF($X$5:$BY$5,T$5,$X53:$BY53) -> 0 | Y53: 1054 | Z53: 1126 | AA53: 974 | AB53: 783 | AC53: 659 | AD53: 396 | AE53: 659 | AF53: 1377 | AG53: 1064 | AH53: 312 | AI53: 481 | AJ53: 511 | AK53: 339 | AL53: 851 | AM53: 573 | AN53: -30 | AO53: 428 | AP53: -60 | AQ53: -482 | AR53: -1566 | AS53: -270 | AT53: -86 | AU53: -195 | AV53: 93
B54: Glass Fiber Cloth | G54: =G$10 -> JPY M | H54: =+SUMIF($X$5:$BY$5,H$5,$X54:$BY54) -> 2031 | I54: =+SUMIF($X$5:$BY$5,I$5,$X54:$BY54) -> 2919 | J54: =+SUMIF($X$5:$BY$5,J$5,$X54:$BY54) -> 2626 | K54: =+SUMIF($X$5:$BY$5,K$5,$X54:$BY54) -> 3065 | L54: =+SUMIF($X$5:$BY$5,L$5,$X54:$BY54) -> 3478 | M54: =+SUMIF($X$5:$BY$5,M$5,$X54:$BY54) -> 5550 | N54: =+SUMIF($X$5:$BY$5,N$5,$X54:$BY54) -> 0 | O54: =+SUMIF($X$5:$BY$5,O$5,$X54:$BY54) -> 0 | ... T54: =+SUMIF($X$5:$BY$5,T$5,$X54:$BY54) -> 0 | Y54: 558 | Z54: 496 | AA54: 555 | AB54: 422 | AC54: 592 | AD54: 635 | AE54: 718 | AF54: 974 | AG54: 940 | AH54: 489 | AI54: 498 | AJ54: 699 | AK54: 721 | AL54: 696 | AM54: 605 | AN54: 1043 | AO54: 1416 | AP54: 1252 | AQ54: 749 | AR54: 61 | AS54: 758 | AT54: 1329 | AU54: 1474 | AV54: 1989
B55: Glass Fiber for Industrial Materials | G55: =G$10 -> JPY M | H55: =+SUMIF($X$5:$BY$5,H$5,$X55:$BY55) -> 629 | I55: =+SUMIF($X$5:$BY$5,I$5,$X55:$BY55) -> 444 | J55: =+SUMIF($X$5:$BY$5,J$5,$X55:$BY55) -> 307 | K55: =+SUMIF($X$5:$BY$5,K$5,$X55:$BY55) -> 255 | L55: =+SUMIF($X$5:$BY$5,L$5,$X55:$BY55) -> 111 | M55: =+SUMIF($X$5:$BY$5,M$5,$X55:$BY55) -> 1188 | N55: =+SUMIF($X$5:$BY$5,N$5,$X55:$BY55) -> 0 | O55: =+SUMIF($X$5:$BY$5,O$5,$X55:$BY55) -> 0 | ... T55: =+SUMIF($X$5:$BY$5,T$5,$X55:$BY55) -> 0 | Y55: -32 | Z55: 219 | AA55: 369 | AB55: 73 | AC55: -110 | AD55: 183 | AE55: 248 | AF55: 123 | AG55: 22 | AH55: 40 | AI55: 217 | AJ55: 28 | AK55: -43 | AL55: 123 | AM55: 256 | AN55: -81 | AO55: -20 | AP55: 110 | AQ55: 87 | AR55: -66 | AS55: 11 | AT55: 350 | AU55: 538 | AV55: 289
B56: Life Science | G56: =G$10 -> JPY M | H56: =+SUMIF($X$5:$BY$5,H$5,$X56:$BY56) -> 2644 | I56: =+SUMIF($X$5:$BY$5,I$5,$X56:$BY56) -> 2878 | J56: =+SUMIF($X$5:$BY$5,J$5,$X56:$BY56) -> 2147 | K56: =+SUMIF($X$5:$BY$5,K$5,$X56:$BY56) -> 2560 | L56: =+SUMIF($X$5:$BY$5,L$5,$X56:$BY56) -> 2791 | M56: =+SUMIF($X$5:$BY$5,M$5,$X56:$BY56) -> 2955 | N56: =+SUMIF($X$5:$BY$5,N$5,$X56:$BY56) -> 0 | O56: =+SUMIF($X$5:$BY$5,O$5,$X56:$BY56) -> 0 | ... T56: =+SUMIF($X$5:$BY$5,T$5,$X56:$BY56) -> 0 | Y56: 706 | Z56: 732 | AA56: 783 | AB56: 423 | AC56: 741 | AD56: 905 | AE56: 436 | AF56: 796 | AG56: 535 | AH56: 545 | AI56: 463 | AJ56: 604 | AK56: 681 | AL56: 742 | AM56: 427 | AN56: 710 | AO56: 869 | AP56: 634 | AQ56: 794 | AR56: 494 | AS56: 554 | AT56: 631 | AU56: 972 | AV56: 798
B57: Others | G57: =G$10 -> JPY M | H57: =+SUMIF($X$5:$BY$5,H$5,$X57:$BY57) -> 211 | I57: =+SUMIF($X$5:$BY$5,I$5,$X57:$BY57) -> 467 | J57: =+SUMIF($X$5:$BY$5,J$5,$X57:$BY57) -> 294 | K57: =+SUMIF($X$5:$BY$5,K$5,$X57:$BY57) -> 456 | L57: =+SUMIF($X$5:$BY$5,L$5,$X57:$BY57) -> 130 | M57: =+SUMIF($X$5:$BY$5,M$5,$X57:$BY57) -> 182 | N57: =+SUMIF($X$5:$BY$5,N$5,$X57:$BY57) -> 0 | O57: =+SUMIF($X$5:$BY$5,O$5,$X57:$BY57) -> 0 | ... T57: =+SUMIF($X$5:$BY$5,T$5,$X57:$BY57) -> 0 | Y57: 102 | Z57: 38 | AA57: 8 | AB57: 63 | AC57: 130 | AD57: 151 | AE57: 171 | AF57: 15 | AG57: 63 | AH57: 23 | AI57: 94 | AJ57: 114 | AK57: 80 | AL57: 178 | AM57: 98 | AN57: 100 | AO57: 37 | AP57: 22 | AQ57: 16 | AR57: 55 | AS57: 81 | AT57: 41 | AU57: 21 | AV57: 39
B59: OPM | G59: % | H59: =IFERROR(H42/H10,"nm") -> 0.099620862 | I59: =IFERROR(I42/I10,"nm") -> 0.095191433 | J59: =IFERROR(J42/J10,"nm") -> 0.075755459 | K59: =IFERROR(K42/K10,"nm") -> 0.086471309 | L59: =IFERROR(L42/L10,"nm") -> 0.05575295 | M59: =IFERROR(M42/M10,"nm") -> 0.089938125 | N59: =IFERROR(N42/N10,"nm") -> 0.15082313 | O59: =IFERROR(O42/O10,"nm") -> 0.17609047 | ... T59: =IFERROR(T42/T10,"nm") -> 0.20646153 | Y59: =IFERROR(Y42/Y10,"nm") -> 0.10396088 | Z59: =IFERROR(Z42/Z10,"nm") -> 0.10763823 | AA59: =IFERROR(AA42/AA10,"nm") -> 0.11407353 | AB59: =IFERROR(AB42/AB10,"nm") -> 0.069750406 | AC59: =IFERROR(AC42/AC10,"nm") -> 0.082343242 | AD59: =IFERROR(AD42/AD10,"nm") -> 0.076599973 | AE59: =IFERROR(AE42/AE10,"nm") -> 0.086670736 | AF59: =IFERROR(AF42/AF10,"nm") -> 0.13480449 | ... BX59: =IFERROR(BX42/BX10,"nm") -> 0.21352676
B60: =B43 -> Electronic Materials | G60: % | H60: =IFERROR(H43/H11,"nm") -> 0.099564107 | I60: =IFERROR(I43/I11,"nm") -> 0.11978196 | J60: =IFERROR(J43/J11,"nm") -> 0.1089876 | K60: =IFERROR(K43/K11,"nm") -> 0.11713337 | L60: =IFERROR(L43/L11,"nm") -> 0.13210198 | M60: =IFERROR(M43/M11,"nm") -> 0.18052618 | N60: =IFERROR(N43/N11,"nm") -> 0.33927306 | O60: =IFERROR(O43/O11,"nm") -> 0.39360601 | ... T60: =IFERROR(T43/T11,"nm") -> 0.38549322 | Y60: =IFERROR(Y43/Y11,"nm") -> 0.11011515 | Z60: =IFERROR(Z43/Z11,"nm") -> 0.096818465 | AA60: =IFERROR(AA43/AA11,"nm") -> 0.10269445 | AB60: =IFERROR(AB43/AB11,"nm") -> 0.087841202 | AC60: =IFERROR(AC43/AC11,"nm") -> 0.11409271 | AD60: =IFERROR(AD43/AD11,"nm") -> 0.1004755 | AE60: =IFERROR(AE43/AE11,"nm") -> 0.11445992 | AF60: =IFERROR(AF43/AF11,"nm") -> 0.1478529 | ... BX60: =IFERROR(BX43/BX11,"nm") -> 0.3926934
B61: =B44 -> Medical | G61: % | H61: =IFERROR(H44/H12,"nm") -> 0.045939235 | I61: =IFERROR(I44/I12,"nm") -> 0.029497741 | J61: =IFERROR(J44/J12,"nm") -> 0.022740741 | K61: =IFERROR(K44/K12,"nm") -> 0.016047829 | L61: =IFERROR(L44/L12,"nm") -> 0.0066233069 | M61: =IFERROR(M44/M12,"nm") -> 0.18805574 | N61: =IFERROR(N44/N12,"nm") -> 0.17503492 | O61: =IFERROR(O44/O12,"nm") -> 0.17552347 | ... T61: =IFERROR(T44/T12,"nm") -> 0.19649903 | Y61: =IFERROR(Y44/Y12,"nm") -> -0.0088938299 | Z61: =IFERROR(Z44/Z12,"nm") -> 0.061019783 | AA61: =IFERROR(AA44/AA12,"nm") -> 0.10946307 | AB61: =IFERROR(AB44/AB12,"nm") -> 0.023292916 | AC61: =IFERROR(AC44/AC12,"nm") -> -0.028578852 | AD61: =IFERROR(AD44/AD12,"nm") -> 0.045864662 | AE61: =IFERROR(AE44/AE12,"nm") -> 0.069957687 | AF61: =IFERROR(AF44/AF12,"nm") -> 0.033533261 | ... BX61: =IFERROR(BX44/BX12,"nm") -> 0.19649903
B62: =B45 -> Composite Materials | G62: % | H62: =IFERROR(H45/H13,"nm") -> 0.31019149 | I62: =IFERROR(I45/I13,"nm") -> 0.2574083 | J62: =IFERROR(J45/J13,"nm") -> 0.21334256 | K62: =IFERROR(K45/K13,"nm") -> 0.15465482 | L62: =IFERROR(L45/L13,"nm") -> -0.14602804 | M62: =IFERROR(M45/M13,"nm") -> -0.058146564 | N62: =IFERROR(N45/N13,"nm") -> -0.066795309 | O62: =IFERROR(O45/O13,"nm") -> -0.0091037982 | ... T62: =IFERROR(T45/T13,"nm") -> -0.0035031617 | Y62: =IFERROR(Y45/Y13,"nm") -> 0.32439553 | Z62: =IFERROR(Z45/Z13,"nm") -> 0.34255744 | AA62: =IFERROR(AA45/AA13,"nm") -> 0.29365654 | AB62: =IFERROR(AB45/AB13,"nm") -> 0.27578191 | AC62: =IFERROR(AC45/AC13,"nm") -> 0.20877687 | AD62: =IFERROR(AD45/AD13,"nm") -> 0.12603116 | AE62: =IFERROR(AE45/AE13,"nm") -> 0.2371186 | AF62: =IFERROR(AF45/AF13,"nm") -> 0.46990172 | ... BX62: =IFERROR(BX45/BX13,"nm") -> 0.018955728
B63: =B46 -> Materials Solution | G63: % | H63: =IFERROR(H46/H14,"nm") -> 0.0471196 | I63: =IFERROR(I46/I14,"nm") -> 0.07005971 | J63: =IFERROR(J46/J14,"nm") -> 0.078699968 | K63: =IFERROR(K46/K14,"nm") -> 0.084951498 | L63: =IFERROR(L46/L14,"nm") -> 0.08986209 | M63: =IFERROR(M46/M14,"nm") -> 0.090600924 | N63: =IFERROR(N46/N14,"nm") -> 0.088961934 | O63: =IFERROR(O46/O14,"nm") -> 0.061797162 | ... T63: =IFERROR(T46/T14,"nm") -> 0.05 | Y63: =IFERROR(Y46/Y14,"nm") -> 0.043016771 | Z63: =IFERROR(Z46/Z14,"nm") -> 0.048379814 | AA63: =IFERROR(AA46/AA14,"nm") -> 0.055817079 | AB63: =IFERROR(AB46/AB14,"nm") -> 0.040084548 | AC63: =IFERROR(AC46/AC14,"nm") -> 0.043922443 | AD63: =IFERROR(AD46/AD14,"nm") -> 0.064666985 | AE63: =IFERROR(AE46/AE14,"nm") -> 0.074857314 | AF63: =IFERROR(AF46/AF14,"nm") -> 0.1019495 | ... BX63: =IFERROR(BX46/BX14,"nm") -> 0.05
B64: =B47 -> Insulation Materials | G64: % | H64: =IFERROR(H47/H15,"nm") -> 0.093229286 | I64: =IFERROR(I47/I15,"nm") -> 0.13642737 | J64: =IFERROR(J47/J15,"nm") -> 0.14149469 | K64: =IFERROR(K47/K15,"nm") -> 0.16631396 | L64: =IFERROR(L47/L15,"nm") -> 0.16976619 | M64: =IFERROR(M47/M15,"nm") -> 0.062121257 | N64: =IFERROR(N47/N15,"nm") -> 0.045234987 | O64: =IFERROR(O47/O15,"nm") -> 0.013345666 | ... T64: =IFERROR(T47/T15,"nm") -> 0.049137161 | Y64: =IFERROR(Y47/Y15,"nm") -> 0.10936887 | Z64: =IFERROR(Z47/Z15,"nm") -> 0.091665127 | AA64: =IFERROR(AA47/AA15,"nm") -> 0.09305835 | AB64: =IFERROR(AB47/AB15,"nm") -> 0.079502638 | AC64: =IFERROR(AC47/AC15,"nm") -> 0.11340996 | AD64: =IFERROR(AD47/AD15,"nm") -> 0.11681383 | AE64: =IFERROR(AE47/AE15,"nm") -> 0.13261914 | AF64: =IFERROR(AF47/AF15,"nm") -> 0.18287646 | ... BX64: =IFERROR(BX47/BX15,"nm") -> 0.049252499
B66: Mix
B67: =B43 -> Electronic Materials | G67: % | H67: =IFERROR(H43/H$42,"nm") -> 0.24031105 | I67: =IFERROR(I43/I$42,"nm") -> 0.34698897 | J67: =IFERROR(J43/J$42,"nm") -> 0.42709926 | K67: =IFERROR(K43/K$42,"nm") -> 0.40906026 | L67: =IFERROR(L43/L$42,"nm") -> 0.69132377 | M67: =IFERROR(M43/M$42,"nm") -> 0.6417074 | N67: =IFERROR(N43/N$42,"nm") -> 0.84402554 | O67: =IFERROR(O43/O$42,"nm") -> 0.93140881 | ... T67: =IFERROR(T43/T$42,"nm") -> 0.91319096 | Y67: =IFERROR(Y43/Y$42,"nm") -> 0.25459078 | Z67: =IFERROR(Z43/Z$42,"nm") -> 0.21232127 | AA67: =IFERROR(AA43/AA$42,"nm") -> 0.21769106 | AB67: =IFERROR(AB43/AB$42,"nm") -> 0.30708177 | AC67: =IFERROR(AC43/AC$42,"nm") -> 0.3381861 | AD67: =IFERROR(AD43/AD$42,"nm") -> 0.36317807 | AE67: =IFERROR(AE43/AE$42,"nm") -> 0.37728061 | AF67: =IFERROR(AF43/AF$42,"nm") -> 0.32355479 | ... BX67: =IFERROR(BX43/BX$42,"nm") -> 0.90746022
B68: =B44 -> Medical | G68: % | H68: =IFERROR(H44/H$42,"nm") -> 0.067518907 | I68: =IFERROR(I44/I$42,"nm") -> 0.047882353 | J68: =IFERROR(J44/J$42,"nm") -> 0.045298457 | K68: =IFERROR(K44/K$42,"nm") -> 0.030875069 | L68: =IFERROR(L44/L$42,"nm") -> 0.020016393 | M68: =IFERROR(M44/M$42,"nm") -> 0.28484559 | N68: =IFERROR(N44/N$42,"nm") -> 0.14478565 | O68: =IFERROR(O44/O$42,"nm") -> 0.11676834 | ... T68: =IFERROR(T44/T$42,"nm") -> 0.088525024 | Y68: =IFERROR(Y44/Y$42,"nm") -> -0.013245532 | Z68: =IFERROR(Z44/Z$42,"nm") -> 0.085048544 | AA68: =IFERROR(AA44/AA$42,"nm") -> 0.13130611 | AB68: =IFERROR(AB44/AB$42,"nm") -> 0.048192048 | AC68: =IFERROR(AC44/AC$42,"nm") -> -0.057008245 | AD68: =IFERROR(AD44/AD$42,"nm") -> 0.09495283 | AE68: =IFERROR(AE44/AE$42,"nm") -> 0.11822319 | AF68: =IFERROR(AF44/AF$42,"nm") -> 0.037068493 | ... BX68: =IFERROR(BX44/BX$42,"nm") -> 0.086124231
B69: =B45 -> Composite Materials | G69: % | H69: =IFERROR(H45/H$42,"nm") -> 0.48023908 | I69: =IFERROR(I45/I$42,"nm") -> 0.37879902 | J69: =IFERROR(J45/J$42,"nm") -> 0.39704896 | K69: =IFERROR(K45/K$42,"nm") -> 0.23844249 | L69: =IFERROR(L45/L$42,"nm") -> -0.3442623 | M69: =IFERROR(M45/M$42,"nm") -> -0.087158698 | N69: =IFERROR(N45/N$42,"nm") -> -0.054727881 | O69: =IFERROR(O45/O$42,"nm") -> -0.0058600317 | ... T69: =IFERROR(T45/T$42,"nm") -> -0.001437861 | Y69: =IFERROR(Y45/Y$42,"nm") -> 0.4957667 | Z69: =IFERROR(Z45/Z$42,"nm") -> 0.49691086 | AA69: =IFERROR(AA45/AA$42,"nm") -> 0.39385362 | AB69: =IFERROR(AB45/AB$42,"nm") -> 0.58739685 | AC69: =IFERROR(AC45/AC$42,"nm") -> 0.38810365 | AD69: =IFERROR(AD45/AD$42,"nm") -> 0.23349057 | AE69: =IFERROR(AE45/AE$42,"nm") -> 0.35698808 | AF69: =IFERROR(AF45/AF$42,"nm") -> 0.47157534 | ... BX69: =IFERROR(BX45/BX$42,"nm") -> 0.0073186509
B70: =B46 -> Materials Solution | G70: % | H70: =IFERROR(H46/H$42,"nm") -> 0.066188095 | I70: =IFERROR(I46/I$42,"nm") -> 0.088805147 | J70: =IFERROR(J46/J$42,"nm") -> 0.10744802 | K70: =IFERROR(K46/K$42,"nm") -> 0.10120391 | L70: =IFERROR(L46/L$42,"nm") -> 0.16665164 | M70: =IFERROR(M46/M$42,"nm") -> 0.098247287 | N70: =IFERROR(N46/N$42,"nm") -> 0.051018547 | O70: =IFERROR(O46/O$42,"nm") -> 0.028243431 | ... T70: =IFERROR(T46/T$42,"nm") -> 0.014501163 | Y70: =IFERROR(Y46/Y$42,"nm") -> 0.058560677 | Z70: =IFERROR(Z46/Z$42,"nm") -> 0.061941748 | AA70: =IFERROR(AA46/AA$42,"nm") -> 0.069522847 | AB70: =IFERROR(AB46/AB$42,"nm") -> 0.079384846 | AC70: =IFERROR(AC46/AC$42,"nm") -> 0.072414605 | AD70: =IFERROR(AD46/AD$42,"nm") -> 0.0990625 | AE70: =IFERROR(AE46/AE$42,"nm") -> 0.10557963 | AF70: =IFERROR(AF46/AF$42,"nm") -> 0.081773973 | ... BX70: =IFERROR(BX46/BX$42,"nm") -> 0.014168292
B71: =B47 -> Insulation Materials | G71: % | H71: =IFERROR(H47/H$42,"nm") -> 0.16846548 | I71: =IFERROR(I47/I$42,"nm") -> 0.24325 | J71: =IFERROR(J47/J$42,"nm") -> 0.29940979 | K71: =IFERROR(K47/K$42,"nm") -> 0.2867639 | L71: =IFERROR(L47/L$42,"nm") -> 0.48463934 | M71: =IFERROR(M47/M$42,"nm") -> 0.10897818 | N71: =IFERROR(N47/N$42,"nm") -> 0.042140468 | O71: =IFERROR(O47/O$42,"nm") -> 0.0097026754 | ... T71: =IFERROR(T47/T$42,"nm") -> 0.026499358 | Y71: =IFERROR(Y47/Y$42,"nm") -> 0.17847601 | Z71: =IFERROR(Z47/Z$42,"nm") -> 0.14884378 | AA71: =IFERROR(AA47/AA$42,"nm") -> 0.15260817 | AB71: =IFERROR(AB47/AB$42,"nm") -> 0.21527382 | AC71: =IFERROR(AC47/AC$42,"nm") -> 0.23707892 | AD71: =IFERROR(AD47/AD$42,"nm") -> 0.25459906 | AE71: =IFERROR(AE47/AE$42,"nm") -> 0.26448537 | AF71: =IFERROR(AF47/AF$42,"nm") -> 0.22682192 | ... BX71: =IFERROR(BX47/BX$42,"nm") -> 0.024442782
B73: Y/Y | I73: =IFERROR(I42/H42-1,"nm") -> -0.0046352769 | J73: =IFERROR(J42/I42-1,"nm") -> -0.26911765 | K73: =IFERROR(K42/J42-1,"nm") -> 0.2186452 | L73: =IFERROR(L42/K42-1,"nm") -> -0.32856357 | M73: =IFERROR(M42/L42-1,"nm") -> 0.71864754 | N73: =IFERROR(N42/M42-1,"nm") -> 0.96077262 | O73: =IFERROR(O42/N42-1,"nm") -> 0.2659775 | P73: =IFERROR(P42/O42-1,"nm") -> 0.48634866 | ... T73: =IFERROR(T42/S42-1,"nm") -> 0.042739542
B74: =B43 -> Electronic Materials | G74: % | I74: =IFERROR(I43/H43-1,"nm") -> 0.43722304 | J74: =IFERROR(J43/I43-1,"nm") -> -0.10037684 | K74: =IFERROR(K43/J43-1,"nm") -> 0.16717441 | L74: =IFERROR(L43/K43-1,"nm") -> 0.13474715 | M74: =IFERROR(M43/L43-1,"nm") -> 0.59530006 | N74: =IFERROR(N43/M43-1,"nm") -> 1.5789669 | O74: =IFERROR(O43/N43-1,"nm") -> 0.39704611 | P74: =IFERROR(P43/O43-1,"nm") -> 0.45136832 | ... T74: =IFERROR(T43/S43-1,"nm") -> 0.039138145 | AC74: =IFERROR(AC43/Y43-1,"nm") -> 0.0609319 | AD74: =IFERROR(AD43/Z43-1,"nm") -> 0.28024194 | AE74: =IFERROR(AE43/AA43-1,"nm") -> 0.29369369 | AF74: =IFERROR(AF43/AB43-1,"nm") -> 1.3080569 | AG74: =IFERROR(AG43/AC43-1,"nm") -> 0.58783784 | AH74: =IFERROR(AH43/AD43-1,"nm") -> -0.22992126 | AI74: =IFERROR(AI43/AE43-1,"nm") -> -0.30640669 | AJ74: =IFERROR(AJ43/AF43-1,"nm") -> -0.28234086 | ... BX74: =IFERROR(BX43/BT43-1,"nm") -> 0.036844126
B75: =B44 -> Medical | G75: % | I75: =IFERROR(I44/H44-1,"nm") -> -0.29411765 | J75: =IFERROR(J44/I44-1,"nm") -> -0.30855856 | K75: =IFERROR(K44/J44-1,"nm") -> -0.16938111 | L75: =IFERROR(L44/K44-1,"nm") -> -0.56470588 | M75: =IFERROR(M44/L44-1,"nm") -> 23.457412 | N75: =IFERROR(N44/M44-1,"nm") -> -0.0033486815 | O75: =IFERROR(O44/N44-1,"nm") -> 0.02099958 | P75: =IFERROR(P44/O44-1,"nm") -> 0.17865129 | ... T75: =IFERROR(T44/S44-1,"nm") -> 0.05 | AC75: =IFERROR(AC44/Y44-1,"nm") -> 2.4375 | AD75: =IFERROR(AD44/Z44-1,"nm") -> -0.16438356 | AE75: =IFERROR(AE44/AA44-1,"nm") -> -0.32791328 | AF75: =IFERROR(AF44/AB44-1,"nm") -> 0.68493151 | AG75: =IFERROR(AG44/AC44-1,"nm") -> -1.2 | AH75: =IFERROR(AH44/AD44-1,"nm") -> -0.78142077 | AI75: =IFERROR(AI44/AE44-1,"nm") -> -0.125 | AJ75: =IFERROR(AJ44/AF44-1,"nm") -> -0.77235772 | ... BX75: =IFERROR(BX44/BT44-1,"nm") -> 0.05
B76: =B45 -> Composite Materials | G76: % | I76: =IFERROR(I45/H45-1,"nm") -> -0.21488443 | J76: =IFERROR(J45/I45-1,"nm") -> -0.23390489 | K76: =IFERROR(K45/J45-1,"nm") -> -0.26815878 | L76: =IFERROR(L45/K45-1,"nm") -> -1.9694172 | M76: =IFERROR(M45/L45-1,"nm") -> -0.56488095 | N76: =IFERROR(N45/M45-1,"nm") -> 0.23119015 | O76: =IFERROR(O45/N45-1,"nm") -> -0.86444444 | P76: =IFERROR(P45/O45-1,"nm") -> -0.30010164 | ... T76: =IFERROR(T45/S45-1,"nm") -> -0.10067389 | AC76: =IFERROR(AC45/Y45-1,"nm") -> -0.37476281 | AD76: =IFERROR(AD45/Z45-1,"nm") -> -0.64831261 | AE76: =IFERROR(AE45/AA45-1,"nm") -> -0.32340862 | AF76: =IFERROR(AF45/AB45-1,"nm") -> 0.75862069 | AG76: =IFERROR(AG45/AC45-1,"nm") -> 0.61456753 | AH76: =IFERROR(AH45/AD45-1,"nm") -> -0.21212121 | AI76: =IFERROR(AI45/AE45-1,"nm") -> -0.27010622 | AJ76: =IFERROR(AJ45/AF45-1,"nm") -> -0.62890341 | ... BX76: =IFERROR(BX45/BT45-1,"nm") -> 0.021125076
B77: =B46 -> Materials Solution | G77: % | I77: =IFERROR(I46/H46-1,"nm") -> 0.33548958 | J77: =IFERROR(J46/I46-1,"nm") -> -0.11568343 | K77: =IFERROR(K46/J46-1,"nm") -> 0.14782622 | L77: =IFERROR(L46/K46-1,"nm") -> 0.10564883 | M77: =IFERROR(M46/L46-1,"nm") -> 0.013206109 | N77: =IFERROR(N46/M46-1,"nm") -> 0.018203883 | O77: =IFERROR(O46/N46-1,"nm") -> -0.29916567 | P77: =IFERROR(P46/O46-1,"nm") -> 0.030857143 | ... T77: =IFERROR(T46/S46-1,"nm") -> 0.03 | AC77: =IFERROR(AC46/Y46-1,"nm") -> -0.012369478 | AD77: =IFERROR(AD46/Z46-1,"nm") -> 0.19699345 | AE77: =IFERROR(AE46/AA46-1,"nm") -> 0.13360088 | AF77: =IFERROR(AF46/AB46-1,"nm") -> 1.2564733 | AG77: =IFERROR(AG46/AC46-1,"nm") -> 0.77976578 | AH77: =IFERROR(AH46/AD46-1,"nm") -> -0.30200583 | AI77: =IFERROR(AI46/AE46-1,"nm") -> -0.27870703 | AJ77: =IFERROR(AJ46/AF46-1,"nm") -> -0.31263087 | ... BX77: =IFERROR(BX46/BT46-1,"nm") -> 0.03
B78: =B47 -> Insulation Materials | G78: % | I78: =IFERROR(I47/H47-1,"nm") -> 0.43722304 | J78: =IFERROR(J47/I47-1,"nm") -> -0.10037684 | K78: =IFERROR(K47/J47-1,"nm") -> 0.16717441 | L78: =IFERROR(L47/K47-1,"nm") -> 0.13474715 | M78: =IFERROR(M47/L47-1,"nm") -> -0.61353719 | N78: =IFERROR(N47/M47-1,"nm") -> -0.24179431 | O78: =IFERROR(O47/N47-1,"nm") -> -0.70851371 | P78: =IFERROR(P47/O47-1,"nm") -> 2.3509653 | ... T78: =IFERROR(T47/S47-1,"nm") -> 0.10730991 | AC78: =IFERROR(AC47/Y47-1,"nm") -> 0.0609319 | AD78: =IFERROR(AD47/Z47-1,"nm") -> 0.28024194 | AE78: =IFERROR(AE47/AA47-1,"nm") -> 0.29369369 | AF78: =IFERROR(AF47/AB47-1,"nm") -> 1.3080569 | AG78: =IFERROR(AG47/AC47-1,"nm") -> 0.58783784 | AH78: =IFERROR(AH47/AD47-1,"nm") -> -0.22992126 | AI78: =IFERROR(AI47/AE47-1,"nm") -> -0.30640669 | AJ78: =IFERROR(AJ47/AF47-1,"nm") -> -0.28234086 | ... BX78: =IFERROR(BX47/BT47-1,"nm") -> 0.10703172
A80: x | B80: INCOME STATEMENT
B82: Revenue | G82: =G$10 -> JPY M | H82: =+SUMIF($X$5:$BY$5,H$5,$X82:$BY82) -> 82292 | I82: =+SUMIF($X$5:$BY$5,I$5,$X82:$BY82) -> 85722 | J82: =+SUMIF($X$5:$BY$5,J$5,$X82:$BY82) -> 78727 | K82: =+SUMIF($X$5:$BY$5,K$5,$X82:$BY82) -> 84051 | L82: =+SUMIF($X$5:$BY$5,L$5,$X82:$BY82) -> 87529 | M82: =+SUMIF($X$5:$BY$5,M$5,$X82:$BY82) -> 93253 | N82: =+SUMIF($X$5:$BY$5,N$5,$X82:$BY82) -> 109035 | O82: =+SUMIF($X$5:$BY$5,O$5,$X82:$BY82) -> 118229 | ... T82: =+SUMIF($X$5:$BY$5,T$5,$X82:$BY82) -> 193564.08 | Y82: 20450 | Z82: 21052 | AA82: 21679 | AB82: 19111 | AC82: 20621 | AD82: 22141 | AE82: 21299 | AF82: 21661 | AG82: 19584 | AH82: 18696 | AI82: 20097 | AJ82: 20350 | AK82: 20518 | AL82: 20568 | AM82: 21034 | AN82: 21931 | AO82: 23827 | AP82: 23210 | AQ82: 21725 | AR82: 18767 | AS82: 20297 | AT82: 22437 | AU82: 25307 | AV82: 25212 | AW82: 26115 | AX82: 26936 | AY82: 28469 | AZ82: 27515 | BA82: 28231 | BB82: 29181 | BC82: 30182 | BD82: 30635 | BE82: 34033 | BF82: =BF10 -> 34065.465 | BG82: =BG10 -> 34825.505 | BH82: =BH10 -> 35704.673 | BI82: =BI10 -> 37806.795 | BJ82: =BJ10 -> 38507.806 | BK82: =BK10 -> 39750.777 | BL82: =BL10 -> 40940.616 | BM82: =BM10 -> 41906.919 | ... BX82: =BX10 -> 49018.055
B83: COGS | G83: =G$10 -> JPY M | H83: =+SUMIF($X$5:$BY$5,H$5,$X83:$BY83) -> -54632 | I83: =+SUMIF($X$5:$BY$5,I$5,$X83:$BY83) -> -57628 | J83: =+SUMIF($X$5:$BY$5,J$5,$X83:$BY83) -> -53066 | K83: =+SUMIF($X$5:$BY$5,K$5,$X83:$BY83) -> -55823 | L83: =+SUMIF($X$5:$BY$5,L$5,$X83:$BY83) -> -60323 | M83: =+SUMIF($X$5:$BY$5,M$5,$X83:$BY83) -> -62639 | N83: =+SUMIF($X$5:$BY$5,N$5,$X83:$BY83) -> -68657 | O83: =+SUMIF($X$5:$BY$5,O$5,$X83:$BY83) -> -70653 | ... T83: =+SUMIF($X$5:$BY$5,T$5,$X83:$BY83) -> -111016.45 | V83: =(O83/J83)^(1/(O$5-J$5))-1 -> 0.058919268 | W83: =(T83/O83)^(1/(T$5-O$5))-1 -> 0.094589669 | Y83: =Y84-Y82 -> -13528 | Z83: =Z84-Z82 -> -13953 | AA83: =AA84-AA82 -> -14230 | AB83: =AB84-AB82 -> -12921 | AC83: =AC84-AC82 -> -13922 | AD83: =AD84-AD82 -> -15403 | AE83: =AE84-AE82 -> -14408 | AF83: =AF84-AF82 -> -13895 | ... BE83: =BE84-BE82 -> -19119 | BF83: =-BF82+BF84 -> -19074.467 | BG83: =-BG82+BG84 -> -19624.114 | BH83: =-BH82+BH84 -> -19884.728 | BI83: =-BI82+BI84 -> -21593.748 | BJ83: =-BJ82+BJ84 -> -22158.32 | BK83: =-BK82+BK84 -> -22145.302 | BL83: =-BL82+BL84 -> -21848.68 | BM83: =-BM82+BM84 -> -23783.479 | ... BX83: =-BX82+BX84 -> -27767.417
B84: Gross profit | G84: =G$10 -> JPY M | H84: =+SUMIF($X$5:$BY$5,H$5,$X84:$BY84) -> 27660 | I84: =+SUMIF($X$5:$BY$5,I$5,$X84:$BY84) -> 28094 | J84: =+SUMIF($X$5:$BY$5,J$5,$X84:$BY84) -> 25661 | K84: =+SUMIF($X$5:$BY$5,K$5,$X84:$BY84) -> 28228 | L84: =+SUMIF($X$5:$BY$5,L$5,$X84:$BY84) -> 27206 | M84: =+SUMIF($X$5:$BY$5,M$5,$X84:$BY84) -> 30614 | N84: =+SUMIF($X$5:$BY$5,N$5,$X84:$BY84) -> 40378 | O84: =+SUMIF($X$5:$BY$5,O$5,$X84:$BY84) -> 47576 | ... T84: =+SUMIF($X$5:$BY$5,T$5,$X84:$BY84) -> 82547.634 | Y84: 6922 | Z84: 7099 | AA84: 7449 | AB84: 6190 | AC84: 6699 | AD84: 6738 | AE84: 6891 | AF84: 7766 | AG84: 6926 | AH84: 5764 | AI84: 6318 | AJ84: 6653 | AK84: 6826 | AL84: 7263 | AM84: 7074 | AN84: 7065 | AO84: 8187 | AP84: 7550 | AQ84: 6792 | AR84: 4677 | AS84: 6432 | AT84: 7658 | AU84: 8342 | AV84: 8182 | AW84: 9568 | AX84: 9611 | AY84: 10581 | AZ84: 10618 | BA84: 10739 | BB84: 11465 | BC84: 12492 | BD84: 12880 | BE84: 14914 | BF84: =BF87-BF85-BF86 -> 14990.999 | BG84: =BG87-BG85-BG86 -> 15201.39 | BH84: =BH87-BH85-BH86 -> 15819.945 | BI84: =BI87-BI85-BI86 -> 16213.047 | BJ84: =BJ87-BJ85-BJ86 -> 16349.486 | BK84: =BK87-BK85-BK86 -> 17605.475 | BL84: =BL87-BL85-BL86 -> 19091.936 | BM84: =BM87-BM85-BM86 -> 18123.439 | ... BX84: =BX87-BX85-BX86 -> 21250.639
B85: SG&A | G85: =G$10 -> JPY M | H85: =+SUMIF($X$5:$BY$5,H$5,$X85:$BY85) -> -19461 | I85: =+SUMIF($X$5:$BY$5,I$5,$X85:$BY85) -> -19933 | J85: =+SUMIF($X$5:$BY$5,J$5,$X85:$BY85) -> -19697 | K85: =+SUMIF($X$5:$BY$5,K$5,$X85:$BY85) -> -20959 | L85: =+SUMIF($X$5:$BY$5,L$5,$X85:$BY85) -> -22326 | M85: =+SUMIF($X$5:$BY$5,M$5,$X85:$BY85) -> -22226 | N85: =+SUMIF($X$5:$BY$5,N$5,$X85:$BY85) -> -23933 | O85: =+SUMIF($X$5:$BY$5,O$5,$X85:$BY85) -> -26757 | ... T85: =+SUMIF($X$5:$BY$5,T$5,$X85:$BY85) -> -42584.098 | Y85: -4795 | Z85: -4834 | AA85: -4975 | AB85: -4857 | AC85: -5001 | AD85: -5042 | AE85: -5044 | AF85: -4846 | AG85: -4877 | AH85: -4909 | AI85: -4950 | AJ85: -4961 | AK85: -5132 | AL85: -5024 | AM85: -5351 | AN85: -5452 | AO85: -5574 | AP85: -5566 | AQ85: -5543 | AR85: -5643 | AS85: -5546 | AT85: -5425 | AU85: -5756 | AV85: -5499 | AW85: -5661 | AX85: -6172 | AY85: -6116 | AZ85: -5984 | BA85: -6440 | BB85: -6309 | BC85: -7014 | BD85: -6994 | BE85: -6971 | BF85: =-BF133 -> -7494.4024 | BG85: =-BG133 -> -7661.611 | BH85: =-BH133 -> -7855.0281 | BI85: =-BI133 -> -8317.495 | BJ85: =-BJ133 -> -8471.7174 | BK85: =-BK133 -> -8745.171 | BL85: =-BL133 -> -9006.9355 | BM85: =-BM133 -> -9219.5221 | ... BX85: =-BX133 -> -10783.972
B86: Others | G86: =G$10 -> JPY M | H86: =+SUMIF($X$5:$BY$5,H$5,$X86:$BY86) -> -1 | I86: =+SUMIF($X$5:$BY$5,I$5,$X86:$BY86) -> -1 | J86: =+SUMIF($X$5:$BY$5,J$5,$X86:$BY86) -> 0 | K86: =+SUMIF($X$5:$BY$5,K$5,$X86:$BY86) -> -1 | L86: =+SUMIF($X$5:$BY$5,L$5,$X86:$BY86) -> 0 | M86: =+SUMIF($X$5:$BY$5,M$5,$X86:$BY86) -> -1 | N86: =+SUMIF($X$5:$BY$5,N$5,$X86:$BY86) -> 0 | O86: =+SUMIF($X$5:$BY$5,O$5,$X86:$BY86) -> 0 | ... T86: =+SUMIF($X$5:$BY$5,T$5,$X86:$BY86) -> 0 | Y86: =Y87-Y84-Y85 -> -1 | Z86: =Z87-Z84-Z85 -> 1 | AA86: =AA87-AA84-AA85 -> -1 | AB86: =AB87-AB84-AB85 -> 0 | AC86: =AC87-AC84-AC85 -> 0 | AD86: =AD87-AD84-AD85 -> 0 | AE86: =AE87-AE84-AE85 -> -1 | AF86: =AF87-AF84-AF85 -> 0 | ... BE86: =BE87-BE84-BE85 -> 0 | BF86: =BE86 -> 0 | BG86: =BF86 -> 0 | BH86: =BG86 -> 0 | BI86: =BH86 -> 0 | BJ86: =BI86 -> 0 | BK86: =BJ86 -> 0 | BL86: =BK86 -> 0 | BM86: =BL86 -> 0 | ... BX86: =BW86 -> 0
B87: EBIT | G87: =G$10 -> JPY M | H87: =+SUMIF($X$5:$BY$5,H$5,$X87:$BY87) -> 8198 | I87: =+SUMIF($X$5:$BY$5,I$5,$X87:$BY87) -> 8160 | J87: =+SUMIF($X$5:$BY$5,J$5,$X87:$BY87) -> 5964 | K87: =+SUMIF($X$5:$BY$5,K$5,$X87:$BY87) -> 7268 | L87: =+SUMIF($X$5:$BY$5,L$5,$X87:$BY87) -> 4880 | M87: =+SUMIF($X$5:$BY$5,M$5,$X87:$BY87) -> 8387 | N87: =+SUMIF($X$5:$BY$5,N$5,$X87:$BY87) -> 16445 | O87: =+SUMIF($X$5:$BY$5,O$5,$X87:$BY87) -> 20819 | ... T87: =+SUMIF($X$5:$BY$5,T$5,$X87:$BY87) -> 39963.536 | Y87: 2126 | Z87: 2266 | AA87: 2473 | AB87: 1333 | AC87: 1698 | AD87: 1696 | AE87: 1846 | AF87: 2920 | AG87: 2049 | AH87: 855 | AI87: 1368 | AJ87: 1692 | AK87: 1693 | AL87: 2239 | AM87: 1723 | AN87: 1613 | AO87: 2613 | AP87: 1984 | AQ87: 1248 | AR87: -965 | AS87: 885 | AT87: 2233 | AU87: 2586 | AV87: 2683 | AW87: 3907 | AX87: 3438 | AY87: 4466 | AZ87: 4634 | BA87: 4298 | BB87: 5156 | BC87: 5479 | BD87: 5886 | BE87: 7943 | BF87: =BF42 -> 7496.5965 | BG87: =BG42 -> 7539.7792 | BH87: =BH42 -> 7964.9171 | BI87: =BI42 -> 7895.5525 | BJ87: =BJ42 -> 7877.769 | BK87: =BK42 -> 8860.3039 | BL87: =BL42 -> 10085.001 | BM87: =BM42 -> 8903.9173 | ... BX87: =BX42 -> 10466.666
C88: Dividend income | G88: =G$10 -> JPY M | H88: =+SUMIF($X$5:$BY$5,H$5,$X88:$BY88) -> 578 | I88: =+SUMIF($X$5:$BY$5,I$5,$X88:$BY88) -> 560 | J88: =+SUMIF($X$5:$BY$5,J$5,$X88:$BY88) -> 446 | K88: =+SUMIF($X$5:$BY$5,K$5,$X88:$BY88) -> 459 | L88: =+SUMIF($X$5:$BY$5,L$5,$X88:$BY88) -> 484 | M88: =+SUMIF($X$5:$BY$5,M$5,$X88:$BY88) -> 495 | N88: =+SUMIF($X$5:$BY$5,N$5,$X88:$BY88) -> 628 | O88: =+SUMIF($X$5:$BY$5,O$5,$X88:$BY88) -> 689 | ... T88: =+SUMIF($X$5:$BY$5,T$5,$X88:$BY88) -> 679 | Y88: 328 | Z88: 8 | AA88: 235 | AB88: 7 | AC88: 335 | AD88: 4 | AE88: 212 | AF88: 9 | AG88: 233 | AH88: 3 | AI88: 204 | AJ88: 6 | AK88: 210 | AL88: 26 | AM88: 214 | AN88: 9 | AO88: 252 | AP88: 19 | AQ88: 206 | AR88: 7 | AS88: 248 | AT88: 2 | AU88: 234 | AV88: 11 | AW88: 290 | AX88: 12 | AY88: 308 | AZ88: 18 | BA88: 340 | BB88: 26 | BC88: 305 | BD88: 18 | BE88: 330 | BF88: =BB88 -> 26 | BG88: =BC88 -> 305 | BH88: =BD88 -> 18 | BI88: =BE88 -> 330 | BJ88: =BF88 -> 26 | BK88: =BG88 -> 305 | BL88: =BH88 -> 18 | BM88: =BI88 -> 330 | ... BX88: =BT88 -> 18
C89: Interest expenses | G89: =G$10 -> JPY M | H89: =+SUMIF($X$5:$BY$5,H$5,$X89:$BY89) -> -208 | I89: =+SUMIF($X$5:$BY$5,I$5,$X89:$BY89) -> -266 | J89: =+SUMIF($X$5:$BY$5,J$5,$X89:$BY89) -> -250 | K89: =+SUMIF($X$5:$BY$5,K$5,$X89:$BY89) -> -219 | L89: =+SUMIF($X$5:$BY$5,L$5,$X89:$BY89) -> -248 | M89: =+SUMIF($X$5:$BY$5,M$5,$X89:$BY89) -> -412 | N89: =+SUMIF($X$5:$BY$5,N$5,$X89:$BY89) -> -559 | O89: =+SUMIF($X$5:$BY$5,O$5,$X89:$BY89) -> -798 | ... T89: =+SUMIF($X$5:$BY$5,T$5,$X89:$BY89) -> -720.52665 | Y89: -48 | Z89: -52 | AA89: -56 | AB89: -52 | AC89: -56 | AD89: -68 | AE89: -72 | AF89: -70 | AG89: -62 | AH89: -63 | AI89: -63 | AJ89: -62 | AK89: -54 | AL89: -54 | AM89: -50 | AN89: -61 | AO89: -56 | AP89: -57 | AQ89: -63 | AR89: -72 | AS89: -73 | AT89: -130 | AU89: -98 | AV89: -111 | AW89: -124 | AX89: -131 | AY89: -152 | AZ89: -152 | BA89: -177 | BB89: -216 | BC89: -216 | BD89: -189 | BE89: -194 | BF89: ='D&E'!BF76 -> -197.072 | BG89: ='D&E'!BG76 -> -183.65732 | BH89: ='D&E'!BH76 -> -183.24356 | BI89: ='D&E'!BI76 -> -182.86704 | BJ89: ='D&E'!BJ76 -> -182.52441 | BK89: ='D&E'!BK76 -> -182.21261 | BL89: ='D&E'!BL76 -> -181.92888 | BM89: ='D&E'!BM76 -> -181.81308 | ... BX89: ='D&E'!BX76 -> -179.98514
B90: Others | G90: =G$10 -> JPY M | H90: =+SUMIF($X$5:$BY$5,H$5,$X90:$BY90) -> 1262 | I90: =+SUMIF($X$5:$BY$5,I$5,$X90:$BY90) -> -862 | J90: =+SUMIF($X$5:$BY$5,J$5,$X90:$BY90) -> 5053 | K90: =+SUMIF($X$5:$BY$5,K$5,$X90:$BY90) -> 1171 | L90: =+SUMIF($X$5:$BY$5,L$5,$X90:$BY90) -> -455 | M90: =+SUMIF($X$5:$BY$5,M$5,$X90:$BY90) -> 613 | N90: =+SUMIF($X$5:$BY$5,N$5,$X90:$BY90) -> 1007 | O90: =+SUMIF($X$5:$BY$5,O$5,$X90:$BY90) -> 37919 | ... T90: =+SUMIF($X$5:$BY$5,T$5,$X90:$BY90) -> 0 | Y90: =Y91-Y87-Y88-Y89 -> -109 | Z90: =Z91-Z87-Z88-Z89 -> 816 | AA90: =AA91-AA87-AA88-AA89 -> -788 | AB90: =AB91-AB87-AB88-AB89 -> 1343 | AC90: =AC91-AC87-AC88-AC89 -> -434 | AD90: =AD91-AD87-AD88-AD89 -> -252 | AE90: =AE91-AE87-AE88-AE89 -> 56 | AF90: =AF91-AF87-AF88-AF89 -> -232 | ... BE90: =BE91-BE87-BE88-BE89 -> 279 | BF90: 0 | BG90: 0 | BH90: 0 | BI90: 0 | BJ90: 0 | BK90: 0 | BL90: 0 | BM90: 0 | BN90: 0 | BO90: 0 | BP90: 0 | BQ90: 0 | BR90: 0 | BS90: 0 | BT90: 0 | BU90: 0 | BV90: 0 | BW90: 0 | BX90: 0
B91: Profit before income tax | G91: =G$10 -> JPY M | H91: =+SUMIF($X$5:$BY$5,H$5,$X91:$BY91) -> 9830 | I91: =+SUMIF($X$5:$BY$5,I$5,$X91:$BY91) -> 7592 | J91: =+SUMIF($X$5:$BY$5,J$5,$X91:$BY91) -> 11213 | K91: =+SUMIF($X$5:$BY$5,K$5,$X91:$BY91) -> 8679 | L91: =+SUMIF($X$5:$BY$5,L$5,$X91:$BY91) -> 4661 | M91: =+SUMIF($X$5:$BY$5,M$5,$X91:$BY91) -> 9083 | N91: =+SUMIF($X$5:$BY$5,N$5,$X91:$BY91) -> 17521 | O91: =+SUMIF($X$5:$BY$5,O$5,$X91:$BY91) -> 58629 | ... T91: =+SUMIF($X$5:$BY$5,T$5,$X91:$BY91) -> 39922.009 | Y91: 2297 | Z91: 3038 | AA91: 1864 | AB91: 2631 | AC91: 1543 | AD91: 1380 | AE91: 2042 | AF91: 2627 | AG91: 12194 | AH91: 35 | AI91: -1260 | AJ91: 244 | AK91: 1383 | AL91: 2119 | AM91: 3526 | AN91: 1651 | AO91: 6617 | AP91: 3245 | AQ91: 532 | AR91: -5733 | AS91: 1845 | AT91: 2228 | AU91: 2443 | AV91: 2567 | AW91: 4719 | AX91: 2980 | AY91: 5421 | AZ91: 4401 | BA91: 4315 | BB91: 4929 | BC91: 40185 | BD91: 9200 | BE91: 8358 | BF91: =SUM(BF87:BF90) -> 7325.5245 | BG91: =SUM(BG87:BG90) -> 7661.1219 | BH91: =SUM(BH87:BH90) -> 7799.6735 | BI91: =SUM(BI87:BI90) -> 8042.6855 | BJ91: =SUM(BJ87:BJ90) -> 7721.2446 | BK91: =SUM(BK87:BK90) -> 8983.0913 | BL91: =SUM(BL87:BL90) -> 9921.0718 | BM91: =SUM(BM87:BM90) -> 9052.1042 | ... BX91: =SUM(BX87:BX90) -> 10304.681
B92: Income tax | G92: =G$10 -> JPY M | H92: =+SUMIF($X$5:$BY$5,H$5,$X92:$BY92) -> -1813 | I92: =+SUMIF($X$5:$BY$5,I$5,$X92:$BY92) -> -1651 | J92: =+SUMIF($X$5:$BY$5,J$5,$X92:$BY92) -> -2935 | K92: =+SUMIF($X$5:$BY$5,K$5,$X92:$BY92) -> -1998 | L92: =+SUMIF($X$5:$BY$5,L$5,$X92:$BY92) -> -1738 | M92: =+SUMIF($X$5:$BY$5,M$5,$X92:$BY92) -> -1775 | N92: =+SUMIF($X$5:$BY$5,N$5,$X92:$BY92) -> -4356 | O92: =+SUMIF($X$5:$BY$5,O$5,$X92:$BY92) -> -16300 | ... T92: =+SUMIF($X$5:$BY$5,T$5,$X92:$BY92) -> -11577.383 | Y92: =Y93-Y91 -> -719 | Z92: =Z93-Z91 -> -65 | AA92: =AA93-AA91 -> -821 | AB92: =AB93-AB91 -> -208 | AC92: =AC93-AC91 -> -553 | AD92: =AD93-AD91 -> -248 | AE92: =AE93-AE91 -> -214 | AF92: =AF93-AF91 -> -636 | ... BE92: =BE93-BE91 -> -2337 | BF92: =-BF142 -> -2124.4021 | BG92: =-BG142 -> -2221.7253 | BH92: =-BH142 -> -2261.9053 | BI92: =-BI142 -> -2332.3788 | BJ92: =-BJ142 -> -2239.1609 | BK92: =-BK142 -> -2605.0965 | BL92: =-BL142 -> -2877.1108 | BM92: =-BM142 -> -2625.1102 | ... BX92: =-BX142 -> -2988.3576
B93: Net profit | G93: =G$10 -> JPY M | H93: =+SUMIF($X$5:$BY$5,H$5,$X93:$BY93) -> 8017 | I93: =+SUMIF($X$5:$BY$5,I$5,$X93:$BY93) -> 5941 | J93: =+SUMIF($X$5:$BY$5,J$5,$X93:$BY93) -> 8278 | K93: =+SUMIF($X$5:$BY$5,K$5,$X93:$BY93) -> 6681 | L93: =+SUMIF($X$5:$BY$5,L$5,$X93:$BY93) -> 2923 | M93: =+SUMIF($X$5:$BY$5,M$5,$X93:$BY93) -> 7308 | N93: =+SUMIF($X$5:$BY$5,N$5,$X93:$BY93) -> 13165 | O93: =+SUMIF($X$5:$BY$5,O$5,$X93:$BY93) -> 42329 | ... T93: =+SUMIF($X$5:$BY$5,T$5,$X93:$BY93) -> 28344.627 | Y93: 1578 | Z93: 2973 | AA93: 1043 | AB93: 2423 | AC93: 990 | AD93: 1132 | AE93: 1828 | AF93: 1991 | AG93: 8625 | AH93: 261 | AI93: -769 | AJ93: 161 | AK93: 856 | AL93: 1558 | AM93: 2691 | AN93: 1576 | AO93: 4827 | AP93: 2760 | AQ93: 378 | AR93: -5042 | AS93: 1056 | AT93: 2442 | AU93: 1866 | AV93: 1944 | AW93: 3315 | AX93: 2248 | AY93: 4058 | AZ93: 3544 | BA93: 3256 | BB93: 3764 | BC93: 28433 | BD93: 6876 | BE93: 6021 | BF93: =SUM(BF91:BF92) -> 5201.1224 | BG93: =SUM(BG91:BG92) -> 5439.3965 | BH93: =SUM(BH91:BH92) -> 5537.7682 | BI93: =SUM(BI91:BI92) -> 5710.3067 | BJ93: =SUM(BJ91:BJ92) -> 5482.0837 | BK93: =SUM(BK91:BK92) -> 6377.9948 | BL93: =SUM(BL91:BL92) -> 7043.9609 | BM93: =SUM(BM91:BM92) -> 6426.994 | ... BX93: =SUM(BX91:BX92) -> 7316.3237
B94: NCI | G94: =G$10 -> JPY M | H94: =+SUMIF($X$5:$BY$5,H$5,$X94:$BY94) -> -33 | I94: =+SUMIF($X$5:$BY$5,I$5,$X94:$BY94) -> -170 | J94: =+SUMIF($X$5:$BY$5,J$5,$X94:$BY94) -> -178 | K94: =+SUMIF($X$5:$BY$5,K$5,$X94:$BY94) -> -161 | L94: =+SUMIF($X$5:$BY$5,L$5,$X94:$BY94) -> -150 | M94: =+SUMIF($X$5:$BY$5,M$5,$X94:$BY94) -> -12 | N94: =+SUMIF($X$5:$BY$5,N$5,$X94:$BY94) -> -328 | O94: =+SUMIF($X$5:$BY$5,O$5,$X94:$BY94) -> -559 | ... T94: =+SUMIF($X$5:$BY$5,T$5,$X94:$BY94) -> -736.96029 | Y94: -9 | Z94: -7 | AA94: -10 | AB94: -7 | AC94: -8 | AD94: -48 | AE94: -66 | AF94: -48 | AG94: -55 | AH94: -43 | AI94: -52 | AJ94: -28 | AK94: -40 | AL94: -31 | AM94: -40 | AN94: -50 | AO94: -39 | AP94: -74 | AQ94: -40 | AR94: 3 | AS94: 2 | AT94: 16 | AU94: -17 | AV94: -13 | AW94: -63 | AX94: -89 | AY94: -47 | AZ94: -129 | BA94: -109 | BB94: -33 | BC94: -200 | BD94: -217 | BE94: -224 | BF94: =-'D&E'!BF120 -> -135.22918 | BG94: =-'D&E'!BG120 -> -141.42431 | BH94: =-'D&E'!BH120 -> -143.98197 | BI94: =-'D&E'!BI120 -> -148.46797 | BJ94: =-'D&E'!BJ120 -> -142.53418 | BK94: =-'D&E'!BK120 -> -165.82787 | BL94: =-'D&E'!BL120 -> -183.14298 | BM94: =-'D&E'!BM120 -> -167.10184 | ... BX94: =-'D&E'!BX120 -> -190.22442
B95: Net income to shareholders | G95: =G$10 -> JPY M | H95: =+SUMIF($X$5:$BY$5,H$5,$X95:$BY95) -> 7984 | I95: =+SUMIF($X$5:$BY$5,I$5,$X95:$BY95) -> 5771 | J95: =+SUMIF($X$5:$BY$5,J$5,$X95:$BY95) -> 8100 | K95: =+SUMIF($X$5:$BY$5,K$5,$X95:$BY95) -> 6520 | L95: =+SUMIF($X$5:$BY$5,L$5,$X95:$BY95) -> 2773 | M95: =+SUMIF($X$5:$BY$5,M$5,$X95:$BY95) -> 7296 | N95: =+SUMIF($X$5:$BY$5,N$5,$X95:$BY95) -> 12837 | O95: =+SUMIF($X$5:$BY$5,O$5,$X95:$BY95) -> 41770 | ... T95: =+SUMIF($X$5:$BY$5,T$5,$X95:$BY95) -> 27607.666 | Y95: =SUM(Y93:Y94) -> 1569 | Z95: =SUM(Z93:Z94) -> 2966 | AA95: =SUM(AA93:AA94) -> 1033 | AB95: =SUM(AB93:AB94) -> 2416 | AC95: =SUM(AC93:AC94) -> 982 | AD95: =SUM(AD93:AD94) -> 1084 | AE95: =SUM(AE93:AE94) -> 1762 | AF95: =SUM(AF93:AF94) -> 1943 | ... BX95: =SUM(BX93:BX94) -> 7126.0993
B97: Shares outstanding | G97: # M | H97: =IFERROR(H95/H98,"nm") -> 194.01244 | I97: =IFERROR(I95/I98,"nm") -> 194.00928 | J97: =IFERROR(J95/J98,"nm") -> 193.99339 | K97: =IFERROR(K95/K98,"nm") -> 194.00143 | L97: =IFERROR(L95/L98,"nm") -> 187.51691 | M97: =IFERROR(M95/M98,"nm") -> 182.04501 | N97: =IFERROR(N95/N98,"nm") -> 182.0283 | O97: =IFERROR(O95/O98,"nm") -> 182.02974 | ... T97: =IFERROR(T95/T98,"nm") -> 182.03062 | Y97: =IFERROR(Y95/Y98,"nm") -> 194.03908 | Z97: =IFERROR(Z95/Z98,"nm") -> 194.00837 | AA97: =IFERROR(AA95/AA98,"nm") -> 194.02705 | AB97: =IFERROR(AB95/AB98,"nm") -> 193.9939 | AC97: =IFERROR(AC95/AC98,"nm") -> 194.07115 | AD97: =IFERROR(AD95/AD98,"nm") -> 193.98712 | AE97: =IFERROR(AE95/AE98,"nm") -> 193.96742 | AF97: =IFERROR(AF95/AF98,"nm") -> 194.02836 | ... BE97: =IFERROR(BE95/BE98,"nm") -> 182.00942 | BF97: ='D&E'!BF84 -> 182.03062 | BG97: ='D&E'!BG84 -> 182.03062 | BH97: ='D&E'!BH84 -> 182.03062 | BI97: ='D&E'!BI84 -> 182.03062 | BJ97: ='D&E'!BJ84 -> 182.03062 | BK97: ='D&E'!BK84 -> 182.03062 | BL97: ='D&E'!BL84 -> 182.03062 | BM97: ='D&E'!BM84 -> 182.03062 | ... BX97: ='D&E'!BX84 -> 182.03062
B98: Diluted EPS | G98: JPY | H98: =+SUMIF($X$5:$BY$5,H$5,$X98:$BY98) -> 41.152 | I98: =+SUMIF($X$5:$BY$5,I$5,$X98:$BY98) -> 29.746 | J98: =+SUMIF($X$5:$BY$5,J$5,$X98:$BY98) -> 41.754 | K98: =+SUMIF($X$5:$BY$5,K$5,$X98:$BY98) -> 33.608 | L98: =+SUMIF($X$5:$BY$5,L$5,$X98:$BY98) -> 14.788 | M98: =+SUMIF($X$5:$BY$5,M$5,$X98:$BY98) -> 40.078 | N98: =+SUMIF($X$5:$BY$5,N$5,$X98:$BY98) -> 70.522 | O98: =+SUMIF($X$5:$BY$5,O$5,$X98:$BY98) -> 229.468 | ... T98: =+SUMIF($X$5:$BY$5,T$5,$X98:$BY98) -> 151.66495 | Y98: 8.086 | Z98: 15.288 | AA98: 5.324 | AB98: 12.454 | AC98: 5.06 | AD98: 5.588 | AE98: 9.084 | AF98: 10.014 | AG98: 44.174 | AH98: 1.13 | AI98: -4.236 | AJ98: 0.686 | AK98: 4.206 | AL98: 7.868 | AM98: 13.67 | AN98: 7.864 | AO98: 24.812 | AP98: 14.252 | AQ98: 2.232 | AR98: -26.508 | AS98: 5.82 | AT98: 13.498 | AU98: 10.158 | AV98: 10.602 | AW98: 17.862 | AX98: 11.864 | AY98: 22.028 | AZ98: 18.768 | BA98: 17.292 | BB98: 20.496 | BC98: 155.096 | BD98: 36.584 | BE98: 31.85 | BF98: =IFERROR(BF95/BF97,"nm") -> 27.829895 | BG98: =IFERROR(BG95/BG97,"nm") -> 29.10484 | BH98: =IFERROR(BH95/BH97,"nm") -> 29.631202 | BI98: =IFERROR(BI95/BI97,"nm") -> 30.554412 | BJ98: =IFERROR(BJ95/BJ97,"nm") -> 29.333248 | BK98: =IFERROR(BK95/BK97,"nm") -> 34.127043 | BL98: =IFERROR(BL95/BL97,"nm") -> 37.69046 | BM98: =IFERROR(BM95/BM97,"nm") -> 34.389225 | ... BX98: =IFERROR(BX95/BX97,"nm") -> 39.147804
B100: EBITDA Reconciliation
B101: EBIT | G101: =G$10 -> JPY M | H101: =H87 -> 8198 | I101: =I87 -> 8160 | J101: =J87 -> 5964 | K101: =K87 -> 7268 | L101: =L87 -> 4880 | M101: =M87 -> 8387 | N101: =N87 -> 16445 | O101: =O87 -> 20819 | ... T101: =T87 -> 39963.536 | Y101: =Y87 -> 2126 | Z101: =Z87 -> 2266 | AA101: =AA87 -> 2473 | AB101: =AB87 -> 1333 | AC101: =AC87 -> 1698 | AD101: =AD87 -> 1696 | AE101: =AE87 -> 1846 | AF101: =AF87 -> 2920 | ... BX101: =BX87 -> 10466.666
B102: D&A | G102: =G$10 -> JPY M | H102: =+SUMIF($X$5:$BY$5,H$5,$X102:$BY102) -> 4080 | I102: =+SUMIF($X$5:$BY$5,I$5,$X102:$BY102) -> 5388.5 | J102: =+SUMIF($X$5:$BY$5,J$5,$X102:$BY102) -> 6332 | K102: =+SUMIF($X$5:$BY$5,K$5,$X102:$BY102) -> 7082 | L102: =+SUMIF($X$5:$BY$5,L$5,$X102:$BY102) -> 8208 | M102: =+SUMIF($X$5:$BY$5,M$5,$X102:$BY102) -> 7166 | N102: =+SUMIF($X$5:$BY$5,N$5,$X102:$BY102) -> 7941 | O102: =+SUMIF($X$5:$BY$5,O$5,$X102:$BY102) -> 9301 | ... T102: =+SUMIF($X$5:$BY$5,T$5,$X102:$BY102) -> 25815.449 | Y102: 971 | Z102: 971 | AA102: 1069 | AB102: 1069 | AC102: 1239.5 | AD102: 1239.5 | AE102: 1454.5 | AF102: 1455 | AG102: 1610 | AH102: 1609 | AI102: 1556 | AJ102: 1557 | AK102: 1639 | AL102: 1639 | AM102: 1902 | AN102: 1902 | AO102: 2056 | AP102: 2055 | AQ102: 2048 | AR102: 2049 | AS102: 1732 | AT102: 1791 | AU102: 1804 | AV102: 1839 | AW102: 1920 | AX102: 1925 | AY102: 1973 | AZ102: 2123 | BA102: 2116 | BB102: 2287 | BC102: 2418 | BD102: 2480 | BE102: 2505 | BF102: =PPE!BF191+PPE!BF192 -> 2484.125 | BG102: =PPE!BG191+PPE!BG192 -> 2724.3706 | BH102: =PPE!BH191+PPE!BH192 -> 3042.4149 | BI102: =PPE!BI191+PPE!BI192 -> 3383.7988 | BJ102: =PPE!BJ191+PPE!BJ192 -> 3724.6846 | BK102: =PPE!BK191+PPE!BK192 -> 4017.7895 | BL102: =PPE!BL191+PPE!BL192 -> 4296.5601 | BM102: =PPE!BM191+PPE!BM192 -> 4571.0305 | ... BX102: =PPE!BX191+PPE!BX192 -> 6730.0143
B103: EBITDA | G103: =G$10 -> JPY M | H103: =+SUMIF($X$5:$BY$5,H$5,$X103:$BY103) -> 12278 | I103: =+SUMIF($X$5:$BY$5,I$5,$X103:$BY103) -> 13548.5 | J103: =+SUMIF($X$5:$BY$5,J$5,$X103:$BY103) -> 12296 | K103: =+SUMIF($X$5:$BY$5,K$5,$X103:$BY103) -> 14350 | L103: =+SUMIF($X$5:$BY$5,L$5,$X103:$BY103) -> 13088 | M103: =+SUMIF($X$5:$BY$5,M$5,$X103:$BY103) -> 15553 | N103: =+SUMIF($X$5:$BY$5,N$5,$X103:$BY103) -> 24386 | O103: =+SUMIF($X$5:$BY$5,O$5,$X103:$BY103) -> 30120 | ... T103: =+SUMIF($X$5:$BY$5,T$5,$X103:$BY103) -> 65778.985 | Y103: =Y87+Y102 -> 3097 | Z103: =Z87+Z102 -> 3237 | AA103: =AA87+AA102 -> 3542 | AB103: =AB87+AB102 -> 2402 | AC103: =AC87+AC102 -> 2937.5 | AD103: =AD87+AD102 -> 2935.5 | AE103: =AE87+AE102 -> 3300.5 | AF103: =AF87+AF102 -> 4375 | ... BX103: =BX87+BX102 -> 17196.681
B105: Y/Y
B106: =B82 -> Revenue | G106: % | H106: =IFERROR(H82/#REF!-1,"nm") -> nm | I106: =IFERROR(I82/H82-1,"nm") -> 0.041680844 | J106: =IFERROR(J82/I82-1,"nm") -> -0.081600989 | K106: =IFERROR(K82/J82-1,"nm") -> 0.0676261 | L106: =IFERROR(L82/K82-1,"nm") -> 0.041379639 | M106: =IFERROR(M82/L82-1,"nm") -> 0.065395469 | N106: =IFERROR(N82/M82-1,"nm") -> 0.16923852 | O106: =IFERROR(O82/N82-1,"nm") -> 0.084321548 | P106: =IFERROR(P82/O82-1,"nm") -> 0.17254348 | ... T106: =IFERROR(T82/S82-1,"nm") -> 0.064201151 | Y106: =IFERROR(Y82/#REF!-1,"nm") -> nm | Z106: =IFERROR(Z82/#REF!-1,"nm") -> nm | AA106: =IFERROR(AA82/#REF!-1,"nm") -> nm | AB106: =IFERROR(AB82/#REF!-1,"nm") -> nm | AC106: =IFERROR(AC82/Y82-1,"nm") -> 0.0083618582 | AD106: =IFERROR(AD82/Z82-1,"nm") -> 0.051729052 | AE106: =IFERROR(AE82/AA82-1,"nm") -> -0.017528484 | AF106: =IFERROR(AF82/AB82-1,"nm") -> 0.13343101 | AG106: =IFERROR(AG82/AC82-1,"nm") -> -0.050288541 | AH106: =IFERROR(AH82/AD82-1,"nm") -> -0.15559369 | AI106: =IFERROR(AI82/AE82-1,"nm") -> -0.056434574 | AJ106: =IFERROR(AJ82/AF82-1,"nm") -> -0.060523522 | ... BX106: =IFERROR(BX82/BT82-1,"nm") -> 0.063297132
B107: =B84 -> Gross profit | G107: % | H107: =IFERROR(H84/#REF!-1,"nm") -> nm | I107: =IFERROR(I84/H84-1,"nm") -> 0.015690528 | J107: =IFERROR(J84/I84-1,"nm") -> -0.086602121 | K107: =IFERROR(K84/J84-1,"nm") -> 0.10003507 | L107: =IFERROR(L84/K84-1,"nm") -> -0.036205186 | M107: =IFERROR(M84/L84-1,"nm") -> 0.12526649 | N107: =IFERROR(N84/M84-1,"nm") -> 0.31893905 | O107: =IFERROR(O84/N84-1,"nm") -> 0.17826539 | P107: =IFERROR(P84/O84-1,"nm") -> 0.28061069 | ... T107: =IFERROR(T84/S84-1,"nm") -> 0.053701777 | Y107: =IFERROR(Y84/#REF!-1,"nm") -> nm | Z107: =IFERROR(Z84/#REF!-1,"nm") -> nm | AA107: =IFERROR(AA84/#REF!-1,"nm") -> nm | AB107: =IFERROR(AB84/#REF!-1,"nm") -> nm | AC107: =IFERROR(AC84/Y84-1,"nm") -> -0.032216123 | AD107: =IFERROR(AD84/Z84-1,"nm") -> -0.050852233 | AE107: =IFERROR(AE84/AA84-1,"nm") -> -0.074909384 | AF107: =IFERROR(AF84/AB84-1,"nm") -> 0.2546042 | AG107: =IFERROR(AG84/AC84-1,"nm") -> 0.033885655 | AH107: =IFERROR(AH84/AD84-1,"nm") -> -0.14455328 | AI107: =IFERROR(AI84/AE84-1,"nm") -> -0.083151937 | AJ107: =IFERROR(AJ84/AF84-1,"nm") -> -0.14331702 | ... BX107: =IFERROR(BX84/BT84-1,"nm") -> 0.051784675
B108: =B87 -> EBIT | G108: % | H108: =IFERROR(H87/#REF!-1,"nm") -> nm | I108: =IFERROR(I87/H87-1,"nm") -> -0.0046352769 | J108: =IFERROR(J87/I87-1,"nm") -> -0.26911765 | K108: =IFERROR(K87/J87-1,"nm") -> 0.2186452 | L108: =IFERROR(L87/K87-1,"nm") -> -0.32856357 | M108: =IFERROR(M87/L87-1,"nm") -> 0.71864754 | N108: =IFERROR(N87/M87-1,"nm") -> 0.96077262 | O108: =IFERROR(O87/N87-1,"nm") -> 0.2659775 | P108: =IFERROR(P87/O87-1,"nm") -> 0.48634866 | ... T108: =IFERROR(T87/S87-1,"nm") -> 0.042739542 | Y108: =IFERROR(Y87/#REF!-1,"nm") -> nm | Z108: =IFERROR(Z87/#REF!-1,"nm") -> nm | AA108: =IFERROR(AA87/#REF!-1,"nm") -> nm | AB108: =IFERROR(AB87/#REF!-1,"nm") -> nm | AC108: =IFERROR(AC87/Y87-1,"nm") -> -0.20131703 | AD108: =IFERROR(AD87/Z87-1,"nm") -> -0.25154457 | AE108: =IFERROR(AE87/AA87-1,"nm") -> -0.25353821 | AF108: =IFERROR(AF87/AB87-1,"nm") -> 1.1905476 | AG108: =IFERROR(AG87/AC87-1,"nm") -> 0.20671378 | AH108: =IFERROR(AH87/AD87-1,"nm") -> -0.49587264 | AI108: =IFERROR(AI87/AE87-1,"nm") -> -0.25893824 | AJ108: =IFERROR(AJ87/AF87-1,"nm") -> -0.42054795 | ... BX108: =IFERROR(BX87/BT87-1,"nm") -> 0.040181076
B109: =B95 -> Net income to shareholders | G109: % | H109: =IFERROR(H95/#REF!-1,"nm") -> nm | I109: =IFERROR(I95/H95-1,"nm") -> -0.27717936 | J109: =IFERROR(J95/I95-1,"nm") -> 0.40356957 | K109: =IFERROR(K95/J95-1,"nm") -> -0.19506173 | L109: =IFERROR(L95/K95-1,"nm") -> -0.57469325 | M109: =IFERROR(M95/L95-1,"nm") -> 1.6310855 | N109: =IFERROR(N95/M95-1,"nm") -> 0.75945724 | O109: =IFERROR(O95/N95-1,"nm") -> 2.2538755 | P109: =IFERROR(P95/O95-1,"nm") -> -0.48396812 | ... T109: =IFERROR(T95/S95-1,"nm") -> 0.042839411 | Y109: =IFERROR(Y95/#REF!-1,"nm") -> nm | Z109: =IFERROR(Z95/#REF!-1,"nm") -> nm | AA109: =IFERROR(AA95/#REF!-1,"nm") -> nm | AB109: =IFERROR(AB95/#REF!-1,"nm") -> nm | AC109: =IFERROR(AC95/Y95-1,"nm") -> -0.37412365 | AD109: =IFERROR(AD95/Z95-1,"nm") -> -0.63452461 | AE109: =IFERROR(AE95/AA95-1,"nm") -> 0.70571152 | AF109: =IFERROR(AF95/AB95-1,"nm") -> -0.19577815 | AG109: =IFERROR(AG95/AC95-1,"nm") -> 7.7270876 | AH109: =IFERROR(AH95/AD95-1,"nm") -> -0.79889299 | AI109: =IFERROR(AI95/AE95-1,"nm") -> -1.4659478 | AJ109: =IFERROR(AJ95/AF95-1,"nm") -> -0.93154915 | ... BX109: =IFERROR(BX95/BT95-1,"nm") -> 0.040883073
B110: =B98 -> Diluted EPS | G110: % | H110: =IFERROR(H98/#REF!-1,"nm") -> nm | I110: =IFERROR(I98/H98-1,"nm") -> -0.27716757 | J110: =IFERROR(J98/I98-1,"nm") -> 0.40368453 | K110: =IFERROR(K98/J98-1,"nm") -> -0.19509508 | L110: =IFERROR(L98/K98-1,"nm") -> -0.55998572 | M110: =IFERROR(M98/L98-1,"nm") -> 1.7101704 | N110: =IFERROR(N98/M98-1,"nm") -> 0.75961874 | O110: =IFERROR(O98/N98-1,"nm") -> 2.2538499 | P110: =IFERROR(P98/O98-1,"nm") -> -0.48395446 | ... T110: =IFERROR(T98/S98-1,"nm") -> 0.042839411 | Y110: =IFERROR(Y98/#REF!-1,"nm") -> nm | Z110: =IFERROR(Z98/#REF!-1,"nm") -> nm | AA110: =IFERROR(AA98/#REF!-1,"nm") -> nm | AB110: =IFERROR(AB98/#REF!-1,"nm") -> nm | AC110: =IFERROR(AC98/Y98-1,"nm") -> -0.37422706 | AD110: =IFERROR(AD98/Z98-1,"nm") -> -0.63448456 | AE110: =IFERROR(AE98/AA98-1,"nm") -> 0.70623591 | AF110: =IFERROR(AF98/AB98-1,"nm") -> -0.19592099 | AG110: =IFERROR(AG98/AC98-1,"nm") -> 7.7300395 | AH110: =IFERROR(AH98/AD98-1,"nm") -> -0.79778096 | AI110: =IFERROR(AI98/AE98-1,"nm") -> -1.4663144 | AJ110: =IFERROR(AJ98/AF98-1,"nm") -> -0.93149591 | ... BX110: =IFERROR(BX98/BT98-1,"nm") -> 0.040883073
B112: Margin
B113: GPM | G113: % | H113: =IFERROR(H84/H$82,"nm") -> 0.33612016 | I113: =IFERROR(I84/I$82,"nm") -> 0.32773384 | J113: =IFERROR(J84/J$82,"nm") -> 0.32594917 | K113: =IFERROR(K84/K$82,"nm") -> 0.33584371 | L113: =IFERROR(L84/L$82,"nm") -> 0.3108227 | M113: =IFERROR(M84/M$82,"nm") -> 0.32828971 | N113: =IFERROR(N84/N$82,"nm") -> 0.37032146 | O113: =IFERROR(O84/O$82,"nm") -> 0.4024055 | ... T113: =IFERROR(T84/T$82,"nm") -> 0.42646153 | Y113: =IFERROR(Y84/Y$82,"nm") -> 0.33848411 | Z113: =IFERROR(Z84/Z$82,"nm") -> 0.33721262 | AA113: =IFERROR(AA84/AA$82,"nm") -> 0.34360441 | AB113: =IFERROR(AB84/AB$82,"nm") -> 0.32389723 | AC113: =IFERROR(AC84/AC$82,"nm") -> 0.324863 | AD113: =IFERROR(AD84/AD$82,"nm") -> 0.3043223 | AE113: =IFERROR(AE84/AE$82,"nm") -> 0.32353632 | AF113: =IFERROR(AF84/AF$82,"nm") -> 0.35852454 | ... BX113: =IFERROR(BX84/BX$82,"nm") -> 0.43352676
C114: Incrementals | G114: % | H114: =IFERROR((H84-#REF!)/(H$82-#REF!),"nm") -> nm | I114: =IFERROR((I84-H84)/(I$82-H$82),"nm") -> 0.12653061 | J114: =IFERROR((J84-I84)/(J$82-I$82),"nm") -> 0.34781987 | K114: =IFERROR((K84-J84)/(K$82-J$82),"nm") -> 0.48215627 | L114: =IFERROR((L84-K84)/(L$82-K$82),"nm") -> -0.29384704 | M114: =IFERROR((M84-L84)/(M$82-L$82),"nm") -> 0.59538784 | N114: =IFERROR((N84-M84)/(N$82-M$82),"nm") -> 0.61867951 | O114: =IFERROR((O84-N84)/(O$82-N$82),"nm") -> 0.78290189 | P114: =IFERROR((P84-O84)/(P$82-O$82),"nm") -> 0.65443959 | ... T114: =IFERROR((T84-S84)/(T$82-S$82),"nm") -> 0.36027299 | Y114: =IFERROR((Y84-#REF!)/(Y82-#REF!),"nm") -> nm | Z114: =IFERROR((Z84-#REF!)/(Z82-#REF!),"nm") -> nm | AA114: =IFERROR((AA84-#REF!)/(AA82-#REF!),"nm") -> nm | AB114: =IFERROR((AB84-#REF!)/(AB82-#REF!),"nm") -> nm | AC114: =IFERROR((AC84-Y84)/(AC82-Y82),"nm") -> -1.3040936 | AD114: =IFERROR((AD84-Z84)/(AD82-Z82),"nm") -> -0.33149679 | AE114: =IFERROR((AE84-AA84)/(AE82-AA82),"nm") -> 1.4684211 | AF114: =IFERROR((AF84-AB84)/(AF82-AB82),"nm") -> 0.61803922 | AG114: =IFERROR((AG84-AC84)/(AG82-AC82),"nm") -> -0.21890068 | AH114: =IFERROR((AH84-AD84)/(AH82-AD82),"nm") -> 0.28272859 | AI114: =IFERROR((AI84-AE84)/(AI82-AE82),"nm") -> 0.47670549 | AJ114: =IFERROR((AJ84-AF84)/(AJ82-AF82),"nm") -> 0.84897025 | ... BX114: =IFERROR((BX84-BT84)/(BX82-BT82),"nm") -> 0.35855925
B115: OPM | G115: % | H115: =IFERROR(H87/H$82,"nm") -> 0.099620862 | I115: =IFERROR(I87/I$82,"nm") -> 0.095191433 | J115: =IFERROR(J87/J$82,"nm") -> 0.075755459 | K115: =IFERROR(K87/K$82,"nm") -> 0.086471309 | L115: =IFERROR(L87/L$82,"nm") -> 0.05575295 | M115: =IFERROR(M87/M$82,"nm") -> 0.089938125 | N115: =IFERROR(N87/N$82,"nm") -> 0.15082313 | O115: =IFERROR(O87/O$82,"nm") -> 0.17609047 | ... T115: =IFERROR(T87/T$82,"nm") -> 0.20646153 | Y115: =IFERROR(Y87/Y$82,"nm") -> 0.10396088 | Z115: =IFERROR(Z87/Z$82,"nm") -> 0.10763823 | AA115: =IFERROR(AA87/AA$82,"nm") -> 0.11407353 | AB115: =IFERROR(AB87/AB$82,"nm") -> 0.069750406 | AC115: =IFERROR(AC87/AC$82,"nm") -> 0.082343242 | AD115: =IFERROR(AD87/AD$82,"nm") -> 0.076599973 | AE115: =IFERROR(AE87/AE$82,"nm") -> 0.086670736 | AF115: =IFERROR(AF87/AF$82,"nm") -> 0.13480449 | ... BX115: =IFERROR(BX87/BX$82,"nm") -> 0.21352676
C116: Incrementals | G116: % | H116: =IFERROR((H87-#REF!)/(H$82-#REF!),"nm") -> nm | I116: =IFERROR((I87-H87)/(I$82-H$82),"nm") -> -0.011078717 | J116: =IFERROR((J87-I87)/(J$82-I$82),"nm") -> 0.31393853 | K116: =IFERROR((K87-J87)/(K$82-J$82),"nm") -> 0.24492863 | L116: =IFERROR((L87-K87)/(L$82-K$82),"nm") -> -0.6866015 | M116: =IFERROR((M87-L87)/(M$82-L$82),"nm") -> 0.61268344 | N116: =IFERROR((N87-M87)/(N$82-M$82),"nm") -> 0.51058168 | O116: =IFERROR((O87-N87)/(O$82-N$82),"nm") -> 0.47574505 | P116: =IFERROR((P87-O87)/(P$82-O$82),"nm") -> 0.49634655 | ... T116: =IFERROR((T87-S87)/(T$82-S$82),"nm") -> 0.14027299 | Y116: =IFERROR((Y87-#REF!)/(Y82-#REF!),"nm") -> nm | Z116: =IFERROR((Z87-#REF!)/(Z82-#REF!),"nm") -> nm | AA116: =IFERROR((AA87-#REF!)/(AA82-#REF!),"nm") -> nm | AB116: =IFERROR((AB87-#REF!)/(AB82-#REF!),"nm") -> nm | AC116: =IFERROR((AC87-Y87)/(AC82-Y82),"nm") -> -2.502924 | AD116: =IFERROR((AD87-Z87)/(AD82-Z82),"nm") -> -0.52341598 | AE116: =IFERROR((AE87-AA87)/(AE82-AA82),"nm") -> 1.65 | AF116: =IFERROR((AF87-AB87)/(AF82-AB82),"nm") -> 0.62235294 | AG116: =IFERROR((AG87-AC87)/(AG82-AC82),"nm") -> -0.33847637 | AH116: =IFERROR((AH87-AD87)/(AH82-AD82),"nm") -> 0.24412192 | AI116: =IFERROR((AI87-AE87)/(AI82-AE82),"nm") -> 0.39767055 | AJ116: =IFERROR((AJ87-AF87)/(AJ82-AF82),"nm") -> 0.93668955 | ... BX116: =IFERROR((BX87-BT87)/(BX82-BT82),"nm") -> 0.13855925
B117: NPM | G117: % | H117: =IFERROR(H93/H$82,"nm") -> 0.097421378 | I117: =IFERROR(I93/I$82,"nm") -> 0.069305429 | J117: =IFERROR(J93/J$82,"nm") -> 0.10514817 | K117: =IFERROR(K93/K$82,"nm") -> 0.079487454 | L117: =IFERROR(L93/L$82,"nm") -> 0.033394646 | M117: =IFERROR(M93/M$82,"nm") -> 0.078367452 | N117: =IFERROR(N93/N$82,"nm") -> 0.12074105 | O117: =IFERROR(O93/O$82,"nm") -> 0.35802553 | ... T117: =IFERROR(T93/T$82,"nm") -> 0.14643536 | Y117: =IFERROR(Y93/Y$82,"nm") -> 0.077163814 | Z117: =IFERROR(Z93/Z$82,"nm") -> 0.14122174 | AA117: =IFERROR(AA93/AA$82,"nm") -> 0.048111075 | AB117: =IFERROR(AB93/AB$82,"nm") -> 0.12678562 | AC117: =IFERROR(AC93/AC$82,"nm") -> 0.048009311 | AD117: =IFERROR(AD93/AD$82,"nm") -> 0.051126869 | AE117: =IFERROR(AE93/AE$82,"nm") -> 0.085825626 | AF117: =IFERROR(AF93/AF$82,"nm") -> 0.091916347 | ... BX117: =IFERROR(BX93/BX$82,"nm") -> 0.14925773
...

Sheet Revenue
A1: =Summary!C2 -> Nitto Boseki
A2: =Summary!C3 -> TYO: 3110 | F2: Case | G2: =Summary!C9 -> 2
B4: FQ | H4: A | I4: A | J4: A | K4: A | L4: A | M4: A | N4: A | O4: A | P4: E | Q4: E | R4: E | S4: E | T4: E | Y4: 1 | Z4: 2 | AA4: 3 | AB4: 4 | AC4: =Y4 -> 1 | AD4: =Z4 -> 2 | AE4: =AA4 -> 3 | AF4: =AB4 -> 4 | AG4: =AC4 -> 1 | AH4: =AD4 -> 2 | AI4: =AE4 -> 3 | AJ4: =AF4 -> 4 | ... BX4: =BT4 -> 4
B5: FY | H5: 2019 | I5: =H5+1 -> 2020 | J5: =I5+1 -> 2021 | K5: =J5+1 -> 2022 | L5: =K5+1 -> 2023 | M5: =L5+1 -> 2024 | N5: =M5+1 -> 2025 | O5: =N5+1 -> 2026 | P5: =O5+1 -> 2027 | ... T5: =S5+1 -> 2031 | V5: FY21-26 | W5: FY26-31 | Y5: 2019 | Z5: 2019 | AA5: 2019 | AB5: 2019 | AC5: =Y5+1 -> 2020 | AD5: =Z5+1 -> 2020 | AE5: =AA5+1 -> 2020 | AF5: =AB5+1 -> 2020 | AG5: =AC5+1 -> 2021 | AH5: =AD5+1 -> 2021 | AI5: =AE5+1 -> 2021 | AJ5: =AF5+1 -> 2021 | ... BX5: =BT5+1 -> 2031
B6: FY End | G6: Units | H6: 43555 | I6: =EOMONTH(J6,-12) -> 43921 | J6: =EOMONTH(K6,-12) -> 44286 | K6: =EOMONTH(L6,-12) -> 44651 | L6: =EOMONTH(M6,-12) -> 45016 | M6: =EOMONTH(N6,-12) -> 45382 | N6: =EOMONTH(O6,-12) -> 45747 | O6: =Summary!$C$6 -> 46112 | P6: =EOMONTH(O6,12) -> 46477 | Q6: =EOMONTH(P6,12) -> 46843 | R6: =EOMONTH(Q6,12) -> 47208 | S6: =EOMONTH(R6,12) -> 47573 | T6: =EOMONTH(S6,12) -> 47938 | V6: CAGR | W6: CAGR | Y6: 43281 | Z6: 43373 | AA6: 43465 | AB6: 43555 | AC6: =EOMONTH(AD6,-3) -> 43646 | AD6: =EOMONTH(AE6,-3) -> 43738 | AE6: =EOMONTH(AF6,-3) -> 43830 | AF6: =EOMONTH(AG6,-3) -> 43921 | AG6: =EOMONTH(AH6,-3) -> 44012 | AH6: =EOMONTH(AI6,-3) -> 44104 | AI6: =EOMONTH(AJ6,-3) -> 44196 | AJ6: =EOMONTH(AK6,-3) -> 44286 | ... BC6: =EOMONTH(BD6,-3) -> 46022 | BD6: =Summary!C6 -> 46112 | BE6: =EOMONTH(BD6,3) -> 46203 | BF6: =EOMONTH(BE6,3) -> 46295 | BG6: =EOMONTH(BF6,3) -> 46387 | BH6: =EOMONTH(BG6,3) -> 46477 | BI6: =EOMONTH(BH6,3) -> 46568 | BJ6: =EOMONTH(BI6,3) -> 46660 | BK6: =EOMONTH(BJ6,3) -> 46752 | BL6: =EOMONTH(BK6,3) -> 46843 | ... BX6: =EOMONTH(BW6,3) -> 47938 | BZ6: Source | CA6: Notes
A8: x | B8: SUMMARY
B10: Revenue | G10: =Summary!C8 -> JPY M | H10: =+SUMIF($X$5:$BY$5,H$5,$X10:$BY10) -> 82290 | I10: =+SUMIF($X$5:$BY$5,I$5,$X10:$BY10) -> 85720 | J10: =+SUMIF($X$5:$BY$5,J$5,$X10:$BY10) -> 78725 | K10: =+SUMIF($X$5:$BY$5,K$5,$X10:$BY10) -> 84049 | L10: =+SUMIF($X$5:$BY$5,L$5,$X10:$BY10) -> 87528 | M10: =+SUMIF($X$5:$BY$5,M$5,$X10:$BY10) -> 93250 | N10: =+SUMIF($X$5:$BY$5,N$5,$X10:$BY10) -> 109033 | O10: =+SUMIF($X$5:$BY$5,O$5,$X10:$BY10) -> 118226 | ... T10: =+SUMIF($X$5:$BY$5,T$5,$X10:$BY10) -> 193564.08 | V10: =(O10/J10)^(1/(O$5-J$5))-1 -> 0.084726038 | W10: =(T10/O10)^(1/(T$5-O$5))-1 -> 0.1036271 | Y10: =SUM(Y11:Y16) -> 20447 | Z10: =SUM(Z11:Z16) -> 21054 | AA10: =SUM(AA11:AA16) -> 21677 | AB10: =SUM(AB11:AB16) -> 19112 | AC10: =SUM(AC11:AC16) -> 20620 | AD10: =SUM(AD11:AD16) -> 22140 | AE10: =SUM(AE11:AE16) -> 21297 | AF10: =SUM(AF11:AF16) -> 21663 | ... BX10: =SUM(BX11:BX16) -> 49018.055
B11: Electronic Materials | G11: =G$10 -> JPY M | H11: =+SUMIF($X$5:$BY$5,H$5,$X11:$BY11) -> 19786.95 | I11: =+SUMIF($X$5:$BY$5,I$5,$X11:$BY11) -> 23638.2 | J11: =+SUMIF($X$5:$BY$5,J$5,$X11:$BY11) -> 23371.65 | K11: =+SUMIF($X$5:$BY$5,K$5,$X11:$BY11) -> 25381.75 | L11: =+SUMIF($X$5:$BY$5,L$5,$X11:$BY11) -> 25538.3 | M11: =+SUMIF($X$5:$BY$5,M$5,$X11:$BY11) -> 29812.85 | N11: =+SUMIF($X$5:$BY$5,N$5,$X11:$BY11) -> 40911 | O11: =+SUMIF($X$5:$BY$5,O$5,$X11:$BY11) -> 49265 | ... T11: =+SUMIF($X$5:$BY$5,T$5,$X11:$BY11) -> 94669.213 | Y11: ='3FS'!Y11 -> 4915.4 | Z11: ='3FS'!Z11 -> 4969.3 | AA11: ='3FS'!AA11 -> 5242.25 | AB11: ='3FS'!AB11 -> 4660 | AC11: ='3FS'!AC11 -> 5033.1 | AD11: ='3FS'!AD11 -> 6130.35 | AE11: ='3FS'!AE11 -> 6084.75 | AF11: ='3FS'!AF11 -> 6390 | ... BE11: ='3FS'!BE11 -> 14589 | BF11: =BF71 -> 15134.711 | BG11: =BG71 -> 15438.299 | BH11: =BH71 -> 16392.44 | BI11: =BI71 -> 17139.195 | BJ11: =BJ71 -> 18369.786 | BK11: =BK71 -> 19144.496 | BL11: =BL71 -> 20394.819 | BM11: =BM71 -> 19946.043 | ... BX11: =BX71 -> 24187.021
B12: Medical | G12: =G$10 -> JPY M | H12: =+SUMIF($X$5:$BY$5,H$5,$X12:$BY12) -> 12048.96 | I12: =+SUMIF($X$5:$BY$5,I$5,$X12:$BY12) -> 13245.76 | J12: =+SUMIF($X$5:$BY$5,J$5,$X12:$BY12) -> 11880 | K12: =+SUMIF($X$5:$BY$5,K$5,$X12:$BY12) -> 13983.2 | L12: =+SUMIF($X$5:$BY$5,L$5,$X12:$BY12) -> 14747.92 | M12: =+SUMIF($X$5:$BY$5,M$5,$X12:$BY12) -> 12703.68 | N12: =+SUMIF($X$5:$BY$5,N$5,$X12:$BY12) -> 13603 | O12: =+SUMIF($X$5:$BY$5,O$5,$X12:$BY12) -> 13850 | ... T12: =+SUMIF($X$5:$BY$5,T$5,$X12:$BY12) -> 18004.023 | Y12: ='3FS'!Y12 -> 3166.24 | Z12: ='3FS'!Z12 -> 3158.32 | AA12: ='3FS'!AA12 -> 2966.48 | AB12: ='3FS'!AB12 -> 2757.92 | AC12: ='3FS'!AC12 -> 3387.12 | AD12: ='3FS'!AD12 -> 3511.2 | AE12: ='3FS'!AE12 -> 3119.6 | AF12: ='3FS'!AF12 -> 3227.84 | ... BE12: ='3FS'!BE12 -> 3818 | BF12: =BF156 -> 3409.3346 | BG12: =BG156 -> 3810.4957 | BH12: =BH156 -> 3774.1237 | BI12: =BI156 -> 4008.9 | BJ12: =BJ156 -> 3579.8013 | BK12: =BK156 -> 4001.0205 | BL12: =BL156 -> 3962.8299 | BM12: =BM156 -> 4209.345 | ... BX12: =BX156 -> 4587.471
B13: Composite Materials | G13: =G$10 -> JPY M | H13: =+SUMIF($X$5:$BY$5,H$5,$X13:$BY13) -> 12692.16 | I13: =+SUMIF($X$5:$BY$5,I$5,$X13:$BY13) -> 12008.16 | J13: =+SUMIF($X$5:$BY$5,J$5,$X13:$BY13) -> 11099.52 | K13: =+SUMIF($X$5:$BY$5,K$5,$X13:$BY13) -> 11205.6 | L13: =+SUMIF($X$5:$BY$5,L$5,$X13:$BY13) -> 11504.64 | M13: =+SUMIF($X$5:$BY$5,M$5,$X13:$BY13) -> 12571.68 | N13: =+SUMIF($X$5:$BY$5,N$5,$X13:$BY13) -> 13474 | O13: =+SUMIF($X$5:$BY$5,O$5,$X13:$BY13) -> 13401 | ... T13: =+SUMIF($X$5:$BY$5,T$5,$X13:$BY13) -> 16402.9 | Y13: ='3FS'!Y13 -> 3249.12 | Z13: ='3FS'!Z13 -> 3287.04 | AA13: ='3FS'!AA13 -> 3316.8 | AB13: ='3FS'!AB13 -> 2839.2 | AC13: ='3FS'!AC13 -> 3156.48 | AD13: ='3FS'!AD13 -> 3142.08 | AE13: ='3FS'!AE13 -> 2779.2 | AF13: ='3FS'!AF13 -> 2930.4 | ... BE13: ='3FS'!BE13 -> 3830 | BF13: =BF166 -> 3977.12 | BG13: =BG166 -> 3502.4 | BH13: =BH166 -> 3697.1 | BI13: =BI166 -> 3944.9 | BJ13: =BJ166 -> 4096.4336 | BK13: =BK166 -> 3607.472 | BL13: =BL166 -> 3808.013 | BM13: =BM166 -> 4023.798 | ... BX13: =BX166 -> 4041.0939
B14: Materials Solution | G14: =G$10 -> JPY M | H14: =+SUMIF($X$5:$BY$5,H$5,$X14:$BY14) -> 11515.59 | I14: =+SUMIF($X$5:$BY$5,I$5,$X14:$BY14) -> 10343.32 | J14: =+SUMIF($X$5:$BY$5,J$5,$X14:$BY14) -> 8142.57 | K14: =+SUMIF($X$5:$BY$5,K$5,$X14:$BY14) -> 8658.47 | L14: =+SUMIF($X$5:$BY$5,L$5,$X14:$BY14) -> 9050.09 | M14: =+SUMIF($X$5:$BY$5,M$5,$X14:$BY14) -> 9094.83 | N14: =+SUMIF($X$5:$BY$5,N$5,$X14:$BY14) -> 9431 | O14: =+SUMIF($X$5:$BY$5,O$5,$X14:$BY14) -> 9515 | ... T14: =+SUMIF($X$5:$BY$5,T$5,$X14:$BY14) -> 11590.355 | Y14: ='3FS'!Y14 -> 2894.22 | Z14: ='3FS'!Z14 -> 2901.21 | AA14: ='3FS'!AA14 -> 3080.24 | AB14: ='3FS'!AB14 -> 2639.92 | AC14: ='3FS'!AC14 -> 2799.48 | AD14: ='3FS'!AD14 -> 2598.08 | AE14: ='3FS'!AE14 -> 2603.62 | AF14: ='3FS'!AF14 -> 2342.14 | ... BE14: ='3FS'!BE14 -> 2615 | BF14: =BF176 -> 2381.82 | BG14: =BG176 -> 2665.9 | BH14: =BH176 -> 2635.16 | BI14: =BI176 -> 2693.45 | BJ14: =BJ176 -> 2453.2746 | BK14: =BK176 -> 2745.877 | BL14: =BL176 -> 2714.2148 | BM14: =BM176 -> 2774.2535 | ... BX14: =BX176 -> 2965.8958
B15: Insulation Materials | G15: =G$10 -> JPY M | H15: =+SUMIF($X$5:$BY$5,H$5,$X15:$BY15) -> 14813.8 | I15: =+SUMIF($X$5:$BY$5,I$5,$X15:$BY15) -> 14549.28 | J15: =+SUMIF($X$5:$BY$5,J$5,$X15:$BY15) -> 12620.12 | K15: =+SUMIF($X$5:$BY$5,K$5,$X15:$BY15) -> 12531.72 | L15: =+SUMIF($X$5:$BY$5,L$5,$X15:$BY15) -> 13931.16 | M15: =+SUMIF($X$5:$BY$5,M$5,$X15:$BY15) -> 14713.16 | N15: =+SUMIF($X$5:$BY$5,N$5,$X15:$BY15) -> 15320 | O15: =+SUMIF($X$5:$BY$5,O$5,$X15:$BY15) -> 15136 | ... T15: =+SUMIF($X$5:$BY$5,T$5,$X15:$BY15) -> 21552.081 | Y15: ='3FS'!Y15 -> 3469.36 | Z15: ='3FS'!Z15 -> 3679.48 | AA15: ='3FS'!AA15 -> 4055.52 | AB15: ='3FS'!AB15 -> 3609.44 | AC15: ='3FS'!AC15 -> 3549.6 | AD15: ='3FS'!AD15 -> 3696.48 | AE15: ='3FS'!AE15 -> 3681.52 | AF15: ='3FS'!AF15 -> 3621.68 | ... BE15: ='3FS'!BE15 -> 4399 | BF15: =BF186 -> 4313.65 | BG15: =BG186 -> 4744.9 | BH15: =BH186 -> 4273.4 | BI15: =BI186 -> 4618.95 | BJ15: =BJ186 -> 4529.3325 | BK15: =BK186 -> 4982.145 | BL15: =BL186 -> 4487.07 | BM15: =BM186 -> 4849.8975 | ... BX15: =BX186 -> 5194.3444
B16: Other Business | G16: =G$10 -> JPY M | H16: =+SUMIF($X$5:$BY$5,H$5,$X16:$BY16) -> 11432.54 | I16: =+SUMIF($X$5:$BY$5,I$5,$X16:$BY16) -> 11935.28 | J16: =+SUMIF($X$5:$BY$5,J$5,$X16:$BY16) -> 11611.14 | K16: =+SUMIF($X$5:$BY$5,K$5,$X16:$BY16) -> 12288.26 | L16: =+SUMIF($X$5:$BY$5,L$5,$X16:$BY16) -> 12755.89 | M16: =+SUMIF($X$5:$BY$5,M$5,$X16:$BY16) -> 14353.8 | N16: =+SUMIF($X$5:$BY$5,N$5,$X16:$BY16) -> 16294 | O16: =+SUMIF($X$5:$BY$5,O$5,$X16:$BY16) -> 17059 | ... T16: =+SUMIF($X$5:$BY$5,T$5,$X16:$BY16) -> 31345.513 | Y16: ='3FS'!Y16 -> 2752.66 | Z16: ='3FS'!Z16 -> 3058.65 | AA16: ='3FS'!AA16 -> 3015.71 | AB16: ='3FS'!AB16 -> 2605.52 | AC16: ='3FS'!AC16 -> 2694.22 | AD16: ='3FS'!AD16 -> 3061.81 | AE16: ='3FS'!AE16 -> 3028.31 | AF16: ='3FS'!AF16 -> 3150.94 | ... BE16: ='3FS'!BE16 -> 4780 | BF16: =BF196 -> 4848.83 | BG16: =BG196 -> 4663.51 | BH16: =BH196 -> 4932.45 | BI16: =BI196 -> 5401.4 | BJ16: =BJ196 -> 5479.1779 | BK16: =BK196 -> 5269.7663 | BL16: =BL196 -> 5573.6685 | BM16: =BM196 -> 6103.582 | ... BX16: =BX196 -> 8042.2296
B18: Mix
B19: =B11 -> Electronic Materials | G19: % | H19: =IFERROR(H11/H$10,"nm") -> 0.24045388 | I19: =IFERROR(I11/I$10,"nm") -> 0.27576062 | J19: =IFERROR(J11/J$10,"nm") -> 0.2968771 | K19: =IFERROR(K11/K$10,"nm") -> 0.30198753 | L19: =IFERROR(L11/L$10,"nm") -> 0.29177292 | M19: =IFERROR(M11/M$10,"nm") -> 0.31970885 | N19: =IFERROR(N11/N$10,"nm") -> 0.37521668 | O19: =IFERROR(O11/O$10,"nm") -> 0.41670191 | ... T19: =IFERROR(T11/T$10,"nm") -> 0.4890846 | Y19: =IFERROR(Y11/Y$10,"nm") -> 0.24039712 | Z19: =IFERROR(Z11/Z$10,"nm") -> 0.23602641 | AA19: =IFERROR(AA11/AA$10,"nm") -> 0.24183466 | AB19: =IFERROR(AB11/AB$10,"nm") -> 0.24382587 | AC19: =IFERROR(AC11/AC$10,"nm") -> 0.24408826 | AD19: =IFERROR(AD11/AD$10,"nm") -> 0.27689024 | AE19: =IFERROR(AE11/AE$10,"nm") -> 0.28570925 | AF19: =IFERROR(AF11/AF$10,"nm") -> 0.294973 | ... BX19: =IFERROR(BX11/BX$10,"nm") -> 0.49343085
B20: =B12 -> Medical | G20: % | H20: =IFERROR(H12/H$10,"nm") -> 0.14642071 | I20: =IFERROR(I12/I$10,"nm") -> 0.15452357 | J20: =IFERROR(J12/J$10,"nm") -> 0.15090505 | K20: =IFERROR(K12/K$10,"nm") -> 0.16636962 | L20: =IFERROR(L12/L$10,"nm") -> 0.16849374 | M20: =IFERROR(M12/M$10,"nm") -> 0.13623249 | N20: =IFERROR(N12/N$10,"nm") -> 0.12476039 | O20: =IFERROR(O12/O$10,"nm") -> 0.11714851 | ... T20: =IFERROR(T12/T$10,"nm") -> 0.093013241 | Y20: =IFERROR(Y12/Y$10,"nm") -> 0.15485108 | Z20: =IFERROR(Z12/Z$10,"nm") -> 0.15001045 | AA20: =IFERROR(AA12/AA$10,"nm") -> 0.13684919 | AB20: =IFERROR(AB12/AB$10,"nm") -> 0.14430306 | AC20: =IFERROR(AC12/AC$10,"nm") -> 0.16426382 | AD20: =IFERROR(AD12/AD$10,"nm") -> 0.15859079 | AE20: =IFERROR(AE12/AE$10,"nm") -> 0.14648072 | AF20: =IFERROR(AF12/AF$10,"nm") -> 0.14900245 | ... BX20: =IFERROR(BX12/BX$10,"nm") -> 0.093587373
B21: =B13 -> Composite Materials | G21: % | H21: =IFERROR(H13/H$10,"nm") -> 0.15423697 | I21: =IFERROR(I13/I$10,"nm") -> 0.14008586 | J21: =IFERROR(J13/J$10,"nm") -> 0.14099104 | K21: =IFERROR(K13/K$10,"nm") -> 0.13332223 | L21: =IFERROR(L13/L$10,"nm") -> 0.13143954 | M21: =IFERROR(M13/M$10,"nm") -> 0.13481694 | N21: =IFERROR(N13/N$10,"nm") -> 0.12357727 | O21: =IFERROR(O13/O$10,"nm") -> 0.1133507 | ... T21: =IFERROR(T13/T$10,"nm") -> 0.084741442 | Y21: =IFERROR(Y13/Y$10,"nm") -> 0.15890448 | Z21: =IFERROR(Z13/Z$10,"nm") -> 0.15612425 | AA21: =IFERROR(AA13/AA$10,"nm") -> 0.1530101 | AB21: =IFERROR(AB13/AB$10,"nm") -> 0.14855588 | AC21: =IFERROR(AC13/AC$10,"nm") -> 0.15307856 | AD21: =IFERROR(AD13/AD$10,"nm") -> 0.1419187 | AE21: =IFERROR(AE13/AE$10,"nm") -> 0.13049725 | AF21: =IFERROR(AF13/AF$10,"nm") -> 0.13527212 | ... BX21: =IFERROR(BX13/BX$10,"nm") -> 0.082440926
B22: =B14 -> Materials Solution | G22: % | H22: =IFERROR(H14/H$10,"nm") -> 0.13993912 | I22: =IFERROR(I14/I$10,"nm") -> 0.12066402 | J22: =IFERROR(J14/J$10,"nm") -> 0.10343055 | K22: =IFERROR(K14/K$10,"nm") -> 0.10301693 | L22: =IFERROR(L14/L$10,"nm") -> 0.10339651 | M22: =IFERROR(M14/M$10,"nm") -> 0.097531689 | N22: =IFERROR(N14/N$10,"nm") -> 0.086496749 | O22: =IFERROR(O14/O$10,"nm") -> 0.080481451 | ... T22: =IFERROR(T14/T$10,"nm") -> 0.059878643 | Y22: =IFERROR(Y14/Y$10,"nm") -> 0.14154742 | Z22: =IFERROR(Z14/Z$10,"nm") -> 0.13779852 | AA22: =IFERROR(AA14/AA$10,"nm") -> 0.14209715 | AB22: =IFERROR(AB14/AB$10,"nm") -> 0.13812892 | AC22: =IFERROR(AC14/AC$10,"nm") -> 0.13576528 | AD22: =IFERROR(AD14/AD$10,"nm") -> 0.11734779 | AE22: =IFERROR(AE14/AE$10,"nm") -> 0.1222529 | AF22: =IFERROR(AF14/AF$10,"nm") -> 0.10811707 | ... BX22: =IFERROR(BX14/BX$10,"nm") -> 0.060506191
B23: =B15 -> Insulation Materials | G23: % | H23: =IFERROR(H15/H$10,"nm") -> 0.18001944 | I23: =IFERROR(I15/I$10,"nm") -> 0.16973028 | J23: =IFERROR(J15/J$10,"nm") -> 0.16030638 | K23: =IFERROR(K15/K$10,"nm") -> 0.14910017 | L23: =IFERROR(L15/L$10,"nm") -> 0.15916233 | M23: =IFERROR(M15/M$10,"nm") -> 0.15778188 | N23: =IFERROR(N15/N$10,"nm") -> 0.14050792 | O23: =IFERROR(O15/O$10,"nm") -> 0.12802598 | ... T23: =IFERROR(T15/T$10,"nm") -> 0.11134339 | Y23: =IFERROR(Y15/Y$10,"nm") -> 0.16967575 | Z23: =IFERROR(Z15/Z$10,"nm") -> 0.17476394 | AA23: =IFERROR(AA15/AA$10,"nm") -> 0.18708862 | AB23: =IFERROR(AB15/AB$10,"nm") -> 0.18885726 | AC23: =IFERROR(AC15/AC$10,"nm") -> 0.17214355 | AD23: =IFERROR(AD15/AD$10,"nm") -> 0.16695935 | AE23: =IFERROR(AE15/AE$10,"nm") -> 0.17286566 | AF23: =IFERROR(AF15/AF$10,"nm") -> 0.16718275 | ... BX23: =IFERROR(BX15/BX$10,"nm") -> 0.10596798
B24: =B16 -> Other Business | G24: % | H24: =IFERROR(H16/H$10,"nm") -> 0.13892988 | I24: =IFERROR(I16/I$10,"nm") -> 0.13923565 | J24: =IFERROR(J16/J$10,"nm") -> 0.14748987 | K24: =IFERROR(K16/K$10,"nm") -> 0.14620352 | L24: =IFERROR(L16/L$10,"nm") -> 0.14573496 | M24: =IFERROR(M16/M$10,"nm") -> 0.15392815 | N24: =IFERROR(N16/N$10,"nm") -> 0.14944099 | O24: =IFERROR(O16/O$10,"nm") -> 0.14429144 | ... T24: =IFERROR(T16/T$10,"nm") -> 0.16193868 | Y24: =IFERROR(Y16/Y$10,"nm") -> 0.13462415 | Z24: =IFERROR(Z16/Z$10,"nm") -> 0.14527643 | AA24: =IFERROR(AA16/AA$10,"nm") -> 0.13912027 | AB24: =IFERROR(AB16/AB$10,"nm") -> 0.13632901 | AC24: =IFERROR(AC16/AC$10,"nm") -> 0.13066052 | AD24: =IFERROR(AD16/AD$10,"nm") -> 0.13829313 | AE24: =IFERROR(AE16/AE$10,"nm") -> 0.14219421 | AF24: =IFERROR(AF16/AF$10,"nm") -> 0.14545262 | ... BX24: =IFERROR(BX16/BX$10,"nm") -> 0.16406668
B26: Y/Y | I26: =IFERROR(I10/H10-1,"nm") -> 0.041681857 | J26: =IFERROR(J10/I10-1,"nm") -> -0.081602893 | K26: =IFERROR(K10/J10-1,"nm") -> 0.067627818 | L26: =IFERROR(L10/K10-1,"nm") -> 0.041392521 | M26: =IFERROR(M10/L10-1,"nm") -> 0.065373366 | N26: =IFERROR(N10/M10-1,"nm") -> 0.16925469 | O26: =IFERROR(O10/N10-1,"nm") -> 0.084313923 | P26: =IFERROR(P10/O10-1,"nm") -> 0.17255632 | ... T26: =IFERROR(T10/S10-1,"nm") -> 0.064201151
B27: =B11 -> Electronic Materials | G27: % | I27: =IFERROR(I11/H11-1,"nm") -> 0.19463586 | J27: =IFERROR(J11/I11-1,"nm") -> -0.011276239 | K27: =IFERROR(K11/J11-1,"nm") -> 0.086005909 | L27: =IFERROR(L11/K11-1,"nm") -> 0.0061678174 | M27: =IFERROR(M11/L11-1,"nm") -> 0.16737802 | N27: =IFERROR(N11/M11-1,"nm") -> 0.37226062 | O27: =IFERROR(O11/N11-1,"nm") -> 0.20419936 | P27: =IFERROR(P11/O11-1,"nm") -> 0.24945599 | ... T27: =IFERROR(T11/S11-1,"nm") -> 0.06201855 | AC27: =IFERROR(AC11/Y11-1,"nm") -> 0.023945152 | AD27: =IFERROR(AD11/Z11-1,"nm") -> 0.23364458 | AE27: =IFERROR(AE11/AA11-1,"nm") -> 0.16071343 | AF27: =IFERROR(AF11/AB11-1,"nm") -> 0.37124464 | AG27: =IFERROR(AG11/AC11-1,"nm") -> 0.22063937 | AH27: =IFERROR(AH11/AD11-1,"nm") -> -0.15506456 | AI27: =IFERROR(AI11/AE11-1,"nm") -> -0.049287152 | AJ27: =IFERROR(AJ11/AF11-1,"nm") -> -0.019804382 | ... BX27: =IFERROR(BX11/BT11-1,"nm") -> 0.059641915
B28: =B12 -> Medical | G28: % | I28: =IFERROR(I12/H12-1,"nm") -> 0.099328075 | J28: =IFERROR(J12/I12-1,"nm") -> -0.10310922 | K28: =IFERROR(K12/J12-1,"nm") -> 0.17703704 | L28: =IFERROR(L12/K12-1,"nm") -> 0.054688483 | M28: =IFERROR(M12/L12-1,"nm") -> -0.13861209 | N28: =IFERROR(N12/M12-1,"nm") -> 0.070792085 | O28: =IFERROR(O12/N12-1,"nm") -> 0.018157759 | P28: =IFERROR(P12/O12-1,"nm") -> 0.069455163 | ... T28: =IFERROR(T12/S12-1,"nm") -> 0.05 | AC28: =IFERROR(AC12/Y12-1,"nm") -> 0.069760978 | AD28: =IFERROR(AD12/Z12-1,"nm") -> 0.11173029 | AE28: =IFERROR(AE12/AA12-1,"nm") -> 0.051616731 | AF28: =IFERROR(AF12/AB12-1,"nm") -> 0.17038928 | AG28: =IFERROR(AG12/AC12-1,"nm") -> -0.1610808 | AH28: =IFERROR(AH12/AD12-1,"nm") -> -0.091478697 | AI28: =IFERROR(AI12/AE12-1,"nm") -> -0.092242595 | AJ28: =IFERROR(AJ12/AF12-1,"nm") -> -0.065430752 | ... BX28: =IFERROR(BX12/BT12-1,"nm") -> 0.05
B29: =B13 -> Composite Materials | G29: % | I29: =IFERROR(I13/H13-1,"nm") -> -0.053891536 | J29: =IFERROR(J13/I13-1,"nm") -> -0.075668545 | K29: =IFERROR(K13/J13-1,"nm") -> 0.00955717 | L29: =IFERROR(L13/K13-1,"nm") -> 0.026686657 | M29: =IFERROR(M13/L13-1,"nm") -> 0.092748665 | N29: =IFERROR(N13/M13-1,"nm") -> 0.071774019 | O29: =IFERROR(O13/N13-1,"nm") -> -0.0054178418 | P29: =IFERROR(P13/O13-1,"nm") -> 0.11981345 | ... T29: =IFERROR(T13/S13-1,"nm") -> 0.02 | AC29: =IFERROR(AC13/Y13-1,"nm") -> -0.028512336 | AD29: =IFERROR(AD13/Z13-1,"nm") -> -0.044100467 | AE29: =IFERROR(AE13/AA13-1,"nm") -> -0.16208394 | AF29: =IFERROR(AF13/AB13-1,"nm") -> 0.032121724 | AG29: =IFERROR(AG13/AC13-1,"nm") -> -0.13534063 | AH29: =IFERROR(AH13/AD13-1,"nm") -> -0.21784296 | AI29: =IFERROR(AI13/AE13-1,"nm") -> 0.082210708 | AJ29: =IFERROR(AJ13/AF13-1,"nm") -> -0.0086814087 | ... BX29: =IFERROR(BX13/BT13-1,"nm") -> 0.02
B30: =B14 -> Materials Solution | G30: % | I30: =IFERROR(I14/H14-1,"nm") -> -0.10179852 | J30: =IFERROR(J14/I14-1,"nm") -> -0.21277017 | K30: =IFERROR(K14/J14-1,"nm") -> 0.063358375 | L30: =IFERROR(L14/K14-1,"nm") -> 0.0452297 | M30: =IFERROR(M14/L14-1,"nm") -> 0.0049435972 | N30: =IFERROR(N14/M14-1,"nm") -> 0.036962758 | O30: =IFERROR(O14/N14-1,"nm") -> 0.0089067967 | P30: =IFERROR(P14/O14-1,"nm") -> 0.082278508 | ... T30: =IFERROR(T14/S14-1,"nm") -> 0.03 | AC30: =IFERROR(AC14/Y14-1,"nm") -> -0.032734208 | AD30: =IFERROR(AD14/Z14-1,"nm") -> -0.10448399 | AE30: =IFERROR(AE14/AA14-1,"nm") -> -0.1547347 | AF30: =IFERROR(AF14/AB14-1,"nm") -> -0.11279887 | AG30: =IFERROR(AG14/AC14-1,"nm") -> -0.30315987 | AH30: =IFERROR(AH14/AD14-1,"nm") -> -0.22405392 | AI30: =IFERROR(AI14/AE14-1,"nm") -> -0.16790469 | AJ30: =IFERROR(AJ14/AF14-1,"nm") -> -0.142088 | ... BX30: =IFERROR(BX14/BT14-1,"nm") -> 0.03
B31: =B15 -> Insulation Materials | G31: % | I31: =IFERROR(I15/H15-1,"nm") -> -0.017856323 | J31: =IFERROR(J15/I15-1,"nm") -> -0.13259488 | K31: =IFERROR(K15/J15-1,"nm") -> -0.0070046878 | L31: =IFERROR(L15/K15-1,"nm") -> 0.11167182 | M31: =IFERROR(M15/L15-1,"nm") -> 0.056133158 | N31: =IFERROR(N15/M15-1,"nm") -> 0.041244709 | O31: =IFERROR(O15/N15-1,"nm") -> -0.012010444 | P31: =IFERROR(P15/O15-1,"nm") -> 0.17144226 | ... T31: =IFERROR(T15/S15-1,"nm") -> 0.05 | AC31: =IFERROR(AC15/Y15-1,"nm") -> 0.023128185 | AD31: =IFERROR(AD15/Z15-1,"nm") -> 0.0046202181 | AE31: =IFERROR(AE15/AA15-1,"nm") -> -0.092219987 | AF31: =IFERROR(AF15/AB15-1,"nm") -> 0.0033911078 | AG31: =IFERROR(AG15/AC15-1,"nm") -> -0.15766284 | AH31: =IFERROR(AH15/AD15-1,"nm") -> -0.14661516 | AI31: =IFERROR(AI15/AE15-1,"nm") -> -0.093091984 | AJ31: =IFERROR(AJ15/AF15-1,"nm") -> -0.13387157 | ... BX31: =IFERROR(BX15/BT15-1,"nm") -> 0.05
B32: =B16 -> Other Business | G32: % | I32: =IFERROR(I16/H16-1,"nm") -> 0.04397448 | J32: =IFERROR(J16/I16-1,"nm") -> -0.02715814 | K32: =IFERROR(K16/J16-1,"nm") -> 0.05831641 | L32: =IFERROR(L16/K16-1,"nm") -> 0.038055022 | M32: =IFERROR(M16/L16-1,"nm") -> 0.12526841 | N32: =IFERROR(N16/M16-1,"nm") -> 0.13516978 | O32: =IFERROR(O16/N16-1,"nm") -> 0.046949797 | P32: =IFERROR(P16/O16-1,"nm") -> 0.12695879 | ... T32: =IFERROR(T16/S16-1,"nm") -> 0.13 | AC32: =IFERROR(AC16/Y16-1,"nm") -> -0.021230374 | AD32: =IFERROR(AD16/Z16-1,"nm") -> 0.0010331355 | AE32: =IFERROR(AE16/AA16-1,"nm") -> 0.0041781206 | AF32: =IFERROR(AF16/AB16-1,"nm") -> 0.20933249 | AG32: =IFERROR(AG16/AC16-1,"nm") -> 0.085972935 | AH32: =IFERROR(AH16/AD16-1,"nm") -> -0.11844301 | AI32: =IFERROR(AI16/AE16-1,"nm") -> -0.020453652 | AJ32: =IFERROR(AJ16/AF16-1,"nm") -> -0.041632021 | ... BX32: =IFERROR(BX16/BT16-1,"nm") -> 0.13
B34: Operating profit | G34: =G$10 -> JPY M | H34: =+SUMIF($X$5:$BY$5,H$5,$X34:$BY34) -> 8198 | I34: =+SUMIF($X$5:$BY$5,I$5,$X34:$BY34) -> 8160 | J34: =+SUMIF($X$5:$BY$5,J$5,$X34:$BY34) -> 5964 | K34: =+SUMIF($X$5:$BY$5,K$5,$X34:$BY34) -> 7268 | L34: =+SUMIF($X$5:$BY$5,L$5,$X34:$BY34) -> 4880 | M34: =+SUMIF($X$5:$BY$5,M$5,$X34:$BY34) -> 8386 | N34: =+SUMIF($X$5:$BY$5,N$5,$X34:$BY34) -> 16444 | O34: =+SUMIF($X$5:$BY$5,O$5,$X34:$BY34) -> 20818 | ... T34: =+SUMIF($X$5:$BY$5,T$5,$X34:$BY34) -> 39963.536 | V34: =(O34/J34)^(1/(O$5-J$5))-1 -> 0.28404509 | W34: =(T34/O34)^(1/(T$5-O$5))-1 -> 0.13931806 | Y34: =SUM(Y35:Y41) -> 2126 | Z34: =SUM(Z35:Z41) -> 2266 | AA34: =SUM(AA35:AA41) -> 2473 | AB34: =SUM(AB35:AB41) -> 1333 | AC34: =SUM(AC35:AC41) -> 1698 | AD34: =SUM(AD35:AD41) -> 1696 | AE34: =SUM(AE35:AE41) -> 1846 | AF34: =SUM(AF35:AF41) -> 2920 | ... BX34: =SUM(BX35:BX41) -> 10466.666
B35: =B11 -> Electronic Materials | G35: =G$10 -> JPY M | H35: =+SUMIF($X$5:$BY$5,H$5,$X35:$BY35) -> 1970.07 | I35: =+SUMIF($X$5:$BY$5,I$5,$X35:$BY35) -> 2831.43 | J35: =+SUMIF($X$5:$BY$5,J$5,$X35:$BY35) -> 2547.22 | K35: =+SUMIF($X$5:$BY$5,K$5,$X35:$BY35) -> 2973.05 | L35: =+SUMIF($X$5:$BY$5,L$5,$X35:$BY35) -> 3373.66 | M35: =+SUMIF($X$5:$BY$5,M$5,$X35:$BY35) -> 5382 | N35: =+SUMIF($X$5:$BY$5,N$5,$X35:$BY35) -> 13880 | O35: =+SUMIF($X$5:$BY$5,O$5,$X35:$BY35) -> 19391 | ... T35: =+SUMIF($X$5:$BY$5,T$5,$X35:$BY35) -> 36494.34 | Y35: ='3FS'!Y43 -> 541.26 | Z35: ='3FS'!Z43 -> 481.12 | AA35: ='3FS'!AA43 -> 538.35 | AB35: ='3FS'!AB43 -> 409.34 | AC35: ='3FS'!AC43 -> 574.24 | AD35: ='3FS'!AD43 -> 615.95 | AE35: ='3FS'!AE43 -> 696.46 | AF35: ='3FS'!AF43 -> 944.78 | ... BE35: ='3FS'!BE43 -> 7036 | BF35: =BF79 -> 7240.8159 | BG35: =BG79 -> 6670.3097 | BH35: =BH79 -> 7196.3575 | BI35: =BI79 -> 7048.888 | BJ35: =BJ79 -> 7602.3859 | BK35: =BK79 -> 7973.2005 | BL35: =BL79 -> 9304.7129 | BM35: =BM79 -> 8022.5672 | ... BX35: =BX79 -> 9498.0834
B36: =B12 -> Medical | G36: =G$10 -> JPY M | H36: =+SUMIF($X$5:$BY$5,H$5,$X36:$BY36) -> 553.52 | I36: =+SUMIF($X$5:$BY$5,I$5,$X36:$BY36) -> 390.72 | J36: =+SUMIF($X$5:$BY$5,J$5,$X36:$BY36) -> 270.16 | K36: =+SUMIF($X$5:$BY$5,K$5,$X36:$BY36) -> 224.4 | L36: =+SUMIF($X$5:$BY$5,L$5,$X36:$BY36) -> 97.68 | M36: =+SUMIF($X$5:$BY$5,M$5,$X36:$BY36) -> 2389 | N36: =+SUMIF($X$5:$BY$5,N$5,$X36:$BY36) -> 2381 | O36: =+SUMIF($X$5:$BY$5,O$5,$X36:$BY36) -> 2431 | ... T36: =+SUMIF($X$5:$BY$5,T$5,$X36:$BY36) -> 3537.773 | Y36: ='3FS'!Y44 -> -28.16 | Z36: ='3FS'!Z44 -> 192.72 | AA36: ='3FS'!AA44 -> 324.72 | AB36: ='3FS'!AB44 -> 64.24 | AC36: ='3FS'!AC44 -> -96.8 | AD36: ='3FS'!AD44 -> 161.04 | AE36: ='3FS'!AE44 -> 218.24 | AF36: ='3FS'!AF44 -> 108.24 | ... BE36: ='3FS'!BE44 -> 705 | BF36: =BF159 -> 669.93093 | BG36: =BG159 -> 748.7587 | BH36: =BH159 -> 741.61165 | BI36: =BI159 -> 787.74496 | BJ36: =BJ159 -> 703.42748 | BK36: =BK159 -> 786.19664 | BL36: =BL159 -> 778.69223 | BM36: =BM159 -> 827.1322 | ... BX36: =BX159 -> 901.4336
B37: =B13 -> Composite Materials | G37: =G$10 -> JPY M | H37: =+SUMIF($X$5:$BY$5,H$5,$X37:$BY37) -> 3937 | I37: =+SUMIF($X$5:$BY$5,I$5,$X37:$BY37) -> 3091 | J37: =+SUMIF($X$5:$BY$5,J$5,$X37:$BY37) -> 2368 | K37: =+SUMIF($X$5:$BY$5,K$5,$X37:$BY37) -> 1733 | L37: =+SUMIF($X$5:$BY$5,L$5,$X37:$BY37) -> -1680 | M37: =+SUMIF($X$5:$BY$5,M$5,$X37:$BY37) -> -731 | N37: =+SUMIF($X$5:$BY$5,N$5,$X37:$BY37) -> -900 | O37: =+SUMIF($X$5:$BY$5,O$5,$X37:$BY37) -> -122 | ... T37: =+SUMIF($X$5:$BY$5,T$5,$X37:$BY37) -> -57.462009 | Y37: ='3FS'!Y45 -> 1054 | Z37: ='3FS'!Z45 -> 1126 | AA37: ='3FS'!AA45 -> 974 | AB37: ='3FS'!AB45 -> 783 | AC37: ='3FS'!AC45 -> 659 | AD37: ='3FS'!AD45 -> 396 | AE37: ='3FS'!AE45 -> 659 | AF37: ='3FS'!AF45 -> 1377 | ... BE37: ='3FS'!BE45 -> 0 | BF37: =BF169 -> -113.4776 | BG37: =BG169 -> -41.632 | BH37: =BH169 -> 69.722 | BI37: =BI169 -> 2.298 | BJ37: =BJ169 -> -111.09133 | BK37: =BK169 -> -39.53056 | BL37: =BL169 -> 71.94026 | BM37: =BM169 -> 3.87596 | ... BX37: =BX169 -> 76.601877
B38: =B14 -> Materials Solution | G38: =G$10 -> JPY M | H38: =+SUMIF($X$5:$BY$5,H$5,$X38:$BY38) -> 542.61 | I38: =+SUMIF($X$5:$BY$5,I$5,$X38:$BY38) -> 724.65 | J38: =+SUMIF($X$5:$BY$5,J$5,$X38:$BY38) -> 640.82 | K38: =+SUMIF($X$5:$BY$5,K$5,$X38:$BY38) -> 735.55 | L38: =+SUMIF($X$5:$BY$5,L$5,$X38:$BY38) -> 813.26 | M38: =+SUMIF($X$5:$BY$5,M$5,$X38:$BY38) -> 824 | N38: =+SUMIF($X$5:$BY$5,N$5,$X38:$BY38) -> 839 | O38: =+SUMIF($X$5:$BY$5,O$5,$X38:$BY38) -> 588 | ... T38: =+SUMIF($X$5:$BY$5,T$5,$X38:$BY38) -> 579.51773 | Y38: ='3FS'!Y46 -> 124.5 | Z38: ='3FS'!Z46 -> 140.36 | AA38: ='3FS'!AA46 -> 171.93 | AB38: ='3FS'!AB46 -> 105.82 | AC38: ='3FS'!AC46 -> 122.96 | AD38: ='3FS'!AD46 -> 168.01 | AE38: ='3FS'!AE46 -> 194.9 | AF38: ='3FS'!AF46 -> 238.78 | ... BE38: ='3FS'!BE46 -> 222 | BF38: =BF179 -> 119.091 | BG38: =BG179 -> 133.295 | BH38: =BH179 -> 131.758 | BI38: =BI179 -> 134.6725 | BJ38: =BJ179 -> 122.66373 | BK38: =BK179 -> 137.29385 | BL38: =BL179 -> 135.71074 | BM38: =BM179 -> 138.71268 | ... BX38: =BX179 -> 148.29479
B39: =B15 -> Insulation Materials | G39: =G$10 -> JPY M | H39: =+SUMIF($X$5:$BY$5,H$5,$X39:$BY39) -> 1381.08 | I39: =+SUMIF($X$5:$BY$5,I$5,$X39:$BY39) -> 1984.92 | J39: =+SUMIF($X$5:$BY$5,J$5,$X39:$BY39) -> 1785.68 | K39: =+SUMIF($X$5:$BY$5,K$5,$X39:$BY39) -> 2084.2 | L39: =+SUMIF($X$5:$BY$5,L$5,$X39:$BY39) -> 2365.04 | M39: =+SUMIF($X$5:$BY$5,M$5,$X39:$BY39) -> 914 | N39: =+SUMIF($X$5:$BY$5,N$5,$X39:$BY39) -> 693 | O39: =+SUMIF($X$5:$BY$5,O$5,$X39:$BY39) -> 202 | ... T39: =+SUMIF($X$5:$BY$5,T$5,$X39:$BY39) -> 1059.0081 | Y39: ='3FS'!Y47 -> 379.44 | Z39: ='3FS'!Z47 -> 337.28 | AA39: ='3FS'!AA47 -> 377.4 | AB39: ='3FS'!AB47 -> 286.96 | AC39: ='3FS'!AC47 -> 402.56 | AD39: ='3FS'!AD47 -> 431.8 | AE39: ='3FS'!AE47 -> 488.24 | AF39: ='3FS'!AF47 -> 662.32 | ... BE39: ='3FS'!BE47 -> 251 | BF39: =BF189 -> -102.735 | BG39: =BG189 -> 364.89 | BH39: =BH189 -> 163.74 | BI39: =BI189 -> 272.995 | BJ39: =BJ189 -> -81.16675 | BK39: =BK189 -> 388.6145 | BL39: =BL189 -> 185.107 | BM39: =BM189 -> 296.08975 | ... BX39: =BX189 -> 255.83444
B40: =B16 -> Other Business | G40: =G$10 -> JPY M | H40: =+SUMIF($X$5:$BY$5,H$5,$X40:$BY40) -> 328.54 | I40: =+SUMIF($X$5:$BY$5,I$5,$X40:$BY40) -> 594.53 | J40: =+SUMIF($X$5:$BY$5,J$5,$X40:$BY40) -> 400.41 | K40: =+SUMIF($X$5:$BY$5,K$5,$X40:$BY40) -> 570.9 | L40: =+SUMIF($X$5:$BY$5,L$5,$X40:$BY40) -> 244.33 | M40: =+SUMIF($X$5:$BY$5,M$5,$X40:$BY40) -> 447 | N40: =+SUMIF($X$5:$BY$5,N$5,$X40:$BY40) -> 409 | O40: =+SUMIF($X$5:$BY$5,O$5,$X40:$BY40) -> 488 | ... T40: =+SUMIF($X$5:$BY$5,T$5,$X40:$BY40) -> 1253.8205 | Y40: ='3FS'!Y48 -> 115.86 | Z40: ='3FS'!Z48 -> 72.59 | AA40: ='3FS'!AA48 -> 57.86 | AB40: ='3FS'!AB48 -> 82.23 | AC40: ='3FS'!AC48 -> 137.86 | AD40: ='3FS'!AD48 -> 186.52 | AE40: ='3FS'!AE48 -> 214.86 | AF40: ='3FS'!AF48 -> 55.29 | ... BE40: ='3FS'!BE48 -> 213 | BF40: =BF199 -> 193.9532 | BG40: =BG199 -> 186.5404 | BH40: =BH199 -> 197.298 | BI40: =BI199 -> 216.056 | BJ40: =BJ199 -> 219.16712 | BK40: =BK199 -> 210.79065 | BL40: =BL199 -> 222.94674 | BM40: =BM199 -> 244.14328 | ... BX40: =BX199 -> 321.68918
B41: Adjustments | G41: =G$10 -> JPY M | H41: =+SUMIF($X$5:$BY$5,H$5,$X41:$BY41) -> -514.82 | I41: =+SUMIF($X$5:$BY$5,I$5,$X41:$BY41) -> -1457.25 | J41: =+SUMIF($X$5:$BY$5,J$5,$X41:$BY41) -> -2048.29 | K41: =+SUMIF($X$5:$BY$5,K$5,$X41:$BY41) -> -1053.1 | L41: =+SUMIF($X$5:$BY$5,L$5,$X41:$BY41) -> -333.97 | M41: =+SUMIF($X$5:$BY$5,M$5,$X41:$BY41) -> -839 | N41: =+SUMIF($X$5:$BY$5,N$5,$X41:$BY41) -> -858 | O41: =+SUMIF($X$5:$BY$5,O$5,$X41:$BY41) -> -2160 | ... T41: =+SUMIF($X$5:$BY$5,T$5,$X41:$BY41) -> -2903.4612 | Y41: ='3FS'!Y49 -> -60.9 | Z41: ='3FS'!Z49 -> -84.07 | AA41: ='3FS'!AA49 -> 28.74 | AB41: ='3FS'!AB49 -> -398.59 | AC41: ='3FS'!AC49 -> -101.82 | AD41: ='3FS'!AD49 -> -263.32 | AE41: ='3FS'!AE49 -> -625.7 | AF41: ='3FS'!AF49 -> -466.41 | ... BE41: ='3FS'!BE49 -> -486 | BF41: =BF206 -> -510.98198 | BG41: =BG206 -> -522.38257 | BH41: =BH206 -> -535.5701 | BI41: =BI206 -> -567.10193 | BJ41: =BJ206 -> -577.61709 | BK41: =BK206 -> -596.26166 | BL41: =BL206 -> -614.10924 | BM41: =BM206 -> -628.60378 | ... BX41: =BX206 -> -735.27083
B43: OPM | G43: % | H43: =IFERROR(H34/H10,"nm") -> 0.099623284 | I43: =IFERROR(I34/I10,"nm") -> 0.095193654 | J43: =IFERROR(J34/J10,"nm") -> 0.075757383 | K43: =IFERROR(K34/K10,"nm") -> 0.086473367 | L43: =IFERROR(L34/L10,"nm") -> 0.055753587 | M43: =IFERROR(M34/M10,"nm") -> 0.089930295 | N43: =IFERROR(N34/N10,"nm") -> 0.15081673 | O43: =IFERROR(O34/O10,"nm") -> 0.17608648 | ... T43: =IFERROR(T34/T10,"nm") -> 0.20646153 | Y43: =IFERROR(Y34/Y10,"nm") -> 0.10397613 | Z43: =IFERROR(Z34/Z10,"nm") -> 0.107628 | AA43: =IFERROR(AA34/AA10,"nm") -> 0.11408405 | AB43: =IFERROR(AB34/AB10,"nm") -> 0.069746756 | AC43: =IFERROR(AC34/AC10,"nm") -> 0.082347236 | AD43: =IFERROR(AD34/AD10,"nm") -> 0.076603433 | AE43: =IFERROR(AE34/AE10,"nm") -> 0.086678875 | AF43: =IFERROR(AF34/AF10,"nm") -> 0.13479204 | ... BX43: =IFERROR(BX34/BX10,"nm") -> 0.21352676
B44: =B35 -> Electronic Materials | G44: % | H44: =IFERROR(H35/H11,"nm") -> 0.099564107 | I44: =IFERROR(I35/I11,"nm") -> 0.11978196 | J44: =IFERROR(J35/J11,"nm") -> 0.1089876 | K44: =IFERROR(K35/K11,"nm") -> 0.11713337 | L44: =IFERROR(L35/L11,"nm") -> 0.13210198 | M44: =IFERROR(M35/M11,"nm") -> 0.18052618 | N44: =IFERROR(N35/N11,"nm") -> 0.33927306 | O44: =IFERROR(O35/O11,"nm") -> 0.39360601 | ... T44: =IFERROR(T35/T11,"nm") -> 0.38549322 | AK44: =IFERROR(AK35/AK11,"nm") -> 0.11267622 | AL44: =IFERROR(AL35/AL11,"nm") -> 0.11176928 | AM44: =IFERROR(AM35/AM11,"nm") -> 0.095798168 | AN44: =IFERROR(AN35/AN11,"nm") -> 0.14435162 | AO44: =IFERROR(AO35/AO11,"nm") -> 0.17966135 | AP44: =IFERROR(AP35/AP11,"nm") -> 0.17360427 | AQ44: =IFERROR(AQ35/AQ11,"nm") -> 0.12351646 | AR44: =IFERROR(AR35/AR11,"nm") -> 0.01179684 | ... BX44: =IFERROR(BX35/BX11,"nm") -> 0.3926934
B45: =B36 -> Medical | G45: % | H45: =IFERROR(H36/H12,"nm") -> 0.045939235 | I45: =IFERROR(I36/I12,"nm") -> 0.029497741 | J45: =IFERROR(J36/J12,"nm") -> 0.022740741 | K45: =IFERROR(K36/K12,"nm") -> 0.016047829 | L45: =IFERROR(L36/L12,"nm") -> 0.0066233069 | M45: =IFERROR(M36/M12,"nm") -> 0.18805574 | N45: =IFERROR(N36/N12,"nm") -> 0.17503492 | O45: =IFERROR(O36/O12,"nm") -> 0.17552347 | ... T45: =IFERROR(T36/T12,"nm") -> 0.19649903 | AK45: =IFERROR(AK36/AK12,"nm") -> -0.010351468 | AL45: =IFERROR(AL36/AL12,"nm") -> 0.029546 | AM45: =IFERROR(AM36/AM12,"nm") -> 0.068559186 | AN45: =IFERROR(AN36/AN12,"nm") -> -0.021099245 | AO45: =IFERROR(AO36/AO12,"nm") -> -0.0044853106 | AP45: =IFERROR(AP36/AP12,"nm") -> 0.023701788 | AQ45: =IFERROR(AQ36/AQ12,"nm") -> 0.019890261 | AR45: =IFERROR(AR36/AR12,"nm") -> -0.020091324 | ... BX45: =IFERROR(BX36/BX12,"nm") -> 0.19649903
B46: =B37 -> Composite Materials | G46: % | H46: =IFERROR(H37/H13,"nm") -> 0.31019149 | I46: =IFERROR(I37/I13,"nm") -> 0.2574083 | J46: =IFERROR(J37/J13,"nm") -> 0.21334256 | K46: =IFERROR(K37/K13,"nm") -> 0.15465482 | L46: =IFERROR(L37/L13,"nm") -> -0.14602804 | M46: =IFERROR(M37/M13,"nm") -> -0.058146564 | N46: =IFERROR(N37/N13,"nm") -> -0.066795309 | O46: =IFERROR(O37/O13,"nm") -> -0.0091037982 | ... T46: =IFERROR(T37/T13,"nm") -> -0.0035031617 | AK46: =IFERROR(AK37/AK13,"nm") -> 0.12316882 | AL46: =IFERROR(AL37/AL13,"nm") -> 0.32423494 | AM46: =IFERROR(AM37/AM13,"nm") -> 0.19932376 | AN46: =IFERROR(AN37/AN13,"nm") -> -0.010155996 | AO46: =IFERROR(AO37/AO13,"nm") -> 0.12945219 | AP46: =IFERROR(AP37/AP13,"nm") -> -0.020654329 | AQ46: =IFERROR(AQ37/AQ13,"nm") -> -0.17319191 | AR46: =IFERROR(AR37/AR13,"nm") -> -0.62380497 | ... BX46: =IFERROR(BX37/BX13,"nm") -> 0.018955728
B47: =B38 -> Materials Solution | G47: % | H47: =IFERROR(H38/H14,"nm") -> 0.0471196 | I47: =IFERROR(I38/I14,"nm") -> 0.07005971 | J47: =IFERROR(J38/J14,"nm") -> 0.078699968 | K47: =IFERROR(K38/K14,"nm") -> 0.084951498 | L47: =IFERROR(L38/L14,"nm") -> 0.08986209 | M47: =IFERROR(M38/M14,"nm") -> 0.090600924 | N47: =IFERROR(N38/N14,"nm") -> 0.088961934 | O47: =IFERROR(O38/O14,"nm") -> 0.061797162 | ... T47: =IFERROR(T38/T14,"nm") -> 0.05 | AK47: =IFERROR(AK38/AK14,"nm") -> 0.07551524 | AL47: =IFERROR(AL38/AL14,"nm") -> 0.081392859 | AM47: =IFERROR(AM38/AM14,"nm") -> 0.072671969 | AN47: =IFERROR(AN38/AN14,"nm") -> 0.11253991 | AO47: =IFERROR(AO38/AO14,"nm") -> 0.14719167 | AP47: =IFERROR(AP38/AP14,"nm") -> 0.13014862 | AQ47: =IFERROR(AQ38/AQ14,"nm") -> 0.074231621 | AR47: =IFERROR(AR38/AR14,"nm") -> 0.0029396906 | ... BX47: =IFERROR(BX38/BX14,"nm") -> 0.05
B48: =B39 -> Insulation Materials | G48: % | H48: =IFERROR(H39/H15,"nm") -> 0.093229286 | I48: =IFERROR(I39/I15,"nm") -> 0.13642737 | J48: =IFERROR(J39/J15,"nm") -> 0.14149469 | K48: =IFERROR(K39/K15,"nm") -> 0.16631396 | L48: =IFERROR(L39/L15,"nm") -> 0.16976619 | M48: =IFERROR(M39/M15,"nm") -> 0.062121257 | N48: =IFERROR(N39/N15,"nm") -> 0.045234987 | O48: =IFERROR(O39/O15,"nm") -> 0.013345666 | ... T48: =IFERROR(T39/T15,"nm") -> 0.049137161 | AK48: =IFERROR(AK39/AK15,"nm") -> 0.17252931 | AL48: =IFERROR(AL39/AL15,"nm") -> 0.15137016 | AM48: =IFERROR(AM39/AM15,"nm") -> 0.12180391 | AN48: =IFERROR(AN39/AN15,"nm") -> 0.2226254 | AO48: =IFERROR(AO39/AO15,"nm") -> 0.30863121 | AP48: =IFERROR(AP39/AP15,"nm") -> 0.2391595 | AQ48: =IFERROR(AQ39/AQ15,"nm") -> 0.13645473 | AR48: =IFERROR(AR39/AR15,"nm") -> 0.01178744 | ... BX48: =IFERROR(BX39/BX15,"nm") -> 0.049252499
B49: =B40 -> Other Business | G49: % | H49: =IFERROR(H40/H16,"nm") -> 0.028737271 | I49: =IFERROR(I40/I16,"nm") -> 0.049812824 | J49: =IFERROR(J40/J16,"nm") -> 0.034484986 | K49: =IFERROR(K40/K16,"nm") -> 0.046458978 | L49: =IFERROR(L40/L16,"nm") -> 0.019154289 | M49: =IFERROR(M40/M16,"nm") -> 0.031141579 | N49: =IFERROR(N40/N16,"nm") -> 0.025101264 | O49: =IFERROR(O40/O16,"nm") -> 0.028606601 | ... T49: =IFERROR(T40/T16,"nm") -> 0.04 | AK49: =IFERROR(AK40/AK16,"nm") -> 0.033343679 | AL49: =IFERROR(AL40/AL16,"nm") -> 0.070812309 | AM49: =IFERROR(AM40/AM16,"nm") -> 0.045915927 | AN49: =IFERROR(AN40/AN16,"nm") -> 0.036903883 | AO49: =IFERROR(AO40/AO16,"nm") -> 0.021383956 | AP49: =IFERROR(AP40/AP16,"nm") -> 0.020723564 | AQ49: =IFERROR(AQ40/AQ16,"nm") -> 0.015346778 | AR49: =IFERROR(AR40/AR16,"nm") -> 0.018474552 | ... BX49: =IFERROR(BX40/BX16,"nm") -> 0.04
B51: Mix
B52: =B35 -> Electronic Materials | G52: % | H52: =IFERROR(H35/H$34,"nm") -> 0.24031105 | I52: =IFERROR(I35/I$34,"nm") -> 0.34698897 | J52: =IFERROR(J35/J$34,"nm") -> 0.42709926 | K52: =IFERROR(K35/K$34,"nm") -> 0.40906026 | L52: =IFERROR(L35/L$34,"nm") -> 0.69132377 | M52: =IFERROR(M35/M$34,"nm") -> 0.64178393 | N52: =IFERROR(N35/N$34,"nm") -> 0.84407687 | O52: =IFERROR(O35/O$34,"nm") -> 0.93145355 | ... T52: =IFERROR(T35/T$34,"nm") -> 0.91319096 | AK52: =IFERROR(AK35/AK$34,"nm") -> 0.4130951 | AL52: =IFERROR(AL35/AL$34,"nm") -> 0.30152747 | AM52: =IFERROR(AM35/AM$34,"nm") -> 0.34059779 | AN52: =IFERROR(AN35/AN$34,"nm") -> 0.62722257 | AO52: =IFERROR(AO35/AO$34,"nm") -> 0.52564868 | AP52: =IFERROR(AP35/AP$34,"nm") -> 0.61211694 | AQ52: =IFERROR(AQ35/AQ$34,"nm") -> 0.58215545 | AR52: =IFERROR(AR35/AR$34,"nm") -> -0.061316062 | ... BX52: =IFERROR(BX35/BX$34,"nm") -> 0.90746022
B53: =B36 -> Medical | G53: % | H53: =IFERROR(H36/H$34,"nm") -> 0.067518907 | I53: =IFERROR(I36/I$34,"nm") -> 0.047882353 | J53: =IFERROR(J36/J$34,"nm") -> 0.045298457 | K53: =IFERROR(K36/K$34,"nm") -> 0.030875069 | L53: =IFERROR(L36/L$34,"nm") -> 0.020016393 | M53: =IFERROR(M36/M$34,"nm") -> 0.28487956 | N53: =IFERROR(N36/N$34,"nm") -> 0.14479445 | O53: =IFERROR(O36/O$34,"nm") -> 0.11677395 | ... T53: =IFERROR(T36/T$34,"nm") -> 0.088525024 | AK53: =IFERROR(AK36/AK$34,"nm") -> -0.022350856 | AL53: =IFERROR(AL36/AL$34,"nm") -> 0.04834301 | AM53: =IFERROR(AM36/AM$34,"nm") -> 0.13074869 | AN53: =IFERROR(AN36/AN$34,"nm") -> -0.044190949 | AO53: =IFERROR(AO36/AO$34,"nm") -> -0.006735553 | AP53: =IFERROR(AP36/AP$34,"nm") -> 0.048790323 | AQ53: =IFERROR(AQ36/AQ$34,"nm") -> 0.061346154 | AR53: =IFERROR(AR36/AR$34,"nm") -> 0.060186528 | ... BX53: =IFERROR(BX36/BX$34,"nm") -> 0.086124231
B54: =B37 -> Composite Materials | G54: % | H54: =IFERROR(H37/H$34,"nm") -> 0.48023908 | I54: =IFERROR(I37/I$34,"nm") -> 0.37879902 | J54: =IFERROR(J37/J$34,"nm") -> 0.39704896 | K54: =IFERROR(K37/K$34,"nm") -> 0.23844249 | L54: =IFERROR(L37/L$34,"nm") -> -0.3442623 | M54: =IFERROR(M37/M$34,"nm") -> -0.087169091 | N54: =IFERROR(N37/N$34,"nm") -> -0.054731209 | O54: =IFERROR(O37/O$34,"nm") -> -0.0058603132 | ... T54: =IFERROR(T37/T$34,"nm") -> -0.001437861 | AK54: =IFERROR(AK37/AK$34,"nm") -> 0.20023627 | AL54: =IFERROR(AL37/AL$34,"nm") -> 0.38008039 | AM54: =IFERROR(AM37/AM$34,"nm") -> 0.33255949 | AN54: =IFERROR(AN37/AN$34,"nm") -> -0.018598884 | AO54: =IFERROR(AO37/AO$34,"nm") -> 0.1637964 | AP54: =IFERROR(AP37/AP$34,"nm") -> -0.030241935 | AQ54: =IFERROR(AQ37/AQ$34,"nm") -> -0.38621795 | AR54: =IFERROR(AR37/AR$34,"nm") -> 1.6227979 | ... BX54: =IFERROR(BX37/BX$34,"nm") -> 0.0073186509
B55: =B38 -> Materials Solution | G55: % | H55: =IFERROR(H38/H$34,"nm") -> 0.066188095 | I55: =IFERROR(I38/I$34,"nm") -> 0.088805147 | J55: =IFERROR(J38/J$34,"nm") -> 0.10744802 | K55: =IFERROR(K38/K$34,"nm") -> 0.10120391 | L55: =IFERROR(L38/L$34,"nm") -> 0.16665164 | M55: =IFERROR(M38/M$34,"nm") -> 0.098259003 | N55: =IFERROR(N38/N$34,"nm") -> 0.051021649 | O55: =IFERROR(O38/O$34,"nm") -> 0.028244788 | ... T55: =IFERROR(T38/T$34,"nm") -> 0.014501163 | AK55: =IFERROR(AK38/AK$34,"nm") -> 0.09490254 | AL55: =IFERROR(AL38/AL$34,"nm") -> 0.078088432 | AM55: =IFERROR(AM38/AM$34,"nm") -> 0.098589669 | AN55: =IFERROR(AN38/AN$34,"nm") -> 0.14269684 | AO55: =IFERROR(AO38/AO$34,"nm") -> 0.12371986 | AP55: =IFERROR(AP38/AP$34,"nm") -> 0.15179435 | AQ55: =IFERROR(AQ38/AQ$34,"nm") -> 0.14640224 | AR55: =IFERROR(AR38/AR$34,"nm") -> -0.0063316062 | ... BX55: =IFERROR(BX38/BX$34,"nm") -> 0.014168292
B56: =B39 -> Insulation Materials | G56: % | H56: =IFERROR(H39/H$34,"nm") -> 0.16846548 | I56: =IFERROR(I39/I$34,"nm") -> 0.24325 | J56: =IFERROR(J39/J$34,"nm") -> 0.29940979 | K56: =IFERROR(K39/K$34,"nm") -> 0.2867639 | L56: =IFERROR(L39/L$34,"nm") -> 0.48463934 | M56: =IFERROR(M39/M$34,"nm") -> 0.10899118 | N56: =IFERROR(N39/N$34,"nm") -> 0.042143031 | O56: =IFERROR(O39/O$34,"nm") -> 0.0097031415 | ... T56: =IFERROR(T39/T$34,"nm") -> 0.026499358 | AK56: =IFERROR(AK39/AK$34,"nm") -> 0.28959244 | AL56: =IFERROR(AL39/AL$34,"nm") -> 0.21138008 | AM56: =IFERROR(AM39/AM$34,"nm") -> 0.23876959 | AN56: =IFERROR(AN39/AN$34,"nm") -> 0.43970242 | AO56: =IFERROR(AO39/AO$34,"nm") -> 0.36849598 | AP56: =IFERROR(AP39/AP$34,"nm") -> 0.4291129 | AQ56: =IFERROR(AQ39/AQ$34,"nm") -> 0.40810897 | AR56: =IFERROR(AR39/AR$34,"nm") -> -0.042984456 | ... BX56: =IFERROR(BX39/BX$34,"nm") -> 0.024442782
B57: =B40 -> Other Business | G57: % | H57: =IFERROR(H40/H$34,"nm") -> 0.040075628 | I57: =IFERROR(I40/I$34,"nm") -> 0.072859069 | J57: =IFERROR(J40/J$34,"nm") -> 0.067137827 | K57: =IFERROR(K40/K$34,"nm") -> 0.078549807 | L57: =IFERROR(L40/L$34,"nm") -> 0.050067623 | M57: =IFERROR(M40/M$34,"nm") -> 0.053303124 | N57: =IFERROR(N40/N$34,"nm") -> 0.024872294 | O57: =IFERROR(O40/O$34,"nm") -> 0.023441253 | ... T57: =IFERROR(T40/T$34,"nm") -> 0.031374113 | AK57: =IFERROR(AK40/AK$34,"nm") -> 0.05774365 | AL57: =IFERROR(AL40/AL$34,"nm") -> 0.09376954 | AM57: =IFERROR(AM40/AM$34,"nm") -> 0.080783517 | AN57: =IFERROR(AN40/AN$34,"nm") -> 0.076875387 | AO57: =IFERROR(AO40/AO$34,"nm") -> 0.029728282 | AP57: =IFERROR(AP40/AP$34,"nm") -> 0.035010081 | AQ57: =IFERROR(AQ40/AQ$34,"nm") -> 0.037099359 | AR57: =IFERROR(AR40/AR$34,"nm") -> -0.052735751 | ... BX57: =IFERROR(BX40/BX$34,"nm") -> 0.030734636
B58: =B41 -> Adjustments | G58: % | H58: =IFERROR(H41/H$34,"nm") -> -0.062798243 | I58: =IFERROR(I41/I$34,"nm") -> -0.17858456 | J58: =IFERROR(J41/J$34,"nm") -> -0.34344232 | K58: =IFERROR(K41/K$34,"nm") -> -0.14489543 | L58: =IFERROR(L41/L$34,"nm") -> -0.068436475 | M58: =IFERROR(M41/M$34,"nm") -> -0.1000477 | N58: =IFERROR(N41/N$34,"nm") -> -0.052177086 | O58: =IFERROR(O41/O$34,"nm") -> -0.10375636 | ... T58: =IFERROR(T41/T$34,"nm") -> -0.072652762 | AK58: =IFERROR(AK41/AK$34,"nm") -> -0.033219138 | AL58: =IFERROR(AL41/AL$34,"nm") -> -0.11318892 | AM58: =IFERROR(AM41/AM$34,"nm") -> -0.22204875 | AN58: =IFERROR(AN41/AN$34,"nm") -> -0.22370738 | AO58: =IFERROR(AO41/AO$34,"nm") -> -0.20465365 | AP58: =IFERROR(AP41/AP$34,"nm") -> -0.24658266 | AQ58: =IFERROR(AQ41/AQ$34,"nm") -> 0.15110577 | AR58: =IFERROR(AR41/AR$34,"nm") -> -0.51961658 | ... BX58: =IFERROR(BX41/BX$34,"nm") -> -0.070248807
B60: Y/Y | I60: =IFERROR(I34/H34-1,"nm") -> -0.0046352769 | J60: =IFERROR(J34/I34-1,"nm") -> -0.26911765 | K60: =IFERROR(K34/J34-1,"nm") -> 0.2186452 | L60: =IFERROR(L34/K34-1,"nm") -> -0.32856357 | M60: =IFERROR(M34/L34-1,"nm") -> 0.71844262 | N60: =IFERROR(N34/M34-1,"nm") -> 0.96088719 | O60: =IFERROR(O34/N34-1,"nm") -> 0.26599368 | P60: =IFERROR(P34/O34-1,"nm") -> 0.48632399 | ... T60: =IFERROR(T34/S34-1,"nm") -> 0.042739542
B61: =B35 -> Electronic Materials | G61: % | I61: =IFERROR(I35/H35-1,"nm") -> 0.43722304 | J61: =IFERROR(J35/I35-1,"nm") -> -0.10037684 | K61: =IFERROR(K35/J35-1,"nm") -> 0.16717441 | L61: =IFERROR(L35/K35-1,"nm") -> 0.13474715 | M61: =IFERROR(M35/L35-1,"nm") -> 0.59530006 | N61: =IFERROR(N35/M35-1,"nm") -> 1.5789669 | O61: =IFERROR(O35/N35-1,"nm") -> 0.39704611 | P61: =IFERROR(P35/O35-1,"nm") -> 0.45136832 | ... T61: =IFERROR(T35/S35-1,"nm") -> 0.039138145 | AK61: =IFERROR(AK35/AG35-1,"nm") -> -0.23297872 | AL61: =IFERROR(AL35/AH35-1,"nm") -> 0.42331288 | AM61: =IFERROR(AM35/AI35-1,"nm") -> 0.21485944 | AN61: =IFERROR(AN35/AJ35-1,"nm") -> 0.49213162 | AO61: =IFERROR(AO35/AK35-1,"nm") -> 0.96393897 | AP61: =IFERROR(AP35/AL35-1,"nm") -> 0.79885057 | AQ61: =IFERROR(AQ35/AM35-1,"nm") -> 0.23801653 | AR61: =IFERROR(AR35/AN35-1,"nm") -> -0.94151486 | ... BX61: =IFERROR(BX35/BT35-1,"nm") -> 0.036844126
B62: =B36 -> Medical | G62: % | I62: =IFERROR(I36/H36-1,"nm") -> -0.29411765 | J62: =IFERROR(J36/I36-1,"nm") -> -0.30855856 | K62: =IFERROR(K36/J36-1,"nm") -> -0.16938111 | L62: =IFERROR(L36/K36-1,"nm") -> -0.56470588 | M62: =IFERROR(M36/L36-1,"nm") -> 23.457412 | N62: =IFERROR(N36/M36-1,"nm") -> -0.0033486815 | O62: =IFERROR(O36/N36-1,"nm") -> 0.02099958 | P62: =IFERROR(P36/O36-1,"nm") -> 0.17865129 | ... T62: =IFERROR(T36/S36-1,"nm") -> 0.05 | AK62: =IFERROR(AK36/AG36-1,"nm") -> -2.9545455 | AL62: =IFERROR(AL36/AH36-1,"nm") -> 2.075 | AM62: =IFERROR(AM36/AI36-1,"nm") -> 0.1797235 | AN62: =IFERROR(AN36/AJ36-1,"nm") -> -3.8928571 | AO62: =IFERROR(AO36/AK36-1,"nm") -> -0.53488372 | AP62: =IFERROR(AP36/AL36-1,"nm") -> -0.10569106 | AQ62: =IFERROR(AQ36/AM36-1,"nm") -> -0.66015625 | AR62: =IFERROR(AR36/AN36-1,"nm") -> -0.18518519 | ... BX62: =IFERROR(BX36/BT36-1,"nm") -> 0.05
B63: =B37 -> Composite Materials | G63: % | I63: =IFERROR(I37/H37-1,"nm") -> -0.21488443 | J63: =IFERROR(J37/I37-1,"nm") -> -0.23390489 | K63: =IFERROR(K37/J37-1,"nm") -> -0.26815878 | L63: =IFERROR(L37/K37-1,"nm") -> -1.9694172 | M63: =IFERROR(M37/L37-1,"nm") -> -0.56488095 | N63: =IFERROR(N37/M37-1,"nm") -> 0.23119015 | O63: =IFERROR(O37/N37-1,"nm") -> -0.86444444 | P63: =IFERROR(P37/O37-1,"nm") -> -0.30010164 | ... T63: =IFERROR(T37/S37-1,"nm") -> -0.10067389 | AK63: =IFERROR(AK37/AG37-1,"nm") -> -0.68139098 | AL63: =IFERROR(AL37/AH37-1,"nm") -> 1.7275641 | AM63: =IFERROR(AM37/AI37-1,"nm") -> 0.19126819 | AN63: =IFERROR(AN37/AJ37-1,"nm") -> -1.0587084 | AO63: =IFERROR(AO37/AK37-1,"nm") -> 0.26253687 | AP63: =IFERROR(AP37/AL37-1,"nm") -> -1.0705053 | AQ63: =IFERROR(AQ37/AM37-1,"nm") -> -1.8411867 | AR63: =IFERROR(AR37/AN37-1,"nm") -> 51.2 | ... BX63: =IFERROR(BX37/BT37-1,"nm") -> 0.021125076
B64: =B38 -> Materials Solution | G64: % | I64: =IFERROR(I38/H38-1,"nm") -> 0.33548958 | J64: =IFERROR(J38/I38-1,"nm") -> -0.11568343 | K64: =IFERROR(K38/J38-1,"nm") -> 0.14782622 | L64: =IFERROR(L38/K38-1,"nm") -> 0.10564883 | M64: =IFERROR(M38/L38-1,"nm") -> 0.013206109 | N64: =IFERROR(N38/M38-1,"nm") -> 0.018203883 | O64: =IFERROR(O38/N38-1,"nm") -> -0.29916567 | P64: =IFERROR(P38/O38-1,"nm") -> 0.030857143 | ... T64: =IFERROR(T38/S38-1,"nm") -> 0.03 | AK64: =IFERROR(AK38/AG38-1,"nm") -> -0.26581064 | AL64: =IFERROR(AL38/AH38-1,"nm") -> 0.49091839 | AM64: =IFERROR(AM38/AI38-1,"nm") -> 0.20835112 | AN64: =IFERROR(AN38/AJ38-1,"nm") -> 0.40236398 | AO64: =IFERROR(AO38/AK38-1,"nm") -> 1.0120744 | AP64: =IFERROR(AP38/AL38-1,"nm") -> 0.72248913 | AQ64: =IFERROR(AQ38/AM38-1,"nm") -> 0.075587214 | AR64: =IFERROR(AR38/AN38-1,"nm") -> -0.9734544 | ... BX64: =IFERROR(BX38/BT38-1,"nm") -> 0.03
B65: =B39 -> Insulation Materials | G65: % | I65: =IFERROR(I39/H39-1,"nm") -> 0.43722304 | J65: =IFERROR(J39/I39-1,"nm") -> -0.10037684 | K65: =IFERROR(K39/J39-1,"nm") -> 0.16717441 | L65: =IFERROR(L39/K39-1,"nm") -> 0.13474715 | M65: =IFERROR(M39/L39-1,"nm") -> -0.61353719 | N65: =IFERROR(N39/M39-1,"nm") -> -0.24179431 | O65: =IFERROR(O39/N39-1,"nm") -> -0.70851371 | P65: =IFERROR(P39/O39-1,"nm") -> 2.3509653 | ... T65: =IFERROR(T39/S39-1,"nm") -> 0.10730991 | AK65: =IFERROR(AK39/AG39-1,"nm") -> -0.23297872 | AL65: =IFERROR(AL39/AH39-1,"nm") -> 0.42331288 | AM65: =IFERROR(AM39/AI39-1,"nm") -> 0.21485944 | AN65: =IFERROR(AN39/AJ39-1,"nm") -> 0.49213162 | AO65: =IFERROR(AO39/AK39-1,"nm") -> 0.96393897 | AP65: =IFERROR(AP39/AL39-1,"nm") -> 0.79885057 | AQ65: =IFERROR(AQ39/AM39-1,"nm") -> 0.23801653 | AR65: =IFERROR(AR39/AN39-1,"nm") -> -0.94151486 | ... BX65: =IFERROR(BX39/BT39-1,"nm") -> 0.10703172
B66: =B40 -> Other Business | G66: % | I66: =IFERROR(I40/H40-1,"nm") -> 0.80961222 | J66: =IFERROR(J40/I40-1,"nm") -> -0.32651002 | K66: =IFERROR(K40/J40-1,"nm") -> 0.42578857 | L66: =IFERROR(L40/K40-1,"nm") -> -0.57202662 | M66: =IFERROR(M40/L40-1,"nm") -> 0.8294929 | N66: =IFERROR(N40/M40-1,"nm") -> -0.085011186 | O66: =IFERROR(O40/N40-1,"nm") -> 0.19315403 | P66: =IFERROR(P40/O40-1,"nm") -> 0.62047459 | ... T66: =IFERROR(T40/S40-1,"nm") -> 0.13 | AK66: =IFERROR(AK40/AG40-1,"nm") -> 0.049152179 | AL66: =IFERROR(AL40/AH40-1,"nm") -> 4.0872304 | AM66: =IFERROR(AM40/AI40-1,"nm") -> 0.083443606 | AN66: =IFERROR(AN40/AJ40-1,"nm") -> -0.098116227 | AO66: =IFERROR(AO40/AK40-1,"nm") -> -0.20540098 | AP66: =IFERROR(AP40/AL40-1,"nm") -> -0.66915932 | AQ66: =IFERROR(AQ40/AM40-1,"nm") -> -0.66736116 | AR66: =IFERROR(AR40/AN40-1,"nm") -> -0.58959677 | ... BX66: =IFERROR(BX40/BT40-1,"nm") -> 0.13
B67: =B41 -> Adjustments | G67: % | I67: =IFERROR(I41/H41-1,"nm") -> 1.830601 | J67: =IFERROR(J41/I41-1,"nm") -> 0.40558586 | K67: =IFERROR(K41/J41-1,"nm") -> -0.48586382 | L67: =IFERROR(L41/K41-1,"nm") -> -0.68286962 | M67: =IFERROR(M41/L41-1,"nm") -> 1.5122017 | N67: =IFERROR(N41/M41-1,"nm") -> 0.022646007 | O67: =IFERROR(O41/N41-1,"nm") -> 1.5174825 | P67: =IFERROR(P41/O41-1,"nm") -> -0.048641364 | ... T67: =IFERROR(T41/S41-1,"nm") -> 0.064201151 | AK67: =IFERROR(AK41/AG41-1,"nm") -> -0.93732867 | AL67: =IFERROR(AL41/AH41-1,"nm") -> -0.4461636 | AM67: =IFERROR(AM41/AI41-1,"nm") -> -0.030706088 | AN67: =IFERROR(AN41/AJ41-1,"nm") -> 0.20839891 | AO67: =IFERROR(AO41/AK41-1,"nm") -> 8.5085349 | AP67: =IFERROR(AP41/AL41-1,"nm") -> 0.93039498 | AQ67: =IFERROR(AQ41/AM41-1,"nm") -> -1.4929036 | AR67: =IFERROR(AR41/AN41-1,"nm") -> -2.3896187 | ... BX67: =IFERROR(BX41/BT41-1,"nm") -> 0.063297132
A69: x | B69: Electronic Materials
B71: Revenue | G71: =G$10 -> JPY M | H71: =+SUMIF($X$5:$BY$5,H$5,$X71:$BY71) -> 19786.95 | I71: =+SUMIF($X$5:$BY$5,I$5,$X71:$BY71) -> 23638.2 | J71: =+SUMIF($X$5:$BY$5,J$5,$X71:$BY71) -> 23371.65 | K71: =+SUMIF($X$5:$BY$5,K$5,$X71:$BY71) -> 25381.75 | L71: =+SUMIF($X$5:$BY$5,L$5,$X71:$BY71) -> 25538.3 | M71: =+SUMIF($X$5:$BY$5,M$5,$X71:$BY71) -> 29812.85 | N71: =+SUMIF($X$5:$BY$5,N$5,$X71:$BY71) -> 40911 | O71: =+SUMIF($X$5:$BY$5,O$5,$X71:$BY71) -> 49265 | ... T71: =+SUMIF($X$5:$BY$5,T$5,$X71:$BY71) -> 94669.213 | V71: =(O71/J71)^(1/(O$5-J$5))-1 -> 0.16083321 | W71: =(T71/O71)^(1/(T$5-O$5))-1 -> 0.13955176 | Y71: =Y11 -> 4915.4 | Z71: =Z11 -> 4969.3 | AA71: =AA11 -> 5242.25 | AB71: =AB11 -> 4660 | AC71: =AC11 -> 5033.1 | AD71: =AD11 -> 6130.35 | AE71: =AE11 -> 6084.75 | AF71: =AF11 -> 6390 | ... BE71: =BE11 -> 14589 | BF71: =SUM(BF72:BF75) -> 15134.711 | BG71: =SUM(BG72:BG75) -> 15438.299 | BH71: =SUM(BH72:BH75) -> 16392.44 | BI71: =SUM(BI72:BI75) -> 17139.195 | BJ71: =SUM(BJ72:BJ75) -> 18369.786 | BK71: =SUM(BK72:BK75) -> 19144.496 | BL71: =SUM(BL72:BL75) -> 20394.819 | BM71: =SUM(BM72:BM75) -> 19946.043 | ... BX71: =SUM(BX72:BX75) -> 24187.021
B72: T-glass | G72: =G$10 -> JPY M | H72: =+SUMIF($X$5:$BY$5,H$5,$X72:$BY72) -> 0 | I72: =+SUMIF($X$5:$BY$5,I$5,$X72:$BY72) -> 0 | J72: =+SUMIF($X$5:$BY$5,J$5,$X72:$BY72) -> 0 | K72: =+SUMIF($X$5:$BY$5,K$5,$X72:$BY72) -> 0 | L72: =+SUMIF($X$5:$BY$5,L$5,$X72:$BY72) -> 0 | M72: =+SUMIF($X$5:$BY$5,M$5,$X72:$BY72) -> 9149 | N72: =+SUMIF($X$5:$BY$5,N$5,$X72:$BY72) -> 11478 | O72: =+SUMIF($X$5:$BY$5,O$5,$X72:$BY72) -> 13628 | ... T72: =+SUMIF($X$5:$BY$5,T$5,$X72:$BY72) -> 52247.338 | AS72: 1677 | AT72: 2243 | AU72: 2472 | AV72: 2757 | AW72: 2592 | AX72: 2680 | AY72: 2963 | AZ72: 3243 | BA72: 3193 | BB72: 3324 | BC72: 3508 | BD72: 3603 | BE72: 4763 | BF72: =BF85 -> 5056.8465 | BG72: =BG85 -> 5405.5945 | BH72: =BH85 -> 6103.0906 | BI72: =BI85 -> 6737.812 | BJ72: =BJ85 -> 7748.4838 | BK72: =BK85 -> 8759.1556 | BL72: =BL85 -> 9769.8274 | BM72: =BM85 -> 9648.9862 | ... BX72: =BX85 -> 13512.242 | BZ72: Mizuho
B73: Low-Dk | G73: =G$10 -> JPY M | H73: =+SUMIF($X$5:$BY$5,H$5,$X73:$BY73) -> 0 | I73: =+SUMIF($X$5:$BY$5,I$5,$X73:$BY73) -> 0 | J73: =+SUMIF($X$5:$BY$5,J$5,$X73:$BY73) -> 0 | K73: =+SUMIF($X$5:$BY$5,K$5,$X73:$BY73) -> 0 | L73: =+SUMIF($X$5:$BY$5,L$5,$X73:$BY73) -> 0 | M73: =+SUMIF($X$5:$BY$5,M$5,$X73:$BY73) -> 14309 | N73: =+SUMIF($X$5:$BY$5,N$5,$X73:$BY73) -> 24866 | O73: =+SUMIF($X$5:$BY$5,O$5,$X73:$BY73) -> 32378 | ... T73: =+SUMIF($X$5:$BY$5,T$5,$X73:$BY73) -> 52642.454 | AS73: 2623 | AT73: 3508 | AU73: 3866 | AV73: 4312 | AW73: 5615 | AX73: 5806 | AY73: 6419 | AZ73: 7026 | BA73: 7585 | BB73: 7898 | BC73: 8334 | BD73: 8561 | BE73: 9183 | BF73: =BF111 -> 9485.7422 | BG73: =BG111 -> 9960.0293 | BH73: =BH111 -> 10339.459 | BI73: =BI111 -> 10740.832 | BJ73: =BJ111 -> 11056.739 | BK73: =BK111 -> 11435.827 | BL73: =BL111 -> 11878.097 | BM73: =BM111 -> 11535.485 | ... BX73: =BX111 -> 13424.412 | BZ73: Mizuho
B74: E-glass / others | G74: =G$10 -> JPY M | H74: =+SUMIF($X$5:$BY$5,H$5,$X74:$BY74) -> 0 | I74: =+SUMIF($X$5:$BY$5,I$5,$X74:$BY74) -> 0 | J74: =+SUMIF($X$5:$BY$5,J$5,$X74:$BY74) -> 0 | K74: =+SUMIF($X$5:$BY$5,K$5,$X74:$BY74) -> 0 | L74: =+SUMIF($X$5:$BY$5,L$5,$X74:$BY74) -> 0 | M74: =+SUMIF($X$5:$BY$5,M$5,$X74:$BY74) -> 13808 | N74: =+SUMIF($X$5:$BY$5,N$5,$X74:$BY74) -> 15756 | O74: =+SUMIF($X$5:$BY$5,O$5,$X74:$BY74) -> 15393 | ... T74: =+SUMIF($X$5:$BY$5,T$5,$X74:$BY74) -> 13446.724 | AS74: 3298 | AT74: 3044 | AU74: 3787 | AV74: 3679 | AW74: 4053 | AX74: 4254 | AY74: 4077 | AZ74: 3372 | BA74: 3622 | BB74: 3978 | BC74: 3745 | BD74: 4048 | BE74: 4153 | BF74: =BF133 -> 4375.8 | BG74: =BG133 -> 3932.25 | BH74: =BH133 -> 4048 | BI74: =BI133 -> 3945.35 | BJ74: =BJ133 -> 4157.01 | BK74: =BK133 -> 3735.6375 | BL74: =BL133 -> 3845.6 | BM74: =BM133 -> 3748.0825 | ... BX74: =BX133 -> 3297.1213 | BZ74: Mizuho
C75: Intersegment (plug) | G75: =G$10 -> JPY M | H75: =+SUMIF($X$5:$BY$5,H$5,$X75:$BY75) -> 0 | I75: =+SUMIF($X$5:$BY$5,I$5,$X75:$BY75) -> 0 | J75: =+SUMIF($X$5:$BY$5,J$5,$X75:$BY75) -> 0 | K75: =+SUMIF($X$5:$BY$5,K$5,$X75:$BY75) -> 0 | L75: =+SUMIF($X$5:$BY$5,L$5,$X75:$BY75) -> 0 | M75: =+SUMIF($X$5:$BY$5,M$5,$X75:$BY75) -> -7453.15 | N75: =+SUMIF($X$5:$BY$5,N$5,$X75:$BY75) -> -11189 | O75: =+SUMIF($X$5:$BY$5,O$5,$X75:$BY75) -> -12134 | ... T75: =+SUMIF($X$5:$BY$5,T$5,$X75:$BY75) -> -23667.303 | AS75: =AS71-SUM(AS72:AS74) -> -1518.95 | AT75: =AT71-SUM(AT72:AT74) -> -1759.3 | AU75: =AU71-SUM(AU72:AU74) -> -2024.9 | AV75: =AV71-SUM(AV72:AV74) -> -2150 | AW75: =AW71-SUM(AW72:AW74) -> -2633 | AX75: =AX71-SUM(AX72:AX74) -> -2736 | AY75: =AY71-SUM(AY72:AY74) -> -2891 | AZ75: =AZ71-SUM(AZ72:AZ74) -> -2929 | ... BE75: =BE71-SUM(BE72:BE74) -> -3510 | BF75: =-SUM(BF72:BF74)*BF77 -> -3783.6777 | BG75: =-SUM(BG72:BG74)*BG77 -> -3859.5748 | BH75: =-SUM(BH72:BH74)*BH77 -> -4098.1099 | BI75: =-SUM(BI72:BI74)*BI77 -> -4284.7989 | BJ75: =-SUM(BJ72:BJ74)*BJ77 -> -4592.4466 | BK75: =-SUM(BK72:BK74)*BK77 -> -4786.1241 | BL75: =-SUM(BL72:BL74)*BL77 -> -5098.7049 | BM75: =-SUM(BM72:BM74)*BM77 -> -4986.5107 | ... BX75: =-SUM(BX72:BX74)*BX77 -> -6046.7552
B77: Intersegment % of total | G77: % | M77: =-M75/SUM(M72:M74) -> 0.19999866 | N77: =-N75/SUM(N72:N74) -> 0.21476008 | O77: =-O75/SUM(O72:O74) -> 0.19762537 | P77: =-P75/SUM(P72:P74) -> 0.19857042 | Q77: =-Q75/SUM(Q72:Q74) -> 0.2 | R77: =-R75/SUM(R72:R74) -> 0.2 | S77: =-S75/SUM(S72:S74) -> 0.2 | T77: =-T75/SUM(T72:T74) -> 0.2 | AS77: =-AS75/SUM(AS72:AS74) -> 0.19991445 | AT77: =-AT75/SUM(AT72:AT74) -> 0.20003411 | AU77: =-AU75/SUM(AU72:AU74) -> 0.19999012 | AV77: =-AV75/SUM(AV72:AV74) -> 0.20003722 | AW77: =-AW75/SUM(AW72:AW74) -> 0.21476346 | AX77: =-AX75/SUM(AX72:AX74) -> 0.21475667 | AY77: =-AY75/SUM(AY72:AY74) -> 0.21480051 | AZ77: =-AZ75/SUM(AZ72:AZ74) -> 0.21472033 | ... BE77: =-BE75/SUM(BE72:BE74) -> 0.19393337 | BF77: 0.2 | BG77: 0.2 | BH77: 0.2 | BI77: 0.2 | BJ77: 0.2 | BK77: 0.2 | BL77: 0.2 | BM77: 0.2 | BN77: 0.2 | BO77: 0.2 | BP77: 0.2 | BQ77: 0.2 | BR77: 0.2 | BS77: 0.2 | BT77: 0.2 | BU77: 0.2 | BV77: 0.2 | BW77: 0.2 | BX77: 0.2
B79: Operating profit | G79: =G$10 -> JPY M | H79: =+SUMIF($X$5:$BY$5,H$5,$X79:$BY79) -> 1970.07 | I79: =+SUMIF($X$5:$BY$5,I$5,$X79:$BY79) -> 2831.43 | J79: =+SUMIF($X$5:$BY$5,J$5,$X79:$BY79) -> 2547.22 | K79: =+SUMIF($X$5:$BY$5,K$5,$X79:$BY79) -> 2973.05 | L79: =+SUMIF($X$5:$BY$5,L$5,$X79:$BY79) -> 3373.66 | M79: =+SUMIF($X$5:$BY$5,M$5,$X79:$BY79) -> 5382 | N79: =+SUMIF($X$5:$BY$5,N$5,$X79:$BY79) -> 13880 | O79: =+SUMIF($X$5:$BY$5,O$5,$X79:$BY79) -> 19391 | ... T79: =+SUMIF($X$5:$BY$5,T$5,$X79:$BY79) -> 36494.34 | Y79: =Y35 -> 541.26 | Z79: =Z35 -> 481.12 | AA79: =AA35 -> 538.35 | AB79: =AB35 -> 409.34 | AC79: =AC35 -> 574.24 | AD79: =AD35 -> 615.95 | AE79: =AE35 -> 696.46 | AF79: =AF35 -> 944.78 | ... BE79: =BE35 -> 7036 | BF79: =BF150 -> 7240.8159 | BG79: =BG150 -> 6670.3097 | BH79: =BH150 -> 7196.3575 | BI79: =BI150 -> 7048.888 | BJ79: =BJ150 -> 7602.3859 | BK79: =BK150 -> 7973.2005 | BL79: =BL150 -> 9304.7129 | BM79: =BM150 -> 8022.5672 | ... BX79: =BX150 -> 9498.0834
C80: y/y | G80: % | I80: =IFERROR(I79/H79-1,"nm") -> 0.43722304 | J80: =IFERROR(J79/I79-1,"nm") -> -0.10037684 | K80: =IFERROR(K79/J79-1,"nm") -> 0.16717441 | L80: =IFERROR(L79/K79-1,"nm") -> 0.13474715 | M80: =IFERROR(M79/L79-1,"nm") -> 0.59530006 | N80: =IFERROR(N79/M79-1,"nm") -> 1.5789669 | O80: =IFERROR(O79/N79-1,"nm") -> 0.39704611 | P80: =IFERROR(P79/O79-1,"nm") -> 0.45136832 | ... T80: =IFERROR(T79/S79-1,"nm") -> 0.039138145 | Y80: =IFERROR(Y79/#REF!-1,"nm") -> nm | Z80: =IFERROR(Z79/#REF!-1,"nm") -> nm | AA80: =IFERROR(AA79/W79-1,"nm") -> nm | AB80: =IFERROR(AB79/X79-1,"nm") -> nm | AC80: =IFERROR(AC79/Y79-1,"nm") -> 0.0609319 | AD80: =IFERROR(AD79/Z79-1,"nm") -> 0.28024194 | AE80: =IFERROR(AE79/AA79-1,"nm") -> 0.29369369 | AF80: =IFERROR(AF79/AB79-1,"nm") -> 1.3080569 | AG80: =IFERROR(AG79/AC79-1,"nm") -> 0.58783784 | AH80: =IFERROR(AH79/AD79-1,"nm") -> -0.22992126 | ... BX80: =IFERROR(BX79/BT79-1,"nm") -> 0.036844126
C81: Incremental | G81: % | J81: =IFERROR((J79-I79)/(J71-I71),"nm") -> 1.066254 | K81: =IFERROR((K79-J79)/(K71-J71),"nm") -> 0.21184518 | L81: =IFERROR((L79-K79)/(L71-K71),"nm") -> 2.5589907 | M81: =IFERROR((M79-L79)/(M71-L71),"nm") -> 0.46983659 | N81: =IFERROR((N79-M79)/(N71-M71),"nm") -> 0.7657132 | O81: =IFERROR((O79-N79)/(O71-N71),"nm") -> 0.65968398 | P81: =IFERROR((P79-O79)/(P71-O71),"nm") -> 0.71219488 | Q81: =IFERROR((Q79-P79)/(Q71-P71),"nm") -> 0.28055038 | ... T81: =IFERROR((T79-S79)/(T71-S71),"nm") -> 0.24863038 | AJ81: =IFERROR((AJ79-AF79)/(AJ71-AF71),"nm") -> 2.1078625 | AK81: =IFERROR((AK79-AG79)/(AK71-AG71),"nm") -> -3.3559242 | AL81: =IFERROR((AL79-AH79)/(AL71-AH71),"nm") -> 0.23332752 | AM81: =IFERROR((AM79-AI79)/(AM71-AI71),"nm") -> 0.30432488 | AN81: =IFERROR((AN79-AJ79)/(AN71-AJ71),"nm") -> 0.44777241 | AO81: =IFERROR((AO79-AK79)/(AO71-AK71),"nm") -> 0.46876195 | AP81: =IFERROR((AP79-AL79)/(AP71-AL71),"nm") -> 0.5646443 | AQ81: =IFERROR((AQ79-AM79)/(AQ71-AM71),"nm") -> -0.57281115 | ... BX81: =IFERROR((BX79-BT79)/(BX71-BT71),"nm") -> 0.2479225
B83: T-glass
B85: Revenue | G85: =G$10 -> JPY M | H85: =+SUMIF($X$5:$BY$5,H$5,$X85:$BY85) -> 0 | I85: =+SUMIF($X$5:$BY$5,I$5,$X85:$BY85) -> 0 | J85: =+SUMIF($X$5:$BY$5,J$5,$X85:$BY85) -> 0 | K85: =+SUMIF($X$5:$BY$5,K$5,$X85:$BY85) -> 0 | L85: =+SUMIF($X$5:$BY$5,L$5,$X85:$BY85) -> 0 | M85: =+SUMIF($X$5:$BY$5,M$5,$X85:$BY85) -> 9149 | N85: =+SUMIF($X$5:$BY$5,N$5,$X85:$BY85) -> 11478 | O85: =+SUMIF($X$5:$BY$5,O$5,$X85:$BY85) -> 13628 | ... T85: =+SUMIF($X$5:$BY$5,T$5,$X85:$BY85) -> 52247.338 | AS85: =AS72 -> 1677 | AT85: =AT72 -> 2243 | AU85: =AU72 -> 2472 | AV85: =AV72 -> 2757 | AW85: =AW72 -> 2592 | AX85: =AX72 -> 2680 | AY85: =AY72 -> 2963 | AZ85: =AZ72 -> 3243 | ... BE85: =BE72 -> 4763 | BF85: =BF98*BF102 -> 5056.8465 | BG85: =BG98*BG102 -> 5405.5945 | BH85: =BH98*BH102 -> 6103.0906 | BI85: =BI98*BI102 -> 6737.812 | BJ85: =BJ98*BJ102 -> 7748.4838 | BK85: =BK98*BK102 -> 8759.1556 | BL85: =BL98*BL102 -> 9769.8274 | BM85: =BM98*BM102 -> 9648.9862 | ... BX85: =BX98*BX102 -> 13512.242
B87: Capacity index | G87: FY24 = 100 | O87: =+IFERROR(AVERAGEIF($X$5:$BY$5,O$5,$X87:$BY87),"nm") -> 127 | P87: =+IFERROR(AVERAGEIF($X$5:$BY$5,P$5,$X87:$BY87),"nm") -> 152.5 | Q87: =+IFERROR(AVERAGEIF($X$5:$BY$5,Q$5,$X87:$BY87),"nm") -> 245 | R87: =+IFERROR(AVERAGEIF($X$5:$BY$5,R$5,$X87:$BY87),"nm") -> 340 | S87: =+IFERROR(AVERAGEIF($X$5:$BY$5,S$5,$X87:$BY87),"nm") -> 395 | T87: =+IFERROR(AVERAGEIF($X$5:$BY$5,T$5,$X87:$BY87),"nm") -> 435 | BA87: 122 | BB87: 125 | BC87: 128 | BD87: 133 | BE87: 135 | BF87: =CHOOSE($G$2,BF88,BF89,BF90) -> 145 | BG87: =CHOOSE($G$2,BG88,BG89,BG90) -> 155 | BH87: =CHOOSE($G$2,BH88,BH89,BH90) -> 175 | BI87: =CHOOSE($G$2,BI88,BI89,BI90) -> 200 | BJ87: =CHOOSE($G$2,BJ88,BJ89,BJ90) -> 230 | BK87: =CHOOSE($G$2,BK88,BK89,BK90) -> 260 | BL87: =CHOOSE($G$2,BL88,BL89,BL90) -> 290 | BM87: =CHOOSE($G$2,BM88,BM89,BM90) -> 310 | ... BX87: =CHOOSE($G$2,BX88,BX89,BX90) -> 450 | BZ87: JPM - Only historicals
D88: 1 | G88: index | BF88: =BF89 -> 145 | BG88: =BG89 -> 155 | BH88: =BH89 -> 175 | BI88: =BI89 -> 200 | BJ88: =BJ89+10 -> 240 | BK88: =BK89+10 -> 270 | BL88: =BL89+10 -> 300 | BM88: =BM89+10 -> 320 | BN88: =BN89+10 -> 340 | BO88: =BO89+10 -> 360 | BP88: =BP89+10 -> 380 | BQ88: =BQ89+10 -> 390 | ... BX88: =BX89+10 -> 460
D89: 2 | G89: index | BF89: 145 | BG89: 155 | BH89: 175 | BI89: 200 | BJ89: 230 | BK89: 260 | BL89: 290 | BM89: 310 | BN89: 330 | BO89: 350 | BP89: 370 | BQ89: 380 | BR89: 390 | BS89: 400 | BT89: 410 | BU89: 420 | BV89: 430 | BW89: 440 | BX89: 450
D90: 3 | G90: index | BF90: =BF89 -> 145 | BG90: =BG89 -> 155 | BH90: =BH89 -> 175 | BI90: =BI89 -> 200 | BJ90: =BJ89-10 -> 220 | BK90: =BK89-10 -> 250 | BL90: =BL89-10 -> 280 | BM90: =BM89-10 -> 300 | BN90: =BN89-10 -> 320 | BO90: =BO89-10 -> 340 | BP90: =BP89-10 -> 360 | BQ90: =BQ89-10 -> 370 | ... BX90: =BX89-10 -> 440
C91: y/y | G91: % | O91: =IFERROR(O87/N87-1,"nm") -> nm | P91: =IFERROR(P87/O87-1,"nm") -> 0.2007874 | Q91: =IFERROR(Q87/P87-1,"nm") -> 0.60655738 | R91: =IFERROR(R87/Q87-1,"nm") -> 0.3877551 | S91: =IFERROR(S87/R87-1,"nm") -> 0.16176471 | T91: =IFERROR(T87/S87-1,"nm") -> 0.10126582 | BE91: =IFERROR(BE87/BA87-1,"nm") -> 0.10655738 | BF91: =IFERROR(BF87/BB87-1,"nm") -> 0.16 | BG91: =IFERROR(BG87/BC87-1,"nm") -> 0.2109375 | BH91: =IFERROR(BH87/BD87-1,"nm") -> 0.31578947 | BI91: =IFERROR(BI87/BE87-1,"nm") -> 0.48148148 | BJ91: =IFERROR(BJ87/BF87-1,"nm") -> 0.5862069 | BK91: =IFERROR(BK87/BG87-1,"nm") -> 0.67741935 | BL91: =IFERROR(BL87/BH87-1,"nm") -> 0.65714286 | ... BX91: =IFERROR(BX87/BT87-1,"nm") -> 0.097560976
B92: Capacity | G92: # | O92: =+SUMIF($X$5:$BY$5,O$5,$X92:$BY92) -> 129.9142 | P92: =+SUMIF($X$5:$BY$5,P$5,$X92:$BY92) -> 155.99934 | Q92: =+SUMIF($X$5:$BY$5,Q$5,$X92:$BY92) -> 250.62189 | R92: =+SUMIF($X$5:$BY$5,R$5,$X92:$BY92) -> 347.80181 | S92: =+SUMIF($X$5:$BY$5,S$5,$X92:$BY92) -> 404.06386 | T92: =+SUMIF($X$5:$BY$5,T$5,$X92:$BY92) -> 444.98172 | BA92: =BA87*$O$98/($O$87*4) -> 31.199868 | BB92: =BB87*$O$98/($O$87*4) -> 31.967078 | BC92: =BC87*$O$98/($O$87*4) -> 32.734288 | BD92: =BD87*$O$98/($O$87*4) -> 34.012971 | BE92: =BE87*$O$98/($O$87*4) -> 34.524444 | BF92: =BF87*$O$98/($O$87*4) -> 37.08181 | BG92: =BG87*$O$98/($O$87*4) -> 39.639176 | BH92: =BH87*$O$98/($O$87*4) -> 44.753909 | ... BX92: =BX87*$O$98/($O$87*4) -> 115.08148
B93: Utilisation Rate | G93: % | O93: =IFERROR(O98/O92,"nm") -> 1 | P93: =IFERROR(P98/P92,"nm") -> 1.0025807 | Q93: =IFERROR(Q98/Q92,"nm") -> 0.92 | R93: =IFERROR(R98/R92,"nm") -> 0.85 | S93: =IFERROR(S98/S92,"nm") -> 0.82 | T93: =IFERROR(T98/T92,"nm") -> 0.82 | BA93: =IFERROR(BA98/BA92,"nm") -> 0.97559749 | BB93: =IFERROR(BB98/BB92,"nm") -> 0.99124861 | BC93: =IFERROR(BC98/BC92,"nm") -> 1.0216007 | BD93: =IFERROR(BD98/BD92,"nm") -> 1.0098206 | BE93: =IFERROR(BE98/BE92,"nm") -> 1.0116611 | BF93: =CHOOSE($G$2,BF94,BF95,BF96) -> 1 | BG93: =CHOOSE($G$2,BG94,BG95,BG96) -> 1 | BH93: =CHOOSE($G$2,BH94,BH95,BH96) -> 1 | BI93: =CHOOSE($G$2,BI94,BI95,BI96) -> 0.92 | BJ93: =CHOOSE($G$2,BJ94,BJ95,BJ96) -> 0.92 | BK93: =CHOOSE($G$2,BK94,BK95,BK96) -> 0.92 | BL93: =CHOOSE($G$2,BL94,BL95,BL96) -> 0.92 | BM93: =CHOOSE($G$2,BM94,BM95,BM96) -> 0.85 | ... BX93: =CHOOSE($G$2,BX94,BX95,BX96) -> 0.82
D94: 1 | G94: % | BF94: 1 | BG94: 1 | BH94: 1 | BI94: 1 | BJ94: =BJ95+0.03 -> 0.95 | BK94: =BK95+0.03 -> 0.95 | BL94: =BL95+0.03 -> 0.95 | BM94: =BM95+0.03 -> 0.88 | BN94: =BN95+0.03 -> 0.88 | BO94: =BO95+0.03 -> 0.88 | BP94: =BP95+0.03 -> 0.88 | BQ94: =BQ95+0.03 -> 0.85 | ... BX94: =BX95+0.03 -> 0.85
D95: 2 | G95: % | BF95: 1 | BG95: 1 | BH95: 1 | BI95: 0.92 | BJ95: 0.92 | BK95: 0.92 | BL95: 0.92 | BM95: 0.85 | BN95: 0.85 | BO95: 0.85 | BP95: 0.85 | BQ95: 0.82 | BR95: 0.82 | BS95: 0.82 | BT95: 0.82 | BU95: 0.82 | BV95: 0.82 | BW95: 0.82 | BX95: 0.82
D96: 3 | G96: % | BF96: 1 | BG96: 1 | BH96: 1 | BI96: =BI95-0.05 -> 0.87 | BJ96: =BJ95-0.05 -> 0.87 | BK96: =BK95-0.05 -> 0.87 | BL96: =BL95-0.05 -> 0.87 | BM96: =BM95-0.05 -> 0.8 | BN96: =BN95-0.05 -> 0.8 | BO96: =BO95-0.05 -> 0.8 | BP96: =BP95-0.05 -> 0.8 | ... BT96: =BT95-0.05 -> 0.77 | BU96: =BU95-0.1 -> 0.72 | BV96: =BV95-0.1 -> 0.72 | BW96: =BW95-0.1 -> 0.72 | BX96: =BX95-0.1 -> 0.72
B98: Volume index | G98: # | M98: =+SUMIF($X$5:$BY$5,M$5,$X98:$BY98) -> 91.49 | N98: =+SUMIF($X$5:$BY$5,N$5,$X98:$BY98) -> 114.78 | O98: =+SUMIF($X$5:$BY$5,O$5,$X98:$BY98) -> 129.9142 | P98: =+SUMIF($X$5:$BY$5,P$5,$X98:$BY98) -> 156.40193 | Q98: =+SUMIF($X$5:$BY$5,Q$5,$X98:$BY98) -> 230.57214 | R98: =+SUMIF($X$5:$BY$5,R$5,$X98:$BY98) -> 295.63154 | S98: =+SUMIF($X$5:$BY$5,S$5,$X98:$BY98) -> 331.33237 | T98: =+SUMIF($X$5:$BY$5,T$5,$X98:$BY98) -> 364.88501 | AS98: =AS85/AS102 -> 16.77 | AT98: =AT85/AT102 -> 22.43 | AU98: =AU85/AU102 -> 24.72 | AV98: =AV85/AV102 -> 27.57 | AW98: =AW85/AW102 -> 25.92 | AX98: =AX85/AX102 -> 26.8 | AY98: =AY85/AY102 -> 29.63 | AZ98: =AZ85/AZ102 -> 32.43 | ... BE98: =BE85/BE102 -> 34.927037 | BF98: =BF92*BF93 -> 37.08181 | BG98: =BG92*BG93 -> 39.639176 | BH98: =BH92*BH93 -> 44.753909 | BI98: =BI92*BI93 -> 47.055538 | BJ98: =BJ92*BJ93 -> 54.113869 | BK98: =BK92*BK93 -> 61.1722 | BL98: =BL92*BL93 -> 68.230531 | BM98: =BM92*BM93 -> 67.3866 | ... BX98: =BX92*BX93 -> 94.366814 | CA98: Derived
C99: y/y | G99: % | N99: =IFERROR(N98/M98-1,"nm") -> 0.25456334 | O99: =IFERROR(O98/N98-1,"nm") -> 0.13185402 | P99: =IFERROR(P98/O98-1,"nm") -> 0.20388631 | Q99: =IFERROR(Q98/P98-1,"nm") -> 0.4742282 | R99: =IFERROR(R98/Q98-1,"nm") -> 0.28216504 | S99: =IFERROR(S98/R98-1,"nm") -> 0.12076125 | T99: =IFERROR(T98/S98-1,"nm") -> 0.10126582 | AW99: =IFERROR(AW98/AS98-1,"nm") -> 0.54561717 | AX99: =IFERROR(AX98/AT98-1,"nm") -> 0.19482835 | AY99: =IFERROR(AY98/AU98-1,"nm") -> 0.1986246 | AZ99: =IFERROR(AZ98/AV98-1,"nm") -> 0.17627856 | BA99: =IFERROR(BA98/AW98-1,"nm") -> 0.17432534 | BB99: =IFERROR(BB98/AX98-1,"nm") -> 0.18236273 | BC99: =IFERROR(BC98/AY98-1,"nm") -> 0.12863222 | BD99: =IFERROR(BD98/AZ98-1,"nm") -> 0.059111845 | ... BX99: =IFERROR(BX98/BT98-1,"nm") -> 0.097560976
C100: q/q | G100: % | AT100: =IFERROR(AT98/AS98-1,"nm") -> 0.33750745 | AU100: =IFERROR(AU98/AT98-1,"nm") -> 0.10209541 | AV100: =IFERROR(AV98/AU98-1,"nm") -> 0.11529126 | AW100: =IFERROR(AW98/AV98-1,"nm") -> -0.059847661 | AX100: =IFERROR(AX98/AW98-1,"nm") -> 0.033950617 | AY100: =IFERROR(AY98/AX98-1,"nm") -> 0.10559701 | AZ100: =IFERROR(AZ98/AY98-1,"nm") -> 0.094498819 | BA100: =IFERROR(BA98/AZ98-1,"nm") -> -0.061408792 | ... BX100: =IFERROR(BX98/BW98-1,"nm") -> 0.022727273
B102: Price index | G102: FY24 = 100 | M102: =+IFERROR(AVERAGEIF($X$5:$BY$5,M$5,$X102:$BY102),"nm") -> 100 | N102: =+IFERROR(AVERAGEIF($X$5:$BY$5,N$5,$X102:$BY102),"nm") -> 100 | O102: =+IFERROR(AVERAGEIF($X$5:$BY$5,O$5,$X102:$BY102),"nm") -> 104.9 | P102: =+IFERROR(AVERAGEIF($X$5:$BY$5,P$5,$X102:$BY102),"nm") -> 136.37 | Q102: =+IFERROR(AVERAGEIF($X$5:$BY$5,Q$5,$X102:$BY102),"nm") -> 143.1885 | R102: =+IFERROR(AVERAGEIF($X$5:$BY$5,R$5,$X102:$BY102),"nm") -> 143.1885 | S102: =+IFERROR(AVERAGEIF($X$5:$BY$5,S$5,$X102:$BY102),"nm") -> 143.1885 | T102: =+IFERROR(AVERAGEIF($X$5:$BY$5,T$5,$X102:$BY102),"nm") -> 143.1885 | AS102: 100 | AT102: 100 | AU102: 100 | AV102: 100 | AW102: 100 | AX102: 100 | AY102: 100 | AZ102: 100 | BA102: 104.9 | BB102: 104.9 | BC102: 104.9 | BD102: 104.9 | BE102: =BA102*(1+BE103) -> 136.37 | BF102: =BB102*(1+BF103) -> 136.37 | BG102: =BC102*(1+BG103) -> 136.37 | BH102: =BD102*(1+BH103) -> 136.37 | BI102: =BE102*(1+BI103) -> 143.1885 | BJ102: =BF102*(1+BJ103) -> 143.1885 | BK102: =BG102*(1+BK103) -> 143.1885 | BL102: =BH102*(1+BL103) -> 143.1885 | ... BX102: =BT102*(1+BX103) -> 143.1885 | BZ102: Mizuho
C103: y/y | G103: % | N103: =IFERROR(N102/M102-1,"nm") -> 0 | O103: =IFERROR(O102/N102-1,"nm") -> 0.049 | P103: =IFERROR(P102/O102-1,"nm") -> 0.3 | Q103: =IFERROR(Q102/P102-1,"nm") -> 0.05 | R103: =IFERROR(R102/Q102-1,"nm") -> 0 | S103: =IFERROR(S102/R102-1,"nm") -> 0 | T103: =IFERROR(T102/S102-1,"nm") -> 0 | AW103: =IFERROR(AW102/AS102-1,"nm") -> 0 | AX103: =IFERROR(AX102/AT102-1,"nm") -> 0 | AY103: =IFERROR(AY102/AU102-1,"nm") -> 0 | AZ103: =IFERROR(AZ102/AV102-1,"nm") -> 0 | BA103: =IFERROR(BA102/AW102-1,"nm") -> 0.049 | BB103: =IFERROR(BB102/AX102-1,"nm") -> 0.049 | BC103: =IFERROR(BC102/AY102-1,"nm") -> 0.049 | BD103: =IFERROR(BD102/AZ102-1,"nm") -> 0.049 | BE103: =CHOOSE($G$2,BE104,BE105,BE106) -> 0.3 | BF103: =CHOOSE($G$2,BF104,BF105,BF106) -> 0.3 | BG103: =CHOOSE($G$2,BG104,BG105,BG106) -> 0.3 | BH103: =CHOOSE($G$2,BH104,BH105,BH106) -> 0.3 | BI103: =CHOOSE($G$2,BI104,BI105,BI106) -> 0.05 | BJ103: =CHOOSE($G$2,BJ104,BJ105,BJ106) -> 0.05 | BK103: =CHOOSE($G$2,BK104,BK105,BK106) -> 0.05 | BL103: =CHOOSE($G$2,BL104,BL105,BL106) -> 0.05 | ... BX103: =CHOOSE($G$2,BX104,BX105,BX106) -> 0
D104: 1 | G104: % | BE104: 0.3 | BF104: 0.3 | BG104: 0.3 | BH104: 0.3 | BI104: 0.1 | BJ104: 0.1 | BK104: 0.1 | BL104: 0.1 | BM104: 0.03 | BN104: 0.03 | BO104: 0.03 | BP104: 0.03 | BQ104: 0.03 | BR104: 0.03 | BS104: 0.03 | BT104: 0.03 | BU104: 0.03 | BV104: 0.03 | BW104: 0.03 | BX104: 0.03
D105: 2 | G105: % | BE105: 0.3 | BF105: 0.3 | BG105: 0.3 | BH105: 0.3 | BI105: 0.05 | BJ105: 0.05 | BK105: 0.05 | BL105: 0.05 | BM105: 0 | BN105: 0 | BO105: 0 | BP105: 0 | BQ105: 0 | BR105: 0 | BS105: 0 | BT105: 0 | BU105: 0 | BV105: 0 | BW105: 0 | BX105: 0
D106: 3 | G106: % | BE106: 0.3 | BF106: 0.3 | BG106: 0.3 | BH106: 0.3 | BI106: 0 | BJ106: 0 | BK106: 0 | BL106: 0 | BM106: -0.03 | BN106: -0.03 | BO106: -0.03 | BP106: -0.03 | BQ106: -0.03 | BR106: -0.03 | BS106: -0.03 | BT106: -0.03 | BU106: -0.03 | BV106: -0.03 | BW106: -0.03 | BX106: -0.03
C107: q/q | G107: % | AT107: =IFERROR(AT102/AS102-1,"nm") -> 0 | AU107: =IFERROR(AU102/AT102-1,"nm") -> 0 | AV107: =IFERROR(AV102/AU102-1,"nm") -> 0 | AW107: =IFERROR(AW102/AV102-1,"nm") -> 0 | AX107: =IFERROR(AX102/AW102-1,"nm") -> 0 | AY107: =IFERROR(AY102/AX102-1,"nm") -> 0 | AZ107: =IFERROR(AZ102/AY102-1,"nm") -> 0 | BA107: =IFERROR(BA102/AZ102-1,"nm") -> 0.049 | ... BX107: =IFERROR(BX102/BW102-1,"nm") -> 0
B109: Low-dk (NE, NER)
B111: Revenue | G111: =G$10 -> JPY M | M111: =+SUMIF($X$5:$BY$5,M$5,$X111:$BY111) -> 14309 | N111: =+SUMIF($X$5:$BY$5,N$5,$X111:$BY111) -> 24866 | O111: =+SUMIF($X$5:$BY$5,O$5,$X111:$BY111) -> 32378 | P111: =+SUMIF($X$5:$BY$5,P$5,$X111:$BY111) -> 38968.23 | Q111: =+SUMIF($X$5:$BY$5,Q$5,$X111:$BY111) -> 45111.496 | R111: =+SUMIF($X$5:$BY$5,R$5,$X111:$BY111) -> 47580.129 | S111: =+SUMIF($X$5:$BY$5,S$5,$X111:$BY111) -> 49828.604 | T111: =+SUMIF($X$5:$BY$5,T$5,$X111:$BY111) -> 52642.454 | AS111: =AS73 -> 2623 | AT111: =AT73 -> 3508 | AU111: =AU73 -> 3866 | AV111: =AV73 -> 4312 | AW111: =AW73 -> 5615 | AX111: =AX73 -> 5806 | AY111: =AY73 -> 6419 | AZ111: =AZ73 -> 7026 | ... BE111: =BE73 -> 9183 | BF111: =BF120*BF124 -> 9485.7422 | BG111: =BG120*BG124 -> 9960.0293 | BH111: =BH120*BH124 -> 10339.459 | BI111: =BI120*BI124 -> 10740.832 | BJ111: =BJ120*BJ124 -> 11056.739 | BK111: =BK120*BK124 -> 11435.827 | BL111: =BL120*BL124 -> 11878.097 | BM111: =BM120*BM124 -> 11535.485 | ... BX111: =BX120*BX124 -> 13424.412
B113: Capacity index | G113: FY24 = 100 | O113: =+IFERROR(AVERAGEIF($X$5:$BY$5,O$5,$X113:$BY113),"nm") -> 256 | P113: =+IFERROR(AVERAGEIF($X$5:$BY$5,P$5,$X113:$BY113),"nm") -> 308 | Q113: =+IFERROR(AVERAGEIF($X$5:$BY$5,Q$5,$X113:$BY113),"nm") -> 357 | R113: =+IFERROR(AVERAGEIF($X$5:$BY$5,R$5,$X113:$BY113),"nm") -> 397 | S113: =+IFERROR(AVERAGEIF($X$5:$BY$5,S$5,$X113:$BY113),"nm") -> 425 | T113: =+IFERROR(AVERAGEIF($X$5:$BY$5,T$5,$X113:$BY113),"nm") -> 449 | BA113: 245 | BB113: 252 | BC113: 260 | BD113: 267 | BE113: 290 | BF113: 300 | BG113: 315 | BH113: 327 | BI113: 340 | BJ113: 350 | BK113: 362 | BL113: 376 | BM113: 385 | BN113: 393 | BO113: 401 | BP113: 409 | BQ113: 415 | BR113: 422 | BS113: 428 | BT113: 435 | BU113: 440 | BV113: 446 | BW113: 452 | BX113: 458 | BZ113: JPM - Only historicals
B114: Capacity | G114: # | O114: =+SUMIF($X$5:$BY$5,O$5,$X114:$BY114) -> 323.78 | P114: =+SUMIF($X$5:$BY$5,P$5,$X114:$BY114) -> 389.54781 | Q114: =+SUMIF($X$5:$BY$5,Q$5,$X114:$BY114) -> 451.52133 | R114: =+SUMIF($X$5:$BY$5,R$5,$X114:$BY114) -> 502.11195 | S114: =+SUMIF($X$5:$BY$5,S$5,$X114:$BY114) -> 537.52539 | T114: =+SUMIF($X$5:$BY$5,T$5,$X114:$BY114) -> 567.87977 | BA114: =BA113*$O$120/($O$113*4) -> 77.466895 | BB114: =BB113*$O$120/($O$113*4) -> 79.680234 | BC114: =BC113*$O$120/($O$113*4) -> 82.209766 | BD114: =BD113*$O$120/($O$113*4) -> 84.423105 | BE114: =BE113*$O$120/($O$113*4) -> 91.695508 | BF114: =BF113*$O$120/($O$113*4) -> 94.857422 | BG114: =BG113*$O$120/($O$113*4) -> 99.600293 | BH114: =BH113*$O$120/($O$113*4) -> 103.39459 | ... BX114: =BX113*$O$120/($O$113*4) -> 144.81566
B115: Utilisation | G115: % | O115: =IFERROR(O120/O114,"nm") -> 1 | P115: =IFERROR(P120/P114,"nm") -> 1.0003453 | Q115: =IFERROR(Q120/Q114,"nm") -> 0.97 | R115: =IFERROR(R120/R114,"nm") -> 0.92 | S115: =IFERROR(S120/S114,"nm") -> 0.9 | T115: =IFERROR(T120/T114,"nm") -> 0.9 | BA115: =IFERROR(BA120/BA114,"nm") -> 0.97912793 | BB115: =IFERROR(BB120/BB114,"nm") -> 0.99121194 | BC115: =IFERROR(BC120/BC114,"nm") -> 1.0137482 | BD115: =IFERROR(BD120/BD114,"nm") -> 1.0140589 | BE115: =IFERROR(BE120/BE114,"nm") -> 1.0014667 | BF115: =CHOOSE($G$2,BF116,BF117,BF118) -> 1 | BG115: =CHOOSE($G$2,BG116,BG117,BG118) -> 1 | BH115: =CHOOSE($G$2,BH116,BH117,BH118) -> 1 | BI115: =CHOOSE($G$2,BI116,BI117,BI118) -> 0.97 | BJ115: =CHOOSE($G$2,BJ116,BJ117,BJ118) -> 0.97 | BK115: =CHOOSE($G$2,BK116,BK117,BK118) -> 0.97 | BL115: =CHOOSE($G$2,BL116,BL117,BL118) -> 0.97 | BM115: =CHOOSE($G$2,BM116,BM117,BM118) -> 0.92 | ... BX115: =CHOOSE($G$2,BX116,BX117,BX118) -> 0.9
D116: 1 | G116: % | BF116: 1 | BG116: 1 | BH116: 1 | BI116: =MIN(BI117+0.03,1) -> 1 | BJ116: =MIN(BJ117+0.03,1) -> 1 | BK116: =MIN(BK117+0.03,1) -> 1 | BL116: =MIN(BL117+0.03,1) -> 1 | BM116: =MIN(BM117+0.03,1) -> 0.95 | BN116: =MIN(BN117+0.03,1) -> 0.95 | BO116: =MIN(BO117+0.03,1) -> 0.95 | BP116: =MIN(BP117+0.03,1) -> 0.95 | ... BX116: =MIN(BX117+0.03,1) -> 0.93
D117: 2 | G117: % | BF117: 1 | BG117: 1 | BH117: 1 | BI117: 0.97 | BJ117: 0.97 | BK117: 0.97 | BL117: 0.97 | BM117: 0.92 | BN117: 0.92 | BO117: 0.92 | BP117: 0.92 | BQ117: 0.9 | BR117: 0.9 | BS117: 0.9 | BT117: 0.9 | BU117: 0.9 | BV117: 0.9 | BW117: 0.9 | BX117: 0.9
D118: 3 | G118: % | BF118: 1 | BG118: 1 | BH118: 1 | BI118: =BI117-0.03 -> 0.94 | BJ118: =BJ117-0.03 -> 0.94 | BK118: =BK117-0.03 -> 0.94 | BL118: =BL117-0.03 -> 0.94 | BM118: =BM117-0.03 -> 0.89 | BN118: =BN117-0.03 -> 0.89 | BO118: =BO117-0.03 -> 0.89 | BP118: =BP117-0.03 -> 0.89 | ... BX118: =BX117-0.03 -> 0.87
B120: Volume index | G120: # | M120: =+SUMIF($X$5:$BY$5,M$5,$X120:$BY120) -> 143.09 | N120: =+SUMIF($X$5:$BY$5,N$5,$X120:$BY120) -> 248.66 | O120: =+SUMIF($X$5:$BY$5,O$5,$X120:$BY120) -> 323.78 | P120: =+SUMIF($X$5:$BY$5,P$5,$X120:$BY120) -> 389.6823 | Q120: =+SUMIF($X$5:$BY$5,Q$5,$X120:$BY120) -> 437.97569 | R120: =+SUMIF($X$5:$BY$5,R$5,$X120:$BY120) -> 461.943 | S120: =+SUMIF($X$5:$BY$5,S$5,$X120:$BY120) -> 483.77285 | T120: =+SUMIF($X$5:$BY$5,T$5,$X120:$BY120) -> 511.09179 | AS120: =AS111/AS124 -> 26.23 | AT120: =AT111/AT124 -> 35.08 | AU120: =AU111/AU124 -> 38.66 | AV120: =AV111/AV124 -> 43.12 | AW120: =AW111/AW124 -> 56.15 | AX120: =AX111/AX124 -> 58.06 | AY120: =AY111/AY124 -> 64.19 | AZ120: =AZ111/AZ124 -> 70.26 | ... BE120: =BE111/BE124 -> 91.83 | BF120: =BF114*BF115 -> 94.857422 | BG120: =BG114*BG115 -> 99.600293 | BH120: =BH114*BH115 -> 103.39459 | BI120: =BI114*BI115 -> 104.27993 | BJ120: =BJ114*BJ115 -> 107.34698 | BK120: =BK114*BK115 -> 111.02745 | BL120: =BL114*BL115 -> 115.32133 | BM120: =BM114*BM115 -> 111.995 | ... BX120: =BX114*BX115 -> 130.3341 | CA120: Derived
C121: y/y | G121: % | N121: =IFERROR(N120/M120-1,"nm") -> 0.73778741 | O121: =IFERROR(O120/N120-1,"nm") -> 0.30209925 | P121: =IFERROR(P120/O120-1,"nm") -> 0.20354038 | Q121: =IFERROR(Q120/P120-1,"nm") -> 0.12393014 | R121: =IFERROR(R120/Q120-1,"nm") -> 0.05472292 | S121: =IFERROR(S120/R120-1,"nm") -> 0.047256598 | T121: =IFERROR(T120/S120-1,"nm") -> 0.056470588 | AW121: =IFERROR(AW120/AS120-1,"nm") -> 1.1406786 | AX121: =IFERROR(AX120/AT120-1,"nm") -> 0.65507412 | AY121: =IFERROR(AY120/AU120-1,"nm") -> 0.66037248 | AZ121: =IFERROR(AZ120/AV120-1,"nm") -> 0.62940631 | BA121: =IFERROR(BA120/AW120-1,"nm") -> 0.35084595 | BB121: =IFERROR(BB120/AX120-1,"nm") -> 0.36031691 | BC121: =IFERROR(BC120/AY120-1,"nm") -> 0.29833307 | BD121: =IFERROR(BD120/AZ120-1,"nm") -> 0.21847424 | ... BX121: =IFERROR(BX120/BT120-1,"nm") -> 0.052873563
C122: q/q | G122: % | AT122: =IFERROR(AT120/AS120-1,"nm") -> 0.33739992 | AU122: =IFERROR(AU120/AT120-1,"nm") -> 0.10205245 | AV122: =IFERROR(AV120/AU120-1,"nm") -> 0.11536472 | AW122: =IFERROR(AW120/AV120-1,"nm") -> 0.30217996 | AX122: =IFERROR(AX120/AW120-1,"nm") -> 0.034016028 | AY122: =IFERROR(AY120/AX120-1,"nm") -> 0.10558043 | AZ122: =IFERROR(AZ120/AY120-1,"nm") -> 0.094563016 | BA122: =IFERROR(BA120/AZ120-1,"nm") -> 0.079561628 | ... BX122: =IFERROR(BX120/BW120-1,"nm") -> 0.013274336
...

Sheet Valuation
A1: =Summary!C2 -> Nitto Boseki
A2: =Summary!C3 -> TYO: 3110 | F2: Case | G2: =Summary!C9 -> 2
B4: FQ | H4: A | I4: A | J4: A | K4: A | L4: A | M4: A | N4: A | O4: A | P4: E | Q4: E | R4: E | S4: E | T4: E
B5: FY | H5: 2019 | I5: =H5+1 -> 2020 | J5: =I5+1 -> 2021 | K5: =J5+1 -> 2022 | L5: =K5+1 -> 2023 | M5: =L5+1 -> 2024 | N5: =M5+1 -> 2025 | O5: =N5+1 -> 2026 | P5: =O5+1 -> 2027 | ... T5: =S5+1 -> 2031
B6: FY End | G6: Units | H6: 43555 | I6: =EOMONTH(J6,-12) -> 43921 | J6: =EOMONTH(K6,-12) -> 44286 | K6: =EOMONTH(L6,-12) -> 44651 | L6: =EOMONTH(M6,-12) -> 45016 | M6: =EOMONTH(N6,-12) -> 45382 | N6: =EOMONTH(O6,-12) -> 45747 | O6: =Summary!$C$6 -> 46112 | P6: =EOMONTH(O6,12) -> 46477 | Q6: =EOMONTH(P6,12) -> 46843 | R6: =EOMONTH(Q6,12) -> 47208 | S6: =EOMONTH(R6,12) -> 47573 | T6: =EOMONTH(S6,12) -> 47938
A8: x | B8: SUMMARY
B10: Valuation | G10: =Summary!C8 -> JPY M | P10: Weightage
B11: P/E | G11: =G$10 -> JPY M | P11: 0.25 | Q11: =Q44 -> 2317.4614
B12: P/B | G12: =G$10 -> JPY M | P12: 0.25 | Q12: =Q53 -> 2771.3865
B13: EV/EBITDA | G13: =G$10 -> JPY M | P13: 0.25 | Q13: =Q72 -> 2867.6997
B14: EV/Rev | G14: =G$10 -> JPY M | P14: 0.25 | Q14: =Q98 -> 1610.0116
B15: DCF - Perpetuity Growth | G15: =G$10 -> JPY M | P15: 0 | Q15: =Q183 -> 1446.9858
B16: DCF - Terminal Multiple Method | G16: =G$10 -> JPY M | P16: 0 | Q16: =Q201 -> 1835.0035
B17: Implied share price | G17: =G$10 -> JPY M | P17: =SUM(P11:P16) -> 1 | Q17: =SUMPRODUCT(Q11:Q16,P11:P16) -> 2391.6398
A19: x | B19: Relative Valuation
B21: Operating profit | G21: =G$10 -> JPY M | H21: =Revenue!H34 -> 8198 | I21: =Revenue!I34 -> 8160 | J21: =Revenue!J34 -> 5964 | K21: =Revenue!K34 -> 7268 | L21: =Revenue!L34 -> 4880 | M21: =Revenue!M34 -> 8386 | N21: =Revenue!N34 -> 16444 | O21: =Revenue!O34 -> 20818 | ... T21: =Revenue!T34 -> 39963.536
B22: Electronic Materials | G22: =G$10 -> JPY M | H22: =Revenue!H35 -> 1970.07 | I22: =Revenue!I35 -> 2831.43 | J22: =Revenue!J35 -> 2547.22 | K22: =Revenue!K35 -> 2973.05 | L22: =Revenue!L35 -> 3373.66 | M22: =Revenue!M35 -> 5382 | N22: =Revenue!N35 -> 13880 | O22: =Revenue!O35 -> 19391 | ... T22: =Revenue!T35 -> 36494.34
B23: Medical | G23: =G$10 -> JPY M | H23: =Revenue!H36 -> 553.52 | I23: =Revenue!I36 -> 390.72 | J23: =Revenue!J36 -> 270.16 | K23: =Revenue!K36 -> 224.4 | L23: =Revenue!L36 -> 97.68 | M23: =Revenue!M36 -> 2389 | N23: =Revenue!N36 -> 2381 | O23: =Revenue!O36 -> 2431 | ... T23: =Revenue!T36 -> 3537.773
B24: Composite Materials | G24: =G$10 -> JPY M | H24: =Revenue!H37 -> 3937 | I24: =Revenue!I37 -> 3091 | J24: =Revenue!J37 -> 2368 | K24: =Revenue!K37 -> 1733 | L24: =Revenue!L37 -> -1680 | M24: =Revenue!M37 -> -731 | N24: =Revenue!N37 -> -900 | O24: =Revenue!O37 -> -122 | ... T24: =Revenue!T37 -> -57.462009
B25: Materials Solution | G25: =G$10 -> JPY M | H25: =Revenue!H38 -> 542.61 | I25: =Revenue!I38 -> 724.65 | J25: =Revenue!J38 -> 640.82 | K25: =Revenue!K38 -> 735.55 | L25: =Revenue!L38 -> 813.26 | M25: =Revenue!M38 -> 824 | N25: =Revenue!N38 -> 839 | O25: =Revenue!O38 -> 588 | ... T25: =Revenue!T38 -> 579.51773
B26: Insulation Materials | G26: =G$10 -> JPY M | H26: =Revenue!H39 -> 1381.08 | I26: =Revenue!I39 -> 1984.92 | J26: =Revenue!J39 -> 1785.68 | K26: =Revenue!K39 -> 2084.2 | L26: =Revenue!L39 -> 2365.04 | M26: =Revenue!M39 -> 914 | N26: =Revenue!N39 -> 693 | O26: =Revenue!O39 -> 202 | ... T26: =Revenue!T39 -> 1059.0081
B27: Other Business | G27: =G$10 -> JPY M | H27: =Revenue!H40 -> 328.54 | I27: =Revenue!I40 -> 594.53 | J27: =Revenue!J40 -> 400.41 | K27: =Revenue!K40 -> 570.9 | L27: =Revenue!L40 -> 244.33 | M27: =Revenue!M40 -> 447 | N27: =Revenue!N40 -> 409 | O27: =Revenue!O40 -> 488 | ... T27: =Revenue!T40 -> 1253.8205
B29: Tax rate | G29: % | H29: =IFERROR('3FS'!H143+0,0) -> 0.1844354 | I29: =IFERROR('3FS'!I143+0,0) -> 0.21746575 | J29: =IFERROR('3FS'!J143+0,0) -> 0.26174975 | K29: =IFERROR('3FS'!K143+0,0) -> 0.23021085 | L29: =IFERROR('3FS'!L143+0,0) -> 0.37288136 | M29: =IFERROR('3FS'!M143+0,0) -> 0.19542002 | N29: =IFERROR('3FS'!N143+0,0) -> 0.24861595 | O29: =IFERROR('3FS'!O143+0,0) -> 0.27801941 | ... T29: =IFERROR('3FS'!T143+0,0) -> 0.29
B31: P/E
B33: Net income by segment | G33: =G$10 -> JPY M | O33: CY27 Multiple | Q33: =SUM(Q34:Q39) -> 26322.338 | R33: Equity value
B34: Electronic Materials | G34: =G$10 -> JPY M | O34: =Comps!AR20*1.2 -> 18.6 | Q34: =Q22*(1-Q$29) -> 22669.723 | R34: =Q34*O34 -> 421656.85
B35: Medical | G35: =G$10 -> JPY M | O35: =Comps!AR36 -> 14.8 | Q35: =Q23*(1-Q$29) -> 2169.8035 | R35: =Q35*O35 -> 32113.092
B36: Composite Materials | G36: =G$10 -> JPY M | O36: =Comps!AR54 -> 18 | Q36: =Q24*(1-Q$29) -> -54.232376 | R36: =Q36*O36 -> -976.18277
B37: Materials Solution | G37: =G$10 -> JPY M | O37: =Comps!AR72 -> 14.4 | Q37: =Q25*(1-Q$29) -> 376.54198 | R37: =Q37*O37 -> 5422.2045
B38: Insulation Materials | G38: =G$10 -> JPY M | O38: =Comps!AR87 -> 12.6 | Q38: =Q26*(1-Q$29) -> 543.54032 | R38: =Q38*O38 -> 6848.6081
B39: Other Business | G39: =G$10 -> JPY M | O39: =Comps!AR104 -> 12.3 | Q39: =Q27*(1-Q$29) -> 616.96196 | R39: =Q39*O39 -> 7588.6321
B40: Equity value | G40: =G$10 -> JPY M | Q40: =SUM(R34:R39) -> 472653.2
B41: Adjustment | G41: =G$10 -> JPY M | Q41: =(Q104+Q106+Q107)*SUM(R34:R39)/Q33 -> -50817.471
B42: Adjusted equity value | Q42: =SUM(Q40:Q41) -> 421835.73
B43: Shares outstanding (post-split) | G43: # M | Q43: ='3FS'!P97 -> 182.02492
B44: Implied share price | G44: JPY | Q44: =Q42/Q43 -> 2317.4614
B45: Current share price | G45: JPY | Q45: =Summary!E5 -> 2989
B46: Upside / (downside) | G46: % | Q46: =Q44/Q45-1 -> -0.22466999
B48: P/B
O49: CY27 Multiple
B50: Book value (equity attrib. to owners, FY28E) | G50: =G$10 -> JPY M | O50: =Comps!BB20 -> 2.4 | Q50: ='3FS'!Q189 -> 210192.26
B51: Equity value | G51: =G$10 -> JPY M | Q51: =Q50*O50 -> 504461.41
B52: Shares outstanding (post-split) | G52: # M | Q52: ='3FS'!P97 -> 182.02492
B53: Implied share price | G53: JPY | Q53: =Q51/Q52 -> 2771.3865
B54: Current share price | G54: JPY | Q54: =Summary!E5 -> 2989
B55: Upside / (downside) | G55: % | Q55: =Q53/Q54-1 -> -0.072804777
B57: EV/EBITDA
B59: EBITDA by segment | G59: =G$10 -> JPY M | O59: CY27 Multiple | Q59: =SUM(Q60:Q65) -> 52496.549 | R59: Enterprise value
B60: Electronic Materials | G60: =G$10 -> JPY M | O60: =Comps!X20*1.2 -> 11.52 | Q60: =Q77 -> 44730.139 | R60: =Q60*O60 -> 515291.2
B61: Medical | G61: =G$10 -> JPY M | O61: =Comps!X36 -> 7.2 | Q61: =Q78 -> 3553.5978 | R61: =Q61*O61 -> 25585.904
B62: Composite Materials | G62: =G$10 -> JPY M | O62: =Comps!X54 -> 9.1 | Q62: =Q79 -> 418.09035 | R62: =Q62*O62 -> 3804.6222
B63: Materials Solution | G63: =G$10 -> JPY M | O63: =Comps!X72 -> 6.9 | Q63: =Q80 -> 869.65998 | R63: =Q63*O63 -> 6000.6538
B64: Insulation Materials | G64: =G$10 -> JPY M | O64: =Comps!X87 -> 6.9 | Q64: =Q81 -> 1361.136 | R64: =Q64*O64 -> 9391.8381
B65: Other Business | G65: =G$10 -> JPY M | O65: =IF(ISNUMBER(Comps!X104),Comps!X104,MEDIAN(O60:O64)) -> 7.2 | Q65: =Q82 -> 1563.9262 | R65: =Q65*O65 -> 11260.269
B66: (+) Corporate adjustments (unallocated OP) | G66: =G$10 -> JPY M | O66: =SUM(R60:R65)/Q59 -> 10.883277 | Q66: =Revenue!Q41 -> -2355.0899 | R66: =Q66*O66 -> -25631.096
B67: Enterprise value | G67: =G$10 -> JPY M | Q67: =SUM(R60:R66) -> 545703.39
B68: (-) Net debt (FY2027E) | G68: JPY M | Q68: ='3FS'!P210 -> 16603.947
B69: (-) Non-controlling interests (FY27E) | G69: JPY M | Q69: ='3FS'!P190 -> 7106.6355
B70: Equity value | G70: =G$10 -> JPY M | Q70: =Q67-Q68-Q69 -> 521992.8
B71: Shares outstanding (post-split) | G71: # M | Q71: ='3FS'!P97 -> 182.02492
B72: Implied share price | G72: JPY | Q72: =Q70/Q71 -> 2867.6997
B73: Current share price | G73: JPY | Q73: =Summary!E5 -> 2989
B74: Upside / (downside) | G74: % | Q74: =Q72/Q73-1 -> -0.040582248
B76: Segment EBITDA build (FY28E) | O76: Operating profit | P76: D&A | Q76: EBITDA
B77: Electronic Materials | G77: JPY M | O77: =Q22 -> 31929.187 | P77: =-Revenue!Q148 -> 12800.951 | Q77: =O77+P77 -> 44730.139
B78: Medical | G78: JPY M | O78: =Q23 -> 3056.0613 | P78: =('3FS'!$Q$102-$P$77)*Revenue!Q12/SUM(Revenue!$Q$12:$Q$16) -> 497.53654 | Q78: =O78+P78 -> 3553.5978
B79: Composite Materials | G79: JPY M | O79: =Q24 -> -76.383628 | P79: =('3FS'!$Q$102-$P$77)*Revenue!Q13/SUM(Revenue!$Q$12:$Q$16) -> 494.47398 | Q79: =O79+P79 -> 418.09035
B80: Materials Solution | G80: JPY M | O80: =Q25 -> 530.34082 | P80: =('3FS'!$Q$102-$P$77)*Revenue!Q14/SUM(Revenue!$Q$12:$Q$16) -> 339.31916 | Q80: =O80+P80 -> 869.65998
B81: Insulation Materials | G81: JPY M | O81: =Q26 -> 765.54975 | P81: =('3FS'!$Q$102-$P$77)*Revenue!Q15/SUM(Revenue!$Q$12:$Q$16) -> 595.58621 | Q81: =O81+P81 -> 1361.136
B82: Other Business | G82: JPY M | O82: =Q27 -> 868.96051 | P82: =('3FS'!$Q$102-$P$77)*Revenue!Q16/SUM(Revenue!$Q$12:$Q$16) -> 694.96571 | Q82: =O82+P82 -> 1563.9262
B84: EV/REV
B86: Revenue by segment | G86: =G$10 -> JPY M | O86: CY27 Multiple | Q86: =SUM(Q87:Q92) -> 157005.99 | R86: Enterprise value
B87: Electronic Materials | G87: =G$10 -> JPY M | O87: =Comps!N20*1.2 -> 2.76 | Q87: =Revenue!Q11 -> 75048.298 | R87: =Q87*O87 -> 207133.3
B88: Medical | G88: =G$10 -> JPY M | O88: =Comps!N36 -> 0.9 | Q88: =Revenue!Q12 -> 15552.552 | R88: =Q88*O88 -> 13997.297
B89: Composite Materials | G89: =G$10 -> JPY M | O89: =Comps!N54 -> 2.9 | Q89: =Revenue!Q13 -> 15456.819 | R89: =Q89*O89 -> 44824.774
B90: Materials Solution | G90: =G$10 -> JPY M | O90: =Comps!N72 -> 0.9 | Q90: =Revenue!Q14 -> 10606.816 | R90: =Q90*O90 -> 9546.1348
B91: Insulation Materials | G91: =G$10 -> JPY M | O91: =Comps!N87 -> 1.4 | Q91: =Revenue!Q15 -> 18617.497 | R91: =Q91*O91 -> 26064.496
B92: Other Business | G92: =G$10 -> JPY M | O92: =Comps!N104 -> 0.7 | Q92: =Revenue!Q16 -> 21724.013 | R92: =Q92*O92 -> 15206.809
B93: Enterprise value | G93: =G$10 -> JPY M | Q93: =SUM(R87:R92) -> 316772.81
B94: (-) Net debt (FY2027E) | G94: JPY M | Q94: ='3FS'!P210 -> 16603.947
B95: (-) Non-controlling interests (FY27E) | G95: JPY M | Q95: ='3FS'!P190 -> 7106.6355
B96: Equity value | G96: =G$10 -> JPY M | Q96: =Q93-Q94-Q95 -> 293062.23
B97: Shares outstanding (post-split) | G97: # M | Q97: ='3FS'!P97 -> 182.02492
B98: Implied share price | G98: JPY | Q98: =Q96/Q97 -> 1610.0116
B99: Current share price | G99: JPY | Q99: =Summary!E5 -> 2989
B100: Upside / (downside) | G100: % | Q100: =Q98/Q99-1 -> -0.46135444
B102: Check
B103: Adjustments (corporate cost) OP | G103: =G$10 -> JPY M | Q103: ='3FS'!Q49 -> -2355.0899
B104: Adjustments after tax | G104: =G$10 -> JPY M | Q104: =Q103*(1-Q$29) -> -1672.1138
B105: Interest expense | G105: =G$10 -> JPY M | Q105: ='3FS'!Q89 -> -729.53293
B106: Net interest after tax | G106: =G$10 -> JPY M | Q106: =Q105*(1-Q$29) -> -517.96838
B107: (-) Non-controlling interests | G107: =G$10 -> JPY M | Q107: ='3FS'!Q94 -> -639.973
B108: Normalised net income to shareholders | G108: =G$10 -> JPY M | Q108: =Q33+Q104+Q106+Q107 -> 23492.283
B109: Reported net income to shareholders | G109: =G$10 -> JPY M | Q109: ='3FS'!Q95 -> 23974.373
B110: Difference (one-offs, dividend inc., other) | G110: =G$10 -> JPY M | Q110: =Q109-Q108 -> 482.09
A112: x | B112: Intrinsic Valuation
B114: Beta
B116: Company Name | K116: Region | L116: Debt | M116: Equity | N116: Average Tax Rate | P116: Debt/Equity | Q116: Levered Beta | S116: Unlevered Beta
B117: Asahi Kasei | K117: Japan | L117: 1011221 | M117: 2088459 | N117: 0.2974 | P117: =L117/M117 -> 0.48419481 | Q117: 0.66 | S117: =Q117/(1+(1-N117)*P117) -> 0.49246555
B118: Nippon Electric Glass | K118: Japan | L118: 97394 | M118: 376760 | N118: 0.2974 | P118: =L118/M118 -> 0.25850409 | Q118: 0.43 | S118: =Q118/(1+(1-N118)*P118) -> 0.36390565
...

Sheet PPE
A1: =Summary!C2 -> Nitto Boseki
A2: =Summary!C3 -> TYO: 3110 | F2: Case | G2: =Summary!C9 -> 2
B4: FQ | H4: A | I4: A | J4: A | K4: A | L4: A | M4: A | N4: A | O4: A | P4: E | Q4: E | R4: E | S4: E | T4: E | Y4: 1 | Z4: 2 | AA4: 3 | AB4: 4 | AC4: =Y4 -> 1 | AD4: =Z4 -> 2 | AE4: =AA4 -> 3 | AF4: =AB4 -> 4 | AG4: =AC4 -> 1 | AH4: =AD4 -> 2 | AI4: =AE4 -> 3 | AJ4: =AF4 -> 4 | ... BX4: =BT4 -> 4
B5: FY | H5: 2019 | I5: =H5+1 -> 2020 | J5: =I5+1 -> 2021 | K5: =J5+1 -> 2022 | L5: =K5+1 -> 2023 | M5: =L5+1 -> 2024 | N5: =M5+1 -> 2025 | O5: =N5+1 -> 2026 | P5: =O5+1 -> 2027 | ... T5: =S5+1 -> 2031 | Y5: 2019 | Z5: 2019 | AA5: 2019 | AB5: 2019 | AC5: =Y5+1 -> 2020 | AD5: =Z5+1 -> 2020 | AE5: =AA5+1 -> 2020 | AF5: =AB5+1 -> 2020 | AG5: =AC5+1 -> 2021 | AH5: =AD5+1 -> 2021 | AI5: =AE5+1 -> 2021 | AJ5: =AF5+1 -> 2021 | ... BX5: =BT5+1 -> 2031
B6: FY End | G6: Units | H6: 43555 | I6: =EOMONTH(J6,-12) -> 43921 | J6: =EOMONTH(K6,-12) -> 44286 | K6: =EOMONTH(L6,-12) -> 44651 | L6: =EOMONTH(M6,-12) -> 45016 | M6: =EOMONTH(N6,-12) -> 45382 | N6: =EOMONTH(O6,-12) -> 45747 | O6: =Summary!$C$6 -> 46112 | P6: =EOMONTH(O6,12) -> 46477 | Q6: =EOMONTH(P6,12) -> 46843 | R6: =EOMONTH(Q6,12) -> 47208 | S6: =EOMONTH(R6,12) -> 47573 | T6: =EOMONTH(S6,12) -> 47938 | Y6: 43281 | Z6: 43373 | AA6: 43465 | AB6: 43555 | AC6: =EOMONTH(AD6,-3) -> 43646 | AD6: =EOMONTH(AE6,-3) -> 43738 | AE6: =EOMONTH(AF6,-3) -> 43830 | AF6: =EOMONTH(AG6,-3) -> 43921 | AG6: =EOMONTH(AH6,-3) -> 44012 | AH6: =EOMONTH(AI6,-3) -> 44104 | AI6: =EOMONTH(AJ6,-3) -> 44196 | AJ6: =EOMONTH(AK6,-3) -> 44286 | ... BC6: =EOMONTH(BD6,-3) -> 46022 | BD6: =Summary!C6 -> 46112 | BE6: =EOMONTH(BD6,3) -> 46203 | BF6: =EOMONTH(BE6,3) -> 46295 | BG6: =EOMONTH(BF6,3) -> 46387 | BH6: =EOMONTH(BG6,3) -> 46477 | BI6: =EOMONTH(BH6,3) -> 46568 | BJ6: =EOMONTH(BI6,3) -> 46660 | BK6: =EOMONTH(BJ6,3) -> 46752 | BL6: =EOMONTH(BK6,3) -> 46843 | ... BX6: =EOMONTH(BW6,3) -> 47938
A8: x | B8: PPE
A10: x | B10: A. Capex
B12: Revenue | G12: =Summary!C8 -> JPY M | H12: =+SUMIF($X$5:$BY$5,H$5,$X12:$BY12) -> 82292 | I12: =+SUMIF($X$5:$BY$5,I$5,$X12:$BY12) -> 85722 | J12: =+SUMIF($X$5:$BY$5,J$5,$X12:$BY12) -> 78727 | K12: =+SUMIF($X$5:$BY$5,K$5,$X12:$BY12) -> 84051 | L12: =+SUMIF($X$5:$BY$5,L$5,$X12:$BY12) -> 87529 | M12: =+SUMIF($X$5:$BY$5,M$5,$X12:$BY12) -> 93253 | N12: =+SUMIF($X$5:$BY$5,N$5,$X12:$BY12) -> 109035 | O12: =+SUMIF($X$5:$BY$5,O$5,$X12:$BY12) -> 118229 | ... T12: =+SUMIF($X$5:$BY$5,T$5,$X12:$BY12) -> 193564.08 | Y12: ='3FS'!Y10 -> 20450 | Z12: ='3FS'!Z10 -> 21052 | AA12: ='3FS'!AA10 -> 21679 | AB12: ='3FS'!AB10 -> 19111 | AC12: ='3FS'!AC10 -> 20621 | AD12: ='3FS'!AD10 -> 22141 | AE12: ='3FS'!AE10 -> 21299 | AF12: ='3FS'!AF10 -> 21661 | ... BX12: ='3FS'!BX10 -> 49018.055
B14: Capex – cash (reported) | G14: =G$12 -> JPY M | H14: =SUMIF($X$5:$BY$5,H$5,$X14:$BY14) -> 0 | I14: =SUMIF($X$5:$BY$5,I$5,$X14:$BY14) -> 17176 | J14: =SUMIF($X$5:$BY$5,J$5,$X14:$BY14) -> 13840 | K14: =SUMIF($X$5:$BY$5,K$5,$X14:$BY14) -> 17326 | L14: =SUMIF($X$5:$BY$5,L$5,$X14:$BY14) -> 7173 | M14: =SUMIF($X$5:$BY$5,M$5,$X14:$BY14) -> 6949 | N14: =SUMIF($X$5:$BY$5,N$5,$X14:$BY14) -> 13138 | O14: =SUMIF($X$5:$BY$5,O$5,$X14:$BY14) -> 20518 | ... T14: =SUMIF($X$5:$BY$5,T$5,$X14:$BY14) -> 0 | AD14: 9749 | AF14: 7427 | AH14: 6580 | AJ14: 7260 | AL14: 9531 | AN14: 7795 | AP14: 4452 | AR14: 2721 | AT14: 3303 | AV14: 3646 | AX14: 5729 | AZ14: 7409 | BB14: 7602 | BD14: 12916
B15: Capital investment – accrual | G15: =G$12 -> JPY M | H15: 16900 | I15: 16700 | J15: 16200 | K15: 15800 | L15: 5900 | M15: 7800 | N15: 13617 | O15: 21702 | P15: =P19 -> 45000 | Q15: =Q19 -> 40000 | R15: =R19 -> 35000 | S15: =S19 -> 32000 | T15: =T19 -> 29000
B16: Total capex | G16: =G$12 -> JPY M | H16: =SUM(H15) -> 16900 | I16: =SUM(I15) -> 16700 | J16: =SUM(J15) -> 16200 | K16: =SUM(K15) -> 15800 | L16: =SUM(L15) -> 5900 | M16: =SUM(M15) -> 7800 | N16: =SUM(N15) -> 13617 | O16: =SUM(O15) -> 21702 | ... T16: =SUM(T15) -> 29000
C17: % of revenue | G17: % | I17: =IFERROR(I16/I12,"nm") -> 0.1948158 | J17: =IFERROR(J16/J12,"nm") -> 0.20577438 | K17: =IFERROR(K16/K12,"nm") -> 0.18798111 | L17: =IFERROR(L16/L12,"nm") -> 0.067406231 | M17: =IFERROR(M16/M12,"nm") -> 0.083643422 | N17: =IFERROR(N16/N12,"nm") -> 0.1248865 | O17: =IFERROR(O16/O12,"nm") -> 0.18355903 | P17: =IFERROR(P16/P12,"nm") -> 0.32460824 | ... T17: =IFERROR(T16/T12,"nm") -> 0.14982118
B19: Capex plan | G19: =G$12 -> JPY M | P19: =CHOOSE($G$2,P20,P21,P22) -> 45000 | Q19: =CHOOSE($G$2,Q20,Q21,Q22) -> 40000 | R19: =CHOOSE($G$2,R20,R21,R22) -> 35000 | S19: =CHOOSE($G$2,S20,S21,S22) -> 32000 | T19: =CHOOSE($G$2,T20,T21,T22) -> 29000
C20: 1 | G20: =G$12 -> JPY M | P20: =P21+2000 -> 47000 | Q20: =Q21+2000 -> 42000 | R20: =R21+2000 -> 37000 | S20: =S21+2000 -> 34000 | T20: =T21+2000 -> 31000
C21: 2 | G21: =G$12 -> JPY M | P21: 45000 | Q21: =P21-5000 -> 40000 | R21: =Q21-5000 -> 35000 | S21: =R21-3000 -> 32000 | T21: =S21-3000 -> 29000
C22: 3 | G22: =G$12 -> JPY M | P22: =P21 -> 45000 | Q22: =Q21 -> 40000 | R22: =R21-2000 -> 33000 | S22: =S21-2000 -> 30000 | T22: =T21-2000 -> 27000
B24: Intangibles share of capex | G24: % | P24: 0.03 | Q24: 0.03 | R24: 0.03 | S24: 0.03 | T24: 0.03
B25: Capex – intangibles | G25: =G$12 -> JPY M | H25: =SUMIF($X$5:$BY$5,H$5,$X25:$BY25) -> 0 | I25: =SUMIF($X$5:$BY$5,I$5,$X25:$BY25) -> 0 | J25: =SUMIF($X$5:$BY$5,J$5,$X25:$BY25) -> 0 | K25: =SUMIF($X$5:$BY$5,K$5,$X25:$BY25) -> 0 | L25: =SUMIF($X$5:$BY$5,L$5,$X25:$BY25) -> 0 | M25: =SUMIF($X$5:$BY$5,M$5,$X25:$BY25) -> 0 | N25: =SUMIF($X$5:$BY$5,N$5,$X25:$BY25) -> 0 | O25: =SUMIF($X$5:$BY$5,O$5,$X25:$BY25) -> 0 | P25: =P24*P16 -> 1350 | Q25: =Q24*Q16 -> 1200 | R25: =R24*R16 -> 1050 | S25: =S24*S16 -> 960 | T25: =T24*T16 -> 870 | BE25: =-'3FS'!BE245 -> 0 | BF25: =(INDEX($P25:$T25,MATCH(BF$5,$P$5:$T$5,0))-SUMIFS($Y25:BE25,$Y$5:BE$5,BF$5,$Y$6:BE$6,"<="&Summary!$C$7))/COUNTIFS($Y$5:$BX$5,BF$5,$Y$6:$BX$6,">"&Summary!$C$7) -> 450 | BG25: =(INDEX($P25:$T25,MATCH(BG$5,$P$5:$T$5,0))-SUMIFS($Y25:BF25,$Y$5:BF$5,BG$5,$Y$6:BF$6,"<="&Summary!$C$7))/COUNTIFS($Y$5:$BX$5,BG$5,$Y$6:$BX$6,">"&Summary!$C$7) -> 450 | BH25: =(INDEX($P25:$T25,MATCH(BH$5,$P$5:$T$5,0))-SUMIFS($Y25:BG25,$Y$5:BG$5,BH$5,$Y$6:BG$6,"<="&Summary!$C$7))/COUNTIFS($Y$5:$BX$5,BH$5,$Y$6:$BX$6,">"&Summary!$C$7) -> 450 | BI25: =(INDEX($P25:$T25,MATCH(BI$5,$P$5:$T$5,0))-SUMIFS($Y25:BH25,$Y$5:BH$5,BI$5,$Y$6:BH$6,"<="&Summary!$C$7))/COUNTIFS($Y$5:$BX$5,BI$5,$Y$6:$BX$6,">"&Summary!$C$7) -> 300 | BJ25: =(INDEX($P25:$T25,MATCH(BJ$5,$P$5:$T$5,0))-SUMIFS($Y25:BI25,$Y$5:BI$5,BJ$5,$Y$6:BI$6,"<="&Summary!$C$7))/COUNTIFS($Y$5:$BX$5,BJ$5,$Y$6:$BX$6,">"&Summary!$C$7) -> 300 | BK25: =(INDEX($P25:$T25,MATCH(BK$5,$P$5:$T$5,0))-SUMIFS($Y25:BJ25,$Y$5:BJ$5,BK$5,$Y$6:BJ$6,"<="&Summary!$C$7))/COUNTIFS($Y$5:$BX$5,BK$5,$Y$6:$BX$6,">"&Summary!$C$7) -> 300 | BL25: =(INDEX($P25:$T25,MATCH(BL$5,$P$5:$T$5,0))-SUMIFS($Y25:BK25,$Y$5:BK$5,BL$5,$Y$6:BK$6,"<="&Summary!$C$7))/COUNTIFS($Y$5:$BX$5,BL$5,$Y$6:$BX$6,">"&Summary!$C$7) -> 300 | BM25: =(INDEX($P25:$T25,MATCH(BM$5,$P$5:$T$5,0))-SUMIFS($Y25:BL25,$Y$5:BL$5,BM$5,$Y$6:BL$6,"<="&Summary!$C$7))/COUNTIFS($Y$5:$BX$5,BM$5,$Y$6:$BX$6,">"&Summary!$C$7) -> 262.5 | ... BX25: =(INDEX($P25:$T25,MATCH(BX$5,$P$5:$T$5,0))-SUMIFS($Y25:BW25,$Y$5:BW$5,BX$5,$Y$6:BW$6,"<="&Summary!$C$7))/COUNTIFS($Y$5:$BX$5,BX$5,$Y$6:$BX$6,">"&Summary!$C$7) -> 217.5
B26: Capex – PP&E | G26: =G$12 -> JPY M | H26: =SUMIF($X$5:$BY$5,H$5,$X26:$BY26) -> 0 | I26: =SUMIF($X$5:$BY$5,I$5,$X26:$BY26) -> 0 | J26: =SUMIF($X$5:$BY$5,J$5,$X26:$BY26) -> 0 | K26: =SUMIF($X$5:$BY$5,K$5,$X26:$BY26) -> 0 | L26: =SUMIF($X$5:$BY$5,L$5,$X26:$BY26) -> 0 | M26: =SUMIF($X$5:$BY$5,M$5,$X26:$BY26) -> 0 | N26: =SUMIF($X$5:$BY$5,N$5,$X26:$BY26) -> 0 | O26: =SUMIF($X$5:$BY$5,O$5,$X26:$BY26) -> 0 | P26: =P16-P25 -> 43650 | Q26: =Q16-Q25 -> 38800 | R26: =R16-R25 -> 33950 | S26: =S16-S25 -> 31040 | T26: =T16-T25 -> 28130 | BE26: =-'3FS'!BE244 -> 6501 | BF26: =(INDEX($P26:$T26,MATCH(BF$5,$P$5:$T$5,0))-SUMIFS($Y26:BE26,$Y$5:BE$5,BF$5,$Y$6:BE$6,"<="&Summary!$C$7))/COUNTIFS($Y$5:$BX$5,BF$5,$Y$6:$BX$6,">"&Summary!$C$7) -> 12383 | BG26: =(INDEX($P26:$T26,MATCH(BG$5,$P$5:$T$5,0))-SUMIFS($Y26:BF26,$Y$5:BF$5,BG$5,$Y$6:BF$6,"<="&Summary!$C$7))/COUNTIFS($Y$5:$BX$5,BG$5,$Y$6:$BX$6,">"&Summary!$C$7) -> 12383 | BH26: =(INDEX($P26:$T26,MATCH(BH$5,$P$5:$T$5,0))-SUMIFS($Y26:BG26,$Y$5:BG$5,BH$5,$Y$6:BG$6,"<="&Summary!$C$7))/COUNTIFS($Y$5:$BX$5,BH$5,$Y$6:$BX$6,">"&Summary!$C$7) -> 12383 | BI26: =(INDEX($P26:$T26,MATCH(BI$5,$P$5:$T$5,0))-SUMIFS($Y26:BH26,$Y$5:BH$5,BI$5,$Y$6:BH$6,"<="&Summary!$C$7))/COUNTIFS($Y$5:$BX$5,BI$5,$Y$6:$BX$6,">"&Summary!$C$7) -> 9700 | BJ26: =(INDEX($P26:$T26,MATCH(BJ$5,$P$5:$T$5,0))-SUMIFS($Y26:BI26,$Y$5:BI$5,BJ$5,$Y$6:BI$6,"<="&Summary!$C$7))/COUNTIFS($Y$5:$BX$5,BJ$5,$Y$6:$BX$6,">"&Summary!$C$7) -> 9700 | BK26: =(INDEX($P26:$T26,MATCH(BK$5,$P$5:$T$5,0))-SUMIFS($Y26:BJ26,$Y$5:BJ$5,BK$5,$Y$6:BJ$6,"<="&Summary!$C$7))/COUNTIFS($Y$5:$BX$5,BK$5,$Y$6:$BX$6,">"&Summary!$C$7) -> 9700 | BL26: =(INDEX($P26:$T26,MATCH(BL$5,$P$5:$T$5,0))-SUMIFS($Y26:BK26,$Y$5:BK$5,BL$5,$Y$6:BK$6,"<="&Summary!$C$7))/COUNTIFS($Y$5:$BX$5,BL$5,$Y$6:$BX$6,">"&Summary!$C$7) -> 9700 | BM26: =(INDEX($P26:$T26,MATCH(BM$5,$P$5:$T$5,0))-SUMIFS($Y26:BL26,$Y$5:BL$5,BM$5,$Y$6:BL$6,"<="&Summary!$C$7))/COUNTIFS($Y$5:$BX$5,BM$5,$Y$6:$BX$6,">"&Summary!$C$7) -> 8487.5 | ... BX26: =(INDEX($P26:$T26,MATCH(BX$5,$P$5:$T$5,0))-SUMIFS($Y26:BW26,$Y$5:BW$5,BX$5,$Y$6:BW$6,"<="&Summary!$C$7))/COUNTIFS($Y$5:$BX$5,BX$5,$Y$6:$BX$6,">"&Summary!$C$7) -> 7032.5
C27: of which Land purchases | G27: =G$12 -> JPY M | H27: =SUMIF($X$5:$BY$5,H$5,$X27:$BY27) -> 0 | I27: =SUMIF($X$5:$BY$5,I$5,$X27:$BY27) -> 0 | J27: =SUMIF($X$5:$BY$5,J$5,$X27:$BY27) -> 0 | K27: =SUMIF($X$5:$BY$5,K$5,$X27:$BY27) -> 0 | L27: =SUMIF($X$5:$BY$5,L$5,$X27:$BY27) -> 0 | M27: =SUMIF($X$5:$BY$5,M$5,$X27:$BY27) -> 0 | N27: =SUMIF($X$5:$BY$5,N$5,$X27:$BY27) -> 0 | O27: =SUMIF($X$5:$BY$5,O$5,$X27:$BY27) -> 0 | ... T27: =SUMIF($X$5:$BY$5,T$5,$X27:$BY27) -> 0 | BF27: 0 | BG27: 0 | BH27: 0 | BI27: 0 | BJ27: 0 | BK27: 0 | BL27: 0 | BM27: 0 | BN27: 0 | BO27: 0 | BP27: 0 | BQ27: 0 | BR27: 0 | BS27: 0 | BT27: 0 | BU27: 0 | BV27: 0 | BW27: 0 | BX27: 0
C28: of which into CIP | G28: =G$12 -> JPY M | H28: =SUMIF($X$5:$BY$5,H$5,$X28:$BY28) -> 0 | I28: =SUMIF($X$5:$BY$5,I$5,$X28:$BY28) -> 0 | J28: =SUMIF($X$5:$BY$5,J$5,$X28:$BY28) -> 0 | K28: =SUMIF($X$5:$BY$5,K$5,$X28:$BY28) -> 0 | L28: =SUMIF($X$5:$BY$5,L$5,$X28:$BY28) -> 0 | M28: =SUMIF($X$5:$BY$5,M$5,$X28:$BY28) -> 0 | N28: =SUMIF($X$5:$BY$5,N$5,$X28:$BY28) -> 0 | O28: =SUMIF($X$5:$BY$5,O$5,$X28:$BY28) -> 0 | P28: =P26-P27 -> 43650 | Q28: =Q26-Q27 -> 38800 | R28: =R26-R27 -> 33950 | S28: =S26-S27 -> 31040 | T28: =T26-T27 -> 28130 | BF28: =BF26-BF27 -> 12383 | BG28: =BG26-BG27 -> 12383 | BH28: =BH26-BH27 -> 12383 | BI28: =BI26-BI27 -> 9700 | BJ28: =BJ26-BJ27 -> 9700 | BK28: =BK26-BK27 -> 9700 | BL28: =BL26-BL27 -> 9700 | BM28: =BM26-BM27 -> 8487.5 | ... BX28: =BX26-BX27 -> 7032.5
A30: x | B30: B. Assumptions
B32: Useful lives | K32: New | L32: Existing
C33: Buildings and structures | G33: yrs | K33: 30 | L33: 15
C34: Machinery and equipment | G34: yrs | K34: 7 | L34: 6
C35: Other | G35: yrs | K35: 5 | L35: 3
C36: Leased assets | G36: yrs | K36: 5 | L36: 2
B38: CIP transfer rate per quarter | G38: % | K38: 0.7
B39: Transfer mix – Buildings | G39: % | K39: 0.35
B40: Transfer mix – Machinery | G40: % | K40: 0.62
B41: Transfer mix – Other | G41: % | K41: 0.03
B43: Land disposals at NBV | G43: =G$12 -> JPY M | H43: =SUMIF($X$5:$BY$5,H$5,$X43:$BY43) -> 0 | I43: =SUMIF($X$5:$BY$5,I$5,$X43:$BY43) -> 0 | J43: =SUMIF($X$5:$BY$5,J$5,$X43:$BY43) -> 0 | K43: =SUMIF($X$5:$BY$5,K$5,$X43:$BY43) -> 0 | L43: =SUMIF($X$5:$BY$5,L$5,$X43:$BY43) -> 0 | M43: =SUMIF($X$5:$BY$5,M$5,$X43:$BY43) -> 0 | N43: =SUMIF($X$5:$BY$5,N$5,$X43:$BY43) -> 0 | O43: =SUMIF($X$5:$BY$5,O$5,$X43:$BY43) -> 0 | ... T43: =SUMIF($X$5:$BY$5,T$5,$X43:$BY43) -> 0 | BF43: 0 | BG43: 0 | BH43: 0 | BI43: 0 | BJ43: 0 | BK43: 0 | BL43: 0 | BM43: 0 | BN43: 0 | BO43: 0 | BP43: 0 | BQ43: 0 | BR43: 0 | BS43: 0 | BT43: 0 | BU43: 0 | BV43: 0 | BW43: 0 | BX43: 0
A45: x | B45: C. PP&E roll-forward
B47: Construction in progress
C48: BOP | G48: =G$12 -> JPY M | H48: =SUMIFS($X48:$BY48,$X$5:$BY$5,H$5,$X$4:$BY$4,1) -> 0 | I48: =SUMIFS($X48:$BY48,$X$5:$BY$5,I$5,$X$4:$BY$4,1) -> 0 | J48: =SUMIFS($X48:$BY48,$X$5:$BY$5,J$5,$X$4:$BY$4,1) -> 0 | K48: =SUMIFS($X48:$BY48,$X$5:$BY$5,K$5,$X$4:$BY$4,1) -> 0 | L48: =SUMIFS($X48:$BY48,$X$5:$BY$5,L$5,$X$4:$BY$4,1) -> 0 | M48: =SUMIFS($X48:$BY48,$X$5:$BY$5,M$5,$X$4:$BY$4,1) -> 5553 | N48: =SUMIFS($X48:$BY48,$X$5:$BY$5,N$5,$X$4:$BY$4,1) -> 2776 | O48: =SUMIFS($X48:$BY48,$X$5:$BY$5,O$5,$X$4:$BY$4,1) -> 7279 | ... T48: =SUMIFS($X48:$BY48,$X$5:$BY$5,T$5,$X$4:$BY$4,1) -> 11094.248 | AS48: =AR51 -> 5553 | AT48: =AS51 -> 6188 | AU48: =AT51 -> 7226 | AV48: =AU51 -> 5555 | AW48: =AV51 -> 2776 | AX48: =AW51 -> 3762 | AY48: =AX51 -> 4967 | AZ48: =AY51 -> 5373 | ... BX48: =BW51 -> 10074.72
C49: (+) Capex into CIP | G49: =G$12 -> JPY M | H49: =SUMIF($X$5:$BY$5,H$5,$X49:$BY49) -> 0 | I49: =SUMIF($X$5:$BY$5,I$5,$X49:$BY49) -> 0 | J49: =SUMIF($X$5:$BY$5,J$5,$X49:$BY49) -> 0 | K49: =SUMIF($X$5:$BY$5,K$5,$X49:$BY49) -> 0 | L49: =SUMIF($X$5:$BY$5,L$5,$X49:$BY49) -> 0 | M49: =SUMIF($X$5:$BY$5,M$5,$X49:$BY49) -> 0 | N49: =SUMIF($X$5:$BY$5,N$5,$X49:$BY49) -> 0 | O49: =SUMIF($X$5:$BY$5,O$5,$X49:$BY49) -> 0 | ... T49: =SUMIF($X$5:$BY$5,T$5,$X49:$BY49) -> 28130 | BF49: =BF28 -> 12383 | BG49: =BG28 -> 12383 | BH49: =BH28 -> 12383 | BI49: =BI28 -> 9700 | BJ49: =BJ28 -> 9700 | BK49: =BK28 -> 9700 | BL49: =BL28 -> 9700 | BM49: =BM28 -> 8487.5 | ... BX49: =BX28 -> 7032.5
C50: (−) Transfers to service | G50: =G$12 -> JPY M | H50: =SUMIF($X$5:$BY$5,H$5,$X50:$BY50) -> 0 | I50: =SUMIF($X$5:$BY$5,I$5,$X50:$BY50) -> 0 | J50: =SUMIF($X$5:$BY$5,J$5,$X50:$BY50) -> 0 | K50: =SUMIF($X$5:$BY$5,K$5,$X50:$BY50) -> 0 | L50: =SUMIF($X$5:$BY$5,L$5,$X50:$BY50) -> 0 | M50: =SUMIF($X$5:$BY$5,M$5,$X50:$BY50) -> 0 | N50: =SUMIF($X$5:$BY$5,N$5,$X50:$BY50) -> 0 | O50: =SUMIF($X$5:$BY$5,O$5,$X50:$BY50) -> 0 | ... T50: =SUMIF($X$5:$BY$5,T$5,$X50:$BY50) -> -29169.332 | BF50: =-BF48*$K$38 -> -8198.4 | BG50: =-BG48*$K$38 -> -11127.62 | BH50: =-BH48*$K$38 -> -12006.386 | BI50: =-BI48*$K$38 -> -12270.016 | BJ50: =-BJ48*$K$38 -> -10471.005 | BK50: =-BK48*$K$38 -> -9931.3014 | BL50: =-BL48*$K$38 -> -9769.3904 | BM50: =-BM48*$K$38 -> -9720.8171 | ... BX50: =-BX48*$K$38 -> -7052.3038
C51: EOP | G51: =G$12 -> JPY M | H51: =SUMIFS($X51:$BY51,$X$5:$BY$5,H$5,$X$4:$BY$4,4) -> 0 | I51: =SUMIFS($X51:$BY51,$X$5:$BY$5,I$5,$X$4:$BY$4,4) -> 0 | J51: =SUMIFS($X51:$BY51,$X$5:$BY$5,J$5,$X$4:$BY$4,4) -> 0 | K51: =SUMIFS($X51:$BY51,$X$5:$BY$5,K$5,$X$4:$BY$4,4) -> 0 | L51: =SUMIFS($X51:$BY51,$X$5:$BY$5,L$5,$X$4:$BY$4,4) -> 5553 | M51: =SUMIFS($X51:$BY51,$X$5:$BY$5,M$5,$X$4:$BY$4,4) -> 2776 | N51: =SUMIFS($X51:$BY51,$X$5:$BY$5,N$5,$X$4:$BY$4,4) -> 7279 | O51: =SUMIFS($X51:$BY51,$X$5:$BY$5,O$5,$X$4:$BY$4,4) -> 12067 | ... T51: =SUMIFS($X51:$BY51,$X$5:$BY$5,T$5,$X$4:$BY$4,4) -> 10054.916 | AR51: 5553 | AS51: 6188 | AT51: 7226 | AU51: 5555 | AV51: 2776 | AW51: 3762 | AX51: 4967 | AY51: 5373 | AZ51: 7279 | BA51: 4462 | BB51: 8284 | BC51: 9699 | BD51: 12067 | BE51: 11712 | BF51: =SUM(BF48:BF50) -> 15896.6 | BG51: =SUM(BG48:BG50) -> 17151.98 | BH51: =SUM(BH48:BH50) -> 17528.594 | BI51: =SUM(BI48:BI50) -> 14958.578 | BJ51: =SUM(BJ48:BJ50) -> 14187.573 | BK51: =SUM(BK48:BK50) -> 13956.272 | BL51: =SUM(BL48:BL50) -> 13886.882 | BM51: =SUM(BM48:BM50) -> 12653.564 | ... BX51: =SUM(BX48:BX50) -> 10054.916
B53: Buildings and structures
C54: BOP | G54: =G$12 -> JPY M | H54: =SUMIFS($X54:$BY54,$X$5:$BY$5,H$5,$X$4:$BY$4,1) -> 0 | I54: =SUMIFS($X54:$BY54,$X$5:$BY$5,I$5,$X$4:$BY$4,1) -> 0 | J54: =SUMIFS($X54:$BY54,$X$5:$BY$5,J$5,$X$4:$BY$4,1) -> 0 | K54: =SUMIFS($X54:$BY54,$X$5:$BY$5,K$5,$X$4:$BY$4,1) -> 0 | L54: =SUMIFS($X54:$BY54,$X$5:$BY$5,L$5,$X$4:$BY$4,1) -> 0 | M54: =SUMIFS($X54:$BY54,$X$5:$BY$5,M$5,$X$4:$BY$4,1) -> 19620 | N54: =SUMIFS($X54:$BY54,$X$5:$BY$5,N$5,$X$4:$BY$4,1) -> 19944 | O54: =SUMIFS($X54:$BY54,$X$5:$BY$5,O$5,$X$4:$BY$4,1) -> 20963 | ... T54: =SUMIFS($X54:$BY54,$X$5:$BY$5,T$5,$X$4:$BY$4,1) -> 63839.469 | AS54: =AR57 -> 19620 | AT54: =AS57 -> 19508 | AU54: =AT57 -> 20200 | AV54: =AU57 -> 20485 | AW54: =AV57 -> 19944 | AX54: =AW57 -> 20154 | AY54: =AX57 -> 20431 | AZ54: =AY57 -> 20231 | ... BX54: =BW57 -> 69116.602
C55: (+) Transfers in | G55: =G$12 -> JPY M | H55: =SUMIF($X$5:$BY$5,H$5,$X55:$BY55) -> 0 | I55: =SUMIF($X$5:$BY$5,I$5,$X55:$BY55) -> 0 | J55: =SUMIF($X$5:$BY$5,J$5,$X55:$BY55) -> 0 | K55: =SUMIF($X$5:$BY$5,K$5,$X55:$BY55) -> 0 | L55: =SUMIF($X$5:$BY$5,L$5,$X55:$BY55) -> 0 | M55: =SUMIF($X$5:$BY$5,M$5,$X55:$BY55) -> 0 | N55: =SUMIF($X$5:$BY$5,N$5,$X55:$BY55) -> 0 | O55: =SUMIF($X$5:$BY$5,O$5,$X55:$BY55) -> 0 | ... T55: =SUMIF($X$5:$BY$5,T$5,$X55:$BY55) -> 10209.266 | BF55: =-BF50*$K$39 -> 2869.44 | BG55: =-BG50*$K$39 -> 3894.667 | BH55: =-BH50*$K$39 -> 4202.2351 | BI55: =-BI50*$K$39 -> 4294.5055 | BJ55: =-BJ50*$K$39 -> 3664.8517 | BK55: =-BK50*$K$39 -> 3475.9555 | BL55: =-BL50*$K$39 -> 3419.2866 | BM55: =-BM50*$K$39 -> 3402.286 | ... BX55: =-BX50*$K$39 -> 2468.3063
C56: (−) Depreciation | G56: =G$12 -> JPY M | H56: =SUMIF($X$5:$BY$5,H$5,$X56:$BY56) -> 0 | I56: =SUMIF($X$5:$BY$5,I$5,$X56:$BY56) -> 0 | J56: =SUMIF($X$5:$BY$5,J$5,$X56:$BY56) -> 0 | K56: =SUMIF($X$5:$BY$5,K$5,$X56:$BY56) -> 0 | L56: =SUMIF($X$5:$BY$5,L$5,$X56:$BY56) -> 0 | M56: =SUMIF($X$5:$BY$5,M$5,$X56:$BY56) -> 0 | N56: =SUMIF($X$5:$BY$5,N$5,$X56:$BY56) -> 0 | O56: =SUMIF($X$5:$BY$5,O$5,$X56:$BY56) -> 0 | ... T56: =SUMIF($X$5:$BY$5,T$5,$X56:$BY56) -> -3327.4582 | BF56: =-BF116 -> -386.25 | BG56: =-BG116 -> -410.162 | BH56: =-BH116 -> -442.61756 | BI56: =-BI116 -> -477.63618 | BJ56: =-BJ116 -> -513.42373 | BK56: =-BK116 -> -543.96416 | BL56: =-BL116 -> -572.93046 | BM56: =-BM116 -> -601.42451 | ... BX56: =-BX116 -> -863.63186
C57: EOP | G57: =G$12 -> JPY M | H57: =SUMIFS($X57:$BY57,$X$5:$BY$5,H$5,$X$4:$BY$4,4) -> 0 | I57: =SUMIFS($X57:$BY57,$X$5:$BY$5,I$5,$X$4:$BY$4,4) -> 0 | J57: =SUMIFS($X57:$BY57,$X$5:$BY$5,J$5,$X$4:$BY$4,4) -> 0 | K57: =SUMIFS($X57:$BY57,$X$5:$BY$5,K$5,$X$4:$BY$4,4) -> 0 | L57: =SUMIFS($X57:$BY57,$X$5:$BY$5,L$5,$X$4:$BY$4,4) -> 19620 | M57: =SUMIFS($X57:$BY57,$X$5:$BY$5,M$5,$X$4:$BY$4,4) -> 19944 | N57: =SUMIFS($X57:$BY57,$X$5:$BY$5,N$5,$X$4:$BY$4,4) -> 20963 | O57: =SUMIFS($X57:$BY57,$X$5:$BY$5,O$5,$X$4:$BY$4,4) -> 22380 | ... T57: =SUMIFS($X57:$BY57,$X$5:$BY$5,T$5,$X$4:$BY$4,4) -> 70721.277 | AR57: 19620 | AS57: 19508 | AT57: 20200 | AU57: 20485 | AV57: 19944 | AW57: 20154 | AX57: 20431 | AY57: 20231 | AZ57: 20963 | BA57: 20142 | BB57: 20747 | BC57: 21082 | BD57: 22380 | BE57: 23175 | BF57: =SUM(BF54:BF56) -> 25658.19 | BG57: =SUM(BG54:BG56) -> 29142.695 | BH57: =SUM(BH54:BH56) -> 32902.313 | BI57: =SUM(BI54:BI56) -> 36719.182 | BJ57: =SUM(BJ54:BJ56) -> 39870.61 | BK57: =SUM(BK54:BK56) -> 42802.601 | BL57: =SUM(BL54:BL56) -> 45648.957 | BM57: =SUM(BM54:BM56) -> 48449.819 | ... BX57: =SUM(BX54:BX56) -> 70721.277
B59: Machinery and equipment
C60: BOP | G60: =G$12 -> JPY M | H60: =SUMIFS($X60:$BY60,$X$5:$BY$5,H$5,$X$4:$BY$4,1) -> 0 | I60: =SUMIFS($X60:$BY60,$X$5:$BY$5,I$5,$X$4:$BY$4,1) -> 0 | J60: =SUMIFS($X60:$BY60,$X$5:$BY$5,J$5,$X$4:$BY$4,1) -> 0 | K60: =SUMIFS($X60:$BY60,$X$5:$BY$5,K$5,$X$4:$BY$4,1) -> 0 | L60: =SUMIFS($X60:$BY60,$X$5:$BY$5,L$5,$X$4:$BY$4,1) -> 0 | M60: =SUMIFS($X60:$BY60,$X$5:$BY$5,M$5,$X$4:$BY$4,1) -> 25756 | N60: =SUMIFS($X60:$BY60,$X$5:$BY$5,N$5,$X$4:$BY$4,1) -> 30351 | O60: =SUMIFS($X60:$BY60,$X$5:$BY$5,O$5,$X$4:$BY$4,1) -> 30855 | ... T60: =SUMIFS($X60:$BY60,$X$5:$BY$5,T$5,$X$4:$BY$4,1) -> 79956.261 | AS60: =AR63 -> 25756 | AT60: =AS63 -> 25923 | AU60: =AT63 -> 26475 | AV60: =AU63 -> 27923 | AW60: =AV63 -> 30351 | AX60: =AW63 -> 30206 | AY60: =AX63 -> 31679 | AZ60: =AY63 -> 31249 | ... BX60: =BW63 -> 78552.767
C61: (+) Transfers in | G61: =G$12 -> JPY M | H61: =SUMIF($X$5:$BY$5,H$5,$X61:$BY61) -> 0 | I61: =SUMIF($X$5:$BY$5,I$5,$X61:$BY61) -> 0 | J61: =SUMIF($X$5:$BY$5,J$5,$X61:$BY61) -> 0 | K61: =SUMIF($X$5:$BY$5,K$5,$X61:$BY61) -> 0 | L61: =SUMIF($X$5:$BY$5,L$5,$X61:$BY61) -> 0 | M61: =SUMIF($X$5:$BY$5,M$5,$X61:$BY61) -> 0 | N61: =SUMIF($X$5:$BY$5,N$5,$X61:$BY61) -> 0 | O61: =SUMIF($X$5:$BY$5,O$5,$X61:$BY61) -> 0 | ... T61: =SUMIF($X$5:$BY$5,T$5,$X61:$BY61) -> 18084.986 | BF61: =-BF50*$K$40 -> 5083.008 | BG61: =-BG50*$K$40 -> 6899.1244 | BH61: =-BH50*$K$40 -> 7443.9593 | BI61: =-BI50*$K$40 -> 7607.4098 | BJ61: =-BJ50*$K$40 -> 6492.0229 | BK61: =-BK50*$K$40 -> 6157.4069 | BL61: =-BL50*$K$40 -> 6057.0221 | BM61: =-BM50*$K$40 -> 6026.9066 | ... BX61: =-BX50*$K$40 -> 4372.4283
C62: (−) Depreciation | G62: =G$12 -> JPY M | H62: =SUMIF($X$5:$BY$5,H$5,$X62:$BY62) -> 0 | I62: =SUMIF($X$5:$BY$5,I$5,$X62:$BY62) -> 0 | J62: =SUMIF($X$5:$BY$5,J$5,$X62:$BY62) -> 0 | K62: =SUMIF($X$5:$BY$5,K$5,$X62:$BY62) -> 0 | L62: =SUMIF($X$5:$BY$5,L$5,$X62:$BY62) -> 0 | M62: =SUMIF($X$5:$BY$5,M$5,$X62:$BY62) -> 0 | N62: =SUMIF($X$5:$BY$5,N$5,$X62:$BY62) -> 0 | O62: =SUMIF($X$5:$BY$5,O$5,$X62:$BY62) -> 0 | ... T62: =SUMIF($X$5:$BY$5,T$5,$X62:$BY62) -> -20476.298 | BF62: =-BF139 -> -1736.0417 | BG62: =-BG139 -> -1917.5777 | BH62: =-BH139 -> -2163.975 | BI62: =-BI139 -> -2429.8307 | BJ62: =-BJ139 -> -2701.5239 | BK62: =-BK139 -> -2933.3818 | BL62: =-BL139 -> -3153.2892 | BM62: =-BM139 -> -3369.6114 | ... BX62: =-BX139 -> -5360.2468
